Workbook

Sheet Cover
A1: CreditIQ — Brightwater Retail Holdings credit underwriting model
A2: DEMO DATA · DEMO INVESTMENT TERMS · $ in millions · as of 2026-03-31
A4: Model status | B4: ='Investment Summary'!$D$52 -> ALL CHECKS PASS
A5: Active scenario | B5: =Assumptions!$D$10 -> Downside
A6: Recommendation (rule-based; see Investment Summary) | B6: ='Investment Summary'!$C$4 -> HOLD
A8: Colour conventions
A9: Blue on pale yellow | B9: Hardcoded input: sourced historical data, explicit assumption, scenario / transaction / macro input, covenant threshold, sensitivity axis, structural block parameter.
A10: Black | B10: Formula or calculation. No outputs, subtotals or metrics are hardcoded anywhere in this workbook.
A11: Green | B11: Direct link to a cell on another worksheet.
A12: Grey fill | B12: Labels and headers.
A14: Flow of logic | B14: Assumptions + Historical → Operating Model → Debt Schedule ↔ Cash Flow → Credit Metrics & Covenants → Recovery → Returns → Sensitivities → Investment Summary
A15: Data classes | B15: PUBLIC FILING = reported inputs · ANALYST PROJECTION = scenario drivers · UNDERWRITING ASSUMPTION = hypothetical purchase price / terms · DEMO = fictional
A17: Tabs
A18: Assumptions | B18: All inputs, scenario drivers, covenants, selector
A19: Historical Financials | B19: Sourced statements; derived lines and LTM calculated
A20: Operating Model | B20: Income statement and FCF, history + projection
A21: Debt Schedule | B21: Per-tranche roll-forward, floors, PIK, refinancing test, sweep
A22: Cash Flow | B22: Cash waterfall, funding gap, default test
A23: Credit Metrics | B23: Ratios, covenant compliance, transparent credit score
A24: Scenarios | B24: Base / Downside / Severe side by side + reconciliation
A25: Capital Structure | B25: Tranches, leverage through the stack, maturity wall & refinancing requirement
A26: Recovery | B26: Seniority waterfall with collateral pools and deficiency claims
A27: Returns | B27: Face, price, coupon, yield, recovery; IRR, XIRR, MOIC
A28: Sensitivities | B28: Seven formula-driven tables
A29: Investment Summary | B29: Live outputs, recommendation evidence, integrity checks
... A31: Calc Engine | B31: Supporting: 63 simultaneous model runs
A33: Validation: docs/MODEL_VALIDATION.md · Audit: scripts/audit_model.py · Change-impact harness: scripts/model_harness.py

Sheet Assumptions
A1: Assumptions — Brightwater Retail Holdings: all explicit inputs live on this tab
A2: DEMO DATA · DEMO INVESTMENT TERMS · Blue on pale yellow = hardcoded input · Black = formula · Green = link to another sheet · $ in millions
A4: 1. General & model settings
A5: Company | C5: Brightwater Retail Holdings
A6: Base period label (year in which the base / LTM period ends) | C6: 2025
A7: Fiscal-period end month (12 = calendar FY; 6 = LTM June periods) | C7: 12
A8: As-of / entry date | C8: 46112
A9: Cash tax rate on positive EBT | B9: % of EBT | C9: 0.25
A10: ACTIVE SCENARIO selector (1=Base, 2=Downside, 3=Severe) | B10: select 1 / 2 / 3 | C10: 2 | D10: =CHOOSE(C10,"Base Case","Downside","Severe Downside") -> Downside
A11: Cash & equivalents at base date (balance sheet) | B11: $M | C11: 45
A12: Minimum operating cash | B12: $M | C12: 0
A13: Cash sweep (% of excess cash applied to prepayable debt) | B13: % | C13: 1
A14: Recovery value override (leave blank = model-derived) | B14: $M, optional
A15: Administrative / DIP costs | B15: % of recovery value | C15: 0.04
A16: Accrued unpaid interest included in claims | B16: months | C16: 3
A17: Rank at which secured deficiency claims join general creditors | C17: 99
A18: Maturity alert window | B18: periods from base | C18: 2
A19: Materiality threshold for maturity alert | B19: % of total debt | C19: 0.25
A20: Concentration threshold (single-period maturities) | B20: % of total debt | C20: 0.3
A21: Market-implied EV / EBITDA (analyst assumption) | B21: x | C21: 6.5
A22: Credit score: maturity-risk window | B22: periods | C22: 3
A24: 2. Collateral / asset base (recovery & LTV)
A25: Illustrative appraised / collateral value (DEMO)
A26: Appraised / collateral asset base | C26: 1040
A27: Total asset base | C27: =SUM(C26) -> 1040
A29: 3. Transaction / position being underwritten — DEMO INVESTMENT TERMS
A30: Target tranche # (row in the debt table below) | C30: 2
A31: Face value held (legal claim) | B31: $M | C31: 100
A32: Purchase price / OID (UNDERWRITING ASSUMPTION) | B32: % of face | C32: 78
A33: Transaction fees | B33: % of cost | C33: 0.005
A34: Hold period (whole years, 1-5) | B34: periods | C34: 2
A35: Coupon payments per year on target tranche (contractual-timing cross-check only) | B35: per year | C35: 1
A36: Default → recovery cash receipt lag | B36: periods | C36: 1
A37: Required IRR (hurdle) | C37: 0.12
A38: Minimum acceptable downside IRR | C38: 0
A39: Minimum yield to maturity | C39: 0.09
A40: Maximum net leverage (net debt / EBITDA) | C40: 6
A41: Minimum downside recovery | C41: 0.6
A42: Minimum covenant headroom (base case) | C42: 0.15
A43: Decision rule: secondary test failures tolerated for PROCEED | B43: count | C43: 2
A44: Decision rule: core test failures that force PASS | B44: count | C44: 3
A45: Unresolved high-priority diligence items (from the CreditIQ diligence tracker) | B45: count | C45: 4
A47: 4. Macro assumptions
A48: Model period | G48: =Assumptions!$C$6+1 -> 2026 | H48: =G48+1 -> 2027 | I48: =H48+1 -> 2028 | J48: =I48+1 -> 2029 | K48: =J48+1 -> 2030
A49: Base rate (SOFR) curve — DEMO assumption | B49: % p.a. | G49: 0.0425 | H49: 0.04 | I49: 0.0375 | J49: 0.0375 | K49: 0.0375
A51: 5. Debt tranches (list in order of cash-repayment priority; rank 1 = most senior, equal rank = pari passu)
A52: Facility | B52: Type | C52: Face / principal $M | D52: Commit. $M | E52: Fixed coupon | F52: Spread (floating) | G52: SOFR floor | H52: PIK rate | I52: Floating (1/0) | J52: Maturity date | K52: Maturity period | L52: Amort. % orig | M52: Rank | N52: Prepay (1/0) | O52: Secured (1/0) | P52: Revolver (1/0) | Q52: Collateral share | R52: Mark / price | S52: Call protection / collateral
A53: ABL Revolver | B53: revolver | C53: 180 | D53: 300 | E53: 0.086 | F53: 0.0435 | G53: 0 | H53: 0 | I53: 1 | J53: 46691 | K53: =YEAR(J53)+IF(MONTH(J53)>Assumptions!$C$7,1,0) -> 2027 | L53: 0 | M53: 1 | N53: 1 | O53: 1 | P53: 1 | Q53: 0 | R53: 100
A54: First-Lien Term Loan | B54: term_loan | C54: 520 | D54: 0 | E54: 0.103 | F54: 0.0605 | G54: 0 | H54: 0 | I54: 1 | J54: 46843 | K54: =YEAR(J54)+IF(MONTH(J54)>Assumptions!$C$7,1,0) -> 2028 | L54: 0.01 | M54: 2 | N54: 0 | O54: 1 | P54: 0 | Q54: 0 | R54: 78
A55: Second-Lien Notes 11.0% | B55: second_lien | C55: 250 | D55: 0 | E55: 0.11 | F55: 0 | G55: 0 | H55: 0 | I55: 0 | J55: 47299 | K55: =YEAR(J55)+IF(MONTH(J55)>Assumptions!$C$7,1,0) -> 2029 | L55: 0 | M55: 3 | N55: 0 | O55: 1 | P55: 0 | Q55: 0 | R55: 52
A56: Senior Unsecured Notes 7.5% | B56: unsecured_notes | C56: 300 | D56: 0 | E56: 0.075 | F56: 0 | G56: 0 | H56: 0 | I56: 0 | J56: 46522 | K56: =YEAR(J56)+IF(MONTH(J56)>Assumptions!$C$7,1,0) -> 2027 | L56: 0 | M56: 4 | N56: 0 | O56: 0 | P56: 0 | Q56: 0 | R56: 33
A57: Floating tranches: all-in rate = MAX(SOFR, floor) + spread + scenario shock. Fixed: coupon. Interest accrues on beginning balances (no circularity). Maturity period = YEAR(date) + 1 if month > period-end month.
A59: 6. Covenants (thresholds per model period). Disclosed = in issuer documents; Hypothetical = UNDERWRITING ASSUMPTION; inactive covenants are shown for reference only
A60: Covenant | B60: Type | C60: Basis | D60: Active (1/0) | E60: Reported ratio | G60: =Assumptions!$C$6+1 -> 2026 | H60: =G60+1 -> 2027 | I60: =H60+1 -> 2028 | J60: =I60+1 -> 2029 | K60: =J60+1 -> 2030
A61: Maximum net leverage | B61: maxNetLeverage | C61: hypothetical | D61: 1 | G61: 8.5 | H61: 8.5 | I61: 8.5 | J61: 8.5 | K61: 8.5
A63: 7. Scenario assumptions (selected via ACTIVE SCENARIO; all three run simultaneously on Calc Engine)
A64: Base Case | G64: =Assumptions!$C$6+1 -> 2026 | H64: =G64+1 -> 2027 | I64: =H64+1 -> 2028 | J64: =I64+1 -> 2029 | K64: =J64+1 -> 2030
A65: Revenue growth | G65: -0.01 | H65: -0.01 | I65: -0.01 | J65: -0.01 | K65: -0.01
A66: Gross margin | G66: 0.36 | H66: 0.362 | I66: 0.364 | J66: 0.366 | K66: 0.368
A67: EBITDA margin | G67: 0.065 | H67: 0.067 | I67: 0.069 | J67: 0.071 | K67: 0.073
A68: Net asset-sale proceeds ($M) | G68: 0 | H68: 0 | I68: 0 | J68: 0 | K68: 0
A69: Capex | B69: % of revenue | C69: 0.02
A70: Working-capital investment | B70: % of Δ revenue | C70: 0.12
A71: Other cash items (+ outflow; incl. distributions, programming timing) | B71: % of revenue | C71: 0
A72: Floating-rate shock | B72: % added to floating rates | C72: 0
A73: Refinancing rate (post-maturity) | B73: % | C73: 0.11
A74: Market access: max net leverage to refinance | B74: x | C74: 8.5
A75: Market access: min EBITDA / pro-forma interest | B75: x | C75: 1.2
A76: Exit EV / EBITDA multiple | B76: x | C76: 6.5
A77: Exit price if no default (cap, % of face) | B77: % of face | C77: 100
A78: Distressed EV / EBITDA multiple (going concern) | B78: x | C78: 4
A79: Asset value decline | B79: % | C79: 0
A80: Liquidation recovery on asset base | B80: % | C80: 0.6
A81: Scenario probability | C81: 0.55
A83: Downside | G83: =Assumptions!$C$6+1 -> 2026 | H83: =G83+1 -> 2027 | I83: =H83+1 -> 2028 | J83: =I83+1 -> 2029 | K83: =J83+1 -> 2030
A84: Revenue growth | G84: -0.078 | H84: -0.039 | I84: -0.005 | J84: -0.01 | K84: -0.01
A85: Gross margin | G85: 0.33 | H85: 0.318 | I85: 0.324 | J85: 0.33 | K85: 0.336
A86: EBITDA margin | G86: 0.035 | H86: 0.023 | I86: 0.029 | J86: 0.035 | K86: 0.041
A87: Net asset-sale proceeds ($M) | G87: 0 | H87: 0 | I87: 0 | J87: 0 | K87: 0
A88: Capex | B88: % of revenue | C88: 0.019
A89: Working-capital investment | B89: % of Δ revenue | C89: 0.12
A90: Other cash items (+ outflow; incl. distributions, programming timing) | B90: % of revenue | C90: 0.002
A91: Floating-rate shock | B91: % added to floating rates | C91: 0.015
A92: Refinancing rate (post-maturity) | B92: % | C92: 0.135
A93: Market access: max net leverage to refinance | B93: x | C93: 5.5
A94: Market access: min EBITDA / pro-forma interest | B94: x | C94: 1.8
A95: Exit EV / EBITDA multiple | B95: x | C95: 5
A96: Exit price if no default (cap, % of face) | B96: % of face | C96: 90
A97: Distressed EV / EBITDA multiple (going concern) | B97: x | C97: 4
A98: Asset value decline | B98: % | C98: 0.15
A99: Liquidation recovery on asset base | B99: % | C99: 0.6
A100: Scenario probability | C100: 0.3
A102: Severe Downside | G102: =Assumptions!$C$6+1 -> 2026 | H102: =G102+1 -> 2027 | I102: =H102+1 -> 2028 | J102: =I102+1 -> 2029 | K102: =J102+1 -> 2030
A103: Revenue growth | G103: -0.234 | H103: -0.13 | I103: -0.026 | J103: -0.01 | K103: -0.01
A104: Gross margin | G104: 0.305 | H104: 0.305 | I104: 0.305 | J104: 0.305 | K104: 0.305
A105: EBITDA margin | G105: 0.01 | H105: 0.01 | I105: 0.01 | J105: 0.01 | K105: 0.01
A106: Net asset-sale proceeds ($M) | G106: 0 | H106: 0 | I106: 0 | J106: 0 | K106: 0
A107: Capex | B107: % of revenue | C107: 0.016
A108: Working-capital investment | B108: % of Δ revenue | C108: 0.12
A109: Other cash items (+ outflow; incl. distributions, programming timing) | B109: % of revenue | C109: 0.006
...

Sheet Historical Financials
A1: Historical Financials — Brightwater Retail Holdings
A2: DEMO data (fictional, illustrative). All subtotals, EBITDA, EBIT, net income, FCF and LTM columns are formulas.
A4: US$ millions | B4: FY2022A | C4: FY2023A | D4: FY2024A | E4: FY2025A | F4: Source datapoint IDs (see Sources tab)
A5: A. Reported inputs
A6: Revenue | B6: 2650 | C6: 2560 | D6: 2470 | E6: 2400 | F6: DEMO input
A7: COGS | B7: 1643 | C7: 1605.12 | D7: 1568.45 | E7: 1536 | F7: DEMO input
A8: Operating expenses (cash, ex-D&A) | B8: 781.75 | C8: 755.2 | D8: 728.65 | E8: 708 | F8: DEMO input
A9: Depreciation & amortization | B9: 58.3 | C9: 56.32 | D9: 54.34 | E9: 52.8 | F9: DEMO input
A10: Interest expense | B10: 101.184 | C10: 107.136 | D10: 113.088 | E10: 119.04 | F10: DEMO input
A11: Taxes | B11: 16.4415 | C11: 9.056 | D11: 1.368 | E11: 0 | F11: DEMO input
A12: Capex | B12: 53 | C12: 51.2 | D12: 49.4 | E12: 48 | F12: DEMO input
A13: Increase in working capital | B13: -3.2121212 | C13: -10.8 | D13: -10.8 | E13: -8.4 | F13: DEMO input
A14: Share-based compensation add-back (none applied for this company) | B14: 0 | C14: 0 | D14: 0 | E14: 0 | F14: DEMO input
A16: B. Standardized statements (calculated)
A17: Revenue | B17: =B6 -> 2650 | C17: =C6 -> 2560 | D17: =D6 -> 2470 | E17: =E6 -> 2400
A18: Direct costs / COGS | B18: =B7 -> 1643 | C18: =C7 -> 1605.12 | D18: =D7 -> 1568.45 | E18: =E7 -> 1536
A19: Gross profit (NOI for real estate) | B19: =B17-B18 -> 1007 | C19: =C17-C18 -> 954.88 | D19: =D17-D18 -> 901.55 | E19: =E17-E18 -> 864
A20: Operating expenses, cash & adjusted (excl. D&A and non-cash add-backs) | B20: =B8 -> 781.75 | C20: =C8 -> 755.2 | D20: =D8 -> 728.65 | E20: =E8 -> 708
A21: EBITDA (company-adjusted basis) | B21: =B19-B20 -> 225.25 | C21: =C19-C20 -> 199.68 | D21: =D19-D20 -> 172.9 | E21: =E19-E20 -> 156
A22: Depreciation & amortization | B22: =B9 -> 58.3 | C22: =C9 -> 56.32 | D22: =D9 -> 54.34 | E22: =E9 -> 52.8
A23: Share-based compensation (non-cash add-back) | B23: =B14 -> 0 | C23: =C14 -> 0 | D23: =D14 -> 0 | E23: =E14 -> 0
A24: EBIT (EBITDA − D&A − SBC) | B24: =B21-B22-B23 -> 166.95 | C24: =C21-C22-C23 -> 143.36 | D24: =D21-D22-D23 -> 118.56 | E24: =E21-E22-E23 -> 103.2
A25: Interest expense | B25: =B10 -> 101.184 | C25: =C10 -> 107.136 | D25: =D10 -> 113.088 | E25: =E10 -> 119.04
A26: EBT | B26: =B24-B25 -> 65.766 | C26: =C24-C25 -> 36.224 | D26: =D24-D25 -> 5.472 | E26: =E24-E25 -> -15.84
A27: Income taxes | B27: =B11 -> 16.4415 | C27: =C11 -> 9.056 | D27: =D11 -> 1.368 | E27: =E11 -> 0
A28: Net income (model basis; excludes impairments and one-offs) | B28: =B26-B27 -> 49.3245 | C28: =C26-C27 -> 27.168 | D28: =D26-D27 -> 4.104 | E28: =E26-E27 -> -15.84
A29: Capex (incl. leasing costs where applicable) | B29: =B12 -> 53 | C29: =C12 -> 51.2 | D29: =D12 -> 49.4 | E29: =E12 -> 48
A30: Increase in working capital | B30: =B13 -> -3.2121212 | C30: =C13 -> -10.8 | D30: =D13 -> -10.8 | E30: =E13 -> -8.4
A31: Free cash flow (NI + D&A + SBC − capex − ΔNWC) | B31: =B28+B22+B23-B29-B30 -> 57.836621 | C31: =C28+C22+C23-C29-C30 -> 43.088 | D31: =D28+D22+D23-D29-D30 -> 19.844 | E31: =E28+E22+E23-E29-E30 -> -2.64
A33: C. Ratios & checks (calculated)
A34: Gross margin | B34: =B19/B17 -> 0.38 | C34: =C19/C17 -> 0.373 | D34: =D19/D17 -> 0.365 | E34: =E19/E17 -> 0.36
A35: EBITDA margin | B35: =B21/B17 -> 0.085 | C35: =C21/C17 -> 0.078 | D35: =D21/D17 -> 0.07 | E35: =E21/E17 -> 0.065
A36: Revenue growth (YoY) | C36: =C17/B17-1 -> -0.033962264 | D36: =D17/C17-1 -> -0.03515625 | E36: =E17/D17-1 -> -0.028340081
A37: EBITDA growth (YoY) | C37: =C21/B21-1 -> -0.11351831 | D37: =D21/C21-1 -> -0.13411458 | E37: =E21/D21-1 -> -0.097744361

Sheet Operating Model
A1: Operating Model — selected scenario (assumptions → statements)
A2: ="Brightwater Retail Holdings · DEMO DATA · DEMO INVESTMENT TERMS · Active scenario: "&Assumptions!$D$10 -> Brightwater Retail Holdings · DEMO DATA · DEMO INVESTMENT TERMS · Active scenario: Downside
A4: $M | C4: FY2022A | D4: FY2023A | E4: FY2024A | F4: FY2025A | G4: FY2026E | H4: FY2027E | I4: FY2028E | J4: FY2029E | K4: FY2030E
A6: Operating drivers (selected scenario → Assumptions)
A7: Model period (year in which the period ends) | C7: =D7-1 -> 2022 | D7: =E7-1 -> 2023 | E7: =F7-1 -> 2024 | F7: =Assumptions!$C$6 -> 2025 | G7: =F7+1 -> 2026 | H7: =G7+1 -> 2027 | I7: =H7+1 -> 2028 | J7: =I7+1 -> 2029 | K7: =J7+1 -> 2030
A8: Projection period # | G8: =G7-Assumptions!$C$6 -> 1 | H8: =H7-Assumptions!$C$6 -> 2 | I8: =I7-Assumptions!$C$6 -> 3 | J8: =J7-Assumptions!$C$6 -> 4 | K8: =K7-Assumptions!$C$6 -> 5
A9: Revenue growth | G9: =CHOOSE(Assumptions!$C$10,Assumptions!$G$65,Assumptions!$G$84,Assumptions!$G$103) -> -0.078 | H9: =CHOOSE(Assumptions!$C$10,Assumptions!$H$65,Assumptions!$H$84,Assumptions!$H$103) -> -0.039 | I9: =CHOOSE(Assumptions!$C$10,Assumptions!$I$65,Assumptions!$I$84,Assumptions!$I$103) -> -0.005 | J9: =CHOOSE(Assumptions!$C$10,Assumptions!$J$65,Assumptions!$J$84,Assumptions!$J$103) -> -0.01 | K9: =CHOOSE(Assumptions!$C$10,Assumptions!$K$65,Assumptions!$K$84,Assumptions!$K$103) -> -0.01
A10: Gross margin | G10: =CHOOSE(Assumptions!$C$10,Assumptions!$G$66,Assumptions!$G$85,Assumptions!$G$104) -> 0.33 | H10: =CHOOSE(Assumptions!$C$10,Assumptions!$H$66,Assumptions!$H$85,Assumptions!$H$104) -> 0.318 | I10: =CHOOSE(Assumptions!$C$10,Assumptions!$I$66,Assumptions!$I$85,Assumptions!$I$104) -> 0.324 | J10: =CHOOSE(Assumptions!$C$10,Assumptions!$J$66,Assumptions!$J$85,Assumptions!$J$104) -> 0.33 | K10: =CHOOSE(Assumptions!$C$10,Assumptions!$K$66,Assumptions!$K$85,Assumptions!$K$104) -> 0.336
A11: EBITDA margin | G11: =CHOOSE(Assumptions!$C$10,Assumptions!$G$67,Assumptions!$G$86,Assumptions!$G$105) -> 0.035 | H11: =CHOOSE(Assumptions!$C$10,Assumptions!$H$67,Assumptions!$H$86,Assumptions!$H$105) -> 0.023 | I11: =CHOOSE(Assumptions!$C$10,Assumptions!$I$67,Assumptions!$I$86,Assumptions!$I$105) -> 0.029 | J11: =CHOOSE(Assumptions!$C$10,Assumptions!$J$67,Assumptions!$J$86,Assumptions!$J$105) -> 0.035 | K11: =CHOOSE(Assumptions!$C$10,Assumptions!$K$67,Assumptions!$K$86,Assumptions!$K$105) -> 0.041
A12: Income statement ($M)
A13: Revenue | C13: ='Historical Financials'!B17 -> 2650 | D13: ='Historical Financials'!C17 -> 2560 | E13: ='Historical Financials'!D17 -> 2470 | F13: ='Historical Financials'!E17 -> 2400 | G13: =F13*(1+G9) -> 2212.8 | H13: =G13*(1+H9) -> 2126.5008 | I13: =H13*(1+I9) -> 2115.8683 | J13: =I13*(1+J9) -> 2094.7096 | K13: =J13*(1+K9) -> 2073.7625
A14: Direct costs / COGS | C14: ='Historical Financials'!B18 -> 1643 | D14: ='Historical Financials'!C18 -> 1605.12 | E14: ='Historical Financials'!D18 -> 1568.45 | F14: ='Historical Financials'!E18 -> 1536 | G14: =G13*(1-G10) -> 1482.576 | H14: =H13*(1-H10) -> 1450.2735 | I14: =I13*(1-I10) -> 1430.327 | J14: =J13*(1-J10) -> 1403.4554 | K14: =K13*(1-K10) -> 1376.9783
A15: Gross profit (NOI for real estate) | C15: =C13-C14 -> 1007 | D15: =D13-D14 -> 954.88 | E15: =E13-E14 -> 901.55 | F15: =F13-F14 -> 864 | G15: =G13-G14 -> 730.224 | H15: =H13-H14 -> 676.22725 | I15: =I13-I14 -> 685.54133 | J15: =J13-J14 -> 691.25417 | K15: =K13-K14 -> 696.78421
A16: Operating expenses (implied: gross profit − EBITDA) | C16: ='Historical Financials'!B20 -> 781.75 | D16: ='Historical Financials'!C20 -> 755.2 | E16: ='Historical Financials'!D20 -> 728.65 | F16: ='Historical Financials'!E20 -> 708 | G16: =G15-G17 -> 652.776 | H16: =H15-H17 -> 627.31774 | I16: =I15-I17 -> 624.18115 | J16: =J15-J17 -> 617.93934 | K16: =K15-K17 -> 611.75994
A17: EBITDA | C17: =C15-C16 -> 225.25 | D17: =D15-D16 -> 199.68 | E17: =E15-E16 -> 172.9 | F17: =F15-F16 -> 156 | G17: =G13*G11 -> 77.448 | H17: =H13*H11 -> 48.909518 | I17: =I13*I11 -> 61.360181 | J17: =J13*J11 -> 73.314836 | K17: =K13*K11 -> 85.024263
A18: D&A | C18: ='Historical Financials'!B22 -> 58.3 | D18: ='Historical Financials'!C22 -> 56.32 | E18: ='Historical Financials'!D22 -> 54.34 | F18: ='Historical Financials'!E22 -> 52.8 | G18: =G13*'Historical Financials'!E22/'Historical Financials'!E17 -> 48.6816 | H18: =H13*'Historical Financials'!E22/'Historical Financials'!E17 -> 46.783018 | I18: =I13*'Historical Financials'!E22/'Historical Financials'!E17 -> 46.549103 | J18: =J13*'Historical Financials'!E22/'Historical Financials'!E17 -> 46.083611 | K18: =K13*'Historical Financials'!E22/'Historical Financials'!E17 -> 45.622775
A19: Share-based compensation (non-cash) | C19: ='Historical Financials'!B23 -> 0 | D19: ='Historical Financials'!C23 -> 0 | E19: ='Historical Financials'!D23 -> 0 | F19: ='Historical Financials'!E23 -> 0 | G19: =G13*'Historical Financials'!E23/'Historical Financials'!E17 -> 0 | H19: =H13*'Historical Financials'!E23/'Historical Financials'!E17 -> 0 | I19: =I13*'Historical Financials'!E23/'Historical Financials'!E17 -> 0 | J19: =J13*'Historical Financials'!E23/'Historical Financials'!E17 -> 0 | K19: =K13*'Historical Financials'!E23/'Historical Financials'!E17 -> 0
A20: EBIT | C20: =C17-C18-C19 -> 166.95 | D20: =D17-D18-D19 -> 143.36 | E20: =E17-E18-E19 -> 118.56 | F20: =F17-F18-F19 -> 103.2 | G20: =G17-G18-G19 -> 28.7664 | H20: =H17-H18-H19 -> 2.1265008 | I20: =I17-I18-I19 -> 14.811078 | J20: =J17-J18-J19 -> 27.231225 | K20: =K17-K18-K19 -> 39.401488
A21: Cash interest expense (Debt Schedule) | G21: ='Debt Schedule'!G21+'Debt Schedule'!G34+'Debt Schedule'!G47+'Debt Schedule'!G60 -> 129.54 | H21: ='Debt Schedule'!H21+'Debt Schedule'!H34+'Debt Schedule'!H47+'Debt Schedule'!H60 -> 130.76463 | I21: ='Debt Schedule'!I21+'Debt Schedule'!I34+'Debt Schedule'!I47+'Debt Schedule'!I60 -> 128.34929 | J21: ='Debt Schedule'!J21+'Debt Schedule'!J34+'Debt Schedule'!J47+'Debt Schedule'!J60 -> 127.76169 | K21: ='Debt Schedule'!K21+'Debt Schedule'!K34+'Debt Schedule'!K47+'Debt Schedule'!K60 -> 127.17409
A22: PIK interest (non-cash) | G22: ='Debt Schedule'!G22+'Debt Schedule'!G35+'Debt Schedule'!G48+'Debt Schedule'!G61 -> 0 | H22: ='Debt Schedule'!H22+'Debt Schedule'!H35+'Debt Schedule'!H48+'Debt Schedule'!H61 -> 0 | I22: ='Debt Schedule'!I22+'Debt Schedule'!I35+'Debt Schedule'!I48+'Debt Schedule'!I61 -> 0 | J22: ='Debt Schedule'!J22+'Debt Schedule'!J35+'Debt Schedule'!J48+'Debt Schedule'!J61 -> 0 | K22: ='Debt Schedule'!K22+'Debt Schedule'!K35+'Debt Schedule'!K48+'Debt Schedule'!K61 -> 0
A23: Interest expense | C23: ='Historical Financials'!B25 -> 101.184 | D23: ='Historical Financials'!C25 -> 107.136 | E23: ='Historical Financials'!D25 -> 113.088 | F23: ='Historical Financials'!E25 -> 119.04 | G23: =G21+G22 -> 129.54 | H23: =H21+H22 -> 130.76463 | I23: =I21+I22 -> 128.34929 | J23: =J21+J22 -> 127.76169 | K23: =K21+K22 -> 127.17409
A24: EBT | C24: =C20-C23 -> 65.766 | D24: =D20-D23 -> 36.224 | E24: =E20-E23 -> 5.472 | F24: =F20-F23 -> -15.84 | G24: =G20-G23 -> -100.7736 | H24: =H20-H23 -> -128.63813 | I24: =I20-I23 -> -113.53821 | J24: =J20-J23 -> -100.53047 | K24: =K20-K23 -> -87.772605
A25: Taxes | C25: ='Historical Financials'!B27 -> 16.4415 | D25: ='Historical Financials'!C27 -> 9.056 | E25: ='Historical Financials'!D27 -> 1.368 | F25: ='Historical Financials'!E27 -> 0 | G25: =MAX(0,G24)*Assumptions!$C$9 -> 0 | H25: =MAX(0,H24)*Assumptions!$C$9 -> 0 | I25: =MAX(0,I24)*Assumptions!$C$9 -> 0 | J25: =MAX(0,J24)*Assumptions!$C$9 -> 0 | K25: =MAX(0,K24)*Assumptions!$C$9 -> 0
A26: Net income (model basis) | C26: =C24-C25 -> 49.3245 | D26: =D24-D25 -> 27.168 | E26: =E24-E25 -> 4.104 | F26: =F24-F25 -> -15.84 | G26: =G24-G25 -> -100.7736 | H26: =H24-H25 -> -128.63813 | I26: =I24-I25 -> -113.53821 | J26: =J24-J25 -> -100.53047 | K26: =K24-K25 -> -87.772605
A27: Free cash flow build ($M)
A28: Capex | C28: ='Historical Financials'!B29 -> 53 | D28: ='Historical Financials'!C29 -> 51.2 | E28: ='Historical Financials'!D29 -> 49.4 | F28: ='Historical Financials'!E29 -> 48 | G28: =G13*CHOOSE(Assumptions!$C$10,Assumptions!$C$69,Assumptions!$C$88,Assumptions!$C$107) -> 42.0432 | H28: =H13*CHOOSE(Assumptions!$C$10,Assumptions!$C$69,Assumptions!$C$88,Assumptions!$C$107) -> 40.403515 | I28: =I13*CHOOSE(Assumptions!$C$10,Assumptions!$C$69,Assumptions!$C$88,Assumptions!$C$107) -> 40.201498 | J28: =J13*CHOOSE(Assumptions!$C$10,Assumptions!$C$69,Assumptions!$C$88,Assumptions!$C$107) -> 39.799483 | K28: =K13*CHOOSE(Assumptions!$C$10,Assumptions!$C$69,Assumptions!$C$88,Assumptions!$C$107) -> 39.401488
A29: Working capital & other cash items (+ = outflow) | C29: ='Historical Financials'!B30 -> -3.2121212 | D29: ='Historical Financials'!C30 -> -10.8 | E29: ='Historical Financials'!D30 -> -10.8 | F29: ='Historical Financials'!E30 -> -8.4 | G29: =CHOOSE(Assumptions!$C$10,Assumptions!$C$70,Assumptions!$C$89,Assumptions!$C$108)*(G13-F13)+CHOOSE(Assumptions!$C$10,Assumptions!$C$71,Assumptions!$C$90,Assumptions!$C$109)*G13 -> -18.0384 | H29: =CHOOSE(Assumptions!$C$10,Assumptions!$C$70,Assumptions!$C$89,Assumptions!$C$108)*(H13-G13)+CHOOSE(Assumptions!$C$10,Assumptions!$C$71,Assumptions!$C$90,Assumptions!$C$109)*H13 -> -6.1029024 | I29: =CHOOSE(Assumptions!$C$10,Assumptions!$C$70,Assumptions!$C$89,Assumptions!$C$108)*(I13-H13)+CHOOSE(Assumptions!$C$10,Assumptions!$C$71,Assumptions!$C$90,Assumptions!$C$109)*I13 -> 2.9558361 | J29: =CHOOSE(Assumptions!$C$10,Assumptions!$C$70,Assumptions!$C$89,Assumptions!$C$108)*(J13-I13)+CHOOSE(Assumptions!$C$10,Assumptions!$C$71,Assumptions!$C$90,Assumptions!$C$109)*J13 -> 1.6503773 | K29: =CHOOSE(Assumptions!$C$10,Assumptions!$C$70,Assumptions!$C$89,Assumptions!$C$108)*(K13-J13)+CHOOSE(Assumptions!$C$10,Assumptions!$C$71,Assumptions!$C$90,Assumptions!$C$109)*K13 -> 1.6338735
A30: Free cash flow (NI + D&A + SBC + PIK − capex − ΔNWC/other) | C30: ='Historical Financials'!B31 -> 57.836621 | D30: ='Historical Financials'!C31 -> 43.088 | E30: ='Historical Financials'!D31 -> 19.844 | F30: ='Historical Financials'!E31 -> -2.64 | G30: =G26+G18+G19+G22-G28-G29 -> -76.0968 | H30: =H26+H18+H19+H22-H28-H29 -> -116.15573 | I30: =I26+I18+I19+I22-I28-I29 -> -110.14645 | J30: =J26+J18+J19+J22-J28-J29 -> -95.896716 | K30: =K26+K18+K19+K22-K28-K29 -> -83.185191

Sheet Debt Schedule
A1: Debt Schedule — tranche roll-forward, rates, PIK, refinancing test, cash sweep
A2: ="Brightwater Retail Holdings · DEMO DATA · DEMO INVESTMENT TERMS · Active scenario: "&Assumptions!$D$10 -> Brightwater Retail Holdings · DEMO DATA · DEMO INVESTMENT TERMS · Active scenario: Downside
A4: $M | C4: FY2022A | D4: FY2023A | E4: FY2024A | F4: FY2025A | G4: FY2026E | H4: FY2027E | I4: FY2028E | J4: FY2029E | K4: FY2030E
A6: Rates & market-access (refinancing) test
A7: Base rate (SOFR) | G7: =Assumptions!$G$49 -> 0.0425 | H7: =Assumptions!$H$49 -> 0.04 | I7: =Assumptions!$I$49 -> 0.0375 | J7: =Assumptions!$J$49 -> 0.0375 | K7: =Assumptions!$K$49 -> 0.0375
A8: Floating-rate shock (selected scenario) | C8: =CHOOSE(Assumptions!$C$10,Assumptions!$C$72,Assumptions!$C$91,Assumptions!$C$110) -> 0.015
A9: Refinancing rate (selected scenario) | C9: =CHOOSE(Assumptions!$C$10,Assumptions!$C$73,Assumptions!$C$92,Assumptions!$C$111) -> 0.135
A10: Max net leverage to refinance | C10: =CHOOSE(Assumptions!$C$10,Assumptions!$C$74,Assumptions!$C$93,Assumptions!$C$112) -> 5.5
A11: Min pro-forma coverage to refinance | C11: =CHOOSE(Assumptions!$C$10,Assumptions!$C$75,Assumptions!$C$94,Assumptions!$C$113) -> 1.8
A12: Beginning total debt | G12: =G17+G30+G43+G56 -> 1250 | H12: =H17+H30+H43+H56 -> 1281.0968 | I12: =I17+I30+I43+I56 -> 1275.8968 | J12: =J17+J30+J43+J56 -> 1270.6968 | K12: =K17+K30+K43+K56 -> 1265.4968
A13: Beginning cash | G13: ='Cash Flow'!F19 -> 45 | H13: ='Cash Flow'!G19 -> 0 | I13: ='Cash Flow'!H19 -> -121.35573 | J13: ='Cash Flow'!I19 -> -236.70218 | K13: ='Cash Flow'!J19 -> -337.79889
A14: Pro-forma interest for refinancing test | G14: =G17*IF(G18=1,$C$9,IF(Assumptions!$I$53=1,MAX(G7,Assumptions!$G$53)+Assumptions!$F$53+$C$8,Assumptions!$E$53))+G30*IF(G31=1,$C$9,IF(Assumptions!$I$54=1,MAX(G7,Assumptions!$G$54)+Assumptions!$F$54+$C$8,Assumptions!$E$54))+G43*IF(G44=1,$C$9,IF(Assumptions!$I$55=1,MAX(G7,Assumptions!$G$55)+Assumptions!$F$55+$C$8,Assumptions!$E$55))+G56*IF(G57=1,$C$9,IF(Assumptions!$I$56=1,MAX(G7,Assumptions!$G$56)+Assumptions!$F$56+$C$8,Assumptions!$E$56)) -> 129.54 | H14: =H17*IF(OR(H18=1,Recovery!G39=1),$C$9,IF(Assumptions!$I$53=1,MAX(H7,Assumptions!$G$53)+Assumptions!$F$53+$C$8,Assumptions!$E$53))+H30*IF(OR(H31=1,Recovery!G40=1),$C$9,IF(Assumptions!$I$54=1,MAX(H7,Assumptions!$G$54)+Assumptions!$F$54+$C$8,Assumptions!$E$54))+H43*IF(OR(H44=1,Recovery!G41=1),$C$9,IF(Assumptions!$I$55=1,MAX(H7,Assumptions!$G$55)+Assumptions!$F$55+$C$8,Assumptions!$E$55))+H56*IF(OR(H57=1,Recovery!G42=1),$C$9,IF(Assumptions!$I$56=1,MAX(H7,Assumptions!$G$56)+Assumptions!$F$56+$C$8,Assumptions!$E$56)) -> 156.65947 | I14: =I17*IF(OR(I18=1,Recovery!H39=1),$C$9,IF(Assumptions!$I$53=1,MAX(I7,Assumptions!$G$53)+Assumptions!$F$53+$C$8,Assumptions!$E$53))+I30*IF(OR(I31=1,Recovery!H40=1),$C$9,IF(Assumptions!$I$54=1,MAX(I7,Assumptions!$G$54)+Assumptions!$F$54+$C$8,Assumptions!$E$54))+I43*IF(OR(I44=1,Recovery!H41=1),$C$9,IF(Assumptions!$I$55=1,MAX(I7,Assumptions!$G$55)+Assumptions!$F$55+$C$8,Assumptions!$E$55))+I56*IF(OR(I57=1,Recovery!H42=1),$C$9,IF(Assumptions!$I$56=1,MAX(I7,Assumptions!$G$56)+Assumptions!$F$56+$C$8,Assumptions!$E$56)) -> 139.56049 | J14: =J17*IF(OR(J18=1,Recovery!I39=1),$C$9,IF(Assumptions!$I$53=1,MAX(J7,Assumptions!$G$53)+Assumptions!$F$53+$C$8,Assumptions!$E$53))+J30*IF(OR(J31=1,Recovery!I40=1),$C$9,IF(Assumptions!$I$54=1,MAX(J7,Assumptions!$G$54)+Assumptions!$F$54+$C$8,Assumptions!$E$54))+J43*IF(OR(J44=1,Recovery!I41=1),$C$9,IF(Assumptions!$I$55=1,MAX(J7,Assumptions!$G$55)+Assumptions!$F$55+$C$8,Assumptions!$E$55))+J56*IF(OR(J57=1,Recovery!I42=1),$C$9,IF(Assumptions!$I$56=1,MAX(J7,Assumptions!$G$56)+Assumptions!$F$56+$C$8,Assumptions!$E$56)) -> 134.01169 | K14: =K17*IF(OR(K18=1,Recovery!J39=1),$C$9,IF(Assumptions!$I$53=1,MAX(K7,Assumptions!$G$53)+Assumptions!$F$53+$C$8,Assumptions!$E$53))+K30*IF(OR(K31=1,Recovery!J40=1),$C$9,IF(Assumptions!$I$54=1,MAX(K7,Assumptions!$G$54)+Assumptions!$F$54+$C$8,Assumptions!$E$54))+K43*IF(OR(K44=1,Recovery!J41=1),$C$9,IF(Assumptions!$I$55=1,MAX(K7,Assumptions!$G$55)+Assumptions!$F$55+$C$8,Assumptions!$E$55))+K56*IF(OR(K57=1,Recovery!J42=1),$C$9,IF(Assumptions!$I$56=1,MAX(K7,Assumptions!$G$56)+Assumptions!$F$56+$C$8,Assumptions!$E$56)) -> 127.17409
A15: Market access to refinance? (1 = yes) | G15: =IF('Operating Model'!G17<=0,0,IF(AND((G12-G13)/'Operating Model'!G17<=$C$10,'Operating Model'!G17/G14>=$C$11),1,0)) -> 0 | H15: =IF('Operating Model'!H17<=0,0,IF(AND((H12-H13)/'Operating Model'!H17<=$C$10,'Operating Model'!H17/H14>=$C$11),1,0)) -> 0 | I15: =IF('Operating Model'!I17<=0,0,IF(AND((I12-I13)/'Operating Model'!I17<=$C$10,'Operating Model'!I17/I14>=$C$11),1,0)) -> 0 | J15: =IF('Operating Model'!J17<=0,0,IF(AND((J12-J13)/'Operating Model'!J17<=$C$10,'Operating Model'!J17/J14>=$C$11),1,0)) -> 0 | K15: =IF('Operating Model'!K17<=0,0,IF(AND((K12-K13)/'Operating Model'!K17<=$C$10,'Operating Model'!K17/K14>=$C$11),1,0)) -> 0
A16: Tranche 1: ABL Revolver
A17: Beginning balance | G17: =F28 -> 180 | H17: =G28 -> 216.2968 | I17: =H28 -> 216.2968 | J17: =I28 -> 216.2968 | K17: =J28 -> 216.2968
A18: Maturing this period? (1 = yes) | G18: =IF('Operating Model'!G7=Assumptions!$K$53,1,0) -> 0 | H18: =IF('Operating Model'!H7=Assumptions!$K$53,1,0) -> 1 | I18: =IF('Operating Model'!I7=Assumptions!$K$53,1,0) -> 0 | J18: =IF('Operating Model'!J7=Assumptions!$K$53,1,0) -> 0 | K18: =IF('Operating Model'!K7=Assumptions!$K$53,1,0) -> 0
A20: All-in interest rate applied | G20: =IF(Assumptions!$I$53=1,MAX(G7,Assumptions!$G$53)+Assumptions!$F$53+$C$8,Assumptions!$E$53) -> 0.101 | H20: =IF(Recovery!G39=1,$C$9,IF(Assumptions!$I$53=1,MAX(H7,Assumptions!$G$53)+Assumptions!$F$53+$C$8,Assumptions!$E$53)) -> 0.0985 | I20: =IF(Recovery!H39=1,$C$9,IF(Assumptions!$I$53=1,MAX(I7,Assumptions!$G$53)+Assumptions!$F$53+$C$8,Assumptions!$E$53)) -> 0.096 | J20: =IF(Recovery!I39=1,$C$9,IF(Assumptions!$I$53=1,MAX(J7,Assumptions!$G$53)+Assumptions!$F$53+$C$8,Assumptions!$E$53)) -> 0.096 | K20: =IF(Recovery!J39=1,$C$9,IF(Assumptions!$I$53=1,MAX(K7,Assumptions!$G$53)+Assumptions!$F$53+$C$8,Assumptions!$E$53)) -> 0.096
A21: Cash interest expense | G21: =G17*G20 -> 18.18 | H21: =H17*H20 -> 21.305235 | I21: =I17*I20 -> 20.764493 | J21: =J17*J20 -> 20.764493 | K21: =K17*K20 -> 20.764493
A22: PIK interest | G22: =G17*Assumptions!$H$53 -> 0 | H22: =H17*Assumptions!$H$53 -> 0 | I22: =I17*Assumptions!$H$53 -> 0 | J22: =J17*Assumptions!$H$53 -> 0 | K22: =K17*Assumptions!$H$53 -> 0
A23: Mandatory amortization | G23: =MIN(G17,Assumptions!$L$53*Assumptions!$C$53) -> 0 | H23: =MIN(H17,Assumptions!$L$53*Assumptions!$C$53) -> 0 | I23: =MIN(I17,Assumptions!$L$53*Assumptions!$C$53) -> 0 | J23: =MIN(J17,Assumptions!$L$53*Assumptions!$C$53) -> 0 | K23: =MIN(K17,Assumptions!$L$53*Assumptions!$C$53) -> 0
A24: New borrowing (revolver draw) | G24: =IF(AND(Assumptions!$P$53=1,'Operating Model'!G7<Assumptions!$K$53),MIN(MAX(0,-'Cash Flow'!G11),MAX(0,Assumptions!$D$53-G17)),0) -> 36.2968 | H24: =IF(AND(Assumptions!$P$53=1,OR('Operating Model'!H7<Assumptions!$K$53,Recovery!G39=1)),MIN(MAX(0,-'Cash Flow'!H11),MAX(0,Assumptions!$D$53-H17)),0) -> 0 | I24: =IF(AND(Assumptions!$P$53=1,OR('Operating Model'!I7<Assumptions!$K$53,Recovery!H39=1)),MIN(MAX(0,-'Cash Flow'!I11),MAX(0,Assumptions!$D$53-I17)),0) -> 0 | J24: =IF(AND(Assumptions!$P$53=1,OR('Operating Model'!J7<Assumptions!$K$53,Recovery!I39=1)),MIN(MAX(0,-'Cash Flow'!J11),MAX(0,Assumptions!$D$53-J17)),0) -> 0 | K24: =IF(AND(Assumptions!$P$53=1,OR('Operating Model'!K7<Assumptions!$K$53,Recovery!J39=1)),MIN(MAX(0,-'Cash Flow'!K11),MAX(0,Assumptions!$D$53-K17)),0) -> 0
A25: Repayment at maturity (from available cash) | G25: =G18*MIN(G17-G23+G22,MAX(0,'Cash Flow'!G13-Assumptions!$C$12*G15)) -> 0 | H25: =H18*MIN(H17-H23+H22,MAX(0,'Cash Flow'!H13-Assumptions!$C$12*H15)) -> 0 | I25: =I18*MIN(I17-I23+I22,MAX(0,'Cash Flow'!I13-Assumptions!$C$12*I15)) -> 0 | J25: =J18*MIN(J17-J23+J22,MAX(0,'Cash Flow'!J13-Assumptions!$C$12*J15)) -> 0 | K25: =K18*MIN(K17-K23+K22,MAX(0,'Cash Flow'!K13-Assumptions!$C$12*K15)) -> 0
A26: Optional repayment (cash sweep) | G26: =Assumptions!$N$53*MIN(G17+G24+G22-G23-G25,MAX(0,'Cash Flow'!G17)) -> 0 | H26: =Assumptions!$N$53*MIN(H17+H24+H22-H23-H25,MAX(0,'Cash Flow'!H17)) -> 0 | I26: =Assumptions!$N$53*MIN(I17+I24+I22-I23-I25,MAX(0,'Cash Flow'!I17)) -> 0 | J26: =Assumptions!$N$53*MIN(J17+J24+J22-J23-J25,MAX(0,'Cash Flow'!J17)) -> 0 | K26: =Assumptions!$N$53*MIN(K17+K24+K22-K23-K25,MAX(0,'Cash Flow'!K17)) -> 0
A27: Unpaid at maturity (no refinancing, insufficient cash) | G27: =G18*(1-G15)*(G17-G23+G22-G25) -> 0 | H27: =H18*(1-H15)*(H17-H23+H22-H25) -> 216.2968 | I27: =I18*(1-I15)*(I17-I23+I22-I25) -> 0 | J27: =J18*(1-J15)*(J17-J23+J22-J25) -> 0 | K27: =K18*(1-K15)*(K17-K23+K22-K25) -> 0
A28: Ending balance | F28: =Assumptions!$C$53 -> 180 | G28: =G17+G24+G22-G23-G25-G26 -> 216.2968 | H28: =H17+H24+H22-H23-H25-H26 -> 216.2968 | I28: =I17+I24+I22-I23-I25-I26 -> 216.2968 | J28: =J17+J24+J22-J23-J25-J26 -> 216.2968 | K28: =K17+K24+K22-K23-K25-K26 -> 216.2968
A29: Tranche 2: First-Lien Term Loan
A30: Beginning balance | G30: =F41 -> 520 | H30: =G41 -> 514.8 | I30: =H41 -> 509.6 | J30: =I41 -> 504.4 | K30: =J41 -> 499.2
A31: Maturing this period? (1 = yes) | G31: =IF('Operating Model'!G7=Assumptions!$K$54,1,0) -> 0 | H31: =IF('Operating Model'!H7=Assumptions!$K$54,1,0) -> 0 | I31: =IF('Operating Model'!I7=Assumptions!$K$54,1,0) -> 1 | J31: =IF('Operating Model'!J7=Assumptions!$K$54,1,0) -> 0 | K31: =IF('Operating Model'!K7=Assumptions!$K$54,1,0) -> 0
A33: All-in interest rate applied | G33: =IF(Assumptions!$I$54=1,MAX(G7,Assumptions!$G$54)+Assumptions!$F$54+$C$8,Assumptions!$E$54) -> 0.118 | H33: =IF(Recovery!G40=1,$C$9,IF(Assumptions!$I$54=1,MAX(H7,Assumptions!$G$54)+Assumptions!$F$54+$C$8,Assumptions!$E$54)) -> 0.1155 | I33: =IF(Recovery!H40=1,$C$9,IF(Assumptions!$I$54=1,MAX(I7,Assumptions!$G$54)+Assumptions!$F$54+$C$8,Assumptions!$E$54)) -> 0.113 | J33: =IF(Recovery!I40=1,$C$9,IF(Assumptions!$I$54=1,MAX(J7,Assumptions!$G$54)+Assumptions!$F$54+$C$8,Assumptions!$E$54)) -> 0.113 | K33: =IF(Recovery!J40=1,$C$9,IF(Assumptions!$I$54=1,MAX(K7,Assumptions!$G$54)+Assumptions!$F$54+$C$8,Assumptions!$E$54)) -> 0.113
A34: Cash interest expense | G34: =G30*G33 -> 61.36 | H34: =H30*H33 -> 59.4594 | I34: =I30*I33 -> 57.5848 | J34: =J30*J33 -> 56.9972 | K34: =K30*K33 -> 56.4096
A35: PIK interest | G35: =G30*Assumptions!$H$54 -> 0 | H35: =H30*Assumptions!$H$54 -> 0 | I35: =I30*Assumptions!$H$54 -> 0 | J35: =J30*Assumptions!$H$54 -> 0 | K35: =K30*Assumptions!$H$54 -> 0
A36: Mandatory amortization | G36: =MIN(G30,Assumptions!$L$54*Assumptions!$C$54) -> 5.2 | H36: =MIN(H30,Assumptions!$L$54*Assumptions!$C$54) -> 5.2 | I36: =MIN(I30,Assumptions!$L$54*Assumptions!$C$54) -> 5.2 | J36: =MIN(J30,Assumptions!$L$54*Assumptions!$C$54) -> 5.2 | K36: =MIN(K30,Assumptions!$L$54*Assumptions!$C$54) -> 5.2
A37: New borrowing (revolver draw) | G37: =IF(AND(Assumptions!$P$54=1,'Operating Model'!G7<Assumptions!$K$54),MIN(MAX(0,-'Cash Flow'!G11),MAX(0,Assumptions!$D$54-G30)),0) -> 0 | H37: =IF(AND(Assumptions!$P$54=1,OR('Operating Model'!H7<Assumptions!$K$54,Recovery!G40=1)),MIN(MAX(0,-'Cash Flow'!H11),MAX(0,Assumptions!$D$54-H30)),0) -> 0 | I37: =IF(AND(Assumptions!$P$54=1,OR('Operating Model'!I7<Assumptions!$K$54,Recovery!H40=1)),MIN(MAX(0,-'Cash Flow'!I11),MAX(0,Assumptions!$D$54-I30)),0) -> 0 | J37: =IF(AND(Assumptions!$P$54=1,OR('Operating Model'!J7<Assumptions!$K$54,Recovery!I40=1)),MIN(MAX(0,-'Cash Flow'!J11),MAX(0,Assumptions!$D$54-J30)),0) -> 0 | K37: =IF(AND(Assumptions!$P$54=1,OR('Operating Model'!K7<Assumptions!$K$54,Recovery!J40=1)),MIN(MAX(0,-'Cash Flow'!K11),MAX(0,Assumptions!$D$54-K30)),0) -> 0
A38: Repayment at maturity (from available cash) | G38: =G31*MIN(G30-G36+G35,MAX(0,'Cash Flow'!G13-Assumptions!$C$12*G15-G25)) -> 0 | H38: =H31*MIN(H30-H36+H35,MAX(0,'Cash Flow'!H13-Assumptions!$C$12*H15-H25)) -> 0 | I38: =I31*MIN(I30-I36+I35,MAX(0,'Cash Flow'!I13-Assumptions!$C$12*I15-I25)) -> 0 | J38: =J31*MIN(J30-J36+J35,MAX(0,'Cash Flow'!J13-Assumptions!$C$12*J15-J25)) -> 0 | K38: =K31*MIN(K30-K36+K35,MAX(0,'Cash Flow'!K13-Assumptions!$C$12*K15-K25)) -> 0
A39: Optional repayment (cash sweep) | G39: =Assumptions!$N$54*MIN(G30+G37+G35-G36-G38,MAX(0,'Cash Flow'!G17-G26)) -> 0 | H39: =Assumptions!$N$54*MIN(H30+H37+H35-H36-H38,MAX(0,'Cash Flow'!H17-H26)) -> 0 | I39: =Assumptions!$N$54*MIN(I30+I37+I35-I36-I38,MAX(0,'Cash Flow'!I17-I26)) -> 0 | J39: =Assumptions!$N$54*MIN(J30+J37+J35-J36-J38,MAX(0,'Cash Flow'!J17-J26)) -> 0 | K39: =Assumptions!$N$54*MIN(K30+K37+K35-K36-K38,MAX(0,'Cash Flow'!K17-K26)) -> 0
A40: Unpaid at maturity (no refinancing, insufficient cash) | G40: =G31*(1-G15)*(G30-G36+G35-G38) -> 0 | H40: =H31*(1-H15)*(H30-H36+H35-H38) -> 0 | I40: =I31*(1-I15)*(I30-I36+I35-I38) -> 504.4 | J40: =J31*(1-J15)*(J30-J36+J35-J38) -> 0 | K40: =K31*(1-K15)*(K30-K36+K35-K38) -> 0
A41: Ending balance | F41: =Assumptions!$C$54 -> 520 | G41: =G30+G37+G35-G36-G38-G39 -> 514.8 | H41: =H30+H37+H35-H36-H38-H39 -> 509.6 | I41: =I30+I37+I35-I36-I38-I39 -> 504.4 | J41: =J30+J37+J35-J36-J38-J39 -> 499.2 | K41: =K30+K37+K35-K36-K38-K39 -> 494
A42: Tranche 3: Second-Lien Notes 11.0%
A43: Beginning balance | G43: =F54 -> 250 | H43: =G54 -> 250 | I43: =H54 -> 250 | J43: =I54 -> 250 | K43: =J54 -> 250
A44: Maturing this period? (1 = yes) | G44: =IF('Operating Model'!G7=Assumptions!$K$55,1,0) -> 0 | H44: =IF('Operating Model'!H7=Assumptions!$K$55,1,0) -> 0 | I44: =IF('Operating Model'!I7=Assumptions!$K$55,1,0) -> 0 | J44: =IF('Operating Model'!J7=Assumptions!$K$55,1,0) -> 1 | K44: =IF('Operating Model'!K7=Assumptions!$K$55,1,0) -> 0
A46: All-in interest rate applied | G46: =IF(Assumptions!$I$55=1,MAX(G7,Assumptions!$G$55)+Assumptions!$F$55+$C$8,Assumptions!$E$55) -> 0.11 | H46: =IF(Recovery!G41=1,$C$9,IF(Assumptions!$I$55=1,MAX(H7,Assumptions!$G$55)+Assumptions!$F$55+$C$8,Assumptions!$E$55)) -> 0.11 | I46: =IF(Recovery!H41=1,$C$9,IF(Assumptions!$I$55=1,MAX(I7,Assumptions!$G$55)+Assumptions!$F$55+$C$8,Assumptions!$E$55)) -> 0.11 | J46: =IF(Recovery!I41=1,$C$9,IF(Assumptions!$I$55=1,MAX(J7,Assumptions!$G$55)+Assumptions!$F$55+$C$8,Assumptions!$E$55)) -> 0.11 | K46: =IF(Recovery!J41=1,$C$9,IF(Assumptions!$I$55=1,MAX(K7,Assumptions!$G$55)+Assumptions!$F$55+$C$8,Assumptions!$E$55)) -> 0.11
A47: Cash interest expense | G47: =G43*G46 -> 27.5 | H47: =H43*H46 -> 27.5 | I47: =I43*I46 -> 27.5 | J47: =J43*J46 -> 27.5 | K47: =K43*K46 -> 27.5
A48: PIK interest | G48: =G43*Assumptions!$H$55 -> 0 | H48: =H43*Assumptions!$H$55 -> 0 | I48: =I43*Assumptions!$H$55 -> 0 | J48: =J43*Assumptions!$H$55 -> 0 | K48: =K43*Assumptions!$H$55 -> 0
A49: Mandatory amortization | G49: =MIN(G43,Assumptions!$L$55*Assumptions!$C$55) -> 0 | H49: =MIN(H43,Assumptions!$L$55*Assumptions!$C$55) -> 0 | I49: =MIN(I43,Assumptions!$L$55*Assumptions!$C$55) -> 0 | J49: =MIN(J43,Assumptions!$L$55*Assumptions!$C$55) -> 0 | K49: =MIN(K43,Assumptions!$L$55*Assumptions!$C$55) -> 0
A50: New borrowing (revolver draw) | G50: =IF(AND(Assumptions!$P$55=1,'Operating Model'!G7<Assumptions!$K$55),MIN(MAX(0,-'Cash Flow'!G11),MAX(0,Assumptions!$D$55-G43)),0) -> 0 | H50: =IF(AND(Assumptions!$P$55=1,OR('Operating Model'!H7<Assumptions!$K$55,Recovery!G41=1)),MIN(MAX(0,-'Cash Flow'!H11),MAX(0,Assumptions!$D$55-H43)),0) -> 0 | I50: =IF(AND(Assumptions!$P$55=1,OR('Operating Model'!I7<Assumptions!$K$55,Recovery!H41=1)),MIN(MAX(0,-'Cash Flow'!I11),MAX(0,Assumptions!$D$55-I43)),0) -> 0 | J50: =IF(AND(Assumptions!$P$55=1,OR('Operating Model'!J7<Assumptions!$K$55,Recovery!I41=1)),MIN(MAX(0,-'Cash Flow'!J11),MAX(0,Assumptions!$D$55-J43)),0) -> 0 | K50: =IF(AND(Assumptions!$P$55=1,OR('Operating Model'!K7<Assumptions!$K$55,Recovery!J41=1)),MIN(MAX(0,-'Cash Flow'!K11),MAX(0,Assumptions!$D$55-K43)),0) -> 0
A51: Repayment at maturity (from available cash) | G51: =G44*MIN(G43-G49+G48,MAX(0,'Cash Flow'!G13-Assumptions!$C$12*G15-G25-G38)) -> 0 | H51: =H44*MIN(H43-H49+H48,MAX(0,'Cash Flow'!H13-Assumptions!$C$12*H15-H25-H38)) -> 0 | I51: =I44*MIN(I43-I49+I48,MAX(0,'Cash Flow'!I13-Assumptions!$C$12*I15-I25-I38)) -> 0 | J51: =J44*MIN(J43-J49+J48,MAX(0,'Cash Flow'!J13-Assumptions!$C$12*J15-J25-J38)) -> 0 | K51: =K44*MIN(K43-K49+K48,MAX(0,'Cash Flow'!K13-Assumptions!$C$12*K15-K25-K38)) -> 0
A52: Optional repayment (cash sweep) | G52: =Assumptions!$N$55*MIN(G43+G50+G48-G49-G51,MAX(0,'Cash Flow'!G17-G26-G39)) -> 0 | H52: =Assumptions!$N$55*MIN(H43+H50+H48-H49-H51,MAX(0,'Cash Flow'!H17-H26-H39)) -> 0 | I52: =Assumptions!$N$55*MIN(I43+I50+I48-I49-I51,MAX(0,'Cash Flow'!I17-I26-I39)) -> 0 | J52: =Assumptions!$N$55*MIN(J43+J50+J48-J49-J51,MAX(0,'Cash Flow'!J17-J26-J39)) -> 0 | K52: =Assumptions!$N$55*MIN(K43+K50+K48-K49-K51,MAX(0,'Cash Flow'!K17-K26-K39)) -> 0
A53: Unpaid at maturity (no refinancing, insufficient cash) | G53: =G44*(1-G15)*(G43-G49+G48-G51) -> 0 | H53: =H44*(1-H15)*(H43-H49+H48-H51) -> 0 | I53: =I44*(1-I15)*(I43-I49+I48-I51) -> 0 | J53: =J44*(1-J15)*(J43-J49+J48-J51) -> 250 | K53: =K44*(1-K15)*(K43-K49+K48-K51) -> 0
A54: Ending balance | F54: =Assumptions!$C$55 -> 250 | G54: =G43+G50+G48-G49-G51-G52 -> 250 | H54: =H43+H50+H48-H49-H51-H52 -> 250 | I54: =I43+I50+I48-I49-I51-I52 -> 250 | J54: =J43+J50+J48-J49-J51-J52 -> 250 | K54: =K43+K50+K48-K49-K51-K52 -> 250
A55: Tranche 4: Senior Unsecured Notes 7.5%
A56: Beginning balance | G56: =F67 -> 300 | H56: =G67 -> 300 | I56: =H67 -> 300 | J56: =I67 -> 300 | K56: =J67 -> 300
A57: Maturing this period? (1 = yes) | G57: =IF('Operating Model'!G7=Assumptions!$K$56,1,0) -> 0 | H57: =IF('Operating Model'!H7=Assumptions!$K$56,1,0) -> 1 | I57: =IF('Operating Model'!I7=Assumptions!$K$56,1,0) -> 0 | J57: =IF('Operating Model'!J7=Assumptions!$K$56,1,0) -> 0 | K57: =IF('Operating Model'!K7=Assumptions!$K$56,1,0) -> 0
A59: All-in interest rate applied | G59: =IF(Assumptions!$I$56=1,MAX(G7,Assumptions!$G$56)+Assumptions!$F$56+$C$8,Assumptions!$E$56) -> 0.075 | H59: =IF(Recovery!G42=1,$C$9,IF(Assumptions!$I$56=1,MAX(H7,Assumptions!$G$56)+Assumptions!$F$56+$C$8,Assumptions!$E$56)) -> 0.075 | I59: =IF(Recovery!H42=1,$C$9,IF(Assumptions!$I$56=1,MAX(I7,Assumptions!$G$56)+Assumptions!$F$56+$C$8,Assumptions!$E$56)) -> 0.075 | J59: =IF(Recovery!I42=1,$C$9,IF(Assumptions!$I$56=1,MAX(J7,Assumptions!$G$56)+Assumptions!$F$56+$C$8,Assumptions!$E$56)) -> 0.075 | K59: =IF(Recovery!J42=1,$C$9,IF(Assumptions!$I$56=1,MAX(K7,Assumptions!$G$56)+Assumptions!$F$56+$C$8,Assumptions!$E$56)) -> 0.075
A60: Cash interest expense | G60: =G56*G59 -> 22.5 | H60: =H56*H59 -> 22.5 | I60: =I56*I59 -> 22.5 | J60: =J56*J59 -> 22.5 | K60: =K56*K59 -> 22.5
A61: PIK interest | G61: =G56*Assumptions!$H$56 -> 0 | H61: =H56*Assumptions!$H$56 -> 0 | I61: =I56*Assumptions!$H$56 -> 0 | J61: =J56*Assumptions!$H$56 -> 0 | K61: =K56*Assumptions!$H$56 -> 0
A62: Mandatory amortization | G62: =MIN(G56,Assumptions!$L$56*Assumptions!$C$56) -> 0 | H62: =MIN(H56,Assumptions!$L$56*Assumptions!$C$56) -> 0 | I62: =MIN(I56,Assumptions!$L$56*Assumptions!$C$56) -> 0 | J62: =MIN(J56,Assumptions!$L$56*Assumptions!$C$56) -> 0 | K62: =MIN(K56,Assumptions!$L$56*Assumptions!$C$56) -> 0
A63: New borrowing (revolver draw) | G63: =IF(AND(Assumptions!$P$56=1,'Operating Model'!G7<Assumptions!$K$56),MIN(MAX(0,-'Cash Flow'!G11),MAX(0,Assumptions!$D$56-G56)),0) -> 0 | H63: =IF(AND(Assumptions!$P$56=1,OR('Operating Model'!H7<Assumptions!$K$56,Recovery!G42=1)),MIN(MAX(0,-'Cash Flow'!H11),MAX(0,Assumptions!$D$56-H56)),0) -> 0 | I63: =IF(AND(Assumptions!$P$56=1,OR('Operating Model'!I7<Assumptions!$K$56,Recovery!H42=1)),MIN(MAX(0,-'Cash Flow'!I11),MAX(0,Assumptions!$D$56-I56)),0) -> 0 | J63: =IF(AND(Assumptions!$P$56=1,OR('Operating Model'!J7<Assumptions!$K$56,Recovery!I42=1)),MIN(MAX(0,-'Cash Flow'!J11),MAX(0,Assumptions!$D$56-J56)),0) -> 0 | K63: =IF(AND(Assumptions!$P$56=1,OR('Operating Model'!K7<Assumptions!$K$56,Recovery!J42=1)),MIN(MAX(0,-'Cash Flow'!K11),MAX(0,Assumptions!$D$56-K56)),0) -> 0
A64: Repayment at maturity (from available cash) | G64: =G57*MIN(G56-G62+G61,MAX(0,'Cash Flow'!G13-Assumptions!$C$12*G15-G25-G38-G51)) -> 0 | H64: =H57*MIN(H56-H62+H61,MAX(0,'Cash Flow'!H13-Assumptions!$C$12*H15-H25-H38-H51)) -> 0 | I64: =I57*MIN(I56-I62+I61,MAX(0,'Cash Flow'!I13-Assumptions!$C$12*I15-I25-I38-I51)) -> 0 | J64: =J57*MIN(J56-J62+J61,MAX(0,'Cash Flow'!J13-Assumptions!$C$12*J15-J25-J38-J51)) -> 0 | K64: =K57*MIN(K56-K62+K61,MAX(0,'Cash Flow'!K13-Assumptions!$C$12*K15-K25-K38-K51)) -> 0
A65: Optional repayment (cash sweep) | G65: =Assumptions!$N$56*MIN(G56+G63+G61-G62-G64,MAX(0,'Cash Flow'!G17-G26-G39-G52)) -> 0 | H65: =Assumptions!$N$56*MIN(H56+H63+H61-H62-H64,MAX(0,'Cash Flow'!H17-H26-H39-H52)) -> 0 | I65: =Assumptions!$N$56*MIN(I56+I63+I61-I62-I64,MAX(0,'Cash Flow'!I17-I26-I39-I52)) -> 0 | J65: =Assumptions!$N$56*MIN(J56+J63+J61-J62-J64,MAX(0,'Cash Flow'!J17-J26-J39-J52)) -> 0 | K65: =Assumptions!$N$56*MIN(K56+K63+K61-K62-K64,MAX(0,'Cash Flow'!K17-K26-K39-K52)) -> 0
A66: Unpaid at maturity (no refinancing, insufficient cash) | G66: =G57*(1-G15)*(G56-G62+G61-G64) -> 0 | H66: =H57*(1-H15)*(H56-H62+H61-H64) -> 300 | I66: =I57*(1-I15)*(I56-I62+I61-I64) -> 0 | J66: =J57*(1-J15)*(J56-J62+J61-J64) -> 0 | K66: =K57*(1-K15)*(K56-K62+K61-K64) -> 0
A67: Ending balance | F67: =Assumptions!$C$56 -> 300 | G67: =G56+G63+G61-G62-G64-G65 -> 300 | H67: =H56+H63+H61-H62-H64-H65 -> 300 | I67: =I56+I63+I61-I62-I64-I65 -> 300 | J67: =J56+J63+J61-J62-J64-J65 -> 300 | K67: =K56+K63+K61-K62-K64-K65 -> 300
A68: Totals
A69: Total debt — ending | F69: =F28+F41+F54+F67 -> 1250 | G69: =G28+G41+G54+G67 -> 1281.0968 | H69: =H28+H41+H54+H67 -> 1275.8968 | I69: =I28+I41+I54+I67 -> 1270.6968 | J69: =J28+J41+J54+J67 -> 1265.4968 | K69: =K28+K41+K54+K67 -> 1260.2968
A70: Contractual maturities by period (from maturity flags) | G70: =G18*Assumptions!$C$53+G31*Assumptions!$C$54+G44*Assumptions!$C$55+G57*Assumptions!$C$56 -> 0 | H70: =H18*Assumptions!$C$53+H31*Assumptions!$C$54+H44*Assumptions!$C$55+H57*Assumptions!$C$56 -> 480 | I70: =I18*Assumptions!$C$53+I31*Assumptions!$C$54+I44*Assumptions!$C$55+I57*Assumptions!$C$56 -> 520 | J70: =J18*Assumptions!$C$53+J31*Assumptions!$C$54+J44*Assumptions!$C$55+J57*Assumptions!$C$56 -> 250 | K70: =K18*Assumptions!$C$53+K31*Assumptions!$C$54+K44*Assumptions!$C$55+K57*Assumptions!$C$56 -> 0
A71: Refinancing risk engine — result per maturing tranche
A72: Tranche 1: balance at maturity | C72: =SUMPRODUCT($G$18:$K$18,$G$17:$K$17-$G$23:$K$23+$G$22:$K$22) -> 216.2968
A73: Tranche 1: repaid from cash at maturity | C73: =SUMPRODUCT($G$18:$K$18,$G$25:$K$25) -> 0
A74: Tranche 1: refinancing test | C74: =IF(SUM($G$18:$K$18)=0,"n/a (beyond horizon)",IF(SUMPRODUCT($G$18:$K$18,$G$15:$K$15)>0,"REFINANCING PASS","REFINANCING FAILURE")) -> REFINANCING FAILURE
A75: Tranche 1: resolution | C75: =IF(SUM($G$18:$K$18)=0,"n/a",IF(C73>=C72-0.001,"Repaid from cash",IF(SUMPRODUCT($G$18:$K$18,$G$15:$K$15)>0,IF(C73>0,"Partly repaid; remainder refinanced","Refinanced"),IF(SUM($G$27:$K$27)>0.001,IF(C73>0,"Partial repayment; PAYMENT DEFAULT","PAYMENT DEFAULT"),"Repaid from cash")))) -> PAYMENT DEFAULT
A76: Tranche 2: balance at maturity | C76: =SUMPRODUCT($G$31:$K$31,$G$30:$K$30-$G$36:$K$36+$G$35:$K$35) -> 504.4
A77: Tranche 2: repaid from cash at maturity | C77: =SUMPRODUCT($G$31:$K$31,$G$38:$K$38) -> 0
A78: Tranche 2: refinancing test | C78: =IF(SUM($G$31:$K$31)=0,"n/a (beyond horizon)",IF(SUMPRODUCT($G$31:$K$31,$G$15:$K$15)>0,"REFINANCING PASS","REFINANCING FAILURE")) -> REFINANCING FAILURE
A79: Tranche 2: resolution | C79: =IF(SUM($G$31:$K$31)=0,"n/a",IF(C77>=C76-0.001,"Repaid from cash",IF(SUMPRODUCT($G$31:$K$31,$G$15:$K$15)>0,IF(C77>0,"Partly repaid; remainder refinanced","Refinanced"),IF(SUM($G$40:$K$40)>0.001,IF(C77>0,"Partial repayment; PAYMENT DEFAULT","PAYMENT DEFAULT"),"Repaid from cash")))) -> PAYMENT DEFAULT
A80: Tranche 3: balance at maturity | C80: =SUMPRODUCT($G$44:$K$44,$G$43:$K$43-$G$49:$K$49+$G$48:$K$48) -> 250
A81: Tranche 3: repaid from cash at maturity | C81: =SUMPRODUCT($G$44:$K$44,$G$51:$K$51) -> 0
A82: Tranche 3: refinancing test | C82: =IF(SUM($G$44:$K$44)=0,"n/a (beyond horizon)",IF(SUMPRODUCT($G$44:$K$44,$G$15:$K$15)>0,"REFINANCING PASS","REFINANCING FAILURE")) -> REFINANCING FAILURE
A83: Tranche 3: resolution | C83: =IF(SUM($G$44:$K$44)=0,"n/a",IF(C81>=C80-0.001,"Repaid from cash",IF(SUMPRODUCT($G$44:$K$44,$G$15:$K$15)>0,IF(C81>0,"Partly repaid; remainder refinanced","Refinanced"),IF(SUM($G$53:$K$53)>0.001,IF(C81>0,"Partial repayment; PAYMENT DEFAULT","PAYMENT DEFAULT"),"Repaid from cash")))) -> PAYMENT DEFAULT
A84: Tranche 4: balance at maturity | C84: =SUMPRODUCT($G$57:$K$57,$G$56:$K$56-$G$62:$K$62+$G$61:$K$61) -> 300
A85: Tranche 4: repaid from cash at maturity | C85: =SUMPRODUCT($G$57:$K$57,$G$64:$K$64) -> 0
A86: Tranche 4: refinancing test | C86: =IF(SUM($G$57:$K$57)=0,"n/a (beyond horizon)",IF(SUMPRODUCT($G$57:$K$57,$G$15:$K$15)>0,"REFINANCING PASS","REFINANCING FAILURE")) -> REFINANCING FAILURE
A87: Tranche 4: resolution | C87: =IF(SUM($G$57:$K$57)=0,"n/a",IF(C85>=C84-0.001,"Repaid from cash",IF(SUMPRODUCT($G$57:$K$57,$G$15:$K$15)>0,IF(C85>0,"Partly repaid; remainder refinanced","Refinanced"),IF(SUM($G$66:$K$66)>0.001,IF(C85>0,"Partial repayment; PAYMENT DEFAULT","PAYMENT DEFAULT"),"Repaid from cash")))) -> PAYMENT DEFAULT
A88: Refinancing failures (count of maturing tranches) | C88: =IF(C74="REFINANCING FAILURE",1,0)+IF(C78="REFINANCING FAILURE",1,0)+IF(C82="REFINANCING FAILURE",1,0)+IF(C86="REFINANCING FAILURE",1,0) -> 4

Sheet Cash Flow
A1: Cash Flow & Liquidity — cash waterfall and default test
A2: ="Brightwater Retail Holdings · DEMO DATA · DEMO INVESTMENT TERMS · Active scenario: "&Assumptions!$D$10 -> Brightwater Retail Holdings · DEMO DATA · DEMO INVESTMENT TERMS · Active scenario: Downside
A4: $M | C4: FY2022A | D4: FY2023A | E4: FY2024A | F4: FY2025A | G4: FY2026E | H4: FY2027E | I4: FY2028E | J4: FY2029E | K4: FY2030E
A6: Cash flow & liquidity waterfall ($M)
A7: Beginning cash | G7: =F19 -> 45 | H7: =G19 -> 0 | I7: =H19 -> -121.35573 | J7: =I19 -> -236.70218 | K7: =J19 -> -337.79889
A8: Free cash flow (from Operating Model) | G8: ='Operating Model'!G30 -> -76.0968 | H8: ='Operating Model'!H30 -> -116.15573 | I8: ='Operating Model'!I30 -> -110.14645 | J8: ='Operating Model'!J30 -> -95.896716 | K8: ='Operating Model'!K30 -> -83.185191
A9: Plus: net asset-sale proceeds | G9: =CHOOSE(Assumptions!$C$10,Assumptions!$G$68,Assumptions!$G$87,Assumptions!$G$106) -> 0 | H9: =CHOOSE(Assumptions!$C$10,Assumptions!$H$68,Assumptions!$H$87,Assumptions!$H$106) -> 0 | I9: =CHOOSE(Assumptions!$C$10,Assumptions!$I$68,Assumptions!$I$87,Assumptions!$I$106) -> 0 | J9: =CHOOSE(Assumptions!$C$10,Assumptions!$J$68,Assumptions!$J$87,Assumptions!$J$106) -> 0 | K9: =CHOOSE(Assumptions!$C$10,Assumptions!$K$68,Assumptions!$K$87,Assumptions!$K$106) -> 0
A10: Less: mandatory amortization | G10: ='Debt Schedule'!G23+'Debt Schedule'!G36+'Debt Schedule'!G49+'Debt Schedule'!G62 -> 5.2 | H10: ='Debt Schedule'!H23+'Debt Schedule'!H36+'Debt Schedule'!H49+'Debt Schedule'!H62 -> 5.2 | I10: ='Debt Schedule'!I23+'Debt Schedule'!I36+'Debt Schedule'!I49+'Debt Schedule'!I62 -> 5.2 | J10: ='Debt Schedule'!J23+'Debt Schedule'!J36+'Debt Schedule'!J49+'Debt Schedule'!J62 -> 5.2 | K10: ='Debt Schedule'!K23+'Debt Schedule'!K36+'Debt Schedule'!K49+'Debt Schedule'!K62 -> 5.2
A11: Cash after mandatory debt service | G11: =G7+G8+G9-G10 -> -36.2968 | H11: =H7+H8+H9-H10 -> -121.35573 | I11: =I7+I8+I9-I10 -> -236.70218 | J11: =J7+J8+J9-J10 -> -337.79889 | K11: =K7+K8+K9-K10 -> -426.18408
A12: Plus: revolver draw | G12: ='Debt Schedule'!G24+'Debt Schedule'!G37+'Debt Schedule'!G50+'Debt Schedule'!G63 -> 36.2968 | H12: ='Debt Schedule'!H24+'Debt Schedule'!H37+'Debt Schedule'!H50+'Debt Schedule'!H63 -> 0 | I12: ='Debt Schedule'!I24+'Debt Schedule'!I37+'Debt Schedule'!I50+'Debt Schedule'!I63 -> 0 | J12: ='Debt Schedule'!J24+'Debt Schedule'!J37+'Debt Schedule'!J50+'Debt Schedule'!J63 -> 0 | K12: ='Debt Schedule'!K24+'Debt Schedule'!K37+'Debt Schedule'!K50+'Debt Schedule'!K63 -> 0
A13: Cash available for maturities | G13: =G11+G12 -> 0 | H13: =H11+H12 -> -121.35573 | I13: =I11+I12 -> -236.70218 | J13: =J11+J12 -> -337.79889 | K13: =K11+K12 -> -426.18408
A14: Less: repayment of maturing debt | G14: ='Debt Schedule'!G25+'Debt Schedule'!G38+'Debt Schedule'!G51+'Debt Schedule'!G64 -> 0 | H14: ='Debt Schedule'!H25+'Debt Schedule'!H38+'Debt Schedule'!H51+'Debt Schedule'!H64 -> 0 | I14: ='Debt Schedule'!I25+'Debt Schedule'!I38+'Debt Schedule'!I51+'Debt Schedule'!I64 -> 0 | J14: ='Debt Schedule'!J25+'Debt Schedule'!J38+'Debt Schedule'!J51+'Debt Schedule'!J64 -> 0 | K14: ='Debt Schedule'!K25+'Debt Schedule'!K38+'Debt Schedule'!K51+'Debt Schedule'!K64 -> 0
A15: Cash before sweep | G15: =G13-G14 -> 0 | H15: =H13-H14 -> -121.35573 | I15: =I13-I14 -> -236.70218 | J15: =J13-J14 -> -337.79889 | K15: =K13-K14 -> -426.18408
A16: Funding gap (shortfall after cash & revolver) | G16: =MAX(0,-G15) -> 0 | H16: =MAX(0,-H15) -> 121.35573 | I16: =MAX(0,-I15) -> 236.70218 | J16: =MAX(0,-J15) -> 337.79889 | K16: =MAX(0,-K15) -> 426.18408
A17: Excess cash available for sweep | G17: =MAX(0,G15-Assumptions!$C$12)*Assumptions!$C$13 -> 0 | H17: =MAX(0,H15-Assumptions!$C$12)*Assumptions!$C$13 -> 0 | I17: =MAX(0,I15-Assumptions!$C$12)*Assumptions!$C$13 -> 0 | J17: =MAX(0,J15-Assumptions!$C$12)*Assumptions!$C$13 -> 0 | K17: =MAX(0,K15-Assumptions!$C$12)*Assumptions!$C$13 -> 0
A18: Less: optional repayment (cash sweep) | G18: ='Debt Schedule'!G26+'Debt Schedule'!G39+'Debt Schedule'!G52+'Debt Schedule'!G65 -> 0 | H18: ='Debt Schedule'!H26+'Debt Schedule'!H39+'Debt Schedule'!H52+'Debt Schedule'!H65 -> 0 | I18: ='Debt Schedule'!I26+'Debt Schedule'!I39+'Debt Schedule'!I52+'Debt Schedule'!I65 -> 0 | J18: ='Debt Schedule'!J26+'Debt Schedule'!J39+'Debt Schedule'!J52+'Debt Schedule'!J65 -> 0 | K18: ='Debt Schedule'!K26+'Debt Schedule'!K39+'Debt Schedule'!K52+'Debt Schedule'!K65 -> 0
A19: Ending cash | F19: =Assumptions!$C$11 -> 45 | G19: =G15-G18 -> 0 | H19: =H15-H18 -> -121.35573 | I19: =I15-I18 -> -236.70218 | J19: =J15-J18 -> -337.79889 | K19: =K15-K18 -> -426.18408
A20: Unpaid maturities (balance left outstanding) | G20: ='Debt Schedule'!G27+'Debt Schedule'!G40+'Debt Schedule'!G53+'Debt Schedule'!G66 -> 0 | H20: ='Debt Schedule'!H27+'Debt Schedule'!H40+'Debt Schedule'!H53+'Debt Schedule'!H66 -> 516.2968 | I20: ='Debt Schedule'!I27+'Debt Schedule'!I40+'Debt Schedule'!I53+'Debt Schedule'!I66 -> 504.4 | J20: ='Debt Schedule'!J27+'Debt Schedule'!J40+'Debt Schedule'!J53+'Debt Schedule'!J66 -> 250 | K20: ='Debt Schedule'!K27+'Debt Schedule'!K40+'Debt Schedule'!K53+'Debt Schedule'!K66 -> 0
A21: Payment default? (1 = yes) | G21: =IF(OR(G16>0.001,G20>0.001),1,0) -> 0 | H21: =IF(OR(H16>0.001,H20>0.001),1,0) -> 1 | I21: =IF(OR(I16>0.001,I20>0.001),1,0) -> 1 | J21: =IF(OR(J16>0.001,J20>0.001),1,0) -> 1 | K21: =IF(OR(K16>0.001,K20>0.001),1,0) -> 1
A22: First default period flag | G22: =IF(G21=1,1,0) -> 0 | H22: =IF(AND(H21=1,SUM($G$21:G21)=0),1,0) -> 1 | I22: =IF(AND(I21=1,SUM($G$21:H21)=0),1,0) -> 0 | J22: =IF(AND(J21=1,SUM($G$21:I21)=0),1,0) -> 0 | K22: =IF(AND(K21=1,SUM($G$21:J21)=0),1,0) -> 0
A23: Check: Δ debt = draws + PIK − repayments | G23: =('Debt Schedule'!G69-'Debt Schedule'!F69)-(G12+'Operating Model'!G22-G10-G14-G18) -> 0 | H23: =('Debt Schedule'!H69-'Debt Schedule'!G69)-(H12+'Operating Model'!H22-H10-H14-H18) -> -4.5297099e-14 | I23: =('Debt Schedule'!I69-'Debt Schedule'!H69)-(I12+'Operating Model'!I22-I10-I14-I18) -> 1.8207658e-13 | J23: =('Debt Schedule'!J69-'Debt Schedule'!I69)-(J12+'Operating Model'!J22-J10-J14-J18) -> -2.7267077e-13 | K23: =('Debt Schedule'!K69-'Debt Schedule'!J69)-(K12+'Operating Model'!K22-K10-K14-K18) -> 1.8207658e-13

Sheet Credit Metrics
A1: Credit Metrics, Covenants & Credit Score
A2: ="Brightwater Retail Holdings · DEMO DATA · DEMO INVESTMENT TERMS · Active scenario: "&Assumptions!$D$10 -> Brightwater Retail Holdings · DEMO DATA · DEMO INVESTMENT TERMS · Active scenario: Downside
A4: $M | C4: FY2022A | D4: FY2023A | E4: FY2024A | F4: FY2025A | G4: FY2026E | H4: FY2027E | I4: FY2028E | J4: FY2029E | K4: FY2030E
A6: Credit metrics (selected scenario)
A7: Total debt (face value) | F7: ='Debt Schedule'!F69 -> 1250 | G7: ='Debt Schedule'!G69 -> 1281.0968 | H7: ='Debt Schedule'!H69 -> 1275.8968 | I7: ='Debt Schedule'!I69 -> 1270.6968 | J7: ='Debt Schedule'!J69 -> 1265.4968 | K7: ='Debt Schedule'!K69 -> 1260.2968
A8: Secured debt | F8: =Assumptions!$O$53*'Debt Schedule'!F28+Assumptions!$O$54*'Debt Schedule'!F41+Assumptions!$O$55*'Debt Schedule'!F54+Assumptions!$O$56*'Debt Schedule'!F67 -> 950 | G8: =Assumptions!$O$53*'Debt Schedule'!G28+Assumptions!$O$54*'Debt Schedule'!G41+Assumptions!$O$55*'Debt Schedule'!G54+Assumptions!$O$56*'Debt Schedule'!G67 -> 981.0968 | H8: =Assumptions!$O$53*'Debt Schedule'!H28+Assumptions!$O$54*'Debt Schedule'!H41+Assumptions!$O$55*'Debt Schedule'!H54+Assumptions!$O$56*'Debt Schedule'!H67 -> 975.8968 | I8: =Assumptions!$O$53*'Debt Schedule'!I28+Assumptions!$O$54*'Debt Schedule'!I41+Assumptions!$O$55*'Debt Schedule'!I54+Assumptions!$O$56*'Debt Schedule'!I67 -> 970.6968 | J8: =Assumptions!$O$53*'Debt Schedule'!J28+Assumptions!$O$54*'Debt Schedule'!J41+Assumptions!$O$55*'Debt Schedule'!J54+Assumptions!$O$56*'Debt Schedule'!J67 -> 965.4968 | K8: =Assumptions!$O$53*'Debt Schedule'!K28+Assumptions!$O$54*'Debt Schedule'!K41+Assumptions!$O$55*'Debt Schedule'!K54+Assumptions!$O$56*'Debt Schedule'!K67 -> 960.2968
A9: Net debt | F9: =F7-'Cash Flow'!F19 -> 1205 | G9: =G7-'Cash Flow'!G19 -> 1281.0968 | H9: =H7-'Cash Flow'!H19 -> 1397.2525 | I9: =I7-'Cash Flow'!I19 -> 1507.399 | J9: =J7-'Cash Flow'!J19 -> 1603.2957 | K9: =K7-'Cash Flow'!K19 -> 1686.4809
A10: Gross debt / EBITDA | F10: =IF('Operating Model'!F17>0,F7/'Operating Model'!F17,0) -> 8.0128205 | G10: =IF('Operating Model'!G17>0,G7/'Operating Model'!G17,0) -> 16.54138 | H10: =IF('Operating Model'!H17>0,H7/'Operating Model'!H17,0) -> 26.086881 | I10: =IF('Operating Model'!I17>0,I7/'Operating Model'!I17,0) -> 20.708818 | J10: =IF('Operating Model'!J17>0,J7/'Operating Model'!J17,0) -> 17.261128 | K10: =IF('Operating Model'!K17>0,K7/'Operating Model'!K17,0) -> 14.82279
A11: Net debt / EBITDA | F11: =IF('Operating Model'!F17>0,F9/'Operating Model'!F17,0) -> 7.724359 | G11: =IF('Operating Model'!G17>0,G9/'Operating Model'!G17,0) -> 16.54138 | H11: =IF('Operating Model'!H17>0,H9/'Operating Model'!H17,0) -> 28.568111 | I11: =IF('Operating Model'!I17>0,I9/'Operating Model'!I17,0) -> 24.566404 | J11: =IF('Operating Model'!J17>0,J9/'Operating Model'!J17,0) -> 21.868639 | K11: =IF('Operating Model'!K17>0,K9/'Operating Model'!K17,0) -> 19.83529
A12: Interest coverage (EBITDA / cash interest) | F12: =IF('Operating Model'!F23>0,'Operating Model'!F17/'Operating Model'!F23,0) -> 1.3104839 | G12: =IF('Operating Model'!G21>0,'Operating Model'!G17/'Operating Model'!G21,0) -> 0.59786938 | H12: =IF('Operating Model'!H21>0,'Operating Model'!H17/'Operating Model'!H21,0) -> 0.37402711 | I12: =IF('Operating Model'!I21>0,'Operating Model'!I17/'Operating Model'!I21,0) -> 0.47807182 | J12: =IF('Operating Model'!J21>0,'Operating Model'!J17/'Operating Model'!J21,0) -> 0.57384052 | K12: =IF('Operating Model'!K21>0,'Operating Model'!K17/'Operating Model'!K21,0) -> 0.66856591
A13: EBIT / interest | F13: =IF('Operating Model'!F23>0,'Operating Model'!F20/'Operating Model'!F23,0) -> 0.86693548 | G13: =IF('Operating Model'!G21>0,'Operating Model'!G20/'Operating Model'!G21,0) -> 0.22206577 | H13: =IF('Operating Model'!H21>0,'Operating Model'!H20/'Operating Model'!H21,0) -> 0.016262048 | I13: =IF('Operating Model'!I21>0,'Operating Model'!I20/'Operating Model'!I21,0) -> 0.11539665 | J13: =IF('Operating Model'!J21>0,'Operating Model'!J20/'Operating Model'!J21,0) -> 0.21314077 | K13: =IF('Operating Model'!K21>0,'Operating Model'!K20/'Operating Model'!K21,0) -> 0.30982323
A14: FCF / debt | F14: =IF(F7>0,'Operating Model'!F30/F7,0) -> -0.002112 | G14: =IF(G7>0,'Operating Model'!G30/G7,0) -> -0.059399727 | H14: =IF(H7>0,'Operating Model'!H30/H7,0) -> -0.091038499 | I14: =IF(I7>0,'Operating Model'!I30/I7,0) -> -0.086681926 | J14: =IF(J7>0,'Operating Model'!J30/J7,0) -> -0.075777921 | K14: =IF(K7>0,'Operating Model'!K30/K7,0) -> -0.066004445
A15: Debt service coverage ((EBITDA − capex − tax) / (cash interest + amortization)) | G15: =IF('Operating Model'!G21+'Cash Flow'!G10>0,('Operating Model'!G17-'Operating Model'!G28-'Operating Model'!G25)/('Operating Model'!G21+'Cash Flow'!G10),0) -> 0.26276384 | H15: =IF('Operating Model'!H21+'Cash Flow'!H10>0,('Operating Model'!H17-'Operating Model'!H28-'Operating Model'!H25)/('Operating Model'!H21+'Cash Flow'!H10),0) -> 0.062560409 | I15: =IF('Operating Model'!I21+'Cash Flow'!I10>0,('Operating Model'!I17-'Operating Model'!I28-'Operating Model'!I25)/('Operating Model'!I21+'Cash Flow'!I10),0) -> 0.15843351 | J15: =IF('Operating Model'!J21+'Cash Flow'!J10>0,('Operating Model'!J17-'Operating Model'!J28-'Operating Model'!J25)/('Operating Model'!J21+'Cash Flow'!J10),0) -> 0.25206774 | K15: =IF('Operating Model'!K21+'Cash Flow'!K10>0,('Operating Model'!K17-'Operating Model'!K28-'Operating Model'!K25)/('Operating Model'!K21+'Cash Flow'!K10),0) -> 0.34465033
A16: Liquidity (cash + undrawn revolver) | F16: =MAX(0,'Cash Flow'!F19)+Assumptions!$P$53*MAX(0,Assumptions!$D$53-'Debt Schedule'!F28)+Assumptions!$P$54*MAX(0,Assumptions!$D$54-'Debt Schedule'!F41)+Assumptions!$P$55*MAX(0,Assumptions!$D$55-'Debt Schedule'!F54)+Assumptions!$P$56*MAX(0,Assumptions!$D$56-'Debt Schedule'!F67) -> 165 | G16: =MAX(0,'Cash Flow'!G19)+Assumptions!$P$53*MAX(0,Assumptions!$D$53-'Debt Schedule'!G28)+Assumptions!$P$54*MAX(0,Assumptions!$D$54-'Debt Schedule'!G41)+Assumptions!$P$55*MAX(0,Assumptions!$D$55-'Debt Schedule'!G54)+Assumptions!$P$56*MAX(0,Assumptions!$D$56-'Debt Schedule'!G67) -> 83.7032 | H16: =MAX(0,'Cash Flow'!H19)+Assumptions!$P$53*MAX(0,Assumptions!$D$53-'Debt Schedule'!H28)+Assumptions!$P$54*MAX(0,Assumptions!$D$54-'Debt Schedule'!H41)+Assumptions!$P$55*MAX(0,Assumptions!$D$55-'Debt Schedule'!H54)+Assumptions!$P$56*MAX(0,Assumptions!$D$56-'Debt Schedule'!H67) -> 83.7032 | I16: =MAX(0,'Cash Flow'!I19)+Assumptions!$P$53*MAX(0,Assumptions!$D$53-'Debt Schedule'!I28)+Assumptions!$P$54*MAX(0,Assumptions!$D$54-'Debt Schedule'!I41)+Assumptions!$P$55*MAX(0,Assumptions!$D$55-'Debt Schedule'!I54)+Assumptions!$P$56*MAX(0,Assumptions!$D$56-'Debt Schedule'!I67) -> 83.7032 | J16: =MAX(0,'Cash Flow'!J19)+Assumptions!$P$53*MAX(0,Assumptions!$D$53-'Debt Schedule'!J28)+Assumptions!$P$54*MAX(0,Assumptions!$D$54-'Debt Schedule'!J41)+Assumptions!$P$55*MAX(0,Assumptions!$D$55-'Debt Schedule'!J54)+Assumptions!$P$56*MAX(0,Assumptions!$D$56-'Debt Schedule'!J67) -> 83.7032 | K16: =MAX(0,'Cash Flow'!K19)+Assumptions!$P$53*MAX(0,Assumptions!$D$53-'Debt Schedule'!K28)+Assumptions!$P$54*MAX(0,Assumptions!$D$54-'Debt Schedule'!K41)+Assumptions!$P$55*MAX(0,Assumptions!$D$55-'Debt Schedule'!K54)+Assumptions!$P$56*MAX(0,Assumptions!$D$56-'Debt Schedule'!K67) -> 83.7032
A17: Debt / capital (debt + implied equity) | G17: =IF(G7>0,G7/(G7+MAX(0,'Operating Model'!G17*CHOOSE(Assumptions!$C$10,Assumptions!$C$76,Assumptions!$C$95,Assumptions!$C$114)-G9)),0) -> 1 | H17: =IF(H7>0,H7/(H7+MAX(0,'Operating Model'!H17*CHOOSE(Assumptions!$C$10,Assumptions!$C$76,Assumptions!$C$95,Assumptions!$C$114)-H9)),0) -> 1 | I17: =IF(I7>0,I7/(I7+MAX(0,'Operating Model'!I17*CHOOSE(Assumptions!$C$10,Assumptions!$C$76,Assumptions!$C$95,Assumptions!$C$114)-I9)),0) -> 1 | J17: =IF(J7>0,J7/(J7+MAX(0,'Operating Model'!J17*CHOOSE(Assumptions!$C$10,Assumptions!$C$76,Assumptions!$C$95,Assumptions!$C$114)-J9)),0) -> 1 | K17: =IF(K7>0,K7/(K7+MAX(0,'Operating Model'!K17*CHOOSE(Assumptions!$C$10,Assumptions!$C$76,Assumptions!$C$95,Assumptions!$C$114)-K9)),0) -> 1
A18: Cash / debt | F18: =IF(F7>0,MAX(0,'Cash Flow'!F19)/F7,0) -> 0.036 | G18: =IF(G7>0,MAX(0,'Cash Flow'!G19)/G7,0) -> 0 | H18: =IF(H7>0,MAX(0,'Cash Flow'!H19)/H7,0) -> 0 | I18: =IF(I7>0,MAX(0,'Cash Flow'!I19)/I7,0) -> 0 | J18: =IF(J7>0,MAX(0,'Cash Flow'!J19)/J7,0) -> 0 | K18: =IF(K7>0,MAX(0,'Cash Flow'!K19)/K7,0) -> 0
A19: Asset value after scenario decline | G19: =Assumptions!$C$27*(1-CHOOSE(Assumptions!$C$10,Assumptions!$C$79,Assumptions!$C$98,Assumptions!$C$117)) -> 884 | H19: =Assumptions!$C$27*(1-CHOOSE(Assumptions!$C$10,Assumptions!$C$79,Assumptions!$C$98,Assumptions!$C$117)) -> 884 | I19: =Assumptions!$C$27*(1-CHOOSE(Assumptions!$C$10,Assumptions!$C$79,Assumptions!$C$98,Assumptions!$C$117)) -> 884 | J19: =Assumptions!$C$27*(1-CHOOSE(Assumptions!$C$10,Assumptions!$C$79,Assumptions!$C$98,Assumptions!$C$117)) -> 884 | K19: =Assumptions!$C$27*(1-CHOOSE(Assumptions!$C$10,Assumptions!$C$79,Assumptions!$C$98,Assumptions!$C$117)) -> 884
A20: Covenant compliance (active covenants; tests use model-basis metrics)
A21: Maximum net leverage [HYPOTHETICAL]
A22: Metric | G22: =IF('Operating Model'!G17>0,G9/'Operating Model'!G17,99) -> 16.54138 | H22: =IF('Operating Model'!H17>0,H9/'Operating Model'!H17,99) -> 28.568111 | I22: =IF('Operating Model'!I17>0,I9/'Operating Model'!I17,99) -> 24.566404 | J22: =IF('Operating Model'!J17>0,J9/'Operating Model'!J17,99) -> 21.868639 | K22: =IF('Operating Model'!K17>0,K9/'Operating Model'!K17,99) -> 19.83529
A23: Covenant threshold | G23: =Assumptions!$G$61 -> 8.5 | H23: =Assumptions!$H$61 -> 8.5 | I23: =Assumptions!$I$61 -> 8.5 | J23: =Assumptions!$J$61 -> 8.5 | K23: =Assumptions!$K$61 -> 8.5
A24: Headroom | G24: =G23-G22 -> -8.04138 | H24: =H23-H22 -> -20.068111 | I24: =I23-I22 -> -16.066404 | J24: =J23-J22 -> -13.368639 | K24: =K23-K22 -> -11.33529
A25: Headroom % of threshold | G25: =IF(G23=0,0,G24/ABS(G23)) -> -0.94604471 | H25: =IF(H23=0,0,H24/ABS(H23)) -> -2.3609542 | I25: =IF(I23=0,0,I24/ABS(I23)) -> -1.8901652 | J25: =IF(J23=0,0,J24/ABS(J23)) -> -1.5727811 | K25: =IF(K23=0,0,K24/ABS(K23)) -> -1.3335635
A26: BREACH? (1 = yes) | G26: =IF(G24<0,1,0) -> 1 | H26: =IF(H24<0,1,0) -> 1 | I26: =IF(I24<0,1,0) -> 1 | J26: =IF(J24<0,1,0) -> 1 | K26: =IF(K24<0,1,0) -> 1
A27: First breach period (0 = none) | C27: =IFERROR(INDEX('Operating Model'!$G$7:$K$7,MATCH(1,$G$26:$K$26,0)),0) -> 2026
A28: Minimum headroom % | C28: =MIN($G$25:$K$25) -> -2.3609542
A29: Covenant breaches (count, all active covenants) | G29: =G26 -> 1 | H29: =H26 -> 1 | I29: =I26 -> 1 | J29: =J26 -> 1 | K29: =K26 -> 1
A30: Total breaches across projection | C30: =SUM($G$29:$K$29) -> 5
A31: Minimum covenant headroom % (all active covenants) | C31: =MIN(C28) -> -2.3609542
A34: Credit score — transparent, formula-driven (base period; weights & thresholds on Assumptions §8)
A35: Factor | C35: Value | D35: Best | E35: Worst | F35: Weight | G35: Points | H35: Score % | I35: Projected value (period 1, selected scenario) | J35: Projected points
A36: Net leverage (net debt / EBITDA) | C36: ='Credit Metrics'!F11 -> 7.724359 | D36: =Assumptions!$D$125 -> 2 | E36: =Assumptions!$E$125 -> 7 | F36: =Assumptions!$C$125 -> 15 | G36: =F36*H36 -> 0 | H36: =MAX(0,MIN(1,(C36-E36)/(D36-E36))) -> 0 | I36: ='Credit Metrics'!G11 -> 16.54138 | J36: =F36*MAX(0,MIN(1,(I36-E36)/(D36-E36))) -> 0
A37: Interest coverage (EBITDA / interest) | C37: ='Credit Metrics'!F12 -> 1.3104839 | D37: =Assumptions!$D$126 -> 5 | E37: =Assumptions!$E$126 -> 1 | F37: =Assumptions!$C$126 -> 15 | G37: =F37*H37 -> 1.1643145 | H37: =MAX(0,MIN(1,(C37-E37)/(D37-E37))) -> 0.077620968 | I37: ='Credit Metrics'!G12 -> 0.59786938 | J37: =F37*MAX(0,MIN(1,(I37-E37)/(D37-E37))) -> 0
A38: Liquidity ratio (liquidity / next-period obligations) | C38: ='Credit Metrics'!F16/(SUMPRODUCT((Assumptions!$K$53:$K$56<=Assumptions!$C$6+1)*Assumptions!$C$53:$C$56)+SUMPRODUCT(Assumptions!$L$53:$L$56*Assumptions!$C$53:$C$56)+'Operating Model'!F23) -> 1.3280747 | D38: =Assumptions!$D$127 -> 2 | E38: =Assumptions!$E$127 -> 0.5 | F38: =Assumptions!$C$127 -> 10 | G38: =F38*H38 -> 5.520498 | H38: =MAX(0,MIN(1,(C38-E38)/(D38-E38))) -> 0.5520498 | I38: ='Credit Metrics'!G16/(SUMPRODUCT((Assumptions!$K$53:$K$56<=Assumptions!$C$6+1)*Assumptions!$C$53:$C$56)+SUMPRODUCT(Assumptions!$L$53:$L$56*Assumptions!$C$53:$C$56)+'Operating Model'!F23) -> 0.67372183 | J38: =F38*MAX(0,MIN(1,(I38-E38)/(D38-E38))) -> 1.1581455
A39: FCF / total debt | C39: ='Credit Metrics'!F14 -> -0.002112 | D39: =Assumptions!$D$128 -> 0.12 | E39: =Assumptions!$E$128 -> -0.02 | F39: =Assumptions!$C$128 -> 10 | G39: =F39*H39 -> 1.2777143 | H39: =MAX(0,MIN(1,(C39-E39)/(D39-E39))) -> 0.12777143 | I39: ='Credit Metrics'!G14 -> -0.059399727 | J39: =F39*MAX(0,MIN(1,(I39-E39)/(D39-E39))) -> 0
A40: Share of debt maturing within window | C40: =SUMPRODUCT((Assumptions!$K$53:$K$56<=Assumptions!$C$6+Assumptions!$C$22)*Assumptions!$C$53:$C$56)/SUM(Assumptions!$C$53:$C$56) -> 0.8 | D40: =Assumptions!$D$129 -> 0 | E40: =Assumptions!$E$129 -> 0.5 | F40: =Assumptions!$C$129 -> 10 | G40: =F40*H40 -> 0 | H40: =MAX(0,MIN(1,(C40-E40)/(D40-E40))) -> 0 | I40: =C40 -> 0.8 | J40: =F40*MAX(0,MIN(1,(I40-E40)/(D40-E40))) -> 0
A41: Margin stability (σ of annual EBITDA margin) | C41: =STDEVP('Historical Financials'!B35:E35) -> 0.0076321688 | D41: =Assumptions!$D$130 -> 0.01 | E41: =Assumptions!$E$130 -> 0.05 | F41: =Assumptions!$C$130 -> 10 | G41: =F41*H41 -> 10 | H41: =MAX(0,MIN(1,(C41-E41)/(D41-E41))) -> 1 | I41: =C41 -> 0.0076321688 | J41: =F41*MAX(0,MIN(1,(I41-E41)/(D41-E41))) -> 10
A42: Revenue stability (σ of annual growth) | C42: =STDEVP('Historical Financials'!C36:E36) -> 0.0029719935 | D42: =Assumptions!$D$131 -> 0.03 | E42: =Assumptions!$E$131 -> 0.15 | F42: =Assumptions!$C$131 -> 8 | G42: =F42*H42 -> 8 | H42: =MAX(0,MIN(1,(C42-E42)/(D42-E42))) -> 1 | I42: =C42 -> 0.0029719935 | J42: =F42*MAX(0,MIN(1,(I42-E42)/(D42-E42))) -> 8
A43: Asset coverage (asset base / debt) | C43: =Assumptions!$C$27/'Credit Metrics'!F7 -> 0.832 | D43: =Assumptions!$D$132 -> 2 | E43: =Assumptions!$E$132 -> 0.6 | F43: =Assumptions!$C$132 -> 12 | G43: =F43*H43 -> 1.9885714 | H43: =MAX(0,MIN(1,(C43-E43)/(D43-E43))) -> 0.16571429 | I43: =C43 -> 0.832 | J43: =F43*MAX(0,MIN(1,(I43-E43)/(D43-E43))) -> 1.9885714
A44: Industry risk factor (analyst input, 0-1) | C44: =Assumptions!$C$134 -> 0.25 | D44: =Assumptions!$D$133 -> 1 | E44: =Assumptions!$E$133 -> 0 | F44: =Assumptions!$C$133 -> 10 | G44: =F44*H44 -> 2.5 | H44: =MAX(0,MIN(1,(C44-E44)/(D44-E44))) -> 0.25 | I44: =C44 -> 0.25 | J44: =F44*MAX(0,MIN(1,(I44-E44)/(D44-E44))) -> 2.5
A45: Credit score (0-100) | F45: =SUM(F36:F44) -> 100 | G45: =SUM(G36:G44) -> 30.451098 | J45: =SUM(J36:J44) -> 23.646717
A46: Risk band | G46: =IF(G45>=Assumptions!$C$138,"Low",IF(G45>=Assumptions!$C$139,"Moderate",IF(G45>=Assumptions!$C$140,"Elevated","High"))) -> High
A47: Each factor earns its weight linearly between the 'worst' threshold (0 pts) and the 'best' threshold (full pts).

Sheet Scenarios
A1: Scenarios — side-by-side (all three run simultaneously on Calc Engine)
A2: ="Active scenario for the detailed tabs: "&Assumptions!$D$10 -> Active scenario for the detailed tabs: Downside
A4: Assumptions (links to Assumptions tab) | C4: Base Case | D4: Downside | E4: Severe Downside | F4: Selected
A5: Average revenue growth (5 periods) | C5: =AVERAGE(Assumptions!$G$65:$K$65) -> -0.01 | D5: =AVERAGE(Assumptions!$G$84:$K$84) -> -0.0284 | E5: =AVERAGE(Assumptions!$G$103:$K$103) -> -0.082 | F5: =CHOOSE(Assumptions!$C$10,C5,D5,E5) -> -0.0284
A6: Average EBITDA margin (5 periods) | C6: =AVERAGE(Assumptions!$G$67:$K$67) -> 0.069 | D6: =AVERAGE(Assumptions!$G$86:$K$86) -> 0.0326 | E6: =AVERAGE(Assumptions!$G$105:$K$105) -> 0.01 | F6: =CHOOSE(Assumptions!$C$10,C6,D6,E6) -> 0.0326
A7: Floating-rate shock | C7: =Assumptions!$C$72 -> 0 | D7: =Assumptions!$C$91 -> 0.015 | E7: =Assumptions!$C$110 -> 0.03 | F7: =CHOOSE(Assumptions!$C$10,C7,D7,E7) -> 0.015
A8: Refinancing rate | C8: =Assumptions!$C$73 -> 0.11 | D8: =Assumptions!$C$92 -> 0.135 | E8: =Assumptions!$C$111 -> 0.16 | F8: =CHOOSE(Assumptions!$C$10,C8,D8,E8) -> 0.135
A9: Market access: max net leverage / min coverage | C9: =TEXT(Assumptions!$C$74,"0.0")&"x / "&TEXT(Assumptions!$C$75,"0.00")&"x" -> 8.5x / 1.20x | D9: =TEXT(Assumptions!$C$93,"0.0")&"x / "&TEXT(Assumptions!$C$94,"0.00")&"x" -> 5.5x / 1.80x | E9: =TEXT(Assumptions!$C$112,"0.0")&"x / "&TEXT(Assumptions!$C$113,"0.00")&"x" -> 5.0x / 2.00x | F9: =CHOOSE(Assumptions!$C$10,C9,D9,E9) -> 5.5x / 1.80x
A10: Exit multiple / distressed multiple | C10: =TEXT(Assumptions!$C$76,"0.0")&"x / "&TEXT(Assumptions!$C$78,"0.0")&"x" -> 6.5x / 4.0x | D10: =TEXT(Assumptions!$C$95,"0.0")&"x / "&TEXT(Assumptions!$C$97,"0.0")&"x" -> 5.0x / 4.0x | E10: =TEXT(Assumptions!$C$114,"0.0")&"x / "&TEXT(Assumptions!$C$116,"0.0")&"x" -> 3.5x / 4.0x | F10: =CHOOSE(Assumptions!$C$10,C10,D10,E10) -> 5.0x / 4.0x
A11: Asset value decline | C11: =Assumptions!$C$79 -> 0 | D11: =Assumptions!$C$98 -> 0.15 | E11: =Assumptions!$C$117 -> 0.35 | F11: =CHOOSE(Assumptions!$C$10,C11,D11,E11) -> 0.15
A12: Scenario probability | C12: =Assumptions!$C$81 -> 0.55 | D12: =Assumptions!$C$100 -> 0.3 | E12: =Assumptions!$C$119 -> 0.15 | F12: =CHOOSE(Assumptions!$C$10,C12,D12,E12) -> 0.3
A14: Outputs (from Calc Engine) | C14: Base Case | D14: Downside | E14: Severe Downside | F14: Selected
A15: FY2030E revenue ($M) | C15: ='Calc Engine'!K19 -> 2282.3761 | D15: ='Calc Engine'!K372 -> 2073.7625 | E15: ='Calc Engine'!K725 -> 1526.8227 | F15: =CHOOSE(Assumptions!$C$10,C15,D15,E15) -> 2073.7625
A16: Trough EBITDA ($M) | C16: =MIN('Calc Engine'!$G$23:$K$23) -> 154.44 | D16: =MIN('Calc Engine'!$G$376:$K$376) -> 48.909518 | E16: =MIN('Calc Engine'!$G$729:$K$729) -> 15.268227 | F16: =CHOOSE(Assumptions!$C$10,C16,D16,E16) -> 48.909518
A17: Cumulative FCF, 5 periods ($M) | C17: ='Calc Engine'!C354 -> -46.975945 | D17: ='Calc Engine'!C707 -> -481.48088 | E17: ='Calc Engine'!C1060 -> -697.7929 | F17: =CHOOSE(Assumptions!$C$10,C17,D17,E17) -> -481.48088
A18: Peak net debt / EBITDA | C18: ='Calc Engine'!C352 -> 7.8622119 | D18: ='Calc Engine'!C705 -> 28.568111 | E18: ='Calc Engine'!C1058 -> 124.62435 | F18: =CHOOSE(Assumptions!$C$10,C18,D18,E18) -> 28.568111
A19: Minimum EBITDA / cash interest | C19: ='Calc Engine'!C353 -> 1.2147366 | D19: ='Calc Engine'!C706 -> 0.37402711 | E19: ='Calc Engine'!C1059 -> 0.10908021 | F19: =CHOOSE(Assumptions!$C$10,C19,D19,E19) -> 0.37402711
A20: Covenant breaches (count of tests failed) | C20: ='Calc Engine'!C165 -> 0 | D20: ='Calc Engine'!C518 -> 5 | E20: ='Calc Engine'!C871 -> 5 | F20: =CHOOSE(Assumptions!$C$10,C20,D20,E20) -> 5
A21: Refinancing failures (maturing tranches) | C21: ='Calc Engine'!C120 -> 0 | D21: ='Calc Engine'!C473 -> 4 | E21: ='Calc Engine'!C826 -> 4 | F21: =CHOOSE(Assumptions!$C$10,C21,D21,E21) -> 4
A22: Payment default modelled? (1 = yes) | C22: ='Calc Engine'!C170 -> 1 | D22: ='Calc Engine'!C523 -> 1 | E22: ='Calc Engine'!C876 -> 1 | F22: =CHOOSE(Assumptions!$C$10,C22,D22,E22) -> 1
A23: Valuation period (default or trough) | C23: ='Calc Engine'!C171 -> 2027 | D23: ='Calc Engine'!C524 -> 2027 | E23: ='Calc Engine'!C877 -> 2027 | F23: =CHOOSE(Assumptions!$C$10,C23,D23,E23) -> 2027
A24: Recovery value used ($M) | C24: ='Calc Engine'!C177 -> 630.40032 | D24: ='Calc Engine'!C530 -> 530.4 | E24: ='Calc Engine'!C883 -> 405.6 | F24: =CHOOSE(Assumptions!$C$10,C24,D24,E24) -> 530.4
A25: Target-tranche recovery % (valuation waterfall) | C25: ='Calc Engine'!C262 -> 0.86642715 | D25: ='Calc Engine'!C615 -> 0.54845094 | E25: ='Calc Engine'!C968 -> 0.28087124 | F25: =CHOOSE(Assumptions!$C$10,C25,D25,E25) -> 0.54845094
A26: Exit price used (% of face) | C26: ='Calc Engine'!C337 -> 100 | D26: ='Calc Engine'!C690 -> 5.543719 | E26: ='Calc Engine'!C1043 -> 0 | F26: =CHOOSE(Assumptions!$C$10,C26,D26,E26) -> 5.543719
A27: IRR | C27: ='Calc Engine'!C351 -> 0.13082152 | D27: ='Calc Engine'!C704 -> 0.0068898968 | E27: ='Calc Engine'!C1057 -> -0.13853405 | F27: =CHOOSE(Assumptions!$C$10,C27,D27,E27) -> 0.0068898968
A28: MOIC | C28: ='Calc Engine'!C350 -> 1.3926472 | D28: ='Calc Engine'!C703 -> 1.0177159 | E28: ='Calc Engine'!C1056 -> 0.70612917 | F28: =CHOOSE(Assumptions!$C$10,C28,D28,E28) -> 1.0177159
A29: Absolute profit ($M) | C29: ='Calc Engine'!C349 -> 30.779613 | D29: ='Calc Engine'!C702 -> 1.3887463 | E29: ='Calc Engine'!C1055 -> -23.036534 | F29: =CHOOSE(Assumptions!$C$10,C29,D29,E29) -> 1.3887463
A31: Probability-weighted IRR (IRR of expected cash flows) | C31: =IF(SUM(D38:I38)<=0,-1,IFERROR(IRR(C38:I38,MAX(-0.9,(SUM(D38:I38)/-C38)^(1/(COLUMNS(C38:I38)-1))-1)),IRR(C38:I38,0.1))) -> 0.064153443
A32: Memo: probability-weighted AVERAGE of scenario IRRs (IRR is non-linear, so this is not an IRR) | C32: =SUMPRODUCT(C12:E12,C27:E27) -> 0.0532387
A33: Probability-weighted MOIC | C33: =SUMPRODUCT(C12:E12,C28:E28) -> 1.1771901
A34: Probability of payment default | C34: =SUMPRODUCT(C12:E12,C22:E22) -> 1
A36: Expected (probability-weighted) position cash flows by period — basis of the probability-weighted IRR
C37: t=0 | D37: t=1 | E37: t=2 | F37: t=3 | G37: t=4 | H37: t=5 | I37: t=6
A38: Expected net cash flow ($M) | C38: =C$12*'Calc Engine'!C344+D$12*'Calc Engine'!C697+E$12*'Calc Engine'!C1050 -> -78.39 | D38: =C$12*'Calc Engine'!D344+D$12*'Calc Engine'!D697+E$12*'Calc Engine'!D1050 -> 11.2 | E38: =C$12*'Calc Engine'!E344+D$12*'Calc Engine'!E697+E$12*'Calc Engine'!E1050 -> 10.95 | F38: =C$12*'Calc Engine'!F344+D$12*'Calc Engine'!F697+E$12*'Calc Engine'!F1050 -> 70.129931 | G38: =C$12*'Calc Engine'!G344+D$12*'Calc Engine'!G697+E$12*'Calc Engine'!G1050 -> 0 | H38: =C$12*'Calc Engine'!H344+D$12*'Calc Engine'!H697+E$12*'Calc Engine'!H1050 -> 0 | I38: =C$12*'Calc Engine'!I344+D$12*'Calc Engine'!I697+E$12*'Calc Engine'!I1050 -> 0
A40: Reconciliation: detailed tabs vs Calc Engine (selected scenario) | C40: Detailed | D40: Calc Engine | E40: Difference
A41: FY2030E EBITDA | C41: ='Operating Model'!K17 -> 85.024263 | D41: =CHOOSE(Assumptions!$C$10,'Calc Engine'!K23,'Calc Engine'!K376,'Calc Engine'!K729) -> 85.024263 | E41: =C41-D41 -> 0
A42: FY2030E total debt | C42: ='Debt Schedule'!K69 -> 1260.2968 | D42: =CHOOSE(Assumptions!$C$10,'Calc Engine'!K101,'Calc Engine'!K454,'Calc Engine'!K807) -> 1260.2968 | E42: =C42-D42 -> 0
A43: FY2030E ending cash | C43: ='Cash Flow'!K19 -> -426.18408 | D43: =CHOOSE(Assumptions!$C$10,'Calc Engine'!K135,'Calc Engine'!K488,'Calc Engine'!K841) -> -426.18408 | E43: =C43-D43 -> 0
A44: Cumulative FCF | C44: =Returns!C107 -> -481.48088 | D44: =CHOOSE(Assumptions!$C$10,'Calc Engine'!C354,'Calc Engine'!C707,'Calc Engine'!C1060) -> -481.48088 | E44: =C44-D44 -> 0
A45: Recovery value used | C45: =Recovery!C15 -> 530.4 | D45: =CHOOSE(Assumptions!$C$10,'Calc Engine'!C177,'Calc Engine'!C530,'Calc Engine'!C883) -> 530.4 | E45: =C45-D45 -> 0
A46: Covenant breaches | C46: ='Credit Metrics'!C30 -> 5 | D46: =CHOOSE(Assumptions!$C$10,'Calc Engine'!C165,'Calc Engine'!C518,'Calc Engine'!C871) -> 5 | E46: =C46-D46 -> 0
A47: IRR | C47: =Returns!C104 -> 0.0068898968 | D47: =CHOOSE(Assumptions!$C$10,'Calc Engine'!C351,'Calc Engine'!C704,'Calc Engine'!C1057) -> 0.0068898968 | E47: =C47-D47 -> 0
A48: MOIC | C48: =Returns!C103 -> 1.0177159 | D48: =CHOOSE(Assumptions!$C$10,'Calc Engine'!C350,'Calc Engine'!C703,'Calc Engine'!C1056) -> 1.0177159 | E48: =C48-D48 -> 0

Sheet Capital Structure
A1: Capital Structure — tranches, leverage through the stack, maturity wall and refinancing requirement
A2: ="Brightwater Retail Holdings · DEMO DATA · DEMO INVESTMENT TERMS · as of "&TEXT(Assumptions!$C$8,"yyyy-mm-dd")&" · $M" -> Brightwater Retail Holdings · DEMO DATA · DEMO INVESTMENT TERMS · as of 2026-03-31 · $M
A4: Facility | B4: Type | C4: Rank | D4: Secured? | E4: Face value | F4: All-in rate | G4: Annual interest | H4: Maturity date | I4: Cum. leverage | J4: % of capitalization | K4: Mark / price | L4: Mkt value
A5: =Assumptions!$A$53 -> ABL Revolver | B5: =Assumptions!$B$53 -> revolver | C5: =Assumptions!$M$53 -> 1 | D5: =IF(Assumptions!$O$53=1,"Secured","Unsecured") -> Secured | E5: =Assumptions!$C$53 -> 180 | F5: ='Debt Schedule'!G20 -> 0.101 | G5: =E5*F5 -> 18.18 | H5: =Assumptions!$J$53 -> 46691 | I5: =SUMIF($C$5:$C$8,"<="&C5,$E$5:$E$8)/'Operating Model'!F17 -> 1.1538462 | J5: =E5/($E$9+$E$13) -> 0.144 | K5: =Assumptions!$R$53 -> 100 | L5: =E5*K5/100 -> 180
A6: =Assumptions!$A$54 -> First-Lien Term Loan | B6: =Assumptions!$B$54 -> term_loan | C6: =Assumptions!$M$54 -> 2 | D6: =IF(Assumptions!$O$54=1,"Secured","Unsecured") -> Secured | E6: =Assumptions!$C$54 -> 520 | F6: ='Debt Schedule'!G33 -> 0.118 | G6: =E6*F6 -> 61.36 | H6: =Assumptions!$J$54 -> 46843 | I6: =SUMIF($C$5:$C$8,"<="&C6,$E$5:$E$8)/'Operating Model'!F17 -> 4.4871795 | J6: =E6/($E$9+$E$13) -> 0.416 | K6: =Assumptions!$R$54 -> 78 | L6: =E6*K6/100 -> 405.6
A7: =Assumptions!$A$55 -> Second-Lien Notes 11.0% | B7: =Assumptions!$B$55 -> second_lien | C7: =Assumptions!$M$55 -> 3 | D7: =IF(Assumptions!$O$55=1,"Secured","Unsecured") -> Secured | E7: =Assumptions!$C$55 -> 250 | F7: ='Debt Schedule'!G46 -> 0.11 | G7: =E7*F7 -> 27.5 | H7: =Assumptions!$J$55 -> 47299 | I7: =SUMIF($C$5:$C$8,"<="&C7,$E$5:$E$8)/'Operating Model'!F17 -> 6.0897436 | J7: =E7/($E$9+$E$13) -> 0.2 | K7: =Assumptions!$R$55 -> 52 | L7: =E7*K7/100 -> 130
A8: =Assumptions!$A$56 -> Senior Unsecured Notes 7.5% | B8: =Assumptions!$B$56 -> unsecured_notes | C8: =Assumptions!$M$56 -> 4 | D8: =IF(Assumptions!$O$56=1,"Secured","Unsecured") -> Unsecured | E8: =Assumptions!$C$56 -> 300 | F8: ='Debt Schedule'!G59 -> 0.075 | G8: =E8*F8 -> 22.5 | H8: =Assumptions!$J$56 -> 46522 | I8: =SUMIF($C$5:$C$8,"<="&C8,$E$5:$E$8)/'Operating Model'!F17 -> 8.0128205 | J8: =E8/($E$9+$E$13) -> 0.24 | K8: =Assumptions!$R$56 -> 33 | L8: =E8*K8/100 -> 99
A9: Total debt | E9: =SUM(E5:E8) -> 1250 | G9: =SUM(G5:G8) -> 129.54 | I9: =E9/'Operating Model'!F17 -> 8.0128205 | L9: =SUM(L5:L8) -> 814.6
A10: Less: cash | E10: =Assumptions!$C$11 -> 45
A11: Net debt | E11: =E9-E10 -> 1205 | I11: =E11/'Operating Model'!F17 -> 7.724359
A12: Enterprise value (base EBITDA × market-implied multiple — analyst assumption) | E12: ='Operating Model'!F17*Assumptions!$C$21 -> 1014
A13: Equity (residual: max(0, EV − net debt)) | E13: =MAX(0,E12-E11) -> 0
A14: Liquidity (cash + undrawn revolver) | E14: ='Credit Metrics'!F16 -> 165
A15: Asset base (collateral / recovery basis) | E15: =Assumptions!$C$27 -> 1040
A16: Loan-to-value through target tranche (cumulative debt ÷ asset base) | E16: =SUMIF($C$5:$C$8,"<="&INDEX($C$5:$C$8,Assumptions!$C$30),$E$5:$E$8)/E15 -> 0.67307692
A19: Maturity wall (from Debt Schedule maturity flags) — selected scenario liquidity
A20: Period | C20: Debt due | D20: % of debt | E20: Cumulative % | F20: Projected liquidity | G20: Refinancing requirement | H20: Liquidity ÷ maturity | I20: Risk | J20: Flag
A21: ="FY2026E"&" (period ending "&'Operating Model'!G7&")" -> FY2026E (period ending 2026) | C21: ='Debt Schedule'!G70 -> 0 | D21: =C21/$E$9 -> 0 | E21: =SUM($D$21:D21) -> 0 | F21: =MAX(0,Assumptions!$C$11)+('Credit Metrics'!F16-MAX(0,Assumptions!$C$11))+MAX(0,'Operating Model'!G30) -> 165 | G21: =MAX(0,C21-F21) -> 0 | H21: =IF(C21>0,F21/C21,0) -> 0 | I21: =IF(AND(G21>0,D21>=Assumptions!$C$19),"High",IF(OR(G21>0,D21>=Assumptions!$C$20),"Medium","Low")) -> Low | J21: =IF(I21="High","$"&TEXT(C21,"#,##0")&"M maturity; only $"&TEXT(F21,"#,##0")&"M projected liquidity; $"&TEXT(G21,"#,##0")&"M refinancing requirement","–") -> –
A22: ="FY2027E"&" (period ending "&'Operating Model'!H7&")" -> FY2027E (period ending 2027) | C22: ='Debt Schedule'!H70 -> 480 | D22: =C22/$E$9 -> 0.384 | E22: =SUM($D$21:D22) -> 0.384 | F22: =MAX(0,'Cash Flow'!G19)+('Credit Metrics'!G16-MAX(0,'Cash Flow'!G19))+MAX(0,'Operating Model'!H30) -> 83.7032 | G22: =MAX(0,C22-F22) -> 396.2968 | H22: =IF(C22>0,F22/C22,0) -> 0.17438167 | I22: =IF(AND(G22>0,D22>=Assumptions!$C$19),"High",IF(OR(G22>0,D22>=Assumptions!$C$20),"Medium","Low")) -> High | J22: =IF(I22="High","$"&TEXT(C22,"#,##0")&"M maturity; only $"&TEXT(F22,"#,##0")&"M projected liquidity; $"&TEXT(G22,"#,##0")&"M refinancing requirement","–") -> $480M maturity; only $84M projected liquidity; $396M refinancing requirement
A23: ="FY2028E"&" (period ending "&'Operating Model'!I7&")" -> FY2028E (period ending 2028) | C23: ='Debt Schedule'!I70 -> 520 | D23: =C23/$E$9 -> 0.416 | E23: =SUM($D$21:D23) -> 0.8 | F23: =MAX(0,'Cash Flow'!H19)+('Credit Metrics'!H16-MAX(0,'Cash Flow'!H19))+MAX(0,'Operating Model'!I30) -> 83.7032 | G23: =MAX(0,C23-F23) -> 436.2968 | H23: =IF(C23>0,F23/C23,0) -> 0.16096769 | I23: =IF(AND(G23>0,D23>=Assumptions!$C$19),"High",IF(OR(G23>0,D23>=Assumptions!$C$20),"Medium","Low")) -> High | J23: =IF(I23="High","$"&TEXT(C23,"#,##0")&"M maturity; only $"&TEXT(F23,"#,##0")&"M projected liquidity; $"&TEXT(G23,"#,##0")&"M refinancing requirement","–") -> $520M maturity; only $84M projected liquidity; $436M refinancing requirement
A24: ="FY2029E"&" (period ending "&'Operating Model'!J7&")" -> FY2029E (period ending 2029) | C24: ='Debt Schedule'!J70 -> 250 | D24: =C24/$E$9 -> 0.2 | E24: =SUM($D$21:D24) -> 1 | F24: =MAX(0,'Cash Flow'!I19)+('Credit Metrics'!I16-MAX(0,'Cash Flow'!I19))+MAX(0,'Operating Model'!J30) -> 83.7032 | G24: =MAX(0,C24-F24) -> 166.2968 | H24: =IF(C24>0,F24/C24,0) -> 0.3348128 | I24: =IF(AND(G24>0,D24>=Assumptions!$C$19),"High",IF(OR(G24>0,D24>=Assumptions!$C$20),"Medium","Low")) -> Medium | J24: =IF(I24="High","$"&TEXT(C24,"#,##0")&"M maturity; only $"&TEXT(F24,"#,##0")&"M projected liquidity; $"&TEXT(G24,"#,##0")&"M refinancing requirement","–") -> –
A25: ="FY2030E"&" (period ending "&'Operating Model'!K7&")" -> FY2030E (period ending 2030) | C25: ='Debt Schedule'!K70 -> 0 | D25: =C25/$E$9 -> 0 | E25: =SUM($D$21:D25) -> 1 | F25: =MAX(0,'Cash Flow'!J19)+('Credit Metrics'!J16-MAX(0,'Cash Flow'!J19))+MAX(0,'Operating Model'!K30) -> 83.7032 | G25: =MAX(0,C25-F25) -> 0 | H25: =IF(C25>0,F25/C25,0) -> 0 | I25: =IF(AND(G25>0,D25>=Assumptions!$C$19),"High",IF(OR(G25>0,D25>=Assumptions!$C$20),"Medium","Low")) -> Low | J25: =IF(I25="High","$"&TEXT(C25,"#,##0")&"M maturity; only $"&TEXT(F25,"#,##0")&"M projected liquidity; $"&TEXT(G25,"#,##0")&"M refinancing requirement","–") -> –
A26: Maturing within horizon / thereafter | C26: =SUM(C21:C25) -> 1250 | D26: =C26/$E$9 -> 1
A27: Thereafter (beyond the 5-period horizon) | C27: =$E$9-C26 -> 0
A29: Maturity concentration | C29: =IF(MAX(D21:D25)>=Assumptions!$C$20,"CONCENTRATED: "&TEXT(MAX(D21:D25),"0%")&" of debt in "&INDEX(A21:A25,MATCH(MAX(D21:D25),D21:D25,0)),"No single-period concentration") -> CONCENTRATED: 42% of debt in FY2028E (period ending 2028)
A30: Debt due within alert window | C30: =SUMPRODUCT((Assumptions!$K$53:$K$56<=Assumptions!$C$6+Assumptions!$C$18)*Assumptions!$C$53:$C$56) -> 480 | D30: =C30/E9 -> 0.384
A31: Maturity alert | C31: =IF(D30>=Assumptions!$C$19,"ALERT: "&TEXT(D30,"0%")&" of debt ($"&TEXT(C30,"#,##0")&"M) due within "&Assumptions!$C$18&" period(s); liquidity covers "&TEXT(E14/C30,"0%"),"OK: no material maturities within window") -> ALERT: 38% of debt ($480M) due within 2 period(s); liquidity covers 34%
A33: Refinancing risk engine — per tranche, selected scenario (see Debt Schedule for the period-by-period test)
A34: Tranche | C34: Balance at maturity | D34: Repaid from cash | E34: Test | F34: Resolution
A35: =Assumptions!$A$53 -> ABL Revolver | C35: ='Debt Schedule'!C72 -> 216.2968 | D35: ='Debt Schedule'!C73 -> 0 | E35: ='Debt Schedule'!C74 -> REFINANCING FAILURE | F35: ='Debt Schedule'!C75 -> PAYMENT DEFAULT
A36: =Assumptions!$A$54 -> First-Lien Term Loan | C36: ='Debt Schedule'!C76 -> 504.4 | D36: ='Debt Schedule'!C77 -> 0 | E36: ='Debt Schedule'!C78 -> REFINANCING FAILURE | F36: ='Debt Schedule'!C79 -> PAYMENT DEFAULT
A37: =Assumptions!$A$55 -> Second-Lien Notes 11.0% | C37: ='Debt Schedule'!C80 -> 250 | D37: ='Debt Schedule'!C81 -> 0 | E37: ='Debt Schedule'!C82 -> REFINANCING FAILURE | F37: ='Debt Schedule'!C83 -> PAYMENT DEFAULT
A38: =Assumptions!$A$56 -> Senior Unsecured Notes 7.5% | C38: ='Debt Schedule'!C84 -> 300 | D38: ='Debt Schedule'!C85 -> 0 | E38: ='Debt Schedule'!C86 -> REFINANCING FAILURE | F38: ='Debt Schedule'!C87 -> PAYMENT DEFAULT

Sheet Recovery
A1: Recovery — waterfall by seniority (collateral pools, deficiency claims) at the valuation event
A2: ="Brightwater Retail Holdings · DEMO DATA · DEMO INVESTMENT TERMS · Active scenario: "&Assumptions!$D$10 -> Brightwater Retail Holdings · DEMO DATA · DEMO INVESTMENT TERMS · Active scenario: Downside
A4: $M | C4: Value
A6: Valuation event (default period, or trough-EBITDA period if no default is modelled)
A7: Valuation event period flag | G7: =IF($C$8=1,'Cash Flow'!G22,IF('Operating Model'!G17=MIN('Operating Model'!$G$17:$K$17),1,0)) -> 0 | H7: =IF($C$8=1,'Cash Flow'!H22,IF(AND('Operating Model'!H17=MIN('Operating Model'!$G$17:$K$17),SUM($G$7:G7)=0),1,0)) -> 1 | I7: =IF($C$8=1,'Cash Flow'!I22,IF(AND('Operating Model'!I17=MIN('Operating Model'!$G$17:$K$17),SUM($G$7:H7)=0),1,0)) -> 0 | J7: =IF($C$8=1,'Cash Flow'!J22,IF(AND('Operating Model'!J17=MIN('Operating Model'!$G$17:$K$17),SUM($G$7:I7)=0),1,0)) -> 0 | K7: =IF($C$8=1,'Cash Flow'!K22,IF(AND('Operating Model'!K17=MIN('Operating Model'!$G$17:$K$17),SUM($G$7:J7)=0),1,0)) -> 0
A8: Default modelled? (1 = yes) | C8: =IF(SUM('Cash Flow'!$G$22:$K$22)>0,1,0) -> 1
A9: Valuation period | C9: =SUMPRODUCT($G$7:$K$7,'Operating Model'!$G$7:$K$7) -> 2027
A10: EBITDA at valuation event | C10: =SUMPRODUCT($G$7:$K$7,'Operating Model'!$G$17:$K$17) -> 48.909518
A11: Cash at valuation event | C11: =MAX(0,SUMPRODUCT($G$7:$K$7,'Cash Flow'!$G$19:$K$19)) -> 0
A12: Going-concern value (distressed multiple × EBITDA) | C12: =(CHOOSE(Assumptions!$C$10,Assumptions!$C$78,Assumptions!$C$97,Assumptions!$C$116))*C10 -> 195.63807
A13: Liquidation value (asset base × (1 − decline) × recovery) | C13: =Assumptions!$C$27*(1-CHOOSE(Assumptions!$C$10,Assumptions!$C$79,Assumptions!$C$98,Assumptions!$C$117))*CHOOSE(Assumptions!$C$10,Assumptions!$C$80,Assumptions!$C$99,Assumptions!$C$118) -> 530.4
A14: Model recovery value (greater of the two + cash) | C14: =MAX(C12,C13)+C11 -> 530.4
A15: Recovery value used (override if provided) | C15: =IF(ISNUMBER(Assumptions!$C$14),Assumptions!$C$14,C14) -> 530.4
A16: Less: administrative / DIP costs | C16: =C15*Assumptions!$C$15 -> 21.216
A17: Net value distributable to creditors | C17: =C15-C16 -> 509.184
A18: Claim at valuation event (balance + accrued interest)
A19: Tranche 1: ABL Revolver | C19: =SUMPRODUCT($G$7:$K$7,'Debt Schedule'!$G$28:$K$28)*(1+SUMPRODUCT($G$7:$K$7,'Debt Schedule'!$G$20:$K$20)*Assumptions!$C$16/12) -> 221.62311
A20: Tranche 2: First-Lien Term Loan | C20: =SUMPRODUCT($G$7:$K$7,'Debt Schedule'!$G$41:$K$41)*(1+SUMPRODUCT($G$7:$K$7,'Debt Schedule'!$G$33:$K$33)*Assumptions!$C$16/12) -> 524.3147
A21: Tranche 3: Second-Lien Notes 11.0% | C21: =SUMPRODUCT($G$7:$K$7,'Debt Schedule'!$G$54:$K$54)*(1+SUMPRODUCT($G$7:$K$7,'Debt Schedule'!$G$46:$K$46)*Assumptions!$C$16/12) -> 256.875
A22: Tranche 4: Senior Unsecured Notes 7.5% | C22: =SUMPRODUCT($G$7:$K$7,'Debt Schedule'!$G$67:$K$67)*(1+SUMPRODUCT($G$7:$K$7,'Debt Schedule'!$G$59:$K$59)*Assumptions!$C$16/12) -> 305.625
A23: Seniority rank
A24: Tranche 1: ABL Revolver | C24: =Assumptions!$M$53 -> 1
A25: Tranche 2: First-Lien Term Loan | C25: =Assumptions!$M$54 -> 2
A26: Tranche 3: Second-Lien Notes 11.0% | C26: =Assumptions!$M$55 -> 3
A27: Tranche 4: Senior Unsecured Notes 7.5% | C27: =Assumptions!$M$56 -> 4
A28: Collateral share (specific lien; 0 = all-asset / pari)
A29: Tranche 1: ABL Revolver | C29: =Assumptions!$Q$53 -> 0
A30: Tranche 2: First-Lien Term Loan | C30: =Assumptions!$Q$54 -> 0
A31: Tranche 3: Second-Lien Notes 11.0% | C31: =Assumptions!$Q$55 -> 0
A32: Tranche 4: Senior Unsecured Notes 7.5% | C32: =Assumptions!$Q$56 -> 0
A33: Paid from own collateral pool
A34: Tranche 1: ABL Revolver | C34: =IF(C29>0,MIN(C19,C29*$C$17),0) -> 0
A35: Tranche 2: First-Lien Term Loan | C35: =IF(C30>0,MIN(C20,C30*$C$17),0) -> 0
A36: Tranche 3: Second-Lien Notes 11.0% | C36: =IF(C31>0,MIN(C21,C31*$C$17),0) -> 0
A37: Tranche 4: Senior Unsecured Notes 7.5% | C37: =IF(C32>0,MIN(C22,C32*$C$17),0) -> 0
A38: Deficiency claim (joins general creditors)
A39: Tranche 1: ABL Revolver | C39: =IF(C29>0,C19-C34,0) -> 0 | G39: =IF(AND('Debt Schedule'!G18=1,'Debt Schedule'!G15=1),1,0) -> 0 | H39: =IF(G39=1,1,IF(AND('Debt Schedule'!H18=1,'Debt Schedule'!H15=1),1,0)) -> 0 | I39: =IF(H39=1,1,IF(AND('Debt Schedule'!I18=1,'Debt Schedule'!I15=1),1,0)) -> 0 | J39: =IF(I39=1,1,IF(AND('Debt Schedule'!J18=1,'Debt Schedule'!J15=1),1,0)) -> 0 | K39: =IF(J39=1,1,IF(AND('Debt Schedule'!K18=1,'Debt Schedule'!K15=1),1,0)) -> 0
A40: Tranche 2: First-Lien Term Loan | C40: =IF(C30>0,C20-C35,0) -> 0 | G40: =IF(AND('Debt Schedule'!G31=1,'Debt Schedule'!G15=1),1,0) -> 0 | H40: =IF(G40=1,1,IF(AND('Debt Schedule'!H31=1,'Debt Schedule'!H15=1),1,0)) -> 0 | I40: =IF(H40=1,1,IF(AND('Debt Schedule'!I31=1,'Debt Schedule'!I15=1),1,0)) -> 0 | J40: =IF(I40=1,1,IF(AND('Debt Schedule'!J31=1,'Debt Schedule'!J15=1),1,0)) -> 0 | K40: =IF(J40=1,1,IF(AND('Debt Schedule'!K31=1,'Debt Schedule'!K15=1),1,0)) -> 0
A41: Tranche 3: Second-Lien Notes 11.0% | C41: =IF(C31>0,C21-C36,0) -> 0 | G41: =IF(AND('Debt Schedule'!G44=1,'Debt Schedule'!G15=1),1,0) -> 0 | H41: =IF(G41=1,1,IF(AND('Debt Schedule'!H44=1,'Debt Schedule'!H15=1),1,0)) -> 0 | I41: =IF(H41=1,1,IF(AND('Debt Schedule'!I44=1,'Debt Schedule'!I15=1),1,0)) -> 0 | J41: =IF(I41=1,1,IF(AND('Debt Schedule'!J44=1,'Debt Schedule'!J15=1),1,0)) -> 0 | K41: =IF(J41=1,1,IF(AND('Debt Schedule'!K44=1,'Debt Schedule'!K15=1),1,0)) -> 0
A42: Tranche 4: Senior Unsecured Notes 7.5% | C42: =IF(C32>0,C22-C37,0) -> 0 | G42: =IF(AND('Debt Schedule'!G57=1,'Debt Schedule'!G15=1),1,0) -> 0 | H42: =IF(G42=1,1,IF(AND('Debt Schedule'!H57=1,'Debt Schedule'!H15=1),1,0)) -> 0 | I42: =IF(H42=1,1,IF(AND('Debt Schedule'!I57=1,'Debt Schedule'!I15=1),1,0)) -> 0 | J42: =IF(I42=1,1,IF(AND('Debt Schedule'!J57=1,'Debt Schedule'!J15=1),1,0)) -> 0 | K42: =IF(J42=1,1,IF(AND('Debt Schedule'!K57=1,'Debt Schedule'!K15=1),1,0)) -> 0
A43: General claim
A44: Tranche 1: ABL Revolver | C44: =IF(C29>0,C39,C19) -> 221.62311
A45: Tranche 2: First-Lien Term Loan | C45: =IF(C30>0,C40,C20) -> 524.3147
A46: Tranche 3: Second-Lien Notes 11.0% | C46: =IF(C31>0,C41,C21) -> 256.875
A47: Tranche 4: Senior Unsecured Notes 7.5% | C47: =IF(C32>0,C42,C22) -> 305.625
A48: General rank
A49: Tranche 1: ABL Revolver | C49: =IF(C29>0,Assumptions!$C$17,C24) -> 1
A50: Tranche 2: First-Lien Term Loan | C50: =IF(C30>0,Assumptions!$C$17,C25) -> 2
A51: Tranche 3: Second-Lien Notes 11.0% | C51: =IF(C31>0,Assumptions!$C$17,C26) -> 3
A52: Tranche 4: Senior Unsecured Notes 7.5% | C52: =IF(C32>0,Assumptions!$C$17,C27) -> 4
A53: General claims ahead
A54: Tranche 1: ABL Revolver | C54: =SUMPRODUCT(($C$49:$C$52<C49)*$C$44:$C$47) -> 0
A55: Tranche 2: First-Lien Term Loan | C55: =SUMPRODUCT(($C$49:$C$52<C50)*$C$44:$C$47) -> 221.62311
A56: Tranche 3: Second-Lien Notes 11.0% | C56: =SUMPRODUCT(($C$49:$C$52<C51)*$C$44:$C$47) -> 745.93781
A57: Tranche 4: Senior Unsecured Notes 7.5% | C57: =SUMPRODUCT(($C$49:$C$52<C52)*$C$44:$C$47) -> 1002.8128
A58: General claims of same rank (pari passu)
A59: Tranche 1: ABL Revolver | C59: =SUMPRODUCT(($C$49:$C$52=C49)*$C$44:$C$47) -> 221.62311
A60: Tranche 2: First-Lien Term Loan | C60: =SUMPRODUCT(($C$49:$C$52=C50)*$C$44:$C$47) -> 524.3147
A61: Tranche 3: Second-Lien Notes 11.0% | C61: =SUMPRODUCT(($C$49:$C$52=C51)*$C$44:$C$47) -> 256.875
A62: Tranche 4: Senior Unsecured Notes 7.5% | C62: =SUMPRODUCT(($C$49:$C$52=C52)*$C$44:$C$47) -> 305.625
A63: Recovery from general pool
A64: Tranche 1: ABL Revolver | C64: =IF(C59=0,0,C44/C59*MAX(0,MIN(C59,$C$17-SUM($C$34:$C$37)-C54))) -> 221.62311
A65: Tranche 2: First-Lien Term Loan | C65: =IF(C60=0,0,C45/C60*MAX(0,MIN(C60,$C$17-SUM($C$34:$C$37)-C55))) -> 287.56089
A66: Tranche 3: Second-Lien Notes 11.0% | C66: =IF(C61=0,0,C46/C61*MAX(0,MIN(C61,$C$17-SUM($C$34:$C$37)-C56))) -> 0
A67: Tranche 4: Senior Unsecured Notes 7.5% | C67: =IF(C62=0,0,C47/C62*MAX(0,MIN(C62,$C$17-SUM($C$34:$C$37)-C57))) -> 0
A68: TOTAL RECOVERY
A69: Tranche 1: ABL Revolver | C69: =C34+C64 -> 221.62311
A70: Tranche 2: First-Lien Term Loan | C70: =C35+C65 -> 287.56089
A71: Tranche 3: Second-Lien Notes 11.0% | C71: =C36+C66 -> 0
A72: Tranche 4: Senior Unsecured Notes 7.5% | C72: =C37+C67 -> 0
A73: Recovery %
A74: Tranche 1: ABL Revolver | C74: =IF(C19=0,1,C69/C19) -> 1
A75: Tranche 2: First-Lien Term Loan | C75: =IF(C20=0,1,C70/C20) -> 0.54845094
A76: Tranche 3: Second-Lien Notes 11.0% | C76: =IF(C21=0,1,C71/C21) -> 0
A77: Tranche 4: Senior Unsecured Notes 7.5% | C77: =IF(C22=0,1,C72/C22) -> 0
A78: Loss amount
A79: Tranche 1: ABL Revolver | C79: =C19-C69 -> 0
A80: Tranche 2: First-Lien Term Loan | C80: =C20-C70 -> 236.75381
A81: Tranche 3: Second-Lien Notes 11.0% | C81: =C21-C71 -> 256.875
A82: Tranche 4: Senior Unsecured Notes 7.5% | C82: =C22-C72 -> 305.625
A83: Loss %
A84: Tranche 1: ABL Revolver | C84: =IF(C19=0,0,C79/C19) -> 0
A85: Tranche 2: First-Lien Term Loan | C85: =IF(C20=0,0,C80/C20) -> 0.45154906
A86: Tranche 3: Second-Lien Notes 11.0% | C86: =IF(C21=0,0,C81/C21) -> 1
A87: Tranche 4: Senior Unsecured Notes 7.5% | C87: =IF(C22=0,0,C82/C22) -> 1
A88: Equity (residual after all claims) | C88: =MAX(0,$C$17-SUM($C$34:$C$37)-SUM($C$44:$C$47)) -> 0
A89: Check: recoveries + equity + costs − value (should be 0) | C89: =SUM($C$69:$C$72)+C88+C16-C15 -> 0

Sheet Returns
A1: Returns — face, purchase price, coupon, yield, recovery, IRR and MOIC (selected scenario)
A2: ="Brightwater Retail Holdings · DEMO DATA · DEMO INVESTMENT TERMS · Active scenario: "&Assumptions!$D$10 -> Brightwater Retail Holdings · DEMO DATA · DEMO INVESTMENT TERMS · Active scenario: Downside
A4: $M | C4: Value / t=0 | D4: t=1 | E4: t=2 | F4: t=3 | G4: t=4 | H4: t=5 | I4: t=6
A6: Position & valuation inputs (links) — face value, purchase price, coupon, yield and recovery are distinct
A7: Target tranche # | C7: =Assumptions!$C$30 -> 2
A8: Face value (legal claim) | C8: =Assumptions!$C$31 -> 100
A9: Purchase price / OID (% of face) | C9: =Assumptions!$C$32 -> 78
A10: Cash investment (face × price × (1 + fees)) | C10: =C8*C9/100*(1+Assumptions!$C$33) -> 78.39
A11: Hold period (periods) | C11: =Assumptions!$C$34 -> 2
A12: Default period # (0 = no default) | C12: =IF(Recovery!C8=1,SUMPRODUCT('Cash Flow'!$G$22:$K$22,'Operating Model'!$G$8:$K$8),0) -> 2
A13: Our share of the tranche at the valuation event | C13: =IFERROR(C8/CHOOSE(C7,SUMPRODUCT(Recovery!$G$7:$K$7,'Debt Schedule'!$G$28:$K$28),SUMPRODUCT(Recovery!$G$7:$K$7,'Debt Schedule'!$G$41:$K$41),SUMPRODUCT(Recovery!$G$7:$K$7,'Debt Schedule'!$G$54:$K$54),SUMPRODUCT(Recovery!$G$7:$K$7,'Debt Schedule'!$G$67:$K$67)),0) -> 0.19623234
A14: Recovery proceeds to our position if default | C14: =CHOOSE(C7,Recovery!C69,Recovery!C70,Recovery!C71,Recovery!C72)*C13 -> 56.428746
A15: Tranche recovery % at valuation event (waterfall) | C15: =CHOOSE(C7,Recovery!C74,Recovery!C75,Recovery!C76,Recovery!C77) -> 0.54845094
A16: Last coupon period # | C16: =IF(Recovery!C8=1,C12,C11) -> 2
A17: Exit price assumption (no default) | C17: =CHOOSE(Assumptions!$C$10,Assumptions!$C$77,Assumptions!$C$96,Assumptions!$C$115) -> 90
A18: Exit EV (exit multiple × EBITDA + cash at hold period) | C18: =INDEX('Operating Model'!$G$17:$K$17,C11)*CHOOSE(Assumptions!$C$10,Assumptions!$C$76,Assumptions!$C$95,Assumptions!$C$114)+MAX(0,INDEX('Cash Flow'!$G$19:$K$19,C11)) -> 244.54759
A19: Claim at exit (balance at hold period)
A20: Tranche 1: ABL Revolver | C20: =INDEX('Debt Schedule'!$G$28:$K$28,C11) -> 216.2968
A21: Tranche 2: First-Lien Term Loan | C21: =INDEX('Debt Schedule'!$G$41:$K$41,C11) -> 509.6
A22: Tranche 3: Second-Lien Notes 11.0% | C22: =INDEX('Debt Schedule'!$G$54:$K$54,C11) -> 250
A23: Tranche 4: Senior Unsecured Notes 7.5% | C23: =INDEX('Debt Schedule'!$G$67:$K$67,C11) -> 300
A24: Seniority rank
A25: Tranche 1: ABL Revolver | C25: =Assumptions!$M$53 -> 1
A26: Tranche 2: First-Lien Term Loan | C26: =Assumptions!$M$54 -> 2
A27: Tranche 3: Second-Lien Notes 11.0% | C27: =Assumptions!$M$55 -> 3
A28: Tranche 4: Senior Unsecured Notes 7.5% | C28: =Assumptions!$M$56 -> 4
A29: Collateral share (specific lien; 0 = all-asset / pari)
A30: Tranche 1: ABL Revolver | C30: =Assumptions!$Q$53 -> 0
A31: Tranche 2: First-Lien Term Loan | C31: =Assumptions!$Q$54 -> 0
A32: Tranche 3: Second-Lien Notes 11.0% | C32: =Assumptions!$Q$55 -> 0
A33: Tranche 4: Senior Unsecured Notes 7.5% | C33: =Assumptions!$Q$56 -> 0
A34: Paid from own collateral pool
A35: Tranche 1: ABL Revolver | C35: =IF(C30>0,MIN(C20,C30*$C$18),0) -> 0
A36: Tranche 2: First-Lien Term Loan | C36: =IF(C31>0,MIN(C21,C31*$C$18),0) -> 0
A37: Tranche 3: Second-Lien Notes 11.0% | C37: =IF(C32>0,MIN(C22,C32*$C$18),0) -> 0
A38: Tranche 4: Senior Unsecured Notes 7.5% | C38: =IF(C33>0,MIN(C23,C33*$C$18),0) -> 0
A39: Deficiency claim (joins general creditors)
A40: Tranche 1: ABL Revolver | C40: =IF(C30>0,C20-C35,0) -> 0
A41: Tranche 2: First-Lien Term Loan | C41: =IF(C31>0,C21-C36,0) -> 0
A42: Tranche 3: Second-Lien Notes 11.0% | C42: =IF(C32>0,C22-C37,0) -> 0
A43: Tranche 4: Senior Unsecured Notes 7.5% | C43: =IF(C33>0,C23-C38,0) -> 0
A44: General claim
A45: Tranche 1: ABL Revolver | C45: =IF(C30>0,C40,C20) -> 216.2968
A46: Tranche 2: First-Lien Term Loan | C46: =IF(C31>0,C41,C21) -> 509.6
A47: Tranche 3: Second-Lien Notes 11.0% | C47: =IF(C32>0,C42,C22) -> 250
A48: Tranche 4: Senior Unsecured Notes 7.5% | C48: =IF(C33>0,C43,C23) -> 300
A49: General rank
A50: Tranche 1: ABL Revolver | C50: =IF(C30>0,Assumptions!$C$17,C25) -> 1
A51: Tranche 2: First-Lien Term Loan | C51: =IF(C31>0,Assumptions!$C$17,C26) -> 2
A52: Tranche 3: Second-Lien Notes 11.0% | C52: =IF(C32>0,Assumptions!$C$17,C27) -> 3
A53: Tranche 4: Senior Unsecured Notes 7.5% | C53: =IF(C33>0,Assumptions!$C$17,C28) -> 4
A54: General claims ahead
A55: Tranche 1: ABL Revolver | C55: =SUMPRODUCT(($C$50:$C$53<C50)*$C$45:$C$48) -> 0
A56: Tranche 2: First-Lien Term Loan | C56: =SUMPRODUCT(($C$50:$C$53<C51)*$C$45:$C$48) -> 216.2968
A57: Tranche 3: Second-Lien Notes 11.0% | C57: =SUMPRODUCT(($C$50:$C$53<C52)*$C$45:$C$48) -> 725.8968
A58: Tranche 4: Senior Unsecured Notes 7.5% | C58: =SUMPRODUCT(($C$50:$C$53<C53)*$C$45:$C$48) -> 975.8968
A59: General claims of same rank (pari passu)
A60: Tranche 1: ABL Revolver | C60: =SUMPRODUCT(($C$50:$C$53=C50)*$C$45:$C$48) -> 216.2968
A61: Tranche 2: First-Lien Term Loan | C61: =SUMPRODUCT(($C$50:$C$53=C51)*$C$45:$C$48) -> 509.6
A62: Tranche 3: Second-Lien Notes 11.0% | C62: =SUMPRODUCT(($C$50:$C$53=C52)*$C$45:$C$48) -> 250
A63: Tranche 4: Senior Unsecured Notes 7.5% | C63: =SUMPRODUCT(($C$50:$C$53=C53)*$C$45:$C$48) -> 300
A64: Recovery from general pool
A65: Tranche 1: ABL Revolver | C65: =IF(C60=0,0,C45/C60*MAX(0,MIN(C60,$C$18-SUM($C$35:$C$38)-C55))) -> 216.2968
A66: Tranche 2: First-Lien Term Loan | C66: =IF(C61=0,0,C46/C61*MAX(0,MIN(C61,$C$18-SUM($C$35:$C$38)-C56))) -> 28.250792
A67: Tranche 3: Second-Lien Notes 11.0% | C67: =IF(C62=0,0,C47/C62*MAX(0,MIN(C62,$C$18-SUM($C$35:$C$38)-C57))) -> 0
A68: Tranche 4: Senior Unsecured Notes 7.5% | C68: =IF(C63=0,0,C48/C63*MAX(0,MIN(C63,$C$18-SUM($C$35:$C$38)-C58))) -> 0
A69: TOTAL RECOVERY
A70: Tranche 1: ABL Revolver | C70: =C35+C65 -> 216.2968
A71: Tranche 2: First-Lien Term Loan | C71: =C36+C66 -> 28.250792
A72: Tranche 3: Second-Lien Notes 11.0% | C72: =C37+C67 -> 0
A73: Tranche 4: Senior Unsecured Notes 7.5% | C73: =C38+C68 -> 0
A74: Recovery %
A75: Tranche 1: ABL Revolver | C75: =IF(C20=0,1,C70/C20) -> 1
A76: Tranche 2: First-Lien Term Loan | C76: =IF(C21=0,1,C71/C21) -> 0.05543719
A77: Tranche 3: Second-Lien Notes 11.0% | C77: =IF(C22=0,1,C72/C22) -> 0
A78: Tranche 4: Senior Unsecured Notes 7.5% | C78: =IF(C23=0,1,C73/C23) -> 0
A79: Loss amount
A80: Tranche 1: ABL Revolver | C80: =C20-C70 -> 0
A81: Tranche 2: First-Lien Term Loan | C81: =C21-C71 -> 481.34921
A82: Tranche 3: Second-Lien Notes 11.0% | C82: =C22-C72 -> 250
A83: Tranche 4: Senior Unsecured Notes 7.5% | C83: =C23-C73 -> 300
A84: Loss %
A85: Tranche 1: ABL Revolver | C85: =IF(C20=0,0,C80/C20) -> 0
A86: Tranche 2: First-Lien Term Loan | C86: =IF(C21=0,0,C81/C21) -> 0.94456281
A87: Tranche 3: Second-Lien Notes 11.0% | C87: =IF(C22=0,0,C82/C22) -> 1
A88: Tranche 4: Senior Unsecured Notes 7.5% | C88: =IF(C23=0,0,C83/C23) -> 1
A89: Equity (residual after all claims) | C89: =MAX(0,$C$18-SUM($C$35:$C$38)-SUM($C$45:$C$48)) -> 0
A90: Exit price used (lesser of assumption and valuation coverage) | C90: =MIN(C17,100*CHOOSE(C7,C75,C76,C77,C78)) -> 5.543719
A91: Principal proceeds received in period # | C91: =IF(Recovery!C8=1,C12+Assumptions!$C$36,C11) -> 3
A92: Cash flows to the position ($M) — period # 0 … 6
A93: Period # | C93: =COLUMN()-COLUMN($C$1) -> 0 | D93: =COLUMN()-COLUMN($C$1) -> 1 | E93: =COLUMN()-COLUMN($C$1) -> 2 | F93: =COLUMN()-COLUMN($C$1) -> 3 | G93: =COLUMN()-COLUMN($C$1) -> 4 | H93: =COLUMN()-COLUMN($C$1) -> 5 | I93: =COLUMN()-COLUMN($C$1) -> 6
A94: Cash coupon rate on target tranche | D94: =CHOOSE($C$7,'Debt Schedule'!G20,'Debt Schedule'!G33,'Debt Schedule'!G46,'Debt Schedule'!G59) -> 0.118 | E94: =CHOOSE($C$7,'Debt Schedule'!H20,'Debt Schedule'!H33,'Debt Schedule'!H46,'Debt Schedule'!H59) -> 0.1155 | F94: =CHOOSE($C$7,'Debt Schedule'!I20,'Debt Schedule'!I33,'Debt Schedule'!I46,'Debt Schedule'!I59) -> 0.113 | G94: =CHOOSE($C$7,'Debt Schedule'!J20,'Debt Schedule'!J33,'Debt Schedule'!J46,'Debt Schedule'!J59) -> 0.113 | H94: =CHOOSE($C$7,'Debt Schedule'!K20,'Debt Schedule'!K33,'Debt Schedule'!K46,'Debt Schedule'!K59) -> 0.113
A95: Cash interest received | D95: =IF(D93<=$C$16,$C$8*D94,0) -> 11.8 | E95: =IF(E93<=$C$16,$C$8*E94,0) -> 11.55 | F95: =IF(F93<=$C$16,$C$8*F94,0) -> 0 | G95: =IF(G93<=$C$16,$C$8*G94,0) -> 0 | H95: =IF(H93<=$C$16,$C$8*H94,0) -> 0
A96: Exit proceeds / recovery | D96: =IF(AND(Recovery!$C$8=0,D93=$C$11),$C$8*$C$90/100,0)+IF(AND(Recovery!$C$8=1,D93=$C$91),$C$14,0) -> 0 | E96: =IF(AND(Recovery!$C$8=0,E93=$C$11),$C$8*$C$90/100,0)+IF(AND(Recovery!$C$8=1,E93=$C$91),$C$14,0) -> 0 | F96: =IF(AND(Recovery!$C$8=0,F93=$C$11),$C$8*$C$90/100,0)+IF(AND(Recovery!$C$8=1,F93=$C$91),$C$14,0) -> 56.428746 | G96: =IF(AND(Recovery!$C$8=0,G93=$C$11),$C$8*$C$90/100,0)+IF(AND(Recovery!$C$8=1,G93=$C$91),$C$14,0) -> 0 | H96: =IF(AND(Recovery!$C$8=0,H93=$C$11),$C$8*$C$90/100,0)+IF(AND(Recovery!$C$8=1,H93=$C$91),$C$14,0) -> 0 | I96: =IF(AND(Recovery!$C$8=0,I93=$C$11),$C$8*$C$90/100,0)+IF(AND(Recovery!$C$8=1,I93=$C$91),$C$14,0) -> 0
A97: Net cash flow | C97: =-$C$10 -> -78.39 | D97: =D95+D96 -> 11.8 | E97: =E95+E96 -> 11.55 | F97: =F95+F96 -> 56.428746 | G97: =G95+G96 -> 0 | H97: =H95+H96 -> 0 | I97: =I95+I96 -> 0
A98: Cash interest received (total) | C98: =SUM($C$95:$I$95) -> 23.35
A99: Exit / recovery proceeds (total) | C99: =SUM($C$96:$I$96) -> 56.428746
A100: Total cash received | C100: =C98+C99 -> 79.778746
A101: Capital gain / (loss) vs purchase price (proceeds − face × price) | C101: =C99-C8*C9/100 -> -21.571254
A102: Absolute profit | C102: =C100-C10 -> 1.3887463
...

Sheet Sensitivities
A1: Sensitivities — position IRR / MOIC under Base, Downside and Severe
A2: Axis values (blue) are inputs. Every cell is a formula: IRR over a cash-flow row, or an IRR / recovery from a full Calc Engine case. No data tables → recalculates in Excel and LibreOffice.
A3: ="Position: "&TEXT(Assumptions!$C$32,"0.0")&" purchase price, hold "&Assumptions!$C$34&" periods | Selected scenario: "&Assumptions!$D$10 -> Position: 78.0 purchase price, hold 2 periods | Selected scenario: Downside
A8: Table 1 — Purchase price vs IRR
A9: Purchase price (% of face) | B9: Offset | C9: Base Case | D9: Downside | E9: Severe Downside | F9: Selected
A10: =Assumptions!$C$32+B10 -> 70 | B10: -8 | C10: =J86 -> 0.17781081 | D10: =J91 -> 0.050645472 | E10: =J96 -> -0.098240015 | F10: =CHOOSE(Assumptions!$C$10,C10,D10,E10) -> 0.050645472
A11: =Assumptions!$C$32+B11 -> 74 | B11: -4 | C11: =J87 -> 0.15340016 | D11: =J92 -> 0.027892804 | E11: =J97 -> -0.11922385 | F11: =CHOOSE(Assumptions!$C$10,C11,D11,E11) -> 0.027892804
A12: =Assumptions!$C$32+B12 -> 78 | B12: 0 | C12: =J88 -> 0.13082152 | D12: =J93 -> 0.0068898968 | E12: =J98 -> -0.13853405 | F12: =CHOOSE(Assumptions!$C$10,C12,D12,E12) -> 0.0068898968
A13: =Assumptions!$C$32+B13 -> 82 | B13: 4 | C13: =J89 -> 0.10985008 | D13: =J94 -> -0.01258185 | E13: =J99 -> -0.15638504 | F13: =CHOOSE(Assumptions!$C$10,C13,D13,E13) -> -0.01258185
A14: =Assumptions!$C$32+B14 -> 86 | B14: 8 | C14: =J90 -> 0.090298166 | D14: =J95 -> -0.030704358 | E14: =J100 -> -0.17295459 | F14: =CHOOSE(Assumptions!$C$10,C14,D14,E14) -> -0.030704358
A18: Table 2 — Exit / recovery value (% of face, received at exit or after default) vs IRR
A19: Proceeds (% of face) | C19: Base Case | D19: Downside | E19: Severe Downside | F19: Selected
A20: 20 | C20: =J101 -> -0.24756996 | D20: =J106 -> -0.22907072 | E20: =J111 -> -0.21034886 | F20: =CHOOSE(Assumptions!$C$10,C20,D20,E20) -> -0.22907072
A21: 40 | C21: =J102 -> -0.098509907 | D21: =J107 -> -0.082588893 | E21: =J112 -> -0.066476246 | F21: =CHOOSE(Assumptions!$C$10,C21,D21,E21) -> -0.082588893
A22: 60 | C22: =J103 -> 0.0094841879 | D22: =J108 -> 0.024141175 | E22: =J113 -> 0.038965314 | F22: =CHOOSE(Assumptions!$C$10,C22,D22,E22) -> 0.024141175
A23: 80 | C23: =J104 -> 0.096737162 | D23: =J109 -> 0.11059759 | E23: =J114 -> 0.12460786 | F23: =CHOOSE(Assumptions!$C$10,C23,D23,E23) -> 0.11059759
A24: 100 | C24: =J105 -> 0.17106829 | D24: =J110 -> 0.1843637 | E24: =J115 -> 0.19779612 | F24: =CHOOSE(Assumptions!$C$10,C24,D24,E24) -> 0.1843637
A28: Table 3 — EBITDA margin shift (all periods) vs IRR — full model re-run
A29: EBITDA margin shift (pts) | C29: Base Case | D29: Downside | E29: Severe Downside | F29: Selected
A30: -0.04 | C30: ='Calc Engine'!C1410 -> 0.048841676 | D30: ='Calc Engine'!C3175 -> -0.21392499 | E30: ='Calc Engine'!C4940 -> -0.46007281 | F30: =CHOOSE(Assumptions!$C$10,C30,D30,E30) -> -0.21392499
A31: -0.02 | C31: ='Calc Engine'!C1763 -> 0.089063078 | D31: ='Calc Engine'!C3528 -> -0.039239922 | E31: ='Calc Engine'!C5293 -> -0.19657482 | F31: =CHOOSE(Assumptions!$C$10,C31,D31,E31) -> -0.039239922
A32: 0 | C32: ='Calc Engine'!C2116 -> 0.13082152 | D32: ='Calc Engine'!C3881 -> 0.0068898968 | E32: ='Calc Engine'!C5646 -> -0.13853405 | F32: =CHOOSE(Assumptions!$C$10,C32,D32,E32) -> 0.0068898968
A33: 0.02 | C33: ='Calc Engine'!C2469 -> 0.25237073 | D33: ='Calc Engine'!C4234 -> 0.048732684 | E33: ='Calc Engine'!C5999 -> -0.088478625 | F33: =CHOOSE(Assumptions!$C$10,C33,D33,E33) -> 0.048732684
A34: 0.04 | C34: ='Calc Engine'!C2822 -> 0.25237073 | D34: ='Calc Engine'!C4587 -> 0.091439807 | E34: ='Calc Engine'!C6352 -> -0.044095903 | F34: =CHOOSE(Assumptions!$C$10,C34,D34,E34) -> 0.091439807
A38: Table 4 — Revenue growth shift (all periods) vs IRR — full model re-run
A39: Revenue growth shift (pts) | C39: Base Case | D39: Downside | E39: Severe Downside | F39: Selected
A40: -0.1 | C40: ='Calc Engine'!C6705 -> 0.13972231 | D40: ='Calc Engine'!C8470 -> 0.03140252 | E40: ='Calc Engine'!C10235 -> -0.095027421 | F40: =CHOOSE(Assumptions!$C$10,C40,D40,E40) -> 0.03140252
A41: -0.05 | C41: ='Calc Engine'!C7058 -> 0.13305047 | D41: ='Calc Engine'!C8823 -> 0.019310228 | E41: ='Calc Engine'!C10588 -> -0.11615504 | F41: =CHOOSE(Assumptions!$C$10,C41,D41,E41) -> 0.019310228
A42: 0 | C42: ='Calc Engine'!C7411 -> 0.13082152 | D42: ='Calc Engine'!C9176 -> 0.0068898968 | E42: ='Calc Engine'!C10941 -> -0.13853405 | F42: =CHOOSE(Assumptions!$C$10,C42,D42,E42) -> 0.0068898968
A43: 0.05 | C43: ='Calc Engine'!C7764 -> 0.16868811 | D43: ='Calc Engine'!C9529 -> -0.0058819464 | E43: ='Calc Engine'!C11294 -> -0.16237223 | F43: =CHOOSE(Assumptions!$C$10,C43,D43,E43) -> -0.0058819464
A44: 0.1 | C44: ='Calc Engine'!C8117 -> 0.17971313 | D44: ='Calc Engine'!C9882 -> -0.019031601 | E44: ='Calc Engine'!C11647 -> -0.18793945 | F44: =CHOOSE(Assumptions!$C$10,C44,D44,E44) -> -0.019031601
A48: Table 5 — Interest rate (SOFR) shift vs IRR — full model re-run (floating coupons and interest burden both move)
A49: SOFR shift (pts) | C49: Base Case | D49: Downside | E49: Severe Downside | F49: Selected
A50: -0.01 | C50: ='Calc Engine'!C12000 -> 0.24026758 | D50: ='Calc Engine'!C13765 -> 0.004406033 | E50: ='Calc Engine'!C15530 -> -0.1390949 | F50: =CHOOSE(Assumptions!$C$10,C50,D50,E50) -> 0.004406033
A51: -0.005 | C51: ='Calc Engine'!C12353 -> 0.12907952 | D51: ='Calc Engine'!C14118 -> 0.0056447107 | E51: ='Calc Engine'!C15883 -> -0.13881096 | F51: =CHOOSE(Assumptions!$C$10,C51,D51,E51) -> 0.0056447107
A52: 0 | C52: ='Calc Engine'!C12706 -> 0.13082152 | D52: ='Calc Engine'!C14471 -> 0.0068898968 | E52: ='Calc Engine'!C16236 -> -0.13853405 | F52: =CHOOSE(Assumptions!$C$10,C52,D52,E52) -> 0.0068898968
A53: 0.01 | C53: ='Calc Engine'!C13059 -> 0.13433278 | D53: ='Calc Engine'!C14824 -> 0.0094002363 | E53: ='Calc Engine'!C16589 -> -0.13800211 | F53: =CHOOSE(Assumptions!$C$10,C53,D53,E53) -> 0.0094002363
A54: 0.02 | C54: ='Calc Engine'!C13412 -> 0.13788105 | D54: ='Calc Engine'!C15177 -> 0.011937956 | E54: ='Calc Engine'!C16942 -> -0.1375007 | F54: =CHOOSE(Assumptions!$C$10,C54,D54,E54) -> 0.011937956
A58: Table 6 — Distressed valuation multiple shift (x) vs target-tranche recovery % (valuation waterfall)
A59: Multiple shift (x EBITDA) | C59: Base Case | D59: Downside | E59: Severe Downside | F59: Selected
A60: -2 | C60: ='Calc Engine'!C17206 -> 0.85466554 | D60: ='Calc Engine'!C18971 -> 0.54845094 | E60: ='Calc Engine'!C20736 -> 0.28087124 | F60: =CHOOSE(Assumptions!$C$10,C60,D60,E60) -> 0.54845094
A61: -1 | C61: ='Calc Engine'!C17559 -> 0.85466554 | D61: ='Calc Engine'!C19324 -> 0.54845094 | E61: ='Calc Engine'!C21089 -> 0.28087124 | F61: =CHOOSE(Assumptions!$C$10,C61,D61,E61) -> 0.54845094
A62: 0 | C62: ='Calc Engine'!C17912 -> 0.86642715 | D62: ='Calc Engine'!C19677 -> 0.54845094 | E62: ='Calc Engine'!C21442 -> 0.28087124 | F62: =CHOOSE(Assumptions!$C$10,C62,D62,E62) -> 0.54845094
A63: 1 | C63: ='Calc Engine'!C18265 -> 1 | D63: ='Calc Engine'!C20030 -> 0.54845094 | E63: ='Calc Engine'!C21795 -> 0.28087124 | F63: =CHOOSE(Assumptions!$C$10,C63,D63,E63) -> 0.54845094
A64: 2 | C64: ='Calc Engine'!C18618 -> 1 | D64: ='Calc Engine'!C20383 -> 0.54845094 | E64: ='Calc Engine'!C22148 -> 0.28087124 | F64: =CHOOSE(Assumptions!$C$10,C64,D64,E64) -> 0.54845094
A68: Table 7 — Recovery / exit value (% of face) vs MOIC
A69: Proceeds (% of face) | C69: Base Case | D69: Downside | E69: Severe Downside | F69: Selected
A70: =$A$20 -> 20 | C70: =(SUM('Calc Engine'!C342:I342)+Assumptions!$C$31*$A$70/100)/'Calc Engine'!C257 -> 0.51473402 | D70: =(SUM('Calc Engine'!C695:I695)+Assumptions!$C$31*$A$70/100)/'Calc Engine'!C610 -> 0.55300421 | E70: =(SUM('Calc Engine'!C1048:I1048)+Assumptions!$C$31*$A$70/100)/'Calc Engine'!C963 -> 0.5912744 | F70: =CHOOSE(Assumptions!$C$10,C70,D70,E70) -> 0.55300421
A71: =$A$21 -> 40 | C71: =(SUM('Calc Engine'!C342:I342)+Assumptions!$C$31*$A$71/100)/'Calc Engine'!C257 -> 0.76986861 | D71: =(SUM('Calc Engine'!C695:I695)+Assumptions!$C$31*$A$71/100)/'Calc Engine'!C610 -> 0.80813879 | E71: =(SUM('Calc Engine'!C1048:I1048)+Assumptions!$C$31*$A$71/100)/'Calc Engine'!C963 -> 0.84640898 | F71: =CHOOSE(Assumptions!$C$10,C71,D71,E71) -> 0.80813879
A72: =$A$22 -> 60 | C72: =(SUM('Calc Engine'!C342:I342)+Assumptions!$C$31*$A$72/100)/'Calc Engine'!C257 -> 1.0250032 | D72: =(SUM('Calc Engine'!C695:I695)+Assumptions!$C$31*$A$72/100)/'Calc Engine'!C610 -> 1.0632734 | E72: =(SUM('Calc Engine'!C1048:I1048)+Assumptions!$C$31*$A$72/100)/'Calc Engine'!C963 -> 1.1015436 | F72: =CHOOSE(Assumptions!$C$10,C72,D72,E72) -> 1.0632734
A73: =$A$23 -> 80 | C73: =(SUM('Calc Engine'!C342:I342)+Assumptions!$C$31*$A$73/100)/'Calc Engine'!C257 -> 1.2801378 | D73: =(SUM('Calc Engine'!C695:I695)+Assumptions!$C$31*$A$73/100)/'Calc Engine'!C610 -> 1.318408 | E73: =(SUM('Calc Engine'!C1048:I1048)+Assumptions!$C$31*$A$73/100)/'Calc Engine'!C963 -> 1.3566781 | F73: =CHOOSE(Assumptions!$C$10,C73,D73,E73) -> 1.318408
A74: =$A$24 -> 100 | C74: =(SUM('Calc Engine'!C342:I342)+Assumptions!$C$31*$A$74/100)/'Calc Engine'!C257 -> 1.5352724 | D74: =(SUM('Calc Engine'!C695:I695)+Assumptions!$C$31*$A$74/100)/'Calc Engine'!C610 -> 1.5735425 | E74: =(SUM('Calc Engine'!C1048:I1048)+Assumptions!$C$31*$A$74/100)/'Calc Engine'!C963 -> 1.6118127 | F74: =CHOOSE(Assumptions!$C$10,C74,D74,E74) -> 1.5735425
A82: Tables 3-6 re-run the operating model, debt schedule, default test and recovery waterfall for every point (Calc Engine cases 4-63).
A84: Supporting cash flows for Tables 1-2 (period 0 → 6) and resulting IRR
A85: Case | C85: t=0 | D85: t=1 | E85: t=2 | F85: t=3 | G85: t=4 | H85: t=5 | I85: t=6 | J85: IRR
A86: ="Base Case · price point 1" -> Base Case · price point 1 | C86: =-Assumptions!$C$31*$A$10/100*(1+Assumptions!$C$33) -> -70.35 | D86: ='Calc Engine'!D342+'Calc Engine'!D343 -> 10.3 | E86: ='Calc Engine'!E342+'Calc Engine'!E343 -> 10.05 | F86: ='Calc Engine'!F342+'Calc Engine'!F343 -> 88.819613 | G86: ='Calc Engine'!G342+'Calc Engine'!G343 -> 0 | H86: ='Calc Engine'!H342+'Calc Engine'!H343 -> 0 | I86: ='Calc Engine'!I342+'Calc Engine'!I343 -> 0 | J86: =IF(SUM(D86:I86)<=0,-1,IFERROR(IRR(C86:I86,MAX(-0.9,(SUM(D86:I86)/-C86)^(1/Assumptions!$C$34)-1)),IRR(C86:I86,0.1))) -> 0.17781081
A87: ="Base Case · price point 2" -> Base Case · price point 2 | C87: =-Assumptions!$C$31*$A$11/100*(1+Assumptions!$C$33) -> -74.37 | D87: ='Calc Engine'!D342+'Calc Engine'!D343 -> 10.3 | E87: ='Calc Engine'!E342+'Calc Engine'!E343 -> 10.05 | F87: ='Calc Engine'!F342+'Calc Engine'!F343 -> 88.819613 | G87: ='Calc Engine'!G342+'Calc Engine'!G343 -> 0 | H87: ='Calc Engine'!H342+'Calc Engine'!H343 -> 0 | I87: ='Calc Engine'!I342+'Calc Engine'!I343 -> 0 | J87: =IF(SUM(D87:I87)<=0,-1,IFERROR(IRR(C87:I87,MAX(-0.9,(SUM(D87:I87)/-C87)^(1/Assumptions!$C$34)-1)),IRR(C87:I87,0.1))) -> 0.15340016
A88: ="Base Case · price point 3" -> Base Case · price point 3 | C88: =-Assumptions!$C$31*$A$12/100*(1+Assumptions!$C$33) -> -78.39 | D88: ='Calc Engine'!D342+'Calc Engine'!D343 -> 10.3 | E88: ='Calc Engine'!E342+'Calc Engine'!E343 -> 10.05 | F88: ='Calc Engine'!F342+'Calc Engine'!F343 -> 88.819613 | G88: ='Calc Engine'!G342+'Calc Engine'!G343 -> 0 | H88: ='Calc Engine'!H342+'Calc Engine'!H343 -> 0 | I88: ='Calc Engine'!I342+'Calc Engine'!I343 -> 0 | J88: =IF(SUM(D88:I88)<=0,-1,IFERROR(IRR(C88:I88,MAX(-0.9,(SUM(D88:I88)/-C88)^(1/Assumptions!$C$34)-1)),IRR(C88:I88,0.1))) -> 0.13082152
A89: ="Base Case · price point 4" -> Base Case · price point 4 | C89: =-Assumptions!$C$31*$A$13/100*(1+Assumptions!$C$33) -> -82.41 | D89: ='Calc Engine'!D342+'Calc Engine'!D343 -> 10.3 | E89: ='Calc Engine'!E342+'Calc Engine'!E343 -> 10.05 | F89: ='Calc Engine'!F342+'Calc Engine'!F343 -> 88.819613 | G89: ='Calc Engine'!G342+'Calc Engine'!G343 -> 0 | H89: ='Calc Engine'!H342+'Calc Engine'!H343 -> 0 | I89: ='Calc Engine'!I342+'Calc Engine'!I343 -> 0 | J89: =IF(SUM(D89:I89)<=0,-1,IFERROR(IRR(C89:I89,MAX(-0.9,(SUM(D89:I89)/-C89)^(1/Assumptions!$C$34)-1)),IRR(C89:I89,0.1))) -> 0.10985008
A90: ="Base Case · price point 5" -> Base Case · price point 5 | C90: =-Assumptions!$C$31*$A$14/100*(1+Assumptions!$C$33) -> -86.43 | D90: ='Calc Engine'!D342+'Calc Engine'!D343 -> 10.3 | E90: ='Calc Engine'!E342+'Calc Engine'!E343 -> 10.05 | F90: ='Calc Engine'!F342+'Calc Engine'!F343 -> 88.819613 | G90: ='Calc Engine'!G342+'Calc Engine'!G343 -> 0 | H90: ='Calc Engine'!H342+'Calc Engine'!H343 -> 0 | I90: ='Calc Engine'!I342+'Calc Engine'!I343 -> 0 | J90: =IF(SUM(D90:I90)<=0,-1,IFERROR(IRR(C90:I90,MAX(-0.9,(SUM(D90:I90)/-C90)^(1/Assumptions!$C$34)-1)),IRR(C90:I90,0.1))) -> 0.090298166
A91: ="Downside · price point 1" -> Downside · price point 1 | C91: =-Assumptions!$C$31*$A$10/100*(1+Assumptions!$C$33) -> -70.35 | D91: ='Calc Engine'!D695+'Calc Engine'!D696 -> 11.8 | E91: ='Calc Engine'!E695+'Calc Engine'!E696 -> 11.55 | F91: ='Calc Engine'!F695+'Calc Engine'!F696 -> 56.428746 | G91: ='Calc Engine'!G695+'Calc Engine'!G696 -> 0 | H91: ='Calc Engine'!H695+'Calc Engine'!H696 -> 0 | I91: ='Calc Engine'!I695+'Calc Engine'!I696 -> 0 | J91: =IF(SUM(D91:I91)<=0,-1,IFERROR(IRR(C91:I91,MAX(-0.9,(SUM(D91:I91)/-C91)^(1/Assumptions!$C$34)-1)),IRR(C91:I91,0.1))) -> 0.050645472
A92: ="Downside · price point 2" -> Downside · price point 2 | C92: =-Assumptions!$C$31*$A$11/100*(1+Assumptions!$C$33) -> -74.37 | D92: ='Calc Engine'!D695+'Calc Engine'!D696 -> 11.8 | E92: ='Calc Engine'!E695+'Calc Engine'!E696 -> 11.55 | F92: ='Calc Engine'!F695+'Calc Engine'!F696 -> 56.428746 | G92: ='Calc Engine'!G695+'Calc Engine'!G696 -> 0 | H92: ='Calc Engine'!H695+'Calc Engine'!H696 -> 0 | I92: ='Calc Engine'!I695+'Calc Engine'!I696 -> 0 | J92: =IF(SUM(D92:I92)<=0,-1,IFERROR(IRR(C92:I92,MAX(-0.9,(SUM(D92:I92)/-C92)^(1/Assumptions!$C$34)-1)),IRR(C92:I92,0.1))) -> 0.027892804
A93: ="Downside · price point 3" -> Downside · price point 3 | C93: =-Assumptions!$C$31*$A$12/100*(1+Assumptions!$C$33) -> -78.39 | D93: ='Calc Engine'!D695+'Calc Engine'!D696 -> 11.8 | E93: ='Calc Engine'!E695+'Calc Engine'!E696 -> 11.55 | F93: ='Calc Engine'!F695+'Calc Engine'!F696 -> 56.428746 | G93: ='Calc Engine'!G695+'Calc Engine'!G696 -> 0 | H93: ='Calc Engine'!H695+'Calc Engine'!H696 -> 0 | I93: ='Calc Engine'!I695+'Calc Engine'!I696 -> 0 | J93: =IF(SUM(D93:I93)<=0,-1,IFERROR(IRR(C93:I93,MAX(-0.9,(SUM(D93:I93)/-C93)^(1/Assumptions!$C$34)-1)),IRR(C93:I93,0.1))) -> 0.0068898968
A94: ="Downside · price point 4" -> Downside · price point 4 | C94: =-Assumptions!$C$31*$A$13/100*(1+Assumptions!$C$33) -> -82.41 | D94: ='Calc Engine'!D695+'Calc Engine'!D696 -> 11.8 | E94: ='Calc Engine'!E695+'Calc Engine'!E696 -> 11.55 | F94: ='Calc Engine'!F695+'Calc Engine'!F696 -> 56.428746 | G94: ='Calc Engine'!G695+'Calc Engine'!G696 -> 0 | H94: ='Calc Engine'!H695+'Calc Engine'!H696 -> 0 | I94: ='Calc Engine'!I695+'Calc Engine'!I696 -> 0 | J94: =IF(SUM(D94:I94)<=0,-1,IFERROR(IRR(C94:I94,MAX(-0.9,(SUM(D94:I94)/-C94)^(1/Assumptions!$C$34)-1)),IRR(C94:I94,0.1))) -> -0.01258185
A95: ="Downside · price point 5" -> Downside · price point 5 | C95: =-Assumptions!$C$31*$A$14/100*(1+Assumptions!$C$33) -> -86.43 | D95: ='Calc Engine'!D695+'Calc Engine'!D696 -> 11.8 | E95: ='Calc Engine'!E695+'Calc Engine'!E696 -> 11.55 | F95: ='Calc Engine'!F695+'Calc Engine'!F696 -> 56.428746 | G95: ='Calc Engine'!G695+'Calc Engine'!G696 -> 0 | H95: ='Calc Engine'!H695+'Calc Engine'!H696 -> 0 | I95: ='Calc Engine'!I695+'Calc Engine'!I696 -> 0 | J95: =IF(SUM(D95:I95)<=0,-1,IFERROR(IRR(C95:I95,MAX(-0.9,(SUM(D95:I95)/-C95)^(1/Assumptions!$C$34)-1)),IRR(C95:I95,0.1))) -> -0.030704358
A96: ="Severe Downside · price point 1" -> Severe Downside · price point 1 | C96: =-Assumptions!$C$31*$A$10/100*(1+Assumptions!$C$33) -> -70.35 | D96: ='Calc Engine'!D1048+'Calc Engine'!D1049 -> 13.3 | E96: ='Calc Engine'!E1048+'Calc Engine'!E1049 -> 13.05 | F96: ='Calc Engine'!F1048+'Calc Engine'!F1049 -> 29.003466 | G96: ='Calc Engine'!G1048+'Calc Engine'!G1049 -> 0 | H96: ='Calc Engine'!H1048+'Calc Engine'!H1049 -> 0 | I96: ='Calc Engine'!I1048+'Calc Engine'!I1049 -> 0 | J96: =IF(SUM(D96:I96)<=0,-1,IFERROR(IRR(C96:I96,MAX(-0.9,(SUM(D96:I96)/-C96)^(1/Assumptions!$C$34)-1)),IRR(C96:I96,0.1))) -> -0.098240015
A97: ="Severe Downside · price point 2" -> Severe Downside · price point 2 | C97: =-Assumptions!$C$31*$A$11/100*(1+Assumptions!$C$33) -> -74.37 | D97: ='Calc Engine'!D1048+'Calc Engine'!D1049 -> 13.3 | E97: ='Calc Engine'!E1048+'Calc Engine'!E1049 -> 13.05 | F97: ='Calc Engine'!F1048+'Calc Engine'!F1049 -> 29.003466 | G97: ='Calc Engine'!G1048+'Calc Engine'!G1049 -> 0 | H97: ='Calc Engine'!H1048+'Calc Engine'!H1049 -> 0 | I97: ='Calc Engine'!I1048+'Calc Engine'!I1049 -> 0 | J97: =IF(SUM(D97:I97)<=0,-1,IFERROR(IRR(C97:I97,MAX(-0.9,(SUM(D97:I97)/-C97)^(1/Assumptions!$C$34)-1)),IRR(C97:I97,0.1))) -> -0.11922385
A98: ="Severe Downside · price point 3" -> Severe Downside · price point 3 | C98: =-Assumptions!$C$31*$A$12/100*(1+Assumptions!$C$33) -> -78.39 | D98: ='Calc Engine'!D1048+'Calc Engine'!D1049 -> 13.3 | E98: ='Calc Engine'!E1048+'Calc Engine'!E1049 -> 13.05 | F98: ='Calc Engine'!F1048+'Calc Engine'!F1049 -> 29.003466 | G98: ='Calc Engine'!G1048+'Calc Engine'!G1049 -> 0 | H98: ='Calc Engine'!H1048+'Calc Engine'!H1049 -> 0 | I98: ='Calc Engine'!I1048+'Calc Engine'!I1049 -> 0 | J98: =IF(SUM(D98:I98)<=0,-1,IFERROR(IRR(C98:I98,MAX(-0.9,(SUM(D98:I98)/-C98)^(1/Assumptions!$C$34)-1)),IRR(C98:I98,0.1))) -> -0.13853405
A99: ="Severe Downside · price point 4" -> Severe Downside · price point 4 | C99: =-Assumptions!$C$31*$A$13/100*(1+Assumptions!$C$33) -> -82.41 | D99: ='Calc Engine'!D1048+'Calc Engine'!D1049 -> 13.3 | E99: ='Calc Engine'!E1048+'Calc Engine'!E1049 -> 13.05 | F99: ='Calc Engine'!F1048+'Calc Engine'!F1049 -> 29.003466 | G99: ='Calc Engine'!G1048+'Calc Engine'!G1049 -> 0 | H99: ='Calc Engine'!H1048+'Calc Engine'!H1049 -> 0 | I99: ='Calc Engine'!I1048+'Calc Engine'!I1049 -> 0 | J99: =IF(SUM(D99:I99)<=0,-1,IFERROR(IRR(C99:I99,MAX(-0.9,(SUM(D99:I99)/-C99)^(1/Assumptions!$C$34)-1)),IRR(C99:I99,0.1))) -> -0.15638504
A100: ="Severe Downside · price point 5" -> Severe Downside · price point 5 | C100: =-Assumptions!$C$31*$A$14/100*(1+Assumptions!$C$33) -> -86.43 | D100: ='Calc Engine'!D1048+'Calc Engine'!D1049 -> 13.3 | E100: ='Calc Engine'!E1048+'Calc Engine'!E1049 -> 13.05 | F100: ='Calc Engine'!F1048+'Calc Engine'!F1049 -> 29.003466 | G100: ='Calc Engine'!G1048+'Calc Engine'!G1049 -> 0 | H100: ='Calc Engine'!H1048+'Calc Engine'!H1049 -> 0 | I100: ='Calc Engine'!I1048+'Calc Engine'!I1049 -> 0 | J100: =IF(SUM(D100:I100)<=0,-1,IFERROR(IRR(C100:I100,MAX(-0.9,(SUM(D100:I100)/-C100)^(1/Assumptions!$C$34)-1)),IRR(C100:I100,0.1))) -> -0.17295459
A101: ="Base Case · rec point 1" -> Base Case · rec point 1 | C101: ='Calc Engine'!C344 -> -78.39 | D101: ='Calc Engine'!D342+IF('Calc Engine'!D340='Calc Engine'!C338,Assumptions!$C$31*$A$20/100,0) -> 10.3 | E101: ='Calc Engine'!E342+IF('Calc Engine'!E340='Calc Engine'!C338,Assumptions!$C$31*$A$20/100,0) -> 10.05 | F101: ='Calc Engine'!F342+IF('Calc Engine'!F340='Calc Engine'!C338,Assumptions!$C$31*$A$20/100,0) -> 20 | G101: ='Calc Engine'!G342+IF('Calc Engine'!G340='Calc Engine'!C338,Assumptions!$C$31*$A$20/100,0) -> 0 | H101: ='Calc Engine'!H342+IF('Calc Engine'!H340='Calc Engine'!C338,Assumptions!$C$31*$A$20/100,0) -> 0 | I101: ='Calc Engine'!I342+IF('Calc Engine'!I340='Calc Engine'!C338,Assumptions!$C$31*$A$20/100,0) -> 0 | J101: =IF(SUM(D101:I101)<=0,-1,IFERROR(IRR(C101:I101,MAX(-0.9,(SUM(D101:I101)/-C101)^(1/Assumptions!$C$34)-1)),IRR(C101:I101,0.1))) -> -0.24756996
A102: ="Base Case · rec point 2" -> Base Case · rec point 2 | C102: ='Calc Engine'!C344 -> -78.39 | D102: ='Calc Engine'!D342+IF('Calc Engine'!D340='Calc Engine'!C338,Assumptions!$C$31*$A$21/100,0) -> 10.3 | E102: ='Calc Engine'!E342+IF('Calc Engine'!E340='Calc Engine'!C338,Assumptions!$C$31*$A$21/100,0) -> 10.05 | F102: ='Calc Engine'!F342+IF('Calc Engine'!F340='Calc Engine'!C338,Assumptions!$C$31*$A$21/100,0) -> 40 | G102: ='Calc Engine'!G342+IF('Calc Engine'!G340='Calc Engine'!C338,Assumptions!$C$31*$A$21/100,0) -> 0 | H102: ='Calc Engine'!H342+IF('Calc Engine'!H340='Calc Engine'!C338,Assumptions!$C$31*$A$21/100,0) -> 0 | I102: ='Calc Engine'!I342+IF('Calc Engine'!I340='Calc Engine'!C338,Assumptions!$C$31*$A$21/100,0) -> 0 | J102: =IF(SUM(D102:I102)<=0,-1,IFERROR(IRR(C102:I102,MAX(-0.9,(SUM(D102:I102)/-C102)^(1/Assumptions!$C$34)-1)),IRR(C102:I102,0.1))) -> -0.098509907
A103: ="Base Case · rec point 3" -> Base Case · rec point 3 | C103: ='Calc Engine'!C344 -> -78.39 | D103: ='Calc Engine'!D342+IF('Calc Engine'!D340='Calc Engine'!C338,Assumptions!$C$31*$A$22/100,0) -> 10.3 | E103: ='Calc Engine'!E342+IF('Calc Engine'!E340='Calc Engine'!C338,Assumptions!$C$31*$A$22/100,0) -> 10.05 | F103: ='Calc Engine'!F342+IF('Calc Engine'!F340='Calc Engine'!C338,Assumptions!$C$31*$A$22/100,0) -> 60 | G103: ='Calc Engine'!G342+IF('Calc Engine'!G340='Calc Engine'!C338,Assumptions!$C$31*$A$22/100,0) -> 0 | H103: ='Calc Engine'!H342+IF('Calc Engine'!H340='Calc Engine'!C338,Assumptions!$C$31*$A$22/100,0) -> 0 | I103: ='Calc Engine'!I342+IF('Calc Engine'!I340='Calc Engine'!C338,Assumptions!$C$31*$A$22/100,0) -> 0 | J103: =IF(SUM(D103:I103)<=0,-1,IFERROR(IRR(C103:I103,MAX(-0.9,(SUM(D103:I103)/-C103)^(1/Assumptions!$C$34)-1)),IRR(C103:I103,0.1))) -> 0.0094841879
A104: ="Base Case · rec point 4" -> Base Case · rec point 4 | C104: ='Calc Engine'!C344 -> -78.39 | D104: ='Calc Engine'!D342+IF('Calc Engine'!D340='Calc Engine'!C338,Assumptions!$C$31*$A$23/100,0) -> 10.3 | E104: ='Calc Engine'!E342+IF('Calc Engine'!E340='Calc Engine'!C338,Assumptions!$C$31*$A$23/100,0) -> 10.05 | F104: ='Calc Engine'!F342+IF('Calc Engine'!F340='Calc Engine'!C338,Assumptions!$C$31*$A$23/100,0) -> 80 | G104: ='Calc Engine'!G342+IF('Calc Engine'!G340='Calc Engine'!C338,Assumptions!$C$31*$A$23/100,0) -> 0 | H104: ='Calc Engine'!H342+IF('Calc Engine'!H340='Calc Engine'!C338,Assumptions!$C$31*$A$23/100,0) -> 0 | I104: ='Calc Engine'!I342+IF('Calc Engine'!I340='Calc Engine'!C338,Assumptions!$C$31*$A$23/100,0) -> 0 | J104: =IF(SUM(D104:I104)<=0,-1,IFERROR(IRR(C104:I104,MAX(-0.9,(SUM(D104:I104)/-C104)^(1/Assumptions!$C$34)-1)),IRR(C104:I104,0.1))) -> 0.096737162
A105: ="Base Case · rec point 5" -> Base Case · rec point 5 | C105: ='Calc Engine'!C344 -> -78.39 | D105: ='Calc Engine'!D342+IF('Calc Engine'!D340='Calc Engine'!C338,Assumptions!$C$31*$A$24/100,0) -> 10.3 | E105: ='Calc Engine'!E342+IF('Calc Engine'!E340='Calc Engine'!C338,Assumptions!$C$31*$A$24/100,0) -> 10.05 | F105: ='Calc Engine'!F342+IF('Calc Engine'!F340='Calc Engine'!C338,Assumptions!$C$31*$A$24/100,0) -> 100 | G105: ='Calc Engine'!G342+IF('Calc Engine'!G340='Calc Engine'!C338,Assumptions!$C$31*$A$24/100,0) -> 0 | H105: ='Calc Engine'!H342+IF('Calc Engine'!H340='Calc Engine'!C338,Assumptions!$C$31*$A$24/100,0) -> 0 | I105: ='Calc Engine'!I342+IF('Calc Engine'!I340='Calc Engine'!C338,Assumptions!$C$31*$A$24/100,0) -> 0 | J105: =IF(SUM(D105:I105)<=0,-1,IFERROR(IRR(C105:I105,MAX(-0.9,(SUM(D105:I105)/-C105)^(1/Assumptions!$C$34)-1)),IRR(C105:I105,0.1))) -> 0.17106829
A106: ="Downside · rec point 1" -> Downside · rec point 1 | C106: ='Calc Engine'!C697 -> -78.39 | D106: ='Calc Engine'!D695+IF('Calc Engine'!D693='Calc Engine'!C691,Assumptions!$C$31*$A$20/100,0) -> 11.8 | E106: ='Calc Engine'!E695+IF('Calc Engine'!E693='Calc Engine'!C691,Assumptions!$C$31*$A$20/100,0) -> 11.55 | F106: ='Calc Engine'!F695+IF('Calc Engine'!F693='Calc Engine'!C691,Assumptions!$C$31*$A$20/100,0) -> 20 | G106: ='Calc Engine'!G695+IF('Calc Engine'!G693='Calc Engine'!C691,Assumptions!$C$31*$A$20/100,0) -> 0 | H106: ='Calc Engine'!H695+IF('Calc Engine'!H693='Calc Engine'!C691,Assumptions!$C$31*$A$20/100,0) -> 0 | I106: ='Calc Engine'!I695+IF('Calc Engine'!I693='Calc Engine'!C691,Assumptions!$C$31*$A$20/100,0) -> 0 | J106: =IF(SUM(D106:I106)<=0,-1,IFERROR(IRR(C106:I106,MAX(-0.9,(SUM(D106:I106)/-C106)^(1/Assumptions!$C$34)-1)),IRR(C106:I106,0.1))) -> -0.22907072
A107: ="Downside · rec point 2" -> Downside · rec point 2 | C107: ='Calc Engine'!C697 -> -78.39 | D107: ='Calc Engine'!D695+IF('Calc Engine'!D693='Calc Engine'!C691,Assumptions!$C$31*$A$21/100,0) -> 11.8 | E107: ='Calc Engine'!E695+IF('Calc Engine'!E693='Calc Engine'!C691,Assumptions!$C$31*$A$21/100,0) -> 11.55 | F107: ='Calc Engine'!F695+IF('Calc Engine'!F693='Calc Engine'!C691,Assumptions!$C$31*$A$21/100,0) -> 40 | G107: ='Calc Engine'!G695+IF('Calc Engine'!G693='Calc Engine'!C691,Assumptions!$C$31*$A$21/100,0) -> 0 | H107: ='Calc Engine'!H695+IF('Calc Engine'!H693='Calc Engine'!C691,Assumptions!$C$31*$A$21/100,0) -> 0 | I107: ='Calc Engine'!I695+IF('Calc Engine'!I693='Calc Engine'!C691,Assumptions!$C$31*$A$21/100,0) -> 0 | J107: =IF(SUM(D107:I107)<=0,-1,IFERROR(IRR(C107:I107,MAX(-0.9,(SUM(D107:I107)/-C107)^(1/Assumptions!$C$34)-1)),IRR(C107:I107,0.1))) -> -0.082588893
A108: ="Downside · rec point 3" -> Downside · rec point 3 | C108: ='Calc Engine'!C697 -> -78.39 | D108: ='Calc Engine'!D695+IF('Calc Engine'!D693='Calc Engine'!C691,Assumptions!$C$31*$A$22/100,0) -> 11.8 | E108: ='Calc Engine'!E695+IF('Calc Engine'!E693='Calc Engine'!C691,Assumptions!$C$31*$A$22/100,0) -> 11.55 | F108: ='Calc Engine'!F695+IF('Calc Engine'!F693='Calc Engine'!C691,Assumptions!$C$31*$A$22/100,0) -> 60 | G108: ='Calc Engine'!G695+IF('Calc Engine'!G693='Calc Engine'!C691,Assumptions!$C$31*$A$22/100,0) -> 0 | H108: ='Calc Engine'!H695+IF('Calc Engine'!H693='Calc Engine'!C691,Assumptions!$C$31*$A$22/100,0) -> 0 | I108: ='Calc Engine'!I695+IF('Calc Engine'!I693='Calc Engine'!C691,Assumptions!$C$31*$A$22/100,0) -> 0 | J108: =IF(SUM(D108:I108)<=0,-1,IFERROR(IRR(C108:I108,MAX(-0.9,(SUM(D108:I108)/-C108)^(1/Assumptions!$C$34)-1)),IRR(C108:I108,0.1))) -> 0.024141175
A109: ="Downside · rec point 4" -> Downside · rec point 4 | C109: ='Calc Engine'!C697 -> -78.39 | D109: ='Calc Engine'!D695+IF('Calc Engine'!D693='Calc Engine'!C691,Assumptions!$C$31*$A$23/100,0) -> 11.8 | E109: ='Calc Engine'!E695+IF('Calc Engine'!E693='Calc Engine'!C691,Assumptions!$C$31*$A$23/100,0) -> 11.55 | F109: ='Calc Engine'!F695+IF('Calc Engine'!F693='Calc Engine'!C691,Assumptions!$C$31*$A$23/100,0) -> 80 | G109: ='Calc Engine'!G695+IF('Calc Engine'!G693='Calc Engine'!C691,Assumptions!$C$31*$A$23/100,0) -> 0 | H109: ='Calc Engine'!H695+IF('Calc Engine'!H693='Calc Engine'!C691,Assumptions!$C$31*$A$23/100,0) -> 0 | I109: ='Calc Engine'!I695+IF('Calc Engine'!I693='Calc Engine'!C691,Assumptions!$C$31*$A$23/100,0) -> 0 | J109: =IF(SUM(D109:I109)<=0,-1,IFERROR(IRR(C109:I109,MAX(-0.9,(SUM(D109:I109)/-C109)^(1/Assumptions!$C$34)-1)),IRR(C109:I109,0.1))) -> 0.11059759
A110: ="Downside · rec point 5" -> Downside · rec point 5 | C110: ='Calc Engine'!C697 -> -78.39 | D110: ='Calc Engine'!D695+IF('Calc Engine'!D693='Calc Engine'!C691,Assumptions!$C$31*$A$24/100,0) -> 11.8 | E110: ='Calc Engine'!E695+IF('Calc Engine'!E693='Calc Engine'!C691,Assumptions!$C$31*$A$24/100,0) -> 11.55 | F110: ='Calc Engine'!F695+IF('Calc Engine'!F693='Calc Engine'!C691,Assumptions!$C$31*$A$24/100,0) -> 100 | G110: ='Calc Engine'!G695+IF('Calc Engine'!G693='Calc Engine'!C691,Assumptions!$C$31*$A$24/100,0) -> 0 | H110: ='Calc Engine'!H695+IF('Calc Engine'!H693='Calc Engine'!C691,Assumptions!$C$31*$A$24/100,0) -> 0 | I110: ='Calc Engine'!I695+IF('Calc Engine'!I693='Calc Engine'!C691,Assumptions!$C$31*$A$24/100,0) -> 0 | J110: =IF(SUM(D110:I110)<=0,-1,IFERROR(IRR(C110:I110,MAX(-0.9,(SUM(D110:I110)/-C110)^(1/Assumptions!$C$34)-1)),IRR(C110:I110,0.1))) -> 0.1843637
A111: ="Severe Downside · rec point 1" -> Severe Downside · rec point 1 | C111: ='Calc Engine'!C1050 -> -78.39 | D111: ='Calc Engine'!D1048+IF('Calc Engine'!D1046='Calc Engine'!C1044,Assumptions!$C$31*$A$20/100,0) -> 13.3 | E111: ='Calc Engine'!E1048+IF('Calc Engine'!E1046='Calc Engine'!C1044,Assumptions!$C$31*$A$20/100,0) -> 13.05 | F111: ='Calc Engine'!F1048+IF('Calc Engine'!F1046='Calc Engine'!C1044,Assumptions!$C$31*$A$20/100,0) -> 20 | G111: ='Calc Engine'!G1048+IF('Calc Engine'!G1046='Calc Engine'!C1044,Assumptions!$C$31*$A$20/100,0) -> 0 | H111: ='Calc Engine'!H1048+IF('Calc Engine'!H1046='Calc Engine'!C1044,Assumptions!$C$31*$A$20/100,0) -> 0 | I111: ='Calc Engine'!I1048+IF('Calc Engine'!I1046='Calc Engine'!C1044,Assumptions!$C$31*$A$20/100,0) -> 0 | J111: =IF(SUM(D111:I111)<=0,-1,IFERROR(IRR(C111:I111,MAX(-0.9,(SUM(D111:I111)/-C111)^(1/Assumptions!$C$34)-1)),IRR(C111:I111,0.1))) -> -0.21034886
A112: ="Severe Downside · rec point 2" -> Severe Downside · rec point 2 | C112: ='Calc Engine'!C1050 -> -78.39 | D112: ='Calc Engine'!D1048+IF('Calc Engine'!D1046='Calc Engine'!C1044,Assumptions!$C$31*$A$21/100,0) -> 13.3 | E112: ='Calc Engine'!E1048+IF('Calc Engine'!E1046='Calc Engine'!C1044,Assumptions!$C$31*$A$21/100,0) -> 13.05 | F112: ='Calc Engine'!F1048+IF('Calc Engine'!F1046='Calc Engine'!C1044,Assumptions!$C$31*$A$21/100,0) -> 40 | G112: ='Calc Engine'!G1048+IF('Calc Engine'!G1046='Calc Engine'!C1044,Assumptions!$C$31*$A$21/100,0) -> 0 | H112: ='Calc Engine'!H1048+IF('Calc Engine'!H1046='Calc Engine'!C1044,Assumptions!$C$31*$A$21/100,0) -> 0 | I112: ='Calc Engine'!I1048+IF('Calc Engine'!I1046='Calc Engine'!C1044,Assumptions!$C$31*$A$21/100,0) -> 0 | J112: =IF(SUM(D112:I112)<=0,-1,IFERROR(IRR(C112:I112,MAX(-0.9,(SUM(D112:I112)/-C112)^(1/Assumptions!$C$34)-1)),IRR(C112:I112,0.1))) -> -0.066476246
A113: ="Severe Downside · rec point 3" -> Severe Downside · rec point 3 | C113: ='Calc Engine'!C1050 -> -78.39 | D113: ='Calc Engine'!D1048+IF('Calc Engine'!D1046='Calc Engine'!C1044,Assumptions!$C$31*$A$22/100,0) -> 13.3 | E113: ='Calc Engine'!E1048+IF('Calc Engine'!E1046='Calc Engine'!C1044,Assumptions!$C$31*$A$22/100,0) -> 13.05 | F113: ='Calc Engine'!F1048+IF('Calc Engine'!F1046='Calc Engine'!C1044,Assumptions!$C$31*$A$22/100,0) -> 60 | G113: ='Calc Engine'!G1048+IF('Calc Engine'!G1046='Calc Engine'!C1044,Assumptions!$C$31*$A$22/100,0) -> 0 | H113: ='Calc Engine'!H1048+IF('Calc Engine'!H1046='Calc Engine'!C1044,Assumptions!$C$31*$A$22/100,0) -> 0 | I113: ='Calc Engine'!I1048+IF('Calc Engine'!I1046='Calc Engine'!C1044,Assumptions!$C$31*$A$22/100,0) -> 0 | J113: =IF(SUM(D113:I113)<=0,-1,IFERROR(IRR(C113:I113,MAX(-0.9,(SUM(D113:I113)/-C113)^(1/Assumptions!$C$34)-1)),IRR(C113:I113,0.1))) -> 0.038965314
A114: ="Severe Downside · rec point 4" -> Severe Downside · rec point 4 | C114: ='Calc Engine'!C1050 -> -78.39 | D114: ='Calc Engine'!D1048+IF('Calc Engine'!D1046='Calc Engine'!C1044,Assumptions!$C$31*$A$23/100,0) -> 13.3 | E114: ='Calc Engine'!E1048+IF('Calc Engine'!E1046='Calc Engine'!C1044,Assumptions!$C$31*$A$23/100,0) -> 13.05 | F114: ='Calc Engine'!F1048+IF('Calc Engine'!F1046='Calc Engine'!C1044,Assumptions!$C$31*$A$23/100,0) -> 80 | G114: ='Calc Engine'!G1048+IF('Calc Engine'!G1046='Calc Engine'!C1044,Assumptions!$C$31*$A$23/100,0) -> 0 | H114: ='Calc Engine'!H1048+IF('Calc Engine'!H1046='Calc Engine'!C1044,Assumptions!$C$31*$A$23/100,0) -> 0 | I114: ='Calc Engine'!I1048+IF('Calc Engine'!I1046='Calc Engine'!C1044,Assumptions!$C$31*$A$23/100,0) -> 0 | J114: =IF(SUM(D114:I114)<=0,-1,IFERROR(IRR(C114:I114,MAX(-0.9,(SUM(D114:I114)/-C114)^(1/Assumptions!$C$34)-1)),IRR(C114:I114,0.1))) -> 0.12460786
A115: ="Severe Downside · rec point 5" -> Severe Downside · rec point 5 | C115: ='Calc Engine'!C1050 -> -78.39 | D115: ='Calc Engine'!D1048+IF('Calc Engine'!D1046='Calc Engine'!C1044,Assumptions!$C$31*$A$24/100,0) -> 13.3 | E115: ='Calc Engine'!E1048+IF('Calc Engine'!E1046='Calc Engine'!C1044,Assumptions!$C$31*$A$24/100,0) -> 13.05 | F115: ='Calc Engine'!F1048+IF('Calc Engine'!F1046='Calc Engine'!C1044,Assumptions!$C$31*$A$24/100,0) -> 100 | G115: ='Calc Engine'!G1048+IF('Calc Engine'!G1046='Calc Engine'!C1044,Assumptions!$C$31*$A$24/100,0) -> 0 | H115: ='Calc Engine'!H1048+IF('Calc Engine'!H1046='Calc Engine'!C1044,Assumptions!$C$31*$A$24/100,0) -> 0 | I115: ='Calc Engine'!I1048+IF('Calc Engine'!I1046='Calc Engine'!C1044,Assumptions!$C$31*$A$24/100,0) -> 0 | J115: =IF(SUM(D115:I115)<=0,-1,IFERROR(IRR(C115:I115,MAX(-0.9,(SUM(D115:I115)/-C115)^(1/Assumptions!$C$34)-1)),IRR(C115:I115,0.1))) -> 0.19779612

Sheet Investment Summary
A1: Investment Summary — every figure is a live link to the model
A2: =Assumptions!$C$5&" | DEMO DATA | DEMO INVESTMENT TERMS | Active scenario: "&Assumptions!$D$10 -> Brightwater Retail Holdings | DEMO DATA | DEMO INVESTMENT TERMS | Active scenario: Downside
A4: Investment recommendation | C4: ='Investment Summary'!$C$41 -> HOLD
A5: Instrument | C5: =CHOOSE(Assumptions!$C$30,Assumptions!$A$53,Assumptions!$A$54,Assumptions!$A$55,Assumptions!$A$56)&" @ "&TEXT(Assumptions!$C$32,"0.0") -> First-Lien Term Loan @ 78.0
A6: Face value / purchase price / cash investment ($M) | C6: =TEXT(Assumptions!$C$31,"0.0")&" / "&TEXT(Assumptions!$C$32,"0.0")&" / "&TEXT(Returns!C10,"0.0") -> 100.0 / 78.0 / 78.4
A7: Credit score (0-100) | C7: ='Credit Metrics'!$G$45 -> 30.451098
A8: Risk band | C8: ='Credit Metrics'!$G$46 -> High
A9: Base-case IRR | C9: =Scenarios!C27 -> 0.13082152
A10: Downside IRR | C10: =Scenarios!D27 -> 0.0068898968
A11: Severe downside IRR | C11: =Scenarios!E27 -> -0.13853405
A12: Base / Downside / Severe MOIC | C12: =TEXT(Scenarios!C28,"0.00x")&" / "&TEXT(Scenarios!D28,"0.00x")&" / "&TEXT(Scenarios!E28,"0.00x") -> 1.39x / 1.02x / 0.71x
A13: Probability-weighted IRR | C13: =Scenarios!$C$31 -> 0.064153443
A14: Probability-weighted MOIC | C14: =Scenarios!$C$33 -> 1.1771901
A15: Probability of payment default | C15: =Scenarios!$C$34 -> 1
A16: Target-tranche recovery — Downside (valuation waterfall) | C16: =Scenarios!D25 -> 0.54845094
A17: Target-tranche recovery — Severe (valuation waterfall) | C17: =Scenarios!E25 -> 0.28087124
A18: Recovery (selected scenario, from Recovery tab) | C18: =Returns!C15 -> 0.54845094
A19: Net leverage — base period (FY2025A) | C19: ='Credit Metrics'!F11 -> 7.724359
A20: Interest coverage — base period | C20: ='Credit Metrics'!F12 -> 1.3104839
A21: Net leverage — FY2026E (selected scenario) | C21: ='Credit Metrics'!G11 -> 16.54138
A22: Interest coverage — FY2026E (selected scenario) | C22: ='Credit Metrics'!G12 -> 0.59786938
A23: Liquidity — FY2026E (selected scenario, $M) | C23: ='Credit Metrics'!G16 -> 83.7032
A24: Covenant breaches (selected scenario, count of failed tests) | C24: ='Credit Metrics'!C30 -> 5
A25: Maturity alert | C25: ='Capital Structure'!$C$31 -> ALERT: 38% of debt ($480M) due within 2 period(s); liquidity covers 34%
A26: Maturity concentration | C26: ='Capital Structure'!$C$29 -> CONCENTRATED: 42% of debt in FY2028E (period ending 2028)
A27: Recommendation evidence (thresholds on Assumptions §3)
A28: Test | C28: Actual | D28: Required | E28: Result | F28: Core?
A29: Base-case IRR clears hurdle | C29: =Scenarios!C27 -> 0.13082152 | D29: =Assumptions!$C$37 -> 0.12 | E29: =IF(C29>=D29,"PASS","FAIL") -> PASS | F29: core
A30: Probability-weighted IRR clears hurdle | C30: =Scenarios!$C$31 -> 0.064153443 | D30: =Assumptions!$C$37 -> 0.12 | E30: =IF(C30>=D30,"PASS","FAIL") -> FAIL | F30: core
A31: Downside IRR stays above floor | C31: =Scenarios!D27 -> 0.0068898968 | D31: =Assumptions!$C$38 -> 0 | E31: =IF(C31>=D31,"PASS","FAIL") -> PASS | F31: core
A32: Downside recovery meets minimum (valuation waterfall) | C32: =Scenarios!D25 -> 0.54845094 | D32: =Assumptions!$C$41 -> 0.6 | E32: =IF(C32>=D32,"PASS","FAIL") -> FAIL | F32: core
A33: Base-case refinancing succeeds (failures = 0) | C33: =Scenarios!C21 -> 0 | D33: =0 -> 0 | E33: =IF(C33<=D33,"PASS","FAIL") -> PASS | F33: core
A34: Yield to maturity meets minimum | C34: =IFERROR(RATE(YEARFRAC(Assumptions!$C$8,CHOOSE(Assumptions!$C$30,Assumptions!$J$53,Assumptions!$J$54,Assumptions!$J$55,Assumptions!$J$56)),'Calc Engine'!D341*100,-Assumptions!$C$32,100),0) -> 0.25701764 | D34: =Assumptions!$C$39 -> 0.09 | E34: =IF(C34>=D34,"PASS","FAIL") -> PASS
A35: Net leverage within maximum | C35: ='Credit Metrics'!F11 -> 7.724359 | D35: =Assumptions!$C$40 -> 6 | E35: =IF(C35<=D35,"PASS","FAIL") -> FAIL
A36: Covenant headroom (base case, minimum) | C36: ='Calc Engine'!C166 -> 0.075033899 | D36: =Assumptions!$C$42 -> 0.15 | E36: =IF(C36>=D36,"PASS","FAIL") -> FAIL
A37: Principal protected in severe case (recovery % × 100 ≥ price) | C37: =Scenarios!E25*100 -> 28.087124 | D37: =Assumptions!$C$32 -> 78 | E37: =IF(C37>=D37,"PASS","FAIL") -> FAIL
A38: No unresolved high-priority diligence | C38: =Assumptions!$C$45 -> 4 | D38: =0 -> 0 | E38: =IF(C38<=D38,"PASS","FAIL") -> FAIL
A39: Core test failures | C39: =COUNTIF(E29:E33,"FAIL") -> 2
A40: Secondary test failures | C40: =COUNTIF(E34:E38,"FAIL") -> 4
A41: DECISION (PROCEED / HOLD / PASS) | C41: =IF(AND(C39=0,C40<=Assumptions!$C$43),"PROCEED",IF(OR(AND(E29="FAIL",E31="FAIL"),C39>=Assumptions!$C$44),"PASS","HOLD")) -> HOLD
A44: Model integrity checks
A45: Check | C45: Value | D45: Status
A46: Scenario probabilities sum to 100% | C46: =Assumptions!$C$121 -> 1 | D46: =IF(ABS(C46-1)<0.0001,"OK","ERROR") -> OK
A47: Credit score weights sum to 100 | C47: =Assumptions!$C$135 -> 100 | D47: =IF(ABS(C47-100)<0.0001,"OK","ERROR") -> OK
A48: Debt roll-forward bridge (sum of abs. differences) | C48: =SUMPRODUCT(ABS('Cash Flow'!$G$23:$K$23)) -> 6.8212103e-13 | D48: =IF(C48<0.001,"OK","ERROR") -> OK
A49: Recovery waterfall: recoveries + equity + costs = value | C49: =Recovery!C89 -> 0 | D49: =IF(ABS(C49)<0.001,"OK","ERROR") -> OK
A50: Detailed tabs reconcile to Calc Engine (sum of abs. diffs) | C50: =SUMPRODUCT(ABS(Scenarios!$E$41:$E$48)) -> 0 | D50: =IF(C50<0.001,"OK","ERROR") -> OK
A51: Formula errors across model tabs (count) | C51: =SUMPRODUCT(--ISERROR('Operating Model'!$C$5:$K$60))+SUMPRODUCT(--ISERROR('Debt Schedule'!$C$5:$K$300))+SUMPRODUCT(--ISERROR('Cash Flow'!$C$5:$K$40))+SUMPRODUCT(--ISERROR('Credit Metrics'!$C$5:$K$120))+SUMPRODUCT(--ISERROR(Recovery!$C$5:$K$300))+SUMPRODUCT(--ISERROR(Returns!$C$5:$K$300))+SUMPRODUCT(--ISERROR(Scenarios!$C$4:$F$60))+SUMPRODUCT(--ISERROR('Capital Structure'!$A$4:$L$60))+SUMPRODUCT(--ISERROR(Sensitivities!$A$4:$J$200))+SUMPRODUCT(--ISERROR('Calc Engine'!$C$5:$K$22254)) -> 0 | D51: =IF(C51=0,"OK","ERROR") -> OK
A52: OVERALL MODEL STATUS | D52: =IF(COUNTIF(D46:D51,"OK")=ROWS(D46:D51),"ALL CHECKS PASS","CHECK MODEL") -> ALL CHECKS PASS

Sheet Sources
A1: Sources — which model input came from which source
A2: DEMO data: fictional and illustrative; there are no filings behind these inputs. Derived values are formulas, never hardcodes.
A4: Source document | B4: Form | C4: Period | D4: Accession | E4: Filed | F4: URL | G4: Retrieved | H4: Data type | I4: Status
A5: Brightwater Retail Holdings — illustrative financial statements FY2022–FY2025 | B5: Income statement / cash flow | C5: FY2022–FY2025 | E5: 2026-03-31 | G5: 2026-03-31 | H5: Income statement / cash flow | I5: DEMO
A6: Brightwater Retail Holdings — illustrative capital structure & covenants | B6: Debt schedule | C6: As of 2026-03-31 | E6: 2026-03-31 | G6: 2026-03-31 | H6: Debt schedule | I6: DEMO
A7: Illustrative indicative bid marks (% of par) | B7: Market price | C7: 2026-03-31 | E7: 2026-03-31 | G7: 2026-03-31 | H7: Market price | I7: DEMO
A9: Analyst notes, derivations and data-quality caveats
A10: • All figures are fictional and illustrative.
A11: Macro: base rate (SOFR) path is an analyst assumption anchored on FRED SOFR; scenario drivers are ANALYST PROJECTIONS; purchase price, fees, hold and covenant thresholds marked hypothetical are UNDERWRITING ASSUMPTIONS.

Sheet Calc Engine
A1: Calc Engine — supporting tab: identical model logic run for all scenarios and sensitivity cases
A2: Cases 1-3 run Base / Downside / Severe simultaneously. Cases 4-63 flex EBITDA margin, revenue growth, SOFR and the distressed multiple (axes on Sensitivities). Same row logic as the detailed tabs; Scenarios › Reconciliation proves the engine ties to them.
A5: CASE 1: Base Case
A6: Scenario index (structural input) | C6: 1
A7: Revenue growth adjustment | C7: 0
A8: EBITDA margin adjustment | C8: 0
A9: SOFR shift | C9: 0
A10: Distressed-multiple shift (x) | C10: 0
A12: Operating drivers (selected scenario → Assumptions)
A13: Model period (year in which the period ends) | F13: =Assumptions!$C$6 -> 2025 | G13: =F13+1 -> 2026 | H13: =G13+1 -> 2027 | I13: =H13+1 -> 2028 | J13: =I13+1 -> 2029 | K13: =J13+1 -> 2030
A14: Projection period # | G14: =G13-Assumptions!$C$6 -> 1 | H14: =H13-Assumptions!$C$6 -> 2 | I14: =I13-Assumptions!$C$6 -> 3 | J14: =J13-Assumptions!$C$6 -> 4 | K14: =K13-Assumptions!$C$6 -> 5
A15: Revenue growth | G15: =CHOOSE($C$6,Assumptions!$G$65,Assumptions!$G$84,Assumptions!$G$103)+$C$7 -> -0.01 | H15: =CHOOSE($C$6,Assumptions!$H$65,Assumptions!$H$84,Assumptions!$H$103)+$C$7 -> -0.01 | I15: =CHOOSE($C$6,Assumptions!$I$65,Assumptions!$I$84,Assumptions!$I$103)+$C$7 -> -0.01 | J15: =CHOOSE($C$6,Assumptions!$J$65,Assumptions!$J$84,Assumptions!$J$103)+$C$7 -> -0.01 | K15: =CHOOSE($C$6,Assumptions!$K$65,Assumptions!$K$84,Assumptions!$K$103)+$C$7 -> -0.01
A16: Gross margin | G16: =CHOOSE($C$6,Assumptions!$G$66,Assumptions!$G$85,Assumptions!$G$104) -> 0.36 | H16: =CHOOSE($C$6,Assumptions!$H$66,Assumptions!$H$85,Assumptions!$H$104) -> 0.362 | I16: =CHOOSE($C$6,Assumptions!$I$66,Assumptions!$I$85,Assumptions!$I$104) -> 0.364 | J16: =CHOOSE($C$6,Assumptions!$J$66,Assumptions!$J$85,Assumptions!$J$104) -> 0.366 | K16: =CHOOSE($C$6,Assumptions!$K$66,Assumptions!$K$85,Assumptions!$K$104) -> 0.368
A17: EBITDA margin | G17: =CHOOSE($C$6,Assumptions!$G$67,Assumptions!$G$86,Assumptions!$G$105)+$C$8 -> 0.065 | H17: =CHOOSE($C$6,Assumptions!$H$67,Assumptions!$H$86,Assumptions!$H$105)+$C$8 -> 0.067 | I17: =CHOOSE($C$6,Assumptions!$I$67,Assumptions!$I$86,Assumptions!$I$105)+$C$8 -> 0.069 | J17: =CHOOSE($C$6,Assumptions!$J$67,Assumptions!$J$86,Assumptions!$J$105)+$C$8 -> 0.071 | K17: =CHOOSE($C$6,Assumptions!$K$67,Assumptions!$K$86,Assumptions!$K$105)+$C$8 -> 0.073
A18: Income statement ($M)
A19: Revenue | F19: ='Historical Financials'!E17 -> 2400 | G19: =F19*(1+G15) -> 2376 | H19: =G19*(1+H15) -> 2352.24 | I19: =H19*(1+I15) -> 2328.7176 | J19: =I19*(1+J15) -> 2305.4304 | K19: =J19*(1+K15) -> 2282.3761
A20: Direct costs / COGS | G20: =G19*(1-G16) -> 1520.64 | H20: =H19*(1-H16) -> 1500.7291 | I20: =I19*(1-I16) -> 1481.0644 | J20: =J19*(1-J16) -> 1461.6429 | K20: =K19*(1-K16) -> 1442.4617
A21: Gross profit (NOI for real estate) | G21: =G19-G20 -> 855.36 | H21: =H19-H20 -> 851.51088 | I21: =I19-I20 -> 847.65321 | J21: =J19-J20 -> 843.78754 | K21: =K19-K20 -> 839.91441
A22: Operating expenses (implied: gross profit − EBITDA) | G22: =G21-G23 -> 700.92 | H22: =H21-H23 -> 693.9108 | I22: =I21-I23 -> 686.97169 | J22: =J21-J23 -> 680.10198 | K22: =K21-K23 -> 673.30096
A23: EBITDA | G23: =G19*G17 -> 154.44 | H23: =H19*H17 -> 157.60008 | I23: =I19*I17 -> 160.68151 | J23: =J19*J17 -> 163.68556 | K23: =K19*K17 -> 166.61346
A24: D&A | G24: =G19*'Historical Financials'!E22/'Historical Financials'!E17 -> 52.272 | H24: =H19*'Historical Financials'!E22/'Historical Financials'!E17 -> 51.74928 | I24: =I19*'Historical Financials'!E22/'Historical Financials'!E17 -> 51.231787 | J24: =J19*'Historical Financials'!E22/'Historical Financials'!E17 -> 50.719469 | K24: =K19*'Historical Financials'!E22/'Historical Financials'!E17 -> 50.212275
A25: Share-based compensation (non-cash) | G25: =G19*'Historical Financials'!E23/'Historical Financials'!E17 -> 0 | H25: =H19*'Historical Financials'!E23/'Historical Financials'!E17 -> 0 | I25: =I19*'Historical Financials'!E23/'Historical Financials'!E17 -> 0 | J25: =J19*'Historical Financials'!E23/'Historical Financials'!E17 -> 0 | K25: =K19*'Historical Financials'!E23/'Historical Financials'!E17 -> 0
A26: EBIT | G26: =G23-G24-G25 -> 102.168 | H26: =H23-H24-H25 -> 105.8508 | I26: =I23-I24-I25 -> 109.44973 | J26: =J23-J24-J25 -> 112.96609 | K26: =K23-K24-K25 -> 116.40118
A27: Cash interest expense (Debt Schedule) | G27: =G53+G66+G79+G92 -> 119.04 | H27: =H53+H66+H79+H92 -> 114.21564 | I27: =I53+I66+I79+I92 -> 126.8792 | J27: =J53+J66+J79+J92 -> 134.74984 | K27: =K53+K66+K79+K92 -> 136.33146
A28: PIK interest (non-cash) | G28: =G54+G67+G80+G93 -> 0 | H28: =H54+H67+H80+H93 -> 0 | I28: =I54+I67+I80+I93 -> 0 | J28: =J54+J67+J80+J93 -> 0 | K28: =K54+K67+K80+K93 -> 0
A29: Interest expense | G29: =G27+G28 -> 119.04 | H29: =H27+H28 -> 114.21564 | I29: =I27+I28 -> 126.8792 | J29: =J27+J28 -> 134.74984 | K29: =K27+K28 -> 136.33146
A30: EBT | G30: =G26-G29 -> -16.872 | H30: =H26-H29 -> -8.36484 | I30: =I26-I29 -> -17.429473 | J30: =J26-J29 -> -21.783745 | K30: =K26-K29 -> -19.930281
A31: Taxes | G31: =MAX(0,G30)*Assumptions!$C$9 -> 0 | H31: =MAX(0,H30)*Assumptions!$C$9 -> 0 | I31: =MAX(0,I30)*Assumptions!$C$9 -> 0 | J31: =MAX(0,J30)*Assumptions!$C$9 -> 0 | K31: =MAX(0,K30)*Assumptions!$C$9 -> 0
A32: Net income (model basis) | G32: =G30-G31 -> -16.872 | H32: =H30-H31 -> -8.36484 | I32: =I30-I31 -> -17.429473 | J32: =J30-J31 -> -21.783745 | K32: =K30-K31 -> -19.930281
A33: Free cash flow build ($M)
A34: Capex | G34: =G19*CHOOSE($C$6,Assumptions!$C$69,Assumptions!$C$88,Assumptions!$C$107) -> 47.52 | H34: =H19*CHOOSE($C$6,Assumptions!$C$69,Assumptions!$C$88,Assumptions!$C$107) -> 47.0448 | I34: =I19*CHOOSE($C$6,Assumptions!$C$69,Assumptions!$C$88,Assumptions!$C$107) -> 46.574352 | J34: =J19*CHOOSE($C$6,Assumptions!$C$69,Assumptions!$C$88,Assumptions!$C$107) -> 46.108608 | K34: =K19*CHOOSE($C$6,Assumptions!$C$69,Assumptions!$C$88,Assumptions!$C$107) -> 45.647522
A35: Working capital & other cash items (+ = outflow) | G35: =CHOOSE($C$6,Assumptions!$C$70,Assumptions!$C$89,Assumptions!$C$108)*(G19-F19)+CHOOSE($C$6,Assumptions!$C$71,Assumptions!$C$90,Assumptions!$C$109)*G19 -> -2.88 | H35: =CHOOSE($C$6,Assumptions!$C$70,Assumptions!$C$89,Assumptions!$C$108)*(H19-G19)+CHOOSE($C$6,Assumptions!$C$71,Assumptions!$C$90,Assumptions!$C$109)*H19 -> -2.8512 | I35: =CHOOSE($C$6,Assumptions!$C$70,Assumptions!$C$89,Assumptions!$C$108)*(I19-H19)+CHOOSE($C$6,Assumptions!$C$71,Assumptions!$C$90,Assumptions!$C$109)*I19 -> -2.822688 | J35: =CHOOSE($C$6,Assumptions!$C$70,Assumptions!$C$89,Assumptions!$C$108)*(J19-I19)+CHOOSE($C$6,Assumptions!$C$71,Assumptions!$C$90,Assumptions!$C$109)*J19 -> -2.7944611 | K35: =CHOOSE($C$6,Assumptions!$C$70,Assumptions!$C$89,Assumptions!$C$108)*(K19-J19)+CHOOSE($C$6,Assumptions!$C$71,Assumptions!$C$90,Assumptions!$C$109)*K19 -> -2.7665165
A36: Free cash flow (NI + D&A + SBC + PIK − capex − ΔNWC/other) | G36: =G32+G24+G25+G28-G34-G35 -> -9.24 | H36: =H32+H24+H25+H28-H34-H35 -> -0.80916 | I36: =I32+I24+I25+I28-I34-I35 -> -9.9493496 | J36: =J32+J24+J25+J28-J34-J35 -> -14.378423 | K36: =K32+K24+K25+K28-K34-K35 -> -12.599012
A38: Rates & market-access (refinancing) test
A39: Base rate (SOFR) | G39: =Assumptions!$G$49 -> 0.0425 | H39: =Assumptions!$H$49 -> 0.04 | I39: =Assumptions!$I$49 -> 0.0375 | J39: =Assumptions!$J$49 -> 0.0375 | K39: =Assumptions!$K$49 -> 0.0375
A40: Floating-rate shock (selected scenario) | C40: =CHOOSE($C$6,Assumptions!$C$72,Assumptions!$C$91,Assumptions!$C$110)+$C$9 -> 0
A41: Refinancing rate (selected scenario) | C41: =CHOOSE($C$6,Assumptions!$C$73,Assumptions!$C$92,Assumptions!$C$111) -> 0.11
A42: Max net leverage to refinance | C42: =CHOOSE($C$6,Assumptions!$C$74,Assumptions!$C$93,Assumptions!$C$112) -> 8.5
A43: Min pro-forma coverage to refinance | C43: =CHOOSE($C$6,Assumptions!$C$75,Assumptions!$C$94,Assumptions!$C$113) -> 1.2
A44: Beginning total debt | G44: =G49+G62+G75+G88 -> 1250 | H44: =H49+H62+H75+H88 -> 1214.24 | I44: =I49+I62+I75+I88 -> 1209.04 | J44: =J49+J62+J75+J88 -> 1224.9985 | K44: =K49+K62+K75+K88 -> 1239.3769
A45: Beginning cash | G45: =F135 -> 45 | H45: =G135 -> 0 | I45: =H135 -> -6.00916 | J45: =I135 -> 0 | K45: =J135 -> 0
A46: Pro-forma interest for refinancing test | G46: =G49*IF(G50=1,$C$41,IF(Assumptions!$I$53=1,MAX(G39,Assumptions!$G$53)+Assumptions!$F$53+$C$40,Assumptions!$E$53))+G62*IF(G63=1,$C$41,IF(Assumptions!$I$54=1,MAX(G39,Assumptions!$G$54)+Assumptions!$F$54+$C$40,Assumptions!$E$54))+G75*IF(G76=1,$C$41,IF(Assumptions!$I$55=1,MAX(G39,Assumptions!$G$55)+Assumptions!$F$55+$C$40,Assumptions!$E$55))+G88*IF(G89=1,$C$41,IF(Assumptions!$I$56=1,MAX(G39,Assumptions!$G$56)+Assumptions!$F$56+$C$40,Assumptions!$E$56)) -> 119.04 | H46: =H49*IF(OR(H50=1,G201=1),$C$41,IF(Assumptions!$I$53=1,MAX(H39,Assumptions!$G$53)+Assumptions!$F$53+$C$40,Assumptions!$E$53))+H62*IF(OR(H63=1,G202=1),$C$41,IF(Assumptions!$I$54=1,MAX(H39,Assumptions!$G$54)+Assumptions!$F$54+$C$40,Assumptions!$E$54))+H75*IF(OR(H76=1,G203=1),$C$41,IF(Assumptions!$I$55=1,MAX(H39,Assumptions!$G$55)+Assumptions!$F$55+$C$40,Assumptions!$E$55))+H88*IF(OR(H89=1,G204=1),$C$41,IF(Assumptions!$I$56=1,MAX(H39,Assumptions!$G$56)+Assumptions!$F$56+$C$40,Assumptions!$E$56)) -> 128.6758 | I46: =I49*IF(OR(I50=1,H201=1),$C$41,IF(Assumptions!$I$53=1,MAX(I39,Assumptions!$G$53)+Assumptions!$F$53+$C$40,Assumptions!$E$53))+I62*IF(OR(I63=1,H202=1),$C$41,IF(Assumptions!$I$54=1,MAX(I39,Assumptions!$G$54)+Assumptions!$F$54+$C$40,Assumptions!$E$54))+I75*IF(OR(I76=1,H203=1),$C$41,IF(Assumptions!$I$55=1,MAX(I39,Assumptions!$G$55)+Assumptions!$F$55+$C$40,Assumptions!$E$55))+I88*IF(OR(I89=1,H204=1),$C$41,IF(Assumptions!$I$56=1,MAX(I39,Assumptions!$G$56)+Assumptions!$F$56+$C$40,Assumptions!$E$56)) -> 132.9944 | J46: =J49*IF(OR(J50=1,I201=1),$C$41,IF(Assumptions!$I$53=1,MAX(J39,Assumptions!$G$53)+Assumptions!$F$53+$C$40,Assumptions!$E$53))+J62*IF(OR(J63=1,I202=1),$C$41,IF(Assumptions!$I$54=1,MAX(J39,Assumptions!$G$54)+Assumptions!$F$54+$C$40,Assumptions!$E$54))+J75*IF(OR(J76=1,I203=1),$C$41,IF(Assumptions!$I$55=1,MAX(J39,Assumptions!$G$55)+Assumptions!$F$55+$C$40,Assumptions!$E$55))+J88*IF(OR(J89=1,I204=1),$C$41,IF(Assumptions!$I$56=1,MAX(J39,Assumptions!$G$56)+Assumptions!$F$56+$C$40,Assumptions!$E$56)) -> 134.74984 | K46: =K49*IF(OR(K50=1,J201=1),$C$41,IF(Assumptions!$I$53=1,MAX(K39,Assumptions!$G$53)+Assumptions!$F$53+$C$40,Assumptions!$E$53))+K62*IF(OR(K63=1,J202=1),$C$41,IF(Assumptions!$I$54=1,MAX(K39,Assumptions!$G$54)+Assumptions!$F$54+$C$40,Assumptions!$E$54))+K75*IF(OR(K76=1,J203=1),$C$41,IF(Assumptions!$I$55=1,MAX(K39,Assumptions!$G$55)+Assumptions!$F$55+$C$40,Assumptions!$E$55))+K88*IF(OR(K89=1,J204=1),$C$41,IF(Assumptions!$I$56=1,MAX(K39,Assumptions!$G$56)+Assumptions!$F$56+$C$40,Assumptions!$E$56)) -> 136.33146
A47: Market access to refinance? (1 = yes) | G47: =IF(G23<=0,0,IF(AND((G44-G45)/G23<=$C$42,G23/G46>=$C$43),1,0)) -> 1 | H47: =IF(H23<=0,0,IF(AND((H44-H45)/H23<=$C$42,H23/H46>=$C$43),1,0)) -> 1 | I47: =IF(I23<=0,0,IF(AND((I44-I45)/I23<=$C$42,I23/I46>=$C$43),1,0)) -> 1 | J47: =IF(J23<=0,0,IF(AND((J44-J45)/J23<=$C$42,J23/J46>=$C$43),1,0)) -> 1 | K47: =IF(K23<=0,0,IF(AND((K44-K45)/K23<=$C$42,K23/K46>=$C$43),1,0)) -> 1
A48: Tranche 1: ABL Revolver
A49: Beginning balance | G49: =F60 -> 180 | H49: =G60 -> 149.44 | I49: =H60 -> 149.44 | J49: =I60 -> 170.59851 | K49: =J60 -> 190.17693
A50: Maturing this period? (1 = yes) | G50: =IF(G13=Assumptions!$K$53,1,0) -> 0 | H50: =IF(H13=Assumptions!$K$53,1,0) -> 1 | I50: =IF(I13=Assumptions!$K$53,1,0) -> 0 | J50: =IF(J13=Assumptions!$K$53,1,0) -> 0 | K50: =IF(K13=Assumptions!$K$53,1,0) -> 0
A52: All-in interest rate applied | G52: =IF(Assumptions!$I$53=1,MAX(G39,Assumptions!$G$53)+Assumptions!$F$53+$C$40,Assumptions!$E$53) -> 0.086 | H52: =IF(G201=1,$C$41,IF(Assumptions!$I$53=1,MAX(H39,Assumptions!$G$53)+Assumptions!$F$53+$C$40,Assumptions!$E$53)) -> 0.0835 | I52: =IF(H201=1,$C$41,IF(Assumptions!$I$53=1,MAX(I39,Assumptions!$G$53)+Assumptions!$F$53+$C$40,Assumptions!$E$53)) -> 0.11 | J52: =IF(I201=1,$C$41,IF(Assumptions!$I$53=1,MAX(J39,Assumptions!$G$53)+Assumptions!$F$53+$C$40,Assumptions!$E$53)) -> 0.11 | K52: =IF(J201=1,$C$41,IF(Assumptions!$I$53=1,MAX(K39,Assumptions!$G$53)+Assumptions!$F$53+$C$40,Assumptions!$E$53)) -> 0.11
A53: Cash interest expense | G53: =G49*G52 -> 15.48 | H53: =H49*H52 -> 12.47824 | I53: =I49*I52 -> 16.4384 | J53: =J49*J52 -> 18.765836 | K53: =K49*K52 -> 20.919463
A54: PIK interest | G54: =G49*Assumptions!$H$53 -> 0 | H54: =H49*Assumptions!$H$53 -> 0 | I54: =I49*Assumptions!$H$53 -> 0 | J54: =J49*Assumptions!$H$53 -> 0 | K54: =K49*Assumptions!$H$53 -> 0
A55: Mandatory amortization | G55: =MIN(G49,Assumptions!$L$53*Assumptions!$C$53) -> 0 | H55: =MIN(H49,Assumptions!$L$53*Assumptions!$C$53) -> 0 | I55: =MIN(I49,Assumptions!$L$53*Assumptions!$C$53) -> 0 | J55: =MIN(J49,Assumptions!$L$53*Assumptions!$C$53) -> 0 | K55: =MIN(K49,Assumptions!$L$53*Assumptions!$C$53) -> 0
A56: New borrowing (revolver draw) | G56: =IF(AND(Assumptions!$P$53=1,G13<Assumptions!$K$53),MIN(MAX(0,-G127),MAX(0,Assumptions!$D$53-G49)),0) -> 0 | H56: =IF(AND(Assumptions!$P$53=1,OR(H13<Assumptions!$K$53,G201=1)),MIN(MAX(0,-H127),MAX(0,Assumptions!$D$53-H49)),0) -> 0 | I56: =IF(AND(Assumptions!$P$53=1,OR(I13<Assumptions!$K$53,H201=1)),MIN(MAX(0,-I127),MAX(0,Assumptions!$D$53-I49)),0) -> 21.15851 | J56: =IF(AND(Assumptions!$P$53=1,OR(J13<Assumptions!$K$53,I201=1)),MIN(MAX(0,-J127),MAX(0,Assumptions!$D$53-J49)),0) -> 19.578423 | K56: =IF(AND(Assumptions!$P$53=1,OR(K13<Assumptions!$K$53,J201=1)),MIN(MAX(0,-K127),MAX(0,Assumptions!$D$53-K49)),0) -> 17.799012
A57: Repayment at maturity (from available cash) | G57: =G50*MIN(G49-G55+G54,MAX(0,G129-Assumptions!$C$12*G47)) -> 0 | H57: =H50*MIN(H49-H55+H54,MAX(0,H129-Assumptions!$C$12*H47)) -> 0 | I57: =I50*MIN(I49-I55+I54,MAX(0,I129-Assumptions!$C$12*I47)) -> 0 | J57: =J50*MIN(J49-J55+J54,MAX(0,J129-Assumptions!$C$12*J47)) -> 0 | K57: =K50*MIN(K49-K55+K54,MAX(0,K129-Assumptions!$C$12*K47)) -> 0
A58: Optional repayment (cash sweep) | G58: =Assumptions!$N$53*MIN(G49+G56+G54-G55-G57,MAX(0,G133)) -> 30.56 | H58: =Assumptions!$N$53*MIN(H49+H56+H54-H55-H57,MAX(0,H133)) -> 0 | I58: =Assumptions!$N$53*MIN(I49+I56+I54-I55-I57,MAX(0,I133)) -> 0 | J58: =Assumptions!$N$53*MIN(J49+J56+J54-J55-J57,MAX(0,J133)) -> 0 | K58: =Assumptions!$N$53*MIN(K49+K56+K54-K55-K57,MAX(0,K133)) -> 0
A59: Unpaid at maturity (no refinancing, insufficient cash) | G59: =G50*(1-G47)*(G49-G55+G54-G57) -> 0 | H59: =H50*(1-H47)*(H49-H55+H54-H57) -> 0 | I59: =I50*(1-I47)*(I49-I55+I54-I57) -> 0 | J59: =J50*(1-J47)*(J49-J55+J54-J57) -> 0 | K59: =K50*(1-K47)*(K49-K55+K54-K57) -> 0
A60: Ending balance | F60: =Assumptions!$C$53 -> 180 | G60: =G49+G56+G54-G55-G57-G58 -> 149.44 | H60: =H49+H56+H54-H55-H57-H58 -> 149.44 | I60: =I49+I56+I54-I55-I57-I58 -> 170.59851 | J60: =J49+J56+J54-J55-J57-J58 -> 190.17693 | K60: =K49+K56+K54-K55-K57-K58 -> 207.97594
A61: Tranche 2: First-Lien Term Loan
A62: Beginning balance | G62: =F73 -> 520 | H62: =G73 -> 514.8 | I62: =H73 -> 509.6 | J62: =I73 -> 504.4 | K62: =J73 -> 499.2
A63: Maturing this period? (1 = yes) | G63: =IF(G13=Assumptions!$K$54,1,0) -> 0 | H63: =IF(H13=Assumptions!$K$54,1,0) -> 0 | I63: =IF(I13=Assumptions!$K$54,1,0) -> 1 | J63: =IF(J13=Assumptions!$K$54,1,0) -> 0 | K63: =IF(K13=Assumptions!$K$54,1,0) -> 0
A65: All-in interest rate applied | G65: =IF(Assumptions!$I$54=1,MAX(G39,Assumptions!$G$54)+Assumptions!$F$54+$C$40,Assumptions!$E$54) -> 0.103 | H65: =IF(G202=1,$C$41,IF(Assumptions!$I$54=1,MAX(H39,Assumptions!$G$54)+Assumptions!$F$54+$C$40,Assumptions!$E$54)) -> 0.1005 | I65: =IF(H202=1,$C$41,IF(Assumptions!$I$54=1,MAX(I39,Assumptions!$G$54)+Assumptions!$F$54+$C$40,Assumptions!$E$54)) -> 0.098 | J65: =IF(I202=1,$C$41,IF(Assumptions!$I$54=1,MAX(J39,Assumptions!$G$54)+Assumptions!$F$54+$C$40,Assumptions!$E$54)) -> 0.11 | K65: =IF(J202=1,$C$41,IF(Assumptions!$I$54=1,MAX(K39,Assumptions!$G$54)+Assumptions!$F$54+$C$40,Assumptions!$E$54)) -> 0.11
A66: Cash interest expense | G66: =G62*G65 -> 53.56 | H66: =H62*H65 -> 51.7374 | I66: =I62*I65 -> 49.9408 | J66: =J62*J65 -> 55.484 | K66: =K62*K65 -> 54.912
A67: PIK interest | G67: =G62*Assumptions!$H$54 -> 0 | H67: =H62*Assumptions!$H$54 -> 0 | I67: =I62*Assumptions!$H$54 -> 0 | J67: =J62*Assumptions!$H$54 -> 0 | K67: =K62*Assumptions!$H$54 -> 0
A68: Mandatory amortization | G68: =MIN(G62,Assumptions!$L$54*Assumptions!$C$54) -> 5.2 | H68: =MIN(H62,Assumptions!$L$54*Assumptions!$C$54) -> 5.2 | I68: =MIN(I62,Assumptions!$L$54*Assumptions!$C$54) -> 5.2 | J68: =MIN(J62,Assumptions!$L$54*Assumptions!$C$54) -> 5.2 | K68: =MIN(K62,Assumptions!$L$54*Assumptions!$C$54) -> 5.2
A69: New borrowing (revolver draw) | G69: =IF(AND(Assumptions!$P$54=1,G13<Assumptions!$K$54),MIN(MAX(0,-G127),MAX(0,Assumptions!$D$54-G62)),0) -> 0 | H69: =IF(AND(Assumptions!$P$54=1,OR(H13<Assumptions!$K$54,G202=1)),MIN(MAX(0,-H127),MAX(0,Assumptions!$D$54-H62)),0) -> 0 | I69: =IF(AND(Assumptions!$P$54=1,OR(I13<Assumptions!$K$54,H202=1)),MIN(MAX(0,-I127),MAX(0,Assumptions!$D$54-I62)),0) -> 0 | J69: =IF(AND(Assumptions!$P$54=1,OR(J13<Assumptions!$K$54,I202=1)),MIN(MAX(0,-J127),MAX(0,Assumptions!$D$54-J62)),0) -> 0 | K69: =IF(AND(Assumptions!$P$54=1,OR(K13<Assumptions!$K$54,J202=1)),MIN(MAX(0,-K127),MAX(0,Assumptions!$D$54-K62)),0) -> 0
A70: Repayment at maturity (from available cash) | G70: =G63*MIN(G62-G68+G67,MAX(0,G129-Assumptions!$C$12*G47-G57)) -> 0 | H70: =H63*MIN(H62-H68+H67,MAX(0,H129-Assumptions!$C$12*H47-H57)) -> 0 | I70: =I63*MIN(I62-I68+I67,MAX(0,I129-Assumptions!$C$12*I47-I57)) -> 0 | J70: =J63*MIN(J62-J68+J67,MAX(0,J129-Assumptions!$C$12*J47-J57)) -> 0 | K70: =K63*MIN(K62-K68+K67,MAX(0,K129-Assumptions!$C$12*K47-K57)) -> 0
A71: Optional repayment (cash sweep) | G71: =Assumptions!$N$54*MIN(G62+G69+G67-G68-G70,MAX(0,G133-G58)) -> 0 | H71: =Assumptions!$N$54*MIN(H62+H69+H67-H68-H70,MAX(0,H133-H58)) -> 0 | I71: =Assumptions!$N$54*MIN(I62+I69+I67-I68-I70,MAX(0,I133-I58)) -> 0 | J71: =Assumptions!$N$54*MIN(J62+J69+J67-J68-J70,MAX(0,J133-J58)) -> 0 | K71: =Assumptions!$N$54*MIN(K62+K69+K67-K68-K70,MAX(0,K133-K58)) -> 0
A72: Unpaid at maturity (no refinancing, insufficient cash) | G72: =G63*(1-G47)*(G62-G68+G67-G70) -> 0 | H72: =H63*(1-H47)*(H62-H68+H67-H70) -> 0 | I72: =I63*(1-I47)*(I62-I68+I67-I70) -> 0 | J72: =J63*(1-J47)*(J62-J68+J67-J70) -> 0 | K72: =K63*(1-K47)*(K62-K68+K67-K70) -> 0
A73: Ending balance | F73: =Assumptions!$C$54 -> 520 | G73: =G62+G69+G67-G68-G70-G71 -> 514.8 | H73: =H62+H69+H67-H68-H70-H71 -> 509.6 | I73: =I62+I69+I67-I68-I70-I71 -> 504.4 | J73: =J62+J69+J67-J68-J70-J71 -> 499.2 | K73: =K62+K69+K67-K68-K70-K71 -> 494
A74: Tranche 3: Second-Lien Notes 11.0%
A75: Beginning balance | G75: =F86 -> 250 | H75: =G86 -> 250 | I75: =H86 -> 250 | J75: =I86 -> 250 | K75: =J86 -> 250
A76: Maturing this period? (1 = yes) | G76: =IF(G13=Assumptions!$K$55,1,0) -> 0 | H76: =IF(H13=Assumptions!$K$55,1,0) -> 0 | I76: =IF(I13=Assumptions!$K$55,1,0) -> 0 | J76: =IF(J13=Assumptions!$K$55,1,0) -> 1 | K76: =IF(K13=Assumptions!$K$55,1,0) -> 0
A78: All-in interest rate applied | G78: =IF(Assumptions!$I$55=1,MAX(G39,Assumptions!$G$55)+Assumptions!$F$55+$C$40,Assumptions!$E$55) -> 0.11 | H78: =IF(G203=1,$C$41,IF(Assumptions!$I$55=1,MAX(H39,Assumptions!$G$55)+Assumptions!$F$55+$C$40,Assumptions!$E$55)) -> 0.11 | I78: =IF(H203=1,$C$41,IF(Assumptions!$I$55=1,MAX(I39,Assumptions!$G$55)+Assumptions!$F$55+$C$40,Assumptions!$E$55)) -> 0.11 | J78: =IF(I203=1,$C$41,IF(Assumptions!$I$55=1,MAX(J39,Assumptions!$G$55)+Assumptions!$F$55+$C$40,Assumptions!$E$55)) -> 0.11 | K78: =IF(J203=1,$C$41,IF(Assumptions!$I$55=1,MAX(K39,Assumptions!$G$55)+Assumptions!$F$55+$C$40,Assumptions!$E$55)) -> 0.11
A79: Cash interest expense | G79: =G75*G78 -> 27.5 | H79: =H75*H78 -> 27.5 | I79: =I75*I78 -> 27.5 | J79: =J75*J78 -> 27.5 | K79: =K75*K78 -> 27.5
A80: PIK interest | G80: =G75*Assumptions!$H$55 -> 0 | H80: =H75*Assumptions!$H$55 -> 0 | I80: =I75*Assumptions!$H$55 -> 0 | J80: =J75*Assumptions!$H$55 -> 0 | K80: =K75*Assumptions!$H$55 -> 0
A81: Mandatory amortization | G81: =MIN(G75,Assumptions!$L$55*Assumptions!$C$55) -> 0 | H81: =MIN(H75,Assumptions!$L$55*Assumptions!$C$55) -> 0 | I81: =MIN(I75,Assumptions!$L$55*Assumptions!$C$55) -> 0 | J81: =MIN(J75,Assumptions!$L$55*Assumptions!$C$55) -> 0 | K81: =MIN(K75,Assumptions!$L$55*Assumptions!$C$55) -> 0
A82: New borrowing (revolver draw) | G82: =IF(AND(Assumptions!$P$55=1,G13<Assumptions!$K$55),MIN(MAX(0,-G127),MAX(0,Assumptions!$D$55-G75)),0) -> 0 | H82: =IF(AND(Assumptions!$P$55=1,OR(H13<Assumptions!$K$55,G203=1)),MIN(MAX(0,-H127),MAX(0,Assumptions!$D$55-H75)),0) -> 0 | I82: =IF(AND(Assumptions!$P$55=1,OR(I13<Assumptions!$K$55,H203=1)),MIN(MAX(0,-I127),MAX(0,Assumptions!$D$55-I75)),0) -> 0 | J82: =IF(AND(Assumptions!$P$55=1,OR(J13<Assumptions!$K$55,I203=1)),MIN(MAX(0,-J127),MAX(0,Assumptions!$D$55-J75)),0) -> 0 | K82: =IF(AND(Assumptions!$P$55=1,OR(K13<Assumptions!$K$55,J203=1)),MIN(MAX(0,-K127),MAX(0,Assumptions!$D$55-K75)),0) -> 0
A83: Repayment at maturity (from available cash) | G83: =G76*MIN(G75-G81+G80,MAX(0,G129-Assumptions!$C$12*G47-G57-G70)) -> 0 | H83: =H76*MIN(H75-H81+H80,MAX(0,H129-Assumptions!$C$12*H47-H57-H70)) -> 0 | I83: =I76*MIN(I75-I81+I80,MAX(0,I129-Assumptions!$C$12*I47-I57-I70)) -> 0 | J83: =J76*MIN(J75-J81+J80,MAX(0,J129-Assumptions!$C$12*J47-J57-J70)) -> 0 | K83: =K76*MIN(K75-K81+K80,MAX(0,K129-Assumptions!$C$12*K47-K57-K70)) -> 0
A84: Optional repayment (cash sweep) | G84: =Assumptions!$N$55*MIN(G75+G82+G80-G81-G83,MAX(0,G133-G58-G71)) -> 0 | H84: =Assumptions!$N$55*MIN(H75+H82+H80-H81-H83,MAX(0,H133-H58-H71)) -> 0 | I84: =Assumptions!$N$55*MIN(I75+I82+I80-I81-I83,MAX(0,I133-I58-I71)) -> 0 | J84: =Assumptions!$N$55*MIN(J75+J82+J80-J81-J83,MAX(0,J133-J58-J71)) -> 0 | K84: =Assumptions!$N$55*MIN(K75+K82+K80-K81-K83,MAX(0,K133-K58-K71)) -> 0
A85: Unpaid at maturity (no refinancing, insufficient cash) | G85: =G76*(1-G47)*(G75-G81+G80-G83) -> 0 | H85: =H76*(1-H47)*(H75-H81+H80-H83) -> 0 | I85: =I76*(1-I47)*(I75-I81+I80-I83) -> 0 | J85: =J76*(1-J47)*(J75-J81+J80-J83) -> 0 | K85: =K76*(1-K47)*(K75-K81+K80-K83) -> 0
A86: Ending balance | F86: =Assumptions!$C$55 -> 250 | G86: =G75+G82+G80-G81-G83-G84 -> 250 | H86: =H75+H82+H80-H81-H83-H84 -> 250 | I86: =I75+I82+I80-I81-I83-I84 -> 250 | J86: =J75+J82+J80-J81-J83-J84 -> 250 | K86: =K75+K82+K80-K81-K83-K84 -> 250
A87: Tranche 4: Senior Unsecured Notes 7.5%
A88: Beginning balance | G88: =F99 -> 300 | H88: =G99 -> 300 | I88: =H99 -> 300 | J88: =I99 -> 300 | K88: =J99 -> 300
A89: Maturing this period? (1 = yes) | G89: =IF(G13=Assumptions!$K$56,1,0) -> 0 | H89: =IF(H13=Assumptions!$K$56,1,0) -> 1 | I89: =IF(I13=Assumptions!$K$56,1,0) -> 0 | J89: =IF(J13=Assumptions!$K$56,1,0) -> 0 | K89: =IF(K13=Assumptions!$K$56,1,0) -> 0
A91: All-in interest rate applied | G91: =IF(Assumptions!$I$56=1,MAX(G39,Assumptions!$G$56)+Assumptions!$F$56+$C$40,Assumptions!$E$56) -> 0.075 | H91: =IF(G204=1,$C$41,IF(Assumptions!$I$56=1,MAX(H39,Assumptions!$G$56)+Assumptions!$F$56+$C$40,Assumptions!$E$56)) -> 0.075 | I91: =IF(H204=1,$C$41,IF(Assumptions!$I$56=1,MAX(I39,Assumptions!$G$56)+Assumptions!$F$56+$C$40,Assumptions!$E$56)) -> 0.11 | J91: =IF(I204=1,$C$41,IF(Assumptions!$I$56=1,MAX(J39,Assumptions!$G$56)+Assumptions!$F$56+$C$40,Assumptions!$E$56)) -> 0.11 | K91: =IF(J204=1,$C$41,IF(Assumptions!$I$56=1,MAX(K39,Assumptions!$G$56)+Assumptions!$F$56+$C$40,Assumptions!$E$56)) -> 0.11
A92: Cash interest expense | G92: =G88*G91 -> 22.5 | H92: =H88*H91 -> 22.5 | I92: =I88*I91 -> 33 | J92: =J88*J91 -> 33 | K92: =K88*K91 -> 33
A93: PIK interest | G93: =G88*Assumptions!$H$56 -> 0 | H93: =H88*Assumptions!$H$56 -> 0 | I93: =I88*Assumptions!$H$56 -> 0 | J93: =J88*Assumptions!$H$56 -> 0 | K93: =K88*Assumptions!$H$56 -> 0
A94: Mandatory amortization | G94: =MIN(G88,Assumptions!$L$56*Assumptions!$C$56) -> 0 | H94: =MIN(H88,Assumptions!$L$56*Assumptions!$C$56) -> 0 | I94: =MIN(I88,Assumptions!$L$56*Assumptions!$C$56) -> 0 | J94: =MIN(J88,Assumptions!$L$56*Assumptions!$C$56) -> 0 | K94: =MIN(K88,Assumptions!$L$56*Assumptions!$C$56) -> 0
A95: New borrowing (revolver draw) | G95: =IF(AND(Assumptions!$P$56=1,G13<Assumptions!$K$56),MIN(MAX(0,-G127),MAX(0,Assumptions!$D$56-G88)),0) -> 0 | H95: =IF(AND(Assumptions!$P$56=1,OR(H13<Assumptions!$K$56,G204=1)),MIN(MAX(0,-H127),MAX(0,Assumptions!$D$56-H88)),0) -> 0 | I95: =IF(AND(Assumptions!$P$56=1,OR(I13<Assumptions!$K$56,H204=1)),MIN(MAX(0,-I127),MAX(0,Assumptions!$D$56-I88)),0) -> 0 | J95: =IF(AND(Assumptions!$P$56=1,OR(J13<Assumptions!$K$56,I204=1)),MIN(MAX(0,-J127),MAX(0,Assumptions!$D$56-J88)),0) -> 0 | K95: =IF(AND(Assumptions!$P$56=1,OR(K13<Assumptions!$K$56,J204=1)),MIN(MAX(0,-K127),MAX(0,Assumptions!$D$56-K88)),0) -> 0
A96: Repayment at maturity (from available cash) | G96: =G89*MIN(G88-G94+G93,MAX(0,G129-Assumptions!$C$12*G47-G57-G70-G83)) -> 0 | H96: =H89*MIN(H88-H94+H93,MAX(0,H129-Assumptions!$C$12*H47-H57-H70-H83)) -> 0 | I96: =I89*MIN(I88-I94+I93,MAX(0,I129-Assumptions!$C$12*I47-I57-I70-I83)) -> 0 | J96: =J89*MIN(J88-J94+J93,MAX(0,J129-Assumptions!$C$12*J47-J57-J70-J83)) -> 0 | K96: =K89*MIN(K88-K94+K93,MAX(0,K129-Assumptions!$C$12*K47-K57-K70-K83)) -> 0
A97: Optional repayment (cash sweep) | G97: =Assumptions!$N$56*MIN(G88+G95+G93-G94-G96,MAX(0,G133-G58-G71-G84)) -> 0 | H97: =Assumptions!$N$56*MIN(H88+H95+H93-H94-H96,MAX(0,H133-H58-H71-H84)) -> 0 | I97: =Assumptions!$N$56*MIN(I88+I95+I93-I94-I96,MAX(0,I133-I58-I71-I84)) -> 0 | J97: =Assumptions!$N$56*MIN(J88+J95+J93-J94-J96,MAX(0,J133-J58-J71-J84)) -> 0 | K97: =Assumptions!$N$56*MIN(K88+K95+K93-K94-K96,MAX(0,K133-K58-K71-K84)) -> 0
A98: Unpaid at maturity (no refinancing, insufficient cash) | G98: =G89*(1-G47)*(G88-G94+G93-G96) -> 0 | H98: =H89*(1-H47)*(H88-H94+H93-H96) -> 0 | I98: =I89*(1-I47)*(I88-I94+I93-I96) -> 0 | J98: =J89*(1-J47)*(J88-J94+J93-J96) -> 0 | K98: =K89*(1-K47)*(K88-K94+K93-K96) -> 0
A99: Ending balance | F99: =Assumptions!$C$56 -> 300 | G99: =G88+G95+G93-G94-G96-G97 -> 300 | H99: =H88+H95+H93-H94-H96-H97 -> 300 | I99: =I88+I95+I93-I94-I96-I97 -> 300 | J99: =J88+J95+J93-J94-J96-J97 -> 300 | K99: =K88+K95+K93-K94-K96-K97 -> 300
A100: Totals
A101: Total debt — ending | F101: =F60+F73+F86+F99 -> 1250 | G101: =G60+G73+G86+G99 -> 1214.24 | H101: =H60+H73+H86+H99 -> 1209.04 | I101: =I60+I73+I86+I99 -> 1224.9985 | J101: =J60+J73+J86+J99 -> 1239.3769 | K101: =K60+K73+K86+K99 -> 1251.9759
A102: Contractual maturities by period (from maturity flags) | G102: =G50*Assumptions!$C$53+G63*Assumptions!$C$54+G76*Assumptions!$C$55+G89*Assumptions!$C$56 -> 0 | H102: =H50*Assumptions!$C$53+H63*Assumptions!$C$54+H76*Assumptions!$C$55+H89*Assumptions!$C$56 -> 480 | I102: =I50*Assumptions!$C$53+I63*Assumptions!$C$54+I76*Assumptions!$C$55+I89*Assumptions!$C$56 -> 520 | J102: =J50*Assumptions!$C$53+J63*Assumptions!$C$54+J76*Assumptions!$C$55+J89*Assumptions!$C$56 -> 250 | K102: =K50*Assumptions!$C$53+K63*Assumptions!$C$54+K76*Assumptions!$C$55+K89*Assumptions!$C$56 -> 0
A103: Refinancing risk engine — result per maturing tranche
A104: Tranche 1: balance at maturity | C104: =SUMPRODUCT($G$50:$K$50,$G$49:$K$49-$G$55:$K$55+$G$54:$K$54) -> 149.44
A105: Tranche 1: repaid from cash at maturity | C105: =SUMPRODUCT($G$50:$K$50,$G$57:$K$57) -> 0
A106: Tranche 1: refinancing test | C106: =IF(SUM($G$50:$K$50)=0,"n/a (beyond horizon)",IF(SUMPRODUCT($G$50:$K$50,$G$47:$K$47)>0,"REFINANCING PASS","REFINANCING FAILURE")) -> REFINANCING PASS
A107: Tranche 1: resolution | C107: =IF(SUM($G$50:$K$50)=0,"n/a",IF(C105>=C104-0.001,"Repaid from cash",IF(SUMPRODUCT($G$50:$K$50,$G$47:$K$47)>0,IF(C105>0,"Partly repaid; remainder refinanced","Refinanced"),IF(SUM($G$59:$K$59)>0.001,IF(C105>0,"Partial repayment; PAYMENT DEFAULT","PAYMENT DEFAULT"),"Repaid from cash")))) -> Refinanced
A108: Tranche 2: balance at maturity | C108: =SUMPRODUCT($G$63:$K$63,$G$62:$K$62-$G$68:$K$68+$G$67:$K$67) -> 504.4
...
