Workbook

Sheet Cover
A1: CreditIQ — Brandywine Realty Trust credit underwriting model
A2: PUBLIC DATA CASE · HYPOTHETICAL INVESTMENT TERMS · $ in millions · as of 2026-06-30
A3: Real estate credit — first-lien secured loan to an office REIT with a 2027–29 maturity wall
A4: Model status | B4: ='Investment Summary'!$D$53 -> ALL CHECKS PASS
A5: Active scenario | B5: =Assumptions!$D$10 -> Downside
A6: Recommendation (rule-based; see Investment Summary) | B6: ='Investment Summary'!$C$4 -> HOLD
A8: Colour conventions
A9: Blue on pale yellow | B9: Hardcoded input: sourced historical data, explicit assumption, scenario / transaction / macro input, covenant threshold, sensitivity axis, structural block parameter.
A10: Black | B10: Formula or calculation. No outputs, subtotals or metrics are hardcoded anywhere in this workbook.
A11: Green | B11: Direct link to a cell on another worksheet.
A12: Grey fill | B12: Labels and headers.
A14: Flow of logic | B14: Assumptions + Historical → Operating Model → Debt Schedule ↔ Cash Flow → Credit Metrics & Covenants → Recovery → Returns → Sensitivities → Investment Summary
A15: Data classes | B15: PUBLIC FILING = reported inputs · ANALYST PROJECTION = scenario drivers · UNDERWRITING ASSUMPTION = hypothetical purchase price / terms · DEMO = fictional
A17: Tabs
A18: Assumptions | B18: All inputs, scenario drivers, covenants, selector
A19: Historical Financials | B19: Sourced statements; derived lines and LTM calculated
A20: Operating Model | B20: Income statement and FCF, history + projection
A21: Debt Schedule | B21: Per-tranche roll-forward, floors, PIK, refinancing test, sweep
A22: Cash Flow | B22: Cash waterfall, funding gap, default test
A23: Credit Metrics | B23: Ratios, covenant compliance, transparent credit score
A24: Scenarios | B24: Base / Downside / Severe side by side + reconciliation
A25: Capital Structure | B25: Tranches, leverage through the stack, maturity wall & refinancing requirement
A26: Recovery | B26: Seniority waterfall with collateral pools and deficiency claims
A27: Returns | B27: Face, price, coupon, yield, recovery; IRR, XIRR, MOIC
A28: Sensitivities | B28: Seven formula-driven tables
A29: Investment Summary | B29: Live outputs, recommendation evidence, integrity checks
... A31: Calc Engine | B31: Supporting: 63 simultaneous model runs
A33: Validation: docs/MODEL_VALIDATION.md · Audit: scripts/audit_model.py · Change-impact harness: scripts/model_harness.py

Sheet Assumptions
A1: Assumptions — Brandywine Realty Trust: all explicit inputs live on this tab
A2: PUBLIC DATA CASE · HYPOTHETICAL INVESTMENT TERMS · Blue on pale yellow = hardcoded input · Black = formula · Green = link to another sheet · $ in millions
A4: 1. General & model settings
A5: Company | C5: Brandywine Realty Trust
A6: Base period label (year in which the base / LTM period ends) | C6: 2026
A7: Fiscal-period end month (12 = calendar FY; 6 = LTM June periods) | C7: 6
A8: As-of / entry date | C8: 46203
A9: Cash tax rate on positive EBT | B9: % of EBT | C9: 0
A10: ACTIVE SCENARIO selector (1=Base, 2=Downside, 3=Severe) | B10: select 1 / 2 / 3 | C10: 2 | D10: =CHOOSE(C10,"Base Case","Downside","Severe Downside") -> Downside
A11: Cash & equivalents at base date (balance sheet) | B11: $M | C11: 37.87
A12: Minimum operating cash | B12: $M | C12: 25
A13: Cash sweep (% of excess cash applied to prepayable debt) | B13: % | C13: 0
A14: Recovery value override (leave blank = model-derived) | B14: $M, optional
A15: Administrative / DIP costs | B15: % of recovery value | C15: 0.04
A16: Accrued unpaid interest included in claims | B16: months | C16: 3
A17: Rank at which secured deficiency claims join general creditors | C17: 99
A18: Maturity alert window | B18: periods from base | C18: 2
A19: Materiality threshold for maturity alert | B19: % of total debt | C19: 0.25
A20: Concentration threshold (single-period maturities) | B20: % of total debt | C20: 0.3
A21: Market-implied EV / EBITDA (analyst assumption) | B21: x | C21: 12.5
A22: Credit score: maturity-risk window | B22: periods | C22: 3
A24: 2. Collateral / asset base (recovery & LTV)
A25: LTM NOI ÷ 7.5% analyst cap rate + construction-in-progress + land held for development + unconsolidated JV book value (6/30/2026). Property values are NOT disclosed in the filings.
A26: Analyst cap rate on LTM NOI | B26: % (assumption) | C26: 0.075
A27: Operating-property value = LTM NOI ÷ cap rate | C27: ='Historical Financials'!G27/Assumptions!$C$26 -> 4020.1467
A28: Construction-in-progress | C28: 85.569 | D28: bdn.cip.2026-06-30
A29: Land held for development | C29: 75.134 | D29: bdn.land.2026-06-30
A30: Investment in unconsolidated real estate ventures (book) | C30: 336.851 | D30: bdn.jv_investment.2026-06-30
A31: Total asset base | C31: =SUM(C27:C30) -> 4517.7007
A33: 3. Transaction / position being underwritten — HYPOTHETICAL INVESTMENT TERMS
A34: Target tranche # (row in the debt table below) | C34: 1
A35: Face value held (legal claim) | B35: $M | C35: 100
A36: Purchase price / OID (UNDERWRITING ASSUMPTION) | B36: % of face | C36: 98
A37: Transaction fees | B37: % of cost | C37: 0.005
A38: Hold period (whole years, 1-5) | B38: periods | C38: 3
A39: Coupon payments per year on target tranche (contractual-timing cross-check only) | B39: per year | C39: 4
A40: Default → recovery cash receipt lag | B40: periods | C40: 1
A41: Required IRR (hurdle) | C41: 0.1
A42: Minimum acceptable downside IRR | C42: 0
A43: Minimum yield to maturity | C43: 0.085
A44: Maximum net leverage (net debt / EBITDA) | C44: 10.5
A45: Minimum downside recovery | C45: 0.9
A46: Minimum covenant headroom (base case) | C46: 0.15
A47: Decision rule: secondary test failures tolerated for PROCEED | B47: count | C47: 2
A48: Decision rule: core test failures that force PASS | B48: count | C48: 3
A49: Unresolved high-priority diligence items (from the CreditIQ diligence tracker) | B49: count | C49: 6
A51: 4. Macro assumptions
A52: Model period | G52: =Assumptions!$C$6+1 -> 2027 | H52: =G52+1 -> 2028 | I52: =H52+1 -> 2029 | J52: =I52+1 -> 2030 | K52: =J52+1 -> 2031
A53: Base rate (SOFR) curve — FRED SOFR 3.90% on 2026-10-06; path is an assumption | B53: % p.a. | G53: 0.039 | H53: 0.0375 | I53: 0.035 | J53: 0.035 | K53: 0.035
A55: 5. Debt tranches (list in order of cash-repayment priority; rank 1 = most senior, equal rank = pari passu)
A56: Facility | B56: Type | C56: Face / principal $M | D56: Commit. $M | E56: Fixed coupon | F56: Spread (floating) | G56: SOFR floor | H56: PIK rate | I56: Floating (1/0) | J56: Maturity date | K56: Maturity period | L56: Amort. % orig | M56: Rank | N56: Prepay (1/0) | O56: Secured (1/0) | P56: Revolver (1/0) | Q56: Collateral share | R56: Mark / price | S56: Call protection / collateral
A57: Hypothetical Senior Secured Term Loan (S+525, 1% floor) | B57: term_loan | C57: 400 | D57: 0 | E57: 0 | F57: 0.0525 | G57: 0.01 | H57: 0 | I57: 1 | J57: 48029 | K57: =YEAR(J57)+IF(MONTH(J57)>Assumptions!$C$7,1,0) -> 2031 | L57: 0.01 | M57: 1 | N57: 0 | O57: 1 | P57: 0 | Q57: 0.3 | R57: 98 | S57: 102 / 101 / par (hypothetical) | First-lien mortgages on a pledged pool of unencumbered properties (assumed 30% of asset value)
A58: Avira Secured Term Loan (swapped to 5.81%) | B58: term_loan | C58: 90 | D58: 0 | E58: 0.0581 | F58: 0 | G58: 0 | H58: 0 | I58: 0 | J58: 48760 | K58: =YEAR(J58)+IF(MONTH(J58)>Assumptions!$C$7,1,0) -> 2033 | L58: 0 | M58: 1 | N58: 0 | O58: 1 | P58: 0 | Q58: 0.033 | R58: 100 | S58: 3025 JFK residential component (assumed collateral value = loan ÷ 60% LTV)
A59: 3151 Market C-PACE Loan | B59: mortgage | C59: 57.324 | D59: 0 | E59: 0.0731 | F59: 0 | G59: 0 | H59: 0 | I59: 0 | J59: 56339 | K59: =YEAR(J59)+IF(MONTH(J59)>Assumptions!$C$7,1,0) -> 2054 | L59: 0 | M59: 1 | N59: 0 | O59: 1 | P59: 0 | Q59: 0.021 | R59: 100 | S59: 3151 Market Street (assumed collateral value = loan ÷ 60% LTV)
A60: Unsecured Revolver ($600M less LCs; hypothetically undrawn pro forma) | B60: revolver | C60: 0 | D60: 574.5 | E60: 0 | F60: 0.015 | G60: 0 | H60: 0 | I60: 1 | J60: 46568 | K60: =YEAR(J60)+IF(MONTH(J60)>Assumptions!$C$7,1,0) -> 2027 | L60: 0 | M60: 2 | N60: 1 | O60: 0 | P60: 1 | Q60: 0 | R60: 100 | S60: Unsecured
A61: 3.95% Guaranteed Notes due Nov-2027 | B61: senior_notes | C61: 450 | D61: 0 | E61: 0.0395 | F61: 0 | G61: 0 | H61: 0 | I61: 0 | J61: 46706 | K61: =YEAR(J61)+IF(MONTH(J61)>Assumptions!$C$7,1,0) -> 2028 | L61: 0 | M61: 2 | N61: 0 | O61: 0 | P61: 0 | Q61: 0 | R61: 100 | S61: Unsecured (guaranteed by Brandywine Realty Trust)
A62: 8.30% Guaranteed Notes due Mar-2028 | B62: senior_notes | C62: 350 | D62: 0 | E62: 0.083 | F62: 0 | G62: 0 | H62: 0 | I62: 0 | J62: 46827 | K62: =YEAR(J62)+IF(MONTH(J62)>Assumptions!$C$7,1,0) -> 2028 | L62: 0 | M62: 2 | N62: 0 | O62: 0 | P62: 0 | Q62: 0 | R62: 100 | S62: Unsecured (guaranteed by Brandywine Realty Trust)
A63: 8.875% Guaranteed Notes due Apr-2029 | B63: senior_notes | C63: 550 | D63: 0 | E63: 0.08875 | F63: 0 | G63: 0 | H63: 0 | I63: 0 | J63: 47223 | K63: =YEAR(J63)+IF(MONTH(J63)>Assumptions!$C$7,1,0) -> 2029 | L63: 0 | M63: 2 | N63: 0 | O63: 0 | P63: 0 | Q63: 0 | R63: 100 | S63: Unsecured (guaranteed by Brandywine Realty Trust)
A64: 4.55% Guaranteed Notes due Oct-2029 | B64: senior_notes | C64: 350 | D64: 0 | E64: 0.0455 | F64: 0 | G64: 0 | H64: 0 | I64: 0 | J64: 47392 | K64: =YEAR(J64)+IF(MONTH(J64)>Assumptions!$C$7,1,0) -> 2030 | L64: 0 | M64: 2 | N64: 0 | O64: 0 | P64: 0 | Q64: 0 | R64: 100 | S64: Unsecured (guaranteed by Brandywine Realty Trust)
A65: 6.125% Guaranteed Notes due Jan-2031 | B65: senior_notes | C65: 300 | D65: 0 | E65: 0.06125 | F65: 0 | G65: 0 | H65: 0 | I65: 0 | J65: 47863 | K65: =YEAR(J65)+IF(MONTH(J65)>Assumptions!$C$7,1,0) -> 2031 | L65: 0 | M65: 2 | N65: 0 | O65: 0 | P65: 0 | Q65: 0 | R65: 100 | S65: Unsecured (guaranteed by Brandywine Realty Trust)
A66: Junior subordinated trust-preferred indentures | B66: subordinated | C66: 78.61 | D66: 0 | E66: 0 | F66: 0.0151 | G66: 0 | H66: 0 | I66: 1 | J66: 49398 | K66: =YEAR(J66)+IF(MONTH(J66)>Assumptions!$C$7,1,0) -> 2035 | L66: 0 | M66: 3 | N66: 0 | O66: 0 | P66: 0 | Q66: 0 | R66: 100 | S66: Unsecured, junior subordinated
A67: Floating tranches: all-in rate = MAX(SOFR, floor) + spread + scenario shock. Fixed: coupon. Interest accrues on beginning balances (no circularity). Maturity period = YEAR(date) + 1 if month > period-end month.
A69: 6. Covenants (thresholds per model period). Disclosed = in issuer documents; Hypothetical = UNDERWRITING ASSUMPTION; inactive covenants are shown for reference only
A70: Covenant | B70: Type | C70: Basis | D70: Active (1/0) | E70: Reported ratio | G70: =Assumptions!$C$6+1 -> 2027 | H70: =G70+1 -> 2028 | I70: =H70+1 -> 2029 | J70: =I70+1 -> 2030 | K70: =J70+1 -> 2031
A71: Credit agreement: leverage ratio ≤ 0.60 (debt ÷ total asset value) — PROXY at analyst cap rate | B71: maxLTV | C71: disclosed | D71: 1 | G71: 0.6 | H71: 0.6 | I71: 0.6 | J71: 0.6 | K71: 0.6
A72: Credit agreement: fixed-charge coverage ≥ 1.5x — PROXY (EBITDA ÷ cash interest) | B72: minInterestCoverage | C72: disclosed | D72: 1 | G72: 1.5 | H72: 1.5 | I72: 1.5 | J72: 1.5 | K72: 1.5
A73: Credit agreement: secured debt ÷ total asset value ≤ 0.40 — PROXY | B73: maxSecuredLTV | C73: disclosed | D73: 1 | G73: 0.4 | H73: 0.4 | I73: 0.4 | J73: 0.4 | K73: 0.4
A74: Hypothetical maintenance covenant on the new loan: min liquidity ($M) | B74: minLiquidity | C74: hypothetical | D74: 1 | G74: 100 | H74: 100 | I74: 100 | J74: 100 | K74: 100
A75: Hypothetical maintenance covenant on the new loan: max net debt / EBITDA | B75: maxNetLeverage | C75: hypothetical | D75: 1 | G75: 10.5 | H75: 10.5 | I75: 10 | J75: 10 | K75: 9.5
A77: 7. Scenario assumptions (selected via ACTIVE SCENARIO; all three run simultaneously on Calc Engine)
A78: Base Case | G78: =Assumptions!$C$6+1 -> 2027 | H78: =G78+1 -> 2028 | I78: =H78+1 -> 2029 | J78: =I78+1 -> 2030 | K78: =J78+1 -> 2031
A79: Revenue growth | G79: -0.03 | H79: 0.02 | I79: 0.02 | J79: 0.02 | K79: 0.02
A80: Gross margin | G80: 0.60392066 | H80: 0.60692066 | I80: 0.60992066 | J80: 0.61192066 | K80: 0.61392066
A81: EBITDA margin | G81: 0.53 | H81: 0.533 | I81: 0.536 | J81: 0.538 | K81: 0.54
A82: Net asset-sale proceeds ($M) | G82: 200 | H82: 0 | I82: 0 | J82: 0 | K82: 0
A83: Capex | B83: % of revenue | C83: 0.22
A84: Working-capital investment | B84: % of Δ revenue | C84: 0
A85: Other cash items (+ outflow; incl. distributions, programming timing) | B85: % of revenue | C85: 0.11
A86: Floating-rate shock | B86: % added to floating rates | C86: 0
A87: Refinancing rate (post-maturity) | B87: % | C87: 0.08
A88: Market access: max net leverage to refinance | B88: x | C88: 11
A89: Market access: min EBITDA / pro-forma interest | B89: x | C89: 1.2
A90: Exit EV / EBITDA multiple | B90: x | C90: 12.5
A91: Exit price if no default (cap, % of face) | B91: % of face | C91: 100
A92: Distressed EV / EBITDA multiple (going concern) | B92: x | C92: 10
A93: Asset value decline | B93: % | C93: 0
A94: Liquidation recovery on asset base | B94: % | C94: 0.85
A95: Scenario probability | C95: 0.5
A97: Downside | G97: =Assumptions!$C$6+1 -> 2027 | H97: =G97+1 -> 2028 | I97: =H97+1 -> 2029 | J97: =I97+1 -> 2030 | K97: =J97+1 -> 2031
A98: Revenue growth | G98: -0.06 | H98: -0.03 | I98: 0 | J98: 0.01 | K98: 0.01
A99: Gross margin | G99: 0.57392066 | H99: 0.55892066 | I99: 0.55892066 | J99: 0.56392066 | K99: 0.56892066
A100: EBITDA margin | G100: 0.5 | H100: 0.485 | I100: 0.485 | J100: 0.49 | K100: 0.495
A101: Net asset-sale proceeds ($M) | G101: 150 | H101: 0 | I101: 0 | J101: 0 | K101: 0
A102: Capex | B102: % of revenue | C102: 0.18
A103: Working-capital investment | B103: % of Δ revenue | C103: 0
A104: Other cash items (+ outflow; incl. distributions, programming timing) | B104: % of revenue | C104: 0.05
A105: Floating-rate shock | B105: % added to floating rates | C105: 0.015
A106: Refinancing rate (post-maturity) | B106: % | C106: 0.1
A107: Market access: max net leverage to refinance | B107: x | C107: 9.5
A108: Market access: min EBITDA / pro-forma interest | B108: x | C108: 1.5
...

Sheet Historical Financials
A1: Historical Financials — Brandywine Realty Trust
A2: PUBLIC FILING data (blue = reported inputs, each traced to a datapoint on the Sources tab). All subtotals, EBITDA, EBIT, net income, FCF and LTM columns are formulas.
A4: US$ millions | B4: FY2023A | C4: FY2024A | D4: FY2025A | E4: H1-25A | F4: H1-26A | G4: LTM Jun-26 | H4: Source datapoint IDs (see Sources tab)
A5: A. Reported inputs
A6: Total revenue | B6: 514.651 | C6: 505.517 | D6: 484.454 | E6: 242.087 | F6: 255.924 | G6: =D6+F6-E6 -> 498.291 | H6: bdn.revenue.* (5 datapoints)
A7: Property operating expenses | B7: 129.885 | C7: 129.89 | D7: 131.347 | E7: 64.891 | F7: 77.094 | G7: =D7+F7-E7 -> 143.55 | H7: bdn.prop_opex.* (5 datapoints)
A8: Real estate taxes | B8: 49.974 | C8: 47.726 | D8: 43.602 | E8: 22.939 | F8: 23.006 | G8: =D8+F8-E8 -> 43.669 | H8: bdn.re_taxes.* (5 datapoints)
A9: Third-party management expenses | B9: 10.088 | C9: 9.714 | D9: 10.245 | E9: 5.117 | F9: 4.433 | G9: =D9+F9-E9 -> 9.561 | H9: bdn.mgmt_exp.* (5 datapoints)
A10: General and administrative expenses | B10: 34.862 | C10: 42.781 | D10: 42.031 | E10: 26.795 | F10: 21.598 | G10: =D10+F10-E10 -> 36.834 | H10: bdn.ga.* (5 datapoints)
A11: Depreciation and amortization | B11: 188.797 | C11: 178.168 | D11: 176.428 | E11: 88.115 | F11: 96.98 | G11: =D11+F11-E11 -> 185.293 | H11: bdn.da.* (5 datapoints)
A12: Interest expense (excl. financing-cost amortization) | B12: 95.456 | C12: 116.306 | D12: 134.955 | E12: 64.19 | F12: 82.82 | G12: =D12+F12-E12 -> 153.585 | H12: bdn.interest_expense.* (5 datapoints)
A13: Income tax provision | B13: 0.072 | C13: 0.014 | D13: 0.112 | E13: 0.085 | F13: 0.024 | G13: =D13+F13-E13 -> 0.051 | H13: bdn.taxes.* (5 datapoints)
A14: Net cash provided by operating activities | B14: 177.273 | C14: 181.125 | D14: 116.701 | E14: 40.704 | F14: 45.821 | G14: =D14+F14-E14 -> 121.818 | H14: bdn.cfo.* (5 datapoints)
A15: Capex: tenant improvements | B15: 48.939 | C15: 72.792 | D15: 74.005 | E15: 39.524 | F15: 33.162 | G15: =D15+F15-E15 -> 67.643 | H15: bdn.capex_ti.* (5 datapoints)
A16: Capex: redevelopments | B16: 59.984 | C16: 18.398 | D16: 6.168 | E16: 4.766 | F16: 1.872 | G16: =D16+F16-E16 -> 3.274 | H16: bdn.capex_redev.* (5 datapoints)
A17: Capex: developments | B17: 47.537 | C17: 38.57 | D17: 33.223 | E17: 17.656 | F17: 26.632 | G17: =D17+F17-E17 -> 42.199 | H17: bdn.capex_dev.* (5 datapoints)
... A22: Share-based compensation add-back (none applied for this company) | B22: 0 | C22: 0 | D22: 0 | E22: 0 | F22: 0 | G22: =D22+F22-E22 -> 0 | H22: none reported
A24: B. Standardized statements (calculated)
A25: Revenue | B25: =B6 -> 514.651 | C25: =C6 -> 505.517 | D25: =D6 -> 484.454 | E25: =E6 -> 242.087 | F25: =F6 -> 255.924 | G25: =G6 -> 498.291
A26: Direct costs / COGS | B26: =B7+B8+B9 -> 189.947 | C26: =C7+C8+C9 -> 187.33 | D26: =D7+D8+D9 -> 185.194 | E26: =E7+E8+E9 -> 92.947 | F26: =F7+F8+F9 -> 104.533 | G26: =G7+G8+G9 -> 196.78
A27: Gross profit (NOI for real estate) | B27: =B25-B26 -> 324.704 | C27: =C25-C26 -> 318.187 | D27: =D25-D26 -> 299.26 | E27: =E25-E26 -> 149.14 | F27: =F25-F26 -> 151.391 | G27: =G25-G26 -> 301.511
A28: Operating expenses, cash & adjusted (excl. D&A and non-cash add-backs) | B28: =B10 -> 34.862 | C28: =C10 -> 42.781 | D28: =D10 -> 42.031 | E28: =E10 -> 26.795 | F28: =F10 -> 21.598 | G28: =G10 -> 36.834
A29: EBITDA (company-adjusted basis) | B29: =B27-B28 -> 289.842 | C29: =C27-C28 -> 275.406 | D29: =D27-D28 -> 257.229 | E29: =E27-E28 -> 122.345 | F29: =F27-F28 -> 129.793 | G29: =G27-G28 -> 264.677
A30: Depreciation & amortization | B30: =B11 -> 188.797 | C30: =C11 -> 178.168 | D30: =D11 -> 176.428 | E30: =E11 -> 88.115 | F30: =F11 -> 96.98 | G30: =G11 -> 185.293
A31: Share-based compensation (non-cash add-back) | B31: =B22 -> 0 | C31: =C22 -> 0 | D31: =D22 -> 0 | E31: =E22 -> 0 | F31: =F22 -> 0 | G31: =G22 -> 0
A32: EBIT (EBITDA − D&A − SBC) | B32: =B29-B30-B31 -> 101.045 | C32: =C29-C30-C31 -> 97.238 | D32: =D29-D30-D31 -> 80.801 | E32: =E29-E30-E31 -> 34.23 | F32: =F29-F30-F31 -> 32.813 | G32: =G29-G30-G31 -> 79.384
A33: Interest expense | B33: =B12 -> 95.456 | C33: =C12 -> 116.306 | D33: =D12 -> 134.955 | E33: =E12 -> 64.19 | F33: =F12 -> 82.82 | G33: =G12 -> 153.585
A34: EBT | B34: =B32-B33 -> 5.589 | C34: =C32-C33 -> -19.068 | D34: =D32-D33 -> -54.154 | E34: =E32-E33 -> -29.96 | F34: =F32-F33 -> -50.007 | G34: =G32-G33 -> -74.201
A35: Income taxes | B35: =B13 -> 0.072 | C35: =C13 -> 0.014 | D35: =D13 -> 0.112 | E35: =E13 -> 0.085 | F35: =F13 -> 0.024 | G35: =G13 -> 0.051
A36: Net income (model basis; excludes impairments and one-offs) | B36: =B34-B35 -> 5.517 | C36: =C34-C35 -> -19.082 | D36: =D34-D35 -> -54.266 | E36: =E34-E35 -> -30.045 | F36: =F34-F35 -> -50.031 | G36: =G34-G35 -> -74.252
A37: Capex (incl. leasing costs where applicable) | B37: =B15+B16+B17+B18 -> 164.339 | C37: =C15+C16+C17+C18 -> 140.317 | D37: =D15+D16+D17+D18 -> 126.145 | E37: =E15+E16+E17+E18 -> 68.672 | F37: =F15+F16+F17+F18 -> 71.552 | G37: =G15+G16+G17+G18 -> 129.025
A38: Net cash provided by operating activities (reported) | B38: =B14 -> 177.273 | C38: =C14 -> 181.125 | D38: =D14 -> 116.701 | E38: =E14 -> 40.704 | F38: =F14 -> 45.821 | G38: =G14 -> 121.818
A39: Free cash flow (CFO − capex) | B39: =B38-B37 -> 12.934 | C39: =C38-C37 -> 40.808 | D39: =D38-D37 -> -9.444 | E39: =E38-E37 -> -27.968 | F39: =F38-F37 -> -25.731 | G39: =G38-G37 -> -7.207
A40: Δ working capital & other (derived plug: NI + D&A + SBC − capex − FCF) | B40: =B36+B30+B31-B37-B39 -> 17.041 | C40: =C36+C30+C31-C37-C39 -> -22.039 | D40: =D36+D30+D31-D37-D39 -> 5.461 | E40: =E36+E30+E31-E37-E39 -> 17.366 | F40: =F36+F30+F31-F37-F39 -> 1.128 | G40: =G36+G30+G31-G37-G39 -> -10.777
A42: C. Ratios & checks (calculated)
A43: Gross margin | B43: =B27/B25 -> 0.63092076 | C43: =C27/C25 -> 0.62942888 | D43: =D27/D25 -> 0.61772635 | E43: =E27/E25 -> 0.61605952 | F43: =F27/F25 -> 0.59154671 | G43: =G27/G25 -> 0.6050902
A44: EBITDA margin | B44: =B29/B25 -> 0.56318165 | C44: =C29/C25 -> 0.54480067 | D44: =D29/D25 -> 0.53096682 | E44: =E29/E25 -> 0.50537617 | F44: =F29/F25 -> 0.50715447 | G44: =G29/G25 -> 0.53116954
A45: Revenue growth (YoY) | C45: =C25/B25-1 -> -0.01774795 | D45: =D25/C25-1 -> -0.041666255 | F45: =F25/E25-1 -> 0.057157138
A46: EBITDA growth (YoY) | C46: =C29/B29-1 -> -0.049806446 | D46: =D29/C29-1 -> -0.066000741 | F46: =F29/E29-1 -> 0.060877028
A47: Check: Calculated NOI (revenue − direct costs) vs company-reported NOI (should be 0.000) | B47: =B27-B21 -> 0 | C47: =C27-C21 -> 0 | D47: =D27-D21 -> 0

Sheet Operating Model
A1: Operating Model — selected scenario (assumptions → statements)
A2: ="Brandywine Realty Trust · PUBLIC DATA CASE · HYPOTHETICAL INVESTMENT TERMS · Active scenario: "&Assumptions!$D$10 -> Brandywine Realty Trust · PUBLIC DATA CASE · HYPOTHETICAL INVESTMENT TERMS · Active scenario: Downside
A4: $M | C4: FY2023A | D4: FY2024A | E4: FY2025A | F4: LTM Jun-26 | G4: LTM Jun-27E | H4: LTM Jun-28E | I4: LTM Jun-29E | J4: LTM Jun-30E | K4: LTM Jun-31E
A6: Operating drivers (selected scenario → Assumptions)
A7: Model period (year in which the period ends) | C7: =D7-1 -> 2023 | D7: =E7-1 -> 2024 | E7: =F7-1 -> 2025 | F7: =Assumptions!$C$6 -> 2026 | G7: =F7+1 -> 2027 | H7: =G7+1 -> 2028 | I7: =H7+1 -> 2029 | J7: =I7+1 -> 2030 | K7: =J7+1 -> 2031
A8: Projection period # | G8: =G7-Assumptions!$C$6 -> 1 | H8: =H7-Assumptions!$C$6 -> 2 | I8: =I7-Assumptions!$C$6 -> 3 | J8: =J7-Assumptions!$C$6 -> 4 | K8: =K7-Assumptions!$C$6 -> 5
A9: Revenue growth | G9: =CHOOSE(Assumptions!$C$10,Assumptions!$G$79,Assumptions!$G$98,Assumptions!$G$117) -> -0.06 | H9: =CHOOSE(Assumptions!$C$10,Assumptions!$H$79,Assumptions!$H$98,Assumptions!$H$117) -> -0.03 | I9: =CHOOSE(Assumptions!$C$10,Assumptions!$I$79,Assumptions!$I$98,Assumptions!$I$117) -> 0 | J9: =CHOOSE(Assumptions!$C$10,Assumptions!$J$79,Assumptions!$J$98,Assumptions!$J$117) -> 0.01 | K9: =CHOOSE(Assumptions!$C$10,Assumptions!$K$79,Assumptions!$K$98,Assumptions!$K$117) -> 0.01
A10: Gross margin | G10: =CHOOSE(Assumptions!$C$10,Assumptions!$G$80,Assumptions!$G$99,Assumptions!$G$118) -> 0.57392066 | H10: =CHOOSE(Assumptions!$C$10,Assumptions!$H$80,Assumptions!$H$99,Assumptions!$H$118) -> 0.55892066 | I10: =CHOOSE(Assumptions!$C$10,Assumptions!$I$80,Assumptions!$I$99,Assumptions!$I$118) -> 0.55892066 | J10: =CHOOSE(Assumptions!$C$10,Assumptions!$J$80,Assumptions!$J$99,Assumptions!$J$118) -> 0.56392066 | K10: =CHOOSE(Assumptions!$C$10,Assumptions!$K$80,Assumptions!$K$99,Assumptions!$K$118) -> 0.56892066
A11: EBITDA margin | G11: =CHOOSE(Assumptions!$C$10,Assumptions!$G$81,Assumptions!$G$100,Assumptions!$G$119) -> 0.5 | H11: =CHOOSE(Assumptions!$C$10,Assumptions!$H$81,Assumptions!$H$100,Assumptions!$H$119) -> 0.485 | I11: =CHOOSE(Assumptions!$C$10,Assumptions!$I$81,Assumptions!$I$100,Assumptions!$I$119) -> 0.485 | J11: =CHOOSE(Assumptions!$C$10,Assumptions!$J$81,Assumptions!$J$100,Assumptions!$J$119) -> 0.49 | K11: =CHOOSE(Assumptions!$C$10,Assumptions!$K$81,Assumptions!$K$100,Assumptions!$K$119) -> 0.495
A12: Income statement ($M)
A13: Revenue | C13: ='Historical Financials'!B25 -> 514.651 | D13: ='Historical Financials'!C25 -> 505.517 | E13: ='Historical Financials'!D25 -> 484.454 | F13: ='Historical Financials'!G25 -> 498.291 | G13: =F13*(1+G9) -> 468.39354 | H13: =G13*(1+H9) -> 454.34173 | I13: =H13*(1+I9) -> 454.34173 | J13: =I13*(1+J9) -> 458.88515 | K13: =J13*(1+K9) -> 463.474
A14: Direct costs / COGS | C14: ='Historical Financials'!B26 -> 189.947 | D14: ='Historical Financials'!C26 -> 187.33 | E14: ='Historical Financials'!D26 -> 185.194 | F14: ='Historical Financials'!G26 -> 196.78 | G14: =G13*(1-G10) -> 199.57281 | H14: =H13*(1-H10) -> 200.40075 | I14: =I13*(1-I10) -> 200.40075 | J14: =J13*(1-J10) -> 200.11033 | K14: =K13*(1-K10) -> 199.79407
A15: Gross profit (NOI for real estate) | C15: =C13-C14 -> 324.704 | D15: =D13-D14 -> 318.187 | E15: =E13-E14 -> 299.26 | F15: =F13-F14 -> 301.511 | G15: =G13-G14 -> 268.82073 | H15: =H13-H14 -> 253.94098 | I15: =I13-I14 -> 253.94098 | J15: =J13-J14 -> 258.77482 | K15: =K13-K14 -> 263.67994
A16: Operating expenses (implied: gross profit − EBITDA) | C16: ='Historical Financials'!B28 -> 34.862 | D16: ='Historical Financials'!C28 -> 42.781 | E16: ='Historical Financials'!D28 -> 42.031 | F16: ='Historical Financials'!G28 -> 36.834 | G16: =G15-G17 -> 34.62396 | H16: =H15-H17 -> 33.585241 | I16: =I15-I17 -> 33.585241 | J16: =J15-J17 -> 33.921094 | K16: =K15-K17 -> 34.260305
A17: EBITDA | C17: =C15-C16 -> 289.842 | D17: =D15-D16 -> 275.406 | E17: =E15-E16 -> 257.229 | F17: =F15-F16 -> 264.677 | G17: =G13*G11 -> 234.19677 | H17: =H13*H11 -> 220.35574 | I17: =I13*I11 -> 220.35574 | J17: =J13*J11 -> 224.85372 | K17: =K13*K11 -> 229.41963
A18: D&A | C18: ='Historical Financials'!B30 -> 188.797 | D18: ='Historical Financials'!C30 -> 178.168 | E18: ='Historical Financials'!D30 -> 176.428 | F18: ='Historical Financials'!G30 -> 185.293 | G18: =G13*'Historical Financials'!G30/'Historical Financials'!G25 -> 174.17542 | H18: =H13*'Historical Financials'!G30/'Historical Financials'!G25 -> 168.95016 | I18: =I13*'Historical Financials'!G30/'Historical Financials'!G25 -> 168.95016 | J18: =J13*'Historical Financials'!G30/'Historical Financials'!G25 -> 170.63966 | K18: =K13*'Historical Financials'!G30/'Historical Financials'!G25 -> 172.34606
A19: Share-based compensation (non-cash) | C19: ='Historical Financials'!B31 -> 0 | D19: ='Historical Financials'!C31 -> 0 | E19: ='Historical Financials'!D31 -> 0 | F19: ='Historical Financials'!G31 -> 0 | G19: =G13*'Historical Financials'!G31/'Historical Financials'!G25 -> 0 | H19: =H13*'Historical Financials'!G31/'Historical Financials'!G25 -> 0 | I19: =I13*'Historical Financials'!G31/'Historical Financials'!G25 -> 0 | J19: =J13*'Historical Financials'!G31/'Historical Financials'!G25 -> 0 | K19: =K13*'Historical Financials'!G31/'Historical Financials'!G25 -> 0
A20: EBIT | C20: =C17-C18-C19 -> 101.045 | D20: =D17-D18-D19 -> 97.238 | E20: =E17-E18-E19 -> 80.801 | F20: =F17-F18-F19 -> 79.384 | G20: =G17-G18-G19 -> 60.02135 | H20: =H17-H18-H19 -> 51.405583 | I20: =I17-I18-I19 -> 51.405583 | J20: =J17-J18-J19 -> 54.214065 | K20: =K17-K18-K19 -> 57.073576
A21: Cash interest expense (Debt Schedule) | G21: ='Debt Schedule'!G21+'Debt Schedule'!G34+'Debt Schedule'!G47+'Debt Schedule'!G60+'Debt Schedule'!G73+'Debt Schedule'!G86+'Debt Schedule'!G99+'Debt Schedule'!G112+'Debt Schedule'!G125+'Debt Schedule'!G138 -> 187.38884 | H21: ='Debt Schedule'!H21+'Debt Schedule'!H34+'Debt Schedule'!H47+'Debt Schedule'!H60+'Debt Schedule'!H73+'Debt Schedule'!H86+'Debt Schedule'!H99+'Debt Schedule'!H112+'Debt Schedule'!H125+'Debt Schedule'!H138 -> 186.25092 | I21: ='Debt Schedule'!I21+'Debt Schedule'!I34+'Debt Schedule'!I47+'Debt Schedule'!I60+'Debt Schedule'!I73+'Debt Schedule'!I86+'Debt Schedule'!I99+'Debt Schedule'!I112+'Debt Schedule'!I125+'Debt Schedule'!I138 -> 182.73653 | J21: ='Debt Schedule'!J21+'Debt Schedule'!J34+'Debt Schedule'!J47+'Debt Schedule'!J60+'Debt Schedule'!J73+'Debt Schedule'!J86+'Debt Schedule'!J99+'Debt Schedule'!J112+'Debt Schedule'!J125+'Debt Schedule'!J138 -> 182.32653 | K21: ='Debt Schedule'!K21+'Debt Schedule'!K34+'Debt Schedule'!K47+'Debt Schedule'!K60+'Debt Schedule'!K73+'Debt Schedule'!K86+'Debt Schedule'!K99+'Debt Schedule'!K112+'Debt Schedule'!K125+'Debt Schedule'!K138 -> 181.91653
A22: PIK interest (non-cash) | G22: ='Debt Schedule'!G22+'Debt Schedule'!G35+'Debt Schedule'!G48+'Debt Schedule'!G61+'Debt Schedule'!G74+'Debt Schedule'!G87+'Debt Schedule'!G100+'Debt Schedule'!G113+'Debt Schedule'!G126+'Debt Schedule'!G139 -> 0 | H22: ='Debt Schedule'!H22+'Debt Schedule'!H35+'Debt Schedule'!H48+'Debt Schedule'!H61+'Debt Schedule'!H74+'Debt Schedule'!H87+'Debt Schedule'!H100+'Debt Schedule'!H113+'Debt Schedule'!H126+'Debt Schedule'!H139 -> 0 | I22: ='Debt Schedule'!I22+'Debt Schedule'!I35+'Debt Schedule'!I48+'Debt Schedule'!I61+'Debt Schedule'!I74+'Debt Schedule'!I87+'Debt Schedule'!I100+'Debt Schedule'!I113+'Debt Schedule'!I126+'Debt Schedule'!I139 -> 0 | J22: ='Debt Schedule'!J22+'Debt Schedule'!J35+'Debt Schedule'!J48+'Debt Schedule'!J61+'Debt Schedule'!J74+'Debt Schedule'!J87+'Debt Schedule'!J100+'Debt Schedule'!J113+'Debt Schedule'!J126+'Debt Schedule'!J139 -> 0 | K22: ='Debt Schedule'!K22+'Debt Schedule'!K35+'Debt Schedule'!K48+'Debt Schedule'!K61+'Debt Schedule'!K74+'Debt Schedule'!K87+'Debt Schedule'!K100+'Debt Schedule'!K113+'Debt Schedule'!K126+'Debt Schedule'!K139 -> 0
A23: Interest expense | C23: ='Historical Financials'!B33 -> 95.456 | D23: ='Historical Financials'!C33 -> 116.306 | E23: ='Historical Financials'!D33 -> 134.955 | F23: ='Historical Financials'!G33 -> 153.585 | G23: =G21+G22 -> 187.38884 | H23: =H21+H22 -> 186.25092 | I23: =I21+I22 -> 182.73653 | J23: =J21+J22 -> 182.32653 | K23: =K21+K22 -> 181.91653
A24: EBT | C24: =C20-C23 -> 5.589 | D24: =D20-D23 -> -19.068 | E24: =E20-E23 -> -54.154 | F24: =F20-F23 -> -74.201 | G24: =G20-G23 -> -127.36749 | H24: =H20-H23 -> -134.84534 | I24: =I20-I23 -> -131.33094 | J24: =J20-J23 -> -128.11246 | K24: =K20-K23 -> -124.84295
A25: Taxes | C25: ='Historical Financials'!B35 -> 0.072 | D25: ='Historical Financials'!C35 -> 0.014 | E25: ='Historical Financials'!D35 -> 0.112 | F25: ='Historical Financials'!G35 -> 0.051 | G25: =MAX(0,G24)*Assumptions!$C$9 -> 0 | H25: =MAX(0,H24)*Assumptions!$C$9 -> 0 | I25: =MAX(0,I24)*Assumptions!$C$9 -> 0 | J25: =MAX(0,J24)*Assumptions!$C$9 -> 0 | K25: =MAX(0,K24)*Assumptions!$C$9 -> 0
A26: Net income (model basis) | C26: =C24-C25 -> 5.517 | D26: =D24-D25 -> -19.082 | E26: =E24-E25 -> -54.266 | F26: =F24-F25 -> -74.252 | G26: =G24-G25 -> -127.36749 | H26: =H24-H25 -> -134.84534 | I26: =I24-I25 -> -131.33094 | J26: =J24-J25 -> -128.11246 | K26: =K24-K25 -> -124.84295
A27: Free cash flow build ($M)
A28: Capex | C28: ='Historical Financials'!B37 -> 164.339 | D28: ='Historical Financials'!C37 -> 140.317 | E28: ='Historical Financials'!D37 -> 126.145 | F28: ='Historical Financials'!G37 -> 129.025 | G28: =G13*CHOOSE(Assumptions!$C$10,Assumptions!$C$83,Assumptions!$C$102,Assumptions!$C$121) -> 84.310837 | H28: =H13*CHOOSE(Assumptions!$C$10,Assumptions!$C$83,Assumptions!$C$102,Assumptions!$C$121) -> 81.781512 | I28: =I13*CHOOSE(Assumptions!$C$10,Assumptions!$C$83,Assumptions!$C$102,Assumptions!$C$121) -> 81.781512 | J28: =J13*CHOOSE(Assumptions!$C$10,Assumptions!$C$83,Assumptions!$C$102,Assumptions!$C$121) -> 82.599327 | K28: =K13*CHOOSE(Assumptions!$C$10,Assumptions!$C$83,Assumptions!$C$102,Assumptions!$C$121) -> 83.42532
A29: Working capital & other cash items (+ = outflow) | C29: ='Historical Financials'!B40 -> 17.041 | D29: ='Historical Financials'!C40 -> -22.039 | E29: ='Historical Financials'!D40 -> 5.461 | F29: ='Historical Financials'!G40 -> -10.777 | G29: =CHOOSE(Assumptions!$C$10,Assumptions!$C$84,Assumptions!$C$103,Assumptions!$C$122)*(G13-F13)+CHOOSE(Assumptions!$C$10,Assumptions!$C$85,Assumptions!$C$104,Assumptions!$C$123)*G13 -> 23.419677 | H29: =CHOOSE(Assumptions!$C$10,Assumptions!$C$84,Assumptions!$C$103,Assumptions!$C$122)*(H13-G13)+CHOOSE(Assumptions!$C$10,Assumptions!$C$85,Assumptions!$C$104,Assumptions!$C$123)*H13 -> 22.717087 | I29: =CHOOSE(Assumptions!$C$10,Assumptions!$C$84,Assumptions!$C$103,Assumptions!$C$122)*(I13-H13)+CHOOSE(Assumptions!$C$10,Assumptions!$C$85,Assumptions!$C$104,Assumptions!$C$123)*I13 -> 22.717087 | J29: =CHOOSE(Assumptions!$C$10,Assumptions!$C$84,Assumptions!$C$103,Assumptions!$C$122)*(J13-I13)+CHOOSE(Assumptions!$C$10,Assumptions!$C$85,Assumptions!$C$104,Assumptions!$C$123)*J13 -> 22.944258 | K29: =CHOOSE(Assumptions!$C$10,Assumptions!$C$84,Assumptions!$C$103,Assumptions!$C$122)*(K13-J13)+CHOOSE(Assumptions!$C$10,Assumptions!$C$85,Assumptions!$C$104,Assumptions!$C$123)*K13 -> 23.1737
A30: Free cash flow (NI + D&A + SBC + PIK − capex − ΔNWC/other) | C30: ='Historical Financials'!B39 -> 12.934 | D30: ='Historical Financials'!C39 -> 40.808 | E30: ='Historical Financials'!D39 -> -9.444 | F30: ='Historical Financials'!G39 -> -7.207 | G30: =G26+G18+G19+G22-G28-G29 -> -60.92258 | H30: =H26+H18+H19+H22-H28-H29 -> -70.393778 | I30: =I26+I18+I19+I22-I28-I29 -> -66.879384 | J30: =J26+J18+J19+J22-J28-J29 -> -63.016387 | K30: =K26+K18+K19+K22-K28-K29 -> -59.095916

Sheet Debt Schedule
A1: Debt Schedule — tranche roll-forward, rates, PIK, refinancing test, cash sweep
A2: ="Brandywine Realty Trust · PUBLIC DATA CASE · HYPOTHETICAL INVESTMENT TERMS · Active scenario: "&Assumptions!$D$10 -> Brandywine Realty Trust · PUBLIC DATA CASE · HYPOTHETICAL INVESTMENT TERMS · Active scenario: Downside
A4: $M | C4: FY2023A | D4: FY2024A | E4: FY2025A | F4: LTM Jun-26 | G4: LTM Jun-27E | H4: LTM Jun-28E | I4: LTM Jun-29E | J4: LTM Jun-30E | K4: LTM Jun-31E
A6: Rates & market-access (refinancing) test
A7: Base rate (SOFR) | G7: =Assumptions!$G$53 -> 0.039 | H7: =Assumptions!$H$53 -> 0.0375 | I7: =Assumptions!$I$53 -> 0.035 | J7: =Assumptions!$J$53 -> 0.035 | K7: =Assumptions!$K$53 -> 0.035
A8: Floating-rate shock (selected scenario) | C8: =CHOOSE(Assumptions!$C$10,Assumptions!$C$86,Assumptions!$C$105,Assumptions!$C$124) -> 0.015
A9: Refinancing rate (selected scenario) | C9: =CHOOSE(Assumptions!$C$10,Assumptions!$C$87,Assumptions!$C$106,Assumptions!$C$125) -> 0.1
A10: Max net leverage to refinance | C10: =CHOOSE(Assumptions!$C$10,Assumptions!$C$88,Assumptions!$C$107,Assumptions!$C$126) -> 9.5
A11: Min pro-forma coverage to refinance | C11: =CHOOSE(Assumptions!$C$10,Assumptions!$C$89,Assumptions!$C$108,Assumptions!$C$127) -> 1.5
A12: Beginning total debt | G12: =G17+G30+G43+G56+G69+G82+G95+G108+G121+G134 -> 2625.934 | H12: =H17+H30+H43+H56+H69+H82+H95+H108+H121+H134 -> 2621.934 | I12: =I17+I30+I43+I56+I69+I82+I95+I108+I121+I134 -> 2569.3804 | J12: =J17+J30+J43+J56+J69+J82+J95+J108+J121+J134 -> 2565.3804 | K12: =K17+K30+K43+K56+K69+K82+K95+K108+K121+K134 -> 2561.3804
A13: Beginning cash | G13: ='Cash Flow'!F19 -> 37.87 | H13: ='Cash Flow'!G19 -> 122.94742 | I13: ='Cash Flow'!H19 -> 0 | J13: ='Cash Flow'!I19 -> -70.879384 | K13: ='Cash Flow'!J19 -> -137.89577
A14: Pro-forma interest for refinancing test | G14: =G17*IF(G18=1,$C$9,IF(Assumptions!$I$57=1,MAX(G7,Assumptions!$G$57)+Assumptions!$F$57+$C$8,Assumptions!$E$57))+G30*IF(G31=1,$C$9,IF(Assumptions!$I$58=1,MAX(G7,Assumptions!$G$58)+Assumptions!$F$58+$C$8,Assumptions!$E$58))+G43*IF(G44=1,$C$9,IF(Assumptions!$I$59=1,MAX(G7,Assumptions!$G$59)+Assumptions!$F$59+$C$8,Assumptions!$E$59))+G56*IF(G57=1,$C$9,IF(Assumptions!$I$60=1,MAX(G7,Assumptions!$G$60)+Assumptions!$F$60+$C$8,Assumptions!$E$60))+G69*IF(G70=1,$C$9,IF(Assumptions!$I$61=1,MAX(G7,Assumptions!$G$61)+Assumptions!$F$61+$C$8,Assumptions!$E$61))+G82*IF(G83=1,$C$9,IF(Assumptions!$I$62=1,MAX(G7,Assumptions!$G$62)+Assumptions!$F$62+$C$8,Assumptions!$E$62))+G95*IF(G96=1,$C$9,IF(Assumptions!$I$63=1,MAX(G7,Assumptions!$G$63)+Assumptions!$F$63+$C$8,Assumptions!$E$63))+G108*IF(G109=1,$C$9,IF(Assumptions!$I$64=1,MAX(G7,Assumptions!$G$64)+Assumptions!$F$64+$C$8,Assumptions!$E$64))+G121*IF(G122=1,$C$9,IF(Assumptions!$I$65=1,MAX(G7,Assumptions!$G$65)+Assumptions!$F$65+$C$8,Assumptions!$E$65))+G134*IF(G135=1,$C$9,IF(Assumptions!$I$66=1,MAX(G7,Assumptions!$G$66)+Assumptions!$F$66+$C$8,Assumptions!$E$66)) -> 187.38884 | H14: =H17*IF(OR(H18=1,Recovery!G63=1),$C$9,IF(Assumptions!$I$57=1,MAX(H7,Assumptions!$G$57)+Assumptions!$F$57+$C$8,Assumptions!$E$57))+H30*IF(OR(H31=1,Recovery!G64=1),$C$9,IF(Assumptions!$I$58=1,MAX(H7,Assumptions!$G$58)+Assumptions!$F$58+$C$8,Assumptions!$E$58))+H43*IF(OR(H44=1,Recovery!G65=1),$C$9,IF(Assumptions!$I$59=1,MAX(H7,Assumptions!$G$59)+Assumptions!$F$59+$C$8,Assumptions!$E$59))+H56*IF(OR(H57=1,Recovery!G66=1),$C$9,IF(Assumptions!$I$60=1,MAX(H7,Assumptions!$G$60)+Assumptions!$F$60+$C$8,Assumptions!$E$60))+H69*IF(OR(H70=1,Recovery!G67=1),$C$9,IF(Assumptions!$I$61=1,MAX(H7,Assumptions!$G$61)+Assumptions!$F$61+$C$8,Assumptions!$E$61))+H82*IF(OR(H83=1,Recovery!G68=1),$C$9,IF(Assumptions!$I$62=1,MAX(H7,Assumptions!$G$62)+Assumptions!$F$62+$C$8,Assumptions!$E$62))+H95*IF(OR(H96=1,Recovery!G69=1),$C$9,IF(Assumptions!$I$63=1,MAX(H7,Assumptions!$G$63)+Assumptions!$F$63+$C$8,Assumptions!$E$63))+H108*IF(OR(H109=1,Recovery!G70=1),$C$9,IF(Assumptions!$I$64=1,MAX(H7,Assumptions!$G$64)+Assumptions!$F$64+$C$8,Assumptions!$E$64))+H121*IF(OR(H122=1,Recovery!G71=1),$C$9,IF(Assumptions!$I$65=1,MAX(H7,Assumptions!$G$65)+Assumptions!$F$65+$C$8,Assumptions!$E$65))+H134*IF(OR(H135=1,Recovery!G72=1),$C$9,IF(Assumptions!$I$66=1,MAX(H7,Assumptions!$G$66)+Assumptions!$F$66+$C$8,Assumptions!$E$66)) -> 219.42592 | I14: =I17*IF(OR(I18=1,Recovery!H63=1),$C$9,IF(Assumptions!$I$57=1,MAX(I7,Assumptions!$G$57)+Assumptions!$F$57+$C$8,Assumptions!$E$57))+I30*IF(OR(I31=1,Recovery!H64=1),$C$9,IF(Assumptions!$I$58=1,MAX(I7,Assumptions!$G$58)+Assumptions!$F$58+$C$8,Assumptions!$E$58))+I43*IF(OR(I44=1,Recovery!H65=1),$C$9,IF(Assumptions!$I$59=1,MAX(I7,Assumptions!$G$59)+Assumptions!$F$59+$C$8,Assumptions!$E$59))+I56*IF(OR(I57=1,Recovery!H66=1),$C$9,IF(Assumptions!$I$60=1,MAX(I7,Assumptions!$G$60)+Assumptions!$F$60+$C$8,Assumptions!$E$60))+I69*IF(OR(I70=1,Recovery!H67=1),$C$9,IF(Assumptions!$I$61=1,MAX(I7,Assumptions!$G$61)+Assumptions!$F$61+$C$8,Assumptions!$E$61))+I82*IF(OR(I83=1,Recovery!H68=1),$C$9,IF(Assumptions!$I$62=1,MAX(I7,Assumptions!$G$62)+Assumptions!$F$62+$C$8,Assumptions!$E$62))+I95*IF(OR(I96=1,Recovery!H69=1),$C$9,IF(Assumptions!$I$63=1,MAX(I7,Assumptions!$G$63)+Assumptions!$F$63+$C$8,Assumptions!$E$63))+I108*IF(OR(I109=1,Recovery!H70=1),$C$9,IF(Assumptions!$I$64=1,MAX(I7,Assumptions!$G$64)+Assumptions!$F$64+$C$8,Assumptions!$E$64))+I121*IF(OR(I122=1,Recovery!H71=1),$C$9,IF(Assumptions!$I$65=1,MAX(I7,Assumptions!$G$65)+Assumptions!$F$65+$C$8,Assumptions!$E$65))+I134*IF(OR(I135=1,Recovery!H72=1),$C$9,IF(Assumptions!$I$66=1,MAX(I7,Assumptions!$G$66)+Assumptions!$F$66+$C$8,Assumptions!$E$66)) -> 188.92403 | J14: =J17*IF(OR(J18=1,Recovery!I63=1),$C$9,IF(Assumptions!$I$57=1,MAX(J7,Assumptions!$G$57)+Assumptions!$F$57+$C$8,Assumptions!$E$57))+J30*IF(OR(J31=1,Recovery!I64=1),$C$9,IF(Assumptions!$I$58=1,MAX(J7,Assumptions!$G$58)+Assumptions!$F$58+$C$8,Assumptions!$E$58))+J43*IF(OR(J44=1,Recovery!I65=1),$C$9,IF(Assumptions!$I$59=1,MAX(J7,Assumptions!$G$59)+Assumptions!$F$59+$C$8,Assumptions!$E$59))+J56*IF(OR(J57=1,Recovery!I66=1),$C$9,IF(Assumptions!$I$60=1,MAX(J7,Assumptions!$G$60)+Assumptions!$F$60+$C$8,Assumptions!$E$60))+J69*IF(OR(J70=1,Recovery!I67=1),$C$9,IF(Assumptions!$I$61=1,MAX(J7,Assumptions!$G$61)+Assumptions!$F$61+$C$8,Assumptions!$E$61))+J82*IF(OR(J83=1,Recovery!I68=1),$C$9,IF(Assumptions!$I$62=1,MAX(J7,Assumptions!$G$62)+Assumptions!$F$62+$C$8,Assumptions!$E$62))+J95*IF(OR(J96=1,Recovery!I69=1),$C$9,IF(Assumptions!$I$63=1,MAX(J7,Assumptions!$G$63)+Assumptions!$F$63+$C$8,Assumptions!$E$63))+J108*IF(OR(J109=1,Recovery!I70=1),$C$9,IF(Assumptions!$I$64=1,MAX(J7,Assumptions!$G$64)+Assumptions!$F$64+$C$8,Assumptions!$E$64))+J121*IF(OR(J122=1,Recovery!I71=1),$C$9,IF(Assumptions!$I$65=1,MAX(J7,Assumptions!$G$65)+Assumptions!$F$65+$C$8,Assumptions!$E$65))+J134*IF(OR(J135=1,Recovery!I72=1),$C$9,IF(Assumptions!$I$66=1,MAX(J7,Assumptions!$G$66)+Assumptions!$F$66+$C$8,Assumptions!$E$66)) -> 201.40153 | K14: =K17*IF(OR(K18=1,Recovery!J63=1),$C$9,IF(Assumptions!$I$57=1,MAX(K7,Assumptions!$G$57)+Assumptions!$F$57+$C$8,Assumptions!$E$57))+K30*IF(OR(K31=1,Recovery!J64=1),$C$9,IF(Assumptions!$I$58=1,MAX(K7,Assumptions!$G$58)+Assumptions!$F$58+$C$8,Assumptions!$E$58))+K43*IF(OR(K44=1,Recovery!J65=1),$C$9,IF(Assumptions!$I$59=1,MAX(K7,Assumptions!$G$59)+Assumptions!$F$59+$C$8,Assumptions!$E$59))+K56*IF(OR(K57=1,Recovery!J66=1),$C$9,IF(Assumptions!$I$60=1,MAX(K7,Assumptions!$G$60)+Assumptions!$F$60+$C$8,Assumptions!$E$60))+K69*IF(OR(K70=1,Recovery!J67=1),$C$9,IF(Assumptions!$I$61=1,MAX(K7,Assumptions!$G$61)+Assumptions!$F$61+$C$8,Assumptions!$E$61))+K82*IF(OR(K83=1,Recovery!J68=1),$C$9,IF(Assumptions!$I$62=1,MAX(K7,Assumptions!$G$62)+Assumptions!$F$62+$C$8,Assumptions!$E$62))+K95*IF(OR(K96=1,Recovery!J69=1),$C$9,IF(Assumptions!$I$63=1,MAX(K7,Assumptions!$G$63)+Assumptions!$F$63+$C$8,Assumptions!$E$63))+K108*IF(OR(K109=1,Recovery!J70=1),$C$9,IF(Assumptions!$I$64=1,MAX(K7,Assumptions!$G$64)+Assumptions!$F$64+$C$8,Assumptions!$E$64))+K121*IF(OR(K122=1,Recovery!J71=1),$C$9,IF(Assumptions!$I$65=1,MAX(K7,Assumptions!$G$65)+Assumptions!$F$65+$C$8,Assumptions!$E$65))+K134*IF(OR(K135=1,Recovery!J72=1),$C$9,IF(Assumptions!$I$66=1,MAX(K7,Assumptions!$G$66)+Assumptions!$F$66+$C$8,Assumptions!$E$66)) -> 192.58153
A15: Market access to refinance? (1 = yes) | G15: =IF('Operating Model'!G17<=0,0,IF(AND((G12-G13)/'Operating Model'!G17<=$C$10,'Operating Model'!G17/G14>=$C$11),1,0)) -> 0 | H15: =IF('Operating Model'!H17<=0,0,IF(AND((H12-H13)/'Operating Model'!H17<=$C$10,'Operating Model'!H17/H14>=$C$11),1,0)) -> 0 | I15: =IF('Operating Model'!I17<=0,0,IF(AND((I12-I13)/'Operating Model'!I17<=$C$10,'Operating Model'!I17/I14>=$C$11),1,0)) -> 0 | J15: =IF('Operating Model'!J17<=0,0,IF(AND((J12-J13)/'Operating Model'!J17<=$C$10,'Operating Model'!J17/J14>=$C$11),1,0)) -> 0 | K15: =IF('Operating Model'!K17<=0,0,IF(AND((K12-K13)/'Operating Model'!K17<=$C$10,'Operating Model'!K17/K14>=$C$11),1,0)) -> 0
A16: Tranche 1: Hypothetical Senior Secured Term Loan (S+525, 1% floor)
A17: Beginning balance | G17: =F28 -> 400 | H17: =G28 -> 396 | I17: =H28 -> 392 | J17: =I28 -> 388 | K17: =J28 -> 384
A18: Maturing this period? (1 = yes) | G18: =IF('Operating Model'!G7=Assumptions!$K$57,1,0) -> 0 | H18: =IF('Operating Model'!H7=Assumptions!$K$57,1,0) -> 0 | I18: =IF('Operating Model'!I7=Assumptions!$K$57,1,0) -> 0 | J18: =IF('Operating Model'!J7=Assumptions!$K$57,1,0) -> 0 | K18: =IF('Operating Model'!K7=Assumptions!$K$57,1,0) -> 1
A20: All-in interest rate applied | G20: =IF(Assumptions!$I$57=1,MAX(G7,Assumptions!$G$57)+Assumptions!$F$57+$C$8,Assumptions!$E$57) -> 0.1065 | H20: =IF(Recovery!G63=1,$C$9,IF(Assumptions!$I$57=1,MAX(H7,Assumptions!$G$57)+Assumptions!$F$57+$C$8,Assumptions!$E$57)) -> 0.105 | I20: =IF(Recovery!H63=1,$C$9,IF(Assumptions!$I$57=1,MAX(I7,Assumptions!$G$57)+Assumptions!$F$57+$C$8,Assumptions!$E$57)) -> 0.1025 | J20: =IF(Recovery!I63=1,$C$9,IF(Assumptions!$I$57=1,MAX(J7,Assumptions!$G$57)+Assumptions!$F$57+$C$8,Assumptions!$E$57)) -> 0.1025 | K20: =IF(Recovery!J63=1,$C$9,IF(Assumptions!$I$57=1,MAX(K7,Assumptions!$G$57)+Assumptions!$F$57+$C$8,Assumptions!$E$57)) -> 0.1025
A21: Cash interest expense | G21: =G17*G20 -> 42.6 | H21: =H17*H20 -> 41.58 | I21: =I17*I20 -> 40.18 | J21: =J17*J20 -> 39.77 | K21: =K17*K20 -> 39.36
A22: PIK interest | G22: =G17*Assumptions!$H$57 -> 0 | H22: =H17*Assumptions!$H$57 -> 0 | I22: =I17*Assumptions!$H$57 -> 0 | J22: =J17*Assumptions!$H$57 -> 0 | K22: =K17*Assumptions!$H$57 -> 0
A23: Mandatory amortization | G23: =MIN(G17,Assumptions!$L$57*Assumptions!$C$57) -> 4 | H23: =MIN(H17,Assumptions!$L$57*Assumptions!$C$57) -> 4 | I23: =MIN(I17,Assumptions!$L$57*Assumptions!$C$57) -> 4 | J23: =MIN(J17,Assumptions!$L$57*Assumptions!$C$57) -> 4 | K23: =MIN(K17,Assumptions!$L$57*Assumptions!$C$57) -> 4
A24: New borrowing (revolver draw) | G24: =IF(AND(Assumptions!$P$57=1,'Operating Model'!G7<Assumptions!$K$57),MIN(MAX(0,-'Cash Flow'!G11),MAX(0,Assumptions!$D$57-G17)),0) -> 0 | H24: =IF(AND(Assumptions!$P$57=1,OR('Operating Model'!H7<Assumptions!$K$57,Recovery!G63=1)),MIN(MAX(0,-'Cash Flow'!H11),MAX(0,Assumptions!$D$57-H17)),0) -> 0 | I24: =IF(AND(Assumptions!$P$57=1,OR('Operating Model'!I7<Assumptions!$K$57,Recovery!H63=1)),MIN(MAX(0,-'Cash Flow'!I11),MAX(0,Assumptions!$D$57-I17)),0) -> 0 | J24: =IF(AND(Assumptions!$P$57=1,OR('Operating Model'!J7<Assumptions!$K$57,Recovery!I63=1)),MIN(MAX(0,-'Cash Flow'!J11),MAX(0,Assumptions!$D$57-J17)),0) -> 0 | K24: =IF(AND(Assumptions!$P$57=1,OR('Operating Model'!K7<Assumptions!$K$57,Recovery!J63=1)),MIN(MAX(0,-'Cash Flow'!K11),MAX(0,Assumptions!$D$57-K17)),0) -> 0
A25: Repayment at maturity (from available cash) | G25: =G18*MIN(G17-G23+G22,MAX(0,'Cash Flow'!G13-Assumptions!$C$12*G15)) -> 0 | H25: =H18*MIN(H17-H23+H22,MAX(0,'Cash Flow'!H13-Assumptions!$C$12*H15)) -> 0 | I25: =I18*MIN(I17-I23+I22,MAX(0,'Cash Flow'!I13-Assumptions!$C$12*I15)) -> 0 | J25: =J18*MIN(J17-J23+J22,MAX(0,'Cash Flow'!J13-Assumptions!$C$12*J15)) -> 0 | K25: =K18*MIN(K17-K23+K22,MAX(0,'Cash Flow'!K13-Assumptions!$C$12*K15)) -> 0
A26: Optional repayment (cash sweep) | G26: =Assumptions!$N$57*MIN(G17+G24+G22-G23-G25,MAX(0,'Cash Flow'!G17)) -> 0 | H26: =Assumptions!$N$57*MIN(H17+H24+H22-H23-H25,MAX(0,'Cash Flow'!H17)) -> 0 | I26: =Assumptions!$N$57*MIN(I17+I24+I22-I23-I25,MAX(0,'Cash Flow'!I17)) -> 0 | J26: =Assumptions!$N$57*MIN(J17+J24+J22-J23-J25,MAX(0,'Cash Flow'!J17)) -> 0 | K26: =Assumptions!$N$57*MIN(K17+K24+K22-K23-K25,MAX(0,'Cash Flow'!K17)) -> 0
A27: Unpaid at maturity (no refinancing, insufficient cash) | G27: =G18*(1-G15)*(G17-G23+G22-G25) -> 0 | H27: =H18*(1-H15)*(H17-H23+H22-H25) -> 0 | I27: =I18*(1-I15)*(I17-I23+I22-I25) -> 0 | J27: =J18*(1-J15)*(J17-J23+J22-J25) -> 0 | K27: =K18*(1-K15)*(K17-K23+K22-K25) -> 380
A28: Ending balance | F28: =Assumptions!$C$57 -> 400 | G28: =G17+G24+G22-G23-G25-G26 -> 396 | H28: =H17+H24+H22-H23-H25-H26 -> 392 | I28: =I17+I24+I22-I23-I25-I26 -> 388 | J28: =J17+J24+J22-J23-J25-J26 -> 384 | K28: =K17+K24+K22-K23-K25-K26 -> 380
A29: Tranche 2: Avira Secured Term Loan (swapped to 5.81%)
A30: Beginning balance | G30: =F41 -> 90 | H30: =G41 -> 90 | I30: =H41 -> 90 | J30: =I41 -> 90 | K30: =J41 -> 90
A31: Maturing this period? (1 = yes) | G31: =IF('Operating Model'!G7=Assumptions!$K$58,1,0) -> 0 | H31: =IF('Operating Model'!H7=Assumptions!$K$58,1,0) -> 0 | I31: =IF('Operating Model'!I7=Assumptions!$K$58,1,0) -> 0 | J31: =IF('Operating Model'!J7=Assumptions!$K$58,1,0) -> 0 | K31: =IF('Operating Model'!K7=Assumptions!$K$58,1,0) -> 0
A33: All-in interest rate applied | G33: =IF(Assumptions!$I$58=1,MAX(G7,Assumptions!$G$58)+Assumptions!$F$58+$C$8,Assumptions!$E$58) -> 0.0581 | H33: =IF(Recovery!G64=1,$C$9,IF(Assumptions!$I$58=1,MAX(H7,Assumptions!$G$58)+Assumptions!$F$58+$C$8,Assumptions!$E$58)) -> 0.0581 | I33: =IF(Recovery!H64=1,$C$9,IF(Assumptions!$I$58=1,MAX(I7,Assumptions!$G$58)+Assumptions!$F$58+$C$8,Assumptions!$E$58)) -> 0.0581 | J33: =IF(Recovery!I64=1,$C$9,IF(Assumptions!$I$58=1,MAX(J7,Assumptions!$G$58)+Assumptions!$F$58+$C$8,Assumptions!$E$58)) -> 0.0581 | K33: =IF(Recovery!J64=1,$C$9,IF(Assumptions!$I$58=1,MAX(K7,Assumptions!$G$58)+Assumptions!$F$58+$C$8,Assumptions!$E$58)) -> 0.0581
A34: Cash interest expense | G34: =G30*G33 -> 5.229 | H34: =H30*H33 -> 5.229 | I34: =I30*I33 -> 5.229 | J34: =J30*J33 -> 5.229 | K34: =K30*K33 -> 5.229
A35: PIK interest | G35: =G30*Assumptions!$H$58 -> 0 | H35: =H30*Assumptions!$H$58 -> 0 | I35: =I30*Assumptions!$H$58 -> 0 | J35: =J30*Assumptions!$H$58 -> 0 | K35: =K30*Assumptions!$H$58 -> 0
A36: Mandatory amortization | G36: =MIN(G30,Assumptions!$L$58*Assumptions!$C$58) -> 0 | H36: =MIN(H30,Assumptions!$L$58*Assumptions!$C$58) -> 0 | I36: =MIN(I30,Assumptions!$L$58*Assumptions!$C$58) -> 0 | J36: =MIN(J30,Assumptions!$L$58*Assumptions!$C$58) -> 0 | K36: =MIN(K30,Assumptions!$L$58*Assumptions!$C$58) -> 0
A37: New borrowing (revolver draw) | G37: =IF(AND(Assumptions!$P$58=1,'Operating Model'!G7<Assumptions!$K$58),MIN(MAX(0,-'Cash Flow'!G11),MAX(0,Assumptions!$D$58-G30)),0) -> 0 | H37: =IF(AND(Assumptions!$P$58=1,OR('Operating Model'!H7<Assumptions!$K$58,Recovery!G64=1)),MIN(MAX(0,-'Cash Flow'!H11),MAX(0,Assumptions!$D$58-H30)),0) -> 0 | I37: =IF(AND(Assumptions!$P$58=1,OR('Operating Model'!I7<Assumptions!$K$58,Recovery!H64=1)),MIN(MAX(0,-'Cash Flow'!I11),MAX(0,Assumptions!$D$58-I30)),0) -> 0 | J37: =IF(AND(Assumptions!$P$58=1,OR('Operating Model'!J7<Assumptions!$K$58,Recovery!I64=1)),MIN(MAX(0,-'Cash Flow'!J11),MAX(0,Assumptions!$D$58-J30)),0) -> 0 | K37: =IF(AND(Assumptions!$P$58=1,OR('Operating Model'!K7<Assumptions!$K$58,Recovery!J64=1)),MIN(MAX(0,-'Cash Flow'!K11),MAX(0,Assumptions!$D$58-K30)),0) -> 0
A38: Repayment at maturity (from available cash) | G38: =G31*MIN(G30-G36+G35,MAX(0,'Cash Flow'!G13-Assumptions!$C$12*G15-G25)) -> 0 | H38: =H31*MIN(H30-H36+H35,MAX(0,'Cash Flow'!H13-Assumptions!$C$12*H15-H25)) -> 0 | I38: =I31*MIN(I30-I36+I35,MAX(0,'Cash Flow'!I13-Assumptions!$C$12*I15-I25)) -> 0 | J38: =J31*MIN(J30-J36+J35,MAX(0,'Cash Flow'!J13-Assumptions!$C$12*J15-J25)) -> 0 | K38: =K31*MIN(K30-K36+K35,MAX(0,'Cash Flow'!K13-Assumptions!$C$12*K15-K25)) -> 0
A39: Optional repayment (cash sweep) | G39: =Assumptions!$N$58*MIN(G30+G37+G35-G36-G38,MAX(0,'Cash Flow'!G17-G26)) -> 0 | H39: =Assumptions!$N$58*MIN(H30+H37+H35-H36-H38,MAX(0,'Cash Flow'!H17-H26)) -> 0 | I39: =Assumptions!$N$58*MIN(I30+I37+I35-I36-I38,MAX(0,'Cash Flow'!I17-I26)) -> 0 | J39: =Assumptions!$N$58*MIN(J30+J37+J35-J36-J38,MAX(0,'Cash Flow'!J17-J26)) -> 0 | K39: =Assumptions!$N$58*MIN(K30+K37+K35-K36-K38,MAX(0,'Cash Flow'!K17-K26)) -> 0
A40: Unpaid at maturity (no refinancing, insufficient cash) | G40: =G31*(1-G15)*(G30-G36+G35-G38) -> 0 | H40: =H31*(1-H15)*(H30-H36+H35-H38) -> 0 | I40: =I31*(1-I15)*(I30-I36+I35-I38) -> 0 | J40: =J31*(1-J15)*(J30-J36+J35-J38) -> 0 | K40: =K31*(1-K15)*(K30-K36+K35-K38) -> 0
A41: Ending balance | F41: =Assumptions!$C$58 -> 90 | G41: =G30+G37+G35-G36-G38-G39 -> 90 | H41: =H30+H37+H35-H36-H38-H39 -> 90 | I41: =I30+I37+I35-I36-I38-I39 -> 90 | J41: =J30+J37+J35-J36-J38-J39 -> 90 | K41: =K30+K37+K35-K36-K38-K39 -> 90
A42: Tranche 3: 3151 Market C-PACE Loan
A43: Beginning balance | G43: =F54 -> 57.324 | H43: =G54 -> 57.324 | I43: =H54 -> 57.324 | J43: =I54 -> 57.324 | K43: =J54 -> 57.324
A44: Maturing this period? (1 = yes) | G44: =IF('Operating Model'!G7=Assumptions!$K$59,1,0) -> 0 | H44: =IF('Operating Model'!H7=Assumptions!$K$59,1,0) -> 0 | I44: =IF('Operating Model'!I7=Assumptions!$K$59,1,0) -> 0 | J44: =IF('Operating Model'!J7=Assumptions!$K$59,1,0) -> 0 | K44: =IF('Operating Model'!K7=Assumptions!$K$59,1,0) -> 0
A46: All-in interest rate applied | G46: =IF(Assumptions!$I$59=1,MAX(G7,Assumptions!$G$59)+Assumptions!$F$59+$C$8,Assumptions!$E$59) -> 0.0731 | H46: =IF(Recovery!G65=1,$C$9,IF(Assumptions!$I$59=1,MAX(H7,Assumptions!$G$59)+Assumptions!$F$59+$C$8,Assumptions!$E$59)) -> 0.0731 | I46: =IF(Recovery!H65=1,$C$9,IF(Assumptions!$I$59=1,MAX(I7,Assumptions!$G$59)+Assumptions!$F$59+$C$8,Assumptions!$E$59)) -> 0.0731 | J46: =IF(Recovery!I65=1,$C$9,IF(Assumptions!$I$59=1,MAX(J7,Assumptions!$G$59)+Assumptions!$F$59+$C$8,Assumptions!$E$59)) -> 0.0731 | K46: =IF(Recovery!J65=1,$C$9,IF(Assumptions!$I$59=1,MAX(K7,Assumptions!$G$59)+Assumptions!$F$59+$C$8,Assumptions!$E$59)) -> 0.0731
A47: Cash interest expense | G47: =G43*G46 -> 4.1903844 | H47: =H43*H46 -> 4.1903844 | I47: =I43*I46 -> 4.1903844 | J47: =J43*J46 -> 4.1903844 | K47: =K43*K46 -> 4.1903844
A48: PIK interest | G48: =G43*Assumptions!$H$59 -> 0 | H48: =H43*Assumptions!$H$59 -> 0 | I48: =I43*Assumptions!$H$59 -> 0 | J48: =J43*Assumptions!$H$59 -> 0 | K48: =K43*Assumptions!$H$59 -> 0
A49: Mandatory amortization | G49: =MIN(G43,Assumptions!$L$59*Assumptions!$C$59) -> 0 | H49: =MIN(H43,Assumptions!$L$59*Assumptions!$C$59) -> 0 | I49: =MIN(I43,Assumptions!$L$59*Assumptions!$C$59) -> 0 | J49: =MIN(J43,Assumptions!$L$59*Assumptions!$C$59) -> 0 | K49: =MIN(K43,Assumptions!$L$59*Assumptions!$C$59) -> 0
A50: New borrowing (revolver draw) | G50: =IF(AND(Assumptions!$P$59=1,'Operating Model'!G7<Assumptions!$K$59),MIN(MAX(0,-'Cash Flow'!G11),MAX(0,Assumptions!$D$59-G43)),0) -> 0 | H50: =IF(AND(Assumptions!$P$59=1,OR('Operating Model'!H7<Assumptions!$K$59,Recovery!G65=1)),MIN(MAX(0,-'Cash Flow'!H11),MAX(0,Assumptions!$D$59-H43)),0) -> 0 | I50: =IF(AND(Assumptions!$P$59=1,OR('Operating Model'!I7<Assumptions!$K$59,Recovery!H65=1)),MIN(MAX(0,-'Cash Flow'!I11),MAX(0,Assumptions!$D$59-I43)),0) -> 0 | J50: =IF(AND(Assumptions!$P$59=1,OR('Operating Model'!J7<Assumptions!$K$59,Recovery!I65=1)),MIN(MAX(0,-'Cash Flow'!J11),MAX(0,Assumptions!$D$59-J43)),0) -> 0 | K50: =IF(AND(Assumptions!$P$59=1,OR('Operating Model'!K7<Assumptions!$K$59,Recovery!J65=1)),MIN(MAX(0,-'Cash Flow'!K11),MAX(0,Assumptions!$D$59-K43)),0) -> 0
A51: Repayment at maturity (from available cash) | G51: =G44*MIN(G43-G49+G48,MAX(0,'Cash Flow'!G13-Assumptions!$C$12*G15-G25-G38)) -> 0 | H51: =H44*MIN(H43-H49+H48,MAX(0,'Cash Flow'!H13-Assumptions!$C$12*H15-H25-H38)) -> 0 | I51: =I44*MIN(I43-I49+I48,MAX(0,'Cash Flow'!I13-Assumptions!$C$12*I15-I25-I38)) -> 0 | J51: =J44*MIN(J43-J49+J48,MAX(0,'Cash Flow'!J13-Assumptions!$C$12*J15-J25-J38)) -> 0 | K51: =K44*MIN(K43-K49+K48,MAX(0,'Cash Flow'!K13-Assumptions!$C$12*K15-K25-K38)) -> 0
A52: Optional repayment (cash sweep) | G52: =Assumptions!$N$59*MIN(G43+G50+G48-G49-G51,MAX(0,'Cash Flow'!G17-G26-G39)) -> 0 | H52: =Assumptions!$N$59*MIN(H43+H50+H48-H49-H51,MAX(0,'Cash Flow'!H17-H26-H39)) -> 0 | I52: =Assumptions!$N$59*MIN(I43+I50+I48-I49-I51,MAX(0,'Cash Flow'!I17-I26-I39)) -> 0 | J52: =Assumptions!$N$59*MIN(J43+J50+J48-J49-J51,MAX(0,'Cash Flow'!J17-J26-J39)) -> 0 | K52: =Assumptions!$N$59*MIN(K43+K50+K48-K49-K51,MAX(0,'Cash Flow'!K17-K26-K39)) -> 0
A53: Unpaid at maturity (no refinancing, insufficient cash) | G53: =G44*(1-G15)*(G43-G49+G48-G51) -> 0 | H53: =H44*(1-H15)*(H43-H49+H48-H51) -> 0 | I53: =I44*(1-I15)*(I43-I49+I48-I51) -> 0 | J53: =J44*(1-J15)*(J43-J49+J48-J51) -> 0 | K53: =K44*(1-K15)*(K43-K49+K48-K51) -> 0
A54: Ending balance | F54: =Assumptions!$C$59 -> 57.324 | G54: =G43+G50+G48-G49-G51-G52 -> 57.324 | H54: =H43+H50+H48-H49-H51-H52 -> 57.324 | I54: =I43+I50+I48-I49-I51-I52 -> 57.324 | J54: =J43+J50+J48-J49-J51-J52 -> 57.324 | K54: =K43+K50+K48-K49-K51-K52 -> 57.324
A55: Tranche 4: Unsecured Revolver ($600M less LCs; hypothetically undrawn pro forma)
A56: Beginning balance | G56: =F67 -> 0 | H56: =G67 -> 0 | I56: =H67 -> 0 | J56: =I67 -> 0 | K56: =J67 -> 0
A57: Maturing this period? (1 = yes) | G57: =IF('Operating Model'!G7=Assumptions!$K$60,1,0) -> 1 | H57: =IF('Operating Model'!H7=Assumptions!$K$60,1,0) -> 0 | I57: =IF('Operating Model'!I7=Assumptions!$K$60,1,0) -> 0 | J57: =IF('Operating Model'!J7=Assumptions!$K$60,1,0) -> 0 | K57: =IF('Operating Model'!K7=Assumptions!$K$60,1,0) -> 0
A59: All-in interest rate applied | G59: =IF(Assumptions!$I$60=1,MAX(G7,Assumptions!$G$60)+Assumptions!$F$60+$C$8,Assumptions!$E$60) -> 0.069 | H59: =IF(Recovery!G66=1,$C$9,IF(Assumptions!$I$60=1,MAX(H7,Assumptions!$G$60)+Assumptions!$F$60+$C$8,Assumptions!$E$60)) -> 0.0675 | I59: =IF(Recovery!H66=1,$C$9,IF(Assumptions!$I$60=1,MAX(I7,Assumptions!$G$60)+Assumptions!$F$60+$C$8,Assumptions!$E$60)) -> 0.065 | J59: =IF(Recovery!I66=1,$C$9,IF(Assumptions!$I$60=1,MAX(J7,Assumptions!$G$60)+Assumptions!$F$60+$C$8,Assumptions!$E$60)) -> 0.065 | K59: =IF(Recovery!J66=1,$C$9,IF(Assumptions!$I$60=1,MAX(K7,Assumptions!$G$60)+Assumptions!$F$60+$C$8,Assumptions!$E$60)) -> 0.065
A60: Cash interest expense | G60: =G56*G59 -> 0 | H60: =H56*H59 -> 0 | I60: =I56*I59 -> 0 | J60: =J56*J59 -> 0 | K60: =K56*K59 -> 0
A61: PIK interest | G61: =G56*Assumptions!$H$60 -> 0 | H61: =H56*Assumptions!$H$60 -> 0 | I61: =I56*Assumptions!$H$60 -> 0 | J61: =J56*Assumptions!$H$60 -> 0 | K61: =K56*Assumptions!$H$60 -> 0
A62: Mandatory amortization | G62: =MIN(G56,Assumptions!$L$60*Assumptions!$C$60) -> 0 | H62: =MIN(H56,Assumptions!$L$60*Assumptions!$C$60) -> 0 | I62: =MIN(I56,Assumptions!$L$60*Assumptions!$C$60) -> 0 | J62: =MIN(J56,Assumptions!$L$60*Assumptions!$C$60) -> 0 | K62: =MIN(K56,Assumptions!$L$60*Assumptions!$C$60) -> 0
A63: New borrowing (revolver draw) | G63: =IF(AND(Assumptions!$P$60=1,'Operating Model'!G7<Assumptions!$K$60),MIN(MAX(0,-'Cash Flow'!G11),MAX(0,Assumptions!$D$60-G56)),0) -> 0 | H63: =IF(AND(Assumptions!$P$60=1,OR('Operating Model'!H7<Assumptions!$K$60,Recovery!G66=1)),MIN(MAX(0,-'Cash Flow'!H11),MAX(0,Assumptions!$D$60-H56)),0) -> 0 | I63: =IF(AND(Assumptions!$P$60=1,OR('Operating Model'!I7<Assumptions!$K$60,Recovery!H66=1)),MIN(MAX(0,-'Cash Flow'!I11),MAX(0,Assumptions!$D$60-I56)),0) -> 0 | J63: =IF(AND(Assumptions!$P$60=1,OR('Operating Model'!J7<Assumptions!$K$60,Recovery!I66=1)),MIN(MAX(0,-'Cash Flow'!J11),MAX(0,Assumptions!$D$60-J56)),0) -> 0 | K63: =IF(AND(Assumptions!$P$60=1,OR('Operating Model'!K7<Assumptions!$K$60,Recovery!J66=1)),MIN(MAX(0,-'Cash Flow'!K11),MAX(0,Assumptions!$D$60-K56)),0) -> 0
A64: Repayment at maturity (from available cash) | G64: =G57*MIN(G56-G62+G61,MAX(0,'Cash Flow'!G13-Assumptions!$C$12*G15-G25-G38-G51)) -> 0 | H64: =H57*MIN(H56-H62+H61,MAX(0,'Cash Flow'!H13-Assumptions!$C$12*H15-H25-H38-H51)) -> 0 | I64: =I57*MIN(I56-I62+I61,MAX(0,'Cash Flow'!I13-Assumptions!$C$12*I15-I25-I38-I51)) -> 0 | J64: =J57*MIN(J56-J62+J61,MAX(0,'Cash Flow'!J13-Assumptions!$C$12*J15-J25-J38-J51)) -> 0 | K64: =K57*MIN(K56-K62+K61,MAX(0,'Cash Flow'!K13-Assumptions!$C$12*K15-K25-K38-K51)) -> 0
A65: Optional repayment (cash sweep) | G65: =Assumptions!$N$60*MIN(G56+G63+G61-G62-G64,MAX(0,'Cash Flow'!G17-G26-G39-G52)) -> 0 | H65: =Assumptions!$N$60*MIN(H56+H63+H61-H62-H64,MAX(0,'Cash Flow'!H17-H26-H39-H52)) -> 0 | I65: =Assumptions!$N$60*MIN(I56+I63+I61-I62-I64,MAX(0,'Cash Flow'!I17-I26-I39-I52)) -> 0 | J65: =Assumptions!$N$60*MIN(J56+J63+J61-J62-J64,MAX(0,'Cash Flow'!J17-J26-J39-J52)) -> 0 | K65: =Assumptions!$N$60*MIN(K56+K63+K61-K62-K64,MAX(0,'Cash Flow'!K17-K26-K39-K52)) -> 0
A66: Unpaid at maturity (no refinancing, insufficient cash) | G66: =G57*(1-G15)*(G56-G62+G61-G64) -> 0 | H66: =H57*(1-H15)*(H56-H62+H61-H64) -> 0 | I66: =I57*(1-I15)*(I56-I62+I61-I64) -> 0 | J66: =J57*(1-J15)*(J56-J62+J61-J64) -> 0 | K66: =K57*(1-K15)*(K56-K62+K61-K64) -> 0
A67: Ending balance | F67: =Assumptions!$C$60 -> 0 | G67: =G56+G63+G61-G62-G64-G65 -> 0 | H67: =H56+H63+H61-H62-H64-H65 -> 0 | I67: =I56+I63+I61-I62-I64-I65 -> 0 | J67: =J56+J63+J61-J62-J64-J65 -> 0 | K67: =K56+K63+K61-K62-K64-K65 -> 0
A68: Tranche 5: 3.95% Guaranteed Notes due Nov-2027
A69: Beginning balance | G69: =F80 -> 450 | H69: =G80 -> 450 | I69: =H80 -> 401.44636 | J69: =I80 -> 401.44636 | K69: =J80 -> 401.44636
A70: Maturing this period? (1 = yes) | G70: =IF('Operating Model'!G7=Assumptions!$K$61,1,0) -> 0 | H70: =IF('Operating Model'!H7=Assumptions!$K$61,1,0) -> 1 | I70: =IF('Operating Model'!I7=Assumptions!$K$61,1,0) -> 0 | J70: =IF('Operating Model'!J7=Assumptions!$K$61,1,0) -> 0 | K70: =IF('Operating Model'!K7=Assumptions!$K$61,1,0) -> 0
A72: All-in interest rate applied | G72: =IF(Assumptions!$I$61=1,MAX(G7,Assumptions!$G$61)+Assumptions!$F$61+$C$8,Assumptions!$E$61) -> 0.0395 | H72: =IF(Recovery!G67=1,$C$9,IF(Assumptions!$I$61=1,MAX(H7,Assumptions!$G$61)+Assumptions!$F$61+$C$8,Assumptions!$E$61)) -> 0.0395 | I72: =IF(Recovery!H67=1,$C$9,IF(Assumptions!$I$61=1,MAX(I7,Assumptions!$G$61)+Assumptions!$F$61+$C$8,Assumptions!$E$61)) -> 0.0395 | J72: =IF(Recovery!I67=1,$C$9,IF(Assumptions!$I$61=1,MAX(J7,Assumptions!$G$61)+Assumptions!$F$61+$C$8,Assumptions!$E$61)) -> 0.0395 | K72: =IF(Recovery!J67=1,$C$9,IF(Assumptions!$I$61=1,MAX(K7,Assumptions!$G$61)+Assumptions!$F$61+$C$8,Assumptions!$E$61)) -> 0.0395
A73: Cash interest expense | G73: =G69*G72 -> 17.775 | H73: =H69*H72 -> 17.775 | I73: =I69*I72 -> 15.857131 | J73: =J69*J72 -> 15.857131 | K73: =K69*K72 -> 15.857131
A74: PIK interest | G74: =G69*Assumptions!$H$61 -> 0 | H74: =H69*Assumptions!$H$61 -> 0 | I74: =I69*Assumptions!$H$61 -> 0 | J74: =J69*Assumptions!$H$61 -> 0 | K74: =K69*Assumptions!$H$61 -> 0
A75: Mandatory amortization | G75: =MIN(G69,Assumptions!$L$61*Assumptions!$C$61) -> 0 | H75: =MIN(H69,Assumptions!$L$61*Assumptions!$C$61) -> 0 | I75: =MIN(I69,Assumptions!$L$61*Assumptions!$C$61) -> 0 | J75: =MIN(J69,Assumptions!$L$61*Assumptions!$C$61) -> 0 | K75: =MIN(K69,Assumptions!$L$61*Assumptions!$C$61) -> 0
A76: New borrowing (revolver draw) | G76: =IF(AND(Assumptions!$P$61=1,'Operating Model'!G7<Assumptions!$K$61),MIN(MAX(0,-'Cash Flow'!G11),MAX(0,Assumptions!$D$61-G69)),0) -> 0 | H76: =IF(AND(Assumptions!$P$61=1,OR('Operating Model'!H7<Assumptions!$K$61,Recovery!G67=1)),MIN(MAX(0,-'Cash Flow'!H11),MAX(0,Assumptions!$D$61-H69)),0) -> 0 | I76: =IF(AND(Assumptions!$P$61=1,OR('Operating Model'!I7<Assumptions!$K$61,Recovery!H67=1)),MIN(MAX(0,-'Cash Flow'!I11),MAX(0,Assumptions!$D$61-I69)),0) -> 0 | J76: =IF(AND(Assumptions!$P$61=1,OR('Operating Model'!J7<Assumptions!$K$61,Recovery!I67=1)),MIN(MAX(0,-'Cash Flow'!J11),MAX(0,Assumptions!$D$61-J69)),0) -> 0 | K76: =IF(AND(Assumptions!$P$61=1,OR('Operating Model'!K7<Assumptions!$K$61,Recovery!J67=1)),MIN(MAX(0,-'Cash Flow'!K11),MAX(0,Assumptions!$D$61-K69)),0) -> 0
A77: Repayment at maturity (from available cash) | G77: =G70*MIN(G69-G75+G74,MAX(0,'Cash Flow'!G13-Assumptions!$C$12*G15-G25-G38-G51-G64)) -> 0 | H77: =H70*MIN(H69-H75+H74,MAX(0,'Cash Flow'!H13-Assumptions!$C$12*H15-H25-H38-H51-H64)) -> 48.553642 | I77: =I70*MIN(I69-I75+I74,MAX(0,'Cash Flow'!I13-Assumptions!$C$12*I15-I25-I38-I51-I64)) -> 0 | J77: =J70*MIN(J69-J75+J74,MAX(0,'Cash Flow'!J13-Assumptions!$C$12*J15-J25-J38-J51-J64)) -> 0 | K77: =K70*MIN(K69-K75+K74,MAX(0,'Cash Flow'!K13-Assumptions!$C$12*K15-K25-K38-K51-K64)) -> 0
A78: Optional repayment (cash sweep) | G78: =Assumptions!$N$61*MIN(G69+G76+G74-G75-G77,MAX(0,'Cash Flow'!G17-G26-G39-G52-G65)) -> 0 | H78: =Assumptions!$N$61*MIN(H69+H76+H74-H75-H77,MAX(0,'Cash Flow'!H17-H26-H39-H52-H65)) -> 0 | I78: =Assumptions!$N$61*MIN(I69+I76+I74-I75-I77,MAX(0,'Cash Flow'!I17-I26-I39-I52-I65)) -> 0 | J78: =Assumptions!$N$61*MIN(J69+J76+J74-J75-J77,MAX(0,'Cash Flow'!J17-J26-J39-J52-J65)) -> 0 | K78: =Assumptions!$N$61*MIN(K69+K76+K74-K75-K77,MAX(0,'Cash Flow'!K17-K26-K39-K52-K65)) -> 0
A79: Unpaid at maturity (no refinancing, insufficient cash) | G79: =G70*(1-G15)*(G69-G75+G74-G77) -> 0 | H79: =H70*(1-H15)*(H69-H75+H74-H77) -> 401.44636 | I79: =I70*(1-I15)*(I69-I75+I74-I77) -> 0 | J79: =J70*(1-J15)*(J69-J75+J74-J77) -> 0 | K79: =K70*(1-K15)*(K69-K75+K74-K77) -> 0
A80: Ending balance | F80: =Assumptions!$C$61 -> 450 | G80: =G69+G76+G74-G75-G77-G78 -> 450 | H80: =H69+H76+H74-H75-H77-H78 -> 401.44636 | I80: =I69+I76+I74-I75-I77-I78 -> 401.44636 | J80: =J69+J76+J74-J75-J77-J78 -> 401.44636 | K80: =K69+K76+K74-K75-K77-K78 -> 401.44636
A81: Tranche 6: 8.30% Guaranteed Notes due Mar-2028
A82: Beginning balance | G82: =F93 -> 350 | H82: =G93 -> 350 | I82: =H93 -> 350 | J82: =I93 -> 350 | K82: =J93 -> 350
A83: Maturing this period? (1 = yes) | G83: =IF('Operating Model'!G7=Assumptions!$K$62,1,0) -> 0 | H83: =IF('Operating Model'!H7=Assumptions!$K$62,1,0) -> 1 | I83: =IF('Operating Model'!I7=Assumptions!$K$62,1,0) -> 0 | J83: =IF('Operating Model'!J7=Assumptions!$K$62,1,0) -> 0 | K83: =IF('Operating Model'!K7=Assumptions!$K$62,1,0) -> 0
A85: All-in interest rate applied | G85: =IF(Assumptions!$I$62=1,MAX(G7,Assumptions!$G$62)+Assumptions!$F$62+$C$8,Assumptions!$E$62) -> 0.083 | H85: =IF(Recovery!G68=1,$C$9,IF(Assumptions!$I$62=1,MAX(H7,Assumptions!$G$62)+Assumptions!$F$62+$C$8,Assumptions!$E$62)) -> 0.083 | I85: =IF(Recovery!H68=1,$C$9,IF(Assumptions!$I$62=1,MAX(I7,Assumptions!$G$62)+Assumptions!$F$62+$C$8,Assumptions!$E$62)) -> 0.083 | J85: =IF(Recovery!I68=1,$C$9,IF(Assumptions!$I$62=1,MAX(J7,Assumptions!$G$62)+Assumptions!$F$62+$C$8,Assumptions!$E$62)) -> 0.083 | K85: =IF(Recovery!J68=1,$C$9,IF(Assumptions!$I$62=1,MAX(K7,Assumptions!$G$62)+Assumptions!$F$62+$C$8,Assumptions!$E$62)) -> 0.083
A86: Cash interest expense | G86: =G82*G85 -> 29.05 | H86: =H82*H85 -> 29.05 | I86: =I82*I85 -> 29.05 | J86: =J82*J85 -> 29.05 | K86: =K82*K85 -> 29.05
A87: PIK interest | G87: =G82*Assumptions!$H$62 -> 0 | H87: =H82*Assumptions!$H$62 -> 0 | I87: =I82*Assumptions!$H$62 -> 0 | J87: =J82*Assumptions!$H$62 -> 0 | K87: =K82*Assumptions!$H$62 -> 0
A88: Mandatory amortization | G88: =MIN(G82,Assumptions!$L$62*Assumptions!$C$62) -> 0 | H88: =MIN(H82,Assumptions!$L$62*Assumptions!$C$62) -> 0 | I88: =MIN(I82,Assumptions!$L$62*Assumptions!$C$62) -> 0 | J88: =MIN(J82,Assumptions!$L$62*Assumptions!$C$62) -> 0 | K88: =MIN(K82,Assumptions!$L$62*Assumptions!$C$62) -> 0
A89: New borrowing (revolver draw) | G89: =IF(AND(Assumptions!$P$62=1,'Operating Model'!G7<Assumptions!$K$62),MIN(MAX(0,-'Cash Flow'!G11),MAX(0,Assumptions!$D$62-G82)),0) -> 0 | H89: =IF(AND(Assumptions!$P$62=1,OR('Operating Model'!H7<Assumptions!$K$62,Recovery!G68=1)),MIN(MAX(0,-'Cash Flow'!H11),MAX(0,Assumptions!$D$62-H82)),0) -> 0 | I89: =IF(AND(Assumptions!$P$62=1,OR('Operating Model'!I7<Assumptions!$K$62,Recovery!H68=1)),MIN(MAX(0,-'Cash Flow'!I11),MAX(0,Assumptions!$D$62-I82)),0) -> 0 | J89: =IF(AND(Assumptions!$P$62=1,OR('Operating Model'!J7<Assumptions!$K$62,Recovery!I68=1)),MIN(MAX(0,-'Cash Flow'!J11),MAX(0,Assumptions!$D$62-J82)),0) -> 0 | K89: =IF(AND(Assumptions!$P$62=1,OR('Operating Model'!K7<Assumptions!$K$62,Recovery!J68=1)),MIN(MAX(0,-'Cash Flow'!K11),MAX(0,Assumptions!$D$62-K82)),0) -> 0
A90: Repayment at maturity (from available cash) | G90: =G83*MIN(G82-G88+G87,MAX(0,'Cash Flow'!G13-Assumptions!$C$12*G15-G25-G38-G51-G64-G77)) -> 0 | H90: =H83*MIN(H82-H88+H87,MAX(0,'Cash Flow'!H13-Assumptions!$C$12*H15-H25-H38-H51-H64-H77)) -> 0 | I90: =I83*MIN(I82-I88+I87,MAX(0,'Cash Flow'!I13-Assumptions!$C$12*I15-I25-I38-I51-I64-I77)) -> 0 | J90: =J83*MIN(J82-J88+J87,MAX(0,'Cash Flow'!J13-Assumptions!$C$12*J15-J25-J38-J51-J64-J77)) -> 0 | K90: =K83*MIN(K82-K88+K87,MAX(0,'Cash Flow'!K13-Assumptions!$C$12*K15-K25-K38-K51-K64-K77)) -> 0
A91: Optional repayment (cash sweep) | G91: =Assumptions!$N$62*MIN(G82+G89+G87-G88-G90,MAX(0,'Cash Flow'!G17-G26-G39-G52-G65-G78)) -> 0 | H91: =Assumptions!$N$62*MIN(H82+H89+H87-H88-H90,MAX(0,'Cash Flow'!H17-H26-H39-H52-H65-H78)) -> 0 | I91: =Assumptions!$N$62*MIN(I82+I89+I87-I88-I90,MAX(0,'Cash Flow'!I17-I26-I39-I52-I65-I78)) -> 0 | J91: =Assumptions!$N$62*MIN(J82+J89+J87-J88-J90,MAX(0,'Cash Flow'!J17-J26-J39-J52-J65-J78)) -> 0 | K91: =Assumptions!$N$62*MIN(K82+K89+K87-K88-K90,MAX(0,'Cash Flow'!K17-K26-K39-K52-K65-K78)) -> 0
A92: Unpaid at maturity (no refinancing, insufficient cash) | G92: =G83*(1-G15)*(G82-G88+G87-G90) -> 0 | H92: =H83*(1-H15)*(H82-H88+H87-H90) -> 350 | I92: =I83*(1-I15)*(I82-I88+I87-I90) -> 0 | J92: =J83*(1-J15)*(J82-J88+J87-J90) -> 0 | K92: =K83*(1-K15)*(K82-K88+K87-K90) -> 0
A93: Ending balance | F93: =Assumptions!$C$62 -> 350 | G93: =G82+G89+G87-G88-G90-G91 -> 350 | H93: =H82+H89+H87-H88-H90-H91 -> 350 | I93: =I82+I89+I87-I88-I90-I91 -> 350 | J93: =J82+J89+J87-J88-J90-J91 -> 350 | K93: =K82+K89+K87-K88-K90-K91 -> 350
A94: Tranche 7: 8.875% Guaranteed Notes due Apr-2029
A95: Beginning balance | G95: =F106 -> 550 | H95: =G106 -> 550 | I95: =H106 -> 550 | J95: =I106 -> 550 | K95: =J106 -> 550
A96: Maturing this period? (1 = yes) | G96: =IF('Operating Model'!G7=Assumptions!$K$63,1,0) -> 0 | H96: =IF('Operating Model'!H7=Assumptions!$K$63,1,0) -> 0 | I96: =IF('Operating Model'!I7=Assumptions!$K$63,1,0) -> 1 | J96: =IF('Operating Model'!J7=Assumptions!$K$63,1,0) -> 0 | K96: =IF('Operating Model'!K7=Assumptions!$K$63,1,0) -> 0
A98: All-in interest rate applied | G98: =IF(Assumptions!$I$63=1,MAX(G7,Assumptions!$G$63)+Assumptions!$F$63+$C$8,Assumptions!$E$63) -> 0.08875 | H98: =IF(Recovery!G69=1,$C$9,IF(Assumptions!$I$63=1,MAX(H7,Assumptions!$G$63)+Assumptions!$F$63+$C$8,Assumptions!$E$63)) -> 0.08875 | I98: =IF(Recovery!H69=1,$C$9,IF(Assumptions!$I$63=1,MAX(I7,Assumptions!$G$63)+Assumptions!$F$63+$C$8,Assumptions!$E$63)) -> 0.08875 | J98: =IF(Recovery!I69=1,$C$9,IF(Assumptions!$I$63=1,MAX(J7,Assumptions!$G$63)+Assumptions!$F$63+$C$8,Assumptions!$E$63)) -> 0.08875 | K98: =IF(Recovery!J69=1,$C$9,IF(Assumptions!$I$63=1,MAX(K7,Assumptions!$G$63)+Assumptions!$F$63+$C$8,Assumptions!$E$63)) -> 0.08875
A99: Cash interest expense | G99: =G95*G98 -> 48.8125 | H99: =H95*H98 -> 48.8125 | I99: =I95*I98 -> 48.8125 | J99: =J95*J98 -> 48.8125 | K99: =K95*K98 -> 48.8125
A100: PIK interest | G100: =G95*Assumptions!$H$63 -> 0 | H100: =H95*Assumptions!$H$63 -> 0 | I100: =I95*Assumptions!$H$63 -> 0 | J100: =J95*Assumptions!$H$63 -> 0 | K100: =K95*Assumptions!$H$63 -> 0
A101: Mandatory amortization | G101: =MIN(G95,Assumptions!$L$63*Assumptions!$C$63) -> 0 | H101: =MIN(H95,Assumptions!$L$63*Assumptions!$C$63) -> 0 | I101: =MIN(I95,Assumptions!$L$63*Assumptions!$C$63) -> 0 | J101: =MIN(J95,Assumptions!$L$63*Assumptions!$C$63) -> 0 | K101: =MIN(K95,Assumptions!$L$63*Assumptions!$C$63) -> 0
A102: New borrowing (revolver draw) | G102: =IF(AND(Assumptions!$P$63=1,'Operating Model'!G7<Assumptions!$K$63),MIN(MAX(0,-'Cash Flow'!G11),MAX(0,Assumptions!$D$63-G95)),0) -> 0 | H102: =IF(AND(Assumptions!$P$63=1,OR('Operating Model'!H7<Assumptions!$K$63,Recovery!G69=1)),MIN(MAX(0,-'Cash Flow'!H11),MAX(0,Assumptions!$D$63-H95)),0) -> 0 | I102: =IF(AND(Assumptions!$P$63=1,OR('Operating Model'!I7<Assumptions!$K$63,Recovery!H69=1)),MIN(MAX(0,-'Cash Flow'!I11),MAX(0,Assumptions!$D$63-I95)),0) -> 0 | J102: =IF(AND(Assumptions!$P$63=1,OR('Operating Model'!J7<Assumptions!$K$63,Recovery!I69=1)),MIN(MAX(0,-'Cash Flow'!J11),MAX(0,Assumptions!$D$63-J95)),0) -> 0 | K102: =IF(AND(Assumptions!$P$63=1,OR('Operating Model'!K7<Assumptions!$K$63,Recovery!J69=1)),MIN(MAX(0,-'Cash Flow'!K11),MAX(0,Assumptions!$D$63-K95)),0) -> 0
A103: Repayment at maturity (from available cash) | G103: =G96*MIN(G95-G101+G100,MAX(0,'Cash Flow'!G13-Assumptions!$C$12*G15-G25-G38-G51-G64-G77-G90)) -> 0 | H103: =H96*MIN(H95-H101+H100,MAX(0,'Cash Flow'!H13-Assumptions!$C$12*H15-H25-H38-H51-H64-H77-H90)) -> 0 | I103: =I96*MIN(I95-I101+I100,MAX(0,'Cash Flow'!I13-Assumptions!$C$12*I15-I25-I38-I51-I64-I77-I90)) -> 0 | J103: =J96*MIN(J95-J101+J100,MAX(0,'Cash Flow'!J13-Assumptions!$C$12*J15-J25-J38-J51-J64-J77-J90)) -> 0 | K103: =K96*MIN(K95-K101+K100,MAX(0,'Cash Flow'!K13-Assumptions!$C$12*K15-K25-K38-K51-K64-K77-K90)) -> 0
A104: Optional repayment (cash sweep) | G104: =Assumptions!$N$63*MIN(G95+G102+G100-G101-G103,MAX(0,'Cash Flow'!G17-G26-G39-G52-G65-G78-G91)) -> 0 | H104: =Assumptions!$N$63*MIN(H95+H102+H100-H101-H103,MAX(0,'Cash Flow'!H17-H26-H39-H52-H65-H78-H91)) -> 0 | I104: =Assumptions!$N$63*MIN(I95+I102+I100-I101-I103,MAX(0,'Cash Flow'!I17-I26-I39-I52-I65-I78-I91)) -> 0 | J104: =Assumptions!$N$63*MIN(J95+J102+J100-J101-J103,MAX(0,'Cash Flow'!J17-J26-J39-J52-J65-J78-J91)) -> 0 | K104: =Assumptions!$N$63*MIN(K95+K102+K100-K101-K103,MAX(0,'Cash Flow'!K17-K26-K39-K52-K65-K78-K91)) -> 0
A105: Unpaid at maturity (no refinancing, insufficient cash) | G105: =G96*(1-G15)*(G95-G101+G100-G103) -> 0 | H105: =H96*(1-H15)*(H95-H101+H100-H103) -> 0 | I105: =I96*(1-I15)*(I95-I101+I100-I103) -> 550 | J105: =J96*(1-J15)*(J95-J101+J100-J103) -> 0 | K105: =K96*(1-K15)*(K95-K101+K100-K103) -> 0
A106: Ending balance | F106: =Assumptions!$C$63 -> 550 | G106: =G95+G102+G100-G101-G103-G104 -> 550 | H106: =H95+H102+H100-H101-H103-H104 -> 550 | I106: =I95+I102+I100-I101-I103-I104 -> 550 | J106: =J95+J102+J100-J101-J103-J104 -> 550 | K106: =K95+K102+K100-K101-K103-K104 -> 550
A107: Tranche 8: 4.55% Guaranteed Notes due Oct-2029
A108: Beginning balance | G108: =F119 -> 350 | H108: =G119 -> 350 | I108: =H119 -> 350 | J108: =I119 -> 350 | K108: =J119 -> 350
A109: Maturing this period? (1 = yes) | G109: =IF('Operating Model'!G7=Assumptions!$K$64,1,0) -> 0 | H109: =IF('Operating Model'!H7=Assumptions!$K$64,1,0) -> 0 | I109: =IF('Operating Model'!I7=Assumptions!$K$64,1,0) -> 0 | J109: =IF('Operating Model'!J7=Assumptions!$K$64,1,0) -> 1 | K109: =IF('Operating Model'!K7=Assumptions!$K$64,1,0) -> 0
...

Sheet Cash Flow
A1: Cash Flow & Liquidity — cash waterfall and default test
A2: ="Brandywine Realty Trust · PUBLIC DATA CASE · HYPOTHETICAL INVESTMENT TERMS · Active scenario: "&Assumptions!$D$10 -> Brandywine Realty Trust · PUBLIC DATA CASE · HYPOTHETICAL INVESTMENT TERMS · Active scenario: Downside
A4: $M | C4: FY2023A | D4: FY2024A | E4: FY2025A | F4: LTM Jun-26 | G4: LTM Jun-27E | H4: LTM Jun-28E | I4: LTM Jun-29E | J4: LTM Jun-30E | K4: LTM Jun-31E
A6: Cash flow & liquidity waterfall ($M)
A7: Beginning cash | G7: =F19 -> 37.87 | H7: =G19 -> 122.94742 | I7: =H19 -> 0 | J7: =I19 -> -70.879384 | K7: =J19 -> -137.89577
A8: Free cash flow (from Operating Model) | G8: ='Operating Model'!G30 -> -60.92258 | H8: ='Operating Model'!H30 -> -70.393778 | I8: ='Operating Model'!I30 -> -66.879384 | J8: ='Operating Model'!J30 -> -63.016387 | K8: ='Operating Model'!K30 -> -59.095916
A9: Plus: net asset-sale proceeds | G9: =CHOOSE(Assumptions!$C$10,Assumptions!$G$82,Assumptions!$G$101,Assumptions!$G$120) -> 150 | H9: =CHOOSE(Assumptions!$C$10,Assumptions!$H$82,Assumptions!$H$101,Assumptions!$H$120) -> 0 | I9: =CHOOSE(Assumptions!$C$10,Assumptions!$I$82,Assumptions!$I$101,Assumptions!$I$120) -> 0 | J9: =CHOOSE(Assumptions!$C$10,Assumptions!$J$82,Assumptions!$J$101,Assumptions!$J$120) -> 0 | K9: =CHOOSE(Assumptions!$C$10,Assumptions!$K$82,Assumptions!$K$101,Assumptions!$K$120) -> 0
A10: Less: mandatory amortization | G10: ='Debt Schedule'!G23+'Debt Schedule'!G36+'Debt Schedule'!G49+'Debt Schedule'!G62+'Debt Schedule'!G75+'Debt Schedule'!G88+'Debt Schedule'!G101+'Debt Schedule'!G114+'Debt Schedule'!G127+'Debt Schedule'!G140 -> 4 | H10: ='Debt Schedule'!H23+'Debt Schedule'!H36+'Debt Schedule'!H49+'Debt Schedule'!H62+'Debt Schedule'!H75+'Debt Schedule'!H88+'Debt Schedule'!H101+'Debt Schedule'!H114+'Debt Schedule'!H127+'Debt Schedule'!H140 -> 4 | I10: ='Debt Schedule'!I23+'Debt Schedule'!I36+'Debt Schedule'!I49+'Debt Schedule'!I62+'Debt Schedule'!I75+'Debt Schedule'!I88+'Debt Schedule'!I101+'Debt Schedule'!I114+'Debt Schedule'!I127+'Debt Schedule'!I140 -> 4 | J10: ='Debt Schedule'!J23+'Debt Schedule'!J36+'Debt Schedule'!J49+'Debt Schedule'!J62+'Debt Schedule'!J75+'Debt Schedule'!J88+'Debt Schedule'!J101+'Debt Schedule'!J114+'Debt Schedule'!J127+'Debt Schedule'!J140 -> 4 | K10: ='Debt Schedule'!K23+'Debt Schedule'!K36+'Debt Schedule'!K49+'Debt Schedule'!K62+'Debt Schedule'!K75+'Debt Schedule'!K88+'Debt Schedule'!K101+'Debt Schedule'!K114+'Debt Schedule'!K127+'Debt Schedule'!K140 -> 4
A11: Cash after mandatory debt service | G11: =G7+G8+G9-G10 -> 122.94742 | H11: =H7+H8+H9-H10 -> 48.553642 | I11: =I7+I8+I9-I10 -> -70.879384 | J11: =J7+J8+J9-J10 -> -137.89577 | K11: =K7+K8+K9-K10 -> -200.99169
A12: Plus: revolver draw | G12: ='Debt Schedule'!G24+'Debt Schedule'!G37+'Debt Schedule'!G50+'Debt Schedule'!G63+'Debt Schedule'!G76+'Debt Schedule'!G89+'Debt Schedule'!G102+'Debt Schedule'!G115+'Debt Schedule'!G128+'Debt Schedule'!G141 -> 0 | H12: ='Debt Schedule'!H24+'Debt Schedule'!H37+'Debt Schedule'!H50+'Debt Schedule'!H63+'Debt Schedule'!H76+'Debt Schedule'!H89+'Debt Schedule'!H102+'Debt Schedule'!H115+'Debt Schedule'!H128+'Debt Schedule'!H141 -> 0 | I12: ='Debt Schedule'!I24+'Debt Schedule'!I37+'Debt Schedule'!I50+'Debt Schedule'!I63+'Debt Schedule'!I76+'Debt Schedule'!I89+'Debt Schedule'!I102+'Debt Schedule'!I115+'Debt Schedule'!I128+'Debt Schedule'!I141 -> 0 | J12: ='Debt Schedule'!J24+'Debt Schedule'!J37+'Debt Schedule'!J50+'Debt Schedule'!J63+'Debt Schedule'!J76+'Debt Schedule'!J89+'Debt Schedule'!J102+'Debt Schedule'!J115+'Debt Schedule'!J128+'Debt Schedule'!J141 -> 0 | K12: ='Debt Schedule'!K24+'Debt Schedule'!K37+'Debt Schedule'!K50+'Debt Schedule'!K63+'Debt Schedule'!K76+'Debt Schedule'!K89+'Debt Schedule'!K102+'Debt Schedule'!K115+'Debt Schedule'!K128+'Debt Schedule'!K141 -> 0
A13: Cash available for maturities | G13: =G11+G12 -> 122.94742 | H13: =H11+H12 -> 48.553642 | I13: =I11+I12 -> -70.879384 | J13: =J11+J12 -> -137.89577 | K13: =K11+K12 -> -200.99169
A14: Less: repayment of maturing debt | G14: ='Debt Schedule'!G25+'Debt Schedule'!G38+'Debt Schedule'!G51+'Debt Schedule'!G64+'Debt Schedule'!G77+'Debt Schedule'!G90+'Debt Schedule'!G103+'Debt Schedule'!G116+'Debt Schedule'!G129+'Debt Schedule'!G142 -> 0 | H14: ='Debt Schedule'!H25+'Debt Schedule'!H38+'Debt Schedule'!H51+'Debt Schedule'!H64+'Debt Schedule'!H77+'Debt Schedule'!H90+'Debt Schedule'!H103+'Debt Schedule'!H116+'Debt Schedule'!H129+'Debt Schedule'!H142 -> 48.553642 | I14: ='Debt Schedule'!I25+'Debt Schedule'!I38+'Debt Schedule'!I51+'Debt Schedule'!I64+'Debt Schedule'!I77+'Debt Schedule'!I90+'Debt Schedule'!I103+'Debt Schedule'!I116+'Debt Schedule'!I129+'Debt Schedule'!I142 -> 0 | J14: ='Debt Schedule'!J25+'Debt Schedule'!J38+'Debt Schedule'!J51+'Debt Schedule'!J64+'Debt Schedule'!J77+'Debt Schedule'!J90+'Debt Schedule'!J103+'Debt Schedule'!J116+'Debt Schedule'!J129+'Debt Schedule'!J142 -> 0 | K14: ='Debt Schedule'!K25+'Debt Schedule'!K38+'Debt Schedule'!K51+'Debt Schedule'!K64+'Debt Schedule'!K77+'Debt Schedule'!K90+'Debt Schedule'!K103+'Debt Schedule'!K116+'Debt Schedule'!K129+'Debt Schedule'!K142 -> 0
A15: Cash before sweep | G15: =G13-G14 -> 122.94742 | H15: =H13-H14 -> 0 | I15: =I13-I14 -> -70.879384 | J15: =J13-J14 -> -137.89577 | K15: =K13-K14 -> -200.99169
A16: Funding gap (shortfall after cash & revolver) | G16: =MAX(0,-G15) -> 0 | H16: =MAX(0,-H15) -> 0 | I16: =MAX(0,-I15) -> 70.879384 | J16: =MAX(0,-J15) -> 137.89577 | K16: =MAX(0,-K15) -> 200.99169
A17: Excess cash available for sweep | G17: =MAX(0,G15-Assumptions!$C$12)*Assumptions!$C$13 -> 0 | H17: =MAX(0,H15-Assumptions!$C$12)*Assumptions!$C$13 -> 0 | I17: =MAX(0,I15-Assumptions!$C$12)*Assumptions!$C$13 -> 0 | J17: =MAX(0,J15-Assumptions!$C$12)*Assumptions!$C$13 -> 0 | K17: =MAX(0,K15-Assumptions!$C$12)*Assumptions!$C$13 -> 0
A18: Less: optional repayment (cash sweep) | G18: ='Debt Schedule'!G26+'Debt Schedule'!G39+'Debt Schedule'!G52+'Debt Schedule'!G65+'Debt Schedule'!G78+'Debt Schedule'!G91+'Debt Schedule'!G104+'Debt Schedule'!G117+'Debt Schedule'!G130+'Debt Schedule'!G143 -> 0 | H18: ='Debt Schedule'!H26+'Debt Schedule'!H39+'Debt Schedule'!H52+'Debt Schedule'!H65+'Debt Schedule'!H78+'Debt Schedule'!H91+'Debt Schedule'!H104+'Debt Schedule'!H117+'Debt Schedule'!H130+'Debt Schedule'!H143 -> 0 | I18: ='Debt Schedule'!I26+'Debt Schedule'!I39+'Debt Schedule'!I52+'Debt Schedule'!I65+'Debt Schedule'!I78+'Debt Schedule'!I91+'Debt Schedule'!I104+'Debt Schedule'!I117+'Debt Schedule'!I130+'Debt Schedule'!I143 -> 0 | J18: ='Debt Schedule'!J26+'Debt Schedule'!J39+'Debt Schedule'!J52+'Debt Schedule'!J65+'Debt Schedule'!J78+'Debt Schedule'!J91+'Debt Schedule'!J104+'Debt Schedule'!J117+'Debt Schedule'!J130+'Debt Schedule'!J143 -> 0 | K18: ='Debt Schedule'!K26+'Debt Schedule'!K39+'Debt Schedule'!K52+'Debt Schedule'!K65+'Debt Schedule'!K78+'Debt Schedule'!K91+'Debt Schedule'!K104+'Debt Schedule'!K117+'Debt Schedule'!K130+'Debt Schedule'!K143 -> 0
A19: Ending cash | F19: =Assumptions!$C$11 -> 37.87 | G19: =G15-G18 -> 122.94742 | H19: =H15-H18 -> 0 | I19: =I15-I18 -> -70.879384 | J19: =J15-J18 -> -137.89577 | K19: =K15-K18 -> -200.99169
A20: Unpaid maturities (balance left outstanding) | G20: ='Debt Schedule'!G27+'Debt Schedule'!G40+'Debt Schedule'!G53+'Debt Schedule'!G66+'Debt Schedule'!G79+'Debt Schedule'!G92+'Debt Schedule'!G105+'Debt Schedule'!G118+'Debt Schedule'!G131+'Debt Schedule'!G144 -> 0 | H20: ='Debt Schedule'!H27+'Debt Schedule'!H40+'Debt Schedule'!H53+'Debt Schedule'!H66+'Debt Schedule'!H79+'Debt Schedule'!H92+'Debt Schedule'!H105+'Debt Schedule'!H118+'Debt Schedule'!H131+'Debt Schedule'!H144 -> 751.44636 | I20: ='Debt Schedule'!I27+'Debt Schedule'!I40+'Debt Schedule'!I53+'Debt Schedule'!I66+'Debt Schedule'!I79+'Debt Schedule'!I92+'Debt Schedule'!I105+'Debt Schedule'!I118+'Debt Schedule'!I131+'Debt Schedule'!I144 -> 550 | J20: ='Debt Schedule'!J27+'Debt Schedule'!J40+'Debt Schedule'!J53+'Debt Schedule'!J66+'Debt Schedule'!J79+'Debt Schedule'!J92+'Debt Schedule'!J105+'Debt Schedule'!J118+'Debt Schedule'!J131+'Debt Schedule'!J144 -> 350 | K20: ='Debt Schedule'!K27+'Debt Schedule'!K40+'Debt Schedule'!K53+'Debt Schedule'!K66+'Debt Schedule'!K79+'Debt Schedule'!K92+'Debt Schedule'!K105+'Debt Schedule'!K118+'Debt Schedule'!K131+'Debt Schedule'!K144 -> 680
A21: Payment default? (1 = yes) | G21: =IF(OR(G16>0.001,G20>0.001),1,0) -> 0 | H21: =IF(OR(H16>0.001,H20>0.001),1,0) -> 1 | I21: =IF(OR(I16>0.001,I20>0.001),1,0) -> 1 | J21: =IF(OR(J16>0.001,J20>0.001),1,0) -> 1 | K21: =IF(OR(K16>0.001,K20>0.001),1,0) -> 1
A22: First default period flag | G22: =IF(G21=1,1,0) -> 0 | H22: =IF(AND(H21=1,SUM($G$21:G21)=0),1,0) -> 1 | I22: =IF(AND(I21=1,SUM($G$21:H21)=0),1,0) -> 0 | J22: =IF(AND(J21=1,SUM($G$21:I21)=0),1,0) -> 0 | K22: =IF(AND(K21=1,SUM($G$21:J21)=0),1,0) -> 0
A23: Check: Δ debt = draws + PIK − repayments | G23: =('Debt Schedule'!G147-'Debt Schedule'!F147)-(G12+'Operating Model'!G22-G10-G14-G18) -> 0 | H23: =('Debt Schedule'!H147-'Debt Schedule'!G147)-(H12+'Operating Model'!H22-H10-H14-H18) -> -3.8369308e-13 | I23: =('Debt Schedule'!I147-'Debt Schedule'!H147)-(I12+'Operating Model'!I22-I10-I14-I18) -> 0 | J23: =('Debt Schedule'!J147-'Debt Schedule'!I147)-(J12+'Operating Model'!J22-J10-J14-J18) -> 0 | K23: =('Debt Schedule'!K147-'Debt Schedule'!J147)-(K12+'Operating Model'!K22-K10-K14-K18) -> 0

Sheet Credit Metrics
A1: Credit Metrics, Covenants & Credit Score
A2: ="Brandywine Realty Trust · PUBLIC DATA CASE · HYPOTHETICAL INVESTMENT TERMS · Active scenario: "&Assumptions!$D$10 -> Brandywine Realty Trust · PUBLIC DATA CASE · HYPOTHETICAL INVESTMENT TERMS · Active scenario: Downside
A4: $M | C4: FY2023A | D4: FY2024A | E4: FY2025A | F4: LTM Jun-26 | G4: LTM Jun-27E | H4: LTM Jun-28E | I4: LTM Jun-29E | J4: LTM Jun-30E | K4: LTM Jun-31E
A6: Credit metrics (selected scenario)
A7: Total debt (face value) | F7: ='Debt Schedule'!F147 -> 2625.934 | G7: ='Debt Schedule'!G147 -> 2621.934 | H7: ='Debt Schedule'!H147 -> 2569.3804 | I7: ='Debt Schedule'!I147 -> 2565.3804 | J7: ='Debt Schedule'!J147 -> 2561.3804 | K7: ='Debt Schedule'!K147 -> 2557.3804
A8: Secured debt | F8: =Assumptions!$O$57*'Debt Schedule'!F28+Assumptions!$O$58*'Debt Schedule'!F41+Assumptions!$O$59*'Debt Schedule'!F54+Assumptions!$O$60*'Debt Schedule'!F67+Assumptions!$O$61*'Debt Schedule'!F80+Assumptions!$O$62*'Debt Schedule'!F93+Assumptions!$O$63*'Debt Schedule'!F106+Assumptions!$O$64*'Debt Schedule'!F119+Assumptions!$O$65*'Debt Schedule'!F132+Assumptions!$O$66*'Debt Schedule'!F145 -> 547.324 | G8: =Assumptions!$O$57*'Debt Schedule'!G28+Assumptions!$O$58*'Debt Schedule'!G41+Assumptions!$O$59*'Debt Schedule'!G54+Assumptions!$O$60*'Debt Schedule'!G67+Assumptions!$O$61*'Debt Schedule'!G80+Assumptions!$O$62*'Debt Schedule'!G93+Assumptions!$O$63*'Debt Schedule'!G106+Assumptions!$O$64*'Debt Schedule'!G119+Assumptions!$O$65*'Debt Schedule'!G132+Assumptions!$O$66*'Debt Schedule'!G145 -> 543.324 | H8: =Assumptions!$O$57*'Debt Schedule'!H28+Assumptions!$O$58*'Debt Schedule'!H41+Assumptions!$O$59*'Debt Schedule'!H54+Assumptions!$O$60*'Debt Schedule'!H67+Assumptions!$O$61*'Debt Schedule'!H80+Assumptions!$O$62*'Debt Schedule'!H93+Assumptions!$O$63*'Debt Schedule'!H106+Assumptions!$O$64*'Debt Schedule'!H119+Assumptions!$O$65*'Debt Schedule'!H132+Assumptions!$O$66*'Debt Schedule'!H145 -> 539.324 | I8: =Assumptions!$O$57*'Debt Schedule'!I28+Assumptions!$O$58*'Debt Schedule'!I41+Assumptions!$O$59*'Debt Schedule'!I54+Assumptions!$O$60*'Debt Schedule'!I67+Assumptions!$O$61*'Debt Schedule'!I80+Assumptions!$O$62*'Debt Schedule'!I93+Assumptions!$O$63*'Debt Schedule'!I106+Assumptions!$O$64*'Debt Schedule'!I119+Assumptions!$O$65*'Debt Schedule'!I132+Assumptions!$O$66*'Debt Schedule'!I145 -> 535.324 | J8: =Assumptions!$O$57*'Debt Schedule'!J28+Assumptions!$O$58*'Debt Schedule'!J41+Assumptions!$O$59*'Debt Schedule'!J54+Assumptions!$O$60*'Debt Schedule'!J67+Assumptions!$O$61*'Debt Schedule'!J80+Assumptions!$O$62*'Debt Schedule'!J93+Assumptions!$O$63*'Debt Schedule'!J106+Assumptions!$O$64*'Debt Schedule'!J119+Assumptions!$O$65*'Debt Schedule'!J132+Assumptions!$O$66*'Debt Schedule'!J145 -> 531.324 | K8: =Assumptions!$O$57*'Debt Schedule'!K28+Assumptions!$O$58*'Debt Schedule'!K41+Assumptions!$O$59*'Debt Schedule'!K54+Assumptions!$O$60*'Debt Schedule'!K67+Assumptions!$O$61*'Debt Schedule'!K80+Assumptions!$O$62*'Debt Schedule'!K93+Assumptions!$O$63*'Debt Schedule'!K106+Assumptions!$O$64*'Debt Schedule'!K119+Assumptions!$O$65*'Debt Schedule'!K132+Assumptions!$O$66*'Debt Schedule'!K145 -> 527.324
A9: Net debt | F9: =F7-'Cash Flow'!F19 -> 2588.064 | G9: =G7-'Cash Flow'!G19 -> 2498.9866 | H9: =H7-'Cash Flow'!H19 -> 2569.3804 | I9: =I7-'Cash Flow'!I19 -> 2636.2597 | J9: =J7-'Cash Flow'!J19 -> 2699.2761 | K9: =K7-'Cash Flow'!K19 -> 2758.372
A10: Gross debt / EBITDA | F10: =IF('Operating Model'!F17>0,F7/'Operating Model'!F17,0) -> 9.9212776 | G10: =IF('Operating Model'!G17>0,G7/'Operating Model'!G17,0) -> 11.195432 | H10: =IF('Operating Model'!H17>0,H7/'Operating Model'!H17,0) -> 11.660147 | I10: =IF('Operating Model'!I17>0,I7/'Operating Model'!I17,0) -> 11.641995 | J10: =IF('Operating Model'!J17>0,J7/'Operating Model'!J17,0) -> 11.391318 | K10: =IF('Operating Model'!K17>0,K7/'Operating Model'!K17,0) -> 11.147173
A11: Net debt / EBITDA | F11: =IF('Operating Model'!F17>0,F9/'Operating Model'!F17,0) -> 9.7781976 | G11: =IF('Operating Model'!G17>0,G9/'Operating Model'!G17,0) -> 10.670457 | H11: =IF('Operating Model'!H17>0,H9/'Operating Model'!H17,0) -> 11.660147 | I11: =IF('Operating Model'!I17>0,I9/'Operating Model'!I17,0) -> 11.963654 | J11: =IF('Operating Model'!J17>0,J9/'Operating Model'!J17,0) -> 12.004587 | K11: =IF('Operating Model'!K17>0,K9/'Operating Model'!K17,0) -> 12.023261
A12: Interest coverage (EBITDA / cash interest) | F12: =IF('Operating Model'!F23>0,'Operating Model'!F17/'Operating Model'!F23,0) -> 1.7233258 | G12: =IF('Operating Model'!G21>0,'Operating Model'!G17/'Operating Model'!G21,0) -> 1.2497904 | H12: =IF('Operating Model'!H21>0,'Operating Model'!H17/'Operating Model'!H21,0) -> 1.1831122 | I12: =IF('Operating Model'!I21>0,'Operating Model'!I17/'Operating Model'!I21,0) -> 1.2058659 | J12: =IF('Operating Model'!J21>0,'Operating Model'!J17/'Operating Model'!J21,0) -> 1.2332475 | K12: =IF('Operating Model'!K21>0,'Operating Model'!K17/'Operating Model'!K21,0) -> 1.2611258
A13: EBIT / interest | F13: =IF('Operating Model'!F23>0,'Operating Model'!F20/'Operating Model'!F23,0) -> 0.51687339 | G13: =IF('Operating Model'!G21>0,'Operating Model'!G20/'Operating Model'!G21,0) -> 0.32030377 | H13: =IF('Operating Model'!H21>0,'Operating Model'!H20/'Operating Model'!H21,0) -> 0.27600177 | I13: =IF('Operating Model'!I21>0,'Operating Model'!I20/'Operating Model'!I21,0) -> 0.28130984 | J13: =IF('Operating Model'!J21>0,'Operating Model'!J20/'Operating Model'!J21,0) -> 0.29734601 | K13: =IF('Operating Model'!K21>0,'Operating Model'!K20/'Operating Model'!K21,0) -> 0.31373497
A14: FCF / debt | F14: =IF(F7>0,'Operating Model'!F30/F7,0) -> -0.0027445473 | G14: =IF(G7>0,'Operating Model'!G30/G7,0) -> -0.023235741 | H14: =IF(H7>0,'Operating Model'!H30/H7,0) -> -0.027397181 | I14: =IF(I7>0,'Operating Model'!I30/I7,0) -> -0.026069968 | J14: =IF(J7>0,'Operating Model'!J30/J7,0) -> -0.024602511 | K14: =IF(K7>0,'Operating Model'!K30/K7,0) -> -0.023107988
A15: Debt service coverage ((EBITDA − capex − tax) / (cash interest + amortization)) | G15: =IF('Operating Model'!G21+'Cash Flow'!G10>0,('Operating Model'!G17-'Operating Model'!G28-'Operating Model'!G25)/('Operating Model'!G21+'Cash Flow'!G10),0) -> 0.78314878 | H15: =IF('Operating Model'!H21+'Cash Flow'!H10>0,('Operating Model'!H17-'Operating Model'!H28-'Operating Model'!H25)/('Operating Model'!H21+'Cash Flow'!H10),0) -> 0.72837613 | I15: =IF('Operating Model'!I21+'Cash Flow'!I10>0,('Operating Model'!I17-'Operating Model'!I28-'Operating Model'!I25)/('Operating Model'!I21+'Cash Flow'!I10),0) -> 0.74208422 | J15: =IF('Operating Model'!J21+'Cash Flow'!J10>0,('Operating Model'!J17-'Operating Model'!J28-'Operating Model'!J25)/('Operating Model'!J21+'Cash Flow'!J10),0) -> 0.7634683 | K15: =IF('Operating Model'!K21+'Cash Flow'!K10>0,('Operating Model'!K17-'Operating Model'!K28-'Operating Model'!K25)/('Operating Model'!K21+'Cash Flow'!K10),0) -> 0.78526806
A16: Liquidity (cash + undrawn revolver) | F16: =MAX(0,'Cash Flow'!F19)+Assumptions!$P$57*MAX(0,Assumptions!$D$57-'Debt Schedule'!F28)+Assumptions!$P$58*MAX(0,Assumptions!$D$58-'Debt Schedule'!F41)+Assumptions!$P$59*MAX(0,Assumptions!$D$59-'Debt Schedule'!F54)+Assumptions!$P$60*MAX(0,Assumptions!$D$60-'Debt Schedule'!F67)+Assumptions!$P$61*MAX(0,Assumptions!$D$61-'Debt Schedule'!F80)+Assumptions!$P$62*MAX(0,Assumptions!$D$62-'Debt Schedule'!F93)+Assumptions!$P$63*MAX(0,Assumptions!$D$63-'Debt Schedule'!F106)+Assumptions!$P$64*MAX(0,Assumptions!$D$64-'Debt Schedule'!F119)+Assumptions!$P$65*MAX(0,Assumptions!$D$65-'Debt Schedule'!F132)+Assumptions!$P$66*MAX(0,Assumptions!$D$66-'Debt Schedule'!F145) -> 612.37 | G16: =MAX(0,'Cash Flow'!G19)+Assumptions!$P$57*MAX(0,Assumptions!$D$57-'Debt Schedule'!G28)+Assumptions!$P$58*MAX(0,Assumptions!$D$58-'Debt Schedule'!G41)+Assumptions!$P$59*MAX(0,Assumptions!$D$59-'Debt Schedule'!G54)+Assumptions!$P$60*MAX(0,Assumptions!$D$60-'Debt Schedule'!G67)+Assumptions!$P$61*MAX(0,Assumptions!$D$61-'Debt Schedule'!G80)+Assumptions!$P$62*MAX(0,Assumptions!$D$62-'Debt Schedule'!G93)+Assumptions!$P$63*MAX(0,Assumptions!$D$63-'Debt Schedule'!G106)+Assumptions!$P$64*MAX(0,Assumptions!$D$64-'Debt Schedule'!G119)+Assumptions!$P$65*MAX(0,Assumptions!$D$65-'Debt Schedule'!G132)+Assumptions!$P$66*MAX(0,Assumptions!$D$66-'Debt Schedule'!G145) -> 697.44742 | H16: =MAX(0,'Cash Flow'!H19)+Assumptions!$P$57*MAX(0,Assumptions!$D$57-'Debt Schedule'!H28)+Assumptions!$P$58*MAX(0,Assumptions!$D$58-'Debt Schedule'!H41)+Assumptions!$P$59*MAX(0,Assumptions!$D$59-'Debt Schedule'!H54)+Assumptions!$P$60*MAX(0,Assumptions!$D$60-'Debt Schedule'!H67)+Assumptions!$P$61*MAX(0,Assumptions!$D$61-'Debt Schedule'!H80)+Assumptions!$P$62*MAX(0,Assumptions!$D$62-'Debt Schedule'!H93)+Assumptions!$P$63*MAX(0,Assumptions!$D$63-'Debt Schedule'!H106)+Assumptions!$P$64*MAX(0,Assumptions!$D$64-'Debt Schedule'!H119)+Assumptions!$P$65*MAX(0,Assumptions!$D$65-'Debt Schedule'!H132)+Assumptions!$P$66*MAX(0,Assumptions!$D$66-'Debt Schedule'!H145) -> 574.5 | I16: =MAX(0,'Cash Flow'!I19)+Assumptions!$P$57*MAX(0,Assumptions!$D$57-'Debt Schedule'!I28)+Assumptions!$P$58*MAX(0,Assumptions!$D$58-'Debt Schedule'!I41)+Assumptions!$P$59*MAX(0,Assumptions!$D$59-'Debt Schedule'!I54)+Assumptions!$P$60*MAX(0,Assumptions!$D$60-'Debt Schedule'!I67)+Assumptions!$P$61*MAX(0,Assumptions!$D$61-'Debt Schedule'!I80)+Assumptions!$P$62*MAX(0,Assumptions!$D$62-'Debt Schedule'!I93)+Assumptions!$P$63*MAX(0,Assumptions!$D$63-'Debt Schedule'!I106)+Assumptions!$P$64*MAX(0,Assumptions!$D$64-'Debt Schedule'!I119)+Assumptions!$P$65*MAX(0,Assumptions!$D$65-'Debt Schedule'!I132)+Assumptions!$P$66*MAX(0,Assumptions!$D$66-'Debt Schedule'!I145) -> 574.5 | J16: =MAX(0,'Cash Flow'!J19)+Assumptions!$P$57*MAX(0,Assumptions!$D$57-'Debt Schedule'!J28)+Assumptions!$P$58*MAX(0,Assumptions!$D$58-'Debt Schedule'!J41)+Assumptions!$P$59*MAX(0,Assumptions!$D$59-'Debt Schedule'!J54)+Assumptions!$P$60*MAX(0,Assumptions!$D$60-'Debt Schedule'!J67)+Assumptions!$P$61*MAX(0,Assumptions!$D$61-'Debt Schedule'!J80)+Assumptions!$P$62*MAX(0,Assumptions!$D$62-'Debt Schedule'!J93)+Assumptions!$P$63*MAX(0,Assumptions!$D$63-'Debt Schedule'!J106)+Assumptions!$P$64*MAX(0,Assumptions!$D$64-'Debt Schedule'!J119)+Assumptions!$P$65*MAX(0,Assumptions!$D$65-'Debt Schedule'!J132)+Assumptions!$P$66*MAX(0,Assumptions!$D$66-'Debt Schedule'!J145) -> 574.5 | K16: =MAX(0,'Cash Flow'!K19)+Assumptions!$P$57*MAX(0,Assumptions!$D$57-'Debt Schedule'!K28)+Assumptions!$P$58*MAX(0,Assumptions!$D$58-'Debt Schedule'!K41)+Assumptions!$P$59*MAX(0,Assumptions!$D$59-'Debt Schedule'!K54)+Assumptions!$P$60*MAX(0,Assumptions!$D$60-'Debt Schedule'!K67)+Assumptions!$P$61*MAX(0,Assumptions!$D$61-'Debt Schedule'!K80)+Assumptions!$P$62*MAX(0,Assumptions!$D$62-'Debt Schedule'!K93)+Assumptions!$P$63*MAX(0,Assumptions!$D$63-'Debt Schedule'!K106)+Assumptions!$P$64*MAX(0,Assumptions!$D$64-'Debt Schedule'!K119)+Assumptions!$P$65*MAX(0,Assumptions!$D$65-'Debt Schedule'!K132)+Assumptions!$P$66*MAX(0,Assumptions!$D$66-'Debt Schedule'!K145) -> 574.5
A17: Debt / capital (debt + implied equity) | G17: =IF(G7>0,G7/(G7+MAX(0,'Operating Model'!G17*CHOOSE(Assumptions!$C$10,Assumptions!$C$90,Assumptions!$C$109,Assumptions!$C$128)-G9)),0) -> 0.97140619 | H17: =IF(H7>0,H7/(H7+MAX(0,'Operating Model'!H17*CHOOSE(Assumptions!$C$10,Assumptions!$C$90,Assumptions!$C$109,Assumptions!$C$128)-H9)),0) -> 1 | I17: =IF(I7>0,I7/(I7+MAX(0,'Operating Model'!I17*CHOOSE(Assumptions!$C$10,Assumptions!$C$90,Assumptions!$C$109,Assumptions!$C$128)-I9)),0) -> 1 | J17: =IF(J7>0,J7/(J7+MAX(0,'Operating Model'!J17*CHOOSE(Assumptions!$C$10,Assumptions!$C$90,Assumptions!$C$109,Assumptions!$C$128)-J9)),0) -> 1 | K17: =IF(K7>0,K7/(K7+MAX(0,'Operating Model'!K17*CHOOSE(Assumptions!$C$10,Assumptions!$C$90,Assumptions!$C$109,Assumptions!$C$128)-K9)),0) -> 1
A18: Cash / debt | F18: =IF(F7>0,MAX(0,'Cash Flow'!F19)/F7,0) -> 0.014421535 | G18: =IF(G7>0,MAX(0,'Cash Flow'!G19)/G7,0) -> 0.046891882 | H18: =IF(H7>0,MAX(0,'Cash Flow'!H19)/H7,0) -> 0 | I18: =IF(I7>0,MAX(0,'Cash Flow'!I19)/I7,0) -> 0 | J18: =IF(J7>0,MAX(0,'Cash Flow'!J19)/J7,0) -> 0 | K18: =IF(K7>0,MAX(0,'Cash Flow'!K19)/K7,0) -> 0
A19: Asset value after scenario decline | G19: =Assumptions!$C$31*(1-CHOOSE(Assumptions!$C$10,Assumptions!$C$93,Assumptions!$C$112,Assumptions!$C$131)) -> 3840.0456 | H19: =Assumptions!$C$31*(1-CHOOSE(Assumptions!$C$10,Assumptions!$C$93,Assumptions!$C$112,Assumptions!$C$131)) -> 3840.0456 | I19: =Assumptions!$C$31*(1-CHOOSE(Assumptions!$C$10,Assumptions!$C$93,Assumptions!$C$112,Assumptions!$C$131)) -> 3840.0456 | J19: =Assumptions!$C$31*(1-CHOOSE(Assumptions!$C$10,Assumptions!$C$93,Assumptions!$C$112,Assumptions!$C$131)) -> 3840.0456 | K19: =Assumptions!$C$31*(1-CHOOSE(Assumptions!$C$10,Assumptions!$C$93,Assumptions!$C$112,Assumptions!$C$131)) -> 3840.0456
A20: Covenant compliance (active covenants; tests use model-basis metrics)
A21: Credit agreement: leverage ratio ≤ 0.60 (debt ÷ total asset value) — PROXY at analyst cap rate [DISCLOSED]
A22: Metric | G22: =IF(G19>0,G7/G19,99) -> 0.68278721 | H22: =IF(H19>0,H7/H19,99) -> 0.66910153 | I22: =IF(I19>0,I7/I19,99) -> 0.66805987 | J22: =IF(J19>0,J7/J19,99) -> 0.66701822 | K22: =IF(K19>0,K7/K19,99) -> 0.66597657
A23: Covenant threshold | G23: =Assumptions!$G$71 -> 0.6 | H23: =Assumptions!$H$71 -> 0.6 | I23: =Assumptions!$I$71 -> 0.6 | J23: =Assumptions!$J$71 -> 0.6 | K23: =Assumptions!$K$71 -> 0.6
A24: Headroom | G24: =G23-G22 -> -0.08278721 | H24: =H23-H22 -> -0.069101528 | I24: =I23-I22 -> -0.068059874 | J24: =J23-J22 -> -0.06701822 | K24: =K23-K22 -> -0.065976566
A25: Headroom % of threshold | G25: =IF(G23=0,0,G24/ABS(G23)) -> -0.13797868 | H25: =IF(H23=0,0,H24/ABS(H23)) -> -0.11516921 | I25: =IF(I23=0,0,I24/ABS(I23)) -> -0.11343312 | J25: =IF(J23=0,0,J24/ABS(J23)) -> -0.11169703 | K25: =IF(K23=0,0,K24/ABS(K23)) -> -0.10996094
A26: BREACH? (1 = yes) | G26: =IF(G24<0,1,0) -> 1 | H26: =IF(H24<0,1,0) -> 1 | I26: =IF(I24<0,1,0) -> 1 | J26: =IF(J24<0,1,0) -> 1 | K26: =IF(K24<0,1,0) -> 1
A27: First breach period (0 = none) | C27: =IFERROR(INDEX('Operating Model'!$G$7:$K$7,MATCH(1,$G$26:$K$26,0)),0) -> 2027
A28: Minimum headroom % | C28: =MIN($G$25:$K$25) -> -0.13797868
A29: Credit agreement: fixed-charge coverage ≥ 1.5x — PROXY (EBITDA ÷ cash interest) [DISCLOSED]
A30: Metric | G30: =IF('Operating Model'!G21>0,'Operating Model'!G17/'Operating Model'!G21,99) -> 1.2497904 | H30: =IF('Operating Model'!H21>0,'Operating Model'!H17/'Operating Model'!H21,99) -> 1.1831122 | I30: =IF('Operating Model'!I21>0,'Operating Model'!I17/'Operating Model'!I21,99) -> 1.2058659 | J30: =IF('Operating Model'!J21>0,'Operating Model'!J17/'Operating Model'!J21,99) -> 1.2332475 | K30: =IF('Operating Model'!K21>0,'Operating Model'!K17/'Operating Model'!K21,99) -> 1.2611258
A31: Covenant threshold | G31: =Assumptions!$G$72 -> 1.5 | H31: =Assumptions!$H$72 -> 1.5 | I31: =Assumptions!$I$72 -> 1.5 | J31: =Assumptions!$J$72 -> 1.5 | K31: =Assumptions!$K$72 -> 1.5
A32: Headroom | G32: =G30-G31 -> -0.25020959 | H32: =H30-H31 -> -0.31688777 | I32: =I30-I31 -> -0.29413413 | J32: =J30-J31 -> -0.26675255 | K32: =K30-K31 -> -0.23887417
A33: Headroom % of threshold | G33: =IF(G31=0,0,G32/ABS(G31)) -> -0.16680639 | H33: =IF(H31=0,0,H32/ABS(H31)) -> -0.21125852 | I33: =IF(I31=0,0,I32/ABS(I31)) -> -0.19608942 | J33: =IF(J31=0,0,J32/ABS(J31)) -> -0.17783503 | K33: =IF(K31=0,0,K32/ABS(K31)) -> -0.15924944
A34: BREACH? (1 = yes) | G34: =IF(G32<0,1,0) -> 1 | H34: =IF(H32<0,1,0) -> 1 | I34: =IF(I32<0,1,0) -> 1 | J34: =IF(J32<0,1,0) -> 1 | K34: =IF(K32<0,1,0) -> 1
A35: First breach period (0 = none) | C35: =IFERROR(INDEX('Operating Model'!$G$7:$K$7,MATCH(1,$G$34:$K$34,0)),0) -> 2027
A36: Minimum headroom % | C36: =MIN($G$33:$K$33) -> -0.21125852
A37: Credit agreement: secured debt ÷ total asset value ≤ 0.40 — PROXY [DISCLOSED]
A38: Metric | G38: =IF(G19>0,G8/G19,99) -> 0.14148895 | H38: =IF(H19>0,H8/H19,99) -> 0.14044729 | I38: =IF(I19>0,I8/I19,99) -> 0.13940564 | J38: =IF(J19>0,J8/J19,99) -> 0.13836398 | K38: =IF(K19>0,K8/K19,99) -> 0.13732233
A39: Covenant threshold | G39: =Assumptions!$G$73 -> 0.4 | H39: =Assumptions!$H$73 -> 0.4 | I39: =Assumptions!$I$73 -> 0.4 | J39: =Assumptions!$J$73 -> 0.4 | K39: =Assumptions!$K$73 -> 0.4
A40: Headroom | G40: =G39-G38 -> 0.25851105 | H40: =H39-H38 -> 0.25955271 | I40: =I39-I38 -> 0.26059436 | J40: =J39-J38 -> 0.26163602 | K40: =K39-K38 -> 0.26267767
A41: Headroom % of threshold | G41: =IF(G39=0,0,G40/ABS(G39)) -> 0.64627763 | H41: =IF(H39=0,0,H40/ABS(H39)) -> 0.64888177 | I41: =IF(I39=0,0,I40/ABS(I39)) -> 0.65148591 | J41: =IF(J39=0,0,J40/ABS(J39)) -> 0.65409004 | K41: =IF(K39=0,0,K40/ABS(K39)) -> 0.65669418
A42: BREACH? (1 = yes) | G42: =IF(G40<0,1,0) -> 0 | H42: =IF(H40<0,1,0) -> 0 | I42: =IF(I40<0,1,0) -> 0 | J42: =IF(J40<0,1,0) -> 0 | K42: =IF(K40<0,1,0) -> 0
A43: First breach period (0 = none) | C43: =IFERROR(INDEX('Operating Model'!$G$7:$K$7,MATCH(1,$G$42:$K$42,0)),0) -> 0
A44: Minimum headroom % | C44: =MIN($G$41:$K$41) -> 0.64627763
A45: Hypothetical maintenance covenant on the new loan: min liquidity ($M) [HYPOTHETICAL]
A46: Metric | G46: =G16 -> 697.44742 | H46: =H16 -> 574.5 | I46: =I16 -> 574.5 | J46: =J16 -> 574.5 | K46: =K16 -> 574.5
A47: Covenant threshold | G47: =Assumptions!$G$74 -> 100 | H47: =Assumptions!$H$74 -> 100 | I47: =Assumptions!$I$74 -> 100 | J47: =Assumptions!$J$74 -> 100 | K47: =Assumptions!$K$74 -> 100
A48: Headroom | G48: =G46-G47 -> 597.44742 | H48: =H46-H47 -> 474.5 | I48: =I46-I47 -> 474.5 | J48: =J46-J47 -> 474.5 | K48: =K46-K47 -> 474.5
A49: Headroom % of threshold | G49: =IF(G47=0,0,G48/ABS(G47)) -> 5.9744742 | H49: =IF(H47=0,0,H48/ABS(H47)) -> 4.745 | I49: =IF(I47=0,0,I48/ABS(I47)) -> 4.745 | J49: =IF(J47=0,0,J48/ABS(J47)) -> 4.745 | K49: =IF(K47=0,0,K48/ABS(K47)) -> 4.745
A50: BREACH? (1 = yes) | G50: =IF(G48<0,1,0) -> 0 | H50: =IF(H48<0,1,0) -> 0 | I50: =IF(I48<0,1,0) -> 0 | J50: =IF(J48<0,1,0) -> 0 | K50: =IF(K48<0,1,0) -> 0
A51: First breach period (0 = none) | C51: =IFERROR(INDEX('Operating Model'!$G$7:$K$7,MATCH(1,$G$50:$K$50,0)),0) -> 0
A52: Minimum headroom % | C52: =MIN($G$49:$K$49) -> 4.745
A53: Hypothetical maintenance covenant on the new loan: max net debt / EBITDA [HYPOTHETICAL]
A54: Metric | G54: =IF('Operating Model'!G17>0,G9/'Operating Model'!G17,99) -> 10.670457 | H54: =IF('Operating Model'!H17>0,H9/'Operating Model'!H17,99) -> 11.660147 | I54: =IF('Operating Model'!I17>0,I9/'Operating Model'!I17,99) -> 11.963654 | J54: =IF('Operating Model'!J17>0,J9/'Operating Model'!J17,99) -> 12.004587 | K54: =IF('Operating Model'!K17>0,K9/'Operating Model'!K17,99) -> 12.023261
A55: Covenant threshold | G55: =Assumptions!$G$75 -> 10.5 | H55: =Assumptions!$H$75 -> 10.5 | I55: =Assumptions!$I$75 -> 10 | J55: =Assumptions!$J$75 -> 10 | K55: =Assumptions!$K$75 -> 9.5
A56: Headroom | G56: =G55-G54 -> -0.17045707 | H56: =H55-H54 -> -1.1601471 | I56: =I55-I54 -> -1.9636536 | J56: =J55-J54 -> -2.0045872 | K56: =K55-K54 -> -2.5232607
A57: Headroom % of threshold | G57: =IF(G55=0,0,G56/ABS(G55)) -> -0.016234006 | H57: =IF(H55=0,0,H56/ABS(H55)) -> -0.1104902 | I57: =IF(I55=0,0,I56/ABS(I55)) -> -0.19636536 | J57: =IF(J55=0,0,J56/ABS(J55)) -> -0.20045872 | K57: =IF(K55=0,0,K56/ABS(K55)) -> -0.26560639
A58: BREACH? (1 = yes) | G58: =IF(G56<0,1,0) -> 1 | H58: =IF(H56<0,1,0) -> 1 | I58: =IF(I56<0,1,0) -> 1 | J58: =IF(J56<0,1,0) -> 1 | K58: =IF(K56<0,1,0) -> 1
A59: First breach period (0 = none) | C59: =IFERROR(INDEX('Operating Model'!$G$7:$K$7,MATCH(1,$G$58:$K$58,0)),0) -> 2027
A60: Minimum headroom % | C60: =MIN($G$57:$K$57) -> -0.26560639
A61: Covenant breaches (count, all active covenants) | G61: =G26+G34+G42+G50+G58 -> 3 | H61: =H26+H34+H42+H50+H58 -> 3 | I61: =I26+I34+I42+I50+I58 -> 3 | J61: =J26+J34+J42+J50+J58 -> 3 | K61: =K26+K34+K42+K50+K58 -> 3
A62: Total breaches across projection | C62: =SUM($G$61:$K$61) -> 15
A63: Minimum covenant headroom % (all active covenants) | C63: =MIN(C28,C36,C44,C52,C60) -> -0.26560639
A66: Credit score — transparent, formula-driven (base period; weights & thresholds on Assumptions §8)
A67: Factor | C67: Value | D67: Best | E67: Worst | F67: Weight | G67: Points | H67: Score % | I67: Projected value (period 1, selected scenario) | J67: Projected points
A68: Net leverage (net debt / EBITDA) | C68: ='Credit Metrics'!F11 -> 9.7781976 | D68: =Assumptions!$D$139 -> 2 | E68: =Assumptions!$E$139 -> 7 | F68: =Assumptions!$C$139 -> 15 | G68: =F68*H68 -> 0 | H68: =MAX(0,MIN(1,(C68-E68)/(D68-E68))) -> 0 | I68: ='Credit Metrics'!G11 -> 10.670457 | J68: =F68*MAX(0,MIN(1,(I68-E68)/(D68-E68))) -> 0
A69: Interest coverage (EBITDA / interest) | C69: ='Credit Metrics'!F12 -> 1.7233258 | D69: =Assumptions!$D$140 -> 5 | E69: =Assumptions!$E$140 -> 1 | F69: =Assumptions!$C$140 -> 15 | G69: =F69*H69 -> 2.7124719 | H69: =MAX(0,MIN(1,(C69-E69)/(D69-E69))) -> 0.18083146 | I69: ='Credit Metrics'!G12 -> 1.2497904 | J69: =F69*MAX(0,MIN(1,(I69-E69)/(D69-E69))) -> 0.93671405
A70: Liquidity ratio (liquidity / next-period obligations) | C70: ='Credit Metrics'!F16/(SUMPRODUCT((Assumptions!$K$57:$K$66<=Assumptions!$C$6+1)*Assumptions!$C$57:$C$66)+SUMPRODUCT(Assumptions!$L$57:$L$66*Assumptions!$C$57:$C$66)+'Operating Model'!F23) -> 3.8859663 | D70: =Assumptions!$D$141 -> 2 | E70: =Assumptions!$E$141 -> 0.5 | F70: =Assumptions!$C$141 -> 10 | G70: =F70*H70 -> 10 | H70: =MAX(0,MIN(1,(C70-E70)/(D70-E70))) -> 1 | I70: ='Credit Metrics'!G16/(SUMPRODUCT((Assumptions!$K$57:$K$66<=Assumptions!$C$6+1)*Assumptions!$C$57:$C$66)+SUMPRODUCT(Assumptions!$L$57:$L$66*Assumptions!$C$57:$C$66)+'Operating Model'!F23) -> 4.425849 | J70: =F70*MAX(0,MIN(1,(I70-E70)/(D70-E70))) -> 10
A71: FCF / total debt | C71: ='Credit Metrics'!F14 -> -0.0027445473 | D71: =Assumptions!$D$142 -> 0.12 | E71: =Assumptions!$E$142 -> -0.02 | F71: =Assumptions!$C$142 -> 10 | G71: =F71*H71 -> 1.2325323 | H71: =MAX(0,MIN(1,(C71-E71)/(D71-E71))) -> 0.12325323 | I71: ='Credit Metrics'!G14 -> -0.023235741 | J71: =F71*MAX(0,MIN(1,(I71-E71)/(D71-E71))) -> 0
A72: Share of debt maturing within window | C72: =SUMPRODUCT((Assumptions!$K$57:$K$66<=Assumptions!$C$6+Assumptions!$C$22)*Assumptions!$C$57:$C$66)/SUM(Assumptions!$C$57:$C$66) -> 0.51410279 | D72: =Assumptions!$D$143 -> 0 | E72: =Assumptions!$E$143 -> 0.5 | F72: =Assumptions!$C$143 -> 10 | G72: =F72*H72 -> 0 | H72: =MAX(0,MIN(1,(C72-E72)/(D72-E72))) -> 0 | I72: =C72 -> 0.51410279 | J72: =F72*MAX(0,MIN(1,(I72-E72)/(D72-E72))) -> 0
A73: Margin stability (σ of annual EBITDA margin) | C73: =STDEVP('Historical Financials'!B44:D44) -> 0.013195248 | D73: =Assumptions!$D$144 -> 0.01 | E73: =Assumptions!$E$144 -> 0.05 | F73: =Assumptions!$C$144 -> 10 | G73: =F73*H73 -> 9.2011879 | H73: =MAX(0,MIN(1,(C73-E73)/(D73-E73))) -> 0.92011879 | I73: =C73 -> 0.013195248 | J73: =F73*MAX(0,MIN(1,(I73-E73)/(D73-E73))) -> 9.2011879
A74: Revenue stability (σ of annual growth) | C74: =STDEVP('Historical Financials'!C45:D45) -> 0.011959152 | D74: =Assumptions!$D$145 -> 0.03 | E74: =Assumptions!$E$145 -> 0.15 | F74: =Assumptions!$C$145 -> 8 | G74: =F74*H74 -> 8 | H74: =MAX(0,MIN(1,(C74-E74)/(D74-E74))) -> 1 | I74: =C74 -> 0.011959152 | J74: =F74*MAX(0,MIN(1,(I74-E74)/(D74-E74))) -> 8
A75: Asset coverage (asset base / debt) | C75: =Assumptions!$C$31/'Credit Metrics'!F7 -> 1.7204167 | D75: =Assumptions!$D$146 -> 2 | E75: =Assumptions!$E$146 -> 0.6 | F75: =Assumptions!$C$146 -> 12 | G75: =F75*H75 -> 9.6035716 | H75: =MAX(0,MIN(1,(C75-E75)/(D75-E75))) -> 0.80029763 | I75: =C75 -> 1.7204167 | J75: =F75*MAX(0,MIN(1,(I75-E75)/(D75-E75))) -> 9.6035716
A76: Industry risk factor (analyst input, 0-1) | C76: =Assumptions!$C$148 -> 0.5 | D76: =Assumptions!$D$147 -> 1 | E76: =Assumptions!$E$147 -> 0 | F76: =Assumptions!$C$147 -> 10 | G76: =F76*H76 -> 5 | H76: =MAX(0,MIN(1,(C76-E76)/(D76-E76))) -> 0.5 | I76: =C76 -> 0.5 | J76: =F76*MAX(0,MIN(1,(I76-E76)/(D76-E76))) -> 5
A77: Credit score (0-100) | F77: =SUM(F68:F76) -> 100 | G77: =SUM(G68:G76) -> 45.749764 | J77: =SUM(J68:J76) -> 42.741474
A78: Risk band | G78: =IF(G77>=Assumptions!$C$152,"Low",IF(G77>=Assumptions!$C$153,"Moderate",IF(G77>=Assumptions!$C$154,"Elevated","High"))) -> Elevated
A79: Each factor earns its weight linearly between the 'worst' threshold (0 pts) and the 'best' threshold (full pts).

Sheet Scenarios
A1: Scenarios — side-by-side (all three run simultaneously on Calc Engine)
A2: ="Active scenario for the detailed tabs: "&Assumptions!$D$10 -> Active scenario for the detailed tabs: Downside
A4: Assumptions (links to Assumptions tab) | C4: Base Case | D4: Downside | E4: Severe Downside | F4: Selected
A5: Average revenue growth (5 periods) | C5: =AVERAGE(Assumptions!$G$79:$K$79) -> 0.01 | D5: =AVERAGE(Assumptions!$G$98:$K$98) -> -0.014 | E5: =AVERAGE(Assumptions!$G$117:$K$117) -> -0.038 | F5: =CHOOSE(Assumptions!$C$10,C5,D5,E5) -> -0.014
A6: Average EBITDA margin (5 periods) | C6: =AVERAGE(Assumptions!$G$81:$K$81) -> 0.5354 | D6: =AVERAGE(Assumptions!$G$100:$K$100) -> 0.491 | E6: =AVERAGE(Assumptions!$G$119:$K$119) -> 0.437 | F6: =CHOOSE(Assumptions!$C$10,C6,D6,E6) -> 0.491
A7: Floating-rate shock | C7: =Assumptions!$C$86 -> 0 | D7: =Assumptions!$C$105 -> 0.015 | E7: =Assumptions!$C$124 -> 0.03 | F7: =CHOOSE(Assumptions!$C$10,C7,D7,E7) -> 0.015
A8: Refinancing rate | C8: =Assumptions!$C$87 -> 0.08 | D8: =Assumptions!$C$106 -> 0.1 | E8: =Assumptions!$C$125 -> 0.12 | F8: =CHOOSE(Assumptions!$C$10,C8,D8,E8) -> 0.1
A9: Market access: max net leverage / min coverage | C9: =TEXT(Assumptions!$C$88,"0.0")&"x / "&TEXT(Assumptions!$C$89,"0.00")&"x" -> 11.0x / 1.20x | D9: =TEXT(Assumptions!$C$107,"0.0")&"x / "&TEXT(Assumptions!$C$108,"0.00")&"x" -> 9.5x / 1.50x | E9: =TEXT(Assumptions!$C$126,"0.0")&"x / "&TEXT(Assumptions!$C$127,"0.00")&"x" -> 9.0x / 1.75x | F9: =CHOOSE(Assumptions!$C$10,C9,D9,E9) -> 9.5x / 1.50x
A10: Exit multiple / distressed multiple | C10: =TEXT(Assumptions!$C$90,"0.0")&"x / "&TEXT(Assumptions!$C$92,"0.0")&"x" -> 12.5x / 10.0x | D10: =TEXT(Assumptions!$C$109,"0.0")&"x / "&TEXT(Assumptions!$C$111,"0.0")&"x" -> 11.0x / 9.0x | E10: =TEXT(Assumptions!$C$128,"0.0")&"x / "&TEXT(Assumptions!$C$130,"0.0")&"x" -> 9.5x / 8.0x | F10: =CHOOSE(Assumptions!$C$10,C10,D10,E10) -> 11.0x / 9.0x
A11: Asset value decline | C11: =Assumptions!$C$93 -> 0 | D11: =Assumptions!$C$112 -> 0.15 | E11: =Assumptions!$C$131 -> 0.3 | F11: =CHOOSE(Assumptions!$C$10,C11,D11,E11) -> 0.15
A12: Scenario probability | C12: =Assumptions!$C$95 -> 0.5 | D12: =Assumptions!$C$114 -> 0.35 | E12: =Assumptions!$C$133 -> 0.15 | F12: =CHOOSE(Assumptions!$C$10,C12,D12,E12) -> 0.35
A14: Outputs (from Calc Engine) | C14: Base Case | D14: Downside | E14: Severe Downside | F14: Selected
A15: LTM Jun-31E revenue ($M) | C15: ='Calc Engine'!K19 -> 523.18522 | D15: ='Calc Engine'!K674 -> 463.474 | E15: ='Calc Engine'!K1329 -> 408.60305 | F15: =CHOOSE(Assumptions!$C$10,C15,D15,E15) -> 463.474
A16: Trough EBITDA ($M) | C16: =MIN('Calc Engine'!$G$23:$K$23) -> 256.1714 | D16: =MIN('Calc Engine'!$G$678:$K$678) -> 220.35574 | E16: =MIN('Calc Engine'!$G$1333:$K$1333) -> 171.93693 | F16: =CHOOSE(Assumptions!$C$10,C16,D16,E16) -> 220.35574
A17: Cumulative FCF, 5 periods ($M) | C17: ='Calc Engine'!C656 -> -435.80544 | D17: ='Calc Engine'!C1311 -> -320.30805 | E17: ='Calc Engine'!C1966 -> -319.39389 | F17: =CHOOSE(Assumptions!$C$10,C17,D17,E17) -> -320.30805
A18: Peak net debt / EBITDA | C18: ='Calc Engine'!C654 -> 9.9952898 | D18: ='Calc Engine'!C1309 -> 12.023261 | E18: ='Calc Engine'!C1964 -> 15.773454 | F18: =CHOOSE(Assumptions!$C$10,C18,D18,E18) -> 12.023261
A19: Minimum EBITDA / cash interest | C19: ='Calc Engine'!C655 -> 1.3427457 | D19: ='Calc Engine'!C1310 -> 1.1831122 | E19: ='Calc Engine'!C1965 -> 0.89963163 | F19: =CHOOSE(Assumptions!$C$10,C19,D19,E19) -> 1.1831122
A20: Covenant breaches (count of tests failed) | C20: ='Calc Engine'!C299 -> 8 | D20: ='Calc Engine'!C954 -> 15 | E20: ='Calc Engine'!C1609 -> 15 | F20: =CHOOSE(Assumptions!$C$10,C20,D20,E20) -> 15
A21: Refinancing failures (maturing tranches) | C21: ='Calc Engine'!C222 -> 0 | D21: ='Calc Engine'!C877 -> 7 | E21: ='Calc Engine'!C1532 -> 7 | F21: =CHOOSE(Assumptions!$C$10,C21,D21,E21) -> 7
A22: Payment default modelled? (1 = yes) | C22: ='Calc Engine'!C304 -> 0 | D22: ='Calc Engine'!C959 -> 1 | E22: ='Calc Engine'!C1614 -> 1 | F22: =CHOOSE(Assumptions!$C$10,C22,D22,E22) -> 1
A23: Valuation period (default or trough) | C23: ='Calc Engine'!C305 -> 2027 | D23: ='Calc Engine'!C960 -> 2028 | E23: ='Calc Engine'!C1615 -> 2028 | F23: =CHOOSE(Assumptions!$C$10,C23,D23,E23) -> 2028
A24: Recovery value used ($M) | C24: ='Calc Engine'!C311 -> 3990.3743 | D24: ='Calc Engine'!C966 -> 3264.0387 | E24: ='Calc Engine'!C1621 -> 2688.0319 | F24: =CHOOSE(Assumptions!$C$10,C24,D24,E24) -> 3264.0387
A25: Target-tranche recovery % (valuation waterfall) | C25: ='Calc Engine'!C480 -> 1 | D25: ='Calc Engine'!C1135 -> 1 | E25: ='Calc Engine'!C1790 -> 1 | F25: =CHOOSE(Assumptions!$C$10,C25,D25,E25) -> 1
A26: Exit price used (% of face) | C26: ='Calc Engine'!C639 -> 100 | D26: ='Calc Engine'!C1294 -> 95 | E26: ='Calc Engine'!C1949 -> 85 | F26: =CHOOSE(Assumptions!$C$10,C26,D26,E26) -> 95
A27: IRR | C27: ='Calc Engine'!C653 -> 0.095815282 | D27: ='Calc Engine'!C1308 -> 0.087396249 | E27: ='Calc Engine'!C1963 -> 0.099407759 | F27: =CHOOSE(Assumptions!$C$10,C27,D27,E27) -> 0.087396249
A28: MOIC | C28: ='Calc Engine'!C652 -> 1.2884557 | D28: ='Calc Engine'!C1307 -> 1.2567266 | E28: ='Calc Engine'!C1962 -> 1.290994 | F28: =CHOOSE(Assumptions!$C$10,C28,D28,E28) -> 1.2567266
A29: Absolute profit ($M) | C29: ='Calc Engine'!C651 -> 28.41 | D29: ='Calc Engine'!C1306 -> 25.285 | E29: ='Calc Engine'!C1961 -> 28.66 | F29: =CHOOSE(Assumptions!$C$10,C29,D29,E29) -> 25.285
A31: Probability-weighted IRR (IRR of expected cash flows) | C31: =IF(SUM(D38:I38)<=0,-1,IFERROR(IRR(C38:I38,MAX(-0.9,(SUM(D38:I38)/-C38)^(1/(COLUMNS(C38:I38)-1))-1)),IRR(C38:I38,0.1))) -> 0.09343237
A32: Memo: probability-weighted AVERAGE of scenario IRRs (IRR is non-linear, so this is not an IRR) | C32: =SUMPRODUCT(C12:E12,C27:E27) -> 0.093407492
A33: Probability-weighted MOIC | C33: =SUMPRODUCT(C12:E12,C28:E28) -> 1.2777312
A34: Probability of payment default | C34: =SUMPRODUCT(C12:E12,C22:E22) -> 0.5
A36: Expected (probability-weighted) position cash flows by period — basis of the probability-weighted IRR
C37: t=0 | D37: t=1 | E37: t=2 | F37: t=3 | G37: t=4 | H37: t=5 | I37: t=6
A38: Expected net cash flow ($M) | C38: =C$12*'Calc Engine'!C646+D$12*'Calc Engine'!C1301+E$12*'Calc Engine'!C1956 -> -98.49 | D38: =C$12*'Calc Engine'!D646+D$12*'Calc Engine'!D1301+E$12*'Calc Engine'!D1956 -> 10.125 | E38: =C$12*'Calc Engine'!E646+D$12*'Calc Engine'!E1301+E$12*'Calc Engine'!E1956 -> 9.975 | F38: =C$12*'Calc Engine'!F646+D$12*'Calc Engine'!F1301+E$12*'Calc Engine'!F1956 -> 105.74375 | G38: =C$12*'Calc Engine'!G646+D$12*'Calc Engine'!G1301+E$12*'Calc Engine'!G1956 -> 0 | H38: =C$12*'Calc Engine'!H646+D$12*'Calc Engine'!H1301+E$12*'Calc Engine'!H1956 -> 0 | I38: =C$12*'Calc Engine'!I646+D$12*'Calc Engine'!I1301+E$12*'Calc Engine'!I1956 -> 0
A40: Reconciliation: detailed tabs vs Calc Engine (selected scenario) | C40: Detailed | D40: Calc Engine | E40: Difference
A41: LTM Jun-31E EBITDA | C41: ='Operating Model'!K17 -> 229.41963 | D41: =CHOOSE(Assumptions!$C$10,'Calc Engine'!K23,'Calc Engine'!K678,'Calc Engine'!K1333) -> 229.41963 | E41: =C41-D41 -> 0
A42: LTM Jun-31E total debt | C42: ='Debt Schedule'!K147 -> 2557.3804 | D42: =CHOOSE(Assumptions!$C$10,'Calc Engine'!K179,'Calc Engine'!K834,'Calc Engine'!K1489) -> 2557.3804 | E42: =C42-D42 -> 0
A43: LTM Jun-31E ending cash | C43: ='Cash Flow'!K19 -> -200.99169 | D43: =CHOOSE(Assumptions!$C$10,'Calc Engine'!K237,'Calc Engine'!K892,'Calc Engine'!K1547) -> -200.99169 | E43: =C43-D43 -> 0
A44: Cumulative FCF | C44: =Returns!C191 -> -320.30805 | D44: =CHOOSE(Assumptions!$C$10,'Calc Engine'!C656,'Calc Engine'!C1311,'Calc Engine'!C1966) -> -320.30805 | E44: =C44-D44 -> 0
A45: Recovery value used | C45: =Recovery!C15 -> 3264.0387 | D45: =CHOOSE(Assumptions!$C$10,'Calc Engine'!C311,'Calc Engine'!C966,'Calc Engine'!C1621) -> 3264.0387 | E45: =C45-D45 -> 0
A46: Covenant breaches | C46: ='Credit Metrics'!C62 -> 15 | D46: =CHOOSE(Assumptions!$C$10,'Calc Engine'!C299,'Calc Engine'!C954,'Calc Engine'!C1609) -> 15 | E46: =C46-D46 -> 0
A47: IRR | C47: =Returns!C188 -> 0.087396249 | D47: =CHOOSE(Assumptions!$C$10,'Calc Engine'!C653,'Calc Engine'!C1308,'Calc Engine'!C1963) -> 0.087396249 | E47: =C47-D47 -> 0
A48: MOIC | C48: =Returns!C187 -> 1.2567266 | D48: =CHOOSE(Assumptions!$C$10,'Calc Engine'!C652,'Calc Engine'!C1307,'Calc Engine'!C1962) -> 1.2567266 | E48: =C48-D48 -> 0

Sheet Capital Structure
A1: Capital Structure — tranches, leverage through the stack, maturity wall and refinancing requirement
A2: ="Brandywine Realty Trust · PUBLIC DATA CASE · HYPOTHETICAL INVESTMENT TERMS · as of "&TEXT(Assumptions!$C$8,"yyyy-mm-dd")&" · $M" -> Brandywine Realty Trust · PUBLIC DATA CASE · HYPOTHETICAL INVESTMENT TERMS · as of 2026-06-30 · $M
A4: Facility | B4: Type | C4: Rank | D4: Secured? | E4: Face value | F4: All-in rate | G4: Annual interest | H4: Maturity date | I4: Cum. leverage | J4: % of capitalization | K4: Mark / price | L4: Mkt value
A5: =Assumptions!$A$57 -> Hypothetical Senior Secured Term Loan (S+525, 1% floor) | B5: =Assumptions!$B$57 -> term_loan | C5: =Assumptions!$M$57 -> 1 | D5: =IF(Assumptions!$O$57=1,"Secured","Unsecured") -> Secured | E5: =Assumptions!$C$57 -> 400 | F5: ='Debt Schedule'!G20 -> 0.1065 | G5: =E5*F5 -> 42.6 | H5: =Assumptions!$J$57 -> 48029 | I5: =SUMIF($C$5:$C$14,"<="&C5,$E$5:$E$14)/'Operating Model'!F17 -> 2.0678941 | J5: =E5/($E$15+$E$19) -> 0.11953385 | K5: =Assumptions!$R$57 -> 98 | L5: =E5*K5/100 -> 392
A6: =Assumptions!$A$58 -> Avira Secured Term Loan (swapped to 5.81%) | B6: =Assumptions!$B$58 -> term_loan | C6: =Assumptions!$M$58 -> 1 | D6: =IF(Assumptions!$O$58=1,"Secured","Unsecured") -> Secured | E6: =Assumptions!$C$58 -> 90 | F6: ='Debt Schedule'!G33 -> 0.0581 | G6: =E6*F6 -> 5.229 | H6: =Assumptions!$J$58 -> 48760 | I6: =SUMIF($C$5:$C$14,"<="&C6,$E$5:$E$14)/'Operating Model'!F17 -> 2.0678941 | J6: =E6/($E$15+$E$19) -> 0.026895116 | K6: =Assumptions!$R$58 -> 100 | L6: =E6*K6/100 -> 90
A7: =Assumptions!$A$59 -> 3151 Market C-PACE Loan | B7: =Assumptions!$B$59 -> mortgage | C7: =Assumptions!$M$59 -> 1 | D7: =IF(Assumptions!$O$59=1,"Secured","Unsecured") -> Secured | E7: =Assumptions!$C$59 -> 57.324 | F7: ='Debt Schedule'!G46 -> 0.0731 | G7: =E7*F7 -> 4.1903844 | H7: =Assumptions!$J$59 -> 56339 | I7: =SUMIF($C$5:$C$14,"<="&C7,$E$5:$E$14)/'Operating Model'!F17 -> 2.0678941 | J7: =E7/($E$15+$E$19) -> 0.017130396 | K7: =Assumptions!$R$59 -> 100 | L7: =E7*K7/100 -> 57.324
A8: =Assumptions!$A$60 -> Unsecured Revolver ($600M less LCs; hypothetically undrawn pro forma) | B8: =Assumptions!$B$60 -> revolver | C8: =Assumptions!$M$60 -> 2 | D8: =IF(Assumptions!$O$60=1,"Secured","Unsecured") -> Unsecured | E8: =Assumptions!$C$60 -> 0 | F8: ='Debt Schedule'!G59 -> 0.069 | G8: =E8*F8 -> 0 | H8: =Assumptions!$J$60 -> 46568 | I8: =SUMIF($C$5:$C$14,"<="&C8,$E$5:$E$14)/'Operating Model'!F17 -> 9.6242741 | J8: =E8/($E$15+$E$19) -> 0 | K8: =Assumptions!$R$60 -> 100 | L8: =E8*K8/100 -> 0
A9: =Assumptions!$A$61 -> 3.95% Guaranteed Notes due Nov-2027 | B9: =Assumptions!$B$61 -> senior_notes | C9: =Assumptions!$M$61 -> 2 | D9: =IF(Assumptions!$O$61=1,"Secured","Unsecured") -> Unsecured | E9: =Assumptions!$C$61 -> 450 | F9: ='Debt Schedule'!G72 -> 0.0395 | G9: =E9*F9 -> 17.775 | H9: =Assumptions!$J$61 -> 46706 | I9: =SUMIF($C$5:$C$14,"<="&C9,$E$5:$E$14)/'Operating Model'!F17 -> 9.6242741 | J9: =E9/($E$15+$E$19) -> 0.13447558 | K9: =Assumptions!$R$61 -> 100 | L9: =E9*K9/100 -> 450
A10: =Assumptions!$A$62 -> 8.30% Guaranteed Notes due Mar-2028 | B10: =Assumptions!$B$62 -> senior_notes | C10: =Assumptions!$M$62 -> 2 | D10: =IF(Assumptions!$O$62=1,"Secured","Unsecured") -> Unsecured | E10: =Assumptions!$C$62 -> 350 | F10: ='Debt Schedule'!G85 -> 0.083 | G10: =E10*F10 -> 29.05 | H10: =Assumptions!$J$62 -> 46827 | I10: =SUMIF($C$5:$C$14,"<="&C10,$E$5:$E$14)/'Operating Model'!F17 -> 9.6242741 | J10: =E10/($E$15+$E$19) -> 0.10459212 | K10: =Assumptions!$R$62 -> 100 | L10: =E10*K10/100 -> 350
A11: =Assumptions!$A$63 -> 8.875% Guaranteed Notes due Apr-2029 | B11: =Assumptions!$B$63 -> senior_notes | C11: =Assumptions!$M$63 -> 2 | D11: =IF(Assumptions!$O$63=1,"Secured","Unsecured") -> Unsecured | E11: =Assumptions!$C$63 -> 550 | F11: ='Debt Schedule'!G98 -> 0.08875 | G11: =E11*F11 -> 48.8125 | H11: =Assumptions!$J$63 -> 47223 | I11: =SUMIF($C$5:$C$14,"<="&C11,$E$5:$E$14)/'Operating Model'!F17 -> 9.6242741 | J11: =E11/($E$15+$E$19) -> 0.16435904 | K11: =Assumptions!$R$63 -> 100 | L11: =E11*K11/100 -> 550
A12: =Assumptions!$A$64 -> 4.55% Guaranteed Notes due Oct-2029 | B12: =Assumptions!$B$64 -> senior_notes | C12: =Assumptions!$M$64 -> 2 | D12: =IF(Assumptions!$O$64=1,"Secured","Unsecured") -> Unsecured | E12: =Assumptions!$C$64 -> 350 | F12: ='Debt Schedule'!G111 -> 0.0455 | G12: =E12*F12 -> 15.925 | H12: =Assumptions!$J$64 -> 47392 | I12: =SUMIF($C$5:$C$14,"<="&C12,$E$5:$E$14)/'Operating Model'!F17 -> 9.6242741 | J12: =E12/($E$15+$E$19) -> 0.10459212 | K12: =Assumptions!$R$64 -> 100 | L12: =E12*K12/100 -> 350
A13: =Assumptions!$A$65 -> 6.125% Guaranteed Notes due Jan-2031 | B13: =Assumptions!$B$65 -> senior_notes | C13: =Assumptions!$M$65 -> 2 | D13: =IF(Assumptions!$O$65=1,"Secured","Unsecured") -> Unsecured | E13: =Assumptions!$C$65 -> 300 | F13: ='Debt Schedule'!G124 -> 0.06125 | G13: =E13*F13 -> 18.375 | H13: =Assumptions!$J$65 -> 47863 | I13: =SUMIF($C$5:$C$14,"<="&C13,$E$5:$E$14)/'Operating Model'!F17 -> 9.6242741 | J13: =E13/($E$15+$E$19) -> 0.089650386 | K13: =Assumptions!$R$65 -> 100 | L13: =E13*K13/100 -> 300
A14: =Assumptions!$A$66 -> Junior subordinated trust-preferred indentures | B14: =Assumptions!$B$66 -> subordinated | C14: =Assumptions!$M$66 -> 3 | D14: =IF(Assumptions!$O$66=1,"Secured","Unsecured") -> Unsecured | E14: =Assumptions!$C$66 -> 78.61 | F14: ='Debt Schedule'!G137 -> 0.0691 | G14: =E14*F14 -> 5.431951 | H14: =Assumptions!$J$66 -> 49398 | I14: =SUMIF($C$5:$C$14,"<="&C14,$E$5:$E$14)/'Operating Model'!F17 -> 9.9212776 | J14: =E14/($E$15+$E$19) -> 0.023491389 | K14: =Assumptions!$R$66 -> 100 | L14: =E14*K14/100 -> 78.61
A15: Total debt | E15: =SUM(E5:E14) -> 2625.934 | G15: =SUM(G5:G14) -> 187.38884 | I15: =E15/'Operating Model'!F17 -> 9.9212776 | L15: =SUM(L5:L14) -> 2617.934
A16: Less: cash | E16: =Assumptions!$C$11 -> 37.87
A17: Net debt | E17: =E15-E16 -> 2588.064 | I17: =E17/'Operating Model'!F17 -> 9.7781976
A18: Enterprise value (base EBITDA × market-implied multiple — analyst assumption) | E18: ='Operating Model'!F17*Assumptions!$C$21 -> 3308.4625
A19: Equity (residual: max(0, EV − net debt)) | E19: =MAX(0,E18-E17) -> 720.3985
A20: Liquidity (cash + undrawn revolver) | E20: ='Credit Metrics'!F16 -> 612.37
A21: Asset base (collateral / recovery basis) | E21: =Assumptions!$C$31 -> 4517.7007
A22: Loan-to-value through target tranche (cumulative debt ÷ asset base) | E22: =SUMIF($C$5:$C$14,"<="&INDEX($C$5:$C$14,Assumptions!$C$34),$E$5:$E$14)/E21 -> 0.12115101
A25: Maturity wall (from Debt Schedule maturity flags) — selected scenario liquidity
A26: Period | C26: Debt due | D26: % of debt | E26: Cumulative % | F26: Projected liquidity | G26: Refinancing requirement | H26: Liquidity ÷ maturity | I26: Risk | J26: Flag
A27: ="LTM Jun-27E"&" (period ending "&'Operating Model'!G7&")" -> LTM Jun-27E (period ending 2027) | C27: ='Debt Schedule'!G148 -> 0 | D27: =C27/$E$15 -> 0 | E27: =SUM($D$27:D27) -> 0 | F27: =MAX(0,Assumptions!$C$11)+('Credit Metrics'!F16-MAX(0,Assumptions!$C$11))+MAX(0,'Operating Model'!G30) -> 612.37 | G27: =MAX(0,C27-F27) -> 0 | H27: =IF(C27>0,F27/C27,0) -> 0 | I27: =IF(AND(G27>0,D27>=Assumptions!$C$19),"High",IF(OR(G27>0,D27>=Assumptions!$C$20),"Medium","Low")) -> Low | J27: =IF(I27="High","$"&TEXT(C27,"#,##0")&"M maturity; only $"&TEXT(F27,"#,##0")&"M projected liquidity; $"&TEXT(G27,"#,##0")&"M refinancing requirement","–") -> –
A28: ="LTM Jun-28E"&" (period ending "&'Operating Model'!H7&")" -> LTM Jun-28E (period ending 2028) | C28: ='Debt Schedule'!H148 -> 800 | D28: =C28/$E$15 -> 0.30465351 | E28: =SUM($D$27:D28) -> 0.30465351 | F28: =MAX(0,'Cash Flow'!G19)+('Credit Metrics'!G16-MAX(0,'Cash Flow'!G19))+MAX(0,'Operating Model'!H30) -> 697.44742 | G28: =MAX(0,C28-F28) -> 102.55258 | H28: =IF(C28>0,F28/C28,0) -> 0.87180928 | I28: =IF(AND(G28>0,D28>=Assumptions!$C$19),"High",IF(OR(G28>0,D28>=Assumptions!$C$20),"Medium","Low")) -> High | J28: =IF(I28="High","$"&TEXT(C28,"#,##0")&"M maturity; only $"&TEXT(F28,"#,##0")&"M projected liquidity; $"&TEXT(G28,"#,##0")&"M refinancing requirement","–") -> $800M maturity; only $697M projected liquidity; $103M refinancing requirement
A29: ="LTM Jun-29E"&" (period ending "&'Operating Model'!I7&")" -> LTM Jun-29E (period ending 2029) | C29: ='Debt Schedule'!I148 -> 550 | D29: =C29/$E$15 -> 0.20944929 | E29: =SUM($D$27:D29) -> 0.51410279 | F29: =MAX(0,'Cash Flow'!H19)+('Credit Metrics'!H16-MAX(0,'Cash Flow'!H19))+MAX(0,'Operating Model'!I30) -> 574.5 | G29: =MAX(0,C29-F29) -> 0 | H29: =IF(C29>0,F29/C29,0) -> 1.0445455 | I29: =IF(AND(G29>0,D29>=Assumptions!$C$19),"High",IF(OR(G29>0,D29>=Assumptions!$C$20),"Medium","Low")) -> Low | J29: =IF(I29="High","$"&TEXT(C29,"#,##0")&"M maturity; only $"&TEXT(F29,"#,##0")&"M projected liquidity; $"&TEXT(G29,"#,##0")&"M refinancing requirement","–") -> –
A30: ="LTM Jun-30E"&" (period ending "&'Operating Model'!J7&")" -> LTM Jun-30E (period ending 2030) | C30: ='Debt Schedule'!J148 -> 350 | D30: =C30/$E$15 -> 0.13328591 | E30: =SUM($D$27:D30) -> 0.6473887 | F30: =MAX(0,'Cash Flow'!I19)+('Credit Metrics'!I16-MAX(0,'Cash Flow'!I19))+MAX(0,'Operating Model'!J30) -> 574.5 | G30: =MAX(0,C30-F30) -> 0 | H30: =IF(C30>0,F30/C30,0) -> 1.6414286 | I30: =IF(AND(G30>0,D30>=Assumptions!$C$19),"High",IF(OR(G30>0,D30>=Assumptions!$C$20),"Medium","Low")) -> Low | J30: =IF(I30="High","$"&TEXT(C30,"#,##0")&"M maturity; only $"&TEXT(F30,"#,##0")&"M projected liquidity; $"&TEXT(G30,"#,##0")&"M refinancing requirement","–") -> –
A31: ="LTM Jun-31E"&" (period ending "&'Operating Model'!K7&")" -> LTM Jun-31E (period ending 2031) | C31: ='Debt Schedule'!K148 -> 700 | D31: =C31/$E$15 -> 0.26657182 | E31: =SUM($D$27:D31) -> 0.91396052 | F31: =MAX(0,'Cash Flow'!J19)+('Credit Metrics'!J16-MAX(0,'Cash Flow'!J19))+MAX(0,'Operating Model'!K30) -> 574.5 | G31: =MAX(0,C31-F31) -> 125.5 | H31: =IF(C31>0,F31/C31,0) -> 0.82071429 | I31: =IF(AND(G31>0,D31>=Assumptions!$C$19),"High",IF(OR(G31>0,D31>=Assumptions!$C$20),"Medium","Low")) -> High | J31: =IF(I31="High","$"&TEXT(C31,"#,##0")&"M maturity; only $"&TEXT(F31,"#,##0")&"M projected liquidity; $"&TEXT(G31,"#,##0")&"M refinancing requirement","–") -> $700M maturity; only $575M projected liquidity; $126M refinancing requirement
A32: Maturing within horizon / thereafter | C32: =SUM(C27:C31) -> 2400 | D32: =C32/$E$15 -> 0.91396052
A33: Thereafter (beyond the 5-period horizon) | C33: =$E$15-C32 -> 225.934
A35: Maturity concentration | C35: =IF(MAX(D27:D31)>=Assumptions!$C$20,"CONCENTRATED: "&TEXT(MAX(D27:D31),"0%")&" of debt in "&INDEX(A27:A31,MATCH(MAX(D27:D31),D27:D31,0)),"No single-period concentration") -> CONCENTRATED: 30% of debt in LTM Jun-28E (period ending 2028)
A36: Debt due within alert window | C36: =SUMPRODUCT((Assumptions!$K$57:$K$66<=Assumptions!$C$6+Assumptions!$C$18)*Assumptions!$C$57:$C$66) -> 800 | D36: =C36/E15 -> 0.30465351
A37: Maturity alert | C37: =IF(D36>=Assumptions!$C$19,"ALERT: "&TEXT(D36,"0%")&" of debt ($"&TEXT(C36,"#,##0")&"M) due within "&Assumptions!$C$18&" period(s); liquidity covers "&TEXT(E20/C36,"0%"),"OK: no material maturities within window") -> ALERT: 30% of debt ($800M) due within 2 period(s); liquidity covers 77%
A39: Refinancing risk engine — per tranche, selected scenario (see Debt Schedule for the period-by-period test)
A40: Tranche | C40: Balance at maturity | D40: Repaid from cash | E40: Test | F40: Resolution
A41: =Assumptions!$A$57 -> Hypothetical Senior Secured Term Loan (S+525, 1% floor) | C41: ='Debt Schedule'!C150 -> 380 | D41: ='Debt Schedule'!C151 -> 0 | E41: ='Debt Schedule'!C152 -> REFINANCING FAILURE | F41: ='Debt Schedule'!C153 -> PAYMENT DEFAULT
A42: =Assumptions!$A$58 -> Avira Secured Term Loan (swapped to 5.81%) | C42: ='Debt Schedule'!C154 -> 0 | D42: ='Debt Schedule'!C155 -> 0 | E42: ='Debt Schedule'!C156 -> n/a (beyond horizon) | F42: ='Debt Schedule'!C157 -> n/a
A43: =Assumptions!$A$59 -> 3151 Market C-PACE Loan | C43: ='Debt Schedule'!C158 -> 0 | D43: ='Debt Schedule'!C159 -> 0 | E43: ='Debt Schedule'!C160 -> n/a (beyond horizon) | F43: ='Debt Schedule'!C161 -> n/a
A44: =Assumptions!$A$60 -> Unsecured Revolver ($600M less LCs; hypothetically undrawn pro forma) | C44: ='Debt Schedule'!C162 -> 0 | D44: ='Debt Schedule'!C163 -> 0 | E44: ='Debt Schedule'!C164 -> REFINANCING FAILURE | F44: ='Debt Schedule'!C165 -> Repaid from cash
A45: =Assumptions!$A$61 -> 3.95% Guaranteed Notes due Nov-2027 | C45: ='Debt Schedule'!C166 -> 450 | D45: ='Debt Schedule'!C167 -> 48.553642 | E45: ='Debt Schedule'!C168 -> REFINANCING FAILURE | F45: ='Debt Schedule'!C169 -> Partial repayment; PAYMENT DEFAULT
A46: =Assumptions!$A$62 -> 8.30% Guaranteed Notes due Mar-2028 | C46: ='Debt Schedule'!C170 -> 350 | D46: ='Debt Schedule'!C171 -> 0 | E46: ='Debt Schedule'!C172 -> REFINANCING FAILURE | F46: ='Debt Schedule'!C173 -> PAYMENT DEFAULT
A47: =Assumptions!$A$63 -> 8.875% Guaranteed Notes due Apr-2029 | C47: ='Debt Schedule'!C174 -> 550 | D47: ='Debt Schedule'!C175 -> 0 | E47: ='Debt Schedule'!C176 -> REFINANCING FAILURE | F47: ='Debt Schedule'!C177 -> PAYMENT DEFAULT
A48: =Assumptions!$A$64 -> 4.55% Guaranteed Notes due Oct-2029 | C48: ='Debt Schedule'!C178 -> 350 | D48: ='Debt Schedule'!C179 -> 0 | E48: ='Debt Schedule'!C180 -> REFINANCING FAILURE | F48: ='Debt Schedule'!C181 -> PAYMENT DEFAULT
A49: =Assumptions!$A$65 -> 6.125% Guaranteed Notes due Jan-2031 | C49: ='Debt Schedule'!C182 -> 300 | D49: ='Debt Schedule'!C183 -> 0 | E49: ='Debt Schedule'!C184 -> REFINANCING FAILURE | F49: ='Debt Schedule'!C185 -> PAYMENT DEFAULT
A50: =Assumptions!$A$66 -> Junior subordinated trust-preferred indentures | C50: ='Debt Schedule'!C186 -> 0 | D50: ='Debt Schedule'!C187 -> 0 | E50: ='Debt Schedule'!C188 -> n/a (beyond horizon) | F50: ='Debt Schedule'!C189 -> n/a

Sheet Recovery
A1: Recovery — waterfall by seniority (collateral pools, deficiency claims) at the valuation event
A2: ="Brandywine Realty Trust · PUBLIC DATA CASE · HYPOTHETICAL INVESTMENT TERMS · Active scenario: "&Assumptions!$D$10 -> Brandywine Realty Trust · PUBLIC DATA CASE · HYPOTHETICAL INVESTMENT TERMS · Active scenario: Downside
A4: $M | C4: Value
A6: Valuation event (default period, or trough-EBITDA period if no default is modelled)
A7: Valuation event period flag | G7: =IF($C$8=1,'Cash Flow'!G22,IF('Operating Model'!G17=MIN('Operating Model'!$G$17:$K$17),1,0)) -> 0 | H7: =IF($C$8=1,'Cash Flow'!H22,IF(AND('Operating Model'!H17=MIN('Operating Model'!$G$17:$K$17),SUM($G$7:G7)=0),1,0)) -> 1 | I7: =IF($C$8=1,'Cash Flow'!I22,IF(AND('Operating Model'!I17=MIN('Operating Model'!$G$17:$K$17),SUM($G$7:H7)=0),1,0)) -> 0 | J7: =IF($C$8=1,'Cash Flow'!J22,IF(AND('Operating Model'!J17=MIN('Operating Model'!$G$17:$K$17),SUM($G$7:I7)=0),1,0)) -> 0 | K7: =IF($C$8=1,'Cash Flow'!K22,IF(AND('Operating Model'!K17=MIN('Operating Model'!$G$17:$K$17),SUM($G$7:J7)=0),1,0)) -> 0
A8: Default modelled? (1 = yes) | C8: =IF(SUM('Cash Flow'!$G$22:$K$22)>0,1,0) -> 1
A9: Valuation period | C9: =SUMPRODUCT($G$7:$K$7,'Operating Model'!$G$7:$K$7) -> 2028
A10: EBITDA at valuation event | C10: =SUMPRODUCT($G$7:$K$7,'Operating Model'!$G$17:$K$17) -> 220.35574
A11: Cash at valuation event | C11: =MAX(0,SUMPRODUCT($G$7:$K$7,'Cash Flow'!$G$19:$K$19)) -> 0
A12: Going-concern value (distressed multiple × EBITDA) | C12: =(CHOOSE(Assumptions!$C$10,Assumptions!$C$92,Assumptions!$C$111,Assumptions!$C$130))*C10 -> 1983.2017
A13: Liquidation value (asset base × (1 − decline) × recovery) | C13: =Assumptions!$C$31*(1-CHOOSE(Assumptions!$C$10,Assumptions!$C$93,Assumptions!$C$112,Assumptions!$C$131))*CHOOSE(Assumptions!$C$10,Assumptions!$C$94,Assumptions!$C$113,Assumptions!$C$132) -> 3264.0387
A14: Model recovery value (greater of the two + cash) | C14: =MAX(C12,C13)+C11 -> 3264.0387
A15: Recovery value used (override if provided) | C15: =IF(ISNUMBER(Assumptions!$C$14),Assumptions!$C$14,C14) -> 3264.0387
A16: Less: administrative / DIP costs | C16: =C15*Assumptions!$C$15 -> 130.56155
A17: Net value distributable to creditors | C17: =C15-C16 -> 3133.4772
A18: Claim at valuation event (balance + accrued interest)
A19: Tranche 1: Hypothetical Senior Secured Term Loan (S+525, 1% | C19: =SUMPRODUCT($G$7:$K$7,'Debt Schedule'!$G$28:$K$28)*(1+SUMPRODUCT($G$7:$K$7,'Debt Schedule'!$G$20:$K$20)*Assumptions!$C$16/12) -> 402.29
A20: Tranche 2: Avira Secured Term Loan (swapped to 5.81%) | C20: =SUMPRODUCT($G$7:$K$7,'Debt Schedule'!$G$41:$K$41)*(1+SUMPRODUCT($G$7:$K$7,'Debt Schedule'!$G$33:$K$33)*Assumptions!$C$16/12) -> 91.30725
A21: Tranche 3: 3151 Market C-PACE Loan | C21: =SUMPRODUCT($G$7:$K$7,'Debt Schedule'!$G$54:$K$54)*(1+SUMPRODUCT($G$7:$K$7,'Debt Schedule'!$G$46:$K$46)*Assumptions!$C$16/12) -> 58.371596
A22: Tranche 4: Unsecured Revolver ($600M less LCs; hypothetical | C22: =SUMPRODUCT($G$7:$K$7,'Debt Schedule'!$G$67:$K$67)*(1+SUMPRODUCT($G$7:$K$7,'Debt Schedule'!$G$59:$K$59)*Assumptions!$C$16/12) -> 0
A23: Tranche 5: 3.95% Guaranteed Notes due Nov-2027 | C23: =SUMPRODUCT($G$7:$K$7,'Debt Schedule'!$G$80:$K$80)*(1+SUMPRODUCT($G$7:$K$7,'Debt Schedule'!$G$72:$K$72)*Assumptions!$C$16/12) -> 405.41064
A24: Tranche 6: 8.30% Guaranteed Notes due Mar-2028 | C24: =SUMPRODUCT($G$7:$K$7,'Debt Schedule'!$G$93:$K$93)*(1+SUMPRODUCT($G$7:$K$7,'Debt Schedule'!$G$85:$K$85)*Assumptions!$C$16/12) -> 357.2625
A25: Tranche 7: 8.875% Guaranteed Notes due Apr-2029 | C25: =SUMPRODUCT($G$7:$K$7,'Debt Schedule'!$G$106:$K$106)*(1+SUMPRODUCT($G$7:$K$7,'Debt Schedule'!$G$98:$K$98)*Assumptions!$C$16/12) -> 562.20312
A26: Tranche 8: 4.55% Guaranteed Notes due Oct-2029 | C26: =SUMPRODUCT($G$7:$K$7,'Debt Schedule'!$G$119:$K$119)*(1+SUMPRODUCT($G$7:$K$7,'Debt Schedule'!$G$111:$K$111)*Assumptions!$C$16/12) -> 353.98125
A27: Tranche 9: 6.125% Guaranteed Notes due Jan-2031 | C27: =SUMPRODUCT($G$7:$K$7,'Debt Schedule'!$G$132:$K$132)*(1+SUMPRODUCT($G$7:$K$7,'Debt Schedule'!$G$124:$K$124)*Assumptions!$C$16/12) -> 304.59375
A28: Tranche 10: Junior subordinated trust-preferred indentures | C28: =SUMPRODUCT($G$7:$K$7,'Debt Schedule'!$G$145:$K$145)*(1+SUMPRODUCT($G$7:$K$7,'Debt Schedule'!$G$137:$K$137)*Assumptions!$C$16/12) -> 79.938509
A29: Seniority rank
A30: Tranche 1: Hypothetical Senior Secured Term Loan (S+525, 1% | C30: =Assumptions!$M$57 -> 1
A31: Tranche 2: Avira Secured Term Loan (swapped to 5.81%) | C31: =Assumptions!$M$58 -> 1
A32: Tranche 3: 3151 Market C-PACE Loan | C32: =Assumptions!$M$59 -> 1
A33: Tranche 4: Unsecured Revolver ($600M less LCs; hypothetical | C33: =Assumptions!$M$60 -> 2
A34: Tranche 5: 3.95% Guaranteed Notes due Nov-2027 | C34: =Assumptions!$M$61 -> 2
A35: Tranche 6: 8.30% Guaranteed Notes due Mar-2028 | C35: =Assumptions!$M$62 -> 2
A36: Tranche 7: 8.875% Guaranteed Notes due Apr-2029 | C36: =Assumptions!$M$63 -> 2
A37: Tranche 8: 4.55% Guaranteed Notes due Oct-2029 | C37: =Assumptions!$M$64 -> 2
A38: Tranche 9: 6.125% Guaranteed Notes due Jan-2031 | C38: =Assumptions!$M$65 -> 2
A39: Tranche 10: Junior subordinated trust-preferred indentures | C39: =Assumptions!$M$66 -> 3
A40: Collateral share (specific lien; 0 = all-asset / pari)
A41: Tranche 1: Hypothetical Senior Secured Term Loan (S+525, 1% | C41: =Assumptions!$Q$57 -> 0.3
A42: Tranche 2: Avira Secured Term Loan (swapped to 5.81%) | C42: =Assumptions!$Q$58 -> 0.033
A43: Tranche 3: 3151 Market C-PACE Loan | C43: =Assumptions!$Q$59 -> 0.021
A44: Tranche 4: Unsecured Revolver ($600M less LCs; hypothetical | C44: =Assumptions!$Q$60 -> 0
A45: Tranche 5: 3.95% Guaranteed Notes due Nov-2027 | C45: =Assumptions!$Q$61 -> 0
A46: Tranche 6: 8.30% Guaranteed Notes due Mar-2028 | C46: =Assumptions!$Q$62 -> 0
A47: Tranche 7: 8.875% Guaranteed Notes due Apr-2029 | C47: =Assumptions!$Q$63 -> 0
A48: Tranche 8: 4.55% Guaranteed Notes due Oct-2029 | C48: =Assumptions!$Q$64 -> 0
A49: Tranche 9: 6.125% Guaranteed Notes due Jan-2031 | C49: =Assumptions!$Q$65 -> 0
A50: Tranche 10: Junior subordinated trust-preferred indentures | C50: =Assumptions!$Q$66 -> 0
A51: Paid from own collateral pool
A52: Tranche 1: Hypothetical Senior Secured Term Loan (S+525, 1% | C52: =IF(C41>0,MIN(C19,C41*$C$17),0) -> 402.29
A53: Tranche 2: Avira Secured Term Loan (swapped to 5.81%) | C53: =IF(C42>0,MIN(C20,C42*$C$17),0) -> 91.30725
A54: Tranche 3: 3151 Market C-PACE Loan | C54: =IF(C43>0,MIN(C21,C43*$C$17),0) -> 58.371596
A55: Tranche 4: Unsecured Revolver ($600M less LCs; hypothetical | C55: =IF(C44>0,MIN(C22,C44*$C$17),0) -> 0
A56: Tranche 5: 3.95% Guaranteed Notes due Nov-2027 | C56: =IF(C45>0,MIN(C23,C45*$C$17),0) -> 0
A57: Tranche 6: 8.30% Guaranteed Notes due Mar-2028 | C57: =IF(C46>0,MIN(C24,C46*$C$17),0) -> 0
A58: Tranche 7: 8.875% Guaranteed Notes due Apr-2029 | C58: =IF(C47>0,MIN(C25,C47*$C$17),0) -> 0
A59: Tranche 8: 4.55% Guaranteed Notes due Oct-2029 | C59: =IF(C48>0,MIN(C26,C48*$C$17),0) -> 0
A60: Tranche 9: 6.125% Guaranteed Notes due Jan-2031 | C60: =IF(C49>0,MIN(C27,C49*$C$17),0) -> 0
A61: Tranche 10: Junior subordinated trust-preferred indentures | C61: =IF(C50>0,MIN(C28,C50*$C$17),0) -> 0
A62: Deficiency claim (joins general creditors)
A63: Tranche 1: Hypothetical Senior Secured Term Loan (S+525, 1% | C63: =IF(C41>0,C19-C52,0) -> 0 | G63: =IF(AND('Debt Schedule'!G18=1,'Debt Schedule'!G15=1),1,0) -> 0 | H63: =IF(G63=1,1,IF(AND('Debt Schedule'!H18=1,'Debt Schedule'!H15=1),1,0)) -> 0 | I63: =IF(H63=1,1,IF(AND('Debt Schedule'!I18=1,'Debt Schedule'!I15=1),1,0)) -> 0 | J63: =IF(I63=1,1,IF(AND('Debt Schedule'!J18=1,'Debt Schedule'!J15=1),1,0)) -> 0 | K63: =IF(J63=1,1,IF(AND('Debt Schedule'!K18=1,'Debt Schedule'!K15=1),1,0)) -> 0
A64: Tranche 2: Avira Secured Term Loan (swapped to 5.81%) | C64: =IF(C42>0,C20-C53,0) -> 0 | G64: =IF(AND('Debt Schedule'!G31=1,'Debt Schedule'!G15=1),1,0) -> 0 | H64: =IF(G64=1,1,IF(AND('Debt Schedule'!H31=1,'Debt Schedule'!H15=1),1,0)) -> 0 | I64: =IF(H64=1,1,IF(AND('Debt Schedule'!I31=1,'Debt Schedule'!I15=1),1,0)) -> 0 | J64: =IF(I64=1,1,IF(AND('Debt Schedule'!J31=1,'Debt Schedule'!J15=1),1,0)) -> 0 | K64: =IF(J64=1,1,IF(AND('Debt Schedule'!K31=1,'Debt Schedule'!K15=1),1,0)) -> 0
A65: Tranche 3: 3151 Market C-PACE Loan | C65: =IF(C43>0,C21-C54,0) -> 0 | G65: =IF(AND('Debt Schedule'!G44=1,'Debt Schedule'!G15=1),1,0) -> 0 | H65: =IF(G65=1,1,IF(AND('Debt Schedule'!H44=1,'Debt Schedule'!H15=1),1,0)) -> 0 | I65: =IF(H65=1,1,IF(AND('Debt Schedule'!I44=1,'Debt Schedule'!I15=1),1,0)) -> 0 | J65: =IF(I65=1,1,IF(AND('Debt Schedule'!J44=1,'Debt Schedule'!J15=1),1,0)) -> 0 | K65: =IF(J65=1,1,IF(AND('Debt Schedule'!K44=1,'Debt Schedule'!K15=1),1,0)) -> 0
A66: Tranche 4: Unsecured Revolver ($600M less LCs; hypothetical | C66: =IF(C44>0,C22-C55,0) -> 0 | G66: =IF(AND('Debt Schedule'!G57=1,'Debt Schedule'!G15=1),1,0) -> 0 | H66: =IF(G66=1,1,IF(AND('Debt Schedule'!H57=1,'Debt Schedule'!H15=1),1,0)) -> 0 | I66: =IF(H66=1,1,IF(AND('Debt Schedule'!I57=1,'Debt Schedule'!I15=1),1,0)) -> 0 | J66: =IF(I66=1,1,IF(AND('Debt Schedule'!J57=1,'Debt Schedule'!J15=1),1,0)) -> 0 | K66: =IF(J66=1,1,IF(AND('Debt Schedule'!K57=1,'Debt Schedule'!K15=1),1,0)) -> 0
A67: Tranche 5: 3.95% Guaranteed Notes due Nov-2027 | C67: =IF(C45>0,C23-C56,0) -> 0 | G67: =IF(AND('Debt Schedule'!G70=1,'Debt Schedule'!G15=1),1,0) -> 0 | H67: =IF(G67=1,1,IF(AND('Debt Schedule'!H70=1,'Debt Schedule'!H15=1),1,0)) -> 0 | I67: =IF(H67=1,1,IF(AND('Debt Schedule'!I70=1,'Debt Schedule'!I15=1),1,0)) -> 0 | J67: =IF(I67=1,1,IF(AND('Debt Schedule'!J70=1,'Debt Schedule'!J15=1),1,0)) -> 0 | K67: =IF(J67=1,1,IF(AND('Debt Schedule'!K70=1,'Debt Schedule'!K15=1),1,0)) -> 0
A68: Tranche 6: 8.30% Guaranteed Notes due Mar-2028 | C68: =IF(C46>0,C24-C57,0) -> 0 | G68: =IF(AND('Debt Schedule'!G83=1,'Debt Schedule'!G15=1),1,0) -> 0 | H68: =IF(G68=1,1,IF(AND('Debt Schedule'!H83=1,'Debt Schedule'!H15=1),1,0)) -> 0 | I68: =IF(H68=1,1,IF(AND('Debt Schedule'!I83=1,'Debt Schedule'!I15=1),1,0)) -> 0 | J68: =IF(I68=1,1,IF(AND('Debt Schedule'!J83=1,'Debt Schedule'!J15=1),1,0)) -> 0 | K68: =IF(J68=1,1,IF(AND('Debt Schedule'!K83=1,'Debt Schedule'!K15=1),1,0)) -> 0
A69: Tranche 7: 8.875% Guaranteed Notes due Apr-2029 | C69: =IF(C47>0,C25-C58,0) -> 0 | G69: =IF(AND('Debt Schedule'!G96=1,'Debt Schedule'!G15=1),1,0) -> 0 | H69: =IF(G69=1,1,IF(AND('Debt Schedule'!H96=1,'Debt Schedule'!H15=1),1,0)) -> 0 | I69: =IF(H69=1,1,IF(AND('Debt Schedule'!I96=1,'Debt Schedule'!I15=1),1,0)) -> 0 | J69: =IF(I69=1,1,IF(AND('Debt Schedule'!J96=1,'Debt Schedule'!J15=1),1,0)) -> 0 | K69: =IF(J69=1,1,IF(AND('Debt Schedule'!K96=1,'Debt Schedule'!K15=1),1,0)) -> 0
A70: Tranche 8: 4.55% Guaranteed Notes due Oct-2029 | C70: =IF(C48>0,C26-C59,0) -> 0 | G70: =IF(AND('Debt Schedule'!G109=1,'Debt Schedule'!G15=1),1,0) -> 0 | H70: =IF(G70=1,1,IF(AND('Debt Schedule'!H109=1,'Debt Schedule'!H15=1),1,0)) -> 0 | I70: =IF(H70=1,1,IF(AND('Debt Schedule'!I109=1,'Debt Schedule'!I15=1),1,0)) -> 0 | J70: =IF(I70=1,1,IF(AND('Debt Schedule'!J109=1,'Debt Schedule'!J15=1),1,0)) -> 0 | K70: =IF(J70=1,1,IF(AND('Debt Schedule'!K109=1,'Debt Schedule'!K15=1),1,0)) -> 0
A71: Tranche 9: 6.125% Guaranteed Notes due Jan-2031 | C71: =IF(C49>0,C27-C60,0) -> 0 | G71: =IF(AND('Debt Schedule'!G122=1,'Debt Schedule'!G15=1),1,0) -> 0 | H71: =IF(G71=1,1,IF(AND('Debt Schedule'!H122=1,'Debt Schedule'!H15=1),1,0)) -> 0 | I71: =IF(H71=1,1,IF(AND('Debt Schedule'!I122=1,'Debt Schedule'!I15=1),1,0)) -> 0 | J71: =IF(I71=1,1,IF(AND('Debt Schedule'!J122=1,'Debt Schedule'!J15=1),1,0)) -> 0 | K71: =IF(J71=1,1,IF(AND('Debt Schedule'!K122=1,'Debt Schedule'!K15=1),1,0)) -> 0
A72: Tranche 10: Junior subordinated trust-preferred indentures | C72: =IF(C50>0,C28-C61,0) -> 0 | G72: =IF(AND('Debt Schedule'!G135=1,'Debt Schedule'!G15=1),1,0) -> 0 | H72: =IF(G72=1,1,IF(AND('Debt Schedule'!H135=1,'Debt Schedule'!H15=1),1,0)) -> 0 | I72: =IF(H72=1,1,IF(AND('Debt Schedule'!I135=1,'Debt Schedule'!I15=1),1,0)) -> 0 | J72: =IF(I72=1,1,IF(AND('Debt Schedule'!J135=1,'Debt Schedule'!J15=1),1,0)) -> 0 | K72: =IF(J72=1,1,IF(AND('Debt Schedule'!K135=1,'Debt Schedule'!K15=1),1,0)) -> 0
A73: General claim
A74: Tranche 1: Hypothetical Senior Secured Term Loan (S+525, 1% | C74: =IF(C41>0,C63,C19) -> 0
A75: Tranche 2: Avira Secured Term Loan (swapped to 5.81%) | C75: =IF(C42>0,C64,C20) -> 0
A76: Tranche 3: 3151 Market C-PACE Loan | C76: =IF(C43>0,C65,C21) -> 0
A77: Tranche 4: Unsecured Revolver ($600M less LCs; hypothetical | C77: =IF(C44>0,C66,C22) -> 0
A78: Tranche 5: 3.95% Guaranteed Notes due Nov-2027 | C78: =IF(C45>0,C67,C23) -> 405.41064
A79: Tranche 6: 8.30% Guaranteed Notes due Mar-2028 | C79: =IF(C46>0,C68,C24) -> 357.2625
A80: Tranche 7: 8.875% Guaranteed Notes due Apr-2029 | C80: =IF(C47>0,C69,C25) -> 562.20312
A81: Tranche 8: 4.55% Guaranteed Notes due Oct-2029 | C81: =IF(C48>0,C70,C26) -> 353.98125
A82: Tranche 9: 6.125% Guaranteed Notes due Jan-2031 | C82: =IF(C49>0,C71,C27) -> 304.59375
A83: Tranche 10: Junior subordinated trust-preferred indentures | C83: =IF(C50>0,C72,C28) -> 79.938509
A84: General rank
A85: Tranche 1: Hypothetical Senior Secured Term Loan (S+525, 1% | C85: =IF(C41>0,Assumptions!$C$17,C30) -> 99
A86: Tranche 2: Avira Secured Term Loan (swapped to 5.81%) | C86: =IF(C42>0,Assumptions!$C$17,C31) -> 99
A87: Tranche 3: 3151 Market C-PACE Loan | C87: =IF(C43>0,Assumptions!$C$17,C32) -> 99
A88: Tranche 4: Unsecured Revolver ($600M less LCs; hypothetical | C88: =IF(C44>0,Assumptions!$C$17,C33) -> 2
A89: Tranche 5: 3.95% Guaranteed Notes due Nov-2027 | C89: =IF(C45>0,Assumptions!$C$17,C34) -> 2
A90: Tranche 6: 8.30% Guaranteed Notes due Mar-2028 | C90: =IF(C46>0,Assumptions!$C$17,C35) -> 2
A91: Tranche 7: 8.875% Guaranteed Notes due Apr-2029 | C91: =IF(C47>0,Assumptions!$C$17,C36) -> 2
A92: Tranche 8: 4.55% Guaranteed Notes due Oct-2029 | C92: =IF(C48>0,Assumptions!$C$17,C37) -> 2
A93: Tranche 9: 6.125% Guaranteed Notes due Jan-2031 | C93: =IF(C49>0,Assumptions!$C$17,C38) -> 2
A94: Tranche 10: Junior subordinated trust-preferred indentures | C94: =IF(C50>0,Assumptions!$C$17,C39) -> 3
A95: General claims ahead
A96: Tranche 1: Hypothetical Senior Secured Term Loan (S+525, 1% | C96: =SUMPRODUCT(($C$85:$C$94<C85)*$C$74:$C$83) -> 2063.3898
A97: Tranche 2: Avira Secured Term Loan (swapped to 5.81%) | C97: =SUMPRODUCT(($C$85:$C$94<C86)*$C$74:$C$83) -> 2063.3898
A98: Tranche 3: 3151 Market C-PACE Loan | C98: =SUMPRODUCT(($C$85:$C$94<C87)*$C$74:$C$83) -> 2063.3898
A99: Tranche 4: Unsecured Revolver ($600M less LCs; hypothetical | C99: =SUMPRODUCT(($C$85:$C$94<C88)*$C$74:$C$83) -> 0
A100: Tranche 5: 3.95% Guaranteed Notes due Nov-2027 | C100: =SUMPRODUCT(($C$85:$C$94<C89)*$C$74:$C$83) -> 0
A101: Tranche 6: 8.30% Guaranteed Notes due Mar-2028 | C101: =SUMPRODUCT(($C$85:$C$94<C90)*$C$74:$C$83) -> 0
A102: Tranche 7: 8.875% Guaranteed Notes due Apr-2029 | C102: =SUMPRODUCT(($C$85:$C$94<C91)*$C$74:$C$83) -> 0
...

Sheet Returns
A1: Returns — face, purchase price, coupon, yield, recovery, IRR and MOIC (selected scenario)
A2: ="Brandywine Realty Trust · PUBLIC DATA CASE · HYPOTHETICAL INVESTMENT TERMS · Active scenario: "&Assumptions!$D$10 -> Brandywine Realty Trust · PUBLIC DATA CASE · HYPOTHETICAL INVESTMENT TERMS · Active scenario: Downside
A4: $M | C4: Value / t=0 | D4: t=1 | E4: t=2 | F4: t=3 | G4: t=4 | H4: t=5 | I4: t=6
A6: Position & valuation inputs (links) — face value, purchase price, coupon, yield and recovery are distinct
A7: Target tranche # | C7: =Assumptions!$C$34 -> 1
A8: Face value (legal claim) | C8: =Assumptions!$C$35 -> 100
A9: Purchase price / OID (% of face) | C9: =Assumptions!$C$36 -> 98
A10: Cash investment (face × price × (1 + fees)) | C10: =C8*C9/100*(1+Assumptions!$C$37) -> 98.49
A11: Hold period (periods) | C11: =Assumptions!$C$38 -> 3
A12: Default period # (0 = no default) | C12: =IF(Recovery!C8=1,SUMPRODUCT('Cash Flow'!$G$22:$K$22,'Operating Model'!$G$8:$K$8),0) -> 2
A13: Our share of the tranche at the valuation event | C13: =IFERROR(C8/CHOOSE(C7,SUMPRODUCT(Recovery!$G$7:$K$7,'Debt Schedule'!$G$28:$K$28),SUMPRODUCT(Recovery!$G$7:$K$7,'Debt Schedule'!$G$41:$K$41),SUMPRODUCT(Recovery!$G$7:$K$7,'Debt Schedule'!$G$54:$K$54),SUMPRODUCT(Recovery!$G$7:$K$7,'Debt Schedule'!$G$67:$K$67),SUMPRODUCT(Recovery!$G$7:$K$7,'Debt Schedule'!$G$80:$K$80),SUMPRODUCT(Recovery!$G$7:$K$7,'Debt Schedule'!$G$93:$K$93),SUMPRODUCT(Recovery!$G$7:$K$7,'Debt Schedule'!$G$106:$K$106),SUMPRODUCT(Recovery!$G$7:$K$7,'Debt Schedule'!$G$119:$K$119),SUMPRODUCT(Recovery!$G$7:$K$7,'Debt Schedule'!$G$132:$K$132),SUMPRODUCT(Recovery!$G$7:$K$7,'Debt Schedule'!$G$145:$K$145)),0) -> 0.25510204
A14: Recovery proceeds to our position if default | C14: =CHOOSE(C7,Recovery!C129,Recovery!C130,Recovery!C131,Recovery!C132,Recovery!C133,Recovery!C134,Recovery!C135,Recovery!C136,Recovery!C137,Recovery!C138)*C13 -> 102.625
A15: Tranche recovery % at valuation event (waterfall) | C15: =CHOOSE(C7,Recovery!C140,Recovery!C141,Recovery!C142,Recovery!C143,Recovery!C144,Recovery!C145,Recovery!C146,Recovery!C147,Recovery!C148,Recovery!C149) -> 1
A16: Last coupon period # | C16: =IF(Recovery!C8=1,C12,C11) -> 2
A17: Exit price assumption (no default) | C17: =CHOOSE(Assumptions!$C$10,Assumptions!$C$91,Assumptions!$C$110,Assumptions!$C$129) -> 95
A18: Exit EV (exit multiple × EBITDA + cash at hold period) | C18: =INDEX('Operating Model'!$G$17:$K$17,C11)*CHOOSE(Assumptions!$C$10,Assumptions!$C$90,Assumptions!$C$109,Assumptions!$C$128)+MAX(0,INDEX('Cash Flow'!$G$19:$K$19,C11)) -> 2423.9131
A19: Claim at exit (balance at hold period)
A20: Tranche 1: Hypothetical Senior Secured Term Loan (S+525, 1% | C20: =INDEX('Debt Schedule'!$G$28:$K$28,C11) -> 388
A21: Tranche 2: Avira Secured Term Loan (swapped to 5.81%) | C21: =INDEX('Debt Schedule'!$G$41:$K$41,C11) -> 90
A22: Tranche 3: 3151 Market C-PACE Loan | C22: =INDEX('Debt Schedule'!$G$54:$K$54,C11) -> 57.324
A23: Tranche 4: Unsecured Revolver ($600M less LCs; hypothetical | C23: =INDEX('Debt Schedule'!$G$67:$K$67,C11) -> 0
A24: Tranche 5: 3.95% Guaranteed Notes due Nov-2027 | C24: =INDEX('Debt Schedule'!$G$80:$K$80,C11) -> 401.44636
A25: Tranche 6: 8.30% Guaranteed Notes due Mar-2028 | C25: =INDEX('Debt Schedule'!$G$93:$K$93,C11) -> 350
A26: Tranche 7: 8.875% Guaranteed Notes due Apr-2029 | C26: =INDEX('Debt Schedule'!$G$106:$K$106,C11) -> 550
A27: Tranche 8: 4.55% Guaranteed Notes due Oct-2029 | C27: =INDEX('Debt Schedule'!$G$119:$K$119,C11) -> 350
A28: Tranche 9: 6.125% Guaranteed Notes due Jan-2031 | C28: =INDEX('Debt Schedule'!$G$132:$K$132,C11) -> 300
A29: Tranche 10: Junior subordinated trust-preferred indentures | C29: =INDEX('Debt Schedule'!$G$145:$K$145,C11) -> 78.61
A30: Seniority rank
A31: Tranche 1: Hypothetical Senior Secured Term Loan (S+525, 1% | C31: =Assumptions!$M$57 -> 1
A32: Tranche 2: Avira Secured Term Loan (swapped to 5.81%) | C32: =Assumptions!$M$58 -> 1
A33: Tranche 3: 3151 Market C-PACE Loan | C33: =Assumptions!$M$59 -> 1
A34: Tranche 4: Unsecured Revolver ($600M less LCs; hypothetical | C34: =Assumptions!$M$60 -> 2
A35: Tranche 5: 3.95% Guaranteed Notes due Nov-2027 | C35: =Assumptions!$M$61 -> 2
A36: Tranche 6: 8.30% Guaranteed Notes due Mar-2028 | C36: =Assumptions!$M$62 -> 2
A37: Tranche 7: 8.875% Guaranteed Notes due Apr-2029 | C37: =Assumptions!$M$63 -> 2
A38: Tranche 8: 4.55% Guaranteed Notes due Oct-2029 | C38: =Assumptions!$M$64 -> 2
A39: Tranche 9: 6.125% Guaranteed Notes due Jan-2031 | C39: =Assumptions!$M$65 -> 2
A40: Tranche 10: Junior subordinated trust-preferred indentures | C40: =Assumptions!$M$66 -> 3
A41: Collateral share (specific lien; 0 = all-asset / pari)
A42: Tranche 1: Hypothetical Senior Secured Term Loan (S+525, 1% | C42: =Assumptions!$Q$57 -> 0.3
A43: Tranche 2: Avira Secured Term Loan (swapped to 5.81%) | C43: =Assumptions!$Q$58 -> 0.033
A44: Tranche 3: 3151 Market C-PACE Loan | C44: =Assumptions!$Q$59 -> 0.021
A45: Tranche 4: Unsecured Revolver ($600M less LCs; hypothetical | C45: =Assumptions!$Q$60 -> 0
A46: Tranche 5: 3.95% Guaranteed Notes due Nov-2027 | C46: =Assumptions!$Q$61 -> 0
A47: Tranche 6: 8.30% Guaranteed Notes due Mar-2028 | C47: =Assumptions!$Q$62 -> 0
A48: Tranche 7: 8.875% Guaranteed Notes due Apr-2029 | C48: =Assumptions!$Q$63 -> 0
A49: Tranche 8: 4.55% Guaranteed Notes due Oct-2029 | C49: =Assumptions!$Q$64 -> 0
A50: Tranche 9: 6.125% Guaranteed Notes due Jan-2031 | C50: =Assumptions!$Q$65 -> 0
A51: Tranche 10: Junior subordinated trust-preferred indentures | C51: =Assumptions!$Q$66 -> 0
A52: Paid from own collateral pool
A53: Tranche 1: Hypothetical Senior Secured Term Loan (S+525, 1% | C53: =IF(C42>0,MIN(C20,C42*$C$18),0) -> 388
A54: Tranche 2: Avira Secured Term Loan (swapped to 5.81%) | C54: =IF(C43>0,MIN(C21,C43*$C$18),0) -> 79.989134
A55: Tranche 3: 3151 Market C-PACE Loan | C55: =IF(C44>0,MIN(C22,C44*$C$18),0) -> 50.902176
A56: Tranche 4: Unsecured Revolver ($600M less LCs; hypothetical | C56: =IF(C45>0,MIN(C23,C45*$C$18),0) -> 0
A57: Tranche 5: 3.95% Guaranteed Notes due Nov-2027 | C57: =IF(C46>0,MIN(C24,C46*$C$18),0) -> 0
A58: Tranche 6: 8.30% Guaranteed Notes due Mar-2028 | C58: =IF(C47>0,MIN(C25,C47*$C$18),0) -> 0
A59: Tranche 7: 8.875% Guaranteed Notes due Apr-2029 | C59: =IF(C48>0,MIN(C26,C48*$C$18),0) -> 0
A60: Tranche 8: 4.55% Guaranteed Notes due Oct-2029 | C60: =IF(C49>0,MIN(C27,C49*$C$18),0) -> 0
A61: Tranche 9: 6.125% Guaranteed Notes due Jan-2031 | C61: =IF(C50>0,MIN(C28,C50*$C$18),0) -> 0
A62: Tranche 10: Junior subordinated trust-preferred indentures | C62: =IF(C51>0,MIN(C29,C51*$C$18),0) -> 0
A63: Deficiency claim (joins general creditors)
A64: Tranche 1: Hypothetical Senior Secured Term Loan (S+525, 1% | C64: =IF(C42>0,C20-C53,0) -> 0
A65: Tranche 2: Avira Secured Term Loan (swapped to 5.81%) | C65: =IF(C43>0,C21-C54,0) -> 10.010866
A66: Tranche 3: 3151 Market C-PACE Loan | C66: =IF(C44>0,C22-C55,0) -> 6.4218239
A67: Tranche 4: Unsecured Revolver ($600M less LCs; hypothetical | C67: =IF(C45>0,C23-C56,0) -> 0
A68: Tranche 5: 3.95% Guaranteed Notes due Nov-2027 | C68: =IF(C46>0,C24-C57,0) -> 0
A69: Tranche 6: 8.30% Guaranteed Notes due Mar-2028 | C69: =IF(C47>0,C25-C58,0) -> 0
A70: Tranche 7: 8.875% Guaranteed Notes due Apr-2029 | C70: =IF(C48>0,C26-C59,0) -> 0
A71: Tranche 8: 4.55% Guaranteed Notes due Oct-2029 | C71: =IF(C49>0,C27-C60,0) -> 0
A72: Tranche 9: 6.125% Guaranteed Notes due Jan-2031 | C72: =IF(C50>0,C28-C61,0) -> 0
A73: Tranche 10: Junior subordinated trust-preferred indentures | C73: =IF(C51>0,C29-C62,0) -> 0
A74: General claim
A75: Tranche 1: Hypothetical Senior Secured Term Loan (S+525, 1% | C75: =IF(C42>0,C64,C20) -> 0
A76: Tranche 2: Avira Secured Term Loan (swapped to 5.81%) | C76: =IF(C43>0,C65,C21) -> 10.010866
A77: Tranche 3: 3151 Market C-PACE Loan | C77: =IF(C44>0,C66,C22) -> 6.4218239
A78: Tranche 4: Unsecured Revolver ($600M less LCs; hypothetical | C78: =IF(C45>0,C67,C23) -> 0
A79: Tranche 5: 3.95% Guaranteed Notes due Nov-2027 | C79: =IF(C46>0,C68,C24) -> 401.44636
A80: Tranche 6: 8.30% Guaranteed Notes due Mar-2028 | C80: =IF(C47>0,C69,C25) -> 350
A81: Tranche 7: 8.875% Guaranteed Notes due Apr-2029 | C81: =IF(C48>0,C70,C26) -> 550
A82: Tranche 8: 4.55% Guaranteed Notes due Oct-2029 | C82: =IF(C49>0,C71,C27) -> 350
A83: Tranche 9: 6.125% Guaranteed Notes due Jan-2031 | C83: =IF(C50>0,C72,C28) -> 300
A84: Tranche 10: Junior subordinated trust-preferred indentures | C84: =IF(C51>0,C73,C29) -> 78.61
A85: General rank
A86: Tranche 1: Hypothetical Senior Secured Term Loan (S+525, 1% | C86: =IF(C42>0,Assumptions!$C$17,C31) -> 99
A87: Tranche 2: Avira Secured Term Loan (swapped to 5.81%) | C87: =IF(C43>0,Assumptions!$C$17,C32) -> 99
A88: Tranche 3: 3151 Market C-PACE Loan | C88: =IF(C44>0,Assumptions!$C$17,C33) -> 99
A89: Tranche 4: Unsecured Revolver ($600M less LCs; hypothetical | C89: =IF(C45>0,Assumptions!$C$17,C34) -> 2
A90: Tranche 5: 3.95% Guaranteed Notes due Nov-2027 | C90: =IF(C46>0,Assumptions!$C$17,C35) -> 2
A91: Tranche 6: 8.30% Guaranteed Notes due Mar-2028 | C91: =IF(C47>0,Assumptions!$C$17,C36) -> 2
A92: Tranche 7: 8.875% Guaranteed Notes due Apr-2029 | C92: =IF(C48>0,Assumptions!$C$17,C37) -> 2
A93: Tranche 8: 4.55% Guaranteed Notes due Oct-2029 | C93: =IF(C49>0,Assumptions!$C$17,C38) -> 2
A94: Tranche 9: 6.125% Guaranteed Notes due Jan-2031 | C94: =IF(C50>0,Assumptions!$C$17,C39) -> 2
A95: Tranche 10: Junior subordinated trust-preferred indentures | C95: =IF(C51>0,Assumptions!$C$17,C40) -> 3
A96: General claims ahead
A97: Tranche 1: Hypothetical Senior Secured Term Loan (S+525, 1% | C97: =SUMPRODUCT(($C$86:$C$95<C86)*$C$75:$C$84) -> 2030.0564
A98: Tranche 2: Avira Secured Term Loan (swapped to 5.81%) | C98: =SUMPRODUCT(($C$86:$C$95<C87)*$C$75:$C$84) -> 2030.0564
A99: Tranche 3: 3151 Market C-PACE Loan | C99: =SUMPRODUCT(($C$86:$C$95<C88)*$C$75:$C$84) -> 2030.0564
A100: Tranche 4: Unsecured Revolver ($600M less LCs; hypothetical | C100: =SUMPRODUCT(($C$86:$C$95<C89)*$C$75:$C$84) -> 0
A101: Tranche 5: 3.95% Guaranteed Notes due Nov-2027 | C101: =SUMPRODUCT(($C$86:$C$95<C90)*$C$75:$C$84) -> 0
A102: Tranche 6: 8.30% Guaranteed Notes due Mar-2028 | C102: =SUMPRODUCT(($C$86:$C$95<C91)*$C$75:$C$84) -> 0
...

Sheet Sensitivities
A1: Sensitivities — position IRR / MOIC under Base, Downside and Severe
A2: Axis values (blue) are inputs. Every cell is a formula: IRR over a cash-flow row, or an IRR / recovery from a full Calc Engine case. No data tables → recalculates in Excel and LibreOffice.
A3: ="Position: "&TEXT(Assumptions!$C$36,"0.0")&" purchase price, hold "&Assumptions!$C$38&" periods | Selected scenario: "&Assumptions!$D$10 -> Position: 98.0 purchase price, hold 3 periods | Selected scenario: Downside
A8: Table 1 — Purchase price vs IRR
A9: Purchase price (% of face) | B9: Offset | C9: Base Case | D9: Downside | E9: Severe Downside | F9: Selected
A10: =Assumptions!$C$36+B10 -> 90 | B10: -8 | C10: =J86 -> 0.13029537 | D10: =J91 -> 0.1221803 | E10: =J96 -> 0.13507029 | F10: =CHOOSE(Assumptions!$C$10,C10,D10,E10) -> 0.1221803
A11: =Assumptions!$C$36+B11 -> 94 | B11: -4 | C11: =J87 -> 0.11253737 | D11: =J92 -> 0.10426043 | E11: =J97 -> 0.11669319 | F11: =CHOOSE(Assumptions!$C$10,C11,D11,E11) -> 0.10426043
A12: =Assumptions!$C$36+B12 -> 98 | B12: 0 | C12: =J88 -> 0.095815282 | D12: =J93 -> 0.087396249 | E12: =J98 -> 0.099407759 | F12: =CHOOSE(Assumptions!$C$10,C12,D12,E12) -> 0.087396249
A13: =Assumptions!$C$36+B13 -> 102 | B13: 4 | C13: =J89 -> 0.080028741 | D13: =J94 -> 0.071484707 | E13: =J99 -> 0.083106767 | F13: =CHOOSE(Assumptions!$C$10,C13,D13,E13) -> 0.071484707
A14: =Assumptions!$C$36+B14 -> 106 | B14: 8 | C14: =J90 -> 0.065090667 | D14: =J95 -> 0.056436476 | E14: =J100 -> 0.06769732 | F14: =CHOOSE(Assumptions!$C$10,C14,D14,E14) -> 0.056436476
A18: Table 2 — Exit / recovery value (% of face, received at exit or after default) vs IRR
A19: Proceeds (% of face) | C19: Base Case | D19: Downside | E19: Severe Downside | F19: Selected
A20: 20 | C20: =J101 -> -0.25635751 | D20: =J106 -> -0.31034127 | E20: =J111 -> -0.29510451 | F20: =CHOOSE(Assumptions!$C$10,C20,D20,E20) -> -0.31034127
A21: 40 | C21: =J102 -> -0.13685355 | D21: =J107 -> -0.17150566 | E21: =J112 -> -0.15842656 | F21: =CHOOSE(Assumptions!$C$10,C21,D21,E21) -> -0.17150566
A22: 60 | C22: =J103 -> -0.045383594 | D22: =J108 -> -0.071088819 | E22: =J113 -> -0.05906606 | F22: =CHOOSE(Assumptions!$C$10,C22,D22,E22) -> -0.071088819
A23: 80 | C23: =J104 -> 0.030365923 | D23: =J109 -> 0.0099803984 | E23: =J114 -> 0.02133754 | F23: =CHOOSE(Assumptions!$C$10,C23,D23,E23) -> 0.0099803984
A24: 100 | C24: =J105 -> 0.095815282 | D24: =J110 -> 0.079012717 | E24: =J115 -> 0.089897638 | F24: =CHOOSE(Assumptions!$C$10,C24,D24,E24) -> 0.079012717
A28: Table 3 — EBITDA margin shift (all periods) vs IRR — full model re-run
A29: EBITDA margin shift (pts) | C29: Base Case | D29: Downside | E29: Severe Downside | F29: Selected
A30: -0.04 | C30: ='Calc Engine'!C2618 -> 0.083196174 | D30: ='Calc Engine'!C5893 -> 0.087396249 | E30: ='Calc Engine'!C9168 -> 0.099407759 | F30: =CHOOSE(Assumptions!$C$10,C30,D30,E30) -> 0.087396249
A31: -0.02 | C31: ='Calc Engine'!C3273 -> 0.095815282 | D31: ='Calc Engine'!C6548 -> 0.087396249 | E31: ='Calc Engine'!C9823 -> 0.099407759 | F31: =CHOOSE(Assumptions!$C$10,C31,D31,E31) -> 0.087396249
A32: 0 | C32: ='Calc Engine'!C3928 -> 0.095815282 | D32: ='Calc Engine'!C7203 -> 0.087396249 | E32: ='Calc Engine'!C10478 -> 0.099407759 | F32: =CHOOSE(Assumptions!$C$10,C32,D32,E32) -> 0.087396249
A33: 0.02 | C33: ='Calc Engine'!C4583 -> 0.095815282 | D33: ='Calc Engine'!C7858 -> 0.087396249 | E33: ='Calc Engine'!C11133 -> 0.099407759 | F33: =CHOOSE(Assumptions!$C$10,C33,D33,E33) -> 0.087396249
A34: 0.04 | C34: ='Calc Engine'!C5238 -> 0.095815282 | D34: ='Calc Engine'!C8513 -> 0.087396249 | E34: ='Calc Engine'!C11788 -> 0.099407759 | F34: =CHOOSE(Assumptions!$C$10,C34,D34,E34) -> 0.087396249
A38: Table 4 — Revenue growth shift (all periods) vs IRR — full model re-run
A39: Revenue growth shift (pts) | C39: Base Case | D39: Downside | E39: Severe Downside | F39: Selected
A40: -0.1 | C40: ='Calc Engine'!C12443 -> 0.07546385 | D40: ='Calc Engine'!C15718 -> 0.087396249 | E40: ='Calc Engine'!C18993 -> 0.099407759 | F40: =CHOOSE(Assumptions!$C$10,C40,D40,E40) -> 0.087396249
A41: -0.05 | C41: ='Calc Engine'!C13098 -> 0.079235273 | D41: ='Calc Engine'!C16373 -> 0.087396249 | E41: ='Calc Engine'!C19648 -> 0.099407759 | F41: =CHOOSE(Assumptions!$C$10,C41,D41,E41) -> 0.087396249
A42: 0 | C42: ='Calc Engine'!C13753 -> 0.095815282 | D42: ='Calc Engine'!C17028 -> 0.087396249 | E42: ='Calc Engine'!C20303 -> 0.099407759 | F42: =CHOOSE(Assumptions!$C$10,C42,D42,E42) -> 0.087396249
A43: 0.05 | C43: ='Calc Engine'!C14408 -> 0.095815282 | D43: ='Calc Engine'!C17683 -> 0.087396249 | E43: ='Calc Engine'!C20958 -> 0.099407759 | F43: =CHOOSE(Assumptions!$C$10,C43,D43,E43) -> 0.087396249
A44: 0.1 | C44: ='Calc Engine'!C15063 -> 0.095815282 | D44: ='Calc Engine'!C18338 -> 0.087396249 | E44: ='Calc Engine'!C21613 -> 0.099407759 | F44: =CHOOSE(Assumptions!$C$10,C44,D44,E44) -> 0.087396249
A48: Table 5 — Interest rate (SOFR) shift vs IRR — full model re-run (floating coupons and interest burden both move)
A49: SOFR shift (pts) | C49: Base Case | D49: Downside | E49: Severe Downside | F49: Selected
A50: -0.01 | C50: ='Calc Engine'!C22268 -> 0.085695413 | D50: ='Calc Engine'!C25543 -> 0.079432456 | E50: ='Calc Engine'!C28818 -> 0.091391352 | F50: =CHOOSE(Assumptions!$C$10,C50,D50,E50) -> 0.079432456
A51: -0.005 | C51: ='Calc Engine'!C22923 -> 0.090755288 | D51: ='Calc Engine'!C26198 -> 0.083409936 | E51: ='Calc Engine'!C29473 -> 0.095395203 | F51: =CHOOSE(Assumptions!$C$10,C51,D51,E51) -> 0.083409936
A52: 0 | C52: ='Calc Engine'!C23578 -> 0.095815282 | D52: ='Calc Engine'!C26853 -> 0.087396249 | E52: ='Calc Engine'!C30128 -> 0.099407759 | F52: =CHOOSE(Assumptions!$C$10,C52,D52,E52) -> 0.087396249
A53: 0.01 | C53: ='Calc Engine'!C24233 -> 0.10593562 | D53: ='Calc Engine'!C27508 -> 0.095395203 | E53: ='Calc Engine'!C30783 -> 0.10745882 | F53: =CHOOSE(Assumptions!$C$10,C53,D53,E53) -> 0.095395203
A54: 0.02 | C54: ='Calc Engine'!C24888 -> 0.11605642 | D54: ='Calc Engine'!C28163 -> 0.10342898 | E54: ='Calc Engine'!C31438 -> 0.11554419 | F54: =CHOOSE(Assumptions!$C$10,C54,D54,E54) -> 0.10342898
A58: Table 6 — Distressed valuation multiple shift (x) vs target-tranche recovery % (valuation waterfall)
A59: Multiple shift (x EBITDA) | C59: Base Case | D59: Downside | E59: Severe Downside | F59: Selected
A60: -2 | C60: ='Calc Engine'!C31920 -> 1 | D60: ='Calc Engine'!C35195 -> 1 | E60: ='Calc Engine'!C38470 -> 1 | F60: =CHOOSE(Assumptions!$C$10,C60,D60,E60) -> 1
A61: -1 | C61: ='Calc Engine'!C32575 -> 1 | D61: ='Calc Engine'!C35850 -> 1 | E61: ='Calc Engine'!C39125 -> 1 | F61: =CHOOSE(Assumptions!$C$10,C61,D61,E61) -> 1
A62: 0 | C62: ='Calc Engine'!C33230 -> 1 | D62: ='Calc Engine'!C36505 -> 1 | E62: ='Calc Engine'!C39780 -> 1 | F62: =CHOOSE(Assumptions!$C$10,C62,D62,E62) -> 1
A63: 1 | C63: ='Calc Engine'!C33885 -> 1 | D63: ='Calc Engine'!C37160 -> 1 | E63: ='Calc Engine'!C40435 -> 1 | F63: =CHOOSE(Assumptions!$C$10,C63,D63,E63) -> 1
A64: 2 | C64: ='Calc Engine'!C34540 -> 1 | D64: ='Calc Engine'!C37815 -> 1 | E64: ='Calc Engine'!C41090 -> 1 | F64: =CHOOSE(Assumptions!$C$10,C64,D64,E64) -> 1
A68: Table 7 — Recovery / exit value (% of face) vs MOIC
A69: Proceeds (% of face) | C69: Base Case | D69: Downside | E69: Severe Downside | F69: Selected
A70: =$A$20 -> 20 | C70: =(SUM('Calc Engine'!C644:I644)+Assumptions!$C$35*$A$70/100)/'Calc Engine'!C475 -> 0.47619048 | D70: =(SUM('Calc Engine'!C1299:I1299)+Assumptions!$C$35*$A$70/100)/'Calc Engine'!C1130 -> 0.41780891 | E70: =(SUM('Calc Engine'!C1954:I1954)+Assumptions!$C$35*$A$70/100)/'Calc Engine'!C1785 -> 0.44826886 | F70: =CHOOSE(Assumptions!$C$10,C70,D70,E70) -> 0.41780891
A71: =$A$21 -> 40 | C71: =(SUM('Calc Engine'!C644:I644)+Assumptions!$C$35*$A$71/100)/'Calc Engine'!C475 -> 0.67925678 | D71: =(SUM('Calc Engine'!C1299:I1299)+Assumptions!$C$35*$A$71/100)/'Calc Engine'!C1130 -> 0.62087522 | E71: =(SUM('Calc Engine'!C1954:I1954)+Assumptions!$C$35*$A$71/100)/'Calc Engine'!C1785 -> 0.65133516 | F71: =CHOOSE(Assumptions!$C$10,C71,D71,E71) -> 0.62087522
A72: =$A$22 -> 60 | C72: =(SUM('Calc Engine'!C644:I644)+Assumptions!$C$35*$A$72/100)/'Calc Engine'!C475 -> 0.88232308 | D72: =(SUM('Calc Engine'!C1299:I1299)+Assumptions!$C$35*$A$72/100)/'Calc Engine'!C1130 -> 0.82394152 | E72: =(SUM('Calc Engine'!C1954:I1954)+Assumptions!$C$35*$A$72/100)/'Calc Engine'!C1785 -> 0.85440146 | F72: =CHOOSE(Assumptions!$C$10,C72,D72,E72) -> 0.82394152
A73: =$A$23 -> 80 | C73: =(SUM('Calc Engine'!C644:I644)+Assumptions!$C$35*$A$73/100)/'Calc Engine'!C475 -> 1.0853894 | D73: =(SUM('Calc Engine'!C1299:I1299)+Assumptions!$C$35*$A$73/100)/'Calc Engine'!C1130 -> 1.0270078 | E73: =(SUM('Calc Engine'!C1954:I1954)+Assumptions!$C$35*$A$73/100)/'Calc Engine'!C1785 -> 1.0574678 | F73: =CHOOSE(Assumptions!$C$10,C73,D73,E73) -> 1.0270078
A74: =$A$24 -> 100 | C74: =(SUM('Calc Engine'!C644:I644)+Assumptions!$C$35*$A$74/100)/'Calc Engine'!C475 -> 1.2884557 | D74: =(SUM('Calc Engine'!C1299:I1299)+Assumptions!$C$35*$A$74/100)/'Calc Engine'!C1130 -> 1.2300741 | E74: =(SUM('Calc Engine'!C1954:I1954)+Assumptions!$C$35*$A$74/100)/'Calc Engine'!C1785 -> 1.2605341 | F74: =CHOOSE(Assumptions!$C$10,C74,D74,E74) -> 1.2300741
A82: Tables 3-6 re-run the operating model, debt schedule, default test and recovery waterfall for every point (Calc Engine cases 4-63).
A84: Supporting cash flows for Tables 1-2 (period 0 → 6) and resulting IRR
A85: Case | C85: t=0 | D85: t=1 | E85: t=2 | F85: t=3 | G85: t=4 | H85: t=5 | I85: t=6 | J85: IRR
A86: ="Base Case · price point 1" -> Base Case · price point 1 | C86: =-Assumptions!$C$35*$A$10/100*(1+Assumptions!$C$37) -> -90.45 | D86: ='Calc Engine'!D644+'Calc Engine'!D645 -> 9.15 | E86: ='Calc Engine'!E644+'Calc Engine'!E645 -> 9 | F86: ='Calc Engine'!F644+'Calc Engine'!F645 -> 108.75 | G86: ='Calc Engine'!G644+'Calc Engine'!G645 -> 0 | H86: ='Calc Engine'!H644+'Calc Engine'!H645 -> 0 | I86: ='Calc Engine'!I644+'Calc Engine'!I645 -> 0 | J86: =IF(SUM(D86:I86)<=0,-1,IFERROR(IRR(C86:I86,MAX(-0.9,(SUM(D86:I86)/-C86)^(1/Assumptions!$C$38)-1)),IRR(C86:I86,0.1))) -> 0.13029537
A87: ="Base Case · price point 2" -> Base Case · price point 2 | C87: =-Assumptions!$C$35*$A$11/100*(1+Assumptions!$C$37) -> -94.47 | D87: ='Calc Engine'!D644+'Calc Engine'!D645 -> 9.15 | E87: ='Calc Engine'!E644+'Calc Engine'!E645 -> 9 | F87: ='Calc Engine'!F644+'Calc Engine'!F645 -> 108.75 | G87: ='Calc Engine'!G644+'Calc Engine'!G645 -> 0 | H87: ='Calc Engine'!H644+'Calc Engine'!H645 -> 0 | I87: ='Calc Engine'!I644+'Calc Engine'!I645 -> 0 | J87: =IF(SUM(D87:I87)<=0,-1,IFERROR(IRR(C87:I87,MAX(-0.9,(SUM(D87:I87)/-C87)^(1/Assumptions!$C$38)-1)),IRR(C87:I87,0.1))) -> 0.11253737
A88: ="Base Case · price point 3" -> Base Case · price point 3 | C88: =-Assumptions!$C$35*$A$12/100*(1+Assumptions!$C$37) -> -98.49 | D88: ='Calc Engine'!D644+'Calc Engine'!D645 -> 9.15 | E88: ='Calc Engine'!E644+'Calc Engine'!E645 -> 9 | F88: ='Calc Engine'!F644+'Calc Engine'!F645 -> 108.75 | G88: ='Calc Engine'!G644+'Calc Engine'!G645 -> 0 | H88: ='Calc Engine'!H644+'Calc Engine'!H645 -> 0 | I88: ='Calc Engine'!I644+'Calc Engine'!I645 -> 0 | J88: =IF(SUM(D88:I88)<=0,-1,IFERROR(IRR(C88:I88,MAX(-0.9,(SUM(D88:I88)/-C88)^(1/Assumptions!$C$38)-1)),IRR(C88:I88,0.1))) -> 0.095815282
A89: ="Base Case · price point 4" -> Base Case · price point 4 | C89: =-Assumptions!$C$35*$A$13/100*(1+Assumptions!$C$37) -> -102.51 | D89: ='Calc Engine'!D644+'Calc Engine'!D645 -> 9.15 | E89: ='Calc Engine'!E644+'Calc Engine'!E645 -> 9 | F89: ='Calc Engine'!F644+'Calc Engine'!F645 -> 108.75 | G89: ='Calc Engine'!G644+'Calc Engine'!G645 -> 0 | H89: ='Calc Engine'!H644+'Calc Engine'!H645 -> 0 | I89: ='Calc Engine'!I644+'Calc Engine'!I645 -> 0 | J89: =IF(SUM(D89:I89)<=0,-1,IFERROR(IRR(C89:I89,MAX(-0.9,(SUM(D89:I89)/-C89)^(1/Assumptions!$C$38)-1)),IRR(C89:I89,0.1))) -> 0.080028741
A90: ="Base Case · price point 5" -> Base Case · price point 5 | C90: =-Assumptions!$C$35*$A$14/100*(1+Assumptions!$C$37) -> -106.53 | D90: ='Calc Engine'!D644+'Calc Engine'!D645 -> 9.15 | E90: ='Calc Engine'!E644+'Calc Engine'!E645 -> 9 | F90: ='Calc Engine'!F644+'Calc Engine'!F645 -> 108.75 | G90: ='Calc Engine'!G644+'Calc Engine'!G645 -> 0 | H90: ='Calc Engine'!H644+'Calc Engine'!H645 -> 0 | I90: ='Calc Engine'!I644+'Calc Engine'!I645 -> 0 | J90: =IF(SUM(D90:I90)<=0,-1,IFERROR(IRR(C90:I90,MAX(-0.9,(SUM(D90:I90)/-C90)^(1/Assumptions!$C$38)-1)),IRR(C90:I90,0.1))) -> 0.065090667
A91: ="Downside · price point 1" -> Downside · price point 1 | C91: =-Assumptions!$C$35*$A$10/100*(1+Assumptions!$C$37) -> -90.45 | D91: ='Calc Engine'!D1299+'Calc Engine'!D1300 -> 10.65 | E91: ='Calc Engine'!E1299+'Calc Engine'!E1300 -> 10.5 | F91: ='Calc Engine'!F1299+'Calc Engine'!F1300 -> 102.625 | G91: ='Calc Engine'!G1299+'Calc Engine'!G1300 -> 0 | H91: ='Calc Engine'!H1299+'Calc Engine'!H1300 -> 0 | I91: ='Calc Engine'!I1299+'Calc Engine'!I1300 -> 0 | J91: =IF(SUM(D91:I91)<=0,-1,IFERROR(IRR(C91:I91,MAX(-0.9,(SUM(D91:I91)/-C91)^(1/Assumptions!$C$38)-1)),IRR(C91:I91,0.1))) -> 0.1221803
A92: ="Downside · price point 2" -> Downside · price point 2 | C92: =-Assumptions!$C$35*$A$11/100*(1+Assumptions!$C$37) -> -94.47 | D92: ='Calc Engine'!D1299+'Calc Engine'!D1300 -> 10.65 | E92: ='Calc Engine'!E1299+'Calc Engine'!E1300 -> 10.5 | F92: ='Calc Engine'!F1299+'Calc Engine'!F1300 -> 102.625 | G92: ='Calc Engine'!G1299+'Calc Engine'!G1300 -> 0 | H92: ='Calc Engine'!H1299+'Calc Engine'!H1300 -> 0 | I92: ='Calc Engine'!I1299+'Calc Engine'!I1300 -> 0 | J92: =IF(SUM(D92:I92)<=0,-1,IFERROR(IRR(C92:I92,MAX(-0.9,(SUM(D92:I92)/-C92)^(1/Assumptions!$C$38)-1)),IRR(C92:I92,0.1))) -> 0.10426043
A93: ="Downside · price point 3" -> Downside · price point 3 | C93: =-Assumptions!$C$35*$A$12/100*(1+Assumptions!$C$37) -> -98.49 | D93: ='Calc Engine'!D1299+'Calc Engine'!D1300 -> 10.65 | E93: ='Calc Engine'!E1299+'Calc Engine'!E1300 -> 10.5 | F93: ='Calc Engine'!F1299+'Calc Engine'!F1300 -> 102.625 | G93: ='Calc Engine'!G1299+'Calc Engine'!G1300 -> 0 | H93: ='Calc Engine'!H1299+'Calc Engine'!H1300 -> 0 | I93: ='Calc Engine'!I1299+'Calc Engine'!I1300 -> 0 | J93: =IF(SUM(D93:I93)<=0,-1,IFERROR(IRR(C93:I93,MAX(-0.9,(SUM(D93:I93)/-C93)^(1/Assumptions!$C$38)-1)),IRR(C93:I93,0.1))) -> 0.087396249
A94: ="Downside · price point 4" -> Downside · price point 4 | C94: =-Assumptions!$C$35*$A$13/100*(1+Assumptions!$C$37) -> -102.51 | D94: ='Calc Engine'!D1299+'Calc Engine'!D1300 -> 10.65 | E94: ='Calc Engine'!E1299+'Calc Engine'!E1300 -> 10.5 | F94: ='Calc Engine'!F1299+'Calc Engine'!F1300 -> 102.625 | G94: ='Calc Engine'!G1299+'Calc Engine'!G1300 -> 0 | H94: ='Calc Engine'!H1299+'Calc Engine'!H1300 -> 0 | I94: ='Calc Engine'!I1299+'Calc Engine'!I1300 -> 0 | J94: =IF(SUM(D94:I94)<=0,-1,IFERROR(IRR(C94:I94,MAX(-0.9,(SUM(D94:I94)/-C94)^(1/Assumptions!$C$38)-1)),IRR(C94:I94,0.1))) -> 0.071484707
A95: ="Downside · price point 5" -> Downside · price point 5 | C95: =-Assumptions!$C$35*$A$14/100*(1+Assumptions!$C$37) -> -106.53 | D95: ='Calc Engine'!D1299+'Calc Engine'!D1300 -> 10.65 | E95: ='Calc Engine'!E1299+'Calc Engine'!E1300 -> 10.5 | F95: ='Calc Engine'!F1299+'Calc Engine'!F1300 -> 102.625 | G95: ='Calc Engine'!G1299+'Calc Engine'!G1300 -> 0 | H95: ='Calc Engine'!H1299+'Calc Engine'!H1300 -> 0 | I95: ='Calc Engine'!I1299+'Calc Engine'!I1300 -> 0 | J95: =IF(SUM(D95:I95)<=0,-1,IFERROR(IRR(C95:I95,MAX(-0.9,(SUM(D95:I95)/-C95)^(1/Assumptions!$C$38)-1)),IRR(C95:I95,0.1))) -> 0.056436476
A96: ="Severe Downside · price point 1" -> Severe Downside · price point 1 | C96: =-Assumptions!$C$35*$A$10/100*(1+Assumptions!$C$37) -> -90.45 | D96: ='Calc Engine'!D1954+'Calc Engine'!D1955 -> 12.15 | E96: ='Calc Engine'!E1954+'Calc Engine'!E1955 -> 12 | F96: ='Calc Engine'!F1954+'Calc Engine'!F1955 -> 103 | G96: ='Calc Engine'!G1954+'Calc Engine'!G1955 -> 0 | H96: ='Calc Engine'!H1954+'Calc Engine'!H1955 -> 0 | I96: ='Calc Engine'!I1954+'Calc Engine'!I1955 -> 0 | J96: =IF(SUM(D96:I96)<=0,-1,IFERROR(IRR(C96:I96,MAX(-0.9,(SUM(D96:I96)/-C96)^(1/Assumptions!$C$38)-1)),IRR(C96:I96,0.1))) -> 0.13507029
A97: ="Severe Downside · price point 2" -> Severe Downside · price point 2 | C97: =-Assumptions!$C$35*$A$11/100*(1+Assumptions!$C$37) -> -94.47 | D97: ='Calc Engine'!D1954+'Calc Engine'!D1955 -> 12.15 | E97: ='Calc Engine'!E1954+'Calc Engine'!E1955 -> 12 | F97: ='Calc Engine'!F1954+'Calc Engine'!F1955 -> 103 | G97: ='Calc Engine'!G1954+'Calc Engine'!G1955 -> 0 | H97: ='Calc Engine'!H1954+'Calc Engine'!H1955 -> 0 | I97: ='Calc Engine'!I1954+'Calc Engine'!I1955 -> 0 | J97: =IF(SUM(D97:I97)<=0,-1,IFERROR(IRR(C97:I97,MAX(-0.9,(SUM(D97:I97)/-C97)^(1/Assumptions!$C$38)-1)),IRR(C97:I97,0.1))) -> 0.11669319
A98: ="Severe Downside · price point 3" -> Severe Downside · price point 3 | C98: =-Assumptions!$C$35*$A$12/100*(1+Assumptions!$C$37) -> -98.49 | D98: ='Calc Engine'!D1954+'Calc Engine'!D1955 -> 12.15 | E98: ='Calc Engine'!E1954+'Calc Engine'!E1955 -> 12 | F98: ='Calc Engine'!F1954+'Calc Engine'!F1955 -> 103 | G98: ='Calc Engine'!G1954+'Calc Engine'!G1955 -> 0 | H98: ='Calc Engine'!H1954+'Calc Engine'!H1955 -> 0 | I98: ='Calc Engine'!I1954+'Calc Engine'!I1955 -> 0 | J98: =IF(SUM(D98:I98)<=0,-1,IFERROR(IRR(C98:I98,MAX(-0.9,(SUM(D98:I98)/-C98)^(1/Assumptions!$C$38)-1)),IRR(C98:I98,0.1))) -> 0.099407759
A99: ="Severe Downside · price point 4" -> Severe Downside · price point 4 | C99: =-Assumptions!$C$35*$A$13/100*(1+Assumptions!$C$37) -> -102.51 | D99: ='Calc Engine'!D1954+'Calc Engine'!D1955 -> 12.15 | E99: ='Calc Engine'!E1954+'Calc Engine'!E1955 -> 12 | F99: ='Calc Engine'!F1954+'Calc Engine'!F1955 -> 103 | G99: ='Calc Engine'!G1954+'Calc Engine'!G1955 -> 0 | H99: ='Calc Engine'!H1954+'Calc Engine'!H1955 -> 0 | I99: ='Calc Engine'!I1954+'Calc Engine'!I1955 -> 0 | J99: =IF(SUM(D99:I99)<=0,-1,IFERROR(IRR(C99:I99,MAX(-0.9,(SUM(D99:I99)/-C99)^(1/Assumptions!$C$38)-1)),IRR(C99:I99,0.1))) -> 0.083106767
A100: ="Severe Downside · price point 5" -> Severe Downside · price point 5 | C100: =-Assumptions!$C$35*$A$14/100*(1+Assumptions!$C$37) -> -106.53 | D100: ='Calc Engine'!D1954+'Calc Engine'!D1955 -> 12.15 | E100: ='Calc Engine'!E1954+'Calc Engine'!E1955 -> 12 | F100: ='Calc Engine'!F1954+'Calc Engine'!F1955 -> 103 | G100: ='Calc Engine'!G1954+'Calc Engine'!G1955 -> 0 | H100: ='Calc Engine'!H1954+'Calc Engine'!H1955 -> 0 | I100: ='Calc Engine'!I1954+'Calc Engine'!I1955 -> 0 | J100: =IF(SUM(D100:I100)<=0,-1,IFERROR(IRR(C100:I100,MAX(-0.9,(SUM(D100:I100)/-C100)^(1/Assumptions!$C$38)-1)),IRR(C100:I100,0.1))) -> 0.06769732
A101: ="Base Case · rec point 1" -> Base Case · rec point 1 | C101: ='Calc Engine'!C646 -> -98.49 | D101: ='Calc Engine'!D644+IF('Calc Engine'!D642='Calc Engine'!C640,Assumptions!$C$35*$A$20/100,0) -> 9.15 | E101: ='Calc Engine'!E644+IF('Calc Engine'!E642='Calc Engine'!C640,Assumptions!$C$35*$A$20/100,0) -> 9 | F101: ='Calc Engine'!F644+IF('Calc Engine'!F642='Calc Engine'!C640,Assumptions!$C$35*$A$20/100,0) -> 28.75 | G101: ='Calc Engine'!G644+IF('Calc Engine'!G642='Calc Engine'!C640,Assumptions!$C$35*$A$20/100,0) -> 0 | H101: ='Calc Engine'!H644+IF('Calc Engine'!H642='Calc Engine'!C640,Assumptions!$C$35*$A$20/100,0) -> 0 | I101: ='Calc Engine'!I644+IF('Calc Engine'!I642='Calc Engine'!C640,Assumptions!$C$35*$A$20/100,0) -> 0 | J101: =IF(SUM(D101:I101)<=0,-1,IFERROR(IRR(C101:I101,MAX(-0.9,(SUM(D101:I101)/-C101)^(1/Assumptions!$C$38)-1)),IRR(C101:I101,0.1))) -> -0.25635751
A102: ="Base Case · rec point 2" -> Base Case · rec point 2 | C102: ='Calc Engine'!C646 -> -98.49 | D102: ='Calc Engine'!D644+IF('Calc Engine'!D642='Calc Engine'!C640,Assumptions!$C$35*$A$21/100,0) -> 9.15 | E102: ='Calc Engine'!E644+IF('Calc Engine'!E642='Calc Engine'!C640,Assumptions!$C$35*$A$21/100,0) -> 9 | F102: ='Calc Engine'!F644+IF('Calc Engine'!F642='Calc Engine'!C640,Assumptions!$C$35*$A$21/100,0) -> 48.75 | G102: ='Calc Engine'!G644+IF('Calc Engine'!G642='Calc Engine'!C640,Assumptions!$C$35*$A$21/100,0) -> 0 | H102: ='Calc Engine'!H644+IF('Calc Engine'!H642='Calc Engine'!C640,Assumptions!$C$35*$A$21/100,0) -> 0 | I102: ='Calc Engine'!I644+IF('Calc Engine'!I642='Calc Engine'!C640,Assumptions!$C$35*$A$21/100,0) -> 0 | J102: =IF(SUM(D102:I102)<=0,-1,IFERROR(IRR(C102:I102,MAX(-0.9,(SUM(D102:I102)/-C102)^(1/Assumptions!$C$38)-1)),IRR(C102:I102,0.1))) -> -0.13685355
A103: ="Base Case · rec point 3" -> Base Case · rec point 3 | C103: ='Calc Engine'!C646 -> -98.49 | D103: ='Calc Engine'!D644+IF('Calc Engine'!D642='Calc Engine'!C640,Assumptions!$C$35*$A$22/100,0) -> 9.15 | E103: ='Calc Engine'!E644+IF('Calc Engine'!E642='Calc Engine'!C640,Assumptions!$C$35*$A$22/100,0) -> 9 | F103: ='Calc Engine'!F644+IF('Calc Engine'!F642='Calc Engine'!C640,Assumptions!$C$35*$A$22/100,0) -> 68.75 | G103: ='Calc Engine'!G644+IF('Calc Engine'!G642='Calc Engine'!C640,Assumptions!$C$35*$A$22/100,0) -> 0 | H103: ='Calc Engine'!H644+IF('Calc Engine'!H642='Calc Engine'!C640,Assumptions!$C$35*$A$22/100,0) -> 0 | I103: ='Calc Engine'!I644+IF('Calc Engine'!I642='Calc Engine'!C640,Assumptions!$C$35*$A$22/100,0) -> 0 | J103: =IF(SUM(D103:I103)<=0,-1,IFERROR(IRR(C103:I103,MAX(-0.9,(SUM(D103:I103)/-C103)^(1/Assumptions!$C$38)-1)),IRR(C103:I103,0.1))) -> -0.045383594
A104: ="Base Case · rec point 4" -> Base Case · rec point 4 | C104: ='Calc Engine'!C646 -> -98.49 | D104: ='Calc Engine'!D644+IF('Calc Engine'!D642='Calc Engine'!C640,Assumptions!$C$35*$A$23/100,0) -> 9.15 | E104: ='Calc Engine'!E644+IF('Calc Engine'!E642='Calc Engine'!C640,Assumptions!$C$35*$A$23/100,0) -> 9 | F104: ='Calc Engine'!F644+IF('Calc Engine'!F642='Calc Engine'!C640,Assumptions!$C$35*$A$23/100,0) -> 88.75 | G104: ='Calc Engine'!G644+IF('Calc Engine'!G642='Calc Engine'!C640,Assumptions!$C$35*$A$23/100,0) -> 0 | H104: ='Calc Engine'!H644+IF('Calc Engine'!H642='Calc Engine'!C640,Assumptions!$C$35*$A$23/100,0) -> 0 | I104: ='Calc Engine'!I644+IF('Calc Engine'!I642='Calc Engine'!C640,Assumptions!$C$35*$A$23/100,0) -> 0 | J104: =IF(SUM(D104:I104)<=0,-1,IFERROR(IRR(C104:I104,MAX(-0.9,(SUM(D104:I104)/-C104)^(1/Assumptions!$C$38)-1)),IRR(C104:I104,0.1))) -> 0.030365923
A105: ="Base Case · rec point 5" -> Base Case · rec point 5 | C105: ='Calc Engine'!C646 -> -98.49 | D105: ='Calc Engine'!D644+IF('Calc Engine'!D642='Calc Engine'!C640,Assumptions!$C$35*$A$24/100,0) -> 9.15 | E105: ='Calc Engine'!E644+IF('Calc Engine'!E642='Calc Engine'!C640,Assumptions!$C$35*$A$24/100,0) -> 9 | F105: ='Calc Engine'!F644+IF('Calc Engine'!F642='Calc Engine'!C640,Assumptions!$C$35*$A$24/100,0) -> 108.75 | G105: ='Calc Engine'!G644+IF('Calc Engine'!G642='Calc Engine'!C640,Assumptions!$C$35*$A$24/100,0) -> 0 | H105: ='Calc Engine'!H644+IF('Calc Engine'!H642='Calc Engine'!C640,Assumptions!$C$35*$A$24/100,0) -> 0 | I105: ='Calc Engine'!I644+IF('Calc Engine'!I642='Calc Engine'!C640,Assumptions!$C$35*$A$24/100,0) -> 0 | J105: =IF(SUM(D105:I105)<=0,-1,IFERROR(IRR(C105:I105,MAX(-0.9,(SUM(D105:I105)/-C105)^(1/Assumptions!$C$38)-1)),IRR(C105:I105,0.1))) -> 0.095815282
A106: ="Downside · rec point 1" -> Downside · rec point 1 | C106: ='Calc Engine'!C1301 -> -98.49 | D106: ='Calc Engine'!D1299+IF('Calc Engine'!D1297='Calc Engine'!C1295,Assumptions!$C$35*$A$20/100,0) -> 10.65 | E106: ='Calc Engine'!E1299+IF('Calc Engine'!E1297='Calc Engine'!C1295,Assumptions!$C$35*$A$20/100,0) -> 10.5 | F106: ='Calc Engine'!F1299+IF('Calc Engine'!F1297='Calc Engine'!C1295,Assumptions!$C$35*$A$20/100,0) -> 20 | G106: ='Calc Engine'!G1299+IF('Calc Engine'!G1297='Calc Engine'!C1295,Assumptions!$C$35*$A$20/100,0) -> 0 | H106: ='Calc Engine'!H1299+IF('Calc Engine'!H1297='Calc Engine'!C1295,Assumptions!$C$35*$A$20/100,0) -> 0 | I106: ='Calc Engine'!I1299+IF('Calc Engine'!I1297='Calc Engine'!C1295,Assumptions!$C$35*$A$20/100,0) -> 0 | J106: =IF(SUM(D106:I106)<=0,-1,IFERROR(IRR(C106:I106,MAX(-0.9,(SUM(D106:I106)/-C106)^(1/Assumptions!$C$38)-1)),IRR(C106:I106,0.1))) -> -0.31034127
A107: ="Downside · rec point 2" -> Downside · rec point 2 | C107: ='Calc Engine'!C1301 -> -98.49 | D107: ='Calc Engine'!D1299+IF('Calc Engine'!D1297='Calc Engine'!C1295,Assumptions!$C$35*$A$21/100,0) -> 10.65 | E107: ='Calc Engine'!E1299+IF('Calc Engine'!E1297='Calc Engine'!C1295,Assumptions!$C$35*$A$21/100,0) -> 10.5 | F107: ='Calc Engine'!F1299+IF('Calc Engine'!F1297='Calc Engine'!C1295,Assumptions!$C$35*$A$21/100,0) -> 40 | G107: ='Calc Engine'!G1299+IF('Calc Engine'!G1297='Calc Engine'!C1295,Assumptions!$C$35*$A$21/100,0) -> 0 | H107: ='Calc Engine'!H1299+IF('Calc Engine'!H1297='Calc Engine'!C1295,Assumptions!$C$35*$A$21/100,0) -> 0 | I107: ='Calc Engine'!I1299+IF('Calc Engine'!I1297='Calc Engine'!C1295,Assumptions!$C$35*$A$21/100,0) -> 0 | J107: =IF(SUM(D107:I107)<=0,-1,IFERROR(IRR(C107:I107,MAX(-0.9,(SUM(D107:I107)/-C107)^(1/Assumptions!$C$38)-1)),IRR(C107:I107,0.1))) -> -0.17150566
A108: ="Downside · rec point 3" -> Downside · rec point 3 | C108: ='Calc Engine'!C1301 -> -98.49 | D108: ='Calc Engine'!D1299+IF('Calc Engine'!D1297='Calc Engine'!C1295,Assumptions!$C$35*$A$22/100,0) -> 10.65 | E108: ='Calc Engine'!E1299+IF('Calc Engine'!E1297='Calc Engine'!C1295,Assumptions!$C$35*$A$22/100,0) -> 10.5 | F108: ='Calc Engine'!F1299+IF('Calc Engine'!F1297='Calc Engine'!C1295,Assumptions!$C$35*$A$22/100,0) -> 60 | G108: ='Calc Engine'!G1299+IF('Calc Engine'!G1297='Calc Engine'!C1295,Assumptions!$C$35*$A$22/100,0) -> 0 | H108: ='Calc Engine'!H1299+IF('Calc Engine'!H1297='Calc Engine'!C1295,Assumptions!$C$35*$A$22/100,0) -> 0 | I108: ='Calc Engine'!I1299+IF('Calc Engine'!I1297='Calc Engine'!C1295,Assumptions!$C$35*$A$22/100,0) -> 0 | J108: =IF(SUM(D108:I108)<=0,-1,IFERROR(IRR(C108:I108,MAX(-0.9,(SUM(D108:I108)/-C108)^(1/Assumptions!$C$38)-1)),IRR(C108:I108,0.1))) -> -0.071088819
A109: ="Downside · rec point 4" -> Downside · rec point 4 | C109: ='Calc Engine'!C1301 -> -98.49 | D109: ='Calc Engine'!D1299+IF('Calc Engine'!D1297='Calc Engine'!C1295,Assumptions!$C$35*$A$23/100,0) -> 10.65 | E109: ='Calc Engine'!E1299+IF('Calc Engine'!E1297='Calc Engine'!C1295,Assumptions!$C$35*$A$23/100,0) -> 10.5 | F109: ='Calc Engine'!F1299+IF('Calc Engine'!F1297='Calc Engine'!C1295,Assumptions!$C$35*$A$23/100,0) -> 80 | G109: ='Calc Engine'!G1299+IF('Calc Engine'!G1297='Calc Engine'!C1295,Assumptions!$C$35*$A$23/100,0) -> 0 | H109: ='Calc Engine'!H1299+IF('Calc Engine'!H1297='Calc Engine'!C1295,Assumptions!$C$35*$A$23/100,0) -> 0 | I109: ='Calc Engine'!I1299+IF('Calc Engine'!I1297='Calc Engine'!C1295,Assumptions!$C$35*$A$23/100,0) -> 0 | J109: =IF(SUM(D109:I109)<=0,-1,IFERROR(IRR(C109:I109,MAX(-0.9,(SUM(D109:I109)/-C109)^(1/Assumptions!$C$38)-1)),IRR(C109:I109,0.1))) -> 0.0099803984
A110: ="Downside · rec point 5" -> Downside · rec point 5 | C110: ='Calc Engine'!C1301 -> -98.49 | D110: ='Calc Engine'!D1299+IF('Calc Engine'!D1297='Calc Engine'!C1295,Assumptions!$C$35*$A$24/100,0) -> 10.65 | E110: ='Calc Engine'!E1299+IF('Calc Engine'!E1297='Calc Engine'!C1295,Assumptions!$C$35*$A$24/100,0) -> 10.5 | F110: ='Calc Engine'!F1299+IF('Calc Engine'!F1297='Calc Engine'!C1295,Assumptions!$C$35*$A$24/100,0) -> 100 | G110: ='Calc Engine'!G1299+IF('Calc Engine'!G1297='Calc Engine'!C1295,Assumptions!$C$35*$A$24/100,0) -> 0 | H110: ='Calc Engine'!H1299+IF('Calc Engine'!H1297='Calc Engine'!C1295,Assumptions!$C$35*$A$24/100,0) -> 0 | I110: ='Calc Engine'!I1299+IF('Calc Engine'!I1297='Calc Engine'!C1295,Assumptions!$C$35*$A$24/100,0) -> 0 | J110: =IF(SUM(D110:I110)<=0,-1,IFERROR(IRR(C110:I110,MAX(-0.9,(SUM(D110:I110)/-C110)^(1/Assumptions!$C$38)-1)),IRR(C110:I110,0.1))) -> 0.079012717
A111: ="Severe Downside · rec point 1" -> Severe Downside · rec point 1 | C111: ='Calc Engine'!C1956 -> -98.49 | D111: ='Calc Engine'!D1954+IF('Calc Engine'!D1952='Calc Engine'!C1950,Assumptions!$C$35*$A$20/100,0) -> 12.15 | E111: ='Calc Engine'!E1954+IF('Calc Engine'!E1952='Calc Engine'!C1950,Assumptions!$C$35*$A$20/100,0) -> 12 | F111: ='Calc Engine'!F1954+IF('Calc Engine'!F1952='Calc Engine'!C1950,Assumptions!$C$35*$A$20/100,0) -> 20 | G111: ='Calc Engine'!G1954+IF('Calc Engine'!G1952='Calc Engine'!C1950,Assumptions!$C$35*$A$20/100,0) -> 0 | H111: ='Calc Engine'!H1954+IF('Calc Engine'!H1952='Calc Engine'!C1950,Assumptions!$C$35*$A$20/100,0) -> 0 | I111: ='Calc Engine'!I1954+IF('Calc Engine'!I1952='Calc Engine'!C1950,Assumptions!$C$35*$A$20/100,0) -> 0 | J111: =IF(SUM(D111:I111)<=0,-1,IFERROR(IRR(C111:I111,MAX(-0.9,(SUM(D111:I111)/-C111)^(1/Assumptions!$C$38)-1)),IRR(C111:I111,0.1))) -> -0.29510451
A112: ="Severe Downside · rec point 2" -> Severe Downside · rec point 2 | C112: ='Calc Engine'!C1956 -> -98.49 | D112: ='Calc Engine'!D1954+IF('Calc Engine'!D1952='Calc Engine'!C1950,Assumptions!$C$35*$A$21/100,0) -> 12.15 | E112: ='Calc Engine'!E1954+IF('Calc Engine'!E1952='Calc Engine'!C1950,Assumptions!$C$35*$A$21/100,0) -> 12 | F112: ='Calc Engine'!F1954+IF('Calc Engine'!F1952='Calc Engine'!C1950,Assumptions!$C$35*$A$21/100,0) -> 40 | G112: ='Calc Engine'!G1954+IF('Calc Engine'!G1952='Calc Engine'!C1950,Assumptions!$C$35*$A$21/100,0) -> 0 | H112: ='Calc Engine'!H1954+IF('Calc Engine'!H1952='Calc Engine'!C1950,Assumptions!$C$35*$A$21/100,0) -> 0 | I112: ='Calc Engine'!I1954+IF('Calc Engine'!I1952='Calc Engine'!C1950,Assumptions!$C$35*$A$21/100,0) -> 0 | J112: =IF(SUM(D112:I112)<=0,-1,IFERROR(IRR(C112:I112,MAX(-0.9,(SUM(D112:I112)/-C112)^(1/Assumptions!$C$38)-1)),IRR(C112:I112,0.1))) -> -0.15842656
A113: ="Severe Downside · rec point 3" -> Severe Downside · rec point 3 | C113: ='Calc Engine'!C1956 -> -98.49 | D113: ='Calc Engine'!D1954+IF('Calc Engine'!D1952='Calc Engine'!C1950,Assumptions!$C$35*$A$22/100,0) -> 12.15 | E113: ='Calc Engine'!E1954+IF('Calc Engine'!E1952='Calc Engine'!C1950,Assumptions!$C$35*$A$22/100,0) -> 12 | F113: ='Calc Engine'!F1954+IF('Calc Engine'!F1952='Calc Engine'!C1950,Assumptions!$C$35*$A$22/100,0) -> 60 | G113: ='Calc Engine'!G1954+IF('Calc Engine'!G1952='Calc Engine'!C1950,Assumptions!$C$35*$A$22/100,0) -> 0 | H113: ='Calc Engine'!H1954+IF('Calc Engine'!H1952='Calc Engine'!C1950,Assumptions!$C$35*$A$22/100,0) -> 0 | I113: ='Calc Engine'!I1954+IF('Calc Engine'!I1952='Calc Engine'!C1950,Assumptions!$C$35*$A$22/100,0) -> 0 | J113: =IF(SUM(D113:I113)<=0,-1,IFERROR(IRR(C113:I113,MAX(-0.9,(SUM(D113:I113)/-C113)^(1/Assumptions!$C$38)-1)),IRR(C113:I113,0.1))) -> -0.05906606
A114: ="Severe Downside · rec point 4" -> Severe Downside · rec point 4 | C114: ='Calc Engine'!C1956 -> -98.49 | D114: ='Calc Engine'!D1954+IF('Calc Engine'!D1952='Calc Engine'!C1950,Assumptions!$C$35*$A$23/100,0) -> 12.15 | E114: ='Calc Engine'!E1954+IF('Calc Engine'!E1952='Calc Engine'!C1950,Assumptions!$C$35*$A$23/100,0) -> 12 | F114: ='Calc Engine'!F1954+IF('Calc Engine'!F1952='Calc Engine'!C1950,Assumptions!$C$35*$A$23/100,0) -> 80 | G114: ='Calc Engine'!G1954+IF('Calc Engine'!G1952='Calc Engine'!C1950,Assumptions!$C$35*$A$23/100,0) -> 0 | H114: ='Calc Engine'!H1954+IF('Calc Engine'!H1952='Calc Engine'!C1950,Assumptions!$C$35*$A$23/100,0) -> 0 | I114: ='Calc Engine'!I1954+IF('Calc Engine'!I1952='Calc Engine'!C1950,Assumptions!$C$35*$A$23/100,0) -> 0 | J114: =IF(SUM(D114:I114)<=0,-1,IFERROR(IRR(C114:I114,MAX(-0.9,(SUM(D114:I114)/-C114)^(1/Assumptions!$C$38)-1)),IRR(C114:I114,0.1))) -> 0.02133754
A115: ="Severe Downside · rec point 5" -> Severe Downside · rec point 5 | C115: ='Calc Engine'!C1956 -> -98.49 | D115: ='Calc Engine'!D1954+IF('Calc Engine'!D1952='Calc Engine'!C1950,Assumptions!$C$35*$A$24/100,0) -> 12.15 | E115: ='Calc Engine'!E1954+IF('Calc Engine'!E1952='Calc Engine'!C1950,Assumptions!$C$35*$A$24/100,0) -> 12 | F115: ='Calc Engine'!F1954+IF('Calc Engine'!F1952='Calc Engine'!C1950,Assumptions!$C$35*$A$24/100,0) -> 100 | G115: ='Calc Engine'!G1954+IF('Calc Engine'!G1952='Calc Engine'!C1950,Assumptions!$C$35*$A$24/100,0) -> 0 | H115: ='Calc Engine'!H1954+IF('Calc Engine'!H1952='Calc Engine'!C1950,Assumptions!$C$35*$A$24/100,0) -> 0 | I115: ='Calc Engine'!I1954+IF('Calc Engine'!I1952='Calc Engine'!C1950,Assumptions!$C$35*$A$24/100,0) -> 0 | J115: =IF(SUM(D115:I115)<=0,-1,IFERROR(IRR(C115:I115,MAX(-0.9,(SUM(D115:I115)/-C115)^(1/Assumptions!$C$38)-1)),IRR(C115:I115,0.1))) -> 0.089897638
A119: Collateral coverage stress — recovery of the target tranche from its pledged pool (asset-based floor; ignores going-concern value, cash and deficiency recovery)
A120: Recovery = MIN(100%, pool share × asset value × (1 − realization cost) × (1 − admin costs) ÷ claim). Claim = target-tranche principal at close. Pool share is an analyst assumption, not a verified allocation.
A122: Pool share of asset value pledged to the target tranche (assumption) | C122: =CHOOSE(Assumptions!$C$34,Assumptions!$Q$57,Assumptions!$Q$58,Assumptions!$Q$59,Assumptions!$Q$60,Assumptions!$Q$61,Assumptions!$Q$62,Assumptions!$Q$63,Assumptions!$Q$64,Assumptions!$Q$65,Assumptions!$Q$66) -> 0.3
A123: Claim: target-tranche principal at close ($M) | C123: =CHOOSE(Assumptions!$C$34,Assumptions!$C$57,Assumptions!$C$58,Assumptions!$C$59,Assumptions!$C$60,Assumptions!$C$61,Assumptions!$C$62,Assumptions!$C$63,Assumptions!$C$64,Assumptions!$C$65,Assumptions!$C$66) -> 400
A124: Administrative / DIP costs | C124: =Assumptions!$C$15 -> 0.04
A125: Liquidation recovery factor (Severe scenario) | C125: =Assumptions!$C$132 -> 0.85
A126: LTM NOI ($M) | C126: ='Historical Financials'!G27 -> 301.511
A127: Analyst cap rate (base) | C127: =Assumptions!$C$26 -> 0.075
A128: Total asset base ($M) | C128: =Assumptions!$C$31 -> 4517.7007
A129: Non-operating asset components, book ($M) | C129: =Assumptions!$C$31-Assumptions!C27 -> 497.554
A131: Table C1 — recovery % vs cap rate (rows) and NOI change (columns), pledged pool at the stated share
A132: Cap rate | C132: 0 | D132: -0.1 | E132: -0.2 | F132: -0.3 | G132: -0.4 | H132: -0.5
A133: 0.065 | C133: =IF($C$123<=0,1,MIN(1,$C$122*($C$126*(1+C$132)/$A133+$C$129)*$C$125*(1-$C$124)/($C$123))) -> 1 | D133: =IF($C$123<=0,1,MIN(1,$C$122*($C$126*(1+D$132)/$A133+$C$129)*$C$125*(1-$C$124)/($C$123))) -> 1 | E133: =IF($C$123<=0,1,MIN(1,$C$122*($C$126*(1+E$132)/$A133+$C$129)*$C$125*(1-$C$124)/($C$123))) -> 1 | F133: =IF($C$123<=0,1,MIN(1,$C$122*($C$126*(1+F$132)/$A133+$C$129)*$C$125*(1-$C$124)/($C$123))) -> 1 | G133: =IF($C$123<=0,1,MIN(1,$C$122*($C$126*(1+G$132)/$A133+$C$129)*$C$125*(1-$C$124)/($C$123))) -> 1 | H133: =IF($C$123<=0,1,MIN(1,$C$122*($C$126*(1+H$132)/$A133+$C$129)*$C$125*(1-$C$124)/($C$123))) -> 1
A134: 0.075 | C134: =IF($C$123<=0,1,MIN(1,$C$122*($C$126*(1+C$132)/$A134+$C$129)*$C$125*(1-$C$124)/($C$123))) -> 1 | D134: =IF($C$123<=0,1,MIN(1,$C$122*($C$126*(1+D$132)/$A134+$C$129)*$C$125*(1-$C$124)/($C$123))) -> 1 | E134: =IF($C$123<=0,1,MIN(1,$C$122*($C$126*(1+E$132)/$A134+$C$129)*$C$125*(1-$C$124)/($C$123))) -> 1 | F134: =IF($C$123<=0,1,MIN(1,$C$122*($C$126*(1+F$132)/$A134+$C$129)*$C$125*(1-$C$124)/($C$123))) -> 1 | G134: =IF($C$123<=0,1,MIN(1,$C$122*($C$126*(1+G$132)/$A134+$C$129)*$C$125*(1-$C$124)/($C$123))) -> 1 | H134: =IF($C$123<=0,1,MIN(1,$C$122*($C$126*(1+H$132)/$A134+$C$129)*$C$125*(1-$C$124)/($C$123))) -> 1
A135: 0.09 | C135: =IF($C$123<=0,1,MIN(1,$C$122*($C$126*(1+C$132)/$A135+$C$129)*$C$125*(1-$C$124)/($C$123))) -> 1 | D135: =IF($C$123<=0,1,MIN(1,$C$122*($C$126*(1+D$132)/$A135+$C$129)*$C$125*(1-$C$124)/($C$123))) -> 1 | E135: =IF($C$123<=0,1,MIN(1,$C$122*($C$126*(1+E$132)/$A135+$C$129)*$C$125*(1-$C$124)/($C$123))) -> 1 | F135: =IF($C$123<=0,1,MIN(1,$C$122*($C$126*(1+F$132)/$A135+$C$129)*$C$125*(1-$C$124)/($C$123))) -> 1 | G135: =IF($C$123<=0,1,MIN(1,$C$122*($C$126*(1+G$132)/$A135+$C$129)*$C$125*(1-$C$124)/($C$123))) -> 1 | H135: =IF($C$123<=0,1,MIN(1,$C$122*($C$126*(1+H$132)/$A135+$C$129)*$C$125*(1-$C$124)/($C$123))) -> 1
...

Sheet Investment Summary
A1: Investment Summary — every figure is a live link to the model
A2: =Assumptions!$C$5&" | PUBLIC DATA CASE | HYPOTHETICAL INVESTMENT TERMS | Active scenario: "&Assumptions!$D$10 -> Brandywine Realty Trust | PUBLIC DATA CASE | HYPOTHETICAL INVESTMENT TERMS | Active scenario: Downside
A4: Investment recommendation | C4: ='Investment Summary'!$C$41 -> HOLD
A5: Instrument | C5: =CHOOSE(Assumptions!$C$34,Assumptions!$A$57,Assumptions!$A$58,Assumptions!$A$59,Assumptions!$A$60,Assumptions!$A$61,Assumptions!$A$62,Assumptions!$A$63,Assumptions!$A$64,Assumptions!$A$65,Assumptions!$A$66)&" @ "&TEXT(Assumptions!$C$36,"0.0") -> Hypothetical Senior Secured Term Loan (S+525, 1% floor) @ 98.0
A6: Face value / purchase price / cash investment ($M) | C6: =TEXT(Assumptions!$C$35,"0.0")&" / "&TEXT(Assumptions!$C$36,"0.0")&" / "&TEXT(Returns!C10,"0.0") -> 100.0 / 98.0 / 98.5
A7: Credit score (0-100) | C7: ='Credit Metrics'!$G$77 -> 45.749764
A8: Risk band | C8: ='Credit Metrics'!$G$78 -> Elevated
A9: Base-case IRR | C9: =Scenarios!C27 -> 0.095815282
A10: Downside IRR | C10: =Scenarios!D27 -> 0.087396249
A11: Severe downside IRR | C11: =Scenarios!E27 -> 0.099407759
A12: Base / Downside / Severe MOIC | C12: =TEXT(Scenarios!C28,"0.00x")&" / "&TEXT(Scenarios!D28,"0.00x")&" / "&TEXT(Scenarios!E28,"0.00x") -> 1.29x / 1.26x / 1.29x
A13: Probability-weighted IRR | C13: =Scenarios!$C$31 -> 0.09343237
A14: Probability-weighted MOIC | C14: =Scenarios!$C$33 -> 1.2777312
A15: Probability of payment default | C15: =Scenarios!$C$34 -> 0.5
A16: Target-tranche recovery — Downside (valuation waterfall) | C16: =Scenarios!D25 -> 1
A17: Target-tranche recovery — Severe (valuation waterfall) | C17: =Scenarios!E25 -> 1
A18: Recovery (selected scenario, from Recovery tab) | C18: =Returns!C15 -> 1
A19: Net leverage — base period (LTM Jun-26) | C19: ='Credit Metrics'!F11 -> 9.7781976
A20: Interest coverage — base period | C20: ='Credit Metrics'!F12 -> 1.7233258
A21: Net leverage — LTM Jun-27E (selected scenario) | C21: ='Credit Metrics'!G11 -> 10.670457
A22: Interest coverage — LTM Jun-27E (selected scenario) | C22: ='Credit Metrics'!G12 -> 1.2497904
A23: Liquidity — LTM Jun-27E (selected scenario, $M) | C23: ='Credit Metrics'!G16 -> 697.44742
A24: Covenant breaches (selected scenario, count of failed tests) | C24: ='Credit Metrics'!C62 -> 15
A25: Maturity alert | C25: ='Capital Structure'!$C$37 -> ALERT: 30% of debt ($800M) due within 2 period(s); liquidity covers 77%
A26: Maturity concentration | C26: ='Capital Structure'!$C$35 -> CONCENTRATED: 30% of debt in LTM Jun-28E (period ending 2028)
A27: Recommendation evidence (thresholds on Assumptions §3)
A28: Test | C28: Actual | D28: Required | E28: Result | F28: Core?
A29: Base-case IRR clears hurdle | C29: =Scenarios!C27 -> 0.095815282 | D29: =Assumptions!$C$41 -> 0.1 | E29: =IF(C29>=D29,"PASS","FAIL") -> FAIL | F29: core
A30: Probability-weighted IRR clears hurdle | C30: =Scenarios!$C$31 -> 0.09343237 | D30: =Assumptions!$C$41 -> 0.1 | E30: =IF(C30>=D30,"PASS","FAIL") -> FAIL | F30: core
A31: Downside IRR stays above floor | C31: =Scenarios!D27 -> 0.087396249 | D31: =Assumptions!$C$42 -> 0 | E31: =IF(C31>=D31,"PASS","FAIL") -> PASS | F31: core
A32: Downside recovery meets minimum (valuation waterfall) | C32: =Scenarios!D25 -> 1 | D32: =Assumptions!$C$45 -> 0.9 | E32: =IF(C32>=D32,"PASS","FAIL") -> PASS | F32: core
A33: Base-case refinancing succeeds (failures = 0) | C33: =Scenarios!C21 -> 0 | D33: =0 -> 0 | E33: =IF(C33<=D33,"PASS","FAIL") -> PASS | F33: core
A34: Yield to maturity meets minimum | C34: =IFERROR(RATE(YEARFRAC(Assumptions!$C$8,CHOOSE(Assumptions!$C$34,Assumptions!$J$57,Assumptions!$J$58,Assumptions!$J$59,Assumptions!$J$60,Assumptions!$J$61,Assumptions!$J$62,Assumptions!$J$63,Assumptions!$J$64,Assumptions!$J$65,Assumptions!$J$66)),'Calc Engine'!D643*100,-Assumptions!$C$36,100),0) -> 0.096731975 | D34: =Assumptions!$C$43 -> 0.085 | E34: =IF(C34>=D34,"PASS","FAIL") -> PASS
A35: Net leverage within maximum | C35: ='Credit Metrics'!F11 -> 9.7781976 | D35: =Assumptions!$C$44 -> 10.5 | E35: =IF(C35<=D35,"PASS","FAIL") -> PASS
A36: Covenant headroom (base case, minimum) | C36: ='Calc Engine'!C300 -> -0.10483623 | D36: =Assumptions!$C$46 -> 0.15 | E36: =IF(C36>=D36,"PASS","FAIL") -> FAIL
A37: Principal protected in severe case (recovery % × 100 ≥ price) | C37: =Scenarios!E25*100 -> 100 | D37: =Assumptions!$C$36 -> 98 | E37: =IF(C37>=D37,"PASS","FAIL") -> PASS
A38: No unresolved high-priority diligence | C38: =Assumptions!$C$49 -> 6 | D38: =0 -> 0 | E38: =IF(C38<=D38,"PASS","FAIL") -> FAIL
A39: Core test failures | C39: =COUNTIF(E29:E33,"FAIL") -> 2
A40: Secondary test failures | C40: =COUNTIF(E34:E38,"FAIL") -> 2
A41: DECISION (PROCEED / HOLD / PASS) | C41: =IF(AND(C39=0,C40<=Assumptions!$C$47),"PROCEED",IF(OR(AND(E29="FAIL",E31="FAIL"),C39>=Assumptions!$C$48),"PASS","HOLD")) -> HOLD
A44: Model integrity checks
A45: Check | C45: Value | D45: Status
A46: Scenario probabilities sum to 100% | C46: =Assumptions!$C$135 -> 1 | D46: =IF(ABS(C46-1)<0.0001,"OK","ERROR") -> OK
A47: Credit score weights sum to 100 | C47: =Assumptions!$C$149 -> 100 | D47: =IF(ABS(C47-100)<0.0001,"OK","ERROR") -> OK
A48: Debt roll-forward bridge (sum of abs. differences) | C48: =SUMPRODUCT(ABS('Cash Flow'!$G$23:$K$23)) -> 3.8369308e-13 | D48: =IF(C48<0.001,"OK","ERROR") -> OK
A49: Recovery waterfall: recoveries + equity + costs = value | C49: =Recovery!C173 -> 0 | D49: =IF(ABS(C49)<0.001,"OK","ERROR") -> OK
A50: Detailed tabs reconcile to Calc Engine (sum of abs. diffs) | C50: =SUMPRODUCT(ABS(Scenarios!$E$41:$E$48)) -> 0 | D50: =IF(C50<0.001,"OK","ERROR") -> OK
A51: Model-calculated EBITDA / NOI equals company-reported figure (sum of abs. differences) | C51: =ABS('Historical Financials'!B47)+ABS('Historical Financials'!C47)+ABS('Historical Financials'!D47) -> 0 | D51: =IF(C51<0.001,"OK","ERROR") -> OK
A52: Formula errors across model tabs (count) | C52: =SUMPRODUCT(--ISERROR('Operating Model'!$C$5:$K$60))+SUMPRODUCT(--ISERROR('Debt Schedule'!$C$5:$K$300))+SUMPRODUCT(--ISERROR('Cash Flow'!$C$5:$K$40))+SUMPRODUCT(--ISERROR('Credit Metrics'!$C$5:$K$120))+SUMPRODUCT(--ISERROR(Recovery!$C$5:$K$300))+SUMPRODUCT(--ISERROR(Returns!$C$5:$K$300))+SUMPRODUCT(--ISERROR(Scenarios!$C$4:$F$60))+SUMPRODUCT(--ISERROR('Capital Structure'!$A$4:$L$60))+SUMPRODUCT(--ISERROR(Sensitivities!$A$4:$J$200))+SUMPRODUCT(--ISERROR('Calc Engine'!$C$5:$K$41280)) -> 0 | D52: =IF(C52=0,"OK","ERROR") -> OK
A53: OVERALL MODEL STATUS | D53: =IF(COUNTIF(D46:D52,"OK")=ROWS(D46:D52),"ALL CHECKS PASS","CHECK MODEL") -> ALL CHECKS PASS

Sheet Sources
A1: Sources — which model input came from which source
A2: PUBLIC FILING datapoints: every reported historical number below is a blue input on the Historical Financials tab; the Value column here is a live LINK to that cell. Page = footer page of the cited filing where recoverable. Derived values are formulas, never hardcodes.
A4: Source document | B4: Form | C4: Period | D4: Accession | E4: Filed | F4: URL | G4: Retrieved | H4: Data type | I4: Status
A5: Brandywine Realty Trust — Form 10-K, period ended 2025-12-31 | B5: Annual report | C5: 2025-12-31 | D5: 0000790816-26-000008 | E5: 2026-02-23 | F5: https://www.sec.gov/Archives/edgar/data/790816/000079081626000008/bdn-20251231.htm | G5: 2026-10-07 | H5: Annual report | I5: PUBLIC FILING
A6: Brandywine Realty Trust — Form 10-Q, period ended 2026-06-30 | B6: Quarterly report | C6: 2026-06-30 | D6: 0000790816-26-000029 | E6: 2026-07-28 | F6: https://www.sec.gov/Archives/edgar/data/790816/000079081626000029/bdn-20260630.htm | G6: 2026-10-07 | H6: Quarterly report | I6: PUBLIC FILING
A7: SOFR — Secured Overnight Financing Rate (3.90% on 2026-10-06) | B7: Macro rate | E7: 2026-10-06 | F7: https://fred.stlouisfed.org/series/SOFR | G7: 2026-10-07 | H7: Macro rate | I7: PUBLIC FILING
A9: Datapoint register (each row: one reported figure or disclosure, with filing, page/section and the model cell it feeds)
A10: Datapoint ID | B10: Metric | C10: Period | D10: Value (US$M) — link to model cell | E10: Unit | F10: Filing | G10: Accession | H10: Filing date | I10: Page | J10: Section | K10: Source URL | L10: Kind | M10: Model cell | N10: Raw text in filing / note
A11: bdn.q2_available_revolver | B11: q2_available_revolver | C11: 2026-06-30 | D11: n/a (text disclosure) | E11: text disclosure | F11: Form 10-Q for period ended 2026-06-30 | G11: 0000790816-26-000029 | H11: 2026-07-28 | I11: 44 | J11: Liquidity: availability at 2026-06-30 (600.0 commitment − 149.0 drawn − 25.5 letters of credit) | K11: https://www.sec.gov/Archives/edgar/data/790816/000079081626000029/bdn-20260630.htm | L11: reported | N11: $425.5 million of available borrowings under our Unsecured Credit Facility, net of $25.5 million in letters of credit outstanding — Liquidity: availability at 2026-06-30 (600.0 commitment − 149.0 drawn − 25.5 letters of credit)
A12: bdn.revenue.FY2023 | B12: revenue | C12: FY2023 | D12: ='Historical Financials'!B6 -> 514.651 | E12: US$M | F12: Form 10-K for period ended 2025-12-31 | G12: 0000790816-26-000008 | H12: 2026-02-23 | I12: F-9 | J12: Consolidated Statements of Operations | K12: https://www.sec.gov/Archives/edgar/data/790816/000079081626000008/bdn-20251231.htm | L12: reported | M12: Historical Financials!B6 | N12: as printed: 514,651 ($ thousands)
A13: bdn.prop_opex.FY2023 | B13: prop_opex | C13: FY2023 | D13: ='Historical Financials'!B7 -> 129.885 | E13: US$M | F13: Form 10-K for period ended 2025-12-31 | G13: 0000790816-26-000008 | H13: 2026-02-23 | I13: F-9 | J13: Consolidated Statements of Operations | K13: https://www.sec.gov/Archives/edgar/data/790816/000079081626000008/bdn-20251231.htm | L13: reported | M13: Historical Financials!B7 | N13: as printed: 129,885 ($ thousands)
A14: bdn.re_taxes.FY2023 | B14: re_taxes | C14: FY2023 | D14: ='Historical Financials'!B8 -> 49.974 | E14: US$M | F14: Form 10-K for period ended 2025-12-31 | G14: 0000790816-26-000008 | H14: 2026-02-23 | I14: F-9 | J14: Consolidated Statements of Operations | K14: https://www.sec.gov/Archives/edgar/data/790816/000079081626000008/bdn-20251231.htm | L14: reported | M14: Historical Financials!B8 | N14: as printed: 49,974 ($ thousands)
A15: bdn.mgmt_exp.FY2023 | B15: mgmt_exp | C15: FY2023 | D15: ='Historical Financials'!B9 -> 10.088 | E15: US$M | F15: Form 10-K for period ended 2025-12-31 | G15: 0000790816-26-000008 | H15: 2026-02-23 | I15: F-9 | J15: Consolidated Statements of Operations | K15: https://www.sec.gov/Archives/edgar/data/790816/000079081626000008/bdn-20251231.htm | L15: reported | M15: Historical Financials!B9 | N15: as printed: 10,088 ($ thousands)
A16: bdn.ga.FY2023 | B16: ga | C16: FY2023 | D16: ='Historical Financials'!B10 -> 34.862 | E16: US$M | F16: Form 10-K for period ended 2025-12-31 | G16: 0000790816-26-000008 | H16: 2026-02-23 | I16: F-9 | J16: Consolidated Statements of Operations | K16: https://www.sec.gov/Archives/edgar/data/790816/000079081626000008/bdn-20251231.htm | L16: reported | M16: Historical Financials!B10 | N16: as printed: 34,862 ($ thousands)
A17: bdn.da.FY2023 | B17: da | C17: FY2023 | D17: ='Historical Financials'!B11 -> 188.797 | E17: US$M | F17: Form 10-K for period ended 2025-12-31 | G17: 0000790816-26-000008 | H17: 2026-02-23 | I17: F-9 | J17: Consolidated Statements of Operations | K17: https://www.sec.gov/Archives/edgar/data/790816/000079081626000008/bdn-20251231.htm | L17: reported | M17: Historical Financials!B11 | N17: as printed: 188,797 ($ thousands)
A18: bdn.interest_expense.FY2023 | B18: interest_expense | C18: FY2023 | D18: ='Historical Financials'!B12 -> 95.456 | E18: US$M | F18: Form 10-K for period ended 2025-12-31 | G18: 0000790816-26-000008 | H18: 2026-02-23 | I18: F-9 | J18: Consolidated Statements of Operations | K18: https://www.sec.gov/Archives/edgar/data/790816/000079081626000008/bdn-20251231.htm | L18: reported | M18: Historical Financials!B12 | N18: as printed: 95,456 ($ thousands) — Excludes amortization of deferred financing costs; net of capitalized interest
