Workbook

Sheet Cover
A1: CreditIQ — AMC Networks (AMC Global Media) credit underwriting model
A2: PUBLIC DATA CASE · HYPOTHETICAL INVESTMENT TERMS · $ in millions · as of 2026-06-30
A3: Corporate credit — senior secured notes of a levered, declining linear-TV network
A4: Model status | B4: ='Investment Summary'!$D$53 -> ALL CHECKS PASS
A5: Active scenario | B5: =Assumptions!$D$10 -> Downside
A6: Recommendation (rule-based; see Investment Summary) | B6: ='Investment Summary'!$C$4 -> HOLD
A8: Colour conventions
A9: Blue on pale yellow | B9: Hardcoded input: sourced historical data, explicit assumption, scenario / transaction / macro input, covenant threshold, sensitivity axis, structural block parameter.
A10: Black | B10: Formula or calculation. No outputs, subtotals or metrics are hardcoded anywhere in this workbook.
A11: Green | B11: Direct link to a cell on another worksheet.
A12: Grey fill | B12: Labels and headers.
A14: Flow of logic | B14: Assumptions + Historical → Operating Model → Debt Schedule ↔ Cash Flow → Credit Metrics & Covenants → Recovery → Returns → Sensitivities → Investment Summary
A15: Data classes | B15: PUBLIC FILING = reported inputs · ANALYST PROJECTION = scenario drivers · UNDERWRITING ASSUMPTION = hypothetical purchase price / terms · DEMO = fictional
A17: Tabs
A18: Assumptions | B18: All inputs, scenario drivers, covenants, selector
A19: Historical Financials | B19: Sourced statements; derived lines and LTM calculated
A20: Operating Model | B20: Income statement and FCF, history + projection
A21: Debt Schedule | B21: Per-tranche roll-forward, floors, PIK, refinancing test, sweep
A22: Cash Flow | B22: Cash waterfall, funding gap, default test
A23: Credit Metrics | B23: Ratios, covenant compliance, transparent credit score
A24: Scenarios | B24: Base / Downside / Severe side by side + reconciliation
A25: Capital Structure | B25: Tranches, leverage through the stack, maturity wall & refinancing requirement
A26: Recovery | B26: Seniority waterfall with collateral pools and deficiency claims
A27: Returns | B27: Face, price, coupon, yield, recovery; IRR, XIRR, MOIC
A28: Sensitivities | B28: Seven formula-driven tables
A29: Investment Summary | B29: Live outputs, recommendation evidence, integrity checks
... A31: Calc Engine | B31: Supporting: 63 simultaneous model runs
A33: Validation: docs/MODEL_VALIDATION.md · Audit: scripts/audit_model.py · Change-impact harness: scripts/model_harness.py

Sheet Assumptions
A1: Assumptions — AMC Networks (AMC Global Media): all explicit inputs live on this tab
A2: PUBLIC DATA CASE · HYPOTHETICAL INVESTMENT TERMS · Blue on pale yellow = hardcoded input · Black = formula · Green = link to another sheet · $ in millions
A4: 1. General & model settings
A5: Company | C5: AMC Networks (AMC Global Media)
A6: Base period label (year in which the base / LTM period ends) | C6: 2026
A7: Fiscal-period end month (12 = calendar FY; 6 = LTM June periods) | C7: 6
A8: As-of / entry date | C8: 46203
A9: Cash tax rate on positive EBT | B9: % of EBT | C9: 0.25
A10: ACTIVE SCENARIO selector (1=Base, 2=Downside, 3=Severe) | B10: select 1 / 2 / 3 | C10: 2 | D10: =CHOOSE(C10,"Base Case","Downside","Severe Downside") -> Downside
A11: Cash & equivalents at base date (balance sheet) | B11: $M | C11: 463.996
A12: Minimum operating cash | B12: $M | C12: 150
A13: Cash sweep (% of excess cash applied to prepayable debt) | B13: % | C13: 0
A14: Recovery value override (leave blank = model-derived) | B14: $M, optional
A15: Administrative / DIP costs | B15: % of recovery value | C15: 0.04
A16: Accrued unpaid interest included in claims | B16: months | C16: 3
A17: Rank at which secured deficiency claims join general creditors | C17: 99
A18: Maturity alert window | B18: periods from base | C18: 2
A19: Materiality threshold for maturity alert | B19: % of total debt | C19: 0.25
A20: Concentration threshold (single-period maturities) | B20: % of total debt | C20: 0.3
A21: Market-implied EV / EBITDA (analyst assumption) | B21: x | C21: 5.5
A22: Credit score: maturity-risk window | B22: periods | C22: 3
A24: 2. Collateral / asset base (recovery & LTV)
A25: Book value of program rights, receivables, PP&E and intangibles at 2026-06-30 (derived from the 10-Q balance sheet); liquidation recovery on that base is an analyst assumption (30%).
A26: Program rights, net | C26: 1627.782 | D26: amcx.program_rights.2026-06-30
A27: Accounts receivable, trade | C27: 547.187 | D27: amcx.ar.2026-06-30
A28: Property and equipment, net | C28: 110.555 | D28: amcx.ppe.2026-06-30
A29: Intangible assets, net | C29: 169.447 | D29: amcx.intangibles.2026-06-30
A30: Total asset base | C30: =SUM(C26:C29) -> 2454.971
A32: 3. Transaction / position being underwritten — HYPOTHETICAL INVESTMENT TERMS
A33: Target tranche # (row in the debt table below) | C33: 1
A34: Face value held (legal claim) | B34: $M | C34: 100
A35: Purchase price / OID (UNDERWRITING ASSUMPTION) | B35: % of face | C35: 95
A36: Transaction fees | B36: % of cost | C36: 0
A37: Hold period (whole years, 1-5) | B37: periods | C37: 3
A38: Coupon payments per year on target tranche (contractual-timing cross-check only) | B38: per year | C38: 2
A39: Default → recovery cash receipt lag | B39: periods | C39: 1
A40: Required IRR (hurdle) | C40: 0.12
A41: Minimum acceptable downside IRR | C41: 0
A42: Minimum yield to maturity | C42: 0.1
A43: Maximum net leverage (net debt / EBITDA) | C43: 6
A44: Minimum downside recovery | C44: 0.7
A45: Minimum covenant headroom (base case) | C45: 0.15
A46: Decision rule: secondary test failures tolerated for PROCEED | B46: count | C46: 2
A47: Decision rule: core test failures that force PASS | B47: count | C47: 3
A48: Unresolved high-priority diligence items (from the CreditIQ diligence tracker) | B48: count | C48: 6
A50: 4. Macro assumptions
A51: Model period | G51: =Assumptions!$C$6+1 -> 2027 | H51: =G51+1 -> 2028 | I51: =H51+1 -> 2029 | J51: =I51+1 -> 2030 | K51: =J51+1 -> 2031
A52: Base rate (SOFR) curve — FRED SOFR 3.90% on 2026-10-06; path is an assumption | B52: % p.a. | G52: 0.039 | H52: 0.0375 | I52: 0.035 | J52: 0.035 | K52: 0.035
A54: 5. Debt tranches (list in order of cash-repayment priority; rank 1 = most senior, equal rank = pari passu)
A55: Facility | B55: Type | C55: Face / principal $M | D55: Commit. $M | E55: Fixed coupon | F55: Spread (floating) | G55: SOFR floor | H55: PIK rate | I55: Floating (1/0) | J55: Maturity date | K55: Maturity period | L55: Amort. % orig | M55: Rank | N55: Prepay (1/0) | O55: Secured (1/0) | P55: Revolver (1/0) | Q55: Collateral share | R55: Mark / price | S55: Call protection / collateral
A56: 10.50% Senior Secured Notes due 2032 | B56: senior_notes | C56: 1315.098 | D56: 0 | E56: 0.105 | F56: 0 | G56: 0 | H56: 0 | I56: 0 | J56: 48410 | K56: =YEAR(J56)+IF(MONTH(J56)>Assumptions!$C$7,1,0) -> 2033 | L56: 0 | M56: 1 | N56: 0 | O56: 1 | P56: 0 | Q56: 0 | R56: 95 | S56: Non-call to 2028-07-15; 105.250% in 2028, 102.625% in 2029, par from 2030 (10-K Note 9) | First-priority lien on substantially all assets of AMC Networks and guarantors
A57: 4.25% Senior Notes due 2029 | B57: unsecured_notes | C57: 276.706 | D57: 0 | E57: 0.0425 | F57: 0 | G57: 0 | H57: 0 | I57: 0 | J57: 47164 | K57: =YEAR(J57)+IF(MONTH(J57)>Assumptions!$C$7,1,0) -> 2029 | L57: 0 | M57: 2 | N57: 0 | O57: 0 | P57: 0 | Q57: 0 | R57: 100 | S57: Unsecured (guaranteed by domestic restricted subsidiaries)
A58: 4.25% Convertible Senior Notes due 2029 | B58: convertible | C58: 143.75 | D58: 0 | E58: 0.0425 | F58: 0 | G58: 0 | H58: 0 | I58: 0 | J58: 47164 | K58: =YEAR(J58)+IF(MONTH(J58)>Assumptions!$C$7,1,0) -> 2029 | L58: 0 | M58: 2 | N58: 0 | O58: 0 | P58: 0 | Q58: 0 | R58: 100 | S58: Unsecured; convertible at 78.5083 Class A shares per $1,000
A59: Floating tranches: all-in rate = MAX(SOFR, floor) + spread + scenario shock. Fixed: coupon. Interest accrues on beginning balances (no circularity). Maturity period = YEAR(date) + 1 if month > period-end month.
A61: 6. Covenants (thresholds per model period). Disclosed = in issuer documents; Hypothetical = UNDERWRITING ASSUMPTION; inactive covenants are shown for reference only
A62: Covenant | B62: Type | C62: Basis | D62: Active (1/0) | E62: Reported ratio | G62: =Assumptions!$C$6+1 -> 2027 | H62: =G62+1 -> 2028 | I62: =H62+1 -> 2029 | J62: =I62+1 -> 2030 | K62: =J62+1 -> 2031
A63: Credit agreement: max total net leverage (5.75x to 3/31/26, then 5.50x) — TERMINATED 2026-05-12 | B63: maxNetLeverage | C63: disclosed | D63: 0 | E63: 4.41 | G63: 5.5 | H63: 5.5 | I63: 5.5 | J63: 5.5 | K63: 5.5
A64: Credit agreement: min interest coverage (1.50x; 1.75x from 12/31/28) — TERMINATED 2026-05-12 | B64: minInterestCoverage | C64: disclosed | D64: 0 | E64: 2.01 | G64: 1.5 | H64: 1.5 | I64: 1.5 | J64: 1.75 | K64: 1.75
A65: Hypothetical maintenance covenant: max net leverage (AOI basis) | B65: maxNetLeverage | C65: hypothetical | D65: 1 | G65: 5.25 | H65: 5.25 | I65: 5 | J65: 5 | K65: 5
A66: Hypothetical maintenance covenant: min interest coverage (AOI / interest) | B66: minInterestCoverage | C66: hypothetical | D66: 1 | G66: 1.4 | H66: 1.4 | I66: 1.4 | J66: 1.5 | K66: 1.5
A67: Hypothetical maintenance covenant: min liquidity ($M) | B67: minLiquidity | C67: hypothetical | D67: 1 | G67: 200 | H67: 200 | I67: 200 | J67: 200 | K67: 200
A69: 7. Scenario assumptions (selected via ACTIVE SCENARIO; all three run simultaneously on Calc Engine)
A70: Base Case | G70: =Assumptions!$C$6+1 -> 2027 | H70: =G70+1 -> 2028 | I70: =H70+1 -> 2029 | J70: =I70+1 -> 2030 | K70: =J70+1 -> 2031
A71: Revenue growth | G71: -0.045 | H71: -0.04 | I71: -0.035 | J71: -0.03 | K71: -0.03
A72: Gross margin | G72: 0.48324667 | H72: 0.48324667 | I72: 0.48124667 | J72: 0.47924667 | K72: 0.47724667
A73: EBITDA margin | G73: 0.14 | H73: 0.14 | I73: 0.138 | J73: 0.136 | K73: 0.134
A74: Net asset-sale proceeds ($M) | G74: 0 | H74: 0 | I74: 0 | J74: 0 | K74: 0
A75: Capex | B75: % of revenue | C75: 0.014
A76: Working-capital investment | B76: % of Δ revenue | C76: 0
A77: Other cash items (+ outflow; incl. distributions, programming timing) | B77: % of revenue | C77: -0.01
A78: Floating-rate shock | B78: % added to floating rates | C78: 0
A79: Refinancing rate (post-maturity) | B79: % | C79: 0.11
A80: Market access: max net leverage to refinance | B80: x | C80: 6
A81: Market access: min EBITDA / pro-forma interest | B81: x | C81: 1.25
A82: Exit EV / EBITDA multiple | B82: x | C82: 5.5
A83: Exit price if no default (cap, % of face) | B83: % of face | C83: 100
A84: Distressed EV / EBITDA multiple (going concern) | B84: x | C84: 5
A85: Asset value decline | B85: % | C85: 0
A86: Liquidation recovery on asset base | B86: % | C86: 0.3
A87: Scenario probability | C87: 0.45
A89: Downside | G89: =Assumptions!$C$6+1 -> 2027 | H89: =G89+1 -> 2028 | I89: =H89+1 -> 2029 | J89: =I89+1 -> 2030 | K89: =J89+1 -> 2031
A90: Revenue growth | G90: -0.08 | H90: -0.07 | I90: -0.06 | J90: -0.05 | K90: -0.05
A91: Gross margin | G91: 0.46324667 | H91: 0.45324667 | I91: 0.44824667 | J91: 0.44324667 | K91: 0.44324667
A92: EBITDA margin | G92: 0.12 | H92: 0.11 | I92: 0.105 | J92: 0.1 | K92: 0.1
A93: Net asset-sale proceeds ($M) | G93: 0 | H93: 0 | I93: 0 | J93: 0 | K93: 0
A94: Capex | B94: % of revenue | C94: 0.013
A95: Working-capital investment | B95: % of Δ revenue | C95: 0
A96: Other cash items (+ outflow; incl. distributions, programming timing) | B96: % of revenue | C96: 0.005
A97: Floating-rate shock | B97: % added to floating rates | C97: 0.015
A98: Refinancing rate (post-maturity) | B98: % | C98: 0.13
A99: Market access: max net leverage to refinance | B99: x | C99: 5.5
A100: Market access: min EBITDA / pro-forma interest | B100: x | C100: 1.5
A101: Exit EV / EBITDA multiple | B101: x | C101: 5
A102: Exit price if no default (cap, % of face) | B102: % of face | C102: 95
A103: Distressed EV / EBITDA multiple (going concern) | B103: x | C103: 4.5
A104: Asset value decline | B104: % | C104: 0.15
A105: Liquidation recovery on asset base | B105: % | C105: 0.3
A106: Scenario probability | C106: 0.35
A108: Severe Downside | G108: =Assumptions!$C$6+1 -> 2027 | H108: =G108+1 -> 2028 | I108: =H108+1 -> 2029 | J108: =I108+1 -> 2030 | K108: =J108+1 -> 2031
A109: Revenue growth | G109: -0.14 | H109: -0.12 | I109: -0.1 | J109: -0.08 | K109: -0.06
...

Sheet Historical Financials
A1: Historical Financials — AMC Networks (AMC Global Media)
A2: PUBLIC FILING data (blue = reported inputs, each traced to a datapoint on the Sources tab). All subtotals, EBITDA, EBIT, net income, FCF and LTM columns are formulas.
A4: US$ millions | B4: FY2023A | C4: FY2024A | D4: FY2025A | E4: H1-25A | F4: H1-26A | G4: LTM Jun-26 | H4: Source datapoint IDs (see Sources tab)
A5: A. Reported inputs
A6: Revenues, net | B6: 2711.877 | C6: 2421.314 | D6: 2311.801 | E6: 1155.257 | F6: 1089.622 | G6: =D6+F6-E6 -> 2246.166 | H6: amcx.revenue.* (5 datapoints)
A7: Technical and operating (excl. D&A) | B7: 1327.5 | C7: 1132.593 | D7: 1141.393 | E7: 551.222 | F7: 571.961 | G7: =D7+F7-E7 -> 1162.132 | H7: amcx.direct_costs.* (5 datapoints)
A8: Selling, general and administrative | B8: 764.087 | C8: 781.329 | D8: 818.341 | E8: 419.679 | F8: 426.623 | G8: =D8+F8-E8 -> 825.285 | H8: amcx.sga.* (5 datapoints)
A9: Share-based compensation (AOI add-back) | B9: 25.665 | C9: 26.051 | D9: 25.33 | E9: 13.8 | F9: 12.826 | G9: =D9+F9-E9 -> 24.356 | H9: amcx.sbc.* (5 datapoints)
A10: Cloud computing amortization (AOI add-back) | B10: 10.543 | C10: 13.452 | D10: 10.733 | E10: 5.938 | F10: 4.416 | G10: =D10+F10-E10 -> 9.211 | H10: amcx.cloud_amort.* (5 datapoints)
A11: Majority-owned equity-investee AOI (AOI add-back) | B11: 13.606 | C11: 15.678 | D11: 23.744 | E11: 9.777 | F11: 6.762 | G11: =D11+F11-E11 -> 20.729 | H11: amcx.jv_aoi.* (5 datapoints)
A12: Depreciation and amortization | B12: 107.402 | C12: 98.015 | D12: 94.425 | E12: 47.372 | F12: 38.243 | G12: =D12+F12-E12 -> 85.296 | H12: amcx.da.* (5 datapoints)
A13: Interest expense | B13: 152.703 | C13: 166.186 | D13: 172.353 | E13: 85.852 | F13: 84.012 | G13: =D13+F13-E13 -> 170.513 | H13: amcx.interest_expense.* (5 datapoints)
A14: Income tax expense (benefit) | B14: 94.606 | C14: 43.49 | D14: 46.226 | E14: 31.027 | F14: -11.413 | G14: =D14+F14-E14 -> 3.786 | H14: amcx.taxes.* (5 datapoints)
A15: Net cash provided by operating activities | B15: 203.919 | C15: 375.615 | D15: 305.67 | E15: 211.596 | F15: 124.659 | G15: =D15+F15-E15 -> 218.733 | H15: amcx.cfo.* (5 datapoints)
A16: Capital expenditures | B16: 35.207 | C16: 44.775 | D16: 33.303 | E16: 21.67 | F16: 16.577 | G16: =D16+F16-E16 -> 28.21 | H16: amcx.capex.* (5 datapoints)
A17: Impairment and other charges (memo, excluded from EBITDA) | B17: 96.689 | C17: 399.513 | D17: 97.784 | E17: 0 | F17: 0 | G17: =D17+F17-E17 -> 97.784 | H17: amcx.impairment.* (3 datapoints)
... A20: Adjusted operating income — company reported (check) | B20: 670.104 | C20: 562.573 | D20: 411.874 | E20: 213.871 | F20: 115.042 | G20: =D20+F20-E20 -> 313.045 | H20: amcx.aoi_reported.* (5 datapoints)
A22: B. Standardized statements (calculated)
A23: Revenue | B23: =B6 -> 2711.877 | C23: =C6 -> 2421.314 | D23: =D6 -> 2311.801 | E23: =E6 -> 1155.257 | F23: =F6 -> 1089.622 | G23: =G6 -> 2246.166
A24: Direct costs / COGS | B24: =B7 -> 1327.5 | C24: =C7 -> 1132.593 | D24: =D7 -> 1141.393 | E24: =E7 -> 551.222 | F24: =F7 -> 571.961 | G24: =G7 -> 1162.132
A25: Gross profit (NOI for real estate) | B25: =B23-B24 -> 1384.377 | C25: =C23-C24 -> 1288.721 | D25: =D23-D24 -> 1170.408 | E25: =E23-E24 -> 604.035 | F25: =F23-F24 -> 517.661 | G25: =G23-G24 -> 1084.034
A26: Operating expenses, cash & adjusted (excl. D&A and non-cash add-backs) | B26: =B8-B9-B10-B11 -> 714.273 | C26: =C8-C9-C10-C11 -> 726.148 | D26: =D8-D9-D10-D11 -> 758.534 | E26: =E8-E9-E10-E11 -> 390.164 | F26: =F8-F9-F10-F11 -> 402.619 | G26: =G8-G9-G10-G11 -> 770.989
A27: EBITDA (company-adjusted basis) | B27: =B25-B26 -> 670.104 | C27: =C25-C26 -> 562.573 | D27: =D25-D26 -> 411.874 | E27: =E25-E26 -> 213.871 | F27: =F25-F26 -> 115.042 | G27: =G25-G26 -> 313.045
A28: Depreciation & amortization | B28: =B12 -> 107.402 | C28: =C12 -> 98.015 | D28: =D12 -> 94.425 | E28: =E12 -> 47.372 | F28: =F12 -> 38.243 | G28: =G12 -> 85.296
A29: Share-based compensation (non-cash add-back) | B29: =B9 -> 25.665 | C29: =C9 -> 26.051 | D29: =D9 -> 25.33 | E29: =E9 -> 13.8 | F29: =F9 -> 12.826 | G29: =G9 -> 24.356
A30: EBIT (EBITDA − D&A − SBC) | B30: =B27-B28-B29 -> 537.037 | C30: =C27-C28-C29 -> 438.507 | D30: =D27-D28-D29 -> 292.119 | E30: =E27-E28-E29 -> 152.699 | F30: =F27-F28-F29 -> 63.973 | G30: =G27-G28-G29 -> 203.393
A31: Interest expense | B31: =B13 -> 152.703 | C31: =C13 -> 166.186 | D31: =D13 -> 172.353 | E31: =E13 -> 85.852 | F31: =F13 -> 84.012 | G31: =G13 -> 170.513
A32: EBT | B32: =B30-B31 -> 384.334 | C32: =C30-C31 -> 272.321 | D32: =D30-D31 -> 119.766 | E32: =E30-E31 -> 66.847 | F32: =F30-F31 -> -20.039 | G32: =G30-G31 -> 32.88
A33: Income taxes | B33: =B14 -> 94.606 | C33: =C14 -> 43.49 | D33: =D14 -> 46.226 | E33: =E14 -> 31.027 | F33: =F14 -> -11.413 | G33: =G14 -> 3.786
A34: Net income (model basis; excludes impairments and one-offs) | B34: =B32-B33 -> 289.728 | C34: =C32-C33 -> 228.831 | D34: =D32-D33 -> 73.54 | E34: =E32-E33 -> 35.82 | F34: =F32-F33 -> -8.626 | G34: =G32-G33 -> 29.094
A35: Capex (incl. leasing costs where applicable) | B35: =B16 -> 35.207 | C35: =C16 -> 44.775 | D35: =D16 -> 33.303 | E35: =E16 -> 21.67 | F35: =F16 -> 16.577 | G35: =G16 -> 28.21
A36: Net cash provided by operating activities (reported) | B36: =B15 -> 203.919 | C36: =C15 -> 375.615 | D36: =D15 -> 305.67 | E36: =E15 -> 211.596 | F36: =F15 -> 124.659 | G36: =G15 -> 218.733
A37: Free cash flow (CFO − capex) | B37: =B36-B35 -> 168.712 | C37: =C36-C35 -> 330.84 | D37: =D36-D35 -> 272.367 | E37: =E36-E35 -> 189.926 | F37: =F36-F35 -> 108.082 | G37: =G36-G35 -> 190.523
A38: Δ working capital & other (derived plug: NI + D&A + SBC − capex − FCF) | B38: =B34+B28+B29-B35-B37 -> 218.876 | C38: =C34+C28+C29-C35-C37 -> -22.718 | D38: =D34+D28+D29-D35-D37 -> -112.375 | E38: =E34+E28+E29-E35-E37 -> -114.604 | F38: =F34+F28+F29-F35-F37 -> -82.216 | G38: =G34+G28+G29-G35-G37 -> -79.987
A40: C. Ratios & checks (calculated)
A41: Gross margin | B41: =B25/B23 -> 0.51048665 | C41: =C25/C23 -> 0.53224035 | D41: =D25/D23 -> 0.50627541 | E41: =E25/E23 -> 0.52285768 | F41: =F25/F23 -> 0.4750831 | G41: =G25/G23 -> 0.48261527
A42: EBITDA margin | B42: =B27/B23 -> 0.2470997 | C42: =C27/C23 -> 0.23234203 | D42: =D27/D23 -> 0.17816153 | E42: =E27/E23 -> 0.1851285 | F42: =F27/F23 -> 0.10557973 | G42: =G27/G23 -> 0.1393686
A43: Revenue growth (YoY) | C43: =C23/B23-1 -> -0.10714461 | D43: =D23/C23-1 -> -0.045228748 | F43: =F23/E23-1 -> -0.056814198
A44: EBITDA growth (YoY) | C44: =C27/B27-1 -> -0.16046912 | D44: =D27/C27-1 -> -0.26787457 | F44: =F27/E27-1 -> -0.46209631
A45: Check: Calculated AOI vs company-reported AOI (should be 0.000) | B45: =B27-B20 -> 0 | C45: =C27-C20 -> 0 | D45: =D27-D20 -> 0 | E45: =E27-E20 -> 0 | F45: =F27-F20 -> 0 | G45: =G27-G20 -> 0

Sheet Operating Model
A1: Operating Model — selected scenario (assumptions → statements)
A2: ="AMC Networks (AMC Global Media) · PUBLIC DATA CASE · HYPOTHETICAL INVESTMENT TERMS · Active scenario: "&Assumptions!$D$10 -> AMC Networks (AMC Global Media) · PUBLIC DATA CASE · HYPOTHETICAL INVESTMENT TERMS · Active scenario: Downside
A4: $M | C4: FY2023A | D4: FY2024A | E4: FY2025A | F4: LTM Jun-26 | G4: LTM Jun-27E | H4: LTM Jun-28E | I4: LTM Jun-29E | J4: LTM Jun-30E | K4: LTM Jun-31E
A6: Operating drivers (selected scenario → Assumptions)
A7: Model period (year in which the period ends) | C7: =D7-1 -> 2023 | D7: =E7-1 -> 2024 | E7: =F7-1 -> 2025 | F7: =Assumptions!$C$6 -> 2026 | G7: =F7+1 -> 2027 | H7: =G7+1 -> 2028 | I7: =H7+1 -> 2029 | J7: =I7+1 -> 2030 | K7: =J7+1 -> 2031
A8: Projection period # | G8: =G7-Assumptions!$C$6 -> 1 | H8: =H7-Assumptions!$C$6 -> 2 | I8: =I7-Assumptions!$C$6 -> 3 | J8: =J7-Assumptions!$C$6 -> 4 | K8: =K7-Assumptions!$C$6 -> 5
A9: Revenue growth | G9: =CHOOSE(Assumptions!$C$10,Assumptions!$G$71,Assumptions!$G$90,Assumptions!$G$109) -> -0.08 | H9: =CHOOSE(Assumptions!$C$10,Assumptions!$H$71,Assumptions!$H$90,Assumptions!$H$109) -> -0.07 | I9: =CHOOSE(Assumptions!$C$10,Assumptions!$I$71,Assumptions!$I$90,Assumptions!$I$109) -> -0.06 | J9: =CHOOSE(Assumptions!$C$10,Assumptions!$J$71,Assumptions!$J$90,Assumptions!$J$109) -> -0.05 | K9: =CHOOSE(Assumptions!$C$10,Assumptions!$K$71,Assumptions!$K$90,Assumptions!$K$109) -> -0.05
A10: Gross margin | G10: =CHOOSE(Assumptions!$C$10,Assumptions!$G$72,Assumptions!$G$91,Assumptions!$G$110) -> 0.46324667 | H10: =CHOOSE(Assumptions!$C$10,Assumptions!$H$72,Assumptions!$H$91,Assumptions!$H$110) -> 0.45324667 | I10: =CHOOSE(Assumptions!$C$10,Assumptions!$I$72,Assumptions!$I$91,Assumptions!$I$110) -> 0.44824667 | J10: =CHOOSE(Assumptions!$C$10,Assumptions!$J$72,Assumptions!$J$91,Assumptions!$J$110) -> 0.44324667 | K10: =CHOOSE(Assumptions!$C$10,Assumptions!$K$72,Assumptions!$K$91,Assumptions!$K$110) -> 0.44324667
A11: EBITDA margin | G11: =CHOOSE(Assumptions!$C$10,Assumptions!$G$73,Assumptions!$G$92,Assumptions!$G$111) -> 0.12 | H11: =CHOOSE(Assumptions!$C$10,Assumptions!$H$73,Assumptions!$H$92,Assumptions!$H$111) -> 0.11 | I11: =CHOOSE(Assumptions!$C$10,Assumptions!$I$73,Assumptions!$I$92,Assumptions!$I$111) -> 0.105 | J11: =CHOOSE(Assumptions!$C$10,Assumptions!$J$73,Assumptions!$J$92,Assumptions!$J$111) -> 0.1 | K11: =CHOOSE(Assumptions!$C$10,Assumptions!$K$73,Assumptions!$K$92,Assumptions!$K$111) -> 0.1
A12: Income statement ($M)
A13: Revenue | C13: ='Historical Financials'!B23 -> 2711.877 | D13: ='Historical Financials'!C23 -> 2421.314 | E13: ='Historical Financials'!D23 -> 2311.801 | F13: ='Historical Financials'!G23 -> 2246.166 | G13: =F13*(1+G9) -> 2066.4727 | H13: =G13*(1+H9) -> 1921.8196 | I13: =H13*(1+I9) -> 1806.5105 | J13: =I13*(1+J9) -> 1716.1849 | K13: =J13*(1+K9) -> 1630.3757
A14: Direct costs / COGS | C14: ='Historical Financials'!B24 -> 1327.5 | D14: ='Historical Financials'!C24 -> 1132.593 | E14: ='Historical Financials'!D24 -> 1141.393 | F14: ='Historical Financials'!G24 -> 1162.132 | G14: =G13*(1-G10) -> 1109.1861 | H14: =H13*(1-H10) -> 1050.7613 | I14: =I13*(1-I10) -> 996.74816 | J14: =J13*(1-J10) -> 955.49167 | K14: =K13*(1-K10) -> 907.71709
A15: Gross profit (NOI for real estate) | C15: =C13-C14 -> 1384.377 | D15: =D13-D14 -> 1288.721 | E15: =E13-E14 -> 1170.408 | F15: =F13-F14 -> 1084.034 | G15: =G13-G14 -> 957.28661 | H15: =H13-H14 -> 871.05835 | I15: =I13-I14 -> 809.76229 | J15: =J13-J14 -> 760.69326 | K15: =K13-K14 -> 722.65859
A16: Operating expenses (implied: gross profit − EBITDA) | C16: ='Historical Financials'!B26 -> 714.273 | D16: ='Historical Financials'!C26 -> 726.148 | E16: ='Historical Financials'!D26 -> 758.534 | F16: ='Historical Financials'!G26 -> 770.989 | G16: =G15-G17 -> 709.30988 | H16: =H15-H17 -> 659.65819 | I16: =I15-I17 -> 620.0787 | J16: =J15-J17 -> 589.07476 | K16: =K15-K17 -> 559.62102
A17: EBITDA | C17: =C15-C16 -> 670.104 | D17: =D15-D16 -> 562.573 | E17: =E15-E16 -> 411.874 | F17: =F15-F16 -> 313.045 | G17: =G13*G11 -> 247.97673 | H17: =H13*H11 -> 211.40016 | I17: =I13*I11 -> 189.6836 | J17: =J13*J11 -> 171.61849 | K17: =K13*K11 -> 163.03757
A18: D&A | C18: ='Historical Financials'!B28 -> 107.402 | D18: ='Historical Financials'!C28 -> 98.015 | E18: ='Historical Financials'!D28 -> 94.425 | F18: ='Historical Financials'!G28 -> 85.296 | G18: =G13*'Historical Financials'!G28/'Historical Financials'!G23 -> 78.47232 | H18: =H13*'Historical Financials'!G28/'Historical Financials'!G23 -> 72.979258 | I18: =I13*'Historical Financials'!G28/'Historical Financials'!G23 -> 68.600502 | J18: =J13*'Historical Financials'!G28/'Historical Financials'!G23 -> 65.170477 | K18: =K13*'Historical Financials'!G28/'Historical Financials'!G23 -> 61.911953
A19: Share-based compensation (non-cash) | C19: ='Historical Financials'!B29 -> 25.665 | D19: ='Historical Financials'!C29 -> 26.051 | E19: ='Historical Financials'!D29 -> 25.33 | F19: ='Historical Financials'!G29 -> 24.356 | G19: =G13*'Historical Financials'!G29/'Historical Financials'!G23 -> 22.40752 | H19: =H13*'Historical Financials'!G29/'Historical Financials'!G23 -> 20.838994 | I19: =I13*'Historical Financials'!G29/'Historical Financials'!G23 -> 19.588654 | J19: =J13*'Historical Financials'!G29/'Historical Financials'!G23 -> 18.609221 | K19: =K13*'Historical Financials'!G29/'Historical Financials'!G23 -> 17.67876
A20: EBIT | C20: =C17-C18-C19 -> 537.037 | D20: =D17-D18-D19 -> 438.507 | E20: =E17-E18-E19 -> 292.119 | F20: =F17-F18-F19 -> 203.393 | G20: =G17-G18-G19 -> 147.09689 | H20: =H17-H18-H19 -> 117.58191 | I20: =I17-I18-I19 -> 101.49444 | J20: =J17-J18-J19 -> 87.838795 | K20: =K17-K18-K19 -> 83.446855
A21: Cash interest expense (Debt Schedule) | G21: ='Debt Schedule'!G21+'Debt Schedule'!G34+'Debt Schedule'!G47 -> 155.95467 | H21: ='Debt Schedule'!H21+'Debt Schedule'!H34+'Debt Schedule'!H47 -> 155.95467 | I21: ='Debt Schedule'!I21+'Debt Schedule'!I34+'Debt Schedule'!I47 -> 155.95467 | J21: ='Debt Schedule'!J21+'Debt Schedule'!J34+'Debt Schedule'!J47 -> 138.08529 | K21: ='Debt Schedule'!K21+'Debt Schedule'!K34+'Debt Schedule'!K47 -> 138.08529
A22: PIK interest (non-cash) | G22: ='Debt Schedule'!G22+'Debt Schedule'!G35+'Debt Schedule'!G48 -> 0 | H22: ='Debt Schedule'!H22+'Debt Schedule'!H35+'Debt Schedule'!H48 -> 0 | I22: ='Debt Schedule'!I22+'Debt Schedule'!I35+'Debt Schedule'!I48 -> 0 | J22: ='Debt Schedule'!J22+'Debt Schedule'!J35+'Debt Schedule'!J48 -> 0 | K22: ='Debt Schedule'!K22+'Debt Schedule'!K35+'Debt Schedule'!K48 -> 0
A23: Interest expense | C23: ='Historical Financials'!B31 -> 152.703 | D23: ='Historical Financials'!C31 -> 166.186 | E23: ='Historical Financials'!D31 -> 172.353 | F23: ='Historical Financials'!G31 -> 170.513 | G23: =G21+G22 -> 155.95467 | H23: =H21+H22 -> 155.95467 | I23: =I21+I22 -> 155.95467 | J23: =J21+J22 -> 138.08529 | K23: =K21+K22 -> 138.08529
A24: EBT | C24: =C20-C23 -> 384.334 | D24: =D20-D23 -> 272.321 | E24: =E20-E23 -> 119.766 | F24: =F20-F23 -> 32.88 | G24: =G20-G23 -> -8.8577836 | H24: =H20-H23 -> -38.372762 | I24: =I20-I23 -> -54.460229 | J24: =J20-J23 -> -50.246495 | K24: =K20-K23 -> -54.638435
A25: Taxes | C25: ='Historical Financials'!B33 -> 94.606 | D25: ='Historical Financials'!C33 -> 43.49 | E25: ='Historical Financials'!D33 -> 46.226 | F25: ='Historical Financials'!G33 -> 3.786 | G25: =MAX(0,G24)*Assumptions!$C$9 -> 0 | H25: =MAX(0,H24)*Assumptions!$C$9 -> 0 | I25: =MAX(0,I24)*Assumptions!$C$9 -> 0 | J25: =MAX(0,J24)*Assumptions!$C$9 -> 0 | K25: =MAX(0,K24)*Assumptions!$C$9 -> 0
A26: Net income (model basis) | C26: =C24-C25 -> 289.728 | D26: =D24-D25 -> 228.831 | E26: =E24-E25 -> 73.54 | F26: =F24-F25 -> 29.094 | G26: =G24-G25 -> -8.8577836 | H26: =H24-H25 -> -38.372762 | I26: =I24-I25 -> -54.460229 | J26: =J24-J25 -> -50.246495 | K26: =K24-K25 -> -54.638435
A27: Free cash flow build ($M)
A28: Capex | C28: ='Historical Financials'!B35 -> 35.207 | D28: ='Historical Financials'!C35 -> 44.775 | E28: ='Historical Financials'!D35 -> 33.303 | F28: ='Historical Financials'!G35 -> 28.21 | G28: =G13*CHOOSE(Assumptions!$C$10,Assumptions!$C$75,Assumptions!$C$94,Assumptions!$C$113) -> 26.864145 | H28: =H13*CHOOSE(Assumptions!$C$10,Assumptions!$C$75,Assumptions!$C$94,Assumptions!$C$113) -> 24.983655 | I28: =I13*CHOOSE(Assumptions!$C$10,Assumptions!$C$75,Assumptions!$C$94,Assumptions!$C$113) -> 23.484636 | J28: =J13*CHOOSE(Assumptions!$C$10,Assumptions!$C$75,Assumptions!$C$94,Assumptions!$C$113) -> 22.310404 | K28: =K13*CHOOSE(Assumptions!$C$10,Assumptions!$C$75,Assumptions!$C$94,Assumptions!$C$113) -> 21.194884
A29: Working capital & other cash items (+ = outflow) | C29: ='Historical Financials'!B38 -> 218.876 | D29: ='Historical Financials'!C38 -> -22.718 | E29: ='Historical Financials'!D38 -> -112.375 | F29: ='Historical Financials'!G38 -> -79.987 | G29: =CHOOSE(Assumptions!$C$10,Assumptions!$C$76,Assumptions!$C$95,Assumptions!$C$114)*(G13-F13)+CHOOSE(Assumptions!$C$10,Assumptions!$C$77,Assumptions!$C$96,Assumptions!$C$115)*G13 -> 10.332364 | H29: =CHOOSE(Assumptions!$C$10,Assumptions!$C$76,Assumptions!$C$95,Assumptions!$C$114)*(H13-G13)+CHOOSE(Assumptions!$C$10,Assumptions!$C$77,Assumptions!$C$96,Assumptions!$C$115)*H13 -> 9.6090981 | I29: =CHOOSE(Assumptions!$C$10,Assumptions!$C$76,Assumptions!$C$95,Assumptions!$C$114)*(I13-H13)+CHOOSE(Assumptions!$C$10,Assumptions!$C$77,Assumptions!$C$96,Assumptions!$C$115)*I13 -> 9.0325523 | J29: =CHOOSE(Assumptions!$C$10,Assumptions!$C$76,Assumptions!$C$95,Assumptions!$C$114)*(J13-I13)+CHOOSE(Assumptions!$C$10,Assumptions!$C$77,Assumptions!$C$96,Assumptions!$C$115)*J13 -> 8.5809246 | K29: =CHOOSE(Assumptions!$C$10,Assumptions!$C$76,Assumptions!$C$95,Assumptions!$C$114)*(K13-J13)+CHOOSE(Assumptions!$C$10,Assumptions!$C$77,Assumptions!$C$96,Assumptions!$C$115)*K13 -> 8.1518784
A30: Free cash flow (NI + D&A + SBC + PIK − capex − ΔNWC/other) | C30: ='Historical Financials'!B37 -> 168.712 | D30: ='Historical Financials'!C37 -> 330.84 | E30: ='Historical Financials'!D37 -> 272.367 | F30: ='Historical Financials'!G37 -> 190.523 | G30: =G26+G18+G19+G22-G28-G29 -> 54.825547 | H30: =H26+H18+H19+H22-H28-H29 -> 20.852736 | I30: =I26+I18+I19+I22-I28-I29 -> 1.2117393 | J30: =J26+J18+J19+J22-J28-J29 -> 2.6418742 | K30: =K26+K18+K19+K22-K28-K29 -> -4.394484

Sheet Debt Schedule
A1: Debt Schedule — tranche roll-forward, rates, PIK, refinancing test, cash sweep
A2: ="AMC Networks (AMC Global Media) · PUBLIC DATA CASE · HYPOTHETICAL INVESTMENT TERMS · Active scenario: "&Assumptions!$D$10 -> AMC Networks (AMC Global Media) · PUBLIC DATA CASE · HYPOTHETICAL INVESTMENT TERMS · Active scenario: Downside
A4: $M | C4: FY2023A | D4: FY2024A | E4: FY2025A | F4: LTM Jun-26 | G4: LTM Jun-27E | H4: LTM Jun-28E | I4: LTM Jun-29E | J4: LTM Jun-30E | K4: LTM Jun-31E
A6: Rates & market-access (refinancing) test
A7: Base rate (SOFR) | G7: =Assumptions!$G$52 -> 0.039 | H7: =Assumptions!$H$52 -> 0.0375 | I7: =Assumptions!$I$52 -> 0.035 | J7: =Assumptions!$J$52 -> 0.035 | K7: =Assumptions!$K$52 -> 0.035
A8: Floating-rate shock (selected scenario) | C8: =CHOOSE(Assumptions!$C$10,Assumptions!$C$78,Assumptions!$C$97,Assumptions!$C$116) -> 0.015
A9: Refinancing rate (selected scenario) | C9: =CHOOSE(Assumptions!$C$10,Assumptions!$C$79,Assumptions!$C$98,Assumptions!$C$117) -> 0.13
A10: Max net leverage to refinance | C10: =CHOOSE(Assumptions!$C$10,Assumptions!$C$80,Assumptions!$C$99,Assumptions!$C$118) -> 5.5
A11: Min pro-forma coverage to refinance | C11: =CHOOSE(Assumptions!$C$10,Assumptions!$C$81,Assumptions!$C$100,Assumptions!$C$119) -> 1.5
A12: Beginning total debt | G12: =G17+G30+G43 -> 1735.554 | H12: =H17+H30+H43 -> 1735.554 | I12: =I17+I30+I43 -> 1735.554 | J12: =J17+J30+J43 -> 1315.098 | K12: =K17+K30+K43 -> 1315.098
A13: Beginning cash | G13: ='Cash Flow'!F19 -> 463.996 | H13: ='Cash Flow'!G19 -> 518.82155 | I13: ='Cash Flow'!H19 -> 539.67428 | J13: ='Cash Flow'!I19 -> 120.43002 | K13: ='Cash Flow'!J19 -> 123.0719
A14: Pro-forma interest for refinancing test | G14: =G17*IF(G18=1,$C$9,IF(Assumptions!$I$56=1,MAX(G7,Assumptions!$G$56)+Assumptions!$F$56+$C$8,Assumptions!$E$56))+G30*IF(G31=1,$C$9,IF(Assumptions!$I$57=1,MAX(G7,Assumptions!$G$57)+Assumptions!$F$57+$C$8,Assumptions!$E$57))+G43*IF(G44=1,$C$9,IF(Assumptions!$I$58=1,MAX(G7,Assumptions!$G$58)+Assumptions!$F$58+$C$8,Assumptions!$E$58)) -> 155.95467 | H14: =H17*IF(OR(H18=1,Recovery!G35=1),$C$9,IF(Assumptions!$I$56=1,MAX(H7,Assumptions!$G$56)+Assumptions!$F$56+$C$8,Assumptions!$E$56))+H30*IF(OR(H31=1,Recovery!G36=1),$C$9,IF(Assumptions!$I$57=1,MAX(H7,Assumptions!$G$57)+Assumptions!$F$57+$C$8,Assumptions!$E$57))+H43*IF(OR(H44=1,Recovery!G37=1),$C$9,IF(Assumptions!$I$58=1,MAX(H7,Assumptions!$G$58)+Assumptions!$F$58+$C$8,Assumptions!$E$58)) -> 155.95467 | I14: =I17*IF(OR(I18=1,Recovery!H35=1),$C$9,IF(Assumptions!$I$56=1,MAX(I7,Assumptions!$G$56)+Assumptions!$F$56+$C$8,Assumptions!$E$56))+I30*IF(OR(I31=1,Recovery!H36=1),$C$9,IF(Assumptions!$I$57=1,MAX(I7,Assumptions!$G$57)+Assumptions!$F$57+$C$8,Assumptions!$E$57))+I43*IF(OR(I44=1,Recovery!H37=1),$C$9,IF(Assumptions!$I$58=1,MAX(I7,Assumptions!$G$58)+Assumptions!$F$58+$C$8,Assumptions!$E$58)) -> 192.74457 | J14: =J17*IF(OR(J18=1,Recovery!I35=1),$C$9,IF(Assumptions!$I$56=1,MAX(J7,Assumptions!$G$56)+Assumptions!$F$56+$C$8,Assumptions!$E$56))+J30*IF(OR(J31=1,Recovery!I36=1),$C$9,IF(Assumptions!$I$57=1,MAX(J7,Assumptions!$G$57)+Assumptions!$F$57+$C$8,Assumptions!$E$57))+J43*IF(OR(J44=1,Recovery!I37=1),$C$9,IF(Assumptions!$I$58=1,MAX(J7,Assumptions!$G$58)+Assumptions!$F$58+$C$8,Assumptions!$E$58)) -> 138.08529 | K14: =K17*IF(OR(K18=1,Recovery!J35=1),$C$9,IF(Assumptions!$I$56=1,MAX(K7,Assumptions!$G$56)+Assumptions!$F$56+$C$8,Assumptions!$E$56))+K30*IF(OR(K31=1,Recovery!J36=1),$C$9,IF(Assumptions!$I$57=1,MAX(K7,Assumptions!$G$57)+Assumptions!$F$57+$C$8,Assumptions!$E$57))+K43*IF(OR(K44=1,Recovery!J37=1),$C$9,IF(Assumptions!$I$58=1,MAX(K7,Assumptions!$G$58)+Assumptions!$F$58+$C$8,Assumptions!$E$58)) -> 138.08529
A15: Market access to refinance? (1 = yes) | G15: =IF('Operating Model'!G17<=0,0,IF(AND((G12-G13)/'Operating Model'!G17<=$C$10,'Operating Model'!G17/G14>=$C$11),1,0)) -> 1 | H15: =IF('Operating Model'!H17<=0,0,IF(AND((H12-H13)/'Operating Model'!H17<=$C$10,'Operating Model'!H17/H14>=$C$11),1,0)) -> 0 | I15: =IF('Operating Model'!I17<=0,0,IF(AND((I12-I13)/'Operating Model'!I17<=$C$10,'Operating Model'!I17/I14>=$C$11),1,0)) -> 0 | J15: =IF('Operating Model'!J17<=0,0,IF(AND((J12-J13)/'Operating Model'!J17<=$C$10,'Operating Model'!J17/J14>=$C$11),1,0)) -> 0 | K15: =IF('Operating Model'!K17<=0,0,IF(AND((K12-K13)/'Operating Model'!K17<=$C$10,'Operating Model'!K17/K14>=$C$11),1,0)) -> 0
A16: Tranche 1: 10.50% Senior Secured Notes due 2032
A17: Beginning balance | G17: =F28 -> 1315.098 | H17: =G28 -> 1315.098 | I17: =H28 -> 1315.098 | J17: =I28 -> 1315.098 | K17: =J28 -> 1315.098
A18: Maturing this period? (1 = yes) | G18: =IF('Operating Model'!G7=Assumptions!$K$56,1,0) -> 0 | H18: =IF('Operating Model'!H7=Assumptions!$K$56,1,0) -> 0 | I18: =IF('Operating Model'!I7=Assumptions!$K$56,1,0) -> 0 | J18: =IF('Operating Model'!J7=Assumptions!$K$56,1,0) -> 0 | K18: =IF('Operating Model'!K7=Assumptions!$K$56,1,0) -> 0
A20: All-in interest rate applied | G20: =IF(Assumptions!$I$56=1,MAX(G7,Assumptions!$G$56)+Assumptions!$F$56+$C$8,Assumptions!$E$56) -> 0.105 | H20: =IF(Recovery!G35=1,$C$9,IF(Assumptions!$I$56=1,MAX(H7,Assumptions!$G$56)+Assumptions!$F$56+$C$8,Assumptions!$E$56)) -> 0.105 | I20: =IF(Recovery!H35=1,$C$9,IF(Assumptions!$I$56=1,MAX(I7,Assumptions!$G$56)+Assumptions!$F$56+$C$8,Assumptions!$E$56)) -> 0.105 | J20: =IF(Recovery!I35=1,$C$9,IF(Assumptions!$I$56=1,MAX(J7,Assumptions!$G$56)+Assumptions!$F$56+$C$8,Assumptions!$E$56)) -> 0.105 | K20: =IF(Recovery!J35=1,$C$9,IF(Assumptions!$I$56=1,MAX(K7,Assumptions!$G$56)+Assumptions!$F$56+$C$8,Assumptions!$E$56)) -> 0.105
A21: Cash interest expense | G21: =G17*G20 -> 138.08529 | H21: =H17*H20 -> 138.08529 | I21: =I17*I20 -> 138.08529 | J21: =J17*J20 -> 138.08529 | K21: =K17*K20 -> 138.08529
A22: PIK interest | G22: =G17*Assumptions!$H$56 -> 0 | H22: =H17*Assumptions!$H$56 -> 0 | I22: =I17*Assumptions!$H$56 -> 0 | J22: =J17*Assumptions!$H$56 -> 0 | K22: =K17*Assumptions!$H$56 -> 0
A23: Mandatory amortization | G23: =MIN(G17,Assumptions!$L$56*Assumptions!$C$56) -> 0 | H23: =MIN(H17,Assumptions!$L$56*Assumptions!$C$56) -> 0 | I23: =MIN(I17,Assumptions!$L$56*Assumptions!$C$56) -> 0 | J23: =MIN(J17,Assumptions!$L$56*Assumptions!$C$56) -> 0 | K23: =MIN(K17,Assumptions!$L$56*Assumptions!$C$56) -> 0
A24: New borrowing (revolver draw) | G24: =IF(AND(Assumptions!$P$56=1,'Operating Model'!G7<Assumptions!$K$56),MIN(MAX(0,-'Cash Flow'!G11),MAX(0,Assumptions!$D$56-G17)),0) -> 0 | H24: =IF(AND(Assumptions!$P$56=1,OR('Operating Model'!H7<Assumptions!$K$56,Recovery!G35=1)),MIN(MAX(0,-'Cash Flow'!H11),MAX(0,Assumptions!$D$56-H17)),0) -> 0 | I24: =IF(AND(Assumptions!$P$56=1,OR('Operating Model'!I7<Assumptions!$K$56,Recovery!H35=1)),MIN(MAX(0,-'Cash Flow'!I11),MAX(0,Assumptions!$D$56-I17)),0) -> 0 | J24: =IF(AND(Assumptions!$P$56=1,OR('Operating Model'!J7<Assumptions!$K$56,Recovery!I35=1)),MIN(MAX(0,-'Cash Flow'!J11),MAX(0,Assumptions!$D$56-J17)),0) -> 0 | K24: =IF(AND(Assumptions!$P$56=1,OR('Operating Model'!K7<Assumptions!$K$56,Recovery!J35=1)),MIN(MAX(0,-'Cash Flow'!K11),MAX(0,Assumptions!$D$56-K17)),0) -> 0
A25: Repayment at maturity (from available cash) | G25: =G18*MIN(G17-G23+G22,MAX(0,'Cash Flow'!G13-Assumptions!$C$12*G15)) -> 0 | H25: =H18*MIN(H17-H23+H22,MAX(0,'Cash Flow'!H13-Assumptions!$C$12*H15)) -> 0 | I25: =I18*MIN(I17-I23+I22,MAX(0,'Cash Flow'!I13-Assumptions!$C$12*I15)) -> 0 | J25: =J18*MIN(J17-J23+J22,MAX(0,'Cash Flow'!J13-Assumptions!$C$12*J15)) -> 0 | K25: =K18*MIN(K17-K23+K22,MAX(0,'Cash Flow'!K13-Assumptions!$C$12*K15)) -> 0
A26: Optional repayment (cash sweep) | G26: =Assumptions!$N$56*MIN(G17+G24+G22-G23-G25,MAX(0,'Cash Flow'!G17)) -> 0 | H26: =Assumptions!$N$56*MIN(H17+H24+H22-H23-H25,MAX(0,'Cash Flow'!H17)) -> 0 | I26: =Assumptions!$N$56*MIN(I17+I24+I22-I23-I25,MAX(0,'Cash Flow'!I17)) -> 0 | J26: =Assumptions!$N$56*MIN(J17+J24+J22-J23-J25,MAX(0,'Cash Flow'!J17)) -> 0 | K26: =Assumptions!$N$56*MIN(K17+K24+K22-K23-K25,MAX(0,'Cash Flow'!K17)) -> 0
A27: Unpaid at maturity (no refinancing, insufficient cash) | G27: =G18*(1-G15)*(G17-G23+G22-G25) -> 0 | H27: =H18*(1-H15)*(H17-H23+H22-H25) -> 0 | I27: =I18*(1-I15)*(I17-I23+I22-I25) -> 0 | J27: =J18*(1-J15)*(J17-J23+J22-J25) -> 0 | K27: =K18*(1-K15)*(K17-K23+K22-K25) -> 0
A28: Ending balance | F28: =Assumptions!$C$56 -> 1315.098 | G28: =G17+G24+G22-G23-G25-G26 -> 1315.098 | H28: =H17+H24+H22-H23-H25-H26 -> 1315.098 | I28: =I17+I24+I22-I23-I25-I26 -> 1315.098 | J28: =J17+J24+J22-J23-J25-J26 -> 1315.098 | K28: =K17+K24+K22-K23-K25-K26 -> 1315.098
A29: Tranche 2: 4.25% Senior Notes due 2029
A30: Beginning balance | G30: =F41 -> 276.706 | H30: =G41 -> 276.706 | I30: =H41 -> 276.706 | J30: =I41 -> 0 | K30: =J41 -> 0
A31: Maturing this period? (1 = yes) | G31: =IF('Operating Model'!G7=Assumptions!$K$57,1,0) -> 0 | H31: =IF('Operating Model'!H7=Assumptions!$K$57,1,0) -> 0 | I31: =IF('Operating Model'!I7=Assumptions!$K$57,1,0) -> 1 | J31: =IF('Operating Model'!J7=Assumptions!$K$57,1,0) -> 0 | K31: =IF('Operating Model'!K7=Assumptions!$K$57,1,0) -> 0
A33: All-in interest rate applied | G33: =IF(Assumptions!$I$57=1,MAX(G7,Assumptions!$G$57)+Assumptions!$F$57+$C$8,Assumptions!$E$57) -> 0.0425 | H33: =IF(Recovery!G36=1,$C$9,IF(Assumptions!$I$57=1,MAX(H7,Assumptions!$G$57)+Assumptions!$F$57+$C$8,Assumptions!$E$57)) -> 0.0425 | I33: =IF(Recovery!H36=1,$C$9,IF(Assumptions!$I$57=1,MAX(I7,Assumptions!$G$57)+Assumptions!$F$57+$C$8,Assumptions!$E$57)) -> 0.0425 | J33: =IF(Recovery!I36=1,$C$9,IF(Assumptions!$I$57=1,MAX(J7,Assumptions!$G$57)+Assumptions!$F$57+$C$8,Assumptions!$E$57)) -> 0.0425 | K33: =IF(Recovery!J36=1,$C$9,IF(Assumptions!$I$57=1,MAX(K7,Assumptions!$G$57)+Assumptions!$F$57+$C$8,Assumptions!$E$57)) -> 0.0425
A34: Cash interest expense | G34: =G30*G33 -> 11.760005 | H34: =H30*H33 -> 11.760005 | I34: =I30*I33 -> 11.760005 | J34: =J30*J33 -> 0 | K34: =K30*K33 -> 0
A35: PIK interest | G35: =G30*Assumptions!$H$57 -> 0 | H35: =H30*Assumptions!$H$57 -> 0 | I35: =I30*Assumptions!$H$57 -> 0 | J35: =J30*Assumptions!$H$57 -> 0 | K35: =K30*Assumptions!$H$57 -> 0
A36: Mandatory amortization | G36: =MIN(G30,Assumptions!$L$57*Assumptions!$C$57) -> 0 | H36: =MIN(H30,Assumptions!$L$57*Assumptions!$C$57) -> 0 | I36: =MIN(I30,Assumptions!$L$57*Assumptions!$C$57) -> 0 | J36: =MIN(J30,Assumptions!$L$57*Assumptions!$C$57) -> 0 | K36: =MIN(K30,Assumptions!$L$57*Assumptions!$C$57) -> 0
A37: New borrowing (revolver draw) | G37: =IF(AND(Assumptions!$P$57=1,'Operating Model'!G7<Assumptions!$K$57),MIN(MAX(0,-'Cash Flow'!G11),MAX(0,Assumptions!$D$57-G30)),0) -> 0 | H37: =IF(AND(Assumptions!$P$57=1,OR('Operating Model'!H7<Assumptions!$K$57,Recovery!G36=1)),MIN(MAX(0,-'Cash Flow'!H11),MAX(0,Assumptions!$D$57-H30)),0) -> 0 | I37: =IF(AND(Assumptions!$P$57=1,OR('Operating Model'!I7<Assumptions!$K$57,Recovery!H36=1)),MIN(MAX(0,-'Cash Flow'!I11),MAX(0,Assumptions!$D$57-I30)),0) -> 0 | J37: =IF(AND(Assumptions!$P$57=1,OR('Operating Model'!J7<Assumptions!$K$57,Recovery!I36=1)),MIN(MAX(0,-'Cash Flow'!J11),MAX(0,Assumptions!$D$57-J30)),0) -> 0 | K37: =IF(AND(Assumptions!$P$57=1,OR('Operating Model'!K7<Assumptions!$K$57,Recovery!J36=1)),MIN(MAX(0,-'Cash Flow'!K11),MAX(0,Assumptions!$D$57-K30)),0) -> 0
A38: Repayment at maturity (from available cash) | G38: =G31*MIN(G30-G36+G35,MAX(0,'Cash Flow'!G13-Assumptions!$C$12*G15-G25)) -> 0 | H38: =H31*MIN(H30-H36+H35,MAX(0,'Cash Flow'!H13-Assumptions!$C$12*H15-H25)) -> 0 | I38: =I31*MIN(I30-I36+I35,MAX(0,'Cash Flow'!I13-Assumptions!$C$12*I15-I25)) -> 276.706 | J38: =J31*MIN(J30-J36+J35,MAX(0,'Cash Flow'!J13-Assumptions!$C$12*J15-J25)) -> 0 | K38: =K31*MIN(K30-K36+K35,MAX(0,'Cash Flow'!K13-Assumptions!$C$12*K15-K25)) -> 0
A39: Optional repayment (cash sweep) | G39: =Assumptions!$N$57*MIN(G30+G37+G35-G36-G38,MAX(0,'Cash Flow'!G17-G26)) -> 0 | H39: =Assumptions!$N$57*MIN(H30+H37+H35-H36-H38,MAX(0,'Cash Flow'!H17-H26)) -> 0 | I39: =Assumptions!$N$57*MIN(I30+I37+I35-I36-I38,MAX(0,'Cash Flow'!I17-I26)) -> 0 | J39: =Assumptions!$N$57*MIN(J30+J37+J35-J36-J38,MAX(0,'Cash Flow'!J17-J26)) -> 0 | K39: =Assumptions!$N$57*MIN(K30+K37+K35-K36-K38,MAX(0,'Cash Flow'!K17-K26)) -> 0
A40: Unpaid at maturity (no refinancing, insufficient cash) | G40: =G31*(1-G15)*(G30-G36+G35-G38) -> 0 | H40: =H31*(1-H15)*(H30-H36+H35-H38) -> 0 | I40: =I31*(1-I15)*(I30-I36+I35-I38) -> 0 | J40: =J31*(1-J15)*(J30-J36+J35-J38) -> 0 | K40: =K31*(1-K15)*(K30-K36+K35-K38) -> 0
A41: Ending balance | F41: =Assumptions!$C$57 -> 276.706 | G41: =G30+G37+G35-G36-G38-G39 -> 276.706 | H41: =H30+H37+H35-H36-H38-H39 -> 276.706 | I41: =I30+I37+I35-I36-I38-I39 -> 0 | J41: =J30+J37+J35-J36-J38-J39 -> 0 | K41: =K30+K37+K35-K36-K38-K39 -> 0
A42: Tranche 3: 4.25% Convertible Senior Notes due 2029
A43: Beginning balance | G43: =F54 -> 143.75 | H43: =G54 -> 143.75 | I43: =H54 -> 143.75 | J43: =I54 -> 0 | K43: =J54 -> 0
A44: Maturing this period? (1 = yes) | G44: =IF('Operating Model'!G7=Assumptions!$K$58,1,0) -> 0 | H44: =IF('Operating Model'!H7=Assumptions!$K$58,1,0) -> 0 | I44: =IF('Operating Model'!I7=Assumptions!$K$58,1,0) -> 1 | J44: =IF('Operating Model'!J7=Assumptions!$K$58,1,0) -> 0 | K44: =IF('Operating Model'!K7=Assumptions!$K$58,1,0) -> 0
A46: All-in interest rate applied | G46: =IF(Assumptions!$I$58=1,MAX(G7,Assumptions!$G$58)+Assumptions!$F$58+$C$8,Assumptions!$E$58) -> 0.0425 | H46: =IF(Recovery!G37=1,$C$9,IF(Assumptions!$I$58=1,MAX(H7,Assumptions!$G$58)+Assumptions!$F$58+$C$8,Assumptions!$E$58)) -> 0.0425 | I46: =IF(Recovery!H37=1,$C$9,IF(Assumptions!$I$58=1,MAX(I7,Assumptions!$G$58)+Assumptions!$F$58+$C$8,Assumptions!$E$58)) -> 0.0425 | J46: =IF(Recovery!I37=1,$C$9,IF(Assumptions!$I$58=1,MAX(J7,Assumptions!$G$58)+Assumptions!$F$58+$C$8,Assumptions!$E$58)) -> 0.0425 | K46: =IF(Recovery!J37=1,$C$9,IF(Assumptions!$I$58=1,MAX(K7,Assumptions!$G$58)+Assumptions!$F$58+$C$8,Assumptions!$E$58)) -> 0.0425
A47: Cash interest expense | G47: =G43*G46 -> 6.109375 | H47: =H43*H46 -> 6.109375 | I47: =I43*I46 -> 6.109375 | J47: =J43*J46 -> 0 | K47: =K43*K46 -> 0
A48: PIK interest | G48: =G43*Assumptions!$H$58 -> 0 | H48: =H43*Assumptions!$H$58 -> 0 | I48: =I43*Assumptions!$H$58 -> 0 | J48: =J43*Assumptions!$H$58 -> 0 | K48: =K43*Assumptions!$H$58 -> 0
A49: Mandatory amortization | G49: =MIN(G43,Assumptions!$L$58*Assumptions!$C$58) -> 0 | H49: =MIN(H43,Assumptions!$L$58*Assumptions!$C$58) -> 0 | I49: =MIN(I43,Assumptions!$L$58*Assumptions!$C$58) -> 0 | J49: =MIN(J43,Assumptions!$L$58*Assumptions!$C$58) -> 0 | K49: =MIN(K43,Assumptions!$L$58*Assumptions!$C$58) -> 0
A50: New borrowing (revolver draw) | G50: =IF(AND(Assumptions!$P$58=1,'Operating Model'!G7<Assumptions!$K$58),MIN(MAX(0,-'Cash Flow'!G11),MAX(0,Assumptions!$D$58-G43)),0) -> 0 | H50: =IF(AND(Assumptions!$P$58=1,OR('Operating Model'!H7<Assumptions!$K$58,Recovery!G37=1)),MIN(MAX(0,-'Cash Flow'!H11),MAX(0,Assumptions!$D$58-H43)),0) -> 0 | I50: =IF(AND(Assumptions!$P$58=1,OR('Operating Model'!I7<Assumptions!$K$58,Recovery!H37=1)),MIN(MAX(0,-'Cash Flow'!I11),MAX(0,Assumptions!$D$58-I43)),0) -> 0 | J50: =IF(AND(Assumptions!$P$58=1,OR('Operating Model'!J7<Assumptions!$K$58,Recovery!I37=1)),MIN(MAX(0,-'Cash Flow'!J11),MAX(0,Assumptions!$D$58-J43)),0) -> 0 | K50: =IF(AND(Assumptions!$P$58=1,OR('Operating Model'!K7<Assumptions!$K$58,Recovery!J37=1)),MIN(MAX(0,-'Cash Flow'!K11),MAX(0,Assumptions!$D$58-K43)),0) -> 0
A51: Repayment at maturity (from available cash) | G51: =G44*MIN(G43-G49+G48,MAX(0,'Cash Flow'!G13-Assumptions!$C$12*G15-G25-G38)) -> 0 | H51: =H44*MIN(H43-H49+H48,MAX(0,'Cash Flow'!H13-Assumptions!$C$12*H15-H25-H38)) -> 0 | I51: =I44*MIN(I43-I49+I48,MAX(0,'Cash Flow'!I13-Assumptions!$C$12*I15-I25-I38)) -> 143.75 | J51: =J44*MIN(J43-J49+J48,MAX(0,'Cash Flow'!J13-Assumptions!$C$12*J15-J25-J38)) -> 0 | K51: =K44*MIN(K43-K49+K48,MAX(0,'Cash Flow'!K13-Assumptions!$C$12*K15-K25-K38)) -> 0
A52: Optional repayment (cash sweep) | G52: =Assumptions!$N$58*MIN(G43+G50+G48-G49-G51,MAX(0,'Cash Flow'!G17-G26-G39)) -> 0 | H52: =Assumptions!$N$58*MIN(H43+H50+H48-H49-H51,MAX(0,'Cash Flow'!H17-H26-H39)) -> 0 | I52: =Assumptions!$N$58*MIN(I43+I50+I48-I49-I51,MAX(0,'Cash Flow'!I17-I26-I39)) -> 0 | J52: =Assumptions!$N$58*MIN(J43+J50+J48-J49-J51,MAX(0,'Cash Flow'!J17-J26-J39)) -> 0 | K52: =Assumptions!$N$58*MIN(K43+K50+K48-K49-K51,MAX(0,'Cash Flow'!K17-K26-K39)) -> 0
A53: Unpaid at maturity (no refinancing, insufficient cash) | G53: =G44*(1-G15)*(G43-G49+G48-G51) -> 0 | H53: =H44*(1-H15)*(H43-H49+H48-H51) -> 0 | I53: =I44*(1-I15)*(I43-I49+I48-I51) -> 0 | J53: =J44*(1-J15)*(J43-J49+J48-J51) -> 0 | K53: =K44*(1-K15)*(K43-K49+K48-K51) -> 0
A54: Ending balance | F54: =Assumptions!$C$58 -> 143.75 | G54: =G43+G50+G48-G49-G51-G52 -> 143.75 | H54: =H43+H50+H48-H49-H51-H52 -> 143.75 | I54: =I43+I50+I48-I49-I51-I52 -> 0 | J54: =J43+J50+J48-J49-J51-J52 -> 0 | K54: =K43+K50+K48-K49-K51-K52 -> 0
A55: Totals
A56: Total debt — ending | F56: =F28+F41+F54 -> 1735.554 | G56: =G28+G41+G54 -> 1735.554 | H56: =H28+H41+H54 -> 1735.554 | I56: =I28+I41+I54 -> 1315.098 | J56: =J28+J41+J54 -> 1315.098 | K56: =K28+K41+K54 -> 1315.098
A57: Contractual maturities by period (from maturity flags) | G57: =G18*Assumptions!$C$56+G31*Assumptions!$C$57+G44*Assumptions!$C$58 -> 0 | H57: =H18*Assumptions!$C$56+H31*Assumptions!$C$57+H44*Assumptions!$C$58 -> 0 | I57: =I18*Assumptions!$C$56+I31*Assumptions!$C$57+I44*Assumptions!$C$58 -> 420.456 | J57: =J18*Assumptions!$C$56+J31*Assumptions!$C$57+J44*Assumptions!$C$58 -> 0 | K57: =K18*Assumptions!$C$56+K31*Assumptions!$C$57+K44*Assumptions!$C$58 -> 0
A58: Refinancing risk engine — result per maturing tranche
A59: Tranche 1: balance at maturity | C59: =SUMPRODUCT($G$18:$K$18,$G$17:$K$17-$G$23:$K$23+$G$22:$K$22) -> 0
A60: Tranche 1: repaid from cash at maturity | C60: =SUMPRODUCT($G$18:$K$18,$G$25:$K$25) -> 0
A61: Tranche 1: refinancing test | C61: =IF(SUM($G$18:$K$18)=0,"n/a (beyond horizon)",IF(SUMPRODUCT($G$18:$K$18,$G$15:$K$15)>0,"REFINANCING PASS","REFINANCING FAILURE")) -> n/a (beyond horizon)
A62: Tranche 1: resolution | C62: =IF(SUM($G$18:$K$18)=0,"n/a",IF(C60>=C59-0.001,"Repaid from cash",IF(SUMPRODUCT($G$18:$K$18,$G$15:$K$15)>0,IF(C60>0,"Partly repaid; remainder refinanced","Refinanced"),IF(SUM($G$27:$K$27)>0.001,IF(C60>0,"Partial repayment; PAYMENT DEFAULT","PAYMENT DEFAULT"),"Repaid from cash")))) -> n/a
A63: Tranche 2: balance at maturity | C63: =SUMPRODUCT($G$31:$K$31,$G$30:$K$30-$G$36:$K$36+$G$35:$K$35) -> 276.706
A64: Tranche 2: repaid from cash at maturity | C64: =SUMPRODUCT($G$31:$K$31,$G$38:$K$38) -> 276.706
A65: Tranche 2: refinancing test | C65: =IF(SUM($G$31:$K$31)=0,"n/a (beyond horizon)",IF(SUMPRODUCT($G$31:$K$31,$G$15:$K$15)>0,"REFINANCING PASS","REFINANCING FAILURE")) -> REFINANCING FAILURE
A66: Tranche 2: resolution | C66: =IF(SUM($G$31:$K$31)=0,"n/a",IF(C64>=C63-0.001,"Repaid from cash",IF(SUMPRODUCT($G$31:$K$31,$G$15:$K$15)>0,IF(C64>0,"Partly repaid; remainder refinanced","Refinanced"),IF(SUM($G$40:$K$40)>0.001,IF(C64>0,"Partial repayment; PAYMENT DEFAULT","PAYMENT DEFAULT"),"Repaid from cash")))) -> Repaid from cash
A67: Tranche 3: balance at maturity | C67: =SUMPRODUCT($G$44:$K$44,$G$43:$K$43-$G$49:$K$49+$G$48:$K$48) -> 143.75
A68: Tranche 3: repaid from cash at maturity | C68: =SUMPRODUCT($G$44:$K$44,$G$51:$K$51) -> 143.75
A69: Tranche 3: refinancing test | C69: =IF(SUM($G$44:$K$44)=0,"n/a (beyond horizon)",IF(SUMPRODUCT($G$44:$K$44,$G$15:$K$15)>0,"REFINANCING PASS","REFINANCING FAILURE")) -> REFINANCING FAILURE
A70: Tranche 3: resolution | C70: =IF(SUM($G$44:$K$44)=0,"n/a",IF(C68>=C67-0.001,"Repaid from cash",IF(SUMPRODUCT($G$44:$K$44,$G$15:$K$15)>0,IF(C68>0,"Partly repaid; remainder refinanced","Refinanced"),IF(SUM($G$53:$K$53)>0.001,IF(C68>0,"Partial repayment; PAYMENT DEFAULT","PAYMENT DEFAULT"),"Repaid from cash")))) -> Repaid from cash
A71: Refinancing failures (count of maturing tranches) | C71: =IF(C61="REFINANCING FAILURE",1,0)+IF(C65="REFINANCING FAILURE",1,0)+IF(C69="REFINANCING FAILURE",1,0) -> 2

Sheet Cash Flow
A1: Cash Flow & Liquidity — cash waterfall and default test
A2: ="AMC Networks (AMC Global Media) · PUBLIC DATA CASE · HYPOTHETICAL INVESTMENT TERMS · Active scenario: "&Assumptions!$D$10 -> AMC Networks (AMC Global Media) · PUBLIC DATA CASE · HYPOTHETICAL INVESTMENT TERMS · Active scenario: Downside
A4: $M | C4: FY2023A | D4: FY2024A | E4: FY2025A | F4: LTM Jun-26 | G4: LTM Jun-27E | H4: LTM Jun-28E | I4: LTM Jun-29E | J4: LTM Jun-30E | K4: LTM Jun-31E
A6: Cash flow & liquidity waterfall ($M)
A7: Beginning cash | G7: =F19 -> 463.996 | H7: =G19 -> 518.82155 | I7: =H19 -> 539.67428 | J7: =I19 -> 120.43002 | K7: =J19 -> 123.0719
A8: Free cash flow (from Operating Model) | G8: ='Operating Model'!G30 -> 54.825547 | H8: ='Operating Model'!H30 -> 20.852736 | I8: ='Operating Model'!I30 -> 1.2117393 | J8: ='Operating Model'!J30 -> 2.6418742 | K8: ='Operating Model'!K30 -> -4.394484
A9: Plus: net asset-sale proceeds | G9: =CHOOSE(Assumptions!$C$10,Assumptions!$G$74,Assumptions!$G$93,Assumptions!$G$112) -> 0 | H9: =CHOOSE(Assumptions!$C$10,Assumptions!$H$74,Assumptions!$H$93,Assumptions!$H$112) -> 0 | I9: =CHOOSE(Assumptions!$C$10,Assumptions!$I$74,Assumptions!$I$93,Assumptions!$I$112) -> 0 | J9: =CHOOSE(Assumptions!$C$10,Assumptions!$J$74,Assumptions!$J$93,Assumptions!$J$112) -> 0 | K9: =CHOOSE(Assumptions!$C$10,Assumptions!$K$74,Assumptions!$K$93,Assumptions!$K$112) -> 0
A10: Less: mandatory amortization | G10: ='Debt Schedule'!G23+'Debt Schedule'!G36+'Debt Schedule'!G49 -> 0 | H10: ='Debt Schedule'!H23+'Debt Schedule'!H36+'Debt Schedule'!H49 -> 0 | I10: ='Debt Schedule'!I23+'Debt Schedule'!I36+'Debt Schedule'!I49 -> 0 | J10: ='Debt Schedule'!J23+'Debt Schedule'!J36+'Debt Schedule'!J49 -> 0 | K10: ='Debt Schedule'!K23+'Debt Schedule'!K36+'Debt Schedule'!K49 -> 0
A11: Cash after mandatory debt service | G11: =G7+G8+G9-G10 -> 518.82155 | H11: =H7+H8+H9-H10 -> 539.67428 | I11: =I7+I8+I9-I10 -> 540.88602 | J11: =J7+J8+J9-J10 -> 123.0719 | K11: =K7+K8+K9-K10 -> 118.67741
A12: Plus: revolver draw | G12: ='Debt Schedule'!G24+'Debt Schedule'!G37+'Debt Schedule'!G50 -> 0 | H12: ='Debt Schedule'!H24+'Debt Schedule'!H37+'Debt Schedule'!H50 -> 0 | I12: ='Debt Schedule'!I24+'Debt Schedule'!I37+'Debt Schedule'!I50 -> 0 | J12: ='Debt Schedule'!J24+'Debt Schedule'!J37+'Debt Schedule'!J50 -> 0 | K12: ='Debt Schedule'!K24+'Debt Schedule'!K37+'Debt Schedule'!K50 -> 0
A13: Cash available for maturities | G13: =G11+G12 -> 518.82155 | H13: =H11+H12 -> 539.67428 | I13: =I11+I12 -> 540.88602 | J13: =J11+J12 -> 123.0719 | K13: =K11+K12 -> 118.67741
A14: Less: repayment of maturing debt | G14: ='Debt Schedule'!G25+'Debt Schedule'!G38+'Debt Schedule'!G51 -> 0 | H14: ='Debt Schedule'!H25+'Debt Schedule'!H38+'Debt Schedule'!H51 -> 0 | I14: ='Debt Schedule'!I25+'Debt Schedule'!I38+'Debt Schedule'!I51 -> 420.456 | J14: ='Debt Schedule'!J25+'Debt Schedule'!J38+'Debt Schedule'!J51 -> 0 | K14: ='Debt Schedule'!K25+'Debt Schedule'!K38+'Debt Schedule'!K51 -> 0
A15: Cash before sweep | G15: =G13-G14 -> 518.82155 | H15: =H13-H14 -> 539.67428 | I15: =I13-I14 -> 120.43002 | J15: =J13-J14 -> 123.0719 | K15: =K13-K14 -> 118.67741
A16: Funding gap (shortfall after cash & revolver) | G16: =MAX(0,-G15) -> 0 | H16: =MAX(0,-H15) -> 0 | I16: =MAX(0,-I15) -> 0 | J16: =MAX(0,-J15) -> 0 | K16: =MAX(0,-K15) -> 0
A17: Excess cash available for sweep | G17: =MAX(0,G15-Assumptions!$C$12)*Assumptions!$C$13 -> 0 | H17: =MAX(0,H15-Assumptions!$C$12)*Assumptions!$C$13 -> 0 | I17: =MAX(0,I15-Assumptions!$C$12)*Assumptions!$C$13 -> 0 | J17: =MAX(0,J15-Assumptions!$C$12)*Assumptions!$C$13 -> 0 | K17: =MAX(0,K15-Assumptions!$C$12)*Assumptions!$C$13 -> 0
A18: Less: optional repayment (cash sweep) | G18: ='Debt Schedule'!G26+'Debt Schedule'!G39+'Debt Schedule'!G52 -> 0 | H18: ='Debt Schedule'!H26+'Debt Schedule'!H39+'Debt Schedule'!H52 -> 0 | I18: ='Debt Schedule'!I26+'Debt Schedule'!I39+'Debt Schedule'!I52 -> 0 | J18: ='Debt Schedule'!J26+'Debt Schedule'!J39+'Debt Schedule'!J52 -> 0 | K18: ='Debt Schedule'!K26+'Debt Schedule'!K39+'Debt Schedule'!K52 -> 0
A19: Ending cash | F19: =Assumptions!$C$11 -> 463.996 | G19: =G15-G18 -> 518.82155 | H19: =H15-H18 -> 539.67428 | I19: =I15-I18 -> 120.43002 | J19: =J15-J18 -> 123.0719 | K19: =K15-K18 -> 118.67741
A20: Unpaid maturities (balance left outstanding) | G20: ='Debt Schedule'!G27+'Debt Schedule'!G40+'Debt Schedule'!G53 -> 0 | H20: ='Debt Schedule'!H27+'Debt Schedule'!H40+'Debt Schedule'!H53 -> 0 | I20: ='Debt Schedule'!I27+'Debt Schedule'!I40+'Debt Schedule'!I53 -> 0 | J20: ='Debt Schedule'!J27+'Debt Schedule'!J40+'Debt Schedule'!J53 -> 0 | K20: ='Debt Schedule'!K27+'Debt Schedule'!K40+'Debt Schedule'!K53 -> 0
A21: Payment default? (1 = yes) | G21: =IF(OR(G16>0.001,G20>0.001),1,0) -> 0 | H21: =IF(OR(H16>0.001,H20>0.001),1,0) -> 0 | I21: =IF(OR(I16>0.001,I20>0.001),1,0) -> 0 | J21: =IF(OR(J16>0.001,J20>0.001),1,0) -> 0 | K21: =IF(OR(K16>0.001,K20>0.001),1,0) -> 0
A22: First default period flag | G22: =IF(G21=1,1,0) -> 0 | H22: =IF(AND(H21=1,SUM($G$21:G21)=0),1,0) -> 0 | I22: =IF(AND(I21=1,SUM($G$21:H21)=0),1,0) -> 0 | J22: =IF(AND(J21=1,SUM($G$21:I21)=0),1,0) -> 0 | K22: =IF(AND(K21=1,SUM($G$21:J21)=0),1,0) -> 0
A23: Check: Δ debt = draws + PIK − repayments | G23: =('Debt Schedule'!G56-'Debt Schedule'!F56)-(G12+'Operating Model'!G22-G10-G14-G18) -> 0 | H23: =('Debt Schedule'!H56-'Debt Schedule'!G56)-(H12+'Operating Model'!H22-H10-H14-H18) -> 0 | I23: =('Debt Schedule'!I56-'Debt Schedule'!H56)-(I12+'Operating Model'!I22-I10-I14-I18) -> 0 | J23: =('Debt Schedule'!J56-'Debt Schedule'!I56)-(J12+'Operating Model'!J22-J10-J14-J18) -> 0 | K23: =('Debt Schedule'!K56-'Debt Schedule'!J56)-(K12+'Operating Model'!K22-K10-K14-K18) -> 0

Sheet Credit Metrics
A1: Credit Metrics, Covenants & Credit Score
A2: ="AMC Networks (AMC Global Media) · PUBLIC DATA CASE · HYPOTHETICAL INVESTMENT TERMS · Active scenario: "&Assumptions!$D$10 -> AMC Networks (AMC Global Media) · PUBLIC DATA CASE · HYPOTHETICAL INVESTMENT TERMS · Active scenario: Downside
A4: $M | C4: FY2023A | D4: FY2024A | E4: FY2025A | F4: LTM Jun-26 | G4: LTM Jun-27E | H4: LTM Jun-28E | I4: LTM Jun-29E | J4: LTM Jun-30E | K4: LTM Jun-31E
A6: Credit metrics (selected scenario)
A7: Total debt (face value) | F7: ='Debt Schedule'!F56 -> 1735.554 | G7: ='Debt Schedule'!G56 -> 1735.554 | H7: ='Debt Schedule'!H56 -> 1735.554 | I7: ='Debt Schedule'!I56 -> 1315.098 | J7: ='Debt Schedule'!J56 -> 1315.098 | K7: ='Debt Schedule'!K56 -> 1315.098
A8: Secured debt | F8: =Assumptions!$O$56*'Debt Schedule'!F28+Assumptions!$O$57*'Debt Schedule'!F41+Assumptions!$O$58*'Debt Schedule'!F54 -> 1315.098 | G8: =Assumptions!$O$56*'Debt Schedule'!G28+Assumptions!$O$57*'Debt Schedule'!G41+Assumptions!$O$58*'Debt Schedule'!G54 -> 1315.098 | H8: =Assumptions!$O$56*'Debt Schedule'!H28+Assumptions!$O$57*'Debt Schedule'!H41+Assumptions!$O$58*'Debt Schedule'!H54 -> 1315.098 | I8: =Assumptions!$O$56*'Debt Schedule'!I28+Assumptions!$O$57*'Debt Schedule'!I41+Assumptions!$O$58*'Debt Schedule'!I54 -> 1315.098 | J8: =Assumptions!$O$56*'Debt Schedule'!J28+Assumptions!$O$57*'Debt Schedule'!J41+Assumptions!$O$58*'Debt Schedule'!J54 -> 1315.098 | K8: =Assumptions!$O$56*'Debt Schedule'!K28+Assumptions!$O$57*'Debt Schedule'!K41+Assumptions!$O$58*'Debt Schedule'!K54 -> 1315.098
A9: Net debt | F9: =F7-'Cash Flow'!F19 -> 1271.558 | G9: =G7-'Cash Flow'!G19 -> 1216.7325 | H9: =H7-'Cash Flow'!H19 -> 1195.8797 | I9: =I7-'Cash Flow'!I19 -> 1194.668 | J9: =J7-'Cash Flow'!J19 -> 1192.0261 | K9: =K7-'Cash Flow'!K19 -> 1196.4206
A10: Gross debt / EBITDA | F10: =IF('Operating Model'!F17>0,F7/'Operating Model'!F17,0) -> 5.5441039 | G10: =IF('Operating Model'!G17>0,G7/'Operating Model'!G17,0) -> 6.9988584 | H10: =IF('Operating Model'!H17>0,H7/'Operating Model'!H17,0) -> 8.2098046 | I10: =IF('Operating Model'!I17>0,I7/'Operating Model'!I17,0) -> 6.933114 | J10: =IF('Operating Model'!J17>0,J7/'Operating Model'!J17,0) -> 7.6629154 | K10: =IF('Operating Model'!K17>0,K7/'Operating Model'!K17,0) -> 8.0662268
A11: Net debt / EBITDA | F11: =IF('Operating Model'!F17>0,F9/'Operating Model'!F17,0) -> 4.0619016 | G11: =IF('Operating Model'!G17>0,G9/'Operating Model'!G17,0) -> 4.9066397 | H11: =IF('Operating Model'!H17>0,H9/'Operating Model'!H17,0) -> 5.656948 | I11: =IF('Operating Model'!I17>0,I9/'Operating Model'!I17,0) -> 6.2982145 | J11: =IF('Operating Model'!J17>0,J9/'Operating Model'!J17,0) -> 6.9457905 | K11: =IF('Operating Model'!K17>0,K9/'Operating Model'!K17,0) -> 7.3383123
A12: Interest coverage (EBITDA / cash interest) | F12: =IF('Operating Model'!F23>0,'Operating Model'!F17/'Operating Model'!F23,0) -> 1.8359011 | G12: =IF('Operating Model'!G21>0,'Operating Model'!G17/'Operating Model'!G21,0) -> 1.5900564 | H12: =IF('Operating Model'!H21>0,'Operating Model'!H17/'Operating Model'!H21,0) -> 1.3555231 | I12: =IF('Operating Model'!I21>0,'Operating Model'!I17/'Operating Model'!I21,0) -> 1.2162739 | J12: =IF('Operating Model'!J21>0,'Operating Model'!J17/'Operating Model'!J21,0) -> 1.2428441 | K12: =IF('Operating Model'!K21>0,'Operating Model'!K17/'Operating Model'!K21,0) -> 1.1807019
A13: EBIT / interest | F13: =IF('Operating Model'!F23>0,'Operating Model'!F20/'Operating Model'!F23,0) -> 1.1928299 | G13: =IF('Operating Model'!G21>0,'Operating Model'!G20/'Operating Model'!G21,0) -> 0.94320283 | H13: =IF('Operating Model'!H21>0,'Operating Model'!H20/'Operating Model'!H21,0) -> 0.75394926 | I13: =IF('Operating Model'!I21>0,'Operating Model'!I20/'Operating Model'!I21,0) -> 0.6507945 | J13: =IF('Operating Model'!J21>0,'Operating Model'!J20/'Operating Model'!J21,0) -> 0.63611985 | K13: =IF('Operating Model'!K21>0,'Operating Model'!K20/'Operating Model'!K21,0) -> 0.60431386
A14: FCF / debt | F14: =IF(F7>0,'Operating Model'!F30/F7,0) -> 0.10977647 | G14: =IF(G7>0,'Operating Model'!G30/G7,0) -> 0.031589652 | H14: =IF(H7>0,'Operating Model'!H30/H7,0) -> 0.012015031 | I14: =IF(I7>0,'Operating Model'!I30/I7,0) -> 0.00092140609 | J14: =IF(J7>0,'Operating Model'!J30/J7,0) -> 0.0020088801 | K14: =IF(K7>0,'Operating Model'!K30/K7,0) -> -0.0033415639
A15: Debt service coverage ((EBITDA − capex − tax) / (cash interest + amortization)) | G15: =IF('Operating Model'!G21+'Cash Flow'!G10>0,('Operating Model'!G17-'Operating Model'!G28-'Operating Model'!G25)/('Operating Model'!G21+'Cash Flow'!G10),0) -> 1.4178003 | H15: =IF('Operating Model'!H21+'Cash Flow'!H10>0,('Operating Model'!H17-'Operating Model'!H28-'Operating Model'!H25)/('Operating Model'!H21+'Cash Flow'!H10),0) -> 1.1953249 | I15: =IF('Operating Model'!I21+'Cash Flow'!I10>0,('Operating Model'!I17-'Operating Model'!I28-'Operating Model'!I25)/('Operating Model'!I21+'Cash Flow'!I10),0) -> 1.0656876 | J15: =IF('Operating Model'!J21+'Cash Flow'!J10>0,('Operating Model'!J17-'Operating Model'!J28-'Operating Model'!J25)/('Operating Model'!J21+'Cash Flow'!J10),0) -> 1.0812744 | K15: =IF('Operating Model'!K21+'Cash Flow'!K10>0,('Operating Model'!K17-'Operating Model'!K28-'Operating Model'!K25)/('Operating Model'!K21+'Cash Flow'!K10),0) -> 1.0272107
A16: Liquidity (cash + undrawn revolver) | F16: =MAX(0,'Cash Flow'!F19)+Assumptions!$P$56*MAX(0,Assumptions!$D$56-'Debt Schedule'!F28)+Assumptions!$P$57*MAX(0,Assumptions!$D$57-'Debt Schedule'!F41)+Assumptions!$P$58*MAX(0,Assumptions!$D$58-'Debt Schedule'!F54) -> 463.996 | G16: =MAX(0,'Cash Flow'!G19)+Assumptions!$P$56*MAX(0,Assumptions!$D$56-'Debt Schedule'!G28)+Assumptions!$P$57*MAX(0,Assumptions!$D$57-'Debt Schedule'!G41)+Assumptions!$P$58*MAX(0,Assumptions!$D$58-'Debt Schedule'!G54) -> 518.82155 | H16: =MAX(0,'Cash Flow'!H19)+Assumptions!$P$56*MAX(0,Assumptions!$D$56-'Debt Schedule'!H28)+Assumptions!$P$57*MAX(0,Assumptions!$D$57-'Debt Schedule'!H41)+Assumptions!$P$58*MAX(0,Assumptions!$D$58-'Debt Schedule'!H54) -> 539.67428 | I16: =MAX(0,'Cash Flow'!I19)+Assumptions!$P$56*MAX(0,Assumptions!$D$56-'Debt Schedule'!I28)+Assumptions!$P$57*MAX(0,Assumptions!$D$57-'Debt Schedule'!I41)+Assumptions!$P$58*MAX(0,Assumptions!$D$58-'Debt Schedule'!I54) -> 120.43002 | J16: =MAX(0,'Cash Flow'!J19)+Assumptions!$P$56*MAX(0,Assumptions!$D$56-'Debt Schedule'!J28)+Assumptions!$P$57*MAX(0,Assumptions!$D$57-'Debt Schedule'!J41)+Assumptions!$P$58*MAX(0,Assumptions!$D$58-'Debt Schedule'!J54) -> 123.0719 | K16: =MAX(0,'Cash Flow'!K19)+Assumptions!$P$56*MAX(0,Assumptions!$D$56-'Debt Schedule'!K28)+Assumptions!$P$57*MAX(0,Assumptions!$D$57-'Debt Schedule'!K41)+Assumptions!$P$58*MAX(0,Assumptions!$D$58-'Debt Schedule'!K54) -> 118.67741
A17: Debt / capital (debt + implied equity) | G17: =IF(G7>0,G7/(G7+MAX(0,'Operating Model'!G17*CHOOSE(Assumptions!$C$10,Assumptions!$C$82,Assumptions!$C$101,Assumptions!$C$120)-G9)),0) -> 0.98683624 | H17: =IF(H7>0,H7/(H7+MAX(0,'Operating Model'!H17*CHOOSE(Assumptions!$C$10,Assumptions!$C$82,Assumptions!$C$101,Assumptions!$C$120)-H9)),0) -> 1 | I17: =IF(I7>0,I7/(I7+MAX(0,'Operating Model'!I17*CHOOSE(Assumptions!$C$10,Assumptions!$C$82,Assumptions!$C$101,Assumptions!$C$120)-I9)),0) -> 1 | J17: =IF(J7>0,J7/(J7+MAX(0,'Operating Model'!J17*CHOOSE(Assumptions!$C$10,Assumptions!$C$82,Assumptions!$C$101,Assumptions!$C$120)-J9)),0) -> 1 | K17: =IF(K7>0,K7/(K7+MAX(0,'Operating Model'!K17*CHOOSE(Assumptions!$C$10,Assumptions!$C$82,Assumptions!$C$101,Assumptions!$C$120)-K9)),0) -> 1
A18: Cash / debt | F18: =IF(F7>0,MAX(0,'Cash Flow'!F19)/F7,0) -> 0.26734749 | G18: =IF(G7>0,MAX(0,'Cash Flow'!G19)/G7,0) -> 0.29893714 | H18: =IF(H7>0,MAX(0,'Cash Flow'!H19)/H7,0) -> 0.31095217 | I18: =IF(I7>0,MAX(0,'Cash Flow'!I19)/I7,0) -> 0.091574942 | J18: =IF(J7>0,MAX(0,'Cash Flow'!J19)/J7,0) -> 0.093583822 | K18: =IF(K7>0,MAX(0,'Cash Flow'!K19)/K7,0) -> 0.090242258
A19: Asset value after scenario decline | G19: =Assumptions!$C$30*(1-CHOOSE(Assumptions!$C$10,Assumptions!$C$85,Assumptions!$C$104,Assumptions!$C$123)) -> 2086.7254 | H19: =Assumptions!$C$30*(1-CHOOSE(Assumptions!$C$10,Assumptions!$C$85,Assumptions!$C$104,Assumptions!$C$123)) -> 2086.7254 | I19: =Assumptions!$C$30*(1-CHOOSE(Assumptions!$C$10,Assumptions!$C$85,Assumptions!$C$104,Assumptions!$C$123)) -> 2086.7254 | J19: =Assumptions!$C$30*(1-CHOOSE(Assumptions!$C$10,Assumptions!$C$85,Assumptions!$C$104,Assumptions!$C$123)) -> 2086.7254 | K19: =Assumptions!$C$30*(1-CHOOSE(Assumptions!$C$10,Assumptions!$C$85,Assumptions!$C$104,Assumptions!$C$123)) -> 2086.7254
A20: Covenant compliance (active covenants; tests use model-basis metrics)
A21: Hypothetical maintenance covenant: max net leverage (AOI basis) [HYPOTHETICAL]
A22: Metric | G22: =IF('Operating Model'!G17>0,G9/'Operating Model'!G17,99) -> 4.9066397 | H22: =IF('Operating Model'!H17>0,H9/'Operating Model'!H17,99) -> 5.656948 | I22: =IF('Operating Model'!I17>0,I9/'Operating Model'!I17,99) -> 6.2982145 | J22: =IF('Operating Model'!J17>0,J9/'Operating Model'!J17,99) -> 6.9457905 | K22: =IF('Operating Model'!K17>0,K9/'Operating Model'!K17,99) -> 7.3383123
A23: Covenant threshold | G23: =Assumptions!$G$65 -> 5.25 | H23: =Assumptions!$H$65 -> 5.25 | I23: =Assumptions!$I$65 -> 5 | J23: =Assumptions!$J$65 -> 5 | K23: =Assumptions!$K$65 -> 5
A24: Headroom | G24: =G23-G22 -> 0.34336029 | H24: =H23-H22 -> -0.40694804 | I24: =I23-I22 -> -1.2982145 | J24: =J23-J22 -> -1.9457905 | K24: =K23-K22 -> -2.3383123
A25: Headroom % of threshold | G25: =IF(G23=0,0,G24/ABS(G23)) -> 0.06540196 | H25: =IF(H23=0,0,H24/ABS(H23)) -> -0.077513912 | I25: =IF(I23=0,0,I24/ABS(I23)) -> -0.25964289 | J25: =IF(J23=0,0,J24/ABS(J23)) -> -0.38915811 | K25: =IF(K23=0,0,K24/ABS(K23)) -> -0.46766245
A26: BREACH? (1 = yes) | G26: =IF(G24<0,1,0) -> 0 | H26: =IF(H24<0,1,0) -> 1 | I26: =IF(I24<0,1,0) -> 1 | J26: =IF(J24<0,1,0) -> 1 | K26: =IF(K24<0,1,0) -> 1
A27: First breach period (0 = none) | C27: =IFERROR(INDEX('Operating Model'!$G$7:$K$7,MATCH(1,$G$26:$K$26,0)),0) -> 2028
A28: Minimum headroom % | C28: =MIN($G$25:$K$25) -> -0.46766245
A29: Hypothetical maintenance covenant: min interest coverage (AOI / interest) [HYPOTHETICAL]
A30: Metric | G30: =IF('Operating Model'!G21>0,'Operating Model'!G17/'Operating Model'!G21,99) -> 1.5900564 | H30: =IF('Operating Model'!H21>0,'Operating Model'!H17/'Operating Model'!H21,99) -> 1.3555231 | I30: =IF('Operating Model'!I21>0,'Operating Model'!I17/'Operating Model'!I21,99) -> 1.2162739 | J30: =IF('Operating Model'!J21>0,'Operating Model'!J17/'Operating Model'!J21,99) -> 1.2428441 | K30: =IF('Operating Model'!K21>0,'Operating Model'!K17/'Operating Model'!K21,99) -> 1.1807019
A31: Covenant threshold | G31: =Assumptions!$G$66 -> 1.4 | H31: =Assumptions!$H$66 -> 1.4 | I31: =Assumptions!$I$66 -> 1.4 | J31: =Assumptions!$J$66 -> 1.5 | K31: =Assumptions!$K$66 -> 1.5
A32: Headroom | G32: =G30-G31 -> 0.19005643 | H32: =H30-H31 -> -0.04447689 | I32: =I30-I31 -> -0.18372608 | J32: =J30-J31 -> -0.25715586 | K32: =K30-K31 -> -0.31929807
A33: Headroom % of threshold | G33: =IF(G31=0,0,G32/ABS(G31)) -> 0.1357546 | H33: =IF(H31=0,0,H32/ABS(H31)) -> -0.031769207 | I33: =IF(I31=0,0,I32/ABS(I31)) -> -0.13123292 | J33: =IF(J31=0,0,J32/ABS(J31)) -> -0.17143724 | K33: =IF(K31=0,0,K32/ABS(K31)) -> -0.21286538
A34: BREACH? (1 = yes) | G34: =IF(G32<0,1,0) -> 0 | H34: =IF(H32<0,1,0) -> 1 | I34: =IF(I32<0,1,0) -> 1 | J34: =IF(J32<0,1,0) -> 1 | K34: =IF(K32<0,1,0) -> 1
A35: First breach period (0 = none) | C35: =IFERROR(INDEX('Operating Model'!$G$7:$K$7,MATCH(1,$G$34:$K$34,0)),0) -> 2028
A36: Minimum headroom % | C36: =MIN($G$33:$K$33) -> -0.21286538
A37: Hypothetical maintenance covenant: min liquidity ($M) [HYPOTHETICAL]
A38: Metric | G38: =G16 -> 518.82155 | H38: =H16 -> 539.67428 | I38: =I16 -> 120.43002 | J38: =J16 -> 123.0719 | K38: =K16 -> 118.67741
A39: Covenant threshold | G39: =Assumptions!$G$67 -> 200 | H39: =Assumptions!$H$67 -> 200 | I39: =Assumptions!$I$67 -> 200 | J39: =Assumptions!$J$67 -> 200 | K39: =Assumptions!$K$67 -> 200
A40: Headroom | G40: =G38-G39 -> 318.82155 | H40: =H38-H39 -> 339.67428 | I40: =I38-I39 -> -79.569977 | J40: =J38-J39 -> -76.928103 | K40: =K38-K39 -> -81.322587
A41: Headroom % of threshold | G41: =IF(G39=0,0,G40/ABS(G39)) -> 1.5941077 | H41: =IF(H39=0,0,H40/ABS(H39)) -> 1.6983714 | I41: =IF(I39=0,0,I40/ABS(I39)) -> -0.39784989 | J41: =IF(J39=0,0,J40/ABS(J39)) -> -0.38464052 | K41: =IF(K39=0,0,K40/ABS(K39)) -> -0.40661294
A42: BREACH? (1 = yes) | G42: =IF(G40<0,1,0) -> 0 | H42: =IF(H40<0,1,0) -> 0 | I42: =IF(I40<0,1,0) -> 1 | J42: =IF(J40<0,1,0) -> 1 | K42: =IF(K40<0,1,0) -> 1
A43: First breach period (0 = none) | C43: =IFERROR(INDEX('Operating Model'!$G$7:$K$7,MATCH(1,$G$42:$K$42,0)),0) -> 2029
A44: Minimum headroom % | C44: =MIN($G$41:$K$41) -> -0.40661294
A45: Covenant breaches (count, all active covenants) | G45: =G26+G34+G42 -> 0 | H45: =H26+H34+H42 -> 2 | I45: =I26+I34+I42 -> 3 | J45: =J26+J34+J42 -> 3 | K45: =K26+K34+K42 -> 3
A46: Total breaches across projection | C46: =SUM($G$45:$K$45) -> 11
A47: Minimum covenant headroom % (all active covenants) | C47: =MIN(C28,C36,C44) -> -0.46766245
A50: Credit score — transparent, formula-driven (base period; weights & thresholds on Assumptions §8)
A51: Factor | C51: Value | D51: Best | E51: Worst | F51: Weight | G51: Points | H51: Score % | I51: Projected value (period 1, selected scenario) | J51: Projected points
A52: Net leverage (net debt / EBITDA) | C52: ='Credit Metrics'!F11 -> 4.0619016 | D52: =Assumptions!$D$131 -> 2 | E52: =Assumptions!$E$131 -> 7 | F52: =Assumptions!$C$131 -> 15 | G52: =F52*H52 -> 8.8142951 | H52: =MAX(0,MIN(1,(C52-E52)/(D52-E52))) -> 0.58761967 | I52: ='Credit Metrics'!G11 -> 4.9066397 | J52: =F52*MAX(0,MIN(1,(I52-E52)/(D52-E52))) -> 6.2800809
A53: Interest coverage (EBITDA / interest) | C53: ='Credit Metrics'!F12 -> 1.8359011 | D53: =Assumptions!$D$132 -> 5 | E53: =Assumptions!$E$132 -> 1 | F53: =Assumptions!$C$132 -> 15 | G53: =F53*H53 -> 3.134629 | H53: =MAX(0,MIN(1,(C53-E53)/(D53-E53))) -> 0.20897527 | I53: ='Credit Metrics'!G12 -> 1.5900564 | J53: =F53*MAX(0,MIN(1,(I53-E53)/(D53-E53))) -> 2.2127116
A54: Liquidity ratio (liquidity / next-period obligations) | C54: ='Credit Metrics'!F16/(SUMPRODUCT((Assumptions!$K$56:$K$58<=Assumptions!$C$6+1)*Assumptions!$C$56:$C$58)+SUMPRODUCT(Assumptions!$L$56:$L$58*Assumptions!$C$56:$C$58)+'Operating Model'!F23) -> 2.7211767 | D54: =Assumptions!$D$133 -> 2 | E54: =Assumptions!$E$133 -> 0.5 | F54: =Assumptions!$C$133 -> 10 | G54: =F54*H54 -> 10 | H54: =MAX(0,MIN(1,(C54-E54)/(D54-E54))) -> 1 | I54: ='Credit Metrics'!G16/(SUMPRODUCT((Assumptions!$K$56:$K$58<=Assumptions!$C$6+1)*Assumptions!$C$56:$C$58)+SUMPRODUCT(Assumptions!$L$56:$L$58*Assumptions!$C$56:$C$58)+'Operating Model'!F23) -> 3.0427096 | J54: =F54*MAX(0,MIN(1,(I54-E54)/(D54-E54))) -> 10
A55: FCF / total debt | C55: ='Credit Metrics'!F14 -> 0.10977647 | D55: =Assumptions!$D$134 -> 0.12 | E55: =Assumptions!$E$134 -> -0.02 | F55: =Assumptions!$C$134 -> 10 | G55: =F55*H55 -> 9.2697482 | H55: =MAX(0,MIN(1,(C55-E55)/(D55-E55))) -> 0.92697482 | I55: ='Credit Metrics'!G14 -> 0.031589652 | J55: =F55*MAX(0,MIN(1,(I55-E55)/(D55-E55))) -> 3.6849752
A56: Share of debt maturing within window | C56: =SUMPRODUCT((Assumptions!$K$56:$K$58<=Assumptions!$C$6+Assumptions!$C$22)*Assumptions!$C$56:$C$58)/SUM(Assumptions!$C$56:$C$58) -> 0.2422604 | D56: =Assumptions!$D$135 -> 0 | E56: =Assumptions!$E$135 -> 0.5 | F56: =Assumptions!$C$135 -> 10 | G56: =F56*H56 -> 5.1547921 | H56: =MAX(0,MIN(1,(C56-E56)/(D56-E56))) -> 0.51547921 | I56: =C56 -> 0.2422604 | J56: =F56*MAX(0,MIN(1,(I56-E56)/(D56-E56))) -> 5.1547921
A57: Margin stability (σ of annual EBITDA margin) | C57: =STDEVP('Historical Financials'!B42:D42) -> 0.029638164 | D57: =Assumptions!$D$136 -> 0.01 | E57: =Assumptions!$E$136 -> 0.05 | F57: =Assumptions!$C$136 -> 10 | G57: =F57*H57 -> 5.0904589 | H57: =MAX(0,MIN(1,(C57-E57)/(D57-E57))) -> 0.50904589 | I57: =C57 -> 0.029638164 | J57: =F57*MAX(0,MIN(1,(I57-E57)/(D57-E57))) -> 5.0904589
A58: Revenue stability (σ of annual growth) | C58: =STDEVP('Historical Financials'!C43:D43) -> 0.030957931 | D58: =Assumptions!$D$137 -> 0.03 | E58: =Assumptions!$E$137 -> 0.15 | F58: =Assumptions!$C$137 -> 8 | G58: =F58*H58 -> 7.936138 | H58: =MAX(0,MIN(1,(C58-E58)/(D58-E58))) -> 0.99201725 | I58: =C58 -> 0.030957931 | J58: =F58*MAX(0,MIN(1,(I58-E58)/(D58-E58))) -> 7.936138
A59: Asset coverage (asset base / debt) | C59: =Assumptions!$C$30/'Credit Metrics'!F7 -> 1.4145172 | D59: =Assumptions!$D$138 -> 2 | E59: =Assumptions!$E$138 -> 0.6 | F59: =Assumptions!$C$138 -> 12 | G59: =F59*H59 -> 6.9815761 | H59: =MAX(0,MIN(1,(C59-E59)/(D59-E59))) -> 0.58179801 | I59: =C59 -> 1.4145172 | J59: =F59*MAX(0,MIN(1,(I59-E59)/(D59-E59))) -> 6.9815761
A60: Industry risk factor (analyst input, 0-1) | C60: =Assumptions!$C$140 -> 0.3 | D60: =Assumptions!$D$139 -> 1 | E60: =Assumptions!$E$139 -> 0 | F60: =Assumptions!$C$139 -> 10 | G60: =F60*H60 -> 3 | H60: =MAX(0,MIN(1,(C60-E60)/(D60-E60))) -> 0.3 | I60: =C60 -> 0.3 | J60: =F60*MAX(0,MIN(1,(I60-E60)/(D60-E60))) -> 3
A61: Credit score (0-100) | F61: =SUM(F52:F60) -> 100 | G61: =SUM(G52:G60) -> 59.381637 | J61: =SUM(J52:J60) -> 50.340733
A62: Risk band | G62: =IF(G61>=Assumptions!$C$144,"Low",IF(G61>=Assumptions!$C$145,"Moderate",IF(G61>=Assumptions!$C$146,"Elevated","High"))) -> Elevated
A63: Each factor earns its weight linearly between the 'worst' threshold (0 pts) and the 'best' threshold (full pts).

Sheet Scenarios
A1: Scenarios — side-by-side (all three run simultaneously on Calc Engine)
A2: ="Active scenario for the detailed tabs: "&Assumptions!$D$10 -> Active scenario for the detailed tabs: Downside
A4: Assumptions (links to Assumptions tab) | C4: Base Case | D4: Downside | E4: Severe Downside | F4: Selected
A5: Average revenue growth (5 periods) | C5: =AVERAGE(Assumptions!$G$71:$K$71) -> -0.036 | D5: =AVERAGE(Assumptions!$G$90:$K$90) -> -0.062 | E5: =AVERAGE(Assumptions!$G$109:$K$109) -> -0.1 | F5: =CHOOSE(Assumptions!$C$10,C5,D5,E5) -> -0.062
A6: Average EBITDA margin (5 periods) | C6: =AVERAGE(Assumptions!$G$73:$K$73) -> 0.1376 | D6: =AVERAGE(Assumptions!$G$92:$K$92) -> 0.107 | E6: =AVERAGE(Assumptions!$G$111:$K$111) -> 0.075 | F6: =CHOOSE(Assumptions!$C$10,C6,D6,E6) -> 0.107
A7: Floating-rate shock | C7: =Assumptions!$C$78 -> 0 | D7: =Assumptions!$C$97 -> 0.015 | E7: =Assumptions!$C$116 -> 0.03 | F7: =CHOOSE(Assumptions!$C$10,C7,D7,E7) -> 0.015
A8: Refinancing rate | C8: =Assumptions!$C$79 -> 0.11 | D8: =Assumptions!$C$98 -> 0.13 | E8: =Assumptions!$C$117 -> 0.15 | F8: =CHOOSE(Assumptions!$C$10,C8,D8,E8) -> 0.13
A9: Market access: max net leverage / min coverage | C9: =TEXT(Assumptions!$C$80,"0.0")&"x / "&TEXT(Assumptions!$C$81,"0.00")&"x" -> 6.0x / 1.25x | D9: =TEXT(Assumptions!$C$99,"0.0")&"x / "&TEXT(Assumptions!$C$100,"0.00")&"x" -> 5.5x / 1.50x | E9: =TEXT(Assumptions!$C$118,"0.0")&"x / "&TEXT(Assumptions!$C$119,"0.00")&"x" -> 5.0x / 1.75x | F9: =CHOOSE(Assumptions!$C$10,C9,D9,E9) -> 5.5x / 1.50x
A10: Exit multiple / distressed multiple | C10: =TEXT(Assumptions!$C$82,"0.0")&"x / "&TEXT(Assumptions!$C$84,"0.0")&"x" -> 5.5x / 5.0x | D10: =TEXT(Assumptions!$C$101,"0.0")&"x / "&TEXT(Assumptions!$C$103,"0.0")&"x" -> 5.0x / 4.5x | E10: =TEXT(Assumptions!$C$120,"0.0")&"x / "&TEXT(Assumptions!$C$122,"0.0")&"x" -> 4.0x / 4.0x | F10: =CHOOSE(Assumptions!$C$10,C10,D10,E10) -> 5.0x / 4.5x
A11: Asset value decline | C11: =Assumptions!$C$85 -> 0 | D11: =Assumptions!$C$104 -> 0.15 | E11: =Assumptions!$C$123 -> 0.35 | F11: =CHOOSE(Assumptions!$C$10,C11,D11,E11) -> 0.15
A12: Scenario probability | C12: =Assumptions!$C$87 -> 0.45 | D12: =Assumptions!$C$106 -> 0.35 | E12: =Assumptions!$C$125 -> 0.2 | F12: =CHOOSE(Assumptions!$C$10,C12,D12,E12) -> 0.35
A14: Outputs (from Calc Engine) | C14: Base Case | D14: Downside | E14: Severe Downside | F14: Selected
A15: LTM Jun-31E revenue ($M) | C15: ='Calc Engine'!K19 -> 1869.7659 | D15: ='Calc Engine'!K343 -> 1630.3757 | E15: ='Calc Engine'!K667 -> 1323.0649 | F15: =CHOOSE(Assumptions!$C$10,C15,D15,E15) -> 1630.3757
A16: Trough EBITDA ($M) | C16: =MIN('Calc Engine'!$G$23:$K$23) -> 250.54863 | D16: =MIN('Calc Engine'!$G$347:$K$347) -> 163.03757 | E16: =MIN('Calc Engine'!$G$671:$K$671) -> 92.614546 | F16: =CHOOSE(Assumptions!$C$10,C16,D16,E16) -> 163.03757
A17: Cumulative FCF, 5 periods ($M) | C17: ='Calc Engine'!C325 -> 555.58835 | D17: ='Calc Engine'!C649 -> 75.137413 | E17: ='Calc Engine'!C973 -> -362.4062 | F17: =CHOOSE(Assumptions!$C$10,C17,D17,E17) -> 75.137413
A18: Peak net debt / EBITDA | C18: ='Calc Engine'!C323 -> 3.8149962 | D18: ='Calc Engine'!C647 -> 7.3383123 | E18: ='Calc Engine'!C971 -> 17.64263 | F18: =CHOOSE(Assumptions!$C$10,C18,D18,E18) -> 7.3383123
A19: Minimum EBITDA / cash interest | C19: ='Calc Engine'!C324 -> 1.7584275 | D19: ='Calc Engine'!C648 -> 1.1807019 | E19: ='Calc Engine'!C972 -> 0.64109145 | F19: =CHOOSE(Assumptions!$C$10,C19,D19,E19) -> 1.1807019
A20: Covenant breaches (count of tests failed) | C20: ='Calc Engine'!C164 -> 0 | D20: ='Calc Engine'!C488 -> 11 | E20: ='Calc Engine'!C812 -> 13 | F20: =CHOOSE(Assumptions!$C$10,C20,D20,E20) -> 11
A21: Refinancing failures (maturing tranches) | C21: ='Calc Engine'!C103 -> 0 | D21: ='Calc Engine'!C427 -> 2 | E21: ='Calc Engine'!C751 -> 2 | F21: =CHOOSE(Assumptions!$C$10,C21,D21,E21) -> 2
A22: Payment default modelled? (1 = yes) | C22: ='Calc Engine'!C169 -> 0 | D22: ='Calc Engine'!C493 -> 0 | E22: ='Calc Engine'!C817 -> 1 | F22: =CHOOSE(Assumptions!$C$10,C22,D22,E22) -> 0
A23: Valuation period (default or trough) | C23: ='Calc Engine'!C170 -> 2031 | D23: ='Calc Engine'!C494 -> 2031 | E23: ='Calc Engine'!C818 -> 2029 | F23: =CHOOSE(Assumptions!$C$10,C23,D23,E23) -> 2031
A24: Recovery value used ($M) | C24: ='Calc Engine'!C176 -> 1851.8715 | D24: ='Calc Engine'!C500 -> 852.34647 | E24: ='Calc Engine'!C824 -> 478.71934 | F24: =CHOOSE(Assumptions!$C$10,C24,D24,E24) -> 852.34647
A25: Target-tranche recovery % (valuation waterfall) | C25: ='Calc Engine'!C247 -> 1 | D25: ='Calc Engine'!C571 -> 0.60628401 | E25: ='Calc Engine'!C895 -> 0.34051867 | F25: =CHOOSE(Assumptions!$C$10,C25,D25,E25) -> 0.60628401
A26: Exit price used (% of face) | C26: ='Calc Engine'!C308 -> 100 | D26: ='Calc Engine'!C632 -> 81.27516 | E26: ='Calc Engine'!C956 -> 32.573573 | F26: =CHOOSE(Assumptions!$C$10,C26,D26,E26) -> 81.27516
A27: IRR | C27: ='Calc Engine'!C322 -> 0.12603362 | D27: ='Calc Engine'!C646 -> 0.065384881 | E27: ='Calc Engine'!C970 -> -0.10811295 | F27: =CHOOSE(Assumptions!$C$10,C27,D27,E27) -> 0.065384881
A28: MOIC | C28: ='Calc Engine'!C321 -> 1.3842105 | D28: ='Calc Engine'!C645 -> 1.187107 | E28: ='Calc Engine'!C969 -> 0.69942872 | F28: =CHOOSE(Assumptions!$C$10,C28,D28,E28) -> 1.187107
A29: Absolute profit ($M) | C29: ='Calc Engine'!C320 -> 36.5 | D29: ='Calc Engine'!C644 -> 17.77516 | E29: ='Calc Engine'!C968 -> -28.554272 | F29: =CHOOSE(Assumptions!$C$10,C29,D29,E29) -> 17.77516
A31: Probability-weighted IRR (IRR of expected cash flows) | C31: =IF(SUM(D38:I38)<=0,-1,IFERROR(IRR(C38:I38,MAX(-0.9,(SUM(D38:I38)/-C38)^(1/(COLUMNS(C38:I38)-1))-1)),IRR(C38:I38,0.1))) -> 0.06109225
A32: Memo: probability-weighted AVERAGE of scenario IRRs (IRR is non-linear, so this is not an IRR) | C32: =SUMPRODUCT(C12:E12,C27:E27) -> 0.057977249
A33: Probability-weighted MOIC | C33: =SUMPRODUCT(C12:E12,C28:E28) -> 1.1782679
A34: Probability of payment default | C34: =SUMPRODUCT(C12:E12,C22:E22) -> 0.2
A36: Expected (probability-weighted) position cash flows by period — basis of the probability-weighted IRR
C37: t=0 | D37: t=1 | E37: t=2 | F37: t=3 | G37: t=4 | H37: t=5 | I37: t=6
A38: Expected net cash flow ($M) | C38: =C$12*'Calc Engine'!C315+D$12*'Calc Engine'!C639+E$12*'Calc Engine'!C963 -> -95 | D38: =C$12*'Calc Engine'!D315+D$12*'Calc Engine'!D639+E$12*'Calc Engine'!D963 -> 10.5 | E38: =C$12*'Calc Engine'!E315+D$12*'Calc Engine'!E639+E$12*'Calc Engine'!E963 -> 10.5 | F38: =C$12*'Calc Engine'!F315+D$12*'Calc Engine'!F639+E$12*'Calc Engine'!F963 -> 83.946306 | G38: =C$12*'Calc Engine'!G315+D$12*'Calc Engine'!G639+E$12*'Calc Engine'!G963 -> 6.9891456 | H38: =C$12*'Calc Engine'!H315+D$12*'Calc Engine'!H639+E$12*'Calc Engine'!H963 -> 0 | I38: =C$12*'Calc Engine'!I315+D$12*'Calc Engine'!I639+E$12*'Calc Engine'!I963 -> 0
A40: Reconciliation: detailed tabs vs Calc Engine (selected scenario) | C40: Detailed | D40: Calc Engine | E40: Difference
A41: LTM Jun-31E EBITDA | C41: ='Operating Model'!K17 -> 163.03757 | D41: =CHOOSE(Assumptions!$C$10,'Calc Engine'!K23,'Calc Engine'!K347,'Calc Engine'!K671) -> 163.03757 | E41: =C41-D41 -> 0
A42: LTM Jun-31E total debt | C42: ='Debt Schedule'!K56 -> 1315.098 | D42: =CHOOSE(Assumptions!$C$10,'Calc Engine'!K88,'Calc Engine'!K412,'Calc Engine'!K736) -> 1315.098 | E42: =C42-D42 -> 0
A43: LTM Jun-31E ending cash | C43: ='Cash Flow'!K19 -> 118.67741 | D43: =CHOOSE(Assumptions!$C$10,'Calc Engine'!K118,'Calc Engine'!K442,'Calc Engine'!K766) -> 118.67741 | E43: =C43-D43 -> 0
A44: Cumulative FCF | C44: =Returns!C93 -> 75.137413 | D44: =CHOOSE(Assumptions!$C$10,'Calc Engine'!C325,'Calc Engine'!C649,'Calc Engine'!C973) -> 75.137413 | E44: =C44-D44 -> 0
A45: Recovery value used | C45: =Recovery!C15 -> 852.34647 | D45: =CHOOSE(Assumptions!$C$10,'Calc Engine'!C176,'Calc Engine'!C500,'Calc Engine'!C824) -> 852.34647 | E45: =C45-D45 -> 0
A46: Covenant breaches | C46: ='Credit Metrics'!C46 -> 11 | D46: =CHOOSE(Assumptions!$C$10,'Calc Engine'!C164,'Calc Engine'!C488,'Calc Engine'!C812) -> 11 | E46: =C46-D46 -> 0
A47: IRR | C47: =Returns!C90 -> 0.065384881 | D47: =CHOOSE(Assumptions!$C$10,'Calc Engine'!C322,'Calc Engine'!C646,'Calc Engine'!C970) -> 0.065384881 | E47: =C47-D47 -> 0
A48: MOIC | C48: =Returns!C89 -> 1.187107 | D48: =CHOOSE(Assumptions!$C$10,'Calc Engine'!C321,'Calc Engine'!C645,'Calc Engine'!C969) -> 1.187107 | E48: =C48-D48 -> 0

Sheet Capital Structure
A1: Capital Structure — tranches, leverage through the stack, maturity wall and refinancing requirement
A2: ="AMC Networks (AMC Global Media) · PUBLIC DATA CASE · HYPOTHETICAL INVESTMENT TERMS · as of "&TEXT(Assumptions!$C$8,"yyyy-mm-dd")&" · $M" -> AMC Networks (AMC Global Media) · PUBLIC DATA CASE · HYPOTHETICAL INVESTMENT TERMS · as of 2026-06-30 · $M
A4: Facility | B4: Type | C4: Rank | D4: Secured? | E4: Face value | F4: All-in rate | G4: Annual interest | H4: Maturity date | I4: Cum. leverage | J4: % of capitalization | K4: Mark / price | L4: Mkt value
A5: =Assumptions!$A$56 -> 10.50% Senior Secured Notes due 2032 | B5: =Assumptions!$B$56 -> senior_notes | C5: =Assumptions!$M$56 -> 1 | D5: =IF(Assumptions!$O$56=1,"Secured","Unsecured") -> Secured | E5: =Assumptions!$C$56 -> 1315.098 | F5: ='Debt Schedule'!G20 -> 0.105 | G5: =E5*F5 -> 138.08529 | H5: =Assumptions!$J$56 -> 48410 | I5: =SUMIF($C$5:$C$7,"<="&C5,$E$5:$E$7)/'Operating Model'!F17 -> 4.2009871 | J5: =E5/($E$8+$E$12) -> 0.60167078 | K5: =Assumptions!$R$56 -> 95 | L5: =E5*K5/100 -> 1249.3431
A6: =Assumptions!$A$57 -> 4.25% Senior Notes due 2029 | B6: =Assumptions!$B$57 -> unsecured_notes | C6: =Assumptions!$M$57 -> 2 | D6: =IF(Assumptions!$O$57=1,"Secured","Unsecured") -> Unsecured | E6: =Assumptions!$C$57 -> 276.706 | F6: ='Debt Schedule'!G33 -> 0.0425 | G6: =E6*F6 -> 11.760005 | H6: =Assumptions!$J$57 -> 47164 | I6: =SUMIF($C$5:$C$7,"<="&C6,$E$5:$E$7)/'Operating Model'!F17 -> 5.5441039 | J6: =E6/($E$8+$E$12) -> 0.12659582 | K6: =Assumptions!$R$57 -> 100 | L6: =E6*K6/100 -> 276.706
A7: =Assumptions!$A$58 -> 4.25% Convertible Senior Notes due 2029 | B7: =Assumptions!$B$58 -> convertible | C7: =Assumptions!$M$58 -> 2 | D7: =IF(Assumptions!$O$58=1,"Secured","Unsecured") -> Unsecured | E7: =Assumptions!$C$58 -> 143.75 | F7: ='Debt Schedule'!G46 -> 0.0425 | G7: =E7*F7 -> 6.109375 | H7: =Assumptions!$J$58 -> 47164 | I7: =SUMIF($C$5:$C$7,"<="&C7,$E$5:$E$7)/'Operating Model'!F17 -> 5.5441039 | J7: =E7/($E$8+$E$12) -> 0.065767095 | K7: =Assumptions!$R$58 -> 100 | L7: =E7*K7/100 -> 143.75
A8: Total debt | E8: =SUM(E5:E7) -> 1735.554 | G8: =SUM(G5:G7) -> 155.95467 | I8: =E8/'Operating Model'!F17 -> 5.5441039 | L8: =SUM(L5:L7) -> 1669.7991
A9: Less: cash | E9: =Assumptions!$C$11 -> 463.996
A10: Net debt | E10: =E8-E9 -> 1271.558 | I10: =E10/'Operating Model'!F17 -> 4.0619016
A11: Enterprise value (base EBITDA × market-implied multiple — analyst assumption) | E11: ='Operating Model'!F17*Assumptions!$C$21 -> 1721.7475
A12: Equity (residual: max(0, EV − net debt)) | E12: =MAX(0,E11-E10) -> 450.1895
A13: Liquidity (cash + undrawn revolver) | E13: ='Credit Metrics'!F16 -> 463.996
A14: Asset base (collateral / recovery basis) | E14: =Assumptions!$C$30 -> 2454.971
A15: Loan-to-value through target tranche (cumulative debt ÷ asset base) | E15: =SUMIF($C$5:$C$7,"<="&INDEX($C$5:$C$7,Assumptions!$C$33),$E$5:$E$7)/E14 -> 0.53568779
A18: Maturity wall (from Debt Schedule maturity flags) — selected scenario liquidity
A19: Period | C19: Debt due | D19: % of debt | E19: Cumulative % | F19: Projected liquidity | G19: Refinancing requirement | H19: Liquidity ÷ maturity | I19: Risk | J19: Flag
A20: ="LTM Jun-27E"&" (period ending "&'Operating Model'!G7&")" -> LTM Jun-27E (period ending 2027) | C20: ='Debt Schedule'!G57 -> 0 | D20: =C20/$E$8 -> 0 | E20: =SUM($D$20:D20) -> 0 | F20: =MAX(0,Assumptions!$C$11)+('Credit Metrics'!F16-MAX(0,Assumptions!$C$11))+MAX(0,'Operating Model'!G30) -> 518.82155 | G20: =MAX(0,C20-F20) -> 0 | H20: =IF(C20>0,F20/C20,0) -> 0 | I20: =IF(AND(G20>0,D20>=Assumptions!$C$19),"High",IF(OR(G20>0,D20>=Assumptions!$C$20),"Medium","Low")) -> Low | J20: =IF(I20="High","$"&TEXT(C20,"#,##0")&"M maturity; only $"&TEXT(F20,"#,##0")&"M projected liquidity; $"&TEXT(G20,"#,##0")&"M refinancing requirement","–") -> –
A21: ="LTM Jun-28E"&" (period ending "&'Operating Model'!H7&")" -> LTM Jun-28E (period ending 2028) | C21: ='Debt Schedule'!H57 -> 0 | D21: =C21/$E$8 -> 0 | E21: =SUM($D$20:D21) -> 0 | F21: =MAX(0,'Cash Flow'!G19)+('Credit Metrics'!G16-MAX(0,'Cash Flow'!G19))+MAX(0,'Operating Model'!H30) -> 539.67428 | G21: =MAX(0,C21-F21) -> 0 | H21: =IF(C21>0,F21/C21,0) -> 0 | I21: =IF(AND(G21>0,D21>=Assumptions!$C$19),"High",IF(OR(G21>0,D21>=Assumptions!$C$20),"Medium","Low")) -> Low | J21: =IF(I21="High","$"&TEXT(C21,"#,##0")&"M maturity; only $"&TEXT(F21,"#,##0")&"M projected liquidity; $"&TEXT(G21,"#,##0")&"M refinancing requirement","–") -> –
A22: ="LTM Jun-29E"&" (period ending "&'Operating Model'!I7&")" -> LTM Jun-29E (period ending 2029) | C22: ='Debt Schedule'!I57 -> 420.456 | D22: =C22/$E$8 -> 0.2422604 | E22: =SUM($D$20:D22) -> 0.2422604 | F22: =MAX(0,'Cash Flow'!H19)+('Credit Metrics'!H16-MAX(0,'Cash Flow'!H19))+MAX(0,'Operating Model'!I30) -> 540.88602 | G22: =MAX(0,C22-F22) -> 0 | H22: =IF(C22>0,F22/C22,0) -> 1.2864272 | I22: =IF(AND(G22>0,D22>=Assumptions!$C$19),"High",IF(OR(G22>0,D22>=Assumptions!$C$20),"Medium","Low")) -> Low | J22: =IF(I22="High","$"&TEXT(C22,"#,##0")&"M maturity; only $"&TEXT(F22,"#,##0")&"M projected liquidity; $"&TEXT(G22,"#,##0")&"M refinancing requirement","–") -> –
A23: ="LTM Jun-30E"&" (period ending "&'Operating Model'!J7&")" -> LTM Jun-30E (period ending 2030) | C23: ='Debt Schedule'!J57 -> 0 | D23: =C23/$E$8 -> 0 | E23: =SUM($D$20:D23) -> 0.2422604 | F23: =MAX(0,'Cash Flow'!I19)+('Credit Metrics'!I16-MAX(0,'Cash Flow'!I19))+MAX(0,'Operating Model'!J30) -> 123.0719 | G23: =MAX(0,C23-F23) -> 0 | H23: =IF(C23>0,F23/C23,0) -> 0 | I23: =IF(AND(G23>0,D23>=Assumptions!$C$19),"High",IF(OR(G23>0,D23>=Assumptions!$C$20),"Medium","Low")) -> Low | J23: =IF(I23="High","$"&TEXT(C23,"#,##0")&"M maturity; only $"&TEXT(F23,"#,##0")&"M projected liquidity; $"&TEXT(G23,"#,##0")&"M refinancing requirement","–") -> –
A24: ="LTM Jun-31E"&" (period ending "&'Operating Model'!K7&")" -> LTM Jun-31E (period ending 2031) | C24: ='Debt Schedule'!K57 -> 0 | D24: =C24/$E$8 -> 0 | E24: =SUM($D$20:D24) -> 0.2422604 | F24: =MAX(0,'Cash Flow'!J19)+('Credit Metrics'!J16-MAX(0,'Cash Flow'!J19))+MAX(0,'Operating Model'!K30) -> 123.0719 | G24: =MAX(0,C24-F24) -> 0 | H24: =IF(C24>0,F24/C24,0) -> 0 | I24: =IF(AND(G24>0,D24>=Assumptions!$C$19),"High",IF(OR(G24>0,D24>=Assumptions!$C$20),"Medium","Low")) -> Low | J24: =IF(I24="High","$"&TEXT(C24,"#,##0")&"M maturity; only $"&TEXT(F24,"#,##0")&"M projected liquidity; $"&TEXT(G24,"#,##0")&"M refinancing requirement","–") -> –
A25: Maturing within horizon / thereafter | C25: =SUM(C20:C24) -> 420.456 | D25: =C25/$E$8 -> 0.2422604
A26: Thereafter (beyond the 5-period horizon) | C26: =$E$8-C25 -> 1315.098
A28: Maturity concentration | C28: =IF(MAX(D20:D24)>=Assumptions!$C$20,"CONCENTRATED: "&TEXT(MAX(D20:D24),"0%")&" of debt in "&INDEX(A20:A24,MATCH(MAX(D20:D24),D20:D24,0)),"No single-period concentration") -> No single-period concentration
A29: Debt due within alert window | C29: =SUMPRODUCT((Assumptions!$K$56:$K$58<=Assumptions!$C$6+Assumptions!$C$18)*Assumptions!$C$56:$C$58) -> 0 | D29: =C29/E8 -> 0
A30: Maturity alert | C30: =IF(D29>=Assumptions!$C$19,"ALERT: "&TEXT(D29,"0%")&" of debt ($"&TEXT(C29,"#,##0")&"M) due within "&Assumptions!$C$18&" period(s); liquidity covers "&TEXT(E13/C29,"0%"),"OK: no material maturities within window") -> OK: no material maturities within window
A32: Refinancing risk engine — per tranche, selected scenario (see Debt Schedule for the period-by-period test)
A33: Tranche | C33: Balance at maturity | D33: Repaid from cash | E33: Test | F33: Resolution
A34: =Assumptions!$A$56 -> 10.50% Senior Secured Notes due 2032 | C34: ='Debt Schedule'!C59 -> 0 | D34: ='Debt Schedule'!C60 -> 0 | E34: ='Debt Schedule'!C61 -> n/a (beyond horizon) | F34: ='Debt Schedule'!C62 -> n/a
A35: =Assumptions!$A$57 -> 4.25% Senior Notes due 2029 | C35: ='Debt Schedule'!C63 -> 276.706 | D35: ='Debt Schedule'!C64 -> 276.706 | E35: ='Debt Schedule'!C65 -> REFINANCING FAILURE | F35: ='Debt Schedule'!C66 -> Repaid from cash
A36: =Assumptions!$A$58 -> 4.25% Convertible Senior Notes due 2029 | C36: ='Debt Schedule'!C67 -> 143.75 | D36: ='Debt Schedule'!C68 -> 143.75 | E36: ='Debt Schedule'!C69 -> REFINANCING FAILURE | F36: ='Debt Schedule'!C70 -> Repaid from cash

Sheet Recovery
A1: Recovery — waterfall by seniority (collateral pools, deficiency claims) at the valuation event
A2: ="AMC Networks (AMC Global Media) · PUBLIC DATA CASE · HYPOTHETICAL INVESTMENT TERMS · Active scenario: "&Assumptions!$D$10 -> AMC Networks (AMC Global Media) · PUBLIC DATA CASE · HYPOTHETICAL INVESTMENT TERMS · Active scenario: Downside
A4: $M | C4: Value
A6: Valuation event (default period, or trough-EBITDA period if no default is modelled)
A7: Valuation event period flag | G7: =IF($C$8=1,'Cash Flow'!G22,IF('Operating Model'!G17=MIN('Operating Model'!$G$17:$K$17),1,0)) -> 0 | H7: =IF($C$8=1,'Cash Flow'!H22,IF(AND('Operating Model'!H17=MIN('Operating Model'!$G$17:$K$17),SUM($G$7:G7)=0),1,0)) -> 0 | I7: =IF($C$8=1,'Cash Flow'!I22,IF(AND('Operating Model'!I17=MIN('Operating Model'!$G$17:$K$17),SUM($G$7:H7)=0),1,0)) -> 0 | J7: =IF($C$8=1,'Cash Flow'!J22,IF(AND('Operating Model'!J17=MIN('Operating Model'!$G$17:$K$17),SUM($G$7:I7)=0),1,0)) -> 0 | K7: =IF($C$8=1,'Cash Flow'!K22,IF(AND('Operating Model'!K17=MIN('Operating Model'!$G$17:$K$17),SUM($G$7:J7)=0),1,0)) -> 1
A8: Default modelled? (1 = yes) | C8: =IF(SUM('Cash Flow'!$G$22:$K$22)>0,1,0) -> 0
A9: Valuation period | C9: =SUMPRODUCT($G$7:$K$7,'Operating Model'!$G$7:$K$7) -> 2031
A10: EBITDA at valuation event | C10: =SUMPRODUCT($G$7:$K$7,'Operating Model'!$G$17:$K$17) -> 163.03757
A11: Cash at valuation event | C11: =MAX(0,SUMPRODUCT($G$7:$K$7,'Cash Flow'!$G$19:$K$19)) -> 118.67741
A12: Going-concern value (distressed multiple × EBITDA) | C12: =(CHOOSE(Assumptions!$C$10,Assumptions!$C$84,Assumptions!$C$103,Assumptions!$C$122))*C10 -> 733.66906
A13: Liquidation value (asset base × (1 − decline) × recovery) | C13: =Assumptions!$C$30*(1-CHOOSE(Assumptions!$C$10,Assumptions!$C$85,Assumptions!$C$104,Assumptions!$C$123))*CHOOSE(Assumptions!$C$10,Assumptions!$C$86,Assumptions!$C$105,Assumptions!$C$124) -> 626.01761
A14: Model recovery value (greater of the two + cash) | C14: =MAX(C12,C13)+C11 -> 852.34647
A15: Recovery value used (override if provided) | C15: =IF(ISNUMBER(Assumptions!$C$14),Assumptions!$C$14,C14) -> 852.34647
A16: Less: administrative / DIP costs | C16: =C15*Assumptions!$C$15 -> 34.093859
A17: Net value distributable to creditors | C17: =C15-C16 -> 818.25261
A18: Claim at valuation event (balance + accrued interest)
A19: Tranche 1: 10.50% Senior Secured Notes due 2032 | C19: =SUMPRODUCT($G$7:$K$7,'Debt Schedule'!$G$28:$K$28)*(1+SUMPRODUCT($G$7:$K$7,'Debt Schedule'!$G$20:$K$20)*Assumptions!$C$16/12) -> 1349.6193
A20: Tranche 2: 4.25% Senior Notes due 2029 | C20: =SUMPRODUCT($G$7:$K$7,'Debt Schedule'!$G$41:$K$41)*(1+SUMPRODUCT($G$7:$K$7,'Debt Schedule'!$G$33:$K$33)*Assumptions!$C$16/12) -> 0
A21: Tranche 3: 4.25% Convertible Senior Notes due 2029 | C21: =SUMPRODUCT($G$7:$K$7,'Debt Schedule'!$G$54:$K$54)*(1+SUMPRODUCT($G$7:$K$7,'Debt Schedule'!$G$46:$K$46)*Assumptions!$C$16/12) -> 0
A22: Seniority rank
A23: Tranche 1: 10.50% Senior Secured Notes due 2032 | C23: =Assumptions!$M$56 -> 1
A24: Tranche 2: 4.25% Senior Notes due 2029 | C24: =Assumptions!$M$57 -> 2
A25: Tranche 3: 4.25% Convertible Senior Notes due 2029 | C25: =Assumptions!$M$58 -> 2
A26: Collateral share (specific lien; 0 = all-asset / pari)
A27: Tranche 1: 10.50% Senior Secured Notes due 2032 | C27: =Assumptions!$Q$56 -> 0
A28: Tranche 2: 4.25% Senior Notes due 2029 | C28: =Assumptions!$Q$57 -> 0
A29: Tranche 3: 4.25% Convertible Senior Notes due 2029 | C29: =Assumptions!$Q$58 -> 0
A30: Paid from own collateral pool
A31: Tranche 1: 10.50% Senior Secured Notes due 2032 | C31: =IF(C27>0,MIN(C19,C27*$C$17),0) -> 0
A32: Tranche 2: 4.25% Senior Notes due 2029 | C32: =IF(C28>0,MIN(C20,C28*$C$17),0) -> 0
A33: Tranche 3: 4.25% Convertible Senior Notes due 2029 | C33: =IF(C29>0,MIN(C21,C29*$C$17),0) -> 0
A34: Deficiency claim (joins general creditors)
A35: Tranche 1: 10.50% Senior Secured Notes due 2032 | C35: =IF(C27>0,C19-C31,0) -> 0 | G35: =IF(AND('Debt Schedule'!G18=1,'Debt Schedule'!G15=1),1,0) -> 0 | H35: =IF(G35=1,1,IF(AND('Debt Schedule'!H18=1,'Debt Schedule'!H15=1),1,0)) -> 0 | I35: =IF(H35=1,1,IF(AND('Debt Schedule'!I18=1,'Debt Schedule'!I15=1),1,0)) -> 0 | J35: =IF(I35=1,1,IF(AND('Debt Schedule'!J18=1,'Debt Schedule'!J15=1),1,0)) -> 0 | K35: =IF(J35=1,1,IF(AND('Debt Schedule'!K18=1,'Debt Schedule'!K15=1),1,0)) -> 0
A36: Tranche 2: 4.25% Senior Notes due 2029 | C36: =IF(C28>0,C20-C32,0) -> 0 | G36: =IF(AND('Debt Schedule'!G31=1,'Debt Schedule'!G15=1),1,0) -> 0 | H36: =IF(G36=1,1,IF(AND('Debt Schedule'!H31=1,'Debt Schedule'!H15=1),1,0)) -> 0 | I36: =IF(H36=1,1,IF(AND('Debt Schedule'!I31=1,'Debt Schedule'!I15=1),1,0)) -> 0 | J36: =IF(I36=1,1,IF(AND('Debt Schedule'!J31=1,'Debt Schedule'!J15=1),1,0)) -> 0 | K36: =IF(J36=1,1,IF(AND('Debt Schedule'!K31=1,'Debt Schedule'!K15=1),1,0)) -> 0
A37: Tranche 3: 4.25% Convertible Senior Notes due 2029 | C37: =IF(C29>0,C21-C33,0) -> 0 | G37: =IF(AND('Debt Schedule'!G44=1,'Debt Schedule'!G15=1),1,0) -> 0 | H37: =IF(G37=1,1,IF(AND('Debt Schedule'!H44=1,'Debt Schedule'!H15=1),1,0)) -> 0 | I37: =IF(H37=1,1,IF(AND('Debt Schedule'!I44=1,'Debt Schedule'!I15=1),1,0)) -> 0 | J37: =IF(I37=1,1,IF(AND('Debt Schedule'!J44=1,'Debt Schedule'!J15=1),1,0)) -> 0 | K37: =IF(J37=1,1,IF(AND('Debt Schedule'!K44=1,'Debt Schedule'!K15=1),1,0)) -> 0
A38: General claim
A39: Tranche 1: 10.50% Senior Secured Notes due 2032 | C39: =IF(C27>0,C35,C19) -> 1349.6193
A40: Tranche 2: 4.25% Senior Notes due 2029 | C40: =IF(C28>0,C36,C20) -> 0
A41: Tranche 3: 4.25% Convertible Senior Notes due 2029 | C41: =IF(C29>0,C37,C21) -> 0
A42: General rank
A43: Tranche 1: 10.50% Senior Secured Notes due 2032 | C43: =IF(C27>0,Assumptions!$C$17,C23) -> 1
A44: Tranche 2: 4.25% Senior Notes due 2029 | C44: =IF(C28>0,Assumptions!$C$17,C24) -> 2
A45: Tranche 3: 4.25% Convertible Senior Notes due 2029 | C45: =IF(C29>0,Assumptions!$C$17,C25) -> 2
A46: General claims ahead
A47: Tranche 1: 10.50% Senior Secured Notes due 2032 | C47: =SUMPRODUCT(($C$43:$C$45<C43)*$C$39:$C$41) -> 0
A48: Tranche 2: 4.25% Senior Notes due 2029 | C48: =SUMPRODUCT(($C$43:$C$45<C44)*$C$39:$C$41) -> 1349.6193
A49: Tranche 3: 4.25% Convertible Senior Notes due 2029 | C49: =SUMPRODUCT(($C$43:$C$45<C45)*$C$39:$C$41) -> 1349.6193
A50: General claims of same rank (pari passu)
A51: Tranche 1: 10.50% Senior Secured Notes due 2032 | C51: =SUMPRODUCT(($C$43:$C$45=C43)*$C$39:$C$41) -> 1349.6193
A52: Tranche 2: 4.25% Senior Notes due 2029 | C52: =SUMPRODUCT(($C$43:$C$45=C44)*$C$39:$C$41) -> 0
A53: Tranche 3: 4.25% Convertible Senior Notes due 2029 | C53: =SUMPRODUCT(($C$43:$C$45=C45)*$C$39:$C$41) -> 0
A54: Recovery from general pool
A55: Tranche 1: 10.50% Senior Secured Notes due 2032 | C55: =IF(C51=0,0,C39/C51*MAX(0,MIN(C51,$C$17-SUM($C$31:$C$33)-C47))) -> 818.25261
A56: Tranche 2: 4.25% Senior Notes due 2029 | C56: =IF(C52=0,0,C40/C52*MAX(0,MIN(C52,$C$17-SUM($C$31:$C$33)-C48))) -> 0
A57: Tranche 3: 4.25% Convertible Senior Notes due 2029 | C57: =IF(C53=0,0,C41/C53*MAX(0,MIN(C53,$C$17-SUM($C$31:$C$33)-C49))) -> 0
A58: TOTAL RECOVERY
A59: Tranche 1: 10.50% Senior Secured Notes due 2032 | C59: =C31+C55 -> 818.25261
A60: Tranche 2: 4.25% Senior Notes due 2029 | C60: =C32+C56 -> 0
A61: Tranche 3: 4.25% Convertible Senior Notes due 2029 | C61: =C33+C57 -> 0
A62: Recovery %
A63: Tranche 1: 10.50% Senior Secured Notes due 2032 | C63: =IF(C19=0,1,C59/C19) -> 0.60628401
A64: Tranche 2: 4.25% Senior Notes due 2029 | C64: =IF(C20=0,1,C60/C20) -> 1
A65: Tranche 3: 4.25% Convertible Senior Notes due 2029 | C65: =IF(C21=0,1,C61/C21) -> 1
A66: Loss amount
A67: Tranche 1: 10.50% Senior Secured Notes due 2032 | C67: =C19-C59 -> 531.36671
A68: Tranche 2: 4.25% Senior Notes due 2029 | C68: =C20-C60 -> 0
A69: Tranche 3: 4.25% Convertible Senior Notes due 2029 | C69: =C21-C61 -> 0
A70: Loss %
A71: Tranche 1: 10.50% Senior Secured Notes due 2032 | C71: =IF(C19=0,0,C67/C19) -> 0.39371599
A72: Tranche 2: 4.25% Senior Notes due 2029 | C72: =IF(C20=0,0,C68/C20) -> 0
A73: Tranche 3: 4.25% Convertible Senior Notes due 2029 | C73: =IF(C21=0,0,C69/C21) -> 0
A74: Equity (residual after all claims) | C74: =MAX(0,$C$17-SUM($C$31:$C$33)-SUM($C$39:$C$41)) -> 0
A75: Check: recoveries + equity + costs − value (should be 0) | C75: =SUM($C$59:$C$61)+C74+C16-C15 -> 0

Sheet Returns
A1: Returns — face, purchase price, coupon, yield, recovery, IRR and MOIC (selected scenario)
A2: ="AMC Networks (AMC Global Media) · PUBLIC DATA CASE · HYPOTHETICAL INVESTMENT TERMS · Active scenario: "&Assumptions!$D$10 -> AMC Networks (AMC Global Media) · PUBLIC DATA CASE · HYPOTHETICAL INVESTMENT TERMS · Active scenario: Downside
A4: $M | C4: Value / t=0 | D4: t=1 | E4: t=2 | F4: t=3 | G4: t=4 | H4: t=5 | I4: t=6
A6: Position & valuation inputs (links) — face value, purchase price, coupon, yield and recovery are distinct
A7: Target tranche # | C7: =Assumptions!$C$33 -> 1
A8: Face value (legal claim) | C8: =Assumptions!$C$34 -> 100
A9: Purchase price / OID (% of face) | C9: =Assumptions!$C$35 -> 95
A10: Cash investment (face × price × (1 + fees)) | C10: =C8*C9/100*(1+Assumptions!$C$36) -> 95
A11: Hold period (periods) | C11: =Assumptions!$C$37 -> 3
A12: Default period # (0 = no default) | C12: =IF(Recovery!C8=1,SUMPRODUCT('Cash Flow'!$G$22:$K$22,'Operating Model'!$G$8:$K$8),0) -> 0
A13: Our share of the tranche at the valuation event | C13: =IFERROR(C8/CHOOSE(C7,SUMPRODUCT(Recovery!$G$7:$K$7,'Debt Schedule'!$G$28:$K$28),SUMPRODUCT(Recovery!$G$7:$K$7,'Debt Schedule'!$G$41:$K$41),SUMPRODUCT(Recovery!$G$7:$K$7,'Debt Schedule'!$G$54:$K$54)),0) -> 0.076039961
A14: Recovery proceeds to our position if default | C14: =CHOOSE(C7,Recovery!C59,Recovery!C60,Recovery!C61)*C13 -> 62.219896
A15: Tranche recovery % at valuation event (waterfall) | C15: =CHOOSE(C7,Recovery!C63,Recovery!C64,Recovery!C65) -> 0.60628401
A16: Last coupon period # | C16: =IF(Recovery!C8=1,C12,C11) -> 3
A17: Exit price assumption (no default) | C17: =CHOOSE(Assumptions!$C$10,Assumptions!$C$83,Assumptions!$C$102,Assumptions!$C$121) -> 95
A18: Exit EV (exit multiple × EBITDA + cash at hold period) | C18: =INDEX('Operating Model'!$G$17:$K$17,C11)*CHOOSE(Assumptions!$C$10,Assumptions!$C$82,Assumptions!$C$101,Assumptions!$C$120)+MAX(0,INDEX('Cash Flow'!$G$19:$K$19,C11)) -> 1068.848
A19: Claim at exit (balance at hold period)
A20: Tranche 1: 10.50% Senior Secured Notes due 2032 | C20: =INDEX('Debt Schedule'!$G$28:$K$28,C11) -> 1315.098
A21: Tranche 2: 4.25% Senior Notes due 2029 | C21: =INDEX('Debt Schedule'!$G$41:$K$41,C11) -> 0
A22: Tranche 3: 4.25% Convertible Senior Notes due 2029 | C22: =INDEX('Debt Schedule'!$G$54:$K$54,C11) -> 0
A23: Seniority rank
A24: Tranche 1: 10.50% Senior Secured Notes due 2032 | C24: =Assumptions!$M$56 -> 1
A25: Tranche 2: 4.25% Senior Notes due 2029 | C25: =Assumptions!$M$57 -> 2
A26: Tranche 3: 4.25% Convertible Senior Notes due 2029 | C26: =Assumptions!$M$58 -> 2
A27: Collateral share (specific lien; 0 = all-asset / pari)
A28: Tranche 1: 10.50% Senior Secured Notes due 2032 | C28: =Assumptions!$Q$56 -> 0
A29: Tranche 2: 4.25% Senior Notes due 2029 | C29: =Assumptions!$Q$57 -> 0
A30: Tranche 3: 4.25% Convertible Senior Notes due 2029 | C30: =Assumptions!$Q$58 -> 0
A31: Paid from own collateral pool
A32: Tranche 1: 10.50% Senior Secured Notes due 2032 | C32: =IF(C28>0,MIN(C20,C28*$C$18),0) -> 0
A33: Tranche 2: 4.25% Senior Notes due 2029 | C33: =IF(C29>0,MIN(C21,C29*$C$18),0) -> 0
A34: Tranche 3: 4.25% Convertible Senior Notes due 2029 | C34: =IF(C30>0,MIN(C22,C30*$C$18),0) -> 0
A35: Deficiency claim (joins general creditors)
A36: Tranche 1: 10.50% Senior Secured Notes due 2032 | C36: =IF(C28>0,C20-C32,0) -> 0
A37: Tranche 2: 4.25% Senior Notes due 2029 | C37: =IF(C29>0,C21-C33,0) -> 0
A38: Tranche 3: 4.25% Convertible Senior Notes due 2029 | C38: =IF(C30>0,C22-C34,0) -> 0
A39: General claim
A40: Tranche 1: 10.50% Senior Secured Notes due 2032 | C40: =IF(C28>0,C36,C20) -> 1315.098
A41: Tranche 2: 4.25% Senior Notes due 2029 | C41: =IF(C29>0,C37,C21) -> 0
A42: Tranche 3: 4.25% Convertible Senior Notes due 2029 | C42: =IF(C30>0,C38,C22) -> 0
A43: General rank
A44: Tranche 1: 10.50% Senior Secured Notes due 2032 | C44: =IF(C28>0,Assumptions!$C$17,C24) -> 1
A45: Tranche 2: 4.25% Senior Notes due 2029 | C45: =IF(C29>0,Assumptions!$C$17,C25) -> 2
A46: Tranche 3: 4.25% Convertible Senior Notes due 2029 | C46: =IF(C30>0,Assumptions!$C$17,C26) -> 2
A47: General claims ahead
A48: Tranche 1: 10.50% Senior Secured Notes due 2032 | C48: =SUMPRODUCT(($C$44:$C$46<C44)*$C$40:$C$42) -> 0
A49: Tranche 2: 4.25% Senior Notes due 2029 | C49: =SUMPRODUCT(($C$44:$C$46<C45)*$C$40:$C$42) -> 1315.098
A50: Tranche 3: 4.25% Convertible Senior Notes due 2029 | C50: =SUMPRODUCT(($C$44:$C$46<C46)*$C$40:$C$42) -> 1315.098
A51: General claims of same rank (pari passu)
A52: Tranche 1: 10.50% Senior Secured Notes due 2032 | C52: =SUMPRODUCT(($C$44:$C$46=C44)*$C$40:$C$42) -> 1315.098
A53: Tranche 2: 4.25% Senior Notes due 2029 | C53: =SUMPRODUCT(($C$44:$C$46=C45)*$C$40:$C$42) -> 0
A54: Tranche 3: 4.25% Convertible Senior Notes due 2029 | C54: =SUMPRODUCT(($C$44:$C$46=C46)*$C$40:$C$42) -> 0
A55: Recovery from general pool
A56: Tranche 1: 10.50% Senior Secured Notes due 2032 | C56: =IF(C52=0,0,C40/C52*MAX(0,MIN(C52,$C$18-SUM($C$32:$C$34)-C48))) -> 1068.848
A57: Tranche 2: 4.25% Senior Notes due 2029 | C57: =IF(C53=0,0,C41/C53*MAX(0,MIN(C53,$C$18-SUM($C$32:$C$34)-C49))) -> 0
A58: Tranche 3: 4.25% Convertible Senior Notes due 2029 | C58: =IF(C54=0,0,C42/C54*MAX(0,MIN(C54,$C$18-SUM($C$32:$C$34)-C50))) -> 0
A59: TOTAL RECOVERY
A60: Tranche 1: 10.50% Senior Secured Notes due 2032 | C60: =C32+C56 -> 1068.848
A61: Tranche 2: 4.25% Senior Notes due 2029 | C61: =C33+C57 -> 0
A62: Tranche 3: 4.25% Convertible Senior Notes due 2029 | C62: =C34+C58 -> 0
A63: Recovery %
A64: Tranche 1: 10.50% Senior Secured Notes due 2032 | C64: =IF(C20=0,1,C60/C20) -> 0.8127516
A65: Tranche 2: 4.25% Senior Notes due 2029 | C65: =IF(C21=0,1,C61/C21) -> 1
A66: Tranche 3: 4.25% Convertible Senior Notes due 2029 | C66: =IF(C22=0,1,C62/C22) -> 1
A67: Loss amount
A68: Tranche 1: 10.50% Senior Secured Notes due 2032 | C68: =C20-C60 -> 246.24999
A69: Tranche 2: 4.25% Senior Notes due 2029 | C69: =C21-C61 -> 0
A70: Tranche 3: 4.25% Convertible Senior Notes due 2029 | C70: =C22-C62 -> 0
A71: Loss %
A72: Tranche 1: 10.50% Senior Secured Notes due 2032 | C72: =IF(C20=0,0,C68/C20) -> 0.1872484
A73: Tranche 2: 4.25% Senior Notes due 2029 | C73: =IF(C21=0,0,C69/C21) -> 0
A74: Tranche 3: 4.25% Convertible Senior Notes due 2029 | C74: =IF(C22=0,0,C70/C22) -> 0
A75: Equity (residual after all claims) | C75: =MAX(0,$C$18-SUM($C$32:$C$34)-SUM($C$40:$C$42)) -> 0
A76: Exit price used (lesser of assumption and valuation coverage) | C76: =MIN(C17,100*CHOOSE(C7,C64,C65,C66)) -> 81.27516
A77: Principal proceeds received in period # | C77: =IF(Recovery!C8=1,C12+Assumptions!$C$39,C11) -> 3
A78: Cash flows to the position ($M) — period # 0 … 6
A79: Period # | C79: =COLUMN()-COLUMN($C$1) -> 0 | D79: =COLUMN()-COLUMN($C$1) -> 1 | E79: =COLUMN()-COLUMN($C$1) -> 2 | F79: =COLUMN()-COLUMN($C$1) -> 3 | G79: =COLUMN()-COLUMN($C$1) -> 4 | H79: =COLUMN()-COLUMN($C$1) -> 5 | I79: =COLUMN()-COLUMN($C$1) -> 6
A80: Cash coupon rate on target tranche | D80: =CHOOSE($C$7,'Debt Schedule'!G20,'Debt Schedule'!G33,'Debt Schedule'!G46) -> 0.105 | E80: =CHOOSE($C$7,'Debt Schedule'!H20,'Debt Schedule'!H33,'Debt Schedule'!H46) -> 0.105 | F80: =CHOOSE($C$7,'Debt Schedule'!I20,'Debt Schedule'!I33,'Debt Schedule'!I46) -> 0.105 | G80: =CHOOSE($C$7,'Debt Schedule'!J20,'Debt Schedule'!J33,'Debt Schedule'!J46) -> 0.105 | H80: =CHOOSE($C$7,'Debt Schedule'!K20,'Debt Schedule'!K33,'Debt Schedule'!K46) -> 0.105
A81: Cash interest received | D81: =IF(D79<=$C$16,$C$8*D80,0) -> 10.5 | E81: =IF(E79<=$C$16,$C$8*E80,0) -> 10.5 | F81: =IF(F79<=$C$16,$C$8*F80,0) -> 10.5 | G81: =IF(G79<=$C$16,$C$8*G80,0) -> 0 | H81: =IF(H79<=$C$16,$C$8*H80,0) -> 0
A82: Exit proceeds / recovery | D82: =IF(AND(Recovery!$C$8=0,D79=$C$11),$C$8*$C$76/100,0)+IF(AND(Recovery!$C$8=1,D79=$C$77),$C$14,0) -> 0 | E82: =IF(AND(Recovery!$C$8=0,E79=$C$11),$C$8*$C$76/100,0)+IF(AND(Recovery!$C$8=1,E79=$C$77),$C$14,0) -> 0 | F82: =IF(AND(Recovery!$C$8=0,F79=$C$11),$C$8*$C$76/100,0)+IF(AND(Recovery!$C$8=1,F79=$C$77),$C$14,0) -> 81.27516 | G82: =IF(AND(Recovery!$C$8=0,G79=$C$11),$C$8*$C$76/100,0)+IF(AND(Recovery!$C$8=1,G79=$C$77),$C$14,0) -> 0 | H82: =IF(AND(Recovery!$C$8=0,H79=$C$11),$C$8*$C$76/100,0)+IF(AND(Recovery!$C$8=1,H79=$C$77),$C$14,0) -> 0 | I82: =IF(AND(Recovery!$C$8=0,I79=$C$11),$C$8*$C$76/100,0)+IF(AND(Recovery!$C$8=1,I79=$C$77),$C$14,0) -> 0
A83: Net cash flow | C83: =-$C$10 -> -95 | D83: =D81+D82 -> 10.5 | E83: =E81+E82 -> 10.5 | F83: =F81+F82 -> 91.77516 | G83: =G81+G82 -> 0 | H83: =H81+H82 -> 0 | I83: =I81+I82 -> 0
A84: Cash interest received (total) | C84: =SUM($C$81:$I$81) -> 31.5
A85: Exit / recovery proceeds (total) | C85: =SUM($C$82:$I$82) -> 81.27516
A86: Total cash received | C86: =C84+C85 -> 112.77516
A87: Capital gain / (loss) vs purchase price (proceeds − face × price) | C87: =C85-C8*C9/100 -> -13.72484
A88: Absolute profit | C88: =C86-C10 -> 17.77516
A89: MOIC | C89: =C86/C10 -> 1.187107
A90: IRR | C90: =IF(C86<=0,-1,IFERROR(IRR($C$83:$I$83,MAX(-0.9,C89^(1/C77)-1)),IRR($C$83:$I$83,0.1))) -> 0.065384881
A91: Peak net leverage (projection) | C91: =MAX('Credit Metrics'!$G$11:$K$11) -> 7.3383123
A92: Minimum interest coverage (projection) | C92: =MIN('Credit Metrics'!$G$12:$K$12) -> 1.1807019
A93: Cumulative FCF (projection) | C93: =SUM('Operating Model'!$G$30:$K$30) -> 75.137413
A95: Yield & cross-checks (selected scenario)
A96: Current yield (year-1 cash coupon ÷ purchase price) | C96: =CHOOSE(Returns!C7,'Debt Schedule'!G20,'Debt Schedule'!G33,'Debt Schedule'!G46)/(Assumptions!$C$35/100) -> 0.11052632
A97: Yield to maturity (annual coupons to final maturity at par; Excel RATE) | C97: =IFERROR(RATE(YEARFRAC(Assumptions!$C$8,CHOOSE(Returns!C7,Assumptions!$J$56,Assumptions!$J$57,Assumptions!$J$58)),CHOOSE(Returns!C7,'Debt Schedule'!G20,'Debt Schedule'!G33,'Debt Schedule'!G46)*100,-Assumptions!$C$35,100),0) -> 0.11699955
A98: Dates for XIRR (entry date, then each model-period end) | C98: =Assumptions!$C$8 -> 46203 | D98: =EDATE(C98,12) -> 46568 | E98: =EDATE(D98,12) -> 46934 | F98: =EDATE(E98,12) -> 47299 | G98: =EDATE(F98,12) -> 47664 | H98: =EDATE(G98,12) -> 48029 | I98: =EDATE(H98,12) -> 48395
A99: XIRR (date-weighted cross-check; Excel XIRR) | C99: =IFERROR(XIRR(C83:I83,C98:I98),0) -> 0.065323461
A101: Summary by scenario (from Calc Engine)
C102: Base Case | D102: Downside | E102: Severe Downside
A103: Default modelled? | C103: ='Calc Engine'!C169 -> 0 | D103: ='Calc Engine'!C493 -> 0 | E103: ='Calc Engine'!C817 -> 1
A104: Cash investment | C104: ='Calc Engine'!C242 -> 95 | D104: ='Calc Engine'!C566 -> 95 | E104: ='Calc Engine'!C890 -> 95
...

Sheet Sensitivities
A1: Sensitivities — position IRR / MOIC under Base, Downside and Severe
A2: Axis values (blue) are inputs. Every cell is a formula: IRR over a cash-flow row, or an IRR / recovery from a full Calc Engine case. No data tables → recalculates in Excel and LibreOffice.
A3: ="Position: "&TEXT(Assumptions!$C$35,"0.0")&" purchase price, hold "&Assumptions!$C$37&" periods | Selected scenario: "&Assumptions!$D$10 -> Position: 95.0 purchase price, hold 3 periods | Selected scenario: Downside
A8: Table 1 — Purchase price vs IRR
A9: Purchase price (% of face) | B9: Offset | C9: Base Case | D9: Downside | E9: Severe Downside | F9: Selected
A10: =Assumptions!$C$35+B10 -> 87 | B10: -8 | C10: =J86 -> 0.16318604 | D10: =J91 -> 0.10082553 | E10: =J96 -> -0.083080837 | F10: =CHOOSE(Assumptions!$C$10,C10,D10,E10) -> 0.10082553
A11: =Assumptions!$C$35+B11 -> 91 | B11: -4 | C11: =J87 -> 0.14402812 | D11: =J92 -> 0.08254769 | E11: =J97 -> -0.095991159 | F11: =CHOOSE(Assumptions!$C$10,C11,D11,E11) -> 0.08254769
A12: =Assumptions!$C$35+B12 -> 95 | B12: 0 | C12: =J88 -> 0.12603362 | D12: =J93 -> 0.065384881 | E12: =J98 -> -0.10811295 | F12: =CHOOSE(Assumptions!$C$10,C12,D12,E12) -> 0.065384881
A13: =Assumptions!$C$35+B13 -> 99 | B13: 4 | C13: =J89 -> 0.10908562 | D13: =J94 -> 0.049224647 | E13: =J99 -> -0.11952677 | F13: =CHOOSE(Assumptions!$C$10,C13,D13,E13) -> 0.049224647
A14: =Assumptions!$C$35+B14 -> 103 | B14: 8 | C14: =J90 -> 0.093083178 | D14: =J95 -> 0.033969968 | E14: =J100 -> -0.13030195 | F14: =CHOOSE(Assumptions!$C$10,C14,D14,E14) -> 0.033969968
A18: Table 2 — Exit / recovery value (% of face, received at exit or after default) vs IRR
A19: Proceeds (% of face) | C19: Base Case | D19: Downside | E19: Severe Downside | F19: Selected
A20: 20 | C20: =J101 -> -0.22002894 | D20: =J106 -> -0.22002894 | E20: =J111 -> -0.18948166 | F20: =CHOOSE(Assumptions!$C$10,C20,D20,E20) -> -0.22002894
A21: 40 | C21: =J102 -> -0.10399063 | D21: =J107 -> -0.10399063 | E21: =J112 -> -0.085629803 | F21: =CHOOSE(Assumptions!$C$10,C21,D21,E21) -> -0.10399063
A22: 60 | C22: =J103 -> -0.014018471 | D22: =J108 -> -0.014018471 | E22: =J113 -> -0.011250165 | F22: =CHOOSE(Assumptions!$C$10,C22,D22,E22) -> -0.014018471
A23: 80 | C23: =J104 -> 0.060977511 | D23: =J109 -> 0.060977511 | E23: =J114 -> 0.048070533 | F23: =CHOOSE(Assumptions!$C$10,C23,D23,E23) -> 0.060977511
A24: 100 | C24: =J105 -> 0.12603362 | D24: =J110 -> 0.12603362 | E24: =J115 -> 0.098015191 | F24: =CHOOSE(Assumptions!$C$10,C24,D24,E24) -> 0.12603362
A28: Table 3 — EBITDA margin shift (all periods) vs IRR — full model re-run
A29: EBITDA margin shift (pts) | C29: Base Case | D29: Downside | E29: Severe Downside | F29: Selected
A30: -0.04 | C30: ='Calc Engine'!C1294 -> 0.10761133 | D30: ='Calc Engine'!C2914 -> -0.062354996 | E30: ='Calc Engine'!C4534 -> -0.10811295 | F30: =CHOOSE(Assumptions!$C$10,C30,D30,E30) -> -0.062354996
A31: -0.02 | C31: ='Calc Engine'!C1618 -> 0.12603362 | D31: ='Calc Engine'!C3238 -> -0.020690893 | E31: ='Calc Engine'!C4858 -> -0.10811295 | F31: =CHOOSE(Assumptions!$C$10,C31,D31,E31) -> -0.020690893
A32: 0 | C32: ='Calc Engine'!C1942 -> 0.12603362 | D32: ='Calc Engine'!C3562 -> 0.065384881 | E32: ='Calc Engine'!C5182 -> -0.10811295 | F32: =CHOOSE(Assumptions!$C$10,C32,D32,E32) -> 0.065384881
A33: 0.02 | C33: ='Calc Engine'!C2266 -> 0.12603362 | D33: ='Calc Engine'!C3886 -> 0.11052632 | E33: ='Calc Engine'!C5506 -> -0.084756486 | F33: =CHOOSE(Assumptions!$C$10,C33,D33,E33) -> 0.11052632
A34: 0.04 | C34: ='Calc Engine'!C2590 -> 0.12603362 | D34: ='Calc Engine'!C4210 -> 0.11052632 | E34: ='Calc Engine'!C5830 -> -0.032883676 | F34: =CHOOSE(Assumptions!$C$10,C34,D34,E34) -> 0.11052632
A38: Table 4 — Revenue growth shift (all periods) vs IRR — full model re-run
A39: Revenue growth shift (pts) | C39: Base Case | D39: Downside | E39: Severe Downside | F39: Selected
A40: -0.1 | C40: ='Calc Engine'!C6154 -> 0.12603362 | D40: ='Calc Engine'!C7774 -> -0.020690893 | E40: ='Calc Engine'!C9394 -> -0.10811295 | F40: =CHOOSE(Assumptions!$C$10,C40,D40,E40) -> -0.020690893
A41: -0.05 | C41: ='Calc Engine'!C6478 -> 0.12603362 | D41: ='Calc Engine'!C8098 -> 0.010319784 | E41: ='Calc Engine'!C9718 -> -0.10811295 | F41: =CHOOSE(Assumptions!$C$10,C41,D41,E41) -> 0.010319784
A42: 0 | C42: ='Calc Engine'!C6802 -> 0.12603362 | D42: ='Calc Engine'!C8422 -> 0.065384881 | E42: ='Calc Engine'!C10042 -> -0.10811295 | F42: =CHOOSE(Assumptions!$C$10,C42,D42,E42) -> 0.065384881
A43: 0.05 | C43: ='Calc Engine'!C7126 -> 0.12603362 | D43: ='Calc Engine'!C8746 -> 0.11052632 | E43: ='Calc Engine'!C10366 -> -0.099139494 | F43: =CHOOSE(Assumptions!$C$10,C43,D43,E43) -> 0.11052632
A44: 0.1 | C44: ='Calc Engine'!C7450 -> 0.12603362 | D44: ='Calc Engine'!C9070 -> 0.11052632 | E44: ='Calc Engine'!C10690 -> -0.072345328 | F44: =CHOOSE(Assumptions!$C$10,C44,D44,E44) -> 0.11052632
A48: Table 5 — Interest rate (SOFR) shift vs IRR — full model re-run (floating coupons and interest burden both move)
A49: SOFR shift (pts) | C49: Base Case | D49: Downside | E49: Severe Downside | F49: Selected
A50: -0.01 | C50: ='Calc Engine'!C11014 -> 0.12603362 | D50: ='Calc Engine'!C12634 -> 0.065384881 | E50: ='Calc Engine'!C14254 -> -0.10811295 | F50: =CHOOSE(Assumptions!$C$10,C50,D50,E50) -> 0.065384881
A51: -0.005 | C51: ='Calc Engine'!C11338 -> 0.12603362 | D51: ='Calc Engine'!C12958 -> 0.065384881 | E51: ='Calc Engine'!C14578 -> -0.10811295 | F51: =CHOOSE(Assumptions!$C$10,C51,D51,E51) -> 0.065384881
A52: 0 | C52: ='Calc Engine'!C11662 -> 0.12603362 | D52: ='Calc Engine'!C13282 -> 0.065384881 | E52: ='Calc Engine'!C14902 -> -0.10811295 | F52: =CHOOSE(Assumptions!$C$10,C52,D52,E52) -> 0.065384881
A53: 0.01 | C53: ='Calc Engine'!C11986 -> 0.12603362 | D53: ='Calc Engine'!C13606 -> 0.065384881 | E53: ='Calc Engine'!C15226 -> -0.10811295 | F53: =CHOOSE(Assumptions!$C$10,C53,D53,E53) -> 0.065384881
A54: 0.02 | C54: ='Calc Engine'!C12310 -> 0.12603362 | D54: ='Calc Engine'!C13930 -> 0.065384881 | E54: ='Calc Engine'!C15550 -> -0.10811295 | F54: =CHOOSE(Assumptions!$C$10,C54,D54,E54) -> 0.065384881
A58: Table 6 — Distressed valuation multiple shift (x) vs target-tranche recovery % (valuation waterfall)
A59: Multiple shift (x EBITDA) | C59: Base Case | D59: Downside | E59: Severe Downside | F59: Selected
A60: -2 | C60: ='Calc Engine'!C15799 -> 0.96082151 | D60: ='Calc Engine'!C17419 -> 0.52971027 | E60: ='Calc Engine'!C19039 -> 0.34051867 | F60: =CHOOSE(Assumptions!$C$10,C60,D60,E60) -> 0.52971027
A61: -1 | C61: ='Calc Engine'!C16123 -> 1 | D61: ='Calc Engine'!C17743 -> 0.52971027 | E61: ='Calc Engine'!C19363 -> 0.34051867 | F61: =CHOOSE(Assumptions!$C$10,C61,D61,E61) -> 0.52971027
A62: 0 | C62: ='Calc Engine'!C16447 -> 1 | D62: ='Calc Engine'!C18067 -> 0.60628401 | E62: ='Calc Engine'!C19687 -> 0.34051867 | F62: =CHOOSE(Assumptions!$C$10,C62,D62,E62) -> 0.60628401
A63: 1 | C63: ='Calc Engine'!C16771 -> 1 | D63: ='Calc Engine'!C18391 -> 0.72225454 | E63: ='Calc Engine'!C20011 -> 0.38088465 | F63: =CHOOSE(Assumptions!$C$10,C63,D63,E63) -> 0.72225454
A64: 2 | C64: ='Calc Engine'!C17095 -> 1 | D64: ='Calc Engine'!C18715 -> 0.83822506 | E64: ='Calc Engine'!C20335 -> 0.45706158 | F64: =CHOOSE(Assumptions!$C$10,C64,D64,E64) -> 0.83822506
A68: Table 7 — Recovery / exit value (% of face) vs MOIC
A69: Proceeds (% of face) | C69: Base Case | D69: Downside | E69: Severe Downside | F69: Selected
A70: =$A$20 -> 20 | C70: =(SUM('Calc Engine'!C313:I313)+Assumptions!$C$34*$A$70/100)/'Calc Engine'!C242 -> 0.54210526 | D70: =(SUM('Calc Engine'!C637:I637)+Assumptions!$C$34*$A$70/100)/'Calc Engine'!C566 -> 0.54210526 | E70: =(SUM('Calc Engine'!C961:I961)+Assumptions!$C$34*$A$70/100)/'Calc Engine'!C890 -> 0.54210526 | F70: =CHOOSE(Assumptions!$C$10,C70,D70,E70) -> 0.54210526
A71: =$A$21 -> 40 | C71: =(SUM('Calc Engine'!C313:I313)+Assumptions!$C$34*$A$71/100)/'Calc Engine'!C242 -> 0.75263158 | D71: =(SUM('Calc Engine'!C637:I637)+Assumptions!$C$34*$A$71/100)/'Calc Engine'!C566 -> 0.75263158 | E71: =(SUM('Calc Engine'!C961:I961)+Assumptions!$C$34*$A$71/100)/'Calc Engine'!C890 -> 0.75263158 | F71: =CHOOSE(Assumptions!$C$10,C71,D71,E71) -> 0.75263158
A72: =$A$22 -> 60 | C72: =(SUM('Calc Engine'!C313:I313)+Assumptions!$C$34*$A$72/100)/'Calc Engine'!C242 -> 0.96315789 | D72: =(SUM('Calc Engine'!C637:I637)+Assumptions!$C$34*$A$72/100)/'Calc Engine'!C566 -> 0.96315789 | E72: =(SUM('Calc Engine'!C961:I961)+Assumptions!$C$34*$A$72/100)/'Calc Engine'!C890 -> 0.96315789 | F72: =CHOOSE(Assumptions!$C$10,C72,D72,E72) -> 0.96315789
A73: =$A$23 -> 80 | C73: =(SUM('Calc Engine'!C313:I313)+Assumptions!$C$34*$A$73/100)/'Calc Engine'!C242 -> 1.1736842 | D73: =(SUM('Calc Engine'!C637:I637)+Assumptions!$C$34*$A$73/100)/'Calc Engine'!C566 -> 1.1736842 | E73: =(SUM('Calc Engine'!C961:I961)+Assumptions!$C$34*$A$73/100)/'Calc Engine'!C890 -> 1.1736842 | F73: =CHOOSE(Assumptions!$C$10,C73,D73,E73) -> 1.1736842
A74: =$A$24 -> 100 | C74: =(SUM('Calc Engine'!C313:I313)+Assumptions!$C$34*$A$74/100)/'Calc Engine'!C242 -> 1.3842105 | D74: =(SUM('Calc Engine'!C637:I637)+Assumptions!$C$34*$A$74/100)/'Calc Engine'!C566 -> 1.3842105 | E74: =(SUM('Calc Engine'!C961:I961)+Assumptions!$C$34*$A$74/100)/'Calc Engine'!C890 -> 1.3842105 | F74: =CHOOSE(Assumptions!$C$10,C74,D74,E74) -> 1.3842105
A82: Tables 3-6 re-run the operating model, debt schedule, default test and recovery waterfall for every point (Calc Engine cases 4-63).
A84: Supporting cash flows for Tables 1-2 (period 0 → 6) and resulting IRR
A85: Case | C85: t=0 | D85: t=1 | E85: t=2 | F85: t=3 | G85: t=4 | H85: t=5 | I85: t=6 | J85: IRR
A86: ="Base Case · price point 1" -> Base Case · price point 1 | C86: =-Assumptions!$C$34*$A$10/100*(1+Assumptions!$C$36) -> -87 | D86: ='Calc Engine'!D313+'Calc Engine'!D314 -> 10.5 | E86: ='Calc Engine'!E313+'Calc Engine'!E314 -> 10.5 | F86: ='Calc Engine'!F313+'Calc Engine'!F314 -> 110.5 | G86: ='Calc Engine'!G313+'Calc Engine'!G314 -> 0 | H86: ='Calc Engine'!H313+'Calc Engine'!H314 -> 0 | I86: ='Calc Engine'!I313+'Calc Engine'!I314 -> 0 | J86: =IF(SUM(D86:I86)<=0,-1,IFERROR(IRR(C86:I86,MAX(-0.9,(SUM(D86:I86)/-C86)^(1/Assumptions!$C$37)-1)),IRR(C86:I86,0.1))) -> 0.16318604
A87: ="Base Case · price point 2" -> Base Case · price point 2 | C87: =-Assumptions!$C$34*$A$11/100*(1+Assumptions!$C$36) -> -91 | D87: ='Calc Engine'!D313+'Calc Engine'!D314 -> 10.5 | E87: ='Calc Engine'!E313+'Calc Engine'!E314 -> 10.5 | F87: ='Calc Engine'!F313+'Calc Engine'!F314 -> 110.5 | G87: ='Calc Engine'!G313+'Calc Engine'!G314 -> 0 | H87: ='Calc Engine'!H313+'Calc Engine'!H314 -> 0 | I87: ='Calc Engine'!I313+'Calc Engine'!I314 -> 0 | J87: =IF(SUM(D87:I87)<=0,-1,IFERROR(IRR(C87:I87,MAX(-0.9,(SUM(D87:I87)/-C87)^(1/Assumptions!$C$37)-1)),IRR(C87:I87,0.1))) -> 0.14402812
A88: ="Base Case · price point 3" -> Base Case · price point 3 | C88: =-Assumptions!$C$34*$A$12/100*(1+Assumptions!$C$36) -> -95 | D88: ='Calc Engine'!D313+'Calc Engine'!D314 -> 10.5 | E88: ='Calc Engine'!E313+'Calc Engine'!E314 -> 10.5 | F88: ='Calc Engine'!F313+'Calc Engine'!F314 -> 110.5 | G88: ='Calc Engine'!G313+'Calc Engine'!G314 -> 0 | H88: ='Calc Engine'!H313+'Calc Engine'!H314 -> 0 | I88: ='Calc Engine'!I313+'Calc Engine'!I314 -> 0 | J88: =IF(SUM(D88:I88)<=0,-1,IFERROR(IRR(C88:I88,MAX(-0.9,(SUM(D88:I88)/-C88)^(1/Assumptions!$C$37)-1)),IRR(C88:I88,0.1))) -> 0.12603362
A89: ="Base Case · price point 4" -> Base Case · price point 4 | C89: =-Assumptions!$C$34*$A$13/100*(1+Assumptions!$C$36) -> -99 | D89: ='Calc Engine'!D313+'Calc Engine'!D314 -> 10.5 | E89: ='Calc Engine'!E313+'Calc Engine'!E314 -> 10.5 | F89: ='Calc Engine'!F313+'Calc Engine'!F314 -> 110.5 | G89: ='Calc Engine'!G313+'Calc Engine'!G314 -> 0 | H89: ='Calc Engine'!H313+'Calc Engine'!H314 -> 0 | I89: ='Calc Engine'!I313+'Calc Engine'!I314 -> 0 | J89: =IF(SUM(D89:I89)<=0,-1,IFERROR(IRR(C89:I89,MAX(-0.9,(SUM(D89:I89)/-C89)^(1/Assumptions!$C$37)-1)),IRR(C89:I89,0.1))) -> 0.10908562
A90: ="Base Case · price point 5" -> Base Case · price point 5 | C90: =-Assumptions!$C$34*$A$14/100*(1+Assumptions!$C$36) -> -103 | D90: ='Calc Engine'!D313+'Calc Engine'!D314 -> 10.5 | E90: ='Calc Engine'!E313+'Calc Engine'!E314 -> 10.5 | F90: ='Calc Engine'!F313+'Calc Engine'!F314 -> 110.5 | G90: ='Calc Engine'!G313+'Calc Engine'!G314 -> 0 | H90: ='Calc Engine'!H313+'Calc Engine'!H314 -> 0 | I90: ='Calc Engine'!I313+'Calc Engine'!I314 -> 0 | J90: =IF(SUM(D90:I90)<=0,-1,IFERROR(IRR(C90:I90,MAX(-0.9,(SUM(D90:I90)/-C90)^(1/Assumptions!$C$37)-1)),IRR(C90:I90,0.1))) -> 0.093083178
A91: ="Downside · price point 1" -> Downside · price point 1 | C91: =-Assumptions!$C$34*$A$10/100*(1+Assumptions!$C$36) -> -87 | D91: ='Calc Engine'!D637+'Calc Engine'!D638 -> 10.5 | E91: ='Calc Engine'!E637+'Calc Engine'!E638 -> 10.5 | F91: ='Calc Engine'!F637+'Calc Engine'!F638 -> 91.77516 | G91: ='Calc Engine'!G637+'Calc Engine'!G638 -> 0 | H91: ='Calc Engine'!H637+'Calc Engine'!H638 -> 0 | I91: ='Calc Engine'!I637+'Calc Engine'!I638 -> 0 | J91: =IF(SUM(D91:I91)<=0,-1,IFERROR(IRR(C91:I91,MAX(-0.9,(SUM(D91:I91)/-C91)^(1/Assumptions!$C$37)-1)),IRR(C91:I91,0.1))) -> 0.10082553
A92: ="Downside · price point 2" -> Downside · price point 2 | C92: =-Assumptions!$C$34*$A$11/100*(1+Assumptions!$C$36) -> -91 | D92: ='Calc Engine'!D637+'Calc Engine'!D638 -> 10.5 | E92: ='Calc Engine'!E637+'Calc Engine'!E638 -> 10.5 | F92: ='Calc Engine'!F637+'Calc Engine'!F638 -> 91.77516 | G92: ='Calc Engine'!G637+'Calc Engine'!G638 -> 0 | H92: ='Calc Engine'!H637+'Calc Engine'!H638 -> 0 | I92: ='Calc Engine'!I637+'Calc Engine'!I638 -> 0 | J92: =IF(SUM(D92:I92)<=0,-1,IFERROR(IRR(C92:I92,MAX(-0.9,(SUM(D92:I92)/-C92)^(1/Assumptions!$C$37)-1)),IRR(C92:I92,0.1))) -> 0.08254769
A93: ="Downside · price point 3" -> Downside · price point 3 | C93: =-Assumptions!$C$34*$A$12/100*(1+Assumptions!$C$36) -> -95 | D93: ='Calc Engine'!D637+'Calc Engine'!D638 -> 10.5 | E93: ='Calc Engine'!E637+'Calc Engine'!E638 -> 10.5 | F93: ='Calc Engine'!F637+'Calc Engine'!F638 -> 91.77516 | G93: ='Calc Engine'!G637+'Calc Engine'!G638 -> 0 | H93: ='Calc Engine'!H637+'Calc Engine'!H638 -> 0 | I93: ='Calc Engine'!I637+'Calc Engine'!I638 -> 0 | J93: =IF(SUM(D93:I93)<=0,-1,IFERROR(IRR(C93:I93,MAX(-0.9,(SUM(D93:I93)/-C93)^(1/Assumptions!$C$37)-1)),IRR(C93:I93,0.1))) -> 0.065384881
A94: ="Downside · price point 4" -> Downside · price point 4 | C94: =-Assumptions!$C$34*$A$13/100*(1+Assumptions!$C$36) -> -99 | D94: ='Calc Engine'!D637+'Calc Engine'!D638 -> 10.5 | E94: ='Calc Engine'!E637+'Calc Engine'!E638 -> 10.5 | F94: ='Calc Engine'!F637+'Calc Engine'!F638 -> 91.77516 | G94: ='Calc Engine'!G637+'Calc Engine'!G638 -> 0 | H94: ='Calc Engine'!H637+'Calc Engine'!H638 -> 0 | I94: ='Calc Engine'!I637+'Calc Engine'!I638 -> 0 | J94: =IF(SUM(D94:I94)<=0,-1,IFERROR(IRR(C94:I94,MAX(-0.9,(SUM(D94:I94)/-C94)^(1/Assumptions!$C$37)-1)),IRR(C94:I94,0.1))) -> 0.049224647
A95: ="Downside · price point 5" -> Downside · price point 5 | C95: =-Assumptions!$C$34*$A$14/100*(1+Assumptions!$C$36) -> -103 | D95: ='Calc Engine'!D637+'Calc Engine'!D638 -> 10.5 | E95: ='Calc Engine'!E637+'Calc Engine'!E638 -> 10.5 | F95: ='Calc Engine'!F637+'Calc Engine'!F638 -> 91.77516 | G95: ='Calc Engine'!G637+'Calc Engine'!G638 -> 0 | H95: ='Calc Engine'!H637+'Calc Engine'!H638 -> 0 | I95: ='Calc Engine'!I637+'Calc Engine'!I638 -> 0 | J95: =IF(SUM(D95:I95)<=0,-1,IFERROR(IRR(C95:I95,MAX(-0.9,(SUM(D95:I95)/-C95)^(1/Assumptions!$C$37)-1)),IRR(C95:I95,0.1))) -> 0.033969968
A96: ="Severe Downside · price point 1" -> Severe Downside · price point 1 | C96: =-Assumptions!$C$34*$A$10/100*(1+Assumptions!$C$36) -> -87 | D96: ='Calc Engine'!D961+'Calc Engine'!D962 -> 10.5 | E96: ='Calc Engine'!E961+'Calc Engine'!E962 -> 10.5 | F96: ='Calc Engine'!F961+'Calc Engine'!F962 -> 10.5 | G96: ='Calc Engine'!G961+'Calc Engine'!G962 -> 34.945728 | H96: ='Calc Engine'!H961+'Calc Engine'!H962 -> 0 | I96: ='Calc Engine'!I961+'Calc Engine'!I962 -> 0 | J96: =IF(SUM(D96:I96)<=0,-1,IFERROR(IRR(C96:I96,MAX(-0.9,(SUM(D96:I96)/-C96)^(1/Assumptions!$C$37)-1)),IRR(C96:I96,0.1))) -> -0.083080837
A97: ="Severe Downside · price point 2" -> Severe Downside · price point 2 | C97: =-Assumptions!$C$34*$A$11/100*(1+Assumptions!$C$36) -> -91 | D97: ='Calc Engine'!D961+'Calc Engine'!D962 -> 10.5 | E97: ='Calc Engine'!E961+'Calc Engine'!E962 -> 10.5 | F97: ='Calc Engine'!F961+'Calc Engine'!F962 -> 10.5 | G97: ='Calc Engine'!G961+'Calc Engine'!G962 -> 34.945728 | H97: ='Calc Engine'!H961+'Calc Engine'!H962 -> 0 | I97: ='Calc Engine'!I961+'Calc Engine'!I962 -> 0 | J97: =IF(SUM(D97:I97)<=0,-1,IFERROR(IRR(C97:I97,MAX(-0.9,(SUM(D97:I97)/-C97)^(1/Assumptions!$C$37)-1)),IRR(C97:I97,0.1))) -> -0.095991159
A98: ="Severe Downside · price point 3" -> Severe Downside · price point 3 | C98: =-Assumptions!$C$34*$A$12/100*(1+Assumptions!$C$36) -> -95 | D98: ='Calc Engine'!D961+'Calc Engine'!D962 -> 10.5 | E98: ='Calc Engine'!E961+'Calc Engine'!E962 -> 10.5 | F98: ='Calc Engine'!F961+'Calc Engine'!F962 -> 10.5 | G98: ='Calc Engine'!G961+'Calc Engine'!G962 -> 34.945728 | H98: ='Calc Engine'!H961+'Calc Engine'!H962 -> 0 | I98: ='Calc Engine'!I961+'Calc Engine'!I962 -> 0 | J98: =IF(SUM(D98:I98)<=0,-1,IFERROR(IRR(C98:I98,MAX(-0.9,(SUM(D98:I98)/-C98)^(1/Assumptions!$C$37)-1)),IRR(C98:I98,0.1))) -> -0.10811295
A99: ="Severe Downside · price point 4" -> Severe Downside · price point 4 | C99: =-Assumptions!$C$34*$A$13/100*(1+Assumptions!$C$36) -> -99 | D99: ='Calc Engine'!D961+'Calc Engine'!D962 -> 10.5 | E99: ='Calc Engine'!E961+'Calc Engine'!E962 -> 10.5 | F99: ='Calc Engine'!F961+'Calc Engine'!F962 -> 10.5 | G99: ='Calc Engine'!G961+'Calc Engine'!G962 -> 34.945728 | H99: ='Calc Engine'!H961+'Calc Engine'!H962 -> 0 | I99: ='Calc Engine'!I961+'Calc Engine'!I962 -> 0 | J99: =IF(SUM(D99:I99)<=0,-1,IFERROR(IRR(C99:I99,MAX(-0.9,(SUM(D99:I99)/-C99)^(1/Assumptions!$C$37)-1)),IRR(C99:I99,0.1))) -> -0.11952677
A100: ="Severe Downside · price point 5" -> Severe Downside · price point 5 | C100: =-Assumptions!$C$34*$A$14/100*(1+Assumptions!$C$36) -> -103 | D100: ='Calc Engine'!D961+'Calc Engine'!D962 -> 10.5 | E100: ='Calc Engine'!E961+'Calc Engine'!E962 -> 10.5 | F100: ='Calc Engine'!F961+'Calc Engine'!F962 -> 10.5 | G100: ='Calc Engine'!G961+'Calc Engine'!G962 -> 34.945728 | H100: ='Calc Engine'!H961+'Calc Engine'!H962 -> 0 | I100: ='Calc Engine'!I961+'Calc Engine'!I962 -> 0 | J100: =IF(SUM(D100:I100)<=0,-1,IFERROR(IRR(C100:I100,MAX(-0.9,(SUM(D100:I100)/-C100)^(1/Assumptions!$C$37)-1)),IRR(C100:I100,0.1))) -> -0.13030195
A101: ="Base Case · rec point 1" -> Base Case · rec point 1 | C101: ='Calc Engine'!C315 -> -95 | D101: ='Calc Engine'!D313+IF('Calc Engine'!D311='Calc Engine'!C309,Assumptions!$C$34*$A$20/100,0) -> 10.5 | E101: ='Calc Engine'!E313+IF('Calc Engine'!E311='Calc Engine'!C309,Assumptions!$C$34*$A$20/100,0) -> 10.5 | F101: ='Calc Engine'!F313+IF('Calc Engine'!F311='Calc Engine'!C309,Assumptions!$C$34*$A$20/100,0) -> 30.5 | G101: ='Calc Engine'!G313+IF('Calc Engine'!G311='Calc Engine'!C309,Assumptions!$C$34*$A$20/100,0) -> 0 | H101: ='Calc Engine'!H313+IF('Calc Engine'!H311='Calc Engine'!C309,Assumptions!$C$34*$A$20/100,0) -> 0 | I101: ='Calc Engine'!I313+IF('Calc Engine'!I311='Calc Engine'!C309,Assumptions!$C$34*$A$20/100,0) -> 0 | J101: =IF(SUM(D101:I101)<=0,-1,IFERROR(IRR(C101:I101,MAX(-0.9,(SUM(D101:I101)/-C101)^(1/Assumptions!$C$37)-1)),IRR(C101:I101,0.1))) -> -0.22002894
A102: ="Base Case · rec point 2" -> Base Case · rec point 2 | C102: ='Calc Engine'!C315 -> -95 | D102: ='Calc Engine'!D313+IF('Calc Engine'!D311='Calc Engine'!C309,Assumptions!$C$34*$A$21/100,0) -> 10.5 | E102: ='Calc Engine'!E313+IF('Calc Engine'!E311='Calc Engine'!C309,Assumptions!$C$34*$A$21/100,0) -> 10.5 | F102: ='Calc Engine'!F313+IF('Calc Engine'!F311='Calc Engine'!C309,Assumptions!$C$34*$A$21/100,0) -> 50.5 | G102: ='Calc Engine'!G313+IF('Calc Engine'!G311='Calc Engine'!C309,Assumptions!$C$34*$A$21/100,0) -> 0 | H102: ='Calc Engine'!H313+IF('Calc Engine'!H311='Calc Engine'!C309,Assumptions!$C$34*$A$21/100,0) -> 0 | I102: ='Calc Engine'!I313+IF('Calc Engine'!I311='Calc Engine'!C309,Assumptions!$C$34*$A$21/100,0) -> 0 | J102: =IF(SUM(D102:I102)<=0,-1,IFERROR(IRR(C102:I102,MAX(-0.9,(SUM(D102:I102)/-C102)^(1/Assumptions!$C$37)-1)),IRR(C102:I102,0.1))) -> -0.10399063
A103: ="Base Case · rec point 3" -> Base Case · rec point 3 | C103: ='Calc Engine'!C315 -> -95 | D103: ='Calc Engine'!D313+IF('Calc Engine'!D311='Calc Engine'!C309,Assumptions!$C$34*$A$22/100,0) -> 10.5 | E103: ='Calc Engine'!E313+IF('Calc Engine'!E311='Calc Engine'!C309,Assumptions!$C$34*$A$22/100,0) -> 10.5 | F103: ='Calc Engine'!F313+IF('Calc Engine'!F311='Calc Engine'!C309,Assumptions!$C$34*$A$22/100,0) -> 70.5 | G103: ='Calc Engine'!G313+IF('Calc Engine'!G311='Calc Engine'!C309,Assumptions!$C$34*$A$22/100,0) -> 0 | H103: ='Calc Engine'!H313+IF('Calc Engine'!H311='Calc Engine'!C309,Assumptions!$C$34*$A$22/100,0) -> 0 | I103: ='Calc Engine'!I313+IF('Calc Engine'!I311='Calc Engine'!C309,Assumptions!$C$34*$A$22/100,0) -> 0 | J103: =IF(SUM(D103:I103)<=0,-1,IFERROR(IRR(C103:I103,MAX(-0.9,(SUM(D103:I103)/-C103)^(1/Assumptions!$C$37)-1)),IRR(C103:I103,0.1))) -> -0.014018471
A104: ="Base Case · rec point 4" -> Base Case · rec point 4 | C104: ='Calc Engine'!C315 -> -95 | D104: ='Calc Engine'!D313+IF('Calc Engine'!D311='Calc Engine'!C309,Assumptions!$C$34*$A$23/100,0) -> 10.5 | E104: ='Calc Engine'!E313+IF('Calc Engine'!E311='Calc Engine'!C309,Assumptions!$C$34*$A$23/100,0) -> 10.5 | F104: ='Calc Engine'!F313+IF('Calc Engine'!F311='Calc Engine'!C309,Assumptions!$C$34*$A$23/100,0) -> 90.5 | G104: ='Calc Engine'!G313+IF('Calc Engine'!G311='Calc Engine'!C309,Assumptions!$C$34*$A$23/100,0) -> 0 | H104: ='Calc Engine'!H313+IF('Calc Engine'!H311='Calc Engine'!C309,Assumptions!$C$34*$A$23/100,0) -> 0 | I104: ='Calc Engine'!I313+IF('Calc Engine'!I311='Calc Engine'!C309,Assumptions!$C$34*$A$23/100,0) -> 0 | J104: =IF(SUM(D104:I104)<=0,-1,IFERROR(IRR(C104:I104,MAX(-0.9,(SUM(D104:I104)/-C104)^(1/Assumptions!$C$37)-1)),IRR(C104:I104,0.1))) -> 0.060977511
A105: ="Base Case · rec point 5" -> Base Case · rec point 5 | C105: ='Calc Engine'!C315 -> -95 | D105: ='Calc Engine'!D313+IF('Calc Engine'!D311='Calc Engine'!C309,Assumptions!$C$34*$A$24/100,0) -> 10.5 | E105: ='Calc Engine'!E313+IF('Calc Engine'!E311='Calc Engine'!C309,Assumptions!$C$34*$A$24/100,0) -> 10.5 | F105: ='Calc Engine'!F313+IF('Calc Engine'!F311='Calc Engine'!C309,Assumptions!$C$34*$A$24/100,0) -> 110.5 | G105: ='Calc Engine'!G313+IF('Calc Engine'!G311='Calc Engine'!C309,Assumptions!$C$34*$A$24/100,0) -> 0 | H105: ='Calc Engine'!H313+IF('Calc Engine'!H311='Calc Engine'!C309,Assumptions!$C$34*$A$24/100,0) -> 0 | I105: ='Calc Engine'!I313+IF('Calc Engine'!I311='Calc Engine'!C309,Assumptions!$C$34*$A$24/100,0) -> 0 | J105: =IF(SUM(D105:I105)<=0,-1,IFERROR(IRR(C105:I105,MAX(-0.9,(SUM(D105:I105)/-C105)^(1/Assumptions!$C$37)-1)),IRR(C105:I105,0.1))) -> 0.12603362
A106: ="Downside · rec point 1" -> Downside · rec point 1 | C106: ='Calc Engine'!C639 -> -95 | D106: ='Calc Engine'!D637+IF('Calc Engine'!D635='Calc Engine'!C633,Assumptions!$C$34*$A$20/100,0) -> 10.5 | E106: ='Calc Engine'!E637+IF('Calc Engine'!E635='Calc Engine'!C633,Assumptions!$C$34*$A$20/100,0) -> 10.5 | F106: ='Calc Engine'!F637+IF('Calc Engine'!F635='Calc Engine'!C633,Assumptions!$C$34*$A$20/100,0) -> 30.5 | G106: ='Calc Engine'!G637+IF('Calc Engine'!G635='Calc Engine'!C633,Assumptions!$C$34*$A$20/100,0) -> 0 | H106: ='Calc Engine'!H637+IF('Calc Engine'!H635='Calc Engine'!C633,Assumptions!$C$34*$A$20/100,0) -> 0 | I106: ='Calc Engine'!I637+IF('Calc Engine'!I635='Calc Engine'!C633,Assumptions!$C$34*$A$20/100,0) -> 0 | J106: =IF(SUM(D106:I106)<=0,-1,IFERROR(IRR(C106:I106,MAX(-0.9,(SUM(D106:I106)/-C106)^(1/Assumptions!$C$37)-1)),IRR(C106:I106,0.1))) -> -0.22002894
A107: ="Downside · rec point 2" -> Downside · rec point 2 | C107: ='Calc Engine'!C639 -> -95 | D107: ='Calc Engine'!D637+IF('Calc Engine'!D635='Calc Engine'!C633,Assumptions!$C$34*$A$21/100,0) -> 10.5 | E107: ='Calc Engine'!E637+IF('Calc Engine'!E635='Calc Engine'!C633,Assumptions!$C$34*$A$21/100,0) -> 10.5 | F107: ='Calc Engine'!F637+IF('Calc Engine'!F635='Calc Engine'!C633,Assumptions!$C$34*$A$21/100,0) -> 50.5 | G107: ='Calc Engine'!G637+IF('Calc Engine'!G635='Calc Engine'!C633,Assumptions!$C$34*$A$21/100,0) -> 0 | H107: ='Calc Engine'!H637+IF('Calc Engine'!H635='Calc Engine'!C633,Assumptions!$C$34*$A$21/100,0) -> 0 | I107: ='Calc Engine'!I637+IF('Calc Engine'!I635='Calc Engine'!C633,Assumptions!$C$34*$A$21/100,0) -> 0 | J107: =IF(SUM(D107:I107)<=0,-1,IFERROR(IRR(C107:I107,MAX(-0.9,(SUM(D107:I107)/-C107)^(1/Assumptions!$C$37)-1)),IRR(C107:I107,0.1))) -> -0.10399063
A108: ="Downside · rec point 3" -> Downside · rec point 3 | C108: ='Calc Engine'!C639 -> -95 | D108: ='Calc Engine'!D637+IF('Calc Engine'!D635='Calc Engine'!C633,Assumptions!$C$34*$A$22/100,0) -> 10.5 | E108: ='Calc Engine'!E637+IF('Calc Engine'!E635='Calc Engine'!C633,Assumptions!$C$34*$A$22/100,0) -> 10.5 | F108: ='Calc Engine'!F637+IF('Calc Engine'!F635='Calc Engine'!C633,Assumptions!$C$34*$A$22/100,0) -> 70.5 | G108: ='Calc Engine'!G637+IF('Calc Engine'!G635='Calc Engine'!C633,Assumptions!$C$34*$A$22/100,0) -> 0 | H108: ='Calc Engine'!H637+IF('Calc Engine'!H635='Calc Engine'!C633,Assumptions!$C$34*$A$22/100,0) -> 0 | I108: ='Calc Engine'!I637+IF('Calc Engine'!I635='Calc Engine'!C633,Assumptions!$C$34*$A$22/100,0) -> 0 | J108: =IF(SUM(D108:I108)<=0,-1,IFERROR(IRR(C108:I108,MAX(-0.9,(SUM(D108:I108)/-C108)^(1/Assumptions!$C$37)-1)),IRR(C108:I108,0.1))) -> -0.014018471
A109: ="Downside · rec point 4" -> Downside · rec point 4 | C109: ='Calc Engine'!C639 -> -95 | D109: ='Calc Engine'!D637+IF('Calc Engine'!D635='Calc Engine'!C633,Assumptions!$C$34*$A$23/100,0) -> 10.5 | E109: ='Calc Engine'!E637+IF('Calc Engine'!E635='Calc Engine'!C633,Assumptions!$C$34*$A$23/100,0) -> 10.5 | F109: ='Calc Engine'!F637+IF('Calc Engine'!F635='Calc Engine'!C633,Assumptions!$C$34*$A$23/100,0) -> 90.5 | G109: ='Calc Engine'!G637+IF('Calc Engine'!G635='Calc Engine'!C633,Assumptions!$C$34*$A$23/100,0) -> 0 | H109: ='Calc Engine'!H637+IF('Calc Engine'!H635='Calc Engine'!C633,Assumptions!$C$34*$A$23/100,0) -> 0 | I109: ='Calc Engine'!I637+IF('Calc Engine'!I635='Calc Engine'!C633,Assumptions!$C$34*$A$23/100,0) -> 0 | J109: =IF(SUM(D109:I109)<=0,-1,IFERROR(IRR(C109:I109,MAX(-0.9,(SUM(D109:I109)/-C109)^(1/Assumptions!$C$37)-1)),IRR(C109:I109,0.1))) -> 0.060977511
A110: ="Downside · rec point 5" -> Downside · rec point 5 | C110: ='Calc Engine'!C639 -> -95 | D110: ='Calc Engine'!D637+IF('Calc Engine'!D635='Calc Engine'!C633,Assumptions!$C$34*$A$24/100,0) -> 10.5 | E110: ='Calc Engine'!E637+IF('Calc Engine'!E635='Calc Engine'!C633,Assumptions!$C$34*$A$24/100,0) -> 10.5 | F110: ='Calc Engine'!F637+IF('Calc Engine'!F635='Calc Engine'!C633,Assumptions!$C$34*$A$24/100,0) -> 110.5 | G110: ='Calc Engine'!G637+IF('Calc Engine'!G635='Calc Engine'!C633,Assumptions!$C$34*$A$24/100,0) -> 0 | H110: ='Calc Engine'!H637+IF('Calc Engine'!H635='Calc Engine'!C633,Assumptions!$C$34*$A$24/100,0) -> 0 | I110: ='Calc Engine'!I637+IF('Calc Engine'!I635='Calc Engine'!C633,Assumptions!$C$34*$A$24/100,0) -> 0 | J110: =IF(SUM(D110:I110)<=0,-1,IFERROR(IRR(C110:I110,MAX(-0.9,(SUM(D110:I110)/-C110)^(1/Assumptions!$C$37)-1)),IRR(C110:I110,0.1))) -> 0.12603362
A111: ="Severe Downside · rec point 1" -> Severe Downside · rec point 1 | C111: ='Calc Engine'!C963 -> -95 | D111: ='Calc Engine'!D961+IF('Calc Engine'!D959='Calc Engine'!C957,Assumptions!$C$34*$A$20/100,0) -> 10.5 | E111: ='Calc Engine'!E961+IF('Calc Engine'!E959='Calc Engine'!C957,Assumptions!$C$34*$A$20/100,0) -> 10.5 | F111: ='Calc Engine'!F961+IF('Calc Engine'!F959='Calc Engine'!C957,Assumptions!$C$34*$A$20/100,0) -> 10.5 | G111: ='Calc Engine'!G961+IF('Calc Engine'!G959='Calc Engine'!C957,Assumptions!$C$34*$A$20/100,0) -> 20 | H111: ='Calc Engine'!H961+IF('Calc Engine'!H959='Calc Engine'!C957,Assumptions!$C$34*$A$20/100,0) -> 0 | I111: ='Calc Engine'!I961+IF('Calc Engine'!I959='Calc Engine'!C957,Assumptions!$C$34*$A$20/100,0) -> 0 | J111: =IF(SUM(D111:I111)<=0,-1,IFERROR(IRR(C111:I111,MAX(-0.9,(SUM(D111:I111)/-C111)^(1/Assumptions!$C$37)-1)),IRR(C111:I111,0.1))) -> -0.18948166
A112: ="Severe Downside · rec point 2" -> Severe Downside · rec point 2 | C112: ='Calc Engine'!C963 -> -95 | D112: ='Calc Engine'!D961+IF('Calc Engine'!D959='Calc Engine'!C957,Assumptions!$C$34*$A$21/100,0) -> 10.5 | E112: ='Calc Engine'!E961+IF('Calc Engine'!E959='Calc Engine'!C957,Assumptions!$C$34*$A$21/100,0) -> 10.5 | F112: ='Calc Engine'!F961+IF('Calc Engine'!F959='Calc Engine'!C957,Assumptions!$C$34*$A$21/100,0) -> 10.5 | G112: ='Calc Engine'!G961+IF('Calc Engine'!G959='Calc Engine'!C957,Assumptions!$C$34*$A$21/100,0) -> 40 | H112: ='Calc Engine'!H961+IF('Calc Engine'!H959='Calc Engine'!C957,Assumptions!$C$34*$A$21/100,0) -> 0 | I112: ='Calc Engine'!I961+IF('Calc Engine'!I959='Calc Engine'!C957,Assumptions!$C$34*$A$21/100,0) -> 0 | J112: =IF(SUM(D112:I112)<=0,-1,IFERROR(IRR(C112:I112,MAX(-0.9,(SUM(D112:I112)/-C112)^(1/Assumptions!$C$37)-1)),IRR(C112:I112,0.1))) -> -0.085629803
A113: ="Severe Downside · rec point 3" -> Severe Downside · rec point 3 | C113: ='Calc Engine'!C963 -> -95 | D113: ='Calc Engine'!D961+IF('Calc Engine'!D959='Calc Engine'!C957,Assumptions!$C$34*$A$22/100,0) -> 10.5 | E113: ='Calc Engine'!E961+IF('Calc Engine'!E959='Calc Engine'!C957,Assumptions!$C$34*$A$22/100,0) -> 10.5 | F113: ='Calc Engine'!F961+IF('Calc Engine'!F959='Calc Engine'!C957,Assumptions!$C$34*$A$22/100,0) -> 10.5 | G113: ='Calc Engine'!G961+IF('Calc Engine'!G959='Calc Engine'!C957,Assumptions!$C$34*$A$22/100,0) -> 60 | H113: ='Calc Engine'!H961+IF('Calc Engine'!H959='Calc Engine'!C957,Assumptions!$C$34*$A$22/100,0) -> 0 | I113: ='Calc Engine'!I961+IF('Calc Engine'!I959='Calc Engine'!C957,Assumptions!$C$34*$A$22/100,0) -> 0 | J113: =IF(SUM(D113:I113)<=0,-1,IFERROR(IRR(C113:I113,MAX(-0.9,(SUM(D113:I113)/-C113)^(1/Assumptions!$C$37)-1)),IRR(C113:I113,0.1))) -> -0.011250165
A114: ="Severe Downside · rec point 4" -> Severe Downside · rec point 4 | C114: ='Calc Engine'!C963 -> -95 | D114: ='Calc Engine'!D961+IF('Calc Engine'!D959='Calc Engine'!C957,Assumptions!$C$34*$A$23/100,0) -> 10.5 | E114: ='Calc Engine'!E961+IF('Calc Engine'!E959='Calc Engine'!C957,Assumptions!$C$34*$A$23/100,0) -> 10.5 | F114: ='Calc Engine'!F961+IF('Calc Engine'!F959='Calc Engine'!C957,Assumptions!$C$34*$A$23/100,0) -> 10.5 | G114: ='Calc Engine'!G961+IF('Calc Engine'!G959='Calc Engine'!C957,Assumptions!$C$34*$A$23/100,0) -> 80 | H114: ='Calc Engine'!H961+IF('Calc Engine'!H959='Calc Engine'!C957,Assumptions!$C$34*$A$23/100,0) -> 0 | I114: ='Calc Engine'!I961+IF('Calc Engine'!I959='Calc Engine'!C957,Assumptions!$C$34*$A$23/100,0) -> 0 | J114: =IF(SUM(D114:I114)<=0,-1,IFERROR(IRR(C114:I114,MAX(-0.9,(SUM(D114:I114)/-C114)^(1/Assumptions!$C$37)-1)),IRR(C114:I114,0.1))) -> 0.048070533
A115: ="Severe Downside · rec point 5" -> Severe Downside · rec point 5 | C115: ='Calc Engine'!C963 -> -95 | D115: ='Calc Engine'!D961+IF('Calc Engine'!D959='Calc Engine'!C957,Assumptions!$C$34*$A$24/100,0) -> 10.5 | E115: ='Calc Engine'!E961+IF('Calc Engine'!E959='Calc Engine'!C957,Assumptions!$C$34*$A$24/100,0) -> 10.5 | F115: ='Calc Engine'!F961+IF('Calc Engine'!F959='Calc Engine'!C957,Assumptions!$C$34*$A$24/100,0) -> 10.5 | G115: ='Calc Engine'!G961+IF('Calc Engine'!G959='Calc Engine'!C957,Assumptions!$C$34*$A$24/100,0) -> 100 | H115: ='Calc Engine'!H961+IF('Calc Engine'!H959='Calc Engine'!C957,Assumptions!$C$34*$A$24/100,0) -> 0 | I115: ='Calc Engine'!I961+IF('Calc Engine'!I959='Calc Engine'!C957,Assumptions!$C$34*$A$24/100,0) -> 0 | J115: =IF(SUM(D115:I115)<=0,-1,IFERROR(IRR(C115:I115,MAX(-0.9,(SUM(D115:I115)/-C115)^(1/Assumptions!$C$37)-1)),IRR(C115:I115,0.1))) -> 0.098015191

Sheet Investment Summary
A1: Investment Summary — every figure is a live link to the model
A2: =Assumptions!$C$5&" | PUBLIC DATA CASE | HYPOTHETICAL INVESTMENT TERMS | Active scenario: "&Assumptions!$D$10 -> AMC Networks (AMC Global Media) | PUBLIC DATA CASE | HYPOTHETICAL INVESTMENT TERMS | Active scenario: Downside
A4: Investment recommendation | C4: ='Investment Summary'!$C$41 -> HOLD
A5: Instrument | C5: =CHOOSE(Assumptions!$C$33,Assumptions!$A$56,Assumptions!$A$57,Assumptions!$A$58)&" @ "&TEXT(Assumptions!$C$35,"0.0") -> 10.50% Senior Secured Notes due 2032 @ 95.0
A6: Face value / purchase price / cash investment ($M) | C6: =TEXT(Assumptions!$C$34,"0.0")&" / "&TEXT(Assumptions!$C$35,"0.0")&" / "&TEXT(Returns!C10,"0.0") -> 100.0 / 95.0 / 95.0
A7: Credit score (0-100) | C7: ='Credit Metrics'!$G$61 -> 59.381637
A8: Risk band | C8: ='Credit Metrics'!$G$62 -> Elevated
A9: Base-case IRR | C9: =Scenarios!C27 -> 0.12603362
A10: Downside IRR | C10: =Scenarios!D27 -> 0.065384881
A11: Severe downside IRR | C11: =Scenarios!E27 -> -0.10811295
A12: Base / Downside / Severe MOIC | C12: =TEXT(Scenarios!C28,"0.00x")&" / "&TEXT(Scenarios!D28,"0.00x")&" / "&TEXT(Scenarios!E28,"0.00x") -> 1.38x / 1.19x / 0.70x
A13: Probability-weighted IRR | C13: =Scenarios!$C$31 -> 0.06109225
A14: Probability-weighted MOIC | C14: =Scenarios!$C$33 -> 1.1782679
A15: Probability of payment default | C15: =Scenarios!$C$34 -> 0.2
A16: Target-tranche recovery — Downside (valuation waterfall) | C16: =Scenarios!D25 -> 0.60628401
A17: Target-tranche recovery — Severe (valuation waterfall) | C17: =Scenarios!E25 -> 0.34051867
A18: Recovery (selected scenario, from Recovery tab) | C18: =Returns!C15 -> 0.60628401
A19: Net leverage — base period (LTM Jun-26) | C19: ='Credit Metrics'!F11 -> 4.0619016
A20: Interest coverage — base period | C20: ='Credit Metrics'!F12 -> 1.8359011
A21: Net leverage — LTM Jun-27E (selected scenario) | C21: ='Credit Metrics'!G11 -> 4.9066397
A22: Interest coverage — LTM Jun-27E (selected scenario) | C22: ='Credit Metrics'!G12 -> 1.5900564
A23: Liquidity — LTM Jun-27E (selected scenario, $M) | C23: ='Credit Metrics'!G16 -> 518.82155
A24: Covenant breaches (selected scenario, count of failed tests) | C24: ='Credit Metrics'!C46 -> 11
A25: Maturity alert | C25: ='Capital Structure'!$C$30 -> OK: no material maturities within window
A26: Maturity concentration | C26: ='Capital Structure'!$C$28 -> No single-period concentration
A27: Recommendation evidence (thresholds on Assumptions §3)
A28: Test | C28: Actual | D28: Required | E28: Result | F28: Core?
A29: Base-case IRR clears hurdle | C29: =Scenarios!C27 -> 0.12603362 | D29: =Assumptions!$C$40 -> 0.12 | E29: =IF(C29>=D29,"PASS","FAIL") -> PASS | F29: core
A30: Probability-weighted IRR clears hurdle | C30: =Scenarios!$C$31 -> 0.06109225 | D30: =Assumptions!$C$40 -> 0.12 | E30: =IF(C30>=D30,"PASS","FAIL") -> FAIL | F30: core
A31: Downside IRR stays above floor | C31: =Scenarios!D27 -> 0.065384881 | D31: =Assumptions!$C$41 -> 0 | E31: =IF(C31>=D31,"PASS","FAIL") -> PASS | F31: core
A32: Downside recovery meets minimum (valuation waterfall) | C32: =Scenarios!D25 -> 0.60628401 | D32: =Assumptions!$C$44 -> 0.7 | E32: =IF(C32>=D32,"PASS","FAIL") -> FAIL | F32: core
A33: Base-case refinancing succeeds (failures = 0) | C33: =Scenarios!C21 -> 0 | D33: =0 -> 0 | E33: =IF(C33<=D33,"PASS","FAIL") -> PASS | F33: core
A34: Yield to maturity meets minimum | C34: =IFERROR(RATE(YEARFRAC(Assumptions!$C$8,CHOOSE(Assumptions!$C$33,Assumptions!$J$56,Assumptions!$J$57,Assumptions!$J$58)),'Calc Engine'!D312*100,-Assumptions!$C$35,100),0) -> 0.11699955 | D34: =Assumptions!$C$42 -> 0.1 | E34: =IF(C34>=D34,"PASS","FAIL") -> PASS
A35: Net leverage within maximum | C35: ='Credit Metrics'!F11 -> 4.0619016 | D35: =Assumptions!$C$43 -> 6 | E35: =IF(C35<=D35,"PASS","FAIL") -> PASS
A36: Covenant headroom (base case, minimum) | C36: ='Calc Engine'!C165 -> 0.20963225 | D36: =Assumptions!$C$45 -> 0.15 | E36: =IF(C36>=D36,"PASS","FAIL") -> PASS
A37: Principal protected in severe case (recovery % × 100 ≥ price) | C37: =Scenarios!E25*100 -> 34.051867 | D37: =Assumptions!$C$35 -> 95 | E37: =IF(C37>=D37,"PASS","FAIL") -> FAIL
A38: No unresolved high-priority diligence | C38: =Assumptions!$C$48 -> 6 | D38: =0 -> 0 | E38: =IF(C38<=D38,"PASS","FAIL") -> FAIL
A39: Core test failures | C39: =COUNTIF(E29:E33,"FAIL") -> 2
A40: Secondary test failures | C40: =COUNTIF(E34:E38,"FAIL") -> 2
A41: DECISION (PROCEED / HOLD / PASS) | C41: =IF(AND(C39=0,C40<=Assumptions!$C$46),"PROCEED",IF(OR(AND(E29="FAIL",E31="FAIL"),C39>=Assumptions!$C$47),"PASS","HOLD")) -> HOLD
A44: Model integrity checks
A45: Check | C45: Value | D45: Status
A46: Scenario probabilities sum to 100% | C46: =Assumptions!$C$127 -> 1 | D46: =IF(ABS(C46-1)<0.0001,"OK","ERROR") -> OK
A47: Credit score weights sum to 100 | C47: =Assumptions!$C$141 -> 100 | D47: =IF(ABS(C47-100)<0.0001,"OK","ERROR") -> OK
A48: Debt roll-forward bridge (sum of abs. differences) | C48: =SUMPRODUCT(ABS('Cash Flow'!$G$23:$K$23)) -> 0 | D48: =IF(C48<0.001,"OK","ERROR") -> OK
A49: Recovery waterfall: recoveries + equity + costs = value | C49: =Recovery!C75 -> 0 | D49: =IF(ABS(C49)<0.001,"OK","ERROR") -> OK
A50: Detailed tabs reconcile to Calc Engine (sum of abs. diffs) | C50: =SUMPRODUCT(ABS(Scenarios!$E$41:$E$48)) -> 0 | D50: =IF(C50<0.001,"OK","ERROR") -> OK
A51: Model-calculated EBITDA / NOI equals company-reported figure (sum of abs. differences) | C51: =ABS('Historical Financials'!B45)+ABS('Historical Financials'!C45)+ABS('Historical Financials'!D45)+ABS('Historical Financials'!E45)+ABS('Historical Financials'!F45)+ABS('Historical Financials'!G45) -> 0 | D51: =IF(C51<0.001,"OK","ERROR") -> OK
A52: Formula errors across model tabs (count) | C52: =SUMPRODUCT(--ISERROR('Operating Model'!$C$5:$K$60))+SUMPRODUCT(--ISERROR('Debt Schedule'!$C$5:$K$300))+SUMPRODUCT(--ISERROR('Cash Flow'!$C$5:$K$40))+SUMPRODUCT(--ISERROR('Credit Metrics'!$C$5:$K$120))+SUMPRODUCT(--ISERROR(Recovery!$C$5:$K$300))+SUMPRODUCT(--ISERROR(Returns!$C$5:$K$300))+SUMPRODUCT(--ISERROR(Scenarios!$C$4:$F$60))+SUMPRODUCT(--ISERROR('Capital Structure'!$A$4:$L$60))+SUMPRODUCT(--ISERROR(Sensitivities!$A$4:$J$200))+SUMPRODUCT(--ISERROR('Calc Engine'!$C$5:$K$20427)) -> 0 | D52: =IF(C52=0,"OK","ERROR") -> OK
A53: OVERALL MODEL STATUS | D53: =IF(COUNTIF(D46:D52,"OK")=ROWS(D46:D52),"ALL CHECKS PASS","CHECK MODEL") -> ALL CHECKS PASS

Sheet Sources
A1: Sources — which model input came from which source
A2: PUBLIC FILING datapoints: every reported historical number below is a blue input on the Historical Financials tab; the Value column here is a live LINK to that cell. Page = footer page of the cited filing where recoverable. Derived values are formulas, never hardcodes.
A4: Source document | B4: Form | C4: Period | D4: Accession | E4: Filed | F4: URL | G4: Retrieved | H4: Data type | I4: Status
A5: AMC Networks Inc. (now AMC Global Media Inc.) — Form 10-K, period ended 2025-12-31 | B5: Annual report | C5: 2025-12-31 | D5: 0001514991-26-000011 | E5: 2026-02-11 | F5: https://www.sec.gov/Archives/edgar/data/1514991/000151499126000011/amcx-20251231.htm | G5: 2026-10-07 | H5: Annual report | I5: PUBLIC FILING
A6: AMC Networks Inc. — Form 10-K, period ended 2024-12-31 | B6: Annual report | C6: 2024-12-31 | D6: 0001514991-25-000009 | E6: 2025-02-14 | F6: https://www.sec.gov/Archives/edgar/data/1514991/000151499125000009/amcx-20241231.htm | G6: 2026-10-07 | H6: Annual report | I6: PUBLIC FILING
A7: AMC Global Media Inc. — Form 10-Q, period ended 2026-06-30 | B7: Quarterly report | C7: 2026-06-30 | D7: 0001514991-26-000089 | E7: 2026-07-30 | F7: https://www.sec.gov/Archives/edgar/data/1514991/000151499126000089/amcx-20260630.htm | G7: 2026-10-07 | H7: Quarterly report | I7: PUBLIC FILING
A8: SOFR — Secured Overnight Financing Rate (3.90% on 2026-10-06) | B8: Macro rate | E8: 2026-10-06 | F8: https://fred.stlouisfed.org/series/SOFR | G8: 2026-10-07 | H8: Macro rate | I8: PUBLIC FILING
A10: Datapoint register (each row: one reported figure or disclosure, with filing, page/section and the model cell it feeds)
A11: Datapoint ID | B11: Metric | C11: Period | D11: Value (US$M) — link to model cell | E11: Unit | F11: Filing | G11: Accession | H11: Filing date | I11: Page | J11: Section | K11: Source URL | L11: Kind | M11: Model cell | N11: Raw text in filing / note
A12: amcx.sbc.FY2023 | B12: sbc | C12: FY2023 | D12: ='Historical Financials'!B9 -> 25.665 | E12: US$M | F12: Form 10-K for period ended 2024-12-31 | G12: 0001514991-25-000009 | H12: 2025-02-14 | I12: 58 | J12: Non-GAAP reconciliation (MD&A) | K12: https://www.sec.gov/Archives/edgar/data/1514991/000151499125000009/amcx-20241231.htm | L12: reported | M12: Historical Financials!B9 | N12: as printed: 25,665 ($ thousands) — AOI add-back (FY2024 10-K, consolidated column)
A13: amcx.revenue.FY2023 | B13: revenue | C13: FY2023 | D13: ='Historical Financials'!B6 -> 2711.877 | E13: US$M | F13: Form 10-K for period ended 2025-12-31 | G13: 0001514991-26-000011 | H13: 2026-02-11 | I13: F-5 | J13: Consolidated Statements of Income (Loss) | K13: https://www.sec.gov/Archives/edgar/data/1514991/000151499126000011/amcx-20251231.htm | L13: reported | M13: Historical Financials!B6 | N13: as printed: 2,711,877 ($ thousands)
A14: amcx.direct_costs.FY2023 | B14: direct_costs | C14: FY2023 | D14: ='Historical Financials'!B7 -> 1327.5 | E14: US$M | F14: Form 10-K for period ended 2025-12-31 | G14: 0001514991-26-000011 | H14: 2026-02-11 | I14: F-5 | J14: Consolidated Statements of Income (Loss) | K14: https://www.sec.gov/Archives/edgar/data/1514991/000151499126000011/amcx-20251231.htm | L14: reported | M14: Historical Financials!B7 | N14: as printed: 1,327,500 ($ thousands)
A15: amcx.sga.FY2023 | B15: sga | C15: FY2023 | D15: ='Historical Financials'!B8 -> 764.087 | E15: US$M | F15: Form 10-K for period ended 2025-12-31 | G15: 0001514991-26-000011 | H15: 2026-02-11 | I15: F-5 | J15: Consolidated Statements of Income (Loss) | K15: https://www.sec.gov/Archives/edgar/data/1514991/000151499126000011/amcx-20251231.htm | L15: reported | M15: Historical Financials!B8 | N15: as printed: 764,087 ($ thousands)
A16: amcx.cloud_amort.FY2023 | B16: cloud_amort | C16: FY2023 | D16: ='Historical Financials'!B10 -> 10.543 | E16: US$M | F16: Form 10-K for period ended 2024-12-31 | G16: 0001514991-25-000009 | H16: 2025-02-14 | I16: 58 | J16: Non-GAAP reconciliation (MD&A) | K16: https://www.sec.gov/Archives/edgar/data/1514991/000151499125000009/amcx-20241231.htm | L16: reported | M16: Historical Financials!B10 | N16: as printed: 10,543 ($ thousands) — AOI add-back (FY2024 10-K)
A17: amcx.jv_aoi.FY2023 | B17: jv_aoi | C17: FY2023 | D17: ='Historical Financials'!B11 -> 13.606 | E17: US$M | F17: Form 10-K for period ended 2024-12-31 | G17: 0001514991-25-000009 | H17: 2025-02-14 | I17: 58 | J17: Non-GAAP reconciliation (MD&A) | K17: https://www.sec.gov/Archives/edgar/data/1514991/000151499125000009/amcx-20241231.htm | L17: reported | M17: Historical Financials!B11 | N17: as printed: 13,606 ($ thousands) — AOI add-back (FY2024 10-K)
A18: amcx.da.FY2023 | B18: da | C18: FY2023 | D18: ='Historical Financials'!B12 -> 107.402 | E18: US$M | F18: Form 10-K for period ended 2025-12-31 | G18: 0001514991-26-000011 | H18: 2026-02-11 | I18: F-5 | J18: Consolidated Statements of Income (Loss) | K18: https://www.sec.gov/Archives/edgar/data/1514991/000151499126000011/amcx-20251231.htm | L18: reported | M18: Historical Financials!B12 | N18: as printed: 107,402 ($ thousands)
A19: amcx.interest_expense.FY2023 | B19: interest_expense | C19: FY2023 | D19: ='Historical Financials'!B13 -> 152.703 | E19: US$M | F19: Form 10-K for period ended 2025-12-31 | G19: 0001514991-26-000011 | H19: 2026-02-11 | I19: F-5 | J19: Consolidated Statements of Income (Loss) | K19: https://www.sec.gov/Archives/edgar/data/1514991/000151499126000011/amcx-20251231.htm | L19: reported | M19: Historical Financials!B13 | N19: as printed: 152,703 ($ thousands)
A20: amcx.taxes.FY2023 | B20: taxes | C20: FY2023 | D20: ='Historical Financials'!B14 -> 94.606 | E20: US$M | F20: Form 10-K for period ended 2025-12-31 | G20: 0001514991-26-000011 | H20: 2026-02-11 | I20: F-5 | J20: Consolidated Statements of Income (Loss) | K20: https://www.sec.gov/Archives/edgar/data/1514991/000151499126000011/amcx-20251231.htm | L20: reported | M20: Historical Financials!B14 | N20: as printed: 94,606 ($ thousands)
A21: amcx.capex.FY2023 | B21: capex | C21: FY2023 | D21: ='Historical Financials'!B16 -> 35.207 | E21: US$M | F21: Form 10-K for period ended 2025-12-31 | G21: 0001514991-26-000011 | H21: 2026-02-11 | I21: F-8 | J21: Consolidated Statements of Cash Flows | K21: https://www.sec.gov/Archives/edgar/data/1514991/000151499126000011/amcx-20251231.htm | L21: reported | M21: Historical Financials!B16 | N21: as printed: 35,207 ($ thousands)
A22: amcx.cfo.FY2023 | B22: cfo | C22: FY2023 | D22: ='Historical Financials'!B15 -> 203.919 | E22: US$M | F22: Form 10-K for period ended 2025-12-31 | G22: 0001514991-26-000011 | H22: 2026-02-11 | I22: F-8 | J22: Consolidated Statements of Cash Flows | K22: https://www.sec.gov/Archives/edgar/data/1514991/000151499126000011/amcx-20251231.htm | L22: reported | M22: Historical Financials!B15 | N22: as printed: 203,919 ($ thousands)
A23: amcx.sbc.FY2024 | B23: sbc | C23: FY2024 | D23: ='Historical Financials'!C9 -> 26.051 | E23: US$M | F23: Form 10-K for period ended 2025-12-31 | G23: 0001514991-26-000011 | H23: 2026-02-11 | I23: 60 | J23: Non-GAAP reconciliation (MD&A) | K23: https://www.sec.gov/Archives/edgar/data/1514991/000151499126000011/amcx-20251231.htm | L23: reported | M23: Historical Financials!C9 | N23: as printed: 26,051 ($ thousands) — AOI add-back
A24: amcx.revenue.FY2024 | B24: revenue | C24: FY2024 | D24: ='Historical Financials'!C6 -> 2421.314 | E24: US$M | F24: Form 10-K for period ended 2025-12-31 | G24: 0001514991-26-000011 | H24: 2026-02-11 | I24: F-5 | J24: Consolidated Statements of Income (Loss) | K24: https://www.sec.gov/Archives/edgar/data/1514991/000151499126000011/amcx-20251231.htm | L24: reported | M24: Historical Financials!C6 | N24: as printed: 2,421,314 ($ thousands)
A25: amcx.direct_costs.FY2024 | B25: direct_costs | C25: FY2024 | D25: ='Historical Financials'!C7 -> 1132.593 | E25: US$M | F25: Form 10-K for period ended 2025-12-31 | G25: 0001514991-26-000011 | H25: 2026-02-11 | I25: F-5 | J25: Consolidated Statements of Income (Loss) | K25: https://www.sec.gov/Archives/edgar/data/1514991/000151499126000011/amcx-20251231.htm | L25: reported | M25: Historical Financials!C7 | N25: as printed: 1,132,593 ($ thousands)
A26: amcx.sga.FY2024 | B26: sga | C26: FY2024 | D26: ='Historical Financials'!C8 -> 781.329 | E26: US$M | F26: Form 10-K for period ended 2025-12-31 | G26: 0001514991-26-000011 | H26: 2026-02-11 | I26: F-5 | J26: Consolidated Statements of Income (Loss) | K26: https://www.sec.gov/Archives/edgar/data/1514991/000151499126000011/amcx-20251231.htm | L26: reported | M26: Historical Financials!C8 | N26: as printed: 781,329 ($ thousands)
A27: amcx.cloud_amort.FY2024 | B27: cloud_amort | C27: FY2024 | D27: ='Historical Financials'!C10 -> 13.452 | E27: US$M | F27: Form 10-K for period ended 2025-12-31 | G27: 0001514991-26-000011 | H27: 2026-02-11 | I27: 60 | J27: Non-GAAP reconciliation (MD&A) | K27: https://www.sec.gov/Archives/edgar/data/1514991/000151499126000011/amcx-20251231.htm | L27: reported | M27: Historical Financials!C10 | N27: as printed: 13,452 ($ thousands) — AOI add-back
A28: amcx.jv_aoi.FY2024 | B28: jv_aoi | C28: FY2024 | D28: ='Historical Financials'!C11 -> 15.678 | E28: US$M | F28: Form 10-K for period ended 2025-12-31 | G28: 0001514991-26-000011 | H28: 2026-02-11 | I28: 60 | J28: Non-GAAP reconciliation (MD&A) | K28: https://www.sec.gov/Archives/edgar/data/1514991/000151499126000011/amcx-20251231.htm | L28: reported | M28: Historical Financials!C11 | N28: as printed: 15,678 ($ thousands) — AOI add-back
A29: amcx.da.FY2024 | B29: da | C29: FY2024 | D29: ='Historical Financials'!C12 -> 98.015 | E29: US$M | F29: Form 10-K for period ended 2025-12-31 | G29: 0001514991-26-000011 | H29: 2026-02-11 | I29: F-5 | J29: Consolidated Statements of Income (Loss) | K29: https://www.sec.gov/Archives/edgar/data/1514991/000151499126000011/amcx-20251231.htm | L29: reported | M29: Historical Financials!C12 | N29: as printed: 98,015 ($ thousands)
A30: amcx.interest_expense.FY2024 | B30: interest_expense | C30: FY2024 | D30: ='Historical Financials'!C13 -> 166.186 | E30: US$M | F30: Form 10-K for period ended 2025-12-31 | G30: 0001514991-26-000011 | H30: 2026-02-11 | I30: F-5 | J30: Consolidated Statements of Income (Loss) | K30: https://www.sec.gov/Archives/edgar/data/1514991/000151499126000011/amcx-20251231.htm | L30: reported | M30: Historical Financials!C13 | N30: as printed: 166,186 ($ thousands)
A31: amcx.taxes.FY2024 | B31: taxes | C31: FY2024 | D31: ='Historical Financials'!C14 -> 43.49 | E31: US$M | F31: Form 10-K for period ended 2025-12-31 | G31: 0001514991-26-000011 | H31: 2026-02-11 | I31: F-5 | J31: Consolidated Statements of Income (Loss) | K31: https://www.sec.gov/Archives/edgar/data/1514991/000151499126000011/amcx-20251231.htm | L31: reported | M31: Historical Financials!C14 | N31: as printed: 43,490 ($ thousands)
A32: amcx.capex.FY2024 | B32: capex | C32: FY2024 | D32: ='Historical Financials'!C16 -> 44.775 | E32: US$M | F32: Form 10-K for period ended 2025-12-31 | G32: 0001514991-26-000011 | H32: 2026-02-11 | I32: F-8 | J32: Consolidated Statements of Cash Flows | K32: https://www.sec.gov/Archives/edgar/data/1514991/000151499126000011/amcx-20251231.htm | L32: reported | M32: Historical Financials!C16 | N32: as printed: 44,775 ($ thousands)
A33: amcx.cfo.FY2024 | B33: cfo | C33: FY2024 | D33: ='Historical Financials'!C15 -> 375.615 | E33: US$M | F33: Form 10-K for period ended 2025-12-31 | G33: 0001514991-26-000011 | H33: 2026-02-11 | I33: F-8 | J33: Consolidated Statements of Cash Flows | K33: https://www.sec.gov/Archives/edgar/data/1514991/000151499126000011/amcx-20251231.htm | L33: reported | M33: Historical Financials!C15 | N33: as printed: 375,615 ($ thousands)
A34: amcx.sbc.FY2025 | B34: sbc | C34: FY2025 | D34: ='Historical Financials'!D9 -> 25.33 | E34: US$M | F34: Form 10-K for period ended 2025-12-31 | G34: 0001514991-26-000011 | H34: 2026-02-11 | I34: 60 | J34: Non-GAAP reconciliation (MD&A) | K34: https://www.sec.gov/Archives/edgar/data/1514991/000151499126000011/amcx-20251231.htm | L34: reported | M34: Historical Financials!D9 | N34: as printed: 25,330 ($ thousands) — AOI add-back
A35: amcx.revenue.FY2025 | B35: revenue | C35: FY2025 | D35: ='Historical Financials'!D6 -> 2311.801 | E35: US$M | F35: Form 10-K for period ended 2025-12-31 | G35: 0001514991-26-000011 | H35: 2026-02-11 | I35: F-5 | J35: Consolidated Statements of Income (Loss) | K35: https://www.sec.gov/Archives/edgar/data/1514991/000151499126000011/amcx-20251231.htm | L35: reported | M35: Historical Financials!D6 | N35: as printed: 2,311,801 ($ thousands)
A36: amcx.direct_costs.FY2025 | B36: direct_costs | C36: FY2025 | D36: ='Historical Financials'!D7 -> 1141.393 | E36: US$M | F36: Form 10-K for period ended 2025-12-31 | G36: 0001514991-26-000011 | H36: 2026-02-11 | I36: F-5 | J36: Consolidated Statements of Income (Loss) | K36: https://www.sec.gov/Archives/edgar/data/1514991/000151499126000011/amcx-20251231.htm | L36: reported | M36: Historical Financials!D7 | N36: as printed: 1,141,393 ($ thousands)
A37: amcx.sga.FY2025 | B37: sga | C37: FY2025 | D37: ='Historical Financials'!D8 -> 818.341 | E37: US$M | F37: Form 10-K for period ended 2025-12-31 | G37: 0001514991-26-000011 | H37: 2026-02-11 | I37: F-5 | J37: Consolidated Statements of Income (Loss) | K37: https://www.sec.gov/Archives/edgar/data/1514991/000151499126000011/amcx-20251231.htm | L37: reported | M37: Historical Financials!D8 | N37: as printed: 818,341 ($ thousands)
A38: amcx.cloud_amort.FY2025 | B38: cloud_amort | C38: FY2025 | D38: ='Historical Financials'!D10 -> 10.733 | E38: US$M | F38: Form 10-K for period ended 2025-12-31 | G38: 0001514991-26-000011 | H38: 2026-02-11 | I38: 60 | J38: Non-GAAP reconciliation (MD&A) | K38: https://www.sec.gov/Archives/edgar/data/1514991/000151499126000011/amcx-20251231.htm | L38: reported | M38: Historical Financials!D10 | N38: as printed: 10,733 ($ thousands) — AOI add-back
A39: amcx.jv_aoi.FY2025 | B39: jv_aoi | C39: FY2025 | D39: ='Historical Financials'!D11 -> 23.744 | E39: US$M | F39: Form 10-K for period ended 2025-12-31 | G39: 0001514991-26-000011 | H39: 2026-02-11 | I39: 60 | J39: Non-GAAP reconciliation (MD&A) | K39: https://www.sec.gov/Archives/edgar/data/1514991/000151499126000011/amcx-20251231.htm | L39: reported | M39: Historical Financials!D11 | N39: as printed: 23,744 ($ thousands) — AOI add-back
A40: amcx.da.FY2025 | B40: da | C40: FY2025 | D40: ='Historical Financials'!D12 -> 94.425 | E40: US$M | F40: Form 10-K for period ended 2025-12-31 | G40: 0001514991-26-000011 | H40: 2026-02-11 | I40: F-5 | J40: Consolidated Statements of Income (Loss) | K40: https://www.sec.gov/Archives/edgar/data/1514991/000151499126000011/amcx-20251231.htm | L40: reported | M40: Historical Financials!D12 | N40: as printed: 94,425 ($ thousands)
A41: amcx.interest_expense.FY2025 | B41: interest_expense | C41: FY2025 | D41: ='Historical Financials'!D13 -> 172.353 | E41: US$M | F41: Form 10-K for period ended 2025-12-31 | G41: 0001514991-26-000011 | H41: 2026-02-11 | I41: F-5 | J41: Consolidated Statements of Income (Loss) | K41: https://www.sec.gov/Archives/edgar/data/1514991/000151499126000011/amcx-20251231.htm | L41: reported | M41: Historical Financials!D13 | N41: as printed: 172,353 ($ thousands)
A42: amcx.taxes.FY2025 | B42: taxes | C42: FY2025 | D42: ='Historical Financials'!D14 -> 46.226 | E42: US$M | F42: Form 10-K for period ended 2025-12-31 | G42: 0001514991-26-000011 | H42: 2026-02-11 | I42: F-5 | J42: Consolidated Statements of Income (Loss) | K42: https://www.sec.gov/Archives/edgar/data/1514991/000151499126000011/amcx-20251231.htm | L42: reported | M42: Historical Financials!D14 | N42: as printed: 46,226 ($ thousands)
A43: amcx.capex.FY2025 | B43: capex | C43: FY2025 | D43: ='Historical Financials'!D16 -> 33.303 | E43: US$M | F43: Form 10-K for period ended 2025-12-31 | G43: 0001514991-26-000011 | H43: 2026-02-11 | I43: F-8 | J43: Consolidated Statements of Cash Flows | K43: https://www.sec.gov/Archives/edgar/data/1514991/000151499126000011/amcx-20251231.htm | L43: reported | M43: Historical Financials!D16 | N43: as printed: 33,303 ($ thousands)
A44: amcx.cfo.FY2025 | B44: cfo | C44: FY2025 | D44: ='Historical Financials'!D15 -> 305.67 | E44: US$M | F44: Form 10-K for period ended 2025-12-31 | G44: 0001514991-26-000011 | H44: 2026-02-11 | I44: F-8 | J44: Consolidated Statements of Cash Flows | K44: https://www.sec.gov/Archives/edgar/data/1514991/000151499126000011/amcx-20251231.htm | L44: reported | M44: Historical Financials!D15 | N44: as printed: 305,670 ($ thousands)
A45: amcx.sbc.H1-2025 | B45: sbc | C45: H1-2025 | D45: ='Historical Financials'!E9 -> 13.8 | E45: US$M | F45: Form 10-Q for period ended 2026-06-30 | G45: 0001514991-26-000089 | H45: 2026-07-30 | I45: section only | J45: Non-GAAP reconciliation (MD&A) | K45: https://www.sec.gov/Archives/edgar/data/1514991/000151499126000089/amcx-20260630.htm | L45: reported | M45: Historical Financials!E9 | N45: as printed: 13,800 ($ thousands) — AOI add-back (reconciliation figure)
A46: amcx.revenue.H1-2025 | B46: revenue | C46: H1-2025 | D46: ='Historical Financials'!E6 -> 1155.257 | E46: US$M | F46: Form 10-Q for period ended 2026-06-30 | G46: 0001514991-26-000089 | H46: 2026-07-30 | I46: section only | J46: Condensed Consolidated Statements of Income (Loss) / MD&A | K46: https://www.sec.gov/Archives/edgar/data/1514991/000151499126000089/amcx-20260630.htm | L46: reported | M46: Historical Financials!E6 | N46: as printed: 1,155,257 ($ thousands)
A47: amcx.direct_costs.H1-2025 | B47: direct_costs | C47: H1-2025 | D47: ='Historical Financials'!E7 -> 551.222 | E47: US$M | F47: Form 10-Q for period ended 2026-06-30 | G47: 0001514991-26-000089 | H47: 2026-07-30 | I47: section only | J47: MD&A results of operations | K47: https://www.sec.gov/Archives/edgar/data/1514991/000151499126000089/amcx-20260630.htm | L47: reported | M47: Historical Financials!E7 | N47: as printed: 551,222 ($ thousands)
A48: amcx.sga.H1-2025 | B48: sga | C48: H1-2025 | D48: ='Historical Financials'!E8 -> 419.679 | E48: US$M | F48: Form 10-Q for period ended 2026-06-30 | G48: 0001514991-26-000089 | H48: 2026-07-30 | I48: section only | J48: MD&A results of operations | K48: https://www.sec.gov/Archives/edgar/data/1514991/000151499126000089/amcx-20260630.htm | L48: reported | M48: Historical Financials!E8 | N48: as printed: 419,679 ($ thousands)
A49: amcx.cloud_amort.H1-2025 | B49: cloud_amort | C49: H1-2025 | D49: ='Historical Financials'!E10 -> 5.938 | E49: US$M | F49: Form 10-Q for period ended 2026-06-30 | G49: 0001514991-26-000089 | H49: 2026-07-30 | I49: section only | J49: Non-GAAP reconciliation (MD&A) | K49: https://www.sec.gov/Archives/edgar/data/1514991/000151499126000089/amcx-20260630.htm | L49: reported | M49: Historical Financials!E10 | N49: as printed: 5,938 ($ thousands)
A50: amcx.jv_aoi.H1-2025 | B50: jv_aoi | C50: H1-2025 | D50: ='Historical Financials'!E11 -> 9.777 | E50: US$M | F50: Form 10-Q for period ended 2026-06-30 | G50: 0001514991-26-000089 | H50: 2026-07-30 | I50: section only | J50: Non-GAAP reconciliation (MD&A) | K50: https://www.sec.gov/Archives/edgar/data/1514991/000151499126000089/amcx-20260630.htm | L50: reported | M50: Historical Financials!E11 | N50: as printed: 9,777 ($ thousands)
A51: amcx.da.H1-2025 | B51: da | C51: H1-2025 | D51: ='Historical Financials'!E12 -> 47.372 | E51: US$M | F51: Form 10-Q for period ended 2026-06-30 | G51: 0001514991-26-000089 | H51: 2026-07-30 | I51: section only | J51: MD&A results of operations | K51: https://www.sec.gov/Archives/edgar/data/1514991/000151499126000089/amcx-20260630.htm | L51: reported | M51: Historical Financials!E12 | N51: as printed: 47,372 ($ thousands)
A52: amcx.interest_expense.H1-2025 | B52: interest_expense | C52: H1-2025 | D52: ='Historical Financials'!E13 -> 85.852 | E52: US$M | F52: Form 10-Q for period ended 2026-06-30 | G52: 0001514991-26-000089 | H52: 2026-07-30 | I52: section only | J52: MD&A results of operations | K52: https://www.sec.gov/Archives/edgar/data/1514991/000151499126000089/amcx-20260630.htm | L52: reported | M52: Historical Financials!E13 | N52: as printed: 85,852 ($ thousands)
A53: amcx.taxes.H1-2025 | B53: taxes | C53: H1-2025 | D53: ='Historical Financials'!E14 -> 31.027 | E53: US$M | F53: Form 10-Q for period ended 2026-06-30 | G53: 0001514991-26-000089 | H53: 2026-07-30 | I53: section only | J53: MD&A results of operations | K53: https://www.sec.gov/Archives/edgar/data/1514991/000151499126000089/amcx-20260630.htm | L53: reported | M53: Historical Financials!E14 | N53: as printed: 31,027 ($ thousands) — H1-2026 is a BENEFIT (sign flipped to a negative provision); H1-2025 is an expense
A54: amcx.capex.H1-2025 | B54: capex | C54: H1-2025 | D54: ='Historical Financials'!E16 -> 21.67 | E54: US$M | F54: Form 10-Q for period ended 2026-06-30 | G54: 0001514991-26-000089 | H54: 2026-07-30 | I54: section only | J54: Condensed Consolidated Statements of Cash Flows | K54: https://www.sec.gov/Archives/edgar/data/1514991/000151499126000089/amcx-20260630.htm | L54: reported | M54: Historical Financials!E16 | N54: as printed: 21,670 ($ thousands)
A55: amcx.cfo.H1-2025 | B55: cfo | C55: H1-2025 | D55: ='Historical Financials'!E15 -> 211.596 | E55: US$M | F55: Form 10-Q for period ended 2026-06-30 | G55: 0001514991-26-000089 | H55: 2026-07-30 | I55: section only | J55: Condensed Consolidated Statements of Cash Flows | K55: https://www.sec.gov/Archives/edgar/data/1514991/000151499126000089/amcx-20260630.htm | L55: reported | M55: Historical Financials!E15 | N55: as printed: 211,596 ($ thousands)
A56: amcx.sbc.H1-2026 | B56: sbc | C56: H1-2026 | D56: ='Historical Financials'!F9 -> 12.826 | E56: US$M | F56: Form 10-Q for period ended 2026-06-30 | G56: 0001514991-26-000089 | H56: 2026-07-30 | I56: section only | J56: Non-GAAP reconciliation (MD&A) | K56: https://www.sec.gov/Archives/edgar/data/1514991/000151499126000089/amcx-20260630.htm | L56: reported | M56: Historical Financials!F9 | N56: as printed: 12,826 ($ thousands) — AOI add-back (reconciliation figure)
A57: amcx.revenue.H1-2026 | B57: revenue | C57: H1-2026 | D57: ='Historical Financials'!F6 -> 1089.622 | E57: US$M | F57: Form 10-Q for period ended 2026-06-30 | G57: 0001514991-26-000089 | H57: 2026-07-30 | I57: section only | J57: Condensed Consolidated Statements of Income (Loss) / MD&A | K57: https://www.sec.gov/Archives/edgar/data/1514991/000151499126000089/amcx-20260630.htm | L57: reported | M57: Historical Financials!F6 | N57: as printed: 1,089,622 ($ thousands)
A58: amcx.direct_costs.H1-2026 | B58: direct_costs | C58: H1-2026 | D58: ='Historical Financials'!F7 -> 571.961 | E58: US$M | F58: Form 10-Q for period ended 2026-06-30 | G58: 0001514991-26-000089 | H58: 2026-07-30 | I58: section only | J58: MD&A results of operations | K58: https://www.sec.gov/Archives/edgar/data/1514991/000151499126000089/amcx-20260630.htm | L58: reported | M58: Historical Financials!F7 | N58: as printed: 571,961 ($ thousands)
A59: amcx.sga.H1-2026 | B59: sga | C59: H1-2026 | D59: ='Historical Financials'!F8 -> 426.623 | E59: US$M | F59: Form 10-Q for period ended 2026-06-30 | G59: 0001514991-26-000089 | H59: 2026-07-30 | I59: section only | J59: MD&A results of operations | K59: https://www.sec.gov/Archives/edgar/data/1514991/000151499126000089/amcx-20260630.htm | L59: reported | M59: Historical Financials!F8 | N59: as printed: 426,623 ($ thousands)
A60: amcx.cloud_amort.H1-2026 | B60: cloud_amort | C60: H1-2026 | D60: ='Historical Financials'!F10 -> 4.416 | E60: US$M | F60: Form 10-Q for period ended 2026-06-30 | G60: 0001514991-26-000089 | H60: 2026-07-30 | I60: section only | J60: Non-GAAP reconciliation (MD&A) | K60: https://www.sec.gov/Archives/edgar/data/1514991/000151499126000089/amcx-20260630.htm | L60: reported | M60: Historical Financials!F10 | N60: as printed: 4,416 ($ thousands)
A61: amcx.jv_aoi.H1-2026 | B61: jv_aoi | C61: H1-2026 | D61: ='Historical Financials'!F11 -> 6.762 | E61: US$M | F61: Form 10-Q for period ended 2026-06-30 | G61: 0001514991-26-000089 | H61: 2026-07-30 | I61: section only | J61: Non-GAAP reconciliation (MD&A) | K61: https://www.sec.gov/Archives/edgar/data/1514991/000151499126000089/amcx-20260630.htm | L61: reported | M61: Historical Financials!F11 | N61: as printed: 6,762 ($ thousands)
A62: amcx.da.H1-2026 | B62: da | C62: H1-2026 | D62: ='Historical Financials'!F12 -> 38.243 | E62: US$M | F62: Form 10-Q for period ended 2026-06-30 | G62: 0001514991-26-000089 | H62: 2026-07-30 | I62: section only | J62: MD&A results of operations | K62: https://www.sec.gov/Archives/edgar/data/1514991/000151499126000089/amcx-20260630.htm | L62: reported | M62: Historical Financials!F12 | N62: as printed: 38,243 ($ thousands)
A63: amcx.interest_expense.H1-2026 | B63: interest_expense | C63: H1-2026 | D63: ='Historical Financials'!F13 -> 84.012 | E63: US$M | F63: Form 10-Q for period ended 2026-06-30 | G63: 0001514991-26-000089 | H63: 2026-07-30 | I63: section only | J63: MD&A results of operations | K63: https://www.sec.gov/Archives/edgar/data/1514991/000151499126000089/amcx-20260630.htm | L63: reported | M63: Historical Financials!F13 | N63: as printed: 84,012 ($ thousands)
A64: amcx.taxes.H1-2026 | B64: taxes | C64: H1-2026 | D64: ='Historical Financials'!F14 -> -11.413 | E64: US$M | F64: Form 10-Q for period ended 2026-06-30 | G64: 0001514991-26-000089 | H64: 2026-07-30 | I64: section only | J64: MD&A results of operations | K64: https://www.sec.gov/Archives/edgar/data/1514991/000151499126000089/amcx-20260630.htm | L64: reported | M64: Historical Financials!F14 | N64: as printed: 11,413 ($ thousands) — H1-2026 is a BENEFIT (sign flipped to a negative provision); H1-2025 is an expense
A65: amcx.capex.H1-2026 | B65: capex | C65: H1-2026 | D65: ='Historical Financials'!F16 -> 16.577 | E65: US$M | F65: Form 10-Q for period ended 2026-06-30 | G65: 0001514991-26-000089 | H65: 2026-07-30 | I65: section only | J65: Condensed Consolidated Statements of Cash Flows | K65: https://www.sec.gov/Archives/edgar/data/1514991/000151499126000089/amcx-20260630.htm | L65: reported | M65: Historical Financials!F16 | N65: as printed: 16,577 ($ thousands)
A66: amcx.cfo.H1-2026 | B66: cfo | C66: H1-2026 | D66: ='Historical Financials'!F15 -> 124.659 | E66: US$M | F66: Form 10-Q for period ended 2026-06-30 | G66: 0001514991-26-000089 | H66: 2026-07-30 | I66: section only | J66: Condensed Consolidated Statements of Cash Flows | K66: https://www.sec.gov/Archives/edgar/data/1514991/000151499126000089/amcx-20260630.htm | L66: reported | M66: Historical Financials!F15 | N66: as printed: 124,659 ($ thousands)
A67: amcx.debt_2032_secured.2026-06-30 | B67: debt_2032_secured | C67: 2026-06-30 | D67: =Assumptions!$C$56 -> 1315.098 | E67: US$M | F67: Form 10-Q for period ended 2026-06-30 | G67: 0001514991-26-000089 | H67: 2026-07-30 | I67: section only | J67: Note 9 Long-term Debt | K67: https://www.sec.gov/Archives/edgar/data/1514991/000151499126000089/amcx-20260630.htm | L67: reported | M67: Assumptions!$C$56 | N67: as printed: 1,315,098 ($ thousands)
A68: amcx.debt_2029_unsecured.2026-06-30 | B68: debt_2029_unsecured | C68: 2026-06-30 | D68: =Assumptions!$C$57 -> 276.706 | E68: US$M | F68: Form 10-Q for period ended 2026-06-30 | G68: 0001514991-26-000089 | H68: 2026-07-30 | I68: section only | J68: Note 9 Long-term Debt | K68: https://www.sec.gov/Archives/edgar/data/1514991/000151499126000089/amcx-20260630.htm | L68: reported | M68: Assumptions!$C$57 | N68: as printed: 276,706 ($ thousands)
A69: amcx.debt_2029_convert.2026-06-30 | B69: debt_2029_convert | C69: 2026-06-30 | D69: =Assumptions!$C$58 -> 143.75 | E69: US$M | F69: Form 10-Q for period ended 2026-06-30 | G69: 0001514991-26-000089 | H69: 2026-07-30 | I69: section only | J69: Note 9 Long-term Debt | K69: https://www.sec.gov/Archives/edgar/data/1514991/000151499126000089/amcx-20260630.htm | L69: reported | M69: Assumptions!$C$58 | N69: as printed: 143,750 ($ thousands)
A70: amcx.cash.2026-06-30 | B70: cash | C70: 2026-06-30 | D70: =Assumptions!$C$11 -> 463.996 | E70: US$M | F70: Form 10-Q for period ended 2026-06-30 | G70: 0001514991-26-000089 | H70: 2026-07-30 | I70: section only | J70: Consolidated Balance Sheets | K70: https://www.sec.gov/Archives/edgar/data/1514991/000151499126000089/amcx-20260630.htm | L70: reported | M70: Assumptions!$C$11 | N70: as printed: 463,996 ($ thousands)
A71: amcx.program_rights.2026-06-30 | B71: program_rights | C71: 2026-06-30 | D71: not a direct model input | E71: US$M | F71: Form 10-Q for period ended 2026-06-30 | G71: 0001514991-26-000089 | H71: 2026-07-30 | I71: section only | J71: Consolidated Balance Sheets | K71: https://www.sec.gov/Archives/edgar/data/1514991/000151499126000089/amcx-20260630.htm | L71: reported | N71: as printed: 1,627,782 ($ thousands) — Largest asset; content library carried at amortized cost
A72: amcx.ar.2026-06-30 | B72: ar | C72: 2026-06-30 | D72: not a direct model input | E72: US$M | F72: Form 10-Q for period ended 2026-06-30 | G72: 0001514991-26-000089 | H72: 2026-07-30 | I72: section only | J72: Consolidated Balance Sheets | K72: https://www.sec.gov/Archives/edgar/data/1514991/000151499126000089/amcx-20260630.htm | L72: reported | N72: as printed: 547,187 ($ thousands)
A73: amcx.ppe.2026-06-30 | B73: ppe | C73: 2026-06-30 | D73: not a direct model input | E73: US$M | F73: Form 10-Q for period ended 2026-06-30 | G73: 0001514991-26-000089 | H73: 2026-07-30 | I73: section only | J73: Consolidated Balance Sheets | K73: https://www.sec.gov/Archives/edgar/data/1514991/000151499126000089/amcx-20260630.htm | L73: reported | N73: as printed: 110,555 ($ thousands)
A74: amcx.intangibles.2026-06-30 | B74: intangibles | C74: 2026-06-30 | D74: not a direct model input | E74: US$M | F74: Form 10-Q for period ended 2026-06-30 | G74: 0001514991-26-000089 | H74: 2026-07-30 | I74: section only | J74: Consolidated Balance Sheets | K74: https://www.sec.gov/Archives/edgar/data/1514991/000151499126000089/amcx-20260630.htm | L74: reported | N74: as printed: 169,447 ($ thousands)
A75: amcx.debt_total.FY2025 | B75: debt_total | C75: FY2025 | D75: not a direct model input | E75: US$M | F75: Form 10-K for period ended 2025-12-31 | G75: 0001514991-26-000011 | H75: 2026-02-11 | I75: F-27 | J75: Note 9 Long-term Debt | K75: https://www.sec.gov/Archives/edgar/data/1514991/000151499126000011/amcx-20251231.htm | L75: reported | N75: as printed: 1,778,251 ($ thousands) — Principal at 2025-12-31 (before the 2026 exchange/refinancing); used for covenant calibration
A76: amcx.fy25_undrawn_revolver | B76: fy25_undrawn_revolver | C76: 2025-12-31 | D76: n/a (text disclosure) | E76: text disclosure | F76: Form 10-K for period ended 2025-12-31 | G76: 0001514991-26-000011 | H76: 2026-02-11 | I76: 56 | J76: MD&A Liquidity: undrawn revolver at 2025-12-31 | K76: https://www.sec.gov/Archives/edgar/data/1514991/000151499126000011/amcx-20251231.htm | L76: reported | N76: undrawn $175.0 million Revolving Credit Facility — MD&A Liquidity: undrawn revolver at 2025-12-31
A77: amcx.cov_net_lev_reported | B77: cov_net_lev_reported | C77: 2025-12-31 | D77: n/a (text disclosure) | E77: text disclosure | F77: Form 10-K for period ended 2025-12-31 | G77: 0001514991-26-000011 | H77: 2026-02-11 | I77: 56 | J77: Total net leverage ratio at 2025-12-31 as reported by the company (credit-agreement definition) | K77: https://www.sec.gov/Archives/edgar/data/1514991/000151499126000011/amcx-20251231.htm | L77: reported | N77: 4.41:1.00 — Total net leverage ratio at 2025-12-31 as reported by the company (credit-agreement definition)
A78: amcx.cov_icr_reported | B78: cov_icr_reported | C78: 2025-12-31 | D78: n/a (text disclosure) | E78: text disclosure | F78: Form 10-K for period ended 2025-12-31 | G78: 0001514991-26-000011 | H78: 2026-02-11 | I78: 56 | J78: Interest coverage at 2025-12-31 as reported by the company | K78: https://www.sec.gov/Archives/edgar/data/1514991/000151499126000011/amcx-20251231.htm | L78: reported | N78: 2.01:1.00 — Interest coverage at 2025-12-31 as reported by the company
A79: amcx.impairment.FY2023 | B79: impairment | C79: FY2023 | D79: ='Historical Financials'!B17 -> 96.689 | E79: US$M | F79: Form 10-K for period ended 2025-12-31 | G79: 0001514991-26-000011 | H79: 2026-02-11 | I79: F-5 | J79: Consolidated Statements of Income (Loss) | K79: https://www.sec.gov/Archives/edgar/data/1514991/000151499126000011/amcx-20251231.htm | L79: reported | M79: Historical Financials!B17 | N79: as printed: 96,689 ($ thousands)
A80: amcx.impairment.FY2024 | B80: impairment | C80: FY2024 | D80: ='Historical Financials'!C17 -> 399.513 | E80: US$M | F80: Form 10-K for period ended 2025-12-31 | G80: 0001514991-26-000011 | H80: 2026-02-11 | I80: F-5 | J80: Consolidated Statements of Income (Loss) | K80: https://www.sec.gov/Archives/edgar/data/1514991/000151499126000011/amcx-20251231.htm | L80: reported | M80: Historical Financials!C17 | N80: as printed: 399,513 ($ thousands)
A81: amcx.impairment.FY2025 | B81: impairment | C81: FY2025 | D81: ='Historical Financials'!D17 -> 97.784 | E81: US$M | F81: Form 10-K for period ended 2025-12-31 | G81: 0001514991-26-000011 | H81: 2026-02-11 | I81: F-5 | J81: Consolidated Statements of Income (Loss) | K81: https://www.sec.gov/Archives/edgar/data/1514991/000151499126000011/amcx-20251231.htm | L81: reported | M81: Historical Financials!D17 | N81: as printed: 97,784 ($ thousands)
A82: amcx.restructuring.FY2023 | B82: restructuring | C82: FY2023 | D82: ='Historical Financials'!B18 -> 27.787 | E82: US$M | F82: Form 10-K for period ended 2025-12-31 | G82: 0001514991-26-000011 | H82: 2026-02-11 | I82: F-5 | J82: Consolidated Statements of Income (Loss) | K82: https://www.sec.gov/Archives/edgar/data/1514991/000151499126000011/amcx-20251231.htm | L82: reported | M82: Historical Financials!B18 | N82: as printed: 27,787 ($ thousands)
A83: amcx.restructuring.FY2024 | B83: restructuring | C83: FY2024 | D83: ='Historical Financials'!C18 -> 49.464 | E83: US$M | F83: Form 10-K for period ended 2025-12-31 | G83: 0001514991-26-000011 | H83: 2026-02-11 | I83: F-5 | J83: Consolidated Statements of Income (Loss) | K83: https://www.sec.gov/Archives/edgar/data/1514991/000151499126000011/amcx-20251231.htm | L83: reported | M83: Historical Financials!C18 | N83: as printed: 49,464 ($ thousands)
A84: amcx.restructuring.FY2025 | B84: restructuring | C84: FY2025 | D84: ='Historical Financials'!D18 -> 26.536 | E84: US$M | F84: Form 10-K for period ended 2025-12-31 | G84: 0001514991-26-000011 | H84: 2026-02-11 | I84: F-5 | J84: Consolidated Statements of Income (Loss) | K84: https://www.sec.gov/Archives/edgar/data/1514991/000151499126000011/amcx-20251231.htm | L84: reported | M84: Historical Financials!D18 | N84: as printed: 26,536 ($ thousands)
A85: amcx.restructuring.H1-2025 | B85: restructuring | C85: H1-2025 | D85: ='Historical Financials'!E18 -> 8.318 | E85: US$M | F85: Form 10-Q for period ended 2026-06-30 | G85: 0001514991-26-000089 | H85: 2026-07-30 | I85: section only | J85: MD&A results of operations | K85: https://www.sec.gov/Archives/edgar/data/1514991/000151499126000089/amcx-20260630.htm | L85: reported | M85: Historical Financials!E18 | N85: as printed: 8,318 ($ thousands)
A86: amcx.restructuring.H1-2026 | B86: restructuring | C86: H1-2026 | D86: ='Historical Financials'!F18 -> 5.68 | E86: US$M | F86: Form 10-Q for period ended 2026-06-30 | G86: 0001514991-26-000089 | H86: 2026-07-30 | I86: section only | J86: MD&A results of operations | K86: https://www.sec.gov/Archives/edgar/data/1514991/000151499126000089/amcx-20260630.htm | L86: reported | M86: Historical Financials!F18 | N86: as printed: 5,680 ($ thousands)
A87: amcx.cash_interest.FY2023 | B87: cash_interest | C87: FY2023 | D87: ='Historical Financials'!B19 -> 149.535 | E87: US$M | F87: Form 10-K for period ended 2025-12-31 | G87: 0001514991-26-000011 | H87: 2026-02-11 | I87: F-46 | J87: Note 19 Supplemental cash flow data | K87: https://www.sec.gov/Archives/edgar/data/1514991/000151499126000011/amcx-20251231.htm | L87: reported | M87: Historical Financials!B19 | N87: as printed: 149,535 ($ thousands)
A88: amcx.cash_interest.FY2024 | B88: cash_interest | C88: FY2024 | D88: ='Historical Financials'!C19 -> 129.164 | E88: US$M | F88: Form 10-K for period ended 2025-12-31 | G88: 0001514991-26-000011 | H88: 2026-02-11 | I88: F-46 | J88: Note 19 Supplemental cash flow data | K88: https://www.sec.gov/Archives/edgar/data/1514991/000151499126000011/amcx-20251231.htm | L88: reported | M88: Historical Financials!C19 | N88: as printed: 129,164 ($ thousands)
A89: amcx.cash_interest.FY2025 | B89: cash_interest | C89: FY2025 | D89: ='Historical Financials'!D19 -> 156.563 | E89: US$M | F89: Form 10-K for period ended 2025-12-31 | G89: 0001514991-26-000011 | H89: 2026-02-11 | I89: F-46 | J89: Note 19 Supplemental cash flow data | K89: https://www.sec.gov/Archives/edgar/data/1514991/000151499126000011/amcx-20251231.htm | L89: reported | M89: Historical Financials!D19 | N89: as printed: 156,563 ($ thousands)
A90: amcx.cash_interest.H1-2025 | B90: cash_interest | C90: H1-2025 | D90: ='Historical Financials'!E19 -> 84.394 | E90: US$M | F90: Form 10-Q for period ended 2026-06-30 | G90: 0001514991-26-000089 | H90: 2026-07-30 | I90: section only | J90: Note: Supplemental data | K90: https://www.sec.gov/Archives/edgar/data/1514991/000151499126000089/amcx-20260630.htm | L90: reported | M90: Historical Financials!E19 | N90: as printed: 84,394 ($ thousands)
A91: amcx.cash_interest.H1-2026 | B91: cash_interest | C91: H1-2026 | D91: ='Historical Financials'!F19 -> 78.984 | E91: US$M | F91: Form 10-Q for period ended 2026-06-30 | G91: 0001514991-26-000089 | H91: 2026-07-30 | I91: section only | J91: Note: Supplemental data | K91: https://www.sec.gov/Archives/edgar/data/1514991/000151499126000089/amcx-20260630.htm | L91: reported | M91: Historical Financials!F19 | N91: as printed: 78,984 ($ thousands)
A92: amcx.aoi_reported.FY2023 | B92: aoi_reported | C92: FY2023 | D92: ='Historical Financials'!B20 -> 670.104 | E92: US$M | F92: Form 10-K for period ended 2024-12-31 | G92: 0001514991-25-000009 | H92: 2025-02-14 | I92: 58 | J92: Non-GAAP reconciliation (MD&A) | K92: https://www.sec.gov/Archives/edgar/data/1514991/000151499125000009/amcx-20241231.htm | L92: reported | M92: Historical Financials!B20 | N92: as printed: 670,104 ($ thousands) — FY2024 10-K
A93: amcx.aoi_reported.FY2024 | B93: aoi_reported | C93: FY2024 | D93: ='Historical Financials'!C20 -> 562.573 | E93: US$M | F93: Form 10-K for period ended 2025-12-31 | G93: 0001514991-26-000011 | H93: 2026-02-11 | I93: 60 | J93: Non-GAAP reconciliation (MD&A) | K93: https://www.sec.gov/Archives/edgar/data/1514991/000151499126000011/amcx-20251231.htm | L93: reported | M93: Historical Financials!C20 | N93: as printed: 562,573 ($ thousands) — Company-reported AOI; used only to check the model's calculated EBITDA
A94: amcx.aoi_reported.FY2025 | B94: aoi_reported | C94: FY2025 | D94: ='Historical Financials'!D20 -> 411.874 | E94: US$M | F94: Form 10-K for period ended 2025-12-31 | G94: 0001514991-26-000011 | H94: 2026-02-11 | I94: 60 | J94: Non-GAAP reconciliation (MD&A) | K94: https://www.sec.gov/Archives/edgar/data/1514991/000151499126000011/amcx-20251231.htm | L94: reported | M94: Historical Financials!D20 | N94: as printed: 411,874 ($ thousands) — Company-reported AOI; used only to check the model's calculated EBITDA
A95: amcx.aoi_reported.H1-2025 | B95: aoi_reported | C95: H1-2025 | D95: ='Historical Financials'!E20 -> 213.871 | E95: US$M | F95: Form 10-Q for period ended 2026-06-30 | G95: 0001514991-26-000089 | H95: 2026-07-30 | I95: section only | J95: Non-GAAP reconciliation (MD&A) | K95: https://www.sec.gov/Archives/edgar/data/1514991/000151499126000089/amcx-20260630.htm | L95: reported | M95: Historical Financials!E20 | N95: as printed: 213,871 ($ thousands)
A96: amcx.aoi_reported.H1-2026 | B96: aoi_reported | C96: H1-2026 | D96: ='Historical Financials'!F20 -> 115.042 | E96: US$M | F96: Form 10-Q for period ended 2026-06-30 | G96: 0001514991-26-000089 | H96: 2026-07-30 | I96: section only | J96: Non-GAAP reconciliation (MD&A) | K96: https://www.sec.gov/Archives/edgar/data/1514991/000151499126000089/amcx-20260630.htm | L96: reported | M96: Historical Financials!F20 | N96: as printed: 115,042 ($ thousands)
A97: amcx.cash.FY2025 | B97: cash | C97: FY2025 | D97: not a direct model input | E97: US$M | F97: Form 10-K for period ended 2025-12-31 | G97: 0001514991-26-000011 | H97: 2026-02-11 | I97: F-4 | J97: Consolidated Balance Sheets | K97: https://www.sec.gov/Archives/edgar/data/1514991/000151499126000011/amcx-20251231.htm | L97: reported | N97: as printed: 502,379 ($ thousands)
A98: amcx.current_assets.2026-06-30 | B98: current_assets | C98: 2026-06-30 | D98: not a direct model input | E98: US$M | F98: Form 10-Q for period ended 2026-06-30 | G98: 0001514991-26-000089 | H98: 2026-07-30 | I98: section only | J98: Consolidated Balance Sheets | K98: https://www.sec.gov/Archives/edgar/data/1514991/000151499126000089/amcx-20260630.htm | L98: reported | N98: as printed: 1,262,345 ($ thousands)
A99: amcx.current_liabilities.2026-06-30 | B99: current_liabilities | C99: 2026-06-30 | D99: not a direct model input | E99: US$M | F99: Form 10-Q for period ended 2026-06-30 | G99: 0001514991-26-000089 | H99: 2026-07-30 | I99: section only | J99: Consolidated Balance Sheets | K99: https://www.sec.gov/Archives/edgar/data/1514991/000151499126000089/amcx-20260630.htm | L99: reported | N99: as printed: 716,838 ($ thousands)
A100: amcx.debt_total.2026-06-30 | B100: debt_total | C100: 2026-06-30 | D100: not a direct model input | E100: US$M | F100: Form 10-Q for period ended 2026-06-30 | G100: 0001514991-26-000089 | H100: 2026-07-30 | I100: section only | J100: Note 9 Long-term Debt | K100: https://www.sec.gov/Archives/edgar/data/1514991/000151499126000089/amcx-20260630.htm | L100: reported | N100: as printed: 1,735,554 ($ thousands)
A102: Analyst notes, derivations and data-quality caveats
A103: • EBITDA = Adjusted Operating Income (AOI), the company's non-GAAP measure: revenue − technical & operating − SG&A + share-based compensation + cloud-computing amortization + majority-owned equity-investee AOI. Model-calculated AOI equals reported AOI in every period.
...

Sheet Calc Engine
A1: Calc Engine — supporting tab: identical model logic run for all scenarios and sensitivity cases
A2: Cases 1-3 run Base / Downside / Severe simultaneously. Cases 4-63 flex EBITDA margin, revenue growth, SOFR and the distressed multiple (axes on Sensitivities). Same row logic as the detailed tabs; Scenarios › Reconciliation proves the engine ties to them.
A5: CASE 1: Base Case
A6: Scenario index (structural input) | C6: 1
A7: Revenue growth adjustment | C7: 0
A8: EBITDA margin adjustment | C8: 0
A9: SOFR shift | C9: 0
A10: Distressed-multiple shift (x) | C10: 0
A12: Operating drivers (selected scenario → Assumptions)
A13: Model period (year in which the period ends) | F13: =Assumptions!$C$6 -> 2026 | G13: =F13+1 -> 2027 | H13: =G13+1 -> 2028 | I13: =H13+1 -> 2029 | J13: =I13+1 -> 2030 | K13: =J13+1 -> 2031
A14: Projection period # | G14: =G13-Assumptions!$C$6 -> 1 | H14: =H13-Assumptions!$C$6 -> 2 | I14: =I13-Assumptions!$C$6 -> 3 | J14: =J13-Assumptions!$C$6 -> 4 | K14: =K13-Assumptions!$C$6 -> 5
A15: Revenue growth | G15: =CHOOSE($C$6,Assumptions!$G$71,Assumptions!$G$90,Assumptions!$G$109)+$C$7 -> -0.045 | H15: =CHOOSE($C$6,Assumptions!$H$71,Assumptions!$H$90,Assumptions!$H$109)+$C$7 -> -0.04 | I15: =CHOOSE($C$6,Assumptions!$I$71,Assumptions!$I$90,Assumptions!$I$109)+$C$7 -> -0.035 | J15: =CHOOSE($C$6,Assumptions!$J$71,Assumptions!$J$90,Assumptions!$J$109)+$C$7 -> -0.03 | K15: =CHOOSE($C$6,Assumptions!$K$71,Assumptions!$K$90,Assumptions!$K$109)+$C$7 -> -0.03
A16: Gross margin | G16: =CHOOSE($C$6,Assumptions!$G$72,Assumptions!$G$91,Assumptions!$G$110) -> 0.48324667 | H16: =CHOOSE($C$6,Assumptions!$H$72,Assumptions!$H$91,Assumptions!$H$110) -> 0.48324667 | I16: =CHOOSE($C$6,Assumptions!$I$72,Assumptions!$I$91,Assumptions!$I$110) -> 0.48124667 | J16: =CHOOSE($C$6,Assumptions!$J$72,Assumptions!$J$91,Assumptions!$J$110) -> 0.47924667 | K16: =CHOOSE($C$6,Assumptions!$K$72,Assumptions!$K$91,Assumptions!$K$110) -> 0.47724667
A17: EBITDA margin | G17: =CHOOSE($C$6,Assumptions!$G$73,Assumptions!$G$92,Assumptions!$G$111)+$C$8 -> 0.14 | H17: =CHOOSE($C$6,Assumptions!$H$73,Assumptions!$H$92,Assumptions!$H$111)+$C$8 -> 0.14 | I17: =CHOOSE($C$6,Assumptions!$I$73,Assumptions!$I$92,Assumptions!$I$111)+$C$8 -> 0.138 | J17: =CHOOSE($C$6,Assumptions!$J$73,Assumptions!$J$92,Assumptions!$J$111)+$C$8 -> 0.136 | K17: =CHOOSE($C$6,Assumptions!$K$73,Assumptions!$K$92,Assumptions!$K$111)+$C$8 -> 0.134
A18: Income statement ($M)
A19: Revenue | F19: ='Historical Financials'!G23 -> 2246.166 | G19: =F19*(1+G15) -> 2145.0885 | H19: =G19*(1+H15) -> 2059.285 | I19: =H19*(1+I15) -> 1987.21 | J19: =I19*(1+J15) -> 1927.5937 | K19: =J19*(1+K15) -> 1869.7659
A20: Direct costs / COGS | G20: =G19*(1-G16) -> 1108.4816 | H20: =H19*(1-H16) -> 1064.1424 | I20: =I19*(1-I16) -> 1030.8718 | J20: =J19*(1-J16) -> 1003.8008 | K20: =K19*(1-K16) -> 977.42635
A21: Gross profit (NOI for real estate) | G21: =G19-G20 -> 1036.6069 | H21: =H19-H20 -> 995.14261 | I21: =I19-I20 -> 956.3382 | J21: =J19-J20 -> 923.79287 | K21: =K19-K20 -> 892.33955
A22: Operating expenses (implied: gross profit − EBITDA) | G22: =G21-G23 -> 736.29449 | H22: =H21-H23 -> 706.84272 | I22: =I21-I23 -> 682.10322 | J22: =J21-J23 -> 661.64012 | K22: =K21-K23 -> 641.79092
A23: EBITDA | G23: =G19*G17 -> 300.31239 | H23: =H19*H17 -> 288.2999 | I23: =I19*I17 -> 274.23498 | J23: =J19*J17 -> 262.15275 | K23: =K19*K17 -> 250.54863
A24: D&A | G24: =G19*'Historical Financials'!G28/'Historical Financials'!G23 -> 81.45768 | H24: =H19*'Historical Financials'!G28/'Historical Financials'!G23 -> 78.199373 | I24: =I19*'Historical Financials'!G28/'Historical Financials'!G23 -> 75.462395 | J24: =J19*'Historical Financials'!G28/'Historical Financials'!G23 -> 73.198523 | K24: =K19*'Historical Financials'!G28/'Historical Financials'!G23 -> 71.002567
A25: Share-based compensation (non-cash) | G25: =G19*'Historical Financials'!G29/'Historical Financials'!G23 -> 23.25998 | H25: =H19*'Historical Financials'!G29/'Historical Financials'!G23 -> 22.329581 | I25: =I19*'Historical Financials'!G29/'Historical Financials'!G23 -> 21.548045 | J25: =J19*'Historical Financials'!G29/'Historical Financials'!G23 -> 20.901604 | K25: =K19*'Historical Financials'!G29/'Historical Financials'!G23 -> 20.274556
A26: EBIT | G26: =G23-G24-G25 -> 195.59473 | H26: =H23-H24-H25 -> 187.77094 | I26: =I23-I24-I25 -> 177.22454 | J26: =J23-J24-J25 -> 168.05262 | K26: =K23-K24-K25 -> 159.27151
A27: Cash interest expense (Debt Schedule) | G27: =G53+G66+G79 -> 155.95467 | H27: =H53+H66+H79 -> 155.95467 | I27: =I53+I66+I79 -> 155.95467 | J27: =J53+J66+J79 -> 138.08529 | K27: =K53+K66+K79 -> 138.08529
A28: PIK interest (non-cash) | G28: =G54+G67+G80 -> 0 | H28: =H54+H67+H80 -> 0 | I28: =I54+I67+I80 -> 0 | J28: =J54+J67+J80 -> 0 | K28: =K54+K67+K80 -> 0
A29: Interest expense | G29: =G27+G28 -> 155.95467 | H29: =H27+H28 -> 155.95467 | I29: =I27+I28 -> 155.95467 | J29: =J27+J28 -> 138.08529 | K29: =K27+K28 -> 138.08529
A30: EBT | G30: =G26-G29 -> 39.640064 | H30: =H26-H29 -> 31.816275 | I30: =I26-I29 -> 21.269872 | J30: =J26-J29 -> 29.967328 | K30: =K26-K29 -> 21.186218
A31: Taxes | G31: =MAX(0,G30)*Assumptions!$C$9 -> 9.910016 | H31: =MAX(0,H30)*Assumptions!$C$9 -> 7.9540687 | I31: =MAX(0,I30)*Assumptions!$C$9 -> 5.3174679 | J31: =MAX(0,J30)*Assumptions!$C$9 -> 7.491832 | K31: =MAX(0,K30)*Assumptions!$C$9 -> 5.2965544
A32: Net income (model basis) | G32: =G30-G31 -> 29.730048 | H32: =H30-H31 -> 23.862206 | I32: =I30-I31 -> 15.952404 | J32: =J30-J31 -> 22.475496 | K32: =K30-K31 -> 15.889663
A33: Free cash flow build ($M)
A34: Capex | G34: =G19*CHOOSE($C$6,Assumptions!$C$75,Assumptions!$C$94,Assumptions!$C$113) -> 30.031239 | H34: =H19*CHOOSE($C$6,Assumptions!$C$75,Assumptions!$C$94,Assumptions!$C$113) -> 28.82999 | I34: =I19*CHOOSE($C$6,Assumptions!$C$75,Assumptions!$C$94,Assumptions!$C$113) -> 27.82094 | J34: =J19*CHOOSE($C$6,Assumptions!$C$75,Assumptions!$C$94,Assumptions!$C$113) -> 26.986312 | K34: =K19*CHOOSE($C$6,Assumptions!$C$75,Assumptions!$C$94,Assumptions!$C$113) -> 26.176723
A35: Working capital & other cash items (+ = outflow) | G35: =CHOOSE($C$6,Assumptions!$C$76,Assumptions!$C$95,Assumptions!$C$114)*(G19-F19)+CHOOSE($C$6,Assumptions!$C$77,Assumptions!$C$96,Assumptions!$C$115)*G19 -> -21.450885 | H35: =CHOOSE($C$6,Assumptions!$C$76,Assumptions!$C$95,Assumptions!$C$114)*(H19-G19)+CHOOSE($C$6,Assumptions!$C$77,Assumptions!$C$96,Assumptions!$C$115)*H19 -> -20.59285 | I35: =CHOOSE($C$6,Assumptions!$C$76,Assumptions!$C$95,Assumptions!$C$114)*(I19-H19)+CHOOSE($C$6,Assumptions!$C$77,Assumptions!$C$96,Assumptions!$C$115)*I19 -> -19.8721 | J35: =CHOOSE($C$6,Assumptions!$C$76,Assumptions!$C$95,Assumptions!$C$114)*(J19-I19)+CHOOSE($C$6,Assumptions!$C$77,Assumptions!$C$96,Assumptions!$C$115)*J19 -> -19.275937 | K35: =CHOOSE($C$6,Assumptions!$C$76,Assumptions!$C$95,Assumptions!$C$114)*(K19-J19)+CHOOSE($C$6,Assumptions!$C$77,Assumptions!$C$96,Assumptions!$C$115)*K19 -> -18.697659
A36: Free cash flow (NI + D&A + SBC + PIK − capex − ΔNWC/other) | G36: =G32+G24+G25+G28-G34-G35 -> 125.86735 | H36: =H32+H24+H25+H28-H34-H35 -> 116.15402 | I36: =I32+I24+I25+I28-I34-I35 -> 105.014 | J36: =J32+J24+J25+J28-J34-J35 -> 108.86525 | K36: =K32+K24+K25+K28-K34-K35 -> 99.687723
A38: Rates & market-access (refinancing) test
A39: Base rate (SOFR) | G39: =Assumptions!$G$52 -> 0.039 | H39: =Assumptions!$H$52 -> 0.0375 | I39: =Assumptions!$I$52 -> 0.035 | J39: =Assumptions!$J$52 -> 0.035 | K39: =Assumptions!$K$52 -> 0.035
A40: Floating-rate shock (selected scenario) | C40: =CHOOSE($C$6,Assumptions!$C$78,Assumptions!$C$97,Assumptions!$C$116)+$C$9 -> 0
A41: Refinancing rate (selected scenario) | C41: =CHOOSE($C$6,Assumptions!$C$79,Assumptions!$C$98,Assumptions!$C$117) -> 0.11
A42: Max net leverage to refinance | C42: =CHOOSE($C$6,Assumptions!$C$80,Assumptions!$C$99,Assumptions!$C$118) -> 6
A43: Min pro-forma coverage to refinance | C43: =CHOOSE($C$6,Assumptions!$C$81,Assumptions!$C$100,Assumptions!$C$119) -> 1.25
A44: Beginning total debt | G44: =G49+G62+G75 -> 1735.554 | H44: =H49+H62+H75 -> 1735.554 | I44: =I49+I62+I75 -> 1735.554 | J44: =J49+J62+J75 -> 1315.098 | K44: =K49+K62+K75 -> 1315.098
A45: Beginning cash | G45: =F118 -> 463.996 | H45: =G118 -> 589.86335 | I45: =H118 -> 706.01737 | J45: =I118 -> 390.57538 | K45: =J118 -> 499.44063
A46: Pro-forma interest for refinancing test | G46: =G49*IF(G50=1,$C$41,IF(Assumptions!$I$56=1,MAX(G39,Assumptions!$G$56)+Assumptions!$F$56+$C$40,Assumptions!$E$56))+G62*IF(G63=1,$C$41,IF(Assumptions!$I$57=1,MAX(G39,Assumptions!$G$57)+Assumptions!$F$57+$C$40,Assumptions!$E$57))+G75*IF(G76=1,$C$41,IF(Assumptions!$I$58=1,MAX(G39,Assumptions!$G$58)+Assumptions!$F$58+$C$40,Assumptions!$E$58)) -> 155.95467 | H46: =H49*IF(OR(H50=1,G196=1),$C$41,IF(Assumptions!$I$56=1,MAX(H39,Assumptions!$G$56)+Assumptions!$F$56+$C$40,Assumptions!$E$56))+H62*IF(OR(H63=1,G197=1),$C$41,IF(Assumptions!$I$57=1,MAX(H39,Assumptions!$G$57)+Assumptions!$F$57+$C$40,Assumptions!$E$57))+H75*IF(OR(H76=1,G198=1),$C$41,IF(Assumptions!$I$58=1,MAX(H39,Assumptions!$G$58)+Assumptions!$F$58+$C$40,Assumptions!$E$58)) -> 155.95467 | I46: =I49*IF(OR(I50=1,H196=1),$C$41,IF(Assumptions!$I$56=1,MAX(I39,Assumptions!$G$56)+Assumptions!$F$56+$C$40,Assumptions!$E$56))+I62*IF(OR(I63=1,H197=1),$C$41,IF(Assumptions!$I$57=1,MAX(I39,Assumptions!$G$57)+Assumptions!$F$57+$C$40,Assumptions!$E$57))+I75*IF(OR(I76=1,H198=1),$C$41,IF(Assumptions!$I$58=1,MAX(I39,Assumptions!$G$58)+Assumptions!$F$58+$C$40,Assumptions!$E$58)) -> 184.33545 | J46: =J49*IF(OR(J50=1,I196=1),$C$41,IF(Assumptions!$I$56=1,MAX(J39,Assumptions!$G$56)+Assumptions!$F$56+$C$40,Assumptions!$E$56))+J62*IF(OR(J63=1,I197=1),$C$41,IF(Assumptions!$I$57=1,MAX(J39,Assumptions!$G$57)+Assumptions!$F$57+$C$40,Assumptions!$E$57))+J75*IF(OR(J76=1,I198=1),$C$41,IF(Assumptions!$I$58=1,MAX(J39,Assumptions!$G$58)+Assumptions!$F$58+$C$40,Assumptions!$E$58)) -> 138.08529 | K46: =K49*IF(OR(K50=1,J196=1),$C$41,IF(Assumptions!$I$56=1,MAX(K39,Assumptions!$G$56)+Assumptions!$F$56+$C$40,Assumptions!$E$56))+K62*IF(OR(K63=1,J197=1),$C$41,IF(Assumptions!$I$57=1,MAX(K39,Assumptions!$G$57)+Assumptions!$F$57+$C$40,Assumptions!$E$57))+K75*IF(OR(K76=1,J198=1),$C$41,IF(Assumptions!$I$58=1,MAX(K39,Assumptions!$G$58)+Assumptions!$F$58+$C$40,Assumptions!$E$58)) -> 138.08529
A47: Market access to refinance? (1 = yes) | G47: =IF(G23<=0,0,IF(AND((G44-G45)/G23<=$C$42,G23/G46>=$C$43),1,0)) -> 1 | H47: =IF(H23<=0,0,IF(AND((H44-H45)/H23<=$C$42,H23/H46>=$C$43),1,0)) -> 1 | I47: =IF(I23<=0,0,IF(AND((I44-I45)/I23<=$C$42,I23/I46>=$C$43),1,0)) -> 1 | J47: =IF(J23<=0,0,IF(AND((J44-J45)/J23<=$C$42,J23/J46>=$C$43),1,0)) -> 1 | K47: =IF(K23<=0,0,IF(AND((K44-K45)/K23<=$C$42,K23/K46>=$C$43),1,0)) -> 1
A48: Tranche 1: 10.50% Senior Secured Notes due 2032
A49: Beginning balance | G49: =F60 -> 1315.098 | H49: =G60 -> 1315.098 | I49: =H60 -> 1315.098 | J49: =I60 -> 1315.098 | K49: =J60 -> 1315.098
A50: Maturing this period? (1 = yes) | G50: =IF(G13=Assumptions!$K$56,1,0) -> 0 | H50: =IF(H13=Assumptions!$K$56,1,0) -> 0 | I50: =IF(I13=Assumptions!$K$56,1,0) -> 0 | J50: =IF(J13=Assumptions!$K$56,1,0) -> 0 | K50: =IF(K13=Assumptions!$K$56,1,0) -> 0
